Workbook

Sheet Cover Page
C11: EuroBank
C16: ATTACHMENT 4-H
C18: INVOICE SUMMARY SAMPLE
C19: Attachment to Exhibit 4 (Pricing and Financial Provisions)

Sheet Invoice Summary
B2: All charges are shown in Euro, excluding VAT | D2: Invoice Summary
B4: Supplier | D4: Period | E4: YTD | F4: ESTIMATED EOY
D5: 39172 | E5: =Period | F5: 39447
B7: Category of Services | D7: Base Charges | E7: Base Charges | F7: Base Charges
B8: EUC | D8: ='Base Charge'!H55 | E8: ='Base Charge'!M55 | F8: ='Base Charge'!N55
B9: Service Desk | D9: ='Base Charge'!H62 | E9: ='Base Charge'!M62 | F9: ='Base Charge'!N62
B10: LAN Services | D10: ='Base Charge'!H70 | E10: ='Base Charge'!M70 | F10: ='Base Charge'!N70
B11: Voice Services | D11: ='Base Charge'!H136 | E11: ='Base Charge'!M136 | F11: ='Base Charge'!N136
B12: Server Management | D12: ='Base Charge'!H146 | E12: ='Base Charge'!M146 | F12: ='Base Charge'!N146
B13: 2IM | D13: ='Base Charge'!H151 | E13: ='Base Charge'!M151 | F13: ='Base Charge'!N151
B14: Sub total | D14: =SUM(D8:D13) | E14: =SUM(E8:E13) | F14: =SUM(F8:F13)
B16: Category of Services | D16: ARC/RRC | E16: ARC/RRC | F16: ARC/RRC
B17: EUC | D17: ='Base Charge'!J55 | E17: ='Base Charge'!O55 | F17: ='Base Charge'!P55
B18: Service Desk | D18: ='Base Charge'!J62 | E18: ='Base Charge'!O62 | F18: ='Base Charge'!P62
B19: LAN Services | D19: ='Base Charge'!J70 | E19: ='Base Charge'!O70 | F19: ='Base Charge'!P70
B20: Voice Services | D20: ='Base Charge'!J136 | E20: ='Base Charge'!O136 | F20: ='Base Charge'!P136
B21: Server Management | D21: ='Base Charge'!J146 | E21: ='Base Charge'!O146 | F21: ='Base Charge'!P146
B22: Sub total | D22: =SUM(D17:D21) | E22: =SUM(E17:E21) | F22: =SUM(F17:F21)
B24: Category of Services | D24: Pass Through | E24: Pass Through | F24: Pass Through
B25: EUC | D25: =Passthrough!M55 | E25: =Passthrough!N55 | F25: =Passthrough!O55
B26: Service Desk | D26: =Passthrough!M62 | E26: =Passthrough!N62 | F26: =Passthrough!O62
B27: LAN Services | D27: =Passthrough!M70 | E27: =Passthrough!N70 | F27: =Passthrough!O70
B28: Voice Services | D28: =Passthrough!M136 | E28: =Passthrough!N136 | F28: =Passthrough!O136
B29: Server Management | D29: =Passthrough!M146 | E29: =Passthrough!N146 | F29: =Passthrough!O146
B30: Sub total | D30: =SUM(D25:D29) | E30: =SUM(E25:E29) | F30: =SUM(F25:F29)
B32: Category of Services | D32: Retained Assets | E32: Retained Assets | F32: Retained Assets
B33: EUC | D33: ='Retained Assets'!M55 | E33: ='Retained Assets'!N55 | F33: ='Retained Assets'!O55
B34: Service Desk | D34: ='Retained Assets'!M62 | E34: ='Retained Assets'!N62 | F34: ='Retained Assets'!O62
B35: LAN Services | D35: ='Retained Assets'!M70 | E35: ='Retained Assets'!N70 | F35: ='Retained Assets'!O70
B36: Voice Services | D36: ='Retained Assets'!M136 | E36: ='Retained Assets'!N136 | F36: ='Retained Assets'!O136
B37: Server Management | D37: ='Retained Assets'!M153 | E37: ='Retained Assets'!N153 | F37: ='Retained Assets'!O153
B38: Sub total | D38: =SUM(D33:D37) | E38: =SUM(E33:E37) | F38: =SUM(F33:F37)
B40: Category of Services | D40: Others | E40: Others | F40: Others
B41: Projects | D41: =Project!D59 | E41: =Project!D60 | F41: =Project!D61
B42: T&T | D42: ='T&T'!D52+'T&T'!J52 | E42: ='T&T'!E52+'T&T'!K52 | F42: ='T&T'!F52+'T&T'!L52
B43: Retained Contract | D43: ='Ret.Contract'!L14 | E43: ='Ret.Contract'!M14 | F43: ='Ret.Contract'!N14
B44: Service Level Credit | D44: ='Serv.level.credit'!J19 | E44: ='Serv.level.credit'!K19
B45: Sub total | D45: =SUM(D41:D44) | E45: =SUM(E41:E44) | F45: =SUM(F41:F44)
B47: Adjustments/Corrections | D47: =Adjustment!D21
B49: Grand Total | D49: =D14+D22+D30+D38+D45+D47 | E49: =E14+E22+E30+E38+E45+E47 | F49: =F14+F22+F30+F38+F45+F47

Sheet Base Charge
B2: Invoice details - Base Charge
B3: End User Computing - VendorAOrigin
B5: Medium Service Level | D5: Period: | E5: =Period
B7: Category of Service | C7: Units | D7: Baseline/Volume | E7: Actual Volume | F7: Add./Red. Resource | G7: Price/Unit | H7: Period Base Charge | I7: ARC/RRC Rate | J7: Period ARC/RRC Amount | K7: Period Resource Unit Charge | M7: YTD Base Charge | N7: Forecast EOY Base Charge | O7: YTD ARC/RRC Amount | P7: Forecast EOYARC/RRC Amount | Q7: YTD Resource Unit Charge | R7: Forecast EOY Resource Unit Charge
B8: Standard Desktops (CEDS) | C8: Desktops per location code | F8: =D8-E8 | H8: =D8*G8 | J8: =F8*I8 | K8: =H8+J8
B9: Non-Standard Desktops (non CEDS) | C9: Desktops per location code | F9: =D9-E9 | H9: =D9*G9 | J9: =F9*I9 | K9: =H9+J9
B10: Standard Laptops (CEDS) | C10: Laptops per User | F10: =D10-E10 | H10: =D10*G10 | J10: =F10*I10 | K10: =H10+J10
B11: Non-Standard Laptops (non CEDS) | C11: Laptops per User | F11: =D11-E11 | H11: =D11*G11 | J11: =F11*I11 | K11: =H11+J11
B12: Standard Local Printers | C12: Desktops per location code | F12: =D12-E12 | H12: =D12*G12 | J12: =F12*I12 | K12: =H12+J12
B13: Non-Standard Local Printers | C13: Desktops per location code | F13: =D13-E13 | H13: =D13*G13 | J13: =F13*I13 | K13: =H13+J13
B14: Standard Network Printers | C14: Desktops per location code | F14: =D14-E14 | H14: =D14*G14 | J14: =F14*I14 | K14: =H14+J14
B15: Non-Standard Network Printers | C15: Desktops per location code | F15: =D15-E15 | H15: =D15*G15 | J15: =F15*I15 | K15: =H15+J15
B16: Other Peripherals | C16: Desktops per location code | F16: =D16-E16 | H16: =D16*G16 | J16: =F16*I16 | K16: =H16+J16
C17: Subtotal: | D17: =SUM(D8:D16) | E17: =SUM(E8:E16) | F17: =SUM(F8:F16) | H17: =SUM(H8:H16) | J17: =SUM(J8:J16) | K17: =SUM(K8:K16) | M17: =SUM(M8:M16) | N17: =SUM(N8:N16) | O17: =SUM(O8:O16) | P17: =SUM(P8:P16) | Q17: =SUM(Q8:Q16) | R17: =SUM(R8:R16)
B19: Installations
B21: Category of Service | C21: Units | D21: Baseline/Volume | E21: Actual Volume | F21: Add./Red. Resource | G21: Price/Unit | H21: Period Base Charge | I21: ARC/RRC Rate | J21: Period ARC/RRC Amount | K21: Period Resource Unit Charge | M21: YTD Base Charge | N21: Forecast EOY Base Charge | O21: YTD ARC/RRC Amount | P21: Forecast EOYARC/RRC Amount | Q21: YTD Resource Unit Charge | R21: Forecast EOY Resource Unit Charge
B22: Moves | C22: Desktops per location code | F22: =D22-E22 | H22: =D22*G22 | J22: =F22*I22 | K22: =H22+J22
B23: Adds | C23: Desktops per location code | F23: =D23-E23 | H23: =D23*G23 | J23: =F23*I23 | K23: =H23+J23
B24: Changes | C24: Desktops per location code | F24: =D24-E24 | H24: =D24*G24 | J24: =F24*I24 | K24: =H24+J24
C25: Subtotal: | D25: =SUM(D22:D24) | E25: =SUM(E22:E24) | F25: =SUM(F22:F24) | H25: =SUM(H22:H24) | J25: =SUM(J22:J24) | K25: =SUM(K22:K24) | M25: =SUM(M22:M24) | N25: =SUM(N22:N24) | O25: =SUM(O22:O24) | P25: =SUM(P22:P24) | Q25: =SUM(Q22:Q24) | R25: =SUM(R22:R24)
B27: Low Service Level
B29: Category of Service | C29: Units | D29: Baseline/Volume | E29: Actual Volume | F29: Add./Red. Resource | G29: Price/Unit | H29: Period Base Charge | I29: ARC/RRC Rate | J29: Period ARC/RRC Amount | K29: Period Resource Unit Charge | M29: YTD Base Charge | N29: Forecast EOY Base Charge | O29: YTD ARC/RRC Amount | P29: Forecast EOYARC/RRC Amount | Q29: YTD Resource Unit Charge | R29: Forecast EOY Resource Unit Charge
B30: Standard Desktops (CEDS) | C30: Desktops per location code | F30: =D30-E30 | H30: =D30*G30 | J30: =F30*I30 | K30: =H30+J30
B31: Non-Standard Desktops (non CEDS) | C31: Desktops per location code | F31: =D31-E31 | H31: =D31*G31 | J31: =F31*I31 | K31: =H31+J31
B32: Standard Laptops (CEDS) | C32: Laptops per User | F32: =D32-E32 | H32: =D32*G32 | J32: =F32*I32 | K32: =H32+J32
B33: Non-Standard Laptops (non CEDS) | C33: Laptops per User | F33: =D33-E33 | H33: =D33*G33 | J33: =F33*I33 | K33: =H33+J33
B34: Standard Local Printers | C34: Desktops per location code | F34: =D34-E34 | H34: =D34*G34 | J34: =F34*I34 | K34: =H34+J34
B35: Non-Standard Local Printers | C35: Desktops per location code | F35: =D35-E35 | H35: =D35*G35 | J35: =F35*I35 | K35: =H35+J35
B36: Standard Network Printers | C36: Desktops per location code | F36: =D36-E36 | H36: =D36*G36 | J36: =F36*I36 | K36: =H36+J36
B37: Non-Standard Network Printers | C37: Desktops per location code | F37: =D37-E37 | H37: =D37*G37 | J37: =F37*I37 | K37: =H37+J37
B38: Other Peripherals | C38: Desktops per location code | F38: =D38-E38 | H38: =D38*G38 | J38: =F38*I38 | K38: =H38+J38
C39: Subtotal: | D39: =SUM(D30:D38) | E39: =SUM(E30:E38) | F39: =SUM(F30:F38) | H39: =SUM(H30:H38) | J39: =SUM(J30:J38) | K39: =SUM(K30:K38) | M39: =SUM(M30:M38) | N39: =SUM(N30:N38) | O39: =SUM(O30:O38) | P39: =SUM(P30:P38) | Q39: =SUM(Q30:Q38) | R39: =SUM(R30:R38)
B41: Installations
B43: Category of Service | C43: Units | D43: Baseline/Volume | E43: Actual Volume | F43: Add./Red. Resource | G43: Price/Unit | H43: Period Base Charge | I43: ARC/RRC Rate | J43: Period ARC/RRC Amount | K43: Period Resource Unit Charge | M43: YTD Base Charge | N43: Forecast EOY Base Charge | O43: YTD ARC/RRC Amount | P43: Forecast EOYARC/RRC Amount | Q43: YTD Resource Unit Charge | R43: Forecast EOY Resource Unit Charge
B44: Moves | C44: Desktops per location code | F44: =D44-E44 | H44: =D44*G44 | J44: =F44*I44 | K44: =H44+J44
B45: Adds | C45: Desktops per location code | F45: =D45-E45 | H45: =D45*G45 | J45: =F45*I45 | K45: =H45+J45
B46: Changes | C46: Desktops per location code | F46: =D46-E46 | H46: =D46*G46 | J46: =F46*I46 | K46: =H46+J46
C47: Subtotal: | D47: =SUM(D44:D46) | E47: =SUM(E44:E46) | F47: =SUM(F44:F46) | H47: =SUM(H44:H46) | J47: =SUM(J44:J46) | K47: =SUM(K44:K46) | M47: =SUM(M44:M46) | N47: =SUM(N44:N46) | O47: =SUM(O44:O46) | P47: =SUM(P44:P46) | Q47: =SUM(Q44:Q46) | R47: =SUM(R44:R46)
B49: Packaging & Distribution
B51: Category of Service | C51: Units | D51: Baseline/Volume | E51: Actual Volume | F51: Add./Red. Resource | G51: Price/Unit | H51: Period Base Charge | I51: ARC/RRC Rate | J51: Period ARC/RRC Amount | K51: Period Resource Unit Charge | M51: YTD Base Charge | N51: Forecast EOY Base Charge | O51: YTD ARC/RRC Amount | P51: Forecast EOYARC/RRC Amount | Q51: YTD Resource Unit Charge | R51: Forecast EOY Resource Unit Charge
B52: Packages Distributed per year | C52: Desktops per location code | F52: =D52-E52 | H52: =D52*G52 | J52: =F52*I52 | K52: =H52+J52
C53: Subtotal: | D53: =SUM(D52) | E53: =SUM(E52) | F53: =SUM(F52) | H53: =SUM(H52) | J53: =SUM(J52) | K53: =SUM(K52) | M53: =SUM(M52) | N53: =SUM(N52) | O53: =SUM(O52) | P53: =SUM(P52) | Q53: =SUM(Q52) | R53: =SUM(R52)
C55: Total End User Computing: | D55: =D17+D25+D39+D47+D53 | E55: =E17+E25+E39+E47+E53 | F55: =F17+F25+F39+F47+F53 | H55: =H17+H25+H39+H47+H53 | J55: =J17+J25+J39+J47+J53 | K55: =K17+K25+K39+K47+K53 | M55: =M17+M25+M39+M47+M53 | N55: =N17+N25+N39+N47+N53 | O55: =O17+O25+O39+O47+O53 | P55: =P17+P25+P39+P47+P53 | Q55: =Q17+Q25+Q39+Q47+Q53 | R55: =R17+R25+R39+R47+R53
B57: Service Desk - Vendor Gamma
B59: Category of Service | C59: Units | D59: Baseline/Volume | E59: Actual Volume | F59: Add./Red. Resource | G59: Price/Unit | H59: Period Base Charge | I59: ARC/RRC Rate | J59: Period ARC/RRC Amount | K59: Period Resource Unit Charge | M59: YTD Base Charge | N59: Forecast EOY Base Charge | O59: YTD ARC/RRC Amount | P59: Forecast EOYARC/RRC Amount | Q59: YTD Resource Unit Charge | R59: Forecast EOY Resource Unit Charge
B60: Seats Supported | C60: Physical users | F60: =D60-E60 | H60: =D60*G60 | J60: =F60*I60 | K60: =H60+J60
C62: Total Service Desk: | D62: =SUM(D60) | E62: =SUM(E60) | F62: =SUM(F60) | H62: =SUM(H60) | J62: =SUM(J60) | K62: =SUM(K60) | M62: =SUM(M60) | N62: =SUM(N60) | O62: =SUM(O60) | P62: =SUM(P60) | Q62: =SUM(Q60) | R62: =SUM(R60)
B64: Lan Services - TelCo
B66: Category of Service | C66: Units | D66: Baseline/Volume | E66: Actual Volume | F66: Add./Red. Resource | G66: Price/Unit | H66: Period Base Charge | I66: ARC/RRC Rate | J66: Period ARC/RRC Amount | K66: Period Resource Unit Charge | M66: YTD Base Charge | N66: Forecast EOY Base Charge | O66: YTD ARC/RRC Amount | P66: Forecast EOYARC/RRC Amount | Q66: YTD Resource Unit Charge | R66: Forecast EOY Resource Unit Charge
B67: LAN-Attached Devices | C67: Active ports | F67: =D67-E67 | H67: =D67*G67 | J67: =F67*I67 | K67: =H67+J67
B68: Monitoring LAN ports | C68: Active ports | F68: =D68-E68 | H68: =D68*G68 | J68: =F68*I68 | K68: =H68+J68
C70: Total LAN Services: | D70: =SUM(D67:D68) | E70: =SUM(E67:E68) | F70: =SUM(F67:F68) | H70: =SUM(H67:H68) | J70: =SUM(J67:J68) | K70: =SUM(K67:K68) | M70: =SUM(M67:M68) | N70: =SUM(N67:N68) | O70: =SUM(O67:O68) | P70: =SUM(P67:P68) | Q70: =SUM(Q67:Q68) | R70: =SUM(R67:R68)
B72: Voice Services - TelCo
B74: Category of Service | C74: Units | D74: Baseline/Volume | E74: Actual Volume | F74: Add./Red. Resource | G74: Price/Unit | H74: Period Base Charge | I74: ARC/RRC Rate | J74: Period ARC/RRC Amount | K74: Period Resource Unit Charge | M74: YTD Base Charge | N74: Forecast EOY Base Charge | O74: YTD ARC/RRC Amount | P74: Forecast EOYARC/RRC Amount | Q74: YTD Resource Unit Charge | R74: Forecast EOY Resource Unit Charge
B75: Call Centers | C75: Seats | F75: =D75-E75 | H75: =D75*G75 | J75: =F75*I75 | K75: =H75+J75
B76: Employee ISDN | C76: ISDN subscriptions | F76: =D76-E76 | H76: =D76*G76 | J76: =F76*I76 | K76: =H76+J76
B77: Video conferencing | C77: Video conference rooms | F77: =D77-E77 | H77: =D77*G77 | J77: =F77*I77 | K77: =H77+J77
B78: Handsets - Digital (incl. DECT) | C78: Sets | F78: =D78-E78 | H78: =D78*G78 | J78: =F78*I78 | K78: =H78+J78
B79: Handsets - Analog | C79: Sets | F79: =D79-E79 | H79: =D79*G79 | J79: =F79*I79 | K79: =H79+J79
B80: Cellular Phones management fee | C80: Subscriptions | F80: =D80-E80 | H80: =D80*G80 | J80: =F80*I80 | K80: =H80+J80
B81: Cellular Phones subscription | C81: Subscriptions | F81: =D81-E81 | H81: =D81*G81 | J81: =F81*I81 | K81: =H81+J81
B82: Cellular Phones refresh | C82: Devices | F82: =D82-E82 | H82: =D82*G82 | J82: =F82*I82 | K82: =H82+J82
B83: GPRS/UMTS Cards or Devices management fee | C83: Subscriptions | F83: =D83-E83 | H83: =D83*G83 | J83: =F83*I83 | K83: =H83+J83
B84: GPRS/UMTS Cards or Devices subscription | C84: Subscriptions | F84: =D84-E84 | H84: =D84*G84 | J84: =F84*I84 | K84: =H84+J84
B85: GPRS/UMTS Cards or Devices refresh | C85: Devices | F85: =D85-E85 | H85: =D85*G85 | J85: =F85*I85 | K85: =H85+J85
B86: Blackberries management fee | C86: Subscriptions | F86: =D86-E86 | H86: =D86*G86 | J86: =F86*I86 | K86: =H86+J86
... B92: External Pagers refresh | C92: Devices | F92: =D92-E92 | H92: =D92*G92 | J92: =F92*I92 | K92: =H92+J92
C93: Subtotal: | D93: =SUM(D75:D92) | E93: =SUM(E75:E92) | F93: =SUM(F75:F92) | H93: =SUM(H75:H92) | J93: =SUM(J75:J92) | K93: =SUM(K75:K92) | M93: =SUM(M75:M92) | N93: =SUM(N75:N92) | O93: =SUM(O75:O92) | P93: =SUM(P75:P92) | Q93: =SUM(Q75:Q92) | R93: =SUM(R75:R92)
B95: Voice consumption
B97: Category of Service | C97: Units | D97: Baseline/Volume | E97: Actual Volume | F97: Add./Red. Resource | G97: Price/Unit | H97: Period Base Charge | I97: ARC/RRC Rate | J97: Period ARC/RRC Amount | K97: Period Resource Unit Charge | M97: YTD Base Charge | N97: Forecast EOY Base Charge | O97: YTD ARC/RRC Amount | P97: Forecast EOYARC/RRC Amount | Q97: YTD Resource Unit Charge | R97: Forecast EOY Resource Unit Charge
B98: Domestic Outbound Calls - Local | C98: Minutes | F98: =D98-E98 | H98: =D98*G98 | J98: =F98*I98 | K98: =H98+J98
B99: Domestic Outbound Calls - Long Distance | C99: Minutes | F99: =D99-E99 | H99: =D99*G99 | J99: =F99*I99 | K99: =H99+J99
B100: Domestic Outbound Calls - Cellular | C100: Minutes | F100: =D100-E100 | H100: =D100*G100 | J100: =F100*I100 | K100: =H100+J100
B101: International Outbound Calls | C101: Minutes | F101: =D101-E101 | H101: =D101*G101 | J101: =F101*I101 | K101: =H101+J101
B102: Mobile - national | C102: Minutes | F102: =D102-E102 | H102: =D102*G102 | J102: =F102*I102 | K102: =H102+J102
B103: Mobile - international | C103: Minutes | F103: =D103-E103 | H103: =D103*G103 | J103: =F103*I103 | K103: =H103+J103
B104: Mobile - roaming outbound | C104: Minutes | F104: =D104-E104 | H104: =D104*G104 | J104: =F104*I104 | K104: =H104+J104
B105: Mobile - roaming inbound | C105: Minutes | F105: =D105-E105 | H105: =D105*G105 | J105: =F105*I105 | K105: =H105+J105
B106: Free phone Service Calls | C106: Calls | F106: =D106-E106 | H106: =D106*G106 | J106: =F106*I106 | K106: =H106+J106
B107: Free phone Services Dedicated per min. | C107: Minutes | F107: =D107-E107 | H107: =D107*G107 | J107: =F107*I107 | K107: =H107+J107
B108: High Tariff Outbound Calls (0900) | C108: Minutes | F108: =D108-E108 | H108: =D108*G108 | J108: =F108*I108 | K108: =H108+J108
B109: High Tariff Outbound Calls (0676 internet) | C109: Minutes | F109: =D109-E109 | H109: =D109*G109 | J109: =F109*I109 | K109: =H109+J109
... B112: Voice - IMACS | C112: IMACS | F112: =D112-E112 | H112: =D112*G112 | J112: =F112*I112 | K112: =H112+J112
C113: Subtotal: | D113: =SUM(D98:D112) | E113: =SUM(E98:E112) | F113: =SUM(F98:F112) | H113: =SUM(H98:H112) | J113: =SUM(J98:J112) | K113: =SUM(K98:K112) | M113: =SUM(M98:M112) | N113: =SUM(N98:N112) | O113: =SUM(O98:O112) | P113: =SUM(P98:P112) | Q113: =SUM(Q98:Q112) | R113: =SUM(R98:R112)
B115: Voice subscriptions
B117: Category of Service | C117: Units | D117: Baseline/Volume | E117: Actual Volume | F117: Add./Red. Resource | G117: Price/Unit | H117: Period Base Charge | I117: ARC/RRC Rate | J117: Period ARC/RRC Amount | K117: Period Resource Unit Charge | M117: YTD Base Charge | N117: Forecast EOY Base Charge | O117: YTD ARC/RRC Amount | P117: Forecast EOYARC/RRC Amount | Q117: YTD Resource Unit Charge | R117: Forecast EOY Resource Unit Charge
B118: ISDN 1 | C118: Subscriptions | F118: =D118-E118 | H118: =D118*G118 | J118: =F118*I118 | K118: =H118+J118
B119: ISDN 2 | C119: Subscriptions | F119: =D119-E119 | H119: =D119*G119 | J119: =F119*I119 | K119: =H119+J119
B120: ISDN 15 | C120: Subscriptions | F120: =D120-E120 | H120: =D120*G120 | J120: =F120*I120 | K120: =H120+J120
B121: ISDN 30 | C121: Subscriptions | F121: =D121-E121 | H121: =D121*G121 | J121: =F121*I121 | K121: =H121+J121
B122: ISDN 30 (CPA) | C122: Subscriptions | F122: =D122-E122 | H122: =D122*G122 | J122: =F122*I122 | K122: =H122+J122
B123: Dual homing telephony | C123: Subscriptions | F123: =D123-E123 | H123: =D123*G123 | J123: =F123*I123 | K123: =H123+J123
B124: DDI reserved numbers (10) | C124: Subscriptions | F124: =D124-E124 | H124: =D124*G124 | J124: =F124*I124 | K124: =H124+J124
B125: DDI reserved numbers (100) | C125: Subscriptions | F125: =D125-E125 | H125: =D125*G125 | J125: =F125*I125 | K125: =H125+J125
B126: DDI reserved numbers (1000) | C126: Subscriptions | F126: =D126-E126 | H126: =D126*G126 | J126: =F126*I126 | K126: =H126+J126
B127: DDI reserved numbers (10000) | C127: Subscriptions | F127: =D127-E127 | H127: =D127*G127 | J127: =F127*I127 | K127: =H127+J127
B128: DDI facilities | C128: Subscriptions | F128: =D128-E128 | H128: =D128*G128 | J128: =F128*I128 | K128: =H128+J128
B129: Calamity services | C129: Services | F129: =D129-E129 | H129: =D129*G129 | J129: =F129*I129 | K129: =H129+J129
... B133: Telex | C133: Subscriptions | F133: =D133-E133 | H133: =D133*G133 | J133: =F133*I133 | K133: =H133+J133
C134: Subtotal: | D134: =SUM(D118:D133) | E134: =SUM(E118:E133) | F134: =SUM(F118:F133) | H134: =SUM(H118:H133) | J134: =SUM(J118:J133) | K134: =SUM(K118:K133) | M134: =SUM(M118:M133) | N134: =SUM(N118:N133) | O134: =SUM(O118:O133) | P134: =SUM(P118:P133) | Q134: =SUM(Q118:Q133) | R134: =SUM(R118:R133)
...

Sheet Passthrough
B2: Invoice details - Passthrough | H2: I = Investment
B3: End User Computing - VendorAOrigin | H3: L = Lease
H4: C = Contract
B5: Medium Service Level | D5: Period: | E5: =Period | H5: D = Direct Expense
B7: Category of Service | C7: Units | D7: Contract code | E7: Supplier | F7: Country | G7: Description | H7: I/L/C/D | I7: Start date | J7: Duration | K7: Volume | L7: Investement/Contract amount | M7: Current month | N7: Ytd | O7: Forecast Year 1 | P7: Forecast Year 2 | Q7: Forecast Year 3 | R7: Forecast Year 4 | S7: Forecast Year 5
B8: Standard Desktops (CEDS) | C8: Desktops per location code
B9: Non-Standard Desktops (non CEDS) | C9: Desktops per location code
B10: Standard Laptops (CEDS) | C10: Laptops per User
B11: Non-Standard Laptops (non CEDS) | C11: Laptops per User
B12: Standard Local Printers | C12: Desktops per location code
B13: Non-Standard Local Printers | C13: Desktops per location code
B14: Standard Network Printers | C14: Desktops per location code
B15: Non-Standard Network Printers | C15: Desktops per location code
B16: Other Peripherals | C16: Desktops per location code
C17: Subtotal: | K17: =SUM(K8:K16) | L17: =SUM(L8:L16) | M17: =SUM(M8:M16) | N17: =SUM(N8:N16) | O17: =SUM(O8:O16) | P17: =SUM(P8:P16) | Q17: =SUM(Q8:Q16) | R17: =SUM(R8:R16) | S17: =SUM(S8:S16)
B19: Installations
B21: Category of Service | C21: Units | D21: Contract code | E21: Supplier | F21: Country | G21: Description | H21: I/L/C/D | I21: Start date | J21: Duration | K21: Volume | L21: Investement/Contract amount | M21: Current month | N21: Ytd | O21: Forecast Year 1 | P21: Forecast Year 2 | Q21: Forecast Year 3 | R21: Forecast Year 4 | S21: Forecast Year 5
B22: Moves | C22: Desktops per location code
B23: Adds | C23: Desktops per location code
B24: Changes | C24: Desktops per location code
C25: Subtotal: | K25: =SUM(K22:K24) | L25: =SUM(L22:L24) | M25: =SUM(M22:M24) | N25: =SUM(N22:N24) | O25: =SUM(O22:O24) | P25: =SUM(P22:P24) | Q25: =SUM(Q22:Q24) | R25: =SUM(R22:R24) | S25: =SUM(S22:S24)
B27: Low Service Level
B29: Category of Service | C29: Units | D29: Contract code | E29: Supplier | F29: Country | G29: Description | H29: I/L/C/D | I29: Start date | J29: Duration | K29: Volume | L29: Investement/Contract amount | M29: Current month | N29: Ytd | O29: Forecast Year 1 | P29: Forecast Year 2 | Q29: Forecast Year 3 | R29: Forecast Year 4 | S29: Forecast Year 5
B30: Standard Desktops (CEDS) | C30: Desktops per location code
B31: Non-Standard Desktops (non CEDS) | C31: Desktops per location code
B32: Standard Laptops (CEDS) | C32: Laptops per User
B33: Non-Standard Laptops (non CEDS) | C33: Laptops per User
B34: Standard Local Printers | C34: Desktops per location code
B35: Non-Standard Local Printers | C35: Desktops per location code
B36: Standard Network Printers | C36: Desktops per location code
B37: Non-Standard Network Printers | C37: Desktops per location code
B38: Other Peripherals | C38: Desktops per location code
C39: Subtotal: | K39: =SUM(K30:K38) | L39: =SUM(L30:L38) | M39: =SUM(M30:M38) | N39: =SUM(N30:N38) | O39: =SUM(O30:O38) | P39: =SUM(P30:P38) | Q39: =SUM(Q30:Q38) | R39: =SUM(R30:R38) | S39: =SUM(S30:S38)
B41: Installations
B43: Category of Service | C43: Units | D43: Contract code | E43: Supplier | F43: Country | G43: Description | H43: I/L/C/D | I43: Start date | J43: Duration | K43: Volume | L43: Investement/Contract amount | M43: Current month | N43: Ytd | O43: Forecast Year 1 | P43: Forecast Year 2 | Q43: Forecast Year 3 | R43: Forecast Year 4 | S43: Forecast Year 5
B44: Moves | C44: Desktops per location code
B45: Adds | C45: Desktops per location code
B46: Changes | C46: Desktops per location code
C47: Subtotal: | K47: =SUM(K44:K46) | L47: =SUM(L44:L46) | M47: =SUM(M44:M46) | N47: =SUM(N44:N46) | O47: =SUM(O44:O46) | P47: =SUM(P44:P46) | Q47: =SUM(Q44:Q46) | R47: =SUM(R44:R46) | S47: =SUM(S44:S46)
B49: Packaging & Distribution
B51: Category of Service | C51: Units | D51: Contract code | E51: Supplier | F51: Country | G51: Description | H51: I/L/C/D | I51: Start date | J51: Duration | K51: Volume | L51: Investement/Contract amount | M51: Current month | N51: Ytd | O51: Forecast Year 1 | P51: Forecast Year 2 | Q51: Forecast Year 3 | R51: Forecast Year 4 | S51: Forecast Year 5
B52: Packages Distributed per year | C52: Desktops per location code
C53: Subtotal: | K53: =SUM(K52) | L53: =SUM(L52) | M53: =SUM(M52) | N53: =SUM(N52) | O53: =SUM(O52) | P53: =SUM(P52) | Q53: =SUM(Q52) | R53: =SUM(R52) | S53: =SUM(S52)
C55: Total End User Computing: | K55: =K17+K25+K39+K47+K53 | L55: =L17+L25+L39+L47+L53 | M55: =M17+M25+M39+M47+M53 | N55: =N17+N25+N39+N47+N53 | O55: =O17+O25+O39+O47+O53 | P55: =P17+P25+P39+P47+P53 | Q55: =Q17+Q25+Q39+Q47+Q53 | R55: =R17+R25+R39+R47+R53 | S55: =S17+S25+S39+S47+S53
B57: Service Desk - Vendor Gamma
B59: Category of Service | C59: Units | D59: Contract code | E59: Supplier | F59: Country | G59: Description | H59: I/L/C/D | I59: Start date | J59: Duration | K59: Volume | L59: Investement/Contract amount | M59: Current month | N59: Ytd | O59: Forecast Year 1 | P59: Forecast Year 2 | Q59: Forecast Year 3 | R59: Forecast Year 4 | S59: Forecast Year 5
B60: Seats Supported | C60: Physical users
C62: Total Service Desk: | K62: =SUM(K60) | L62: =SUM(L60) | M62: =SUM(M60) | N62: =SUM(N60) | O62: =SUM(O60) | P62: =SUM(P60) | Q62: =SUM(Q60) | R62: =SUM(R60) | S62: =SUM(S60)
B64: Lan Services - TelCo
B66: Category of Service | C66: Units | D66: Contract code | E66: Supplier | F66: Country | G66: Description | H66: I/L/C/D | I66: Start date | J66: Duration | K66: Volume | L66: Investement/Contract amount | M66: Current month | N66: Ytd | O66: Forecast Year 1 | P66: Forecast Year 2 | Q66: Forecast Year 3 | R66: Forecast Year 4 | S66: Forecast Year 5
B67: LAN-Attached Devices | C67: Active ports
B68: Monitoring LAN ports | C68: Active ports
C70: Total LAN Services: | K70: =SUM(K67) | L70: =SUM(L67) | M70: =SUM(M67) | N70: =SUM(N67) | O70: =SUM(O67) | P70: =SUM(P67) | Q70: =SUM(Q67) | R70: =SUM(R67) | S70: =SUM(S67)
B72: Voice Services - TelCo
B74: Category of Service | C74: Units | D74: Contract code | E74: Supplier | F74: Country | G74: Description | H74: I/L/C/D | I74: Start date | J74: Duration | K74: Volume | L74: Investement/Contract amount | M74: Current month | N74: Ytd | O74: Forecast Year 1 | P74: Forecast Year 2 | Q74: Forecast Year 3 | R74: Forecast Year 4 | S74: Forecast Year 5
B75: Call Centers | C75: Seats
B76: Employee ISDN | C76: ISDN subscriptions
B77: Video conferencing | C77: Video conference rooms
B78: Handsets - Digital (incl. DECT) | C78: Sets
B79: Handsets - Analog | C79: Sets
B80: Cellular Phones management fee | C80: Subscriptions
B81: Cellular Phones subscription | C81: Subscriptions
B82: Cellular Phones refresh | C82: Devices
B83: GPRS/UMTS Cards or Devices management fee | C83: Subscriptions
B84: GPRS/UMTS Cards or Devices subscription | C84: Subscriptions
B85: GPRS/UMTS Cards or Devices refresh | C85: Devices
B86: Blackberries management fee | C86: Subscriptions
... B92: External Pagers refresh | C92: Devices
C93: Subtotal: | K93: =SUM(K75:K92) | L93: =SUM(L75:L92) | M93: =SUM(M75:M92) | N93: =SUM(N75:N92) | O93: =SUM(O75:O92) | P93: =SUM(P75:P92) | Q93: =SUM(Q75:Q92) | R93: =SUM(R75:R92) | S93: =SUM(S75:S92)
B95: Voice consumption
B97: Category of Service | C97: Units | D97: Contract code | E97: Supplier | F97: Country | G97: Description | H97: I/L/C/D | I97: Start date | J97: Duration | K97: Volume | L97: Investement/Contract amount | M97: Current month | N97: Ytd | O97: Forecast Year 1 | P97: Forecast Year 2 | Q97: Forecast Year 3 | R97: Forecast Year 4 | S97: Forecast Year 5
B98: Domestic Outbound Calls - Local | C98: Minutes
B99: Domestic Outbound Calls - Long Distance | C99: Minutes
B100: Domestic Outbound Calls - Cellular | C100: Minutes
B101: International Outbound Calls | C101: Minutes
B102: Mobile - national | C102: Minutes
B103: Mobile - international | C103: Minutes
B104: Mobile - roaming outbound | C104: Minutes
B105: Mobile - roaming inbound | C105: Minutes
B106: Free phone Service Calls | C106: Calls
B107: Free phone Services Dedicated per min. | C107: Minutes
B108: High Tariff Outbound Calls (0900) | C108: Minutes
B109: High Tariff Outbound Calls (0676 internet) | C109: Minutes
... B112: Voice - IMACS | C112: IMACS
C113: Subtotal: | K113: =SUM(K98:K112) | L113: =SUM(L98:L112) | M113: =SUM(M98:M112) | N113: =SUM(N98:N112) | O113: =SUM(O98:O112) | P113: =SUM(P98:P112) | Q113: =SUM(Q98:Q112) | R113: =SUM(R98:R112) | S113: =SUM(S98:S112)
B115: Voice subscriptions
B117: Category of Service | C117: Units | D117: Contract code | E117: Supplier | F117: Country | G117: Description | H117: I/L/C/D | I117: Start date | J117: Duration | K117: Volume | L117: Investement/Contract amount | M117: Current month | N117: Ytd | O117: Forecast Year 1 | P117: Forecast Year 2 | Q117: Forecast Year 3 | R117: Forecast Year 4 | S117: Forecast Year 5
B118: ISDN 1 | C118: Subscriptions
B119: ISDN 2 | C119: Subscriptions
B120: ISDN 15 | C120: Subscriptions
B121: ISDN 30 | C121: Subscriptions
B122: ISDN 30 (CPA) | C122: Subscriptions
B123: Dual homing telephony | C123: Subscriptions
B124: DDI reserved numbers (10) | C124: Subscriptions
B125: DDI reserved numbers (100) | C125: Subscriptions
B126: DDI reserved numbers (1000) | C126: Subscriptions
B127: DDI reserved numbers (10000) | C127: Subscriptions
B128: DDI facilities | C128: Subscriptions
B129: Calamity services | C129: Services
... B133: Telex | C133: Subscriptions
...

Sheet Retained Assets
B2: Invoice details - Asset | H2: I = Investment
B3: End User Computing - VendorAOrigin | H3: L = Lease
H4: C = Contract
B5: Medium Service Level | D5: Period: | E5: Period: | F5: =Period | H5: D = Direct Expense
B7: Category of Service | C7: Units | D7: Contract code | E7: Supplier | F7: Country | G7: Description | H7: I/L/C/D | I7: Start date | J7: Duration | K7: Volume | L7: Investement/Contract amount | M7: Current month | N7: Ytd | O7: Forecast Year 1 | P7: Forecast Year 2 | Q7: Forecast Year 3 | R7: Forecast Year 4 | S7: Forecast Year 5
B8: Standard Desktops (CEDS) | C8: Desktops per location code
B9: Non-Standard Desktops (non CEDS) | C9: Desktops per location code
B10: Standard Laptops (CEDS) | C10: Laptops per User
B11: Non-Standard Laptops (non CEDS) | C11: Laptops per User
B12: Standard Local Printers | C12: Desktops per location code
B13: Non-Standard Local Printers | C13: Desktops per location code
B14: Standard Network Printers | C14: Desktops per location code
B15: Non-Standard Network Printers | C15: Desktops per location code
B16: Other Peripherals | C16: Desktops per location code
C17: Subtotal: | K17: =SUM(K8:K16) | L17: =SUM(L8:L16) | M17: =SUM(M8:M16) | N17: =SUM(N8:N16) | O17: =SUM(O8:O16) | P17: =SUM(P8:P16) | Q17: =SUM(Q8:Q16) | R17: =SUM(R8:R16) | S17: =SUM(S8:S16)
B19: Installations
B21: Category of Service | C21: Units | D21: Contract code | E21: Contract code | F21: Country | G21: Description | H21: I/L/C/D | I21: Start date | J21: Duration | K21: Volume | L21: Investement/Contract amount | M21: Current month | N21: Ytd | O21: Year 1 | P21: Year 2 | Q21: Year 3 | R21: Year 4 | S21: Year 5
B22: Moves | C22: Desktops per location code
B23: Adds | C23: Desktops per location code
B24: Changes | C24: Desktops per location code
C25: Subtotal: | K25: =SUM(K22:K24) | L25: =SUM(L22:L24) | M25: =SUM(M22:M24) | N25: =SUM(N22:N24) | O25: =SUM(O22:O24) | P25: =SUM(P22:P24) | Q25: =SUM(Q22:Q24) | R25: =SUM(R22:R24) | S25: =SUM(S22:S24)
B27: Low Service Level
B29: Category of Service | C29: Units | D29: Contract code | E29: Contract code | F29: Country | G29: Description | H29: I/L/C/D | I29: Start date | J29: Duration | K29: Volume | L29: Investement/Contract amount | M29: Current month | N29: Ytd | O29: Year 1 | P29: Year 2 | Q29: Year 3 | R29: Year 4 | S29: Year 5
B30: Standard Desktops (CEDS) | C30: Desktops per location code
B31: Non-Standard Desktops (non CEDS) | C31: Desktops per location code
B32: Standard Laptops (CEDS) | C32: Laptops per User
B33: Non-Standard Laptops (non CEDS) | C33: Laptops per User
B34: Standard Local Printers | C34: Desktops per location code
B35: Non-Standard Local Printers | C35: Desktops per location code
B36: Standard Network Printers | C36: Desktops per location code
B37: Non-Standard Network Printers | C37: Desktops per location code
B38: Other Peripherals | C38: Desktops per location code
C39: Subtotal: | K39: =SUM(K30:K38) | L39: =SUM(L30:L38) | M39: =SUM(M30:M38) | N39: =SUM(N30:N38) | O39: =SUM(O30:O38) | P39: =SUM(P30:P38) | Q39: =SUM(Q30:Q38) | R39: =SUM(R30:R38) | S39: =SUM(S30:S38)
B41: Installations
B43: Category of Service | C43: Units | D43: Contract code | E43: Contract code | F43: Country | G43: Description | H43: I/L/C/D | I43: Start date | J43: Duration | K43: Volume | L43: Investement/Contract amount | M43: Current month | N43: Ytd | O43: Year 1 | P43: Year 2 | Q43: Year 3 | R43: Year 4 | S43: Year 5
B44: Moves | C44: Desktops per location code
B45: Adds | C45: Desktops per location code
B46: Changes | C46: Desktops per location code
C47: Subtotal: | K47: =SUM(K44:K46) | L47: =SUM(L44:L46) | M47: =SUM(M44:M46) | N47: =SUM(N44:N46) | O47: =SUM(O44:O46) | P47: =SUM(P44:P46) | Q47: =SUM(Q44:Q46) | R47: =SUM(R44:R46) | S47: =SUM(S44:S46)
B49: Packaging & Distribution
B51: Category of Service | C51: Units | D51: Contract code | E51: Contract code | F51: Country | G51: Description | H51: I/L/C/D | I51: Start date | J51: Duration | K51: Volume | L51: Investement/Contract amount | M51: Current month | N51: Ytd | O51: Year 1 | P51: Year 2 | Q51: Year 3 | R51: Year 4 | S51: Year 5
B52: Packages Distributed per year | C52: Desktops per location code
C53: Subtotal: | K53: =SUM(K52) | L53: =SUM(L52) | M53: =SUM(M52) | N53: =SUM(N52) | O53: =SUM(O52) | P53: =SUM(P52) | Q53: =SUM(Q52) | R53: =SUM(R52) | S53: =SUM(S52)
C55: Total End User Computing: | K55: =K17+K25+K39+K47+K53 | L55: =L17+L25+L39+L47+L53 | M55: =M17+M25+M39+M47+M53 | N55: =N17+N25+N39+N47+N53 | O55: =O17+O25+O39+O47+O53 | P55: =P17+P25+P39+P47+P53 | Q55: =Q17+Q25+Q39+Q47+Q53 | R55: =R17+R25+R39+R47+R53 | S55: =S17+S25+S39+S47+S53
B57: Service Desk - Vendor Gamma
B59: Category of Service | C59: Units | D59: Contract code | E59: Contract code | F59: Country | G59: Description | H59: I/L/C/D | I59: Start date | J59: Duration | K59: Volume | L59: Investement/Contract amount | M59: Current month | N59: Ytd | O59: Year 1 | P59: Year 2 | Q59: Year 3 | R59: Year 4 | S59: Year 5
B60: Seats Supported | C60: Physical users
C62: Total Sevice Desk: | K62: =SUM(K60) | L62: =SUM(L60) | M62: =SUM(M60) | N62: =SUM(N60) | O62: =SUM(O60) | P62: =SUM(P60) | Q62: =SUM(Q60) | R62: =SUM(R60) | S62: =SUM(S60)
B64: Lan Services - TelCo
B66: Category of Service | C66: Units | D66: Contract code | E66: Contract code | F66: Country | G66: Description | H66: I/L/C/D | I66: Start date | J66: Duration | K66: Volume | L66: Investement/Contract amount | M66: Current month | N66: Ytd | O66: Year 1 | P66: Year 2 | Q66: Year 3 | R66: Year 4 | S66: Year 5
B67: LAN-Attached Devices | C67: Active ports
B68: Monitoring LAN ports | C68: Active ports
C70: Total LAN Services: | K70: =SUM(K67) | L70: =SUM(L67) | M70: =SUM(M67) | N70: =SUM(N67) | O70: =SUM(O67) | P70: =SUM(P67) | Q70: =SUM(Q67) | R70: =SUM(R67) | S70: =SUM(S67)
B72: Voice Services - TelCo
B74: Category of Service | C74: Units | D74: Contract code | E74: Contract code | F74: Country | G74: Description | H74: I/L/C/D | I74: Start date | J74: Duration | K74: Volume | L74: Investement/Contract amount | M74: Current month | N74: Ytd | O74: Year 1 | P74: Year 2 | Q74: Year 3 | R74: Year 4 | S74: Year 5
B75: Call Centers | C75: Seats
B76: Employee ISDN | C76: ISDN subscriptions
B77: Video conferencing | C77: Video conference rooms
B78: Handsets - Digital (incl. DECT) | C78: Sets
B79: Handsets - Analog | C79: Sets
B80: Cellular Phones management fee | C80: Subscriptions
B81: Cellular Phones subscription | C81: Subscriptions
B82: Cellular Phones refresh | C82: Devices
B83: GPRS/UMTS Cards or Devices management fee | C83: Subscriptions
B84: GPRS/UMTS Cards or Devices subscription | C84: Subscriptions
B85: GPRS/UMTS Cards or Devices refresh | C85: Devices
B86: Blackberries management fee | C86: Subscriptions
... B92: External Pagers refresh | C92: Devices
C93: Subtotal: | K93: =SUM(K75:K92) | L93: =SUM(L75:L92) | M93: =SUM(M75:M92) | N93: =SUM(N75:N92) | O93: =SUM(O75:O92) | P93: =SUM(P75:P92) | Q93: =SUM(Q75:Q92) | R93: =SUM(R75:R92) | S93: =SUM(S75:S92)
B95: Voice consumption
B97: Category of Service | C97: Units | D97: Contract code | E97: Contract code | F97: Country | G97: Description | H97: I/L/C/D | I97: Start date | J97: Duration | K97: Volume | L97: Investement/Contract amount | M97: Current month | N97: Ytd | O97: Year 1 | P97: Year 2 | Q97: Year 3 | R97: Year 4 | S97: Year 5
B98: Domestic Outbound Calls - Local | C98: Minutes
B99: Domestic Outbound Calls - Long Distance | C99: Minutes
B100: Domestic Outbound Calls - Cellular | C100: Minutes
B101: International Outbound Calls | C101: Minutes
B102: Mobile - national | C102: Minutes
B103: Mobile - international | C103: Minutes
B104: Mobile - roaming outbound | C104: Minutes
B105: Mobile - roaming inbound | C105: Minutes
B106: Free phone Service Calls | C106: Calls
B107: Free phone Services Dedicated per min. | C107: Minutes
B108: High Tariff Outbound Calls (0900) | C108: Minutes
B109: High Tariff Outbound Calls (0676 internet) | C109: Minutes
... B112: Voice - IMACS | C112: IMACS
C113: Subtotal: | K113: =SUM(K98:K112) | L113: =SUM(L98:L112) | M113: =SUM(M98:M112) | N113: =SUM(N98:N112) | O113: =SUM(O98:O112) | P113: =SUM(P98:P112) | Q113: =SUM(Q98:Q112) | R113: =SUM(R98:R112) | S113: =SUM(S98:S112)
B115: Voice subscriptions
B117: Category of Service | C117: Units | D117: Contract code | E117: Contract code | F117: Country | G117: Description | H117: I/L/C/D | I117: Start date | J117: Duration | K117: Volume | L117: Investement/Contract amount | M117: Current month | N117: Ytd | O117: Year 1 | P117: Year 2 | Q117: Year 3 | R117: Year 4 | S117: Year 5
B118: ISDN 1 | C118: Subscriptions
B119: ISDN 2 | C119: Subscriptions
B120: ISDN 15 | C120: Subscriptions
B121: ISDN 30 | C121: Subscriptions
B122: ISDN 30 (CPA) | C122: Subscriptions
B123: Dual homing telephony | C123: Subscriptions
B124: DDI reserved numbers (10) | C124: Subscriptions
B125: DDI reserved numbers (100) | C125: Subscriptions
B126: DDI reserved numbers (1000) | C126: Subscriptions
B127: DDI reserved numbers (10000) | C127: Subscriptions
B128: DDI facilities | C128: Subscriptions
B129: Calamity services | C129: Services
... B133: Telex | C133: Subscriptions
...

Sheet Ret.Contract
B2: Invoice details - Retained Contract | D2: Period: | E2: =Period
B4: bundle | C4: Contract code / Ref. No. | D4: Agreement Number | E4: Location (NL/Be) | F4: PST member | G4: Third Party Vendor | H4: Description of Services | I4: Start date | J4: Expiration Date | K4: Contract period | L4: Current month | M4: YTD payment | N4: Forecast Year 1 | O4: Forecast Year 2 | P4: Forecast Year 3 | Q4: Forecast Year 4 | R4: Forecast Year 5 | S4: remarks
B14: Total | H14: =SUM(H5:H13) | I14: =SUM(I5:I13) | J14: =SUM(J5:J13) | K14: =SUM(K5:K13) | L14: =SUM(L5:L13) | M14: =SUM(M5:M13) | N14: =SUM(N5:N13) | O14: =SUM(O5:O13) | ... S14: =SUM(S5:S13)

Sheet Project
B2: Invoice details - Projects
B4: Project Name: | D4: Project1 | F4: Project2 | H4: Project3
B5: Project Description: | D5: Project1 | F5: Project2 | H5: Project3 | J5: Definition | K5: Description | L5: Formula/Value
B6: Infra senior supplier: | J6: % Completion Actual YTD (PCA) | K6: Actual % of project total agreed mandays completed during a given period
B7: Bundle: | J7: % Completion Planned YTD (PCP) | K7: Planned % of physical work completed during a given period
B8: Theme: | J8: Earned Value (EV) | K8: Physical work completed during a given period | L8: PCA*BAC
B9: Sponsor: | J9: Actual Cost YTD (AC) | K9: Total costs incurred in completing work during a given period
B10: Infra senior supplier: | J10: Planned Value YTD (PV) | K10: Physical work scheduled for completion during a given period | L10: PCP*BAC
B11: SAMBA nr: | J11: Cost Variance YTD (CV) | K11: Cost overrun during a given period | L11: EV-AC
B12: Start date: | J12: Schedule Variance YTD (SV) | K12: Schedule slipped during a given period | L12: EV-PV
B13: End date: | J13: Cost Performance Index YTD (CPI) | K13: Cost efficiency ratio | L13: EV/AC
B14: Portfolio Category (SAMBA): | J14: Schedule Performance Index YTD (SPI) | K14: Schedule efficiency ratio | L14: EV/PV
B15: Impact: | J15: Estimate to Completion (ETC) | K15: Expected additional cost needed | L15: EAC-AC
B16: Service Group: | J16: Estimate at Completion (EAC) | K16: Expected total cost | L16: BAC/CPI
B17: Service cluster: | J17: Budget at Completion (BAC) | K17: Baseline project cost
B18: Program/project manager: | J18: Variance at Completion (VAC) | K18: Estimated cost overrun at end of project | L18: BAC-EAC
B19: Project Role: | J19: Status Based on AVG. PI | K19: Average of CPI and SPI | L19: (CPI+SPI)/2
B20: PST supplier - TelCo (Y/N):
B21: PST supplier - Vendor Gamma (Y/N): | J21: Status color key: | K21: Value
B22: PST supplier - VendorA (Y/N): | J22: GREEN = On track | K22: ³1.0
B23: PST supplier 2IM (Y/N): | J23: YELLOW = Slightly behind schedule/budget | K23: ³0.85 but <1.0
B24: Costs part of current bill (Y/N): | J24: RED = Needs immediate attention | K24: <0.85
D26: =Period | F26: =Period | H26: =Period
B28: Actual Cost for thePeriod
B29: % Completion Actual YTD | D29: 0.08 | F29: 0.1 | H29: 0.12
B30: % Completion Planned YTD | D30: 0.1 | F30: 0.1 | H30: 0.1
B31: Earned Value YTD | D31: =D29*D40 | F31: =F29*F40 | H31: =H29*H40
B32: Actual Cost YTD | D32: 140 | F32: 170 | H32: 185
B33: Planned Value YTD | D33: =D30*D40 | F33: =F30*F40 | H33: =H30*H40
B34: Cost Variance YTD | D34: =D31-D32 | F34: =F31-F32 | H34: =H31-H32
B35: Schedule Variance YTD | D35: =D31-D33 | F35: =F31-F33 | H35: =H31-H33
B36: Cost Performance Index YTD | D36: =D31/D32 | F36: =F31/F32 | H36: =H31/H32
B37: Schedule Performance Index YTD | D37: =D31/D33 | F37: =F31/F33 | H37: =H31/H33
B38: Estimate to Completion | D38: =D39-D32 | F38: =F39-F32 | H38: =H39-H32
B39: Estimate at Completion | D39: =D40/D36 | F39: =F40/F36 | H39: =H40/H36
B40: Budget at Completion | D40: =1200 | F40: 1500 | H40: 1750
B41: Variance at Completion (VAC) | D41: =D39-D40 | F41: =F39-F40 | H41: =H39-H40
B42: Status based on Average Performance Index | D42: =(D36+D37)/2 | F42: =(F36+F37)/2 | H42: =(H36+H37)/2
B44: No. of FTE Actual - TelCo
B45: No. of FTE Budget - TelCo
B46: FTE Variance - TelCo | D46: =D44-D45 | F46: =F44-F45 | H46: =H44-H45
B47: No. of FTE Actual - Vendor Gamma
B48: No. of FTE Budget - Vendor Gamma
B49: FTE Variance - Vendor Gamma | D49: =D47-D48 | F49: =F47-F48 | H49: =H47-H48
B50: No. of FTE Actual - VendorA
B51: No. of FTE Budget - VendorA
B52: FTE Variance - VendorA | D52: =D50-D51 | F52: =F50-F51 | H52: =H50-H51
B53: No. of FTE Actual - 2IM
B54: No. of FTE Budget - 2IM
B55: FTE Variance - 2IM | D55: =D53-D54 | F55: =F53-F54 | H55: =H53-H54
B57: Comments
B59: Total Project Cost for the Peiod | D59: =D28+F28+H28
B60: Total Project Cost YTD | D60: =D32+F32+H32
B61: Total Project Cost Estimated EOY | D61: =D39+F39+H39

Sheet T&T
B2: Invoice details - Transition & Transformation
B4: 2IM | D4: Period | E4: YTD | F4: Forecast | H4: 2IM | J4: Period | K4: YTD | L4: Forecast
D5: =Period | E5: =Period | F5: EOY | J5: =Period | K5: =Period | L5: EOY
B6: 1. Transition Program Management Stream | H6: 1. From As to Be
B7: 2. Service Management Stream | H7: 2. Business Continuity Planning (BCP) / Disaster Recovery
B8: 3. Unit Operations Stream | H8: 3. ITIL (CAP €996.000)
B9: 4. Communications Stream | H9: 4. Security/SAS70 (CAP €1.000.000)
B10: 5. Finance and Contract Management Stream | H10: Programme Management & Programme Management Office Staffing
B11: 6. People Transfer Stream
B12: 7. Knowledge Transfer Stream
B13: TOTAL | D13: =SUM(D6:D12) | E13: =SUM(E6:E12) | F13: =SUM(F6:F12) | H13: TOTAL | J13: =SUM(J6:J12) | K13: =SUM(K6:K12) | L13: =SUM(L6:L12)
B15: Vendor Alpha | D15: Period | E15: YTD | F15: Forecast | H15: Vendor Alpha | J15: Period | K15: YTD | L15: Forecast
D16: =Period | E16: =Period | F16: EOY | J16: =Period | K16: =Period | L16: EOY
B17: 1. Transition Program Management Stream | H17: 1. From As to Be
B18: 2. Service Management Stream | H18: 2. Self Service Portal
B19: 3. Unit Operations Stream | H19: 2. Implement MOM monitoring framework
B20: 4. Communications Stream | H20: 4. Client Deployment Rework
B21: 5. Finance and Contract Management Stream | H21: 5. Integrate Metadirectory with Neptune services
B22: 6. People Transfer Stream | H22: 6. Introduction of Vista
B23: 7. Knowledge Transfer Stream | H23: 7. User Self Restore
B24: Communication Expenses | H24: 8. Distributed File system
B25: Expenses | H25: Expenses
B26: TOTAL | D26: =SUM(D17:D25) | E26: =SUM(E17:E25) | F26: =SUM(F17:F25) | H26: TOTAL | J26: =SUM(J17:J25) | K26: =SUM(K17:K25) | L26: =SUM(L17:L25)
B28: Vendor Gamma | D28: Period | E28: YTD | F28: Forecast | H28: Vendor Gamma | J28: Period | K28: YTD | L28: Forecast
D29: =Period | E29: =Period | F29: EOY | J29: =Period | K29: =Period | L29: EOY
B30: 0. asset management licences | H30: 1. From As to Be
B31: 1. Transition Program Management Stream | H31: 2. Consolidation and Near Shore Service Desk
B32: 2. Service Management Stream
B33: 3. Unit Operations Stream
B34: 4. Communications Stream
B35: 5. Finance and Contract Management Stream
B36: 6. People Transfer Stream
B37: 7. Knowledge Transfer Stream
B38: TOTAL | D38: =SUM(D30:D37) | E38: =SUM(E30:E37) | F38: =SUM(F30:F37) | H38: TOTAL | J38: =SUM(J30:J37) | K38: =SUM(K30:K37) | L38: =SUM(L30:L37)
B41: TelCo | D41: Period | E41: YTD | F41: Forecast | H41: TelCo | J41: Period | K41: YTD | L41: Forecast
D42: =Period | E42: =Period | F42: EOY | J42: =Period | K42: =Period | L42: EOY
B43: 1. Transition Program Management Stream | H43: 1. From As to Be
B44: 2. Service Management Stream | H44: 2. Voice N-1
B45: 3. Unit Operations Stream | H45: 1. From As to Be
B46: 4. Communications Stream | H46: 1. From As to Be
B47: 5. Finance and Contract Management Stream | H47: 2. Voice N-1
B48: 6. People Transfer Stream | H48: 1. From As to Be
B49: 7. Knowledge Transfer Stream | H49: 2. Voice N-1
B50: TOTAL | D50: =SUM(D43:D49) | E50: =SUM(E43:E49) | F50: =SUM(F43:F49) | H50: TOTAL | J50: =SUM(J43:J49) | K50: =SUM(K43:K49) | L50: =SUM(L43:L49)
B52: Total Transition phase | D52: =D13+D26+D38+D50 | E52: =E13+E26+E38+E50 | F52: =F13+F26+F38+F50 | H52: Total Transformation phase | J52: =J13+J26+J38+J50 | K52: =K13+K26+K38+K50 | L52: =L13+L26+L38+L50

Sheet Serv.level.credit
B2: Invoice details - Service Level Credit | D2: Period: | E2: =Period
B4: Critical service level -category | C4: Allocation of Pool Percentage | D4: Eff + mos** | E4: Minimum | F4: SL Measured | G4: Allocation* | H4: % of Invoice | I4: SL Default (Y/N) | J4: SL credit amount | K4: # of SL Defaults YTD | L4: Average SL YTD
B5: Desktop Services Availability - Performance Category
B6: Desktop Services Performance - Performance Category
B7: Access Services Performance - Performance Category
B8: Voice Services Availability - Performance Category
B9: Service Desk Services Availability - Performance Category
B10: Base Service Desk Services Performance - Performance Category
B11: IMAC Services Performance - Performance Category
B12: Incident Services Performance - Performance Category
B13: Integrator Services - Performance Category
B14: Transition & Transformation Plan
B15: Policies & Procedures Including Security
B16: First set of critical report (CSL Reporting)
... B18: Exit Plan Framework
B19: Total | J19: =SUM(J5:J18) | K19: =SUM(K5:K18) | L19: =SUM(L5:L18)

Sheet Adjustment
D2: Period
B3: Invoice details - Adjustments/Corrections | D3: =Period
B5: Adjustments -Description | D5: Amount
B21: Total

Sheet Variables
A1: _Example
A2: _Shading
A3: _Series
A4: _Look
