Workbook

Sheet Cover Page
C11: EuroBank
C16: ATTACHMENT 4-A
C18: PST PRICING FORMS
C19: Attachment to Exhibit 4 (Pricing and Financial Provisions)

Sheet Summary Fees
A1: TOTAL | B1: Category of Services | C1: Year 1 | D1: Year 2 | E1: Year 3 | F1: Year 4 | G1: Year 5 | H1: Total 5 Yr
A2: BASE CHARGES
B3: EUC | C3: =+C49+C95 | D3: =+D49+D95 | E3: =+E49+E95 | F3: =+F49+F95 | G3: =+G49+G95 | H3: =SUM(C3:G3)
B5: Service Desk | C5: =+C51+C97 | D5: =+D51+D97 | E5: =+E51+E97 | F5: =+F51+F97 | G5: =+G51+G97 | H5: =SUM(C5:G5)
B7: LAN Services | C7: =+C53+C99 | D7: =+D53+D99 | E7: =+E53+E99 | F7: =+F53+F99 | G7: =+G53+G99 | H7: =SUM(C7:G7)
B9: Voice Services | C9: =+C55+C101 | D9: =+D55+D101 | E9: =+E55+E101 | F9: =+F55+F101 | G9: =+G55+G101 | H9: =SUM(C9:G9)
B11: Desktop Hardware | C11: =+C57+C103 | D11: =+D57+D103 | E11: =+E57+E103 | F11: =+F57+F103 | G11: =+G57+G103 | H11: =SUM(C11:G11)
B13: Server Management | C13: =+C59+C105 | D13: =+D59+D105 | E13: =+E59+E105 | F13: =+F59+F105 | G13: =+G59+G105 | H13: =SUM(C13:G13)
B15: 2IM | C15: =+C61+C107 | D15: =+D61+D107 | E15: =+E61+E107 | F15: =+F61+F107 | G15: =+G61+G107 | H15: =SUM(C15:G15)
A17: TOTAL BASE CHARGES | C17: =SUM(C3:C15) | D17: =SUM(D3:D15) | E17: =SUM(E3:E15) | F17: =SUM(F3:F15) | G17: =SUM(G3:G15) | H17: =SUM(C17:G17)
A20: PASS THROUGH COSTS
B21: EUC | C21: =+C67+C113 | D21: =+D67+D113 | E21: =+E67+E113 | F21: =+F67+F113 | G21: =+G67+G113 | H21: =SUM(C21:G21)
B23: Service Desk | C23: =+C69+C115 | D23: =+D69+D115 | E23: =+E69+E115 | F23: =+F69+F115 | G23: =+G69+G115 | H23: =SUM(C23:G23)
B25: LAN Services | C25: =+C71+C117 | D25: =+D71+D117 | E25: =+E71+E117 | F25: =+F71+F117 | G25: =+G71+G117 | H25: =SUM(C25:G25)
B27: Voice Services | C27: =+C73+C119 | D27: =+D73+D119 | E27: =+E73+E119 | F27: =+F73+F119 | G27: =+G73+G119 | H27: =SUM(C27:G27)
B29: Desktop Hardware | C29: =+C75+C121 | D29: =+D75+D121 | E29: =+E75+E121 | F29: =+F75+F121 | G29: =+G75+G121 | H29: =SUM(C29:G29)
B31: Server Management | C31: =+C77+C123 | D31: =+D77+D123 | E31: =+E77+E123 | F31: =+F77+F123 | G31: =+G77+G123 | H31: =SUM(C31:G31)
B33: 2IM | C33: =+C79+C125 | D33: =+D79+D125 | E33: =+E79+E125 | F33: =+F79+F125 | G33: =+G79+G125 | H33: =SUM(C33:G33)
A35: TOTAL PASS THROUGH | C35: =SUM(C21:C33) | D35: =SUM(D21:D33) | E35: =SUM(E21:E33) | F35: =SUM(F21:F33) | G35: =SUM(G21:G33) | H35: =SUM(C35:G35)
A38: ONE-TIME CHARGES
B39: Transition | C39: =+C85+C131 | D39: =+D85+D131 | E39: =+E85+E131 | F39: =+F85+F131 | G39: =+G85+G131 | H39: =SUM(C39:G39)
B40: Transformation | C40: =+C86+C132 | D40: =+D86+D132 | E40: =+E86+E132 | F40: =+F86+F132 | G40: =+G86+G132 | H40: =SUM(C40:G40)
B41: BCP/ Sercurity (fixed) | C41: =+C87+C133 | D41: =+D87+D133 | E41: =+E87+E133 | F41: =+F87+F133 | G41: =+G87+G133 | H41: =SUM(C41:G41)
B42: extra one time charges | C42: =+C88+C134 | D42: =+D88+D134 | E42: =+E88+E134 | F42: =+F88+F134 | G42: =+G88+G134 | H42: =SUM(C42:G42)
A43: TOTAL ONE-TIME CHARGES | C43: =SUM(C39:C42) | D43: =SUM(D39:D42) | E43: =SUM(E39:E42) | F43: =SUM(F39:F42) | G43: =SUM(G39:G42) | H43: =SUM(C43:G43)
A45: GRAND TOTAL FEES | C45: =SUM(C17,C35,C43) | D45: =SUM(D17,D35,D43) | E45: =SUM(E17,E35,E43) | F45: =SUM(F17,F35,F43) | G45: =SUM(G17,G35,G43) | H45: =SUM(H17,H35,H43)
A47: NETHERLANDS | B47: Category of Services | C47: Year 1 | D47: Year 2 | E47: Year 3 | F47: Year 4 | G47: Year 5 | H47: Total 5 Yr
A48: BASE CHARGES
B49: EUC | C49: =+'Detailed Base Charges NL'!B36 | D49: =+'Detailed Base Charges NL'!C36 | E49: =+'Detailed Base Charges NL'!D36 | F49: =+'Detailed Base Charges NL'!E36 | G49: =+'Detailed Base Charges NL'!F36 | H49: =SUM(C49:G49)
B51: Service Desk | C51: =+'Detailed Base Charges NL'!B46 | D51: =+'Detailed Base Charges NL'!C46 | E51: =+'Detailed Base Charges NL'!D46 | F51: =+'Detailed Base Charges NL'!E46 | G51: =+'Detailed Base Charges NL'!F46 | H51: =SUM(C51:G51)
B53: LAN Services | C53: =+'Detailed Base Charges NL'!B53 | D53: =+'Detailed Base Charges NL'!C53 | E53: =+'Detailed Base Charges NL'!D53 | F53: =+'Detailed Base Charges NL'!E53 | G53: =+'Detailed Base Charges NL'!F53 | H53: =SUM(C53:G53)
B55: Voice Services | C55: =+'Detailed Base Charges NL'!B113 | D55: =+'Detailed Base Charges NL'!C113 | E55: =+'Detailed Base Charges NL'!D113 | F55: =+'Detailed Base Charges NL'!E113 | G55: =+'Detailed Base Charges NL'!F113 | H55: =SUM(C55:G55)
B57: Desktop Hardware | C57: =+'Detailed Base Charges NL'!B117 | D57: =+'Detailed Base Charges NL'!C117 | E57: =+'Detailed Base Charges NL'!D117 | F57: =+'Detailed Base Charges NL'!E117 | G57: =+'Detailed Base Charges NL'!F117 | H57: =SUM(C57:G57)
B59: Server Management | C59: =+'Detailed Base Charges NL'!B133 | D59: =+'Detailed Base Charges NL'!C133 | E59: =+'Detailed Base Charges NL'!D133 | F59: =+'Detailed Base Charges NL'!E133 | G59: =+'Detailed Base Charges NL'!F133 | H59: =SUM(C59:G59)
B61: 2IM | C61: =+'Detailed Base Charges NL'!B137 | D61: =+'Detailed Base Charges NL'!C137 | E61: =+'Detailed Base Charges NL'!D137 | F61: =+'Detailed Base Charges NL'!E137 | G61: =+'Detailed Base Charges NL'!F137 | H61: =SUM(C61:G61)
A63: TOTAL BASE CHARGES | C63: =SUM(C49:C61) | D63: =SUM(D49:D61) | E63: =SUM(E49:E61) | F63: =SUM(F49:F61) | G63: =SUM(G49:G61) | H63: =SUM(C63:G63)
A66: PASS THROUGH COSTS
B67: EUC | H67: =SUM(C67:G67)
B69: Service Desk | H69: =SUM(C69:G69)
B71: LAN Services | C71: ='Pass Through overview'!H3 | D71: ='Pass Through overview'!I3 | E71: ='Pass Through overview'!J3 | F71: ='Pass Through overview'!K3 | G71: ='Pass Through overview'!L3 | H71: =SUM(C71:G71)
B73: Voice Services | C73: =SUM('Pass Through overview'!H17:H24) | D73: =SUM('Pass Through overview'!I17:I24) | E73: =SUM('Pass Through overview'!J17:J24) | F73: =SUM('Pass Through overview'!K17:K24) | G73: =SUM('Pass Through overview'!L17:L24) | H73: =SUM(C73:G73)
B75: Desktop Hardware | C75: =SUM('Pass Through overview'!H36:H92) | D75: =SUM('Pass Through overview'!I36:I92) | E75: =SUM('Pass Through overview'!J36:J92) | F75: =SUM('Pass Through overview'!K36:K92) | G75: =SUM('Pass Through overview'!L36:L92) | H75: =SUM(C75:G75)
B77: Server Management | C77: =SUM('Pass Through overview'!H151:H175) | D77: =SUM('Pass Through overview'!I151:I175) | E77: =SUM('Pass Through overview'!J151:J175) | F77: =SUM('Pass Through overview'!K151:K175) | G77: =SUM('Pass Through overview'!L151:L175) | H77: =SUM(C77:G77)
B79: 2IM | C79: 329876 | D79: 67549 | E79: 42218 | F79: 16887 | G79: 0 | H79: =SUM(C79:G79)
A81: TOTAL PASS THROUGH | C81: =SUM(C67:C79) | D81: =SUM(D67:D79) | E81: =SUM(E67:E79) | F81: =SUM(F67:F79) | G81: =SUM(G67:G79) | H81: =SUM(C81:G81)
A84: ONE-TIME CHARGES
B85: Transition | C85: ='One Time Charges'!S245 | D85: ='One Time Charges'!T245 | E85: ='One Time Charges'!U245 | F85: ='One Time Charges'!V245 | H85: =SUM(C85:G85)
B86: Transformation | C86: ='One Time Charges'!S246 | D86: ='One Time Charges'!AF246 | E86: ='One Time Charges'!AS246 | F86: ='One Time Charges'!BF246 | H86: =SUM(C86:G86)
B87: BCP/ Sercurity (fixed) | C87: ='One Time Charges'!S247 | H87: =SUM(C87:G87)
B88: extra one time charges | C88: ='One Time Charges'!AF292 | D88: =+'One Time Charges'!BF292 | H88: =SUM(C88:G88)
A89: TOTAL ONE-TIME CHARGES | C89: =SUM(C85:C88) | D89: =SUM(D85:D88) | E89: =SUM(E85:E88) | F89: =SUM(F85:F88) | G89: =SUM(G85:G88) | H89: =SUM(C89:G89)
A91: GRAND TOTAL FEES | C91: =SUM(C63,C81,C89) | D91: =SUM(D63,D81,D89) | E91: =SUM(E63,E81,E89) | F91: =SUM(F63,F81,F89) | G91: =SUM(G63,G81,G89) | H91: =SUM(H63,H81,H89)
A93: BELGIUM | B93: Category of Services | C93: Year 1 | D93: Year 2 | E93: Year 3 | F93: Year 4 | G93: Year 5 | H93: Total 5 Yr
A94: BASE CHARGES
B95: EUC | C95: =+'Detailed Base Charges BE'!B36 | D95: =+'Detailed Base Charges BE'!C36 | E95: =+'Detailed Base Charges BE'!D36 | F95: =+'Detailed Base Charges BE'!E36 | G95: =+'Detailed Base Charges BE'!F36 | H95: =SUM(C95:G95)
B97: Service Desk | C97: =+'Detailed Base Charges BE'!B46 | D97: =+'Detailed Base Charges BE'!C46 | E97: =+'Detailed Base Charges BE'!D46 | F97: =+'Detailed Base Charges BE'!E46 | G97: =+'Detailed Base Charges BE'!F46 | H97: =SUM(C97:G97)
B99: LAN Services | C99: =+'Detailed Base Charges BE'!B53 | D99: =+'Detailed Base Charges BE'!C53 | E99: =+'Detailed Base Charges BE'!D53 | F99: =+'Detailed Base Charges BE'!E53 | G99: =+'Detailed Base Charges BE'!F53 | H99: =SUM(C99:G99)
B101: Voice Services | C101: =+'Detailed Base Charges BE'!B113 | D101: =+'Detailed Base Charges BE'!C113 | E101: =+'Detailed Base Charges BE'!D113 | F101: =+'Detailed Base Charges BE'!E113 | G101: =+'Detailed Base Charges BE'!F113 | H101: =SUM(C101:G101)
B103: Desktop Hardware | C103: =+'Detailed Base Charges BE'!B117 | D103: =+'Detailed Base Charges BE'!C117 | E103: =+'Detailed Base Charges BE'!D117 | F103: =+'Detailed Base Charges BE'!E117 | G103: =+'Detailed Base Charges BE'!F117 | H103: =SUM(C103:G103)
B105: Server Management | C105: =+'Detailed Base Charges BE'!B133 | D105: =+'Detailed Base Charges BE'!C133 | E105: =+'Detailed Base Charges BE'!D133 | F105: =+'Detailed Base Charges BE'!E133 | G105: =+'Detailed Base Charges BE'!F133 | H105: =SUM(C105:G105)
B107: 2IM | C107: =+'Detailed Base Charges BE'!B137 | D107: =+'Detailed Base Charges BE'!C137 | E107: =+'Detailed Base Charges BE'!D137 | F107: =+'Detailed Base Charges BE'!E137 | G107: =+'Detailed Base Charges BE'!F137 | H107: =SUM(C107:G107)
A109: TOTAL BASE CHARGES | C109: =SUM(C95:C107) | D109: =SUM(D95:D107) | E109: =SUM(E95:E107) | F109: =SUM(F95:F107) | G109: =SUM(G95:G107) | H109: =SUM(C109:G109)
A112: PASS THROUGH COSTS
B113: EUC | H113: =SUM(C113:G113)
B115: Service Desk | H115: =SUM(C115:G115)
B117: LAN Services | C117: ='Pass Through overview'!H13 | D117: ='Pass Through overview'!I13 | E117: ='Pass Through overview'!J13 | F117: ='Pass Through overview'!K13 | G117: ='Pass Through overview'!L13 | H117: =SUM(C117:G117)
B119: Voice Services | C119: =SUM('Pass Through overview'!H27:H34) | D119: =SUM('Pass Through overview'!I27:I34) | E119: =SUM('Pass Through overview'!J27:J34) | F119: =SUM('Pass Through overview'!K27:K34) | G119: =SUM('Pass Through overview'!L27:L34) | H119: =SUM(C119:G119)
B121: Desktop Hardware | C121: =SUM('Pass Through overview'!H93:H149) | D121: =SUM('Pass Through overview'!I93:I149) | E121: =SUM('Pass Through overview'!J93:J149) | F121: =SUM('Pass Through overview'!K93:K149) | G121: =SUM('Pass Through overview'!L93:L149) | H121: =SUM(C121:G121)
B123: Server Management | C123: =SUM('Pass Through overview'!H176:H201) | D123: =SUM('Pass Through overview'!I176:I201) | E123: =SUM('Pass Through overview'!J176:J201) | F123: =SUM('Pass Through overview'!K176:K201) | G123: =SUM('Pass Through overview'!L176:L201) | H123: =SUM(C123:G123)
B125: 2IM | H125: =SUM(C125:G125)
A127: TOTAL PASS THROUGH | C127: =SUM(C113:C125) | D127: =SUM(D113:D125) | E127: =SUM(E113:E125) | F127: =SUM(F113:F125) | G127: =SUM(G113:G125) | H127: =SUM(C127:G127)
A130: ONE-TIME CHARGES
B131: Transition | C131: ='One Time Charges'!S250 | D131: ='One Time Charges'!T250 | E131: ='One Time Charges'!U250 | F131: ='One Time Charges'!V250 | H131: =SUM(C131:G131)
B132: Transformation | C132: ='One Time Charges'!S251 | D132: ='One Time Charges'!AF251 | E132: ='One Time Charges'!AS251 | F132: ='One Time Charges'!BF251 | H132: =SUM(C132:G132)
B133: BCP/ Sercurity (fixed) | C133: ='One Time Charges'!S252 | H133: =SUM(C133:G133)
B134: extra one time charges | C134: ='One Time Charges'!AS292 | D134: =+'One Time Charges'!BG292 | H134: =SUM(C134:G134)
A136: TOTAL ONE-TIME CHARGES | C136: =SUM(C131:C134) | D136: =SUM(D131:D134) | E136: =SUM(E131:E134) | F136: =SUM(F131:F134) | G136: =SUM(G131:G134) | H136: =SUM(C136:G136)
A138: GRAND TOTAL FEES | C138: =SUM(C109,C127,C136) | D138: =SUM(D109,D127,D136) | E138: =SUM(E109,E127,E136) | F138: =SUM(F109,F127,F136) | G138: =SUM(G109,G127,G136) | H138: =SUM(H109,H127,H136)
A141: The Pricing for Year 6 and 7 will be based on the Pricing of Year 5, subject to indexation calculated as the movement in the relevant COLA index during Contract Year 5, and further subject always to the Mincing and Benchmark Procedure set out in Exhibit 34. In addition, an adjustment will be made to reflect the actual refresh volumes and activities or otherwise the refresh volumes and activities from Year 3 and Year 4 will be applied to Year 6 and Year 7 respectively. This agreement shall apply throughout Exhibit 4 and attachments of Exhibit 4.

Sheet Detailed Base Charges Total
A1: Detailed Base Charges - Total | B1: Year 1 | C1: Year 2 | D1: Year 3 | E1: Year 4 | F1: Year 5 | G1: Total 5 Yr
A2: EUC
A3: Support Services
A4: Medium Service Level
A5: Standard Desktops (CEDS) | B5: =+'Detailed Base Charges NL'!B5+'Detailed Base Charges BE'!B5 | C5: =+'Detailed Base Charges NL'!C5+'Detailed Base Charges BE'!C5 | D5: =+'Detailed Base Charges NL'!D5+'Detailed Base Charges BE'!D5 | E5: =+'Detailed Base Charges NL'!E5+'Detailed Base Charges BE'!E5 | F5: =+'Detailed Base Charges NL'!F5+'Detailed Base Charges BE'!F5 | G5: =SUM(B5:F5)
A6: Non-Standard Desktops (non CEDS) | B6: =+'Detailed Base Charges NL'!B6+'Detailed Base Charges BE'!B6 | C6: =+'Detailed Base Charges NL'!C6+'Detailed Base Charges BE'!C6 | D6: =+'Detailed Base Charges NL'!D6+'Detailed Base Charges BE'!D6 | E6: =+'Detailed Base Charges NL'!E6+'Detailed Base Charges BE'!E6 | F6: =+'Detailed Base Charges NL'!F6+'Detailed Base Charges BE'!F6 | G6: =SUM(B6:F6)
A7: Standard Laptops (CEDS) | B7: =+'Detailed Base Charges NL'!B7+'Detailed Base Charges BE'!B7 | C7: =+'Detailed Base Charges NL'!C7+'Detailed Base Charges BE'!C7 | D7: =+'Detailed Base Charges NL'!D7+'Detailed Base Charges BE'!D7 | E7: =+'Detailed Base Charges NL'!E7+'Detailed Base Charges BE'!E7 | F7: =+'Detailed Base Charges NL'!F7+'Detailed Base Charges BE'!F7 | G7: =SUM(B7:F7)
A8: Non-Standard Laptops (non CEDS) | B8: =+'Detailed Base Charges NL'!B8+'Detailed Base Charges BE'!B8 | C8: =+'Detailed Base Charges NL'!C8+'Detailed Base Charges BE'!C8 | D8: =+'Detailed Base Charges NL'!D8+'Detailed Base Charges BE'!D8 | E8: =+'Detailed Base Charges NL'!E8+'Detailed Base Charges BE'!E8 | F8: =+'Detailed Base Charges NL'!F8+'Detailed Base Charges BE'!F8 | G8: =SUM(B8:F8)
A9: Standard Local Printers | B9: =+'Detailed Base Charges NL'!B9+'Detailed Base Charges BE'!B9 | C9: =+'Detailed Base Charges NL'!C9+'Detailed Base Charges BE'!C9 | D9: =+'Detailed Base Charges NL'!D9+'Detailed Base Charges BE'!D9 | E9: =+'Detailed Base Charges NL'!E9+'Detailed Base Charges BE'!E9 | F9: =+'Detailed Base Charges NL'!F9+'Detailed Base Charges BE'!F9 | G9: =SUM(B9:F9)
A10: Non-Standard Local Printers | B10: =+'Detailed Base Charges NL'!B10+'Detailed Base Charges BE'!B10 | C10: =+'Detailed Base Charges NL'!C10+'Detailed Base Charges BE'!C10 | D10: =+'Detailed Base Charges NL'!D10+'Detailed Base Charges BE'!D10 | E10: =+'Detailed Base Charges NL'!E10+'Detailed Base Charges BE'!E10 | F10: =+'Detailed Base Charges NL'!F10+'Detailed Base Charges BE'!F10 | G10: =SUM(B10:F10)
A11: Standard Network Printers | B11: =+'Detailed Base Charges NL'!B11+'Detailed Base Charges BE'!B11 | C11: =+'Detailed Base Charges NL'!C11+'Detailed Base Charges BE'!C11 | D11: =+'Detailed Base Charges NL'!D11+'Detailed Base Charges BE'!D11 | E11: =+'Detailed Base Charges NL'!E11+'Detailed Base Charges BE'!E11 | F11: =+'Detailed Base Charges NL'!F11+'Detailed Base Charges BE'!F11 | G11: =SUM(B11:F11)
A12: Non-Standard Network Printers | B12: =+'Detailed Base Charges NL'!B12+'Detailed Base Charges BE'!B12 | C12: =+'Detailed Base Charges NL'!C12+'Detailed Base Charges BE'!C12 | D12: =+'Detailed Base Charges NL'!D12+'Detailed Base Charges BE'!D12 | E12: =+'Detailed Base Charges NL'!E12+'Detailed Base Charges BE'!E12 | F12: =+'Detailed Base Charges NL'!F12+'Detailed Base Charges BE'!F12 | G12: =SUM(B12:F12)
A13: Other Peripherals | B13: =+'Detailed Base Charges NL'!B13+'Detailed Base Charges BE'!B13 | C13: =+'Detailed Base Charges NL'!C13+'Detailed Base Charges BE'!C13 | D13: =+'Detailed Base Charges NL'!D13+'Detailed Base Charges BE'!D13 | E13: =+'Detailed Base Charges NL'!E13+'Detailed Base Charges BE'!E13 | F13: =+'Detailed Base Charges NL'!F13+'Detailed Base Charges BE'!F13 | G13: =SUM(B13:F13)
A14: Dealing room support | B14: =+'Detailed Base Charges NL'!B14+'Detailed Base Charges BE'!B14 | C14: =+'Detailed Base Charges NL'!C14+'Detailed Base Charges BE'!C14 | D14: =+'Detailed Base Charges NL'!D14+'Detailed Base Charges BE'!D14 | E14: =+'Detailed Base Charges NL'!E14+'Detailed Base Charges BE'!E14 | F14: =+'Detailed Base Charges NL'!F14+'Detailed Base Charges BE'!F14 | G14: =SUM(B14:F14)
A15: Installations | B15: =+'Detailed Base Charges NL'!B15+'Detailed Base Charges BE'!B15 | C15: =+'Detailed Base Charges NL'!C15+'Detailed Base Charges BE'!C15 | D15: =+'Detailed Base Charges NL'!D15+'Detailed Base Charges BE'!D15 | E15: =+'Detailed Base Charges NL'!E15+'Detailed Base Charges BE'!E15 | F15: =+'Detailed Base Charges NL'!F15+'Detailed Base Charges BE'!F15 | G15: =SUM(B15:F15)
A16: Moves | B16: =+'Detailed Base Charges NL'!B16+'Detailed Base Charges BE'!B16 | C16: =+'Detailed Base Charges NL'!C16+'Detailed Base Charges BE'!C16 | D16: =+'Detailed Base Charges NL'!D16+'Detailed Base Charges BE'!D16 | E16: =+'Detailed Base Charges NL'!E16+'Detailed Base Charges BE'!E16 | F16: =+'Detailed Base Charges NL'!F16+'Detailed Base Charges BE'!F16 | G16: =SUM(B16:F16)
... A18: Changes | B18: =+'Detailed Base Charges NL'!B18+'Detailed Base Charges BE'!B18 | C18: =+'Detailed Base Charges NL'!C18+'Detailed Base Charges BE'!C18 | D18: =+'Detailed Base Charges NL'!D18+'Detailed Base Charges BE'!D18 | E18: =+'Detailed Base Charges NL'!E18+'Detailed Base Charges BE'!E18 | F18: =+'Detailed Base Charges NL'!F18+'Detailed Base Charges BE'!F18 | G18: =SUM(B18:F18)
A19: Low Service Level
A20: Standard Desktops | B20: =+'Detailed Base Charges NL'!B20+'Detailed Base Charges BE'!B20 | C20: =+'Detailed Base Charges NL'!C20+'Detailed Base Charges BE'!C20 | D20: =+'Detailed Base Charges NL'!D20+'Detailed Base Charges BE'!D20 | E20: =+'Detailed Base Charges NL'!E20+'Detailed Base Charges BE'!E20 | F20: =+'Detailed Base Charges NL'!F20+'Detailed Base Charges BE'!F20 | G20: =SUM(B20:F20)
A21: Non-Standard Desktops | B21: =+'Detailed Base Charges NL'!B21+'Detailed Base Charges BE'!B21 | C21: =+'Detailed Base Charges NL'!C21+'Detailed Base Charges BE'!C21 | D21: =+'Detailed Base Charges NL'!D21+'Detailed Base Charges BE'!D21 | E21: =+'Detailed Base Charges NL'!E21+'Detailed Base Charges BE'!E21 | F21: =+'Detailed Base Charges NL'!F21+'Detailed Base Charges BE'!F21 | G21: =SUM(B21:F21)
A22: Standard Laptops | B22: =+'Detailed Base Charges NL'!B22+'Detailed Base Charges BE'!B22 | C22: =+'Detailed Base Charges NL'!C22+'Detailed Base Charges BE'!C22 | D22: =+'Detailed Base Charges NL'!D22+'Detailed Base Charges BE'!D22 | E22: =+'Detailed Base Charges NL'!E22+'Detailed Base Charges BE'!E22 | F22: =+'Detailed Base Charges NL'!F22+'Detailed Base Charges BE'!F22 | G22: =SUM(B22:F22)
A23: Non-Standard Laptops | B23: =+'Detailed Base Charges NL'!B23+'Detailed Base Charges BE'!B23 | C23: =+'Detailed Base Charges NL'!C23+'Detailed Base Charges BE'!C23 | D23: =+'Detailed Base Charges NL'!D23+'Detailed Base Charges BE'!D23 | E23: =+'Detailed Base Charges NL'!E23+'Detailed Base Charges BE'!E23 | F23: =+'Detailed Base Charges NL'!F23+'Detailed Base Charges BE'!F23 | G23: =SUM(B23:F23)
A24: Standard Local Printers | B24: =+'Detailed Base Charges NL'!B24+'Detailed Base Charges BE'!B24 | C24: =+'Detailed Base Charges NL'!C24+'Detailed Base Charges BE'!C24 | D24: =+'Detailed Base Charges NL'!D24+'Detailed Base Charges BE'!D24 | E24: =+'Detailed Base Charges NL'!E24+'Detailed Base Charges BE'!E24 | F24: =+'Detailed Base Charges NL'!F24+'Detailed Base Charges BE'!F24 | G24: =SUM(B24:F24)
A25: Non-Standard Local Printers | B25: =+'Detailed Base Charges NL'!B25+'Detailed Base Charges BE'!B25 | C25: =+'Detailed Base Charges NL'!C25+'Detailed Base Charges BE'!C25 | D25: =+'Detailed Base Charges NL'!D25+'Detailed Base Charges BE'!D25 | E25: =+'Detailed Base Charges NL'!E25+'Detailed Base Charges BE'!E25 | F25: =+'Detailed Base Charges NL'!F25+'Detailed Base Charges BE'!F25 | G25: =SUM(B25:F25)
A26: Standard Network Printers | B26: =+'Detailed Base Charges NL'!B26+'Detailed Base Charges BE'!B26 | C26: =+'Detailed Base Charges NL'!C26+'Detailed Base Charges BE'!C26 | D26: =+'Detailed Base Charges NL'!D26+'Detailed Base Charges BE'!D26 | E26: =+'Detailed Base Charges NL'!E26+'Detailed Base Charges BE'!E26 | F26: =+'Detailed Base Charges NL'!F26+'Detailed Base Charges BE'!F26 | G26: =SUM(B26:F26)
A27: Non-Standard Network Printers | B27: =+'Detailed Base Charges NL'!B27+'Detailed Base Charges BE'!B27 | C27: =+'Detailed Base Charges NL'!C27+'Detailed Base Charges BE'!C27 | D27: =+'Detailed Base Charges NL'!D27+'Detailed Base Charges BE'!D27 | E27: =+'Detailed Base Charges NL'!E27+'Detailed Base Charges BE'!E27 | F27: =+'Detailed Base Charges NL'!F27+'Detailed Base Charges BE'!F27 | G27: =SUM(B27:F27)
A28: Other Peripherals | B28: =+'Detailed Base Charges NL'!B28+'Detailed Base Charges BE'!B28 | C28: =+'Detailed Base Charges NL'!C28+'Detailed Base Charges BE'!C28 | D28: =+'Detailed Base Charges NL'!D28+'Detailed Base Charges BE'!D28 | E28: =+'Detailed Base Charges NL'!E28+'Detailed Base Charges BE'!E28 | F28: =+'Detailed Base Charges NL'!F28+'Detailed Base Charges BE'!F28 | G28: =SUM(B28:F28)
A29: UAS POOL & Secondment of 5 FTE | B29: =+'Detailed Base Charges NL'!B29+'Detailed Base Charges BE'!B29 | C29: =+'Detailed Base Charges NL'!C29+'Detailed Base Charges BE'!C29 | D29: =+'Detailed Base Charges NL'!D29+'Detailed Base Charges BE'!D29 | E29: =+'Detailed Base Charges NL'!E29+'Detailed Base Charges BE'!E29 | F29: =+'Detailed Base Charges NL'!F29+'Detailed Base Charges BE'!F29 | G29: =SUM(B29:F29)
A30: Installations | B30: =+'Detailed Base Charges NL'!B30+'Detailed Base Charges BE'!B30 | C30: =+'Detailed Base Charges NL'!C30+'Detailed Base Charges BE'!C30 | D30: =+'Detailed Base Charges NL'!D30+'Detailed Base Charges BE'!D30 | E30: =+'Detailed Base Charges NL'!E30+'Detailed Base Charges BE'!E30 | F30: =+'Detailed Base Charges NL'!F30+'Detailed Base Charges BE'!F30 | G30: =SUM(B30:F30)
A31: Moves | B31: =+'Detailed Base Charges NL'!B31+'Detailed Base Charges BE'!B31 | C31: =+'Detailed Base Charges NL'!C31+'Detailed Base Charges BE'!C31 | D31: =+'Detailed Base Charges NL'!D31+'Detailed Base Charges BE'!D31 | E31: =+'Detailed Base Charges NL'!E31+'Detailed Base Charges BE'!E31 | F31: =+'Detailed Base Charges NL'!F31+'Detailed Base Charges BE'!F31 | G31: =SUM(B31:F31)
... A33: Changes | B33: =+'Detailed Base Charges NL'!B33+'Detailed Base Charges BE'!B33 | C33: =+'Detailed Base Charges NL'!C33+'Detailed Base Charges BE'!C33 | D33: =+'Detailed Base Charges NL'!D33+'Detailed Base Charges BE'!D33 | E33: =+'Detailed Base Charges NL'!E33+'Detailed Base Charges BE'!E33 | F33: =+'Detailed Base Charges NL'!F33+'Detailed Base Charges BE'!F33 | G33: =SUM(B33:F33)
A34: Packaging & Distribution | B34: =+'Detailed Base Charges NL'!B34+'Detailed Base Charges BE'!B34 | C34: =+'Detailed Base Charges NL'!C34+'Detailed Base Charges BE'!C34 | G34: =SUM(B34:F34) | H34: Row used for PST reimbursement for use of EuroBank facilities
A35: Packages Distributed per year | B35: =+'Detailed Base Charges NL'!B35+'Detailed Base Charges BE'!B35 | C35: =+'Detailed Base Charges NL'!C35+'Detailed Base Charges BE'!C35 | D35: =+'Detailed Base Charges NL'!D35+'Detailed Base Charges BE'!D35 | E35: =+'Detailed Base Charges NL'!E35+'Detailed Base Charges BE'!E35 | F35: =+'Detailed Base Charges NL'!F35+'Detailed Base Charges BE'!F35 | G35: =SUM(B35:F35)
A36: TOTAL EUC | B36: =SUM(B5:B35) | C36: =SUM(C5:C35) | D36: =SUM(D5:D35) | E36: =SUM(E5:E35) | F36: =SUM(F5:F35) | G36: =SUM(B36:F36)
A37: Service Desk
A38: Seats | B38: =+'Detailed Base Charges NL'!B38+'Detailed Base Charges BE'!B38 | C38: =+'Detailed Base Charges NL'!C38+'Detailed Base Charges BE'!C38 | D38: =+'Detailed Base Charges NL'!D38+'Detailed Base Charges BE'!D38 | E38: =+'Detailed Base Charges NL'!E38+'Detailed Base Charges BE'!E38 | F38: =+'Detailed Base Charges NL'!F38+'Detailed Base Charges BE'!F38 | G38: =SUM(B38:F38)
G39: =SUM(B39:F39)
G40: =SUM(B40:F40)
G41: =SUM(B41:F41)
G42: =SUM(B42:F42)
G43: =SUM(B43:F43)
G44: =SUM(B44:F44)
B45: =+'Detailed Base Charges NL'!B45+'Detailed Base Charges BE'!B45 | C45: =+'Detailed Base Charges NL'!C45+'Detailed Base Charges BE'!C45 | G45: =SUM(B45:F45) | H45: Row used for PST reimbursement for use of EuroBank facilities
A46: TOTAL SERVICE DESK (seats supported) | B46: =SUM(B38:B45) | C46: =SUM(C38:C45) | D46: =SUM(D38:D45) | E46: =SUM(E38:E45) | F46: =SUM(F38:F45) | G46: =SUM(B46:F46)
A47: LAN Services
A48: Support Services
A49: Monitoring LAN port IT, SP, ... | B49: =+'Detailed Base Charges NL'!B49+'Detailed Base Charges BE'!B49 | C49: =+'Detailed Base Charges NL'!C49+'Detailed Base Charges BE'!C49 | D49: =+'Detailed Base Charges NL'!D49+'Detailed Base Charges BE'!D49 | E49: =+'Detailed Base Charges NL'!E49+'Detailed Base Charges BE'!E49 | F49: =+'Detailed Base Charges NL'!F49+'Detailed Base Charges BE'!F49 | G49: =SUM(B49:F49)
A50: Site Type A: # of Active LAN Ports | B50: =+'Detailed Base Charges NL'!B50+'Detailed Base Charges BE'!B50 | C50: =+'Detailed Base Charges NL'!C50+'Detailed Base Charges BE'!C50 | D50: =+'Detailed Base Charges NL'!D50+'Detailed Base Charges BE'!D50 | E50: =+'Detailed Base Charges NL'!E50+'Detailed Base Charges BE'!E50 | F50: =+'Detailed Base Charges NL'!F50+'Detailed Base Charges BE'!F50 | G50: =SUM(B50:F50)
A51: Site Type B: # of Active LAN Ports | B51: =+'Detailed Base Charges NL'!B51+'Detailed Base Charges BE'!B51 | C51: =+'Detailed Base Charges NL'!C51+'Detailed Base Charges BE'!C51 | D51: =+'Detailed Base Charges NL'!D51+'Detailed Base Charges BE'!D51 | E51: =+'Detailed Base Charges NL'!E51+'Detailed Base Charges BE'!E51 | F51: =+'Detailed Base Charges NL'!F51+'Detailed Base Charges BE'!F51 | G51: =SUM(B51:F51)
A52: Site Type C: # of Active LAN Ports | B52: =+'Detailed Base Charges NL'!B52+'Detailed Base Charges BE'!B52 | C52: =+'Detailed Base Charges NL'!C52+'Detailed Base Charges BE'!C52 | D52: =+'Detailed Base Charges NL'!D52+'Detailed Base Charges BE'!D52 | E52: =+'Detailed Base Charges NL'!E52+'Detailed Base Charges BE'!E52 | F52: =+'Detailed Base Charges NL'!F52+'Detailed Base Charges BE'!F52 | G52: =SUM(B52:F52)
A53: TOTAL LAN SERVICES | B53: =SUM(B47:B52) | C53: =SUM(C47:C52) | D53: =SUM(D47:D52) | E53: =SUM(E47:E52) | F53: =SUM(F47:F52) | G53: =SUM(B53:F53)
A54: Voice Services
A55: Locations (Systems & Services)
A56: Call Centres | B56: =+'Detailed Base Charges NL'!B56+'Detailed Base Charges BE'!B56 | C56: =+'Detailed Base Charges NL'!C56+'Detailed Base Charges BE'!C56 | D56: =+'Detailed Base Charges NL'!D56+'Detailed Base Charges BE'!D56 | E56: =+'Detailed Base Charges NL'!E56+'Detailed Base Charges BE'!E56 | F56: =+'Detailed Base Charges NL'!F56+'Detailed Base Charges BE'!F56 | G56: =SUM(B56:F56)
A57: Employee ISDN | B57: =+'Detailed Base Charges NL'!B57+'Detailed Base Charges BE'!B57 | C57: =+'Detailed Base Charges NL'!C57+'Detailed Base Charges BE'!C57 | D57: =+'Detailed Base Charges NL'!D57+'Detailed Base Charges BE'!D57 | E57: =+'Detailed Base Charges NL'!E57+'Detailed Base Charges BE'!E57 | F57: =+'Detailed Base Charges NL'!F57+'Detailed Base Charges BE'!F57 | G57: =SUM(B57:F57)
A58: Dealing room | B58: =+'Detailed Base Charges NL'!B58+'Detailed Base Charges BE'!B58 | C58: =+'Detailed Base Charges NL'!C58+'Detailed Base Charges BE'!C58 | D58: =+'Detailed Base Charges NL'!D58+'Detailed Base Charges BE'!D58 | E58: =+'Detailed Base Charges NL'!E58+'Detailed Base Charges BE'!E58 | F58: =+'Detailed Base Charges NL'!F58+'Detailed Base Charges BE'!F58 | G58: =SUM(B58:F58)
A59: Video conferencing | B59: =+'Detailed Base Charges NL'!B59+'Detailed Base Charges BE'!B59 | C59: =+'Detailed Base Charges NL'!C59+'Detailed Base Charges BE'!C59 | D59: =+'Detailed Base Charges NL'!D59+'Detailed Base Charges BE'!D59 | E59: =+'Detailed Base Charges NL'!E59+'Detailed Base Charges BE'!E59 | F59: =+'Detailed Base Charges NL'!F59+'Detailed Base Charges BE'!F59 | G59: =SUM(B59:F59)
A60: Assets Call Center | B60: =+'Detailed Base Charges NL'!B60+'Detailed Base Charges BE'!B60 | C60: =+'Detailed Base Charges NL'!C60+'Detailed Base Charges BE'!C60 | D60: =+'Detailed Base Charges NL'!D60+'Detailed Base Charges BE'!D60 | E60: =+'Detailed Base Charges NL'!E60+'Detailed Base Charges BE'!E60 | F60: =+'Detailed Base Charges NL'!F60+'Detailed Base Charges BE'!F60 | G60: =SUM(B60:F60) | H60: Charges for PBX's: Small, Medium, and Large per Attachment 4-D are included in the Handsets
A61: Assets Digital Voice Fixed | B61: =+'Detailed Base Charges NL'!B61+'Detailed Base Charges BE'!B61 | C61: =+'Detailed Base Charges NL'!C61+'Detailed Base Charges BE'!C61 | D61: =+'Detailed Base Charges NL'!D61+'Detailed Base Charges BE'!D61 | E61: =+'Detailed Base Charges NL'!E61+'Detailed Base Charges BE'!E61 | F61: =+'Detailed Base Charges NL'!F61+'Detailed Base Charges BE'!F61 | G61: =SUM(B61:F61) | H61: Charges for PBX's: Small, Medium, and Large per Attachment 4-D are included in the Handsets
A62: Assets Analogue Voice Fixed | B62: =+'Detailed Base Charges NL'!B62+'Detailed Base Charges BE'!B62 | C62: =+'Detailed Base Charges NL'!C62+'Detailed Base Charges BE'!C62 | D62: =+'Detailed Base Charges NL'!D62+'Detailed Base Charges BE'!D62 | E62: =+'Detailed Base Charges NL'!E62+'Detailed Base Charges BE'!E62 | F62: =+'Detailed Base Charges NL'!F62+'Detailed Base Charges BE'!F62 | G62: =SUM(B62:F62) | H62: Charges for PBX's: Small, Medium, and Large per Attachment 4-D are included in the Handsets
A63: Handsets - Digital (incl. DECT) | B63: =+'Detailed Base Charges NL'!B63+'Detailed Base Charges BE'!B63 | C63: =+'Detailed Base Charges NL'!C63+'Detailed Base Charges BE'!C63 | D63: =+'Detailed Base Charges NL'!D63+'Detailed Base Charges BE'!D63 | E63: =+'Detailed Base Charges NL'!E63+'Detailed Base Charges BE'!E63 | F63: =+'Detailed Base Charges NL'!F63+'Detailed Base Charges BE'!F63 | G63: =SUM(B63:F63)
A64: Handsets - Analog | B64: =+'Detailed Base Charges NL'!B64+'Detailed Base Charges BE'!B64 | C64: =+'Detailed Base Charges NL'!C64+'Detailed Base Charges BE'!C64 | D64: =+'Detailed Base Charges NL'!D64+'Detailed Base Charges BE'!D64 | E64: =+'Detailed Base Charges NL'!E64+'Detailed Base Charges BE'!E64 | F64: =+'Detailed Base Charges NL'!F64+'Detailed Base Charges BE'!F64 | G64: =SUM(B64:F64)
A65: Cellular Phones management fee | B65: =+'Detailed Base Charges NL'!B65+'Detailed Base Charges BE'!B65 | C65: =+'Detailed Base Charges NL'!C65+'Detailed Base Charges BE'!C65 | D65: =+'Detailed Base Charges NL'!D65+'Detailed Base Charges BE'!D65 | E65: =+'Detailed Base Charges NL'!E65+'Detailed Base Charges BE'!E65 | F65: =+'Detailed Base Charges NL'!F65+'Detailed Base Charges BE'!F65 | G65: =SUM(B65:F65)
A66: Cellular Phones subscription | B66: =+'Detailed Base Charges NL'!B66+'Detailed Base Charges BE'!B66 | C66: =+'Detailed Base Charges NL'!C66+'Detailed Base Charges BE'!C66 | D66: =+'Detailed Base Charges NL'!D66+'Detailed Base Charges BE'!D66 | E66: =+'Detailed Base Charges NL'!E66+'Detailed Base Charges BE'!E66 | F66: =+'Detailed Base Charges NL'!F66+'Detailed Base Charges BE'!F66 | G66: =SUM(B66:F66)
A67: Cellular Phones refresh (budget) | B67: =+'Detailed Base Charges NL'!B67+'Detailed Base Charges BE'!B67 | C67: =+'Detailed Base Charges NL'!C67+'Detailed Base Charges BE'!C67 | D67: =+'Detailed Base Charges NL'!D67+'Detailed Base Charges BE'!D67 | E67: =+'Detailed Base Charges NL'!E67+'Detailed Base Charges BE'!E67 | F67: =+'Detailed Base Charges NL'!F67+'Detailed Base Charges BE'!F67 | G67: =SUM(B67:F67)
A68: GPRS/UMTS Cards or Devices management fee | B68: =+'Detailed Base Charges NL'!B68+'Detailed Base Charges BE'!B68 | C68: =+'Detailed Base Charges NL'!C68+'Detailed Base Charges BE'!C68 | D68: =+'Detailed Base Charges NL'!D68+'Detailed Base Charges BE'!D68 | E68: =+'Detailed Base Charges NL'!E68+'Detailed Base Charges BE'!E68 | F68: =+'Detailed Base Charges NL'!F68+'Detailed Base Charges BE'!F68 | G68: =SUM(B68:F68)
A69: GPRS/UMTS Cards or Devices subscription | B69: =+'Detailed Base Charges NL'!B69+'Detailed Base Charges BE'!B69 | C69: =+'Detailed Base Charges NL'!C69+'Detailed Base Charges BE'!C69 | D69: =+'Detailed Base Charges NL'!D69+'Detailed Base Charges BE'!D69 | E69: =+'Detailed Base Charges NL'!E69+'Detailed Base Charges BE'!E69 | F69: =+'Detailed Base Charges NL'!F69+'Detailed Base Charges BE'!F69 | G69: =SUM(B69:F69)
A70: GPRS/UMTS Cards or Devices refresh (budget) | B70: =+'Detailed Base Charges NL'!B70+'Detailed Base Charges BE'!B70 | C70: =+'Detailed Base Charges NL'!C70+'Detailed Base Charges BE'!C70 | D70: =+'Detailed Base Charges NL'!D70+'Detailed Base Charges BE'!D70 | E70: =+'Detailed Base Charges NL'!E70+'Detailed Base Charges BE'!E70 | F70: =+'Detailed Base Charges NL'!F70+'Detailed Base Charges BE'!F70 | G70: =SUM(B70:F70)
A71: Blackberries management fee | B71: =+'Detailed Base Charges NL'!B71+'Detailed Base Charges BE'!B71 | C71: =+'Detailed Base Charges NL'!C71+'Detailed Base Charges BE'!C71 | D71: =+'Detailed Base Charges NL'!D71+'Detailed Base Charges BE'!D71 | E71: =+'Detailed Base Charges NL'!E71+'Detailed Base Charges BE'!E71 | F71: =+'Detailed Base Charges NL'!F71+'Detailed Base Charges BE'!F71 | G71: =SUM(B71:F71)
A72: Blackberries subscription (data) | B72: =+'Detailed Base Charges NL'!B72+'Detailed Base Charges BE'!B72 | C72: =+'Detailed Base Charges NL'!C72+'Detailed Base Charges BE'!C72 | D72: =+'Detailed Base Charges NL'!D72+'Detailed Base Charges BE'!D72 | E72: =+'Detailed Base Charges NL'!E72+'Detailed Base Charges BE'!E72 | F72: =+'Detailed Base Charges NL'!F72+'Detailed Base Charges BE'!F72 | G72: =SUM(B72:F72)
A73: Blackberries refresh incl CAL licence (budget) | B73: =+'Detailed Base Charges NL'!B73+'Detailed Base Charges BE'!B73 | C73: =+'Detailed Base Charges NL'!C73+'Detailed Base Charges BE'!C73 | D73: =+'Detailed Base Charges NL'!D73+'Detailed Base Charges BE'!D73 | E73: =+'Detailed Base Charges NL'!E73+'Detailed Base Charges BE'!E73 | F73: =+'Detailed Base Charges NL'!F73+'Detailed Base Charges BE'!F73 | G73: =SUM(B73:F73)
A74: Internal Pagers management fee | B74: =+'Detailed Base Charges NL'!B74+'Detailed Base Charges BE'!B74 | C74: =+'Detailed Base Charges NL'!C74+'Detailed Base Charges BE'!C74 | D74: =+'Detailed Base Charges NL'!D74+'Detailed Base Charges BE'!D74 | E74: =+'Detailed Base Charges NL'!E74+'Detailed Base Charges BE'!E74 | F74: =+'Detailed Base Charges NL'!F74+'Detailed Base Charges BE'!F74 | G74: =SUM(B74:F74)
... A77: External Pagers refresh (budget) | B77: =+'Detailed Base Charges NL'!B77+'Detailed Base Charges BE'!B77 | C77: =+'Detailed Base Charges NL'!C77+'Detailed Base Charges BE'!C77 | D77: =+'Detailed Base Charges NL'!D77+'Detailed Base Charges BE'!D77 | E77: =+'Detailed Base Charges NL'!E77+'Detailed Base Charges BE'!E77 | F77: =+'Detailed Base Charges NL'!F77+'Detailed Base Charges BE'!F77 | G77: =SUM(B77:F77)
A79: VOICE
A80: Domestic Outbound Calls - Local | B80: =+'Detailed Base Charges NL'!B80+'Detailed Base Charges BE'!B80 | C80: =+'Detailed Base Charges NL'!C80+'Detailed Base Charges BE'!C80 | D80: =+'Detailed Base Charges NL'!D80+'Detailed Base Charges BE'!D80 | E80: =+'Detailed Base Charges NL'!E80+'Detailed Base Charges BE'!E80 | F80: =+'Detailed Base Charges NL'!F80+'Detailed Base Charges BE'!F80 | G80: =SUM(B80:F80)
A81: Domestic Outbound Calls - Long Distance | B81: =+'Detailed Base Charges NL'!B81+'Detailed Base Charges BE'!B81 | C81: =+'Detailed Base Charges NL'!C81+'Detailed Base Charges BE'!C81 | D81: =+'Detailed Base Charges NL'!D81+'Detailed Base Charges BE'!D81 | E81: =+'Detailed Base Charges NL'!E81+'Detailed Base Charges BE'!E81 | F81: =+'Detailed Base Charges NL'!F81+'Detailed Base Charges BE'!F81 | G81: =SUM(B81:F81)
A82: Domestic Outbound Calls - Cellular | B82: =+'Detailed Base Charges NL'!B82+'Detailed Base Charges BE'!B82 | C82: =+'Detailed Base Charges NL'!C82+'Detailed Base Charges BE'!C82 | D82: =+'Detailed Base Charges NL'!D82+'Detailed Base Charges BE'!D82 | E82: =+'Detailed Base Charges NL'!E82+'Detailed Base Charges BE'!E82 | F82: =+'Detailed Base Charges NL'!F82+'Detailed Base Charges BE'!F82 | G82: =SUM(B82:F82)
A83: International Outbound Calls | B83: =+'Detailed Base Charges NL'!B83+'Detailed Base Charges BE'!B83 | C83: =+'Detailed Base Charges NL'!C83+'Detailed Base Charges BE'!C83 | D83: =+'Detailed Base Charges NL'!D83+'Detailed Base Charges BE'!D83 | E83: =+'Detailed Base Charges NL'!E83+'Detailed Base Charges BE'!E83 | F83: =+'Detailed Base Charges NL'!F83+'Detailed Base Charges BE'!F83 | G83: =SUM(B83:F83)
A84: Free phone Service Calls | B84: =+'Detailed Base Charges NL'!B84+'Detailed Base Charges BE'!B84 | C84: =+'Detailed Base Charges NL'!C84+'Detailed Base Charges BE'!C84 | D84: =+'Detailed Base Charges NL'!D84+'Detailed Base Charges BE'!D84 | E84: =+'Detailed Base Charges NL'!E84+'Detailed Base Charges BE'!E84 | F84: =+'Detailed Base Charges NL'!F84+'Detailed Base Charges BE'!F84 | G84: =SUM(B84:F84)
A85: Mobile - national | B85: =+'Detailed Base Charges NL'!B85+'Detailed Base Charges BE'!B85 | C85: =+'Detailed Base Charges NL'!C85+'Detailed Base Charges BE'!C85 | D85: =+'Detailed Base Charges NL'!D85+'Detailed Base Charges BE'!D85 | E85: =+'Detailed Base Charges NL'!E85+'Detailed Base Charges BE'!E85 | F85: =+'Detailed Base Charges NL'!F85+'Detailed Base Charges BE'!F85 | G85: =SUM(B85:F85)
A86: Mobile - international | B86: =+'Detailed Base Charges NL'!B86+'Detailed Base Charges BE'!B86 | C86: =+'Detailed Base Charges NL'!C86+'Detailed Base Charges BE'!C86 | D86: =+'Detailed Base Charges NL'!D86+'Detailed Base Charges BE'!D86 | E86: =+'Detailed Base Charges NL'!E86+'Detailed Base Charges BE'!E86 | F86: =+'Detailed Base Charges NL'!F86+'Detailed Base Charges BE'!F86 | G86: =SUM(B86:F86)
A87: Mobile - roaming outbound | B87: =+'Detailed Base Charges NL'!B87+'Detailed Base Charges BE'!B87 | C87: =+'Detailed Base Charges NL'!C87+'Detailed Base Charges BE'!C87 | D87: =+'Detailed Base Charges NL'!D87+'Detailed Base Charges BE'!D87 | E87: =+'Detailed Base Charges NL'!E87+'Detailed Base Charges BE'!E87 | F87: =+'Detailed Base Charges NL'!F87+'Detailed Base Charges BE'!F87 | G87: =SUM(B87:F87)
A88: Mobile - roaming inbound | B88: =+'Detailed Base Charges NL'!B88+'Detailed Base Charges BE'!B88 | C88: =+'Detailed Base Charges NL'!C88+'Detailed Base Charges BE'!C88 | D88: =+'Detailed Base Charges NL'!D88+'Detailed Base Charges BE'!D88 | E88: =+'Detailed Base Charges NL'!E88+'Detailed Base Charges BE'!E88 | F88: =+'Detailed Base Charges NL'!F88+'Detailed Base Charges BE'!F88 | G88: =SUM(B88:F88)
A89: Free phone Services Dedicated per min. | B89: =+'Detailed Base Charges NL'!B89+'Detailed Base Charges BE'!B89 | C89: =+'Detailed Base Charges NL'!C89+'Detailed Base Charges BE'!C89 | D89: =+'Detailed Base Charges NL'!D89+'Detailed Base Charges BE'!D89 | E89: =+'Detailed Base Charges NL'!E89+'Detailed Base Charges BE'!E89 | F89: =+'Detailed Base Charges NL'!F89+'Detailed Base Charges BE'!F89 | G89: =SUM(B89:F89)
A90: High Tariff Outbound Calls (0900) | B90: =+'Detailed Base Charges NL'!B90+'Detailed Base Charges BE'!B90 | C90: =+'Detailed Base Charges NL'!C90+'Detailed Base Charges BE'!C90 | D90: =+'Detailed Base Charges NL'!D90+'Detailed Base Charges BE'!D90 | E90: =+'Detailed Base Charges NL'!E90+'Detailed Base Charges BE'!E90 | F90: =+'Detailed Base Charges NL'!F90+'Detailed Base Charges BE'!F90 | G90: =SUM(B90:F90)
A91: High Tariff Outbound Calls (0676 internet) | B91: =+'Detailed Base Charges NL'!B91+'Detailed Base Charges BE'!B91 | C91: =+'Detailed Base Charges NL'!C91+'Detailed Base Charges BE'!C91 | D91: =+'Detailed Base Charges NL'!D91+'Detailed Base Charges BE'!D91 | E91: =+'Detailed Base Charges NL'!E91+'Detailed Base Charges BE'!E91 | F91: =+'Detailed Base Charges NL'!F91+'Detailed Base Charges BE'!F91 | G91: =SUM(B91:F91)
... A94: Voice - IMACS | B94: =+'Detailed Base Charges NL'!B94+'Detailed Base Charges BE'!B94 | C94: =+'Detailed Base Charges NL'!C94+'Detailed Base Charges BE'!C94 | D94: =+'Detailed Base Charges NL'!D94+'Detailed Base Charges BE'!D94 | E94: =+'Detailed Base Charges NL'!E94+'Detailed Base Charges BE'!E94 | F94: =+'Detailed Base Charges NL'!F94+'Detailed Base Charges BE'!F94 | G94: =SUM(B94:F94)
A96: Subscriptions
A97: ISDN 1 | B97: =+'Detailed Base Charges NL'!B97+'Detailed Base Charges BE'!B97 | C97: =+'Detailed Base Charges NL'!C97+'Detailed Base Charges BE'!C97 | D97: =+'Detailed Base Charges NL'!D97+'Detailed Base Charges BE'!D97 | E97: =+'Detailed Base Charges NL'!E97+'Detailed Base Charges BE'!E97 | F97: =+'Detailed Base Charges NL'!F97+'Detailed Base Charges BE'!F97 | G97: =SUM(B97:F97)
A98: ISDN 2 | B98: =+'Detailed Base Charges NL'!B98+'Detailed Base Charges BE'!B98 | C98: =+'Detailed Base Charges NL'!C98+'Detailed Base Charges BE'!C98 | D98: =+'Detailed Base Charges NL'!D98+'Detailed Base Charges BE'!D98 | E98: =+'Detailed Base Charges NL'!E98+'Detailed Base Charges BE'!E98 | F98: =+'Detailed Base Charges NL'!F98+'Detailed Base Charges BE'!F98 | G98: =SUM(B98:F98)
A99: ISDN 15 | B99: =+'Detailed Base Charges NL'!B99+'Detailed Base Charges BE'!B99 | C99: =+'Detailed Base Charges NL'!C99+'Detailed Base Charges BE'!C99 | D99: =+'Detailed Base Charges NL'!D99+'Detailed Base Charges BE'!D99 | E99: =+'Detailed Base Charges NL'!E99+'Detailed Base Charges BE'!E99 | F99: =+'Detailed Base Charges NL'!F99+'Detailed Base Charges BE'!F99 | G99: =SUM(B99:F99)
A100: ISDN 30 | B100: =+'Detailed Base Charges NL'!B100+'Detailed Base Charges BE'!B100 | C100: =+'Detailed Base Charges NL'!C100+'Detailed Base Charges BE'!C100 | D100: =+'Detailed Base Charges NL'!D100+'Detailed Base Charges BE'!D100 | E100: =+'Detailed Base Charges NL'!E100+'Detailed Base Charges BE'!E100 | F100: =+'Detailed Base Charges NL'!F100+'Detailed Base Charges BE'!F100 | G100: =SUM(B100:F100)
A101: ISDN 30 (CPA) | B101: =+'Detailed Base Charges NL'!B101+'Detailed Base Charges BE'!B101 | C101: =+'Detailed Base Charges NL'!C101+'Detailed Base Charges BE'!C101 | D101: =+'Detailed Base Charges NL'!D101+'Detailed Base Charges BE'!D101 | E101: =+'Detailed Base Charges NL'!E101+'Detailed Base Charges BE'!E101 | F101: =+'Detailed Base Charges NL'!F101+'Detailed Base Charges BE'!F101 | G101: =SUM(B101:F101)
A102: Dual homing telephony | B102: =+'Detailed Base Charges NL'!B102+'Detailed Base Charges BE'!B102 | C102: =+'Detailed Base Charges NL'!C102+'Detailed Base Charges BE'!C102 | D102: =+'Detailed Base Charges NL'!D102+'Detailed Base Charges BE'!D102 | E102: =+'Detailed Base Charges NL'!E102+'Detailed Base Charges BE'!E102 | F102: =+'Detailed Base Charges NL'!F102+'Detailed Base Charges BE'!F102 | G102: =SUM(B102:F102)
A103: DDI reserved numbers (10) | B103: =+'Detailed Base Charges NL'!B103+'Detailed Base Charges BE'!B103 | C103: =+'Detailed Base Charges NL'!C103+'Detailed Base Charges BE'!C103 | D103: =+'Detailed Base Charges NL'!D103+'Detailed Base Charges BE'!D103 | E103: =+'Detailed Base Charges NL'!E103+'Detailed Base Charges BE'!E103 | F103: =+'Detailed Base Charges NL'!F103+'Detailed Base Charges BE'!F103 | G103: =SUM(B103:F103)
A104: DDI reserved numbers (100) | B104: =+'Detailed Base Charges NL'!B104+'Detailed Base Charges BE'!B104 | C104: =+'Detailed Base Charges NL'!C104+'Detailed Base Charges BE'!C104 | D104: =+'Detailed Base Charges NL'!D104+'Detailed Base Charges BE'!D104 | E104: =+'Detailed Base Charges NL'!E104+'Detailed Base Charges BE'!E104 | F104: =+'Detailed Base Charges NL'!F104+'Detailed Base Charges BE'!F104 | G104: =SUM(B104:F104)
A105: DDI reserved numbers (1000) | B105: =+'Detailed Base Charges NL'!B105+'Detailed Base Charges BE'!B105 | C105: =+'Detailed Base Charges NL'!C105+'Detailed Base Charges BE'!C105 | D105: =+'Detailed Base Charges NL'!D105+'Detailed Base Charges BE'!D105 | E105: =+'Detailed Base Charges NL'!E105+'Detailed Base Charges BE'!E105 | F105: =+'Detailed Base Charges NL'!F105+'Detailed Base Charges BE'!F105 | G105: =SUM(B105:F105)
A106: DDI reserved numbers (10000) | B106: =+'Detailed Base Charges NL'!B106+'Detailed Base Charges BE'!B106 | C106: =+'Detailed Base Charges NL'!C106+'Detailed Base Charges BE'!C106 | D106: =+'Detailed Base Charges NL'!D106+'Detailed Base Charges BE'!D106 | E106: =+'Detailed Base Charges NL'!E106+'Detailed Base Charges BE'!E106 | F106: =+'Detailed Base Charges NL'!F106+'Detailed Base Charges BE'!F106 | G106: =SUM(B106:F106)
A107: DDI facilities | B107: =+'Detailed Base Charges NL'!B107+'Detailed Base Charges BE'!B107 | C107: =+'Detailed Base Charges NL'!C107+'Detailed Base Charges BE'!C107 | D107: =+'Detailed Base Charges NL'!D107+'Detailed Base Charges BE'!D107 | E107: =+'Detailed Base Charges NL'!E107+'Detailed Base Charges BE'!E107 | F107: =+'Detailed Base Charges NL'!F107+'Detailed Base Charges BE'!F107 | G107: =SUM(B107:F107)
A108: Calamity services | B108: =+'Detailed Base Charges NL'!B108+'Detailed Base Charges BE'!B108 | C108: =+'Detailed Base Charges NL'!C108+'Detailed Base Charges BE'!C108 | D108: =+'Detailed Base Charges NL'!D108+'Detailed Base Charges BE'!D108 | E108: =+'Detailed Base Charges NL'!E108+'Detailed Base Charges BE'!E108 | F108: =+'Detailed Base Charges NL'!F108+'Detailed Base Charges BE'!F108 | G108: =SUM(B108:F108)
...

Sheet Detailed Base Charges NL
A1: Detailed Base Charges - Netherlands | B1: Year 1 | C1: Year 2 | D1: Year 3 | E1: Year 4 | F1: Year 5 | G1: Total 5 Yr
A2: EUC
A3: Support Services
A4: Medium Service Level
A5: Standard Desktops (CEDS) | B5: 2686580.3 | C5: 2431515.9 | D5: 2256759.5 | E5: 2145688.7 | F5: 2066173 | G5: =SUM(B5:F5)
A6: Non-Standard Desktops (non CEDS) | B6: 28967.187 | C6: 26495.484 | D6: 24910.421 | E6: 23855.469 | F6: 23124.263 | G6: =SUM(B6:F6)
A7: Standard Laptops (CEDS) | B7: 738801.52 | C7: 681619.43 | D7: 647554.65 | E7: 625277.62 | F7: 608398.36 | G7: =SUM(B7:F7)
A8: Non-Standard Laptops (non CEDS) | G8: =SUM(B8:F8)
A9: Standard Local Printers | B9: 325875.74 | C9: 320921.91 | D9: 327682.86 | E9: 328432.65 | F9: 330064.73 | G9: =SUM(B9:F9)
A10: Non-Standard Local Printers | G10: =SUM(B10:F10)
A11: Standard Network Printers | G11: =SUM(B11:F11)
A12: Non-Standard Network Printers | G12: =SUM(B12:F12)
A13: Other Peripherals | G13: =SUM(B13:F13)
A14: Dealing room support | B14: =6*90000 | C14: =6*90000 | D14: =6*90000 | E14: =6*90000 | F14: =6*90000 | G14: =SUM(B14:F14)
A15: Installations | B15: 424279.59 | C15: 328394.49 | D15: 336723.18 | E15: 336713.61 | F15: 339817.95 | G15: =SUM(B15:F15)
A16: Moves | B16: 118251.38 | C16: 119512.42 | D16: 125117.57 | E16: 123696.24 | F16: 127443.81 | G16: =SUM(B16:F16)
A17: Adds | B17: 35204.572 | C17: 34780.957 | D17: 35626.293 | E17: 35645.534 | F17: 35936.924 | G17: =SUM(B17:F17)
A18: Changes | B18: 41387.983 | C18: 41829.348 | D18: 43791.148 | E18: 43293.685 | F18: 44605.334 | G18: =SUM(B18:F18)
A19: Low Service Level
A20: Standard Desktops | B20: 7469082.9 | C20: 6721280.1 | D20: 6194069.4 | E20: 5870452.5 | F20: 5629150.6 | G20: =SUM(B20:F20)
A21: Non-Standard Desktops | B21: 136694.53 | C21: 124335.46 | D21: 116113.15 | E21: 110888.48 | F21: 107063.44 | G21: =SUM(B21:F21)
A22: Standard Laptops | B22: 712664.63 | C22: 654316.35 | D22: 618046.2 | E22: 595316.76 | F22: 577376.47 | G22: =SUM(B22:F22)
A23: Non-Standard Laptops | B23: 38985.382 | C23: 36254.538 | D23: 34767.222 | E23: 33794.476 | F23: 33003.218 | G23: =SUM(B23:F23)
A24: Standard Local Printers | B24: 71349.611 | C24: 70209.228 | D24: 71632.066 | E24: 71827.099 | F24: 72126.919 | G24: =SUM(B24:F24)
A25: Non-Standard Local Printers | B25: 102905.81 | C25: 101425.88 | D25: 103647.84 | E25: 103837.88 | F25: 104440.34 | G25: =SUM(B25:F25)
A26: Standard Network Printers | B26: 588318.44 | C26: 562295.52 | D26: 546416.32 | E26: 547568.26 | F26: 547772.78 | G26: =SUM(B26:F26)
A27: Non-Standard Network Printers | B27: 113376.08 | C27: 110208.76 | D27: 110362.51 | E27: 110768.17 | F27: 110854.88 | G27: =SUM(B27:F27)
A28: Other Peripherals | B28: 280600.14 | C28: 274818.76 | D28: 279078.42 | E28: 280563.25 | F28: 280404.86 | G28: =SUM(B28:F28)
A29: UAS POOL | B29: 3750000 | C29: 3750000 | D29: 3750000 | E29: 3750000 | F29: 3750000 | G29: =SUM(B29:F29)
A30: Installations | B30: 397668.18 | C30: 402766.57 | D30: 407892.63 | E30: 405053.17 | F30: 410256.98 | G30: =SUM(B30:F30)
A31: Moves | B31: 500734.38 | C31: 518260.09 | D31: 535880.93 | E31: 526120.27 | F31: 544008.36 | G31: =SUM(B31:F31)
A32: Adds | G32: =SUM(B32:F32)
A33: Changes | B33: 141116.05 | C33: 146055.12 | D33: 151020.99 | E33: 148270.26 | F33: 153311.45 | G33: =SUM(B33:F33)
A34: Packaging & Distribution | B34: =SUM(Facilities!D44,Facilities!D46,Facilities!D48) | C34: =SUM(Facilities!E44,Facilities!E46,Facilities!E48) | G34: =SUM(B34:F34) | H34: Row used for PST reimbursement for use of EuroBank facilities
A35: Packaging | B35: 922016.77 | C35: 921891.98 | D35: 917027.32 | E35: 912162.65 | F35: 920481.65 | G35: =SUM(B35:F35)
A36: TOTAL EUC | B36: =SUM(B5:B35) | C36: =SUM(C5:C35) | D36: =SUM(D5:D35) | E36: =SUM(E5:E35) | F36: =SUM(F5:F35) | G36: =SUM(B36:F36)
A37: Service Desk
A38: Seats | B38: 7602704.5 | C38: 7303292.9 | D38: 5662512.3 | E38: 4262523.4 | F38: 3863518.2 | G38: =SUM(B38:F38)
G39: =SUM(B39:F39)
G40: =SUM(B40:F40)
G41: =SUM(B41:F41)
G42: =SUM(B42:F42)
G43: =SUM(B43:F43)
G44: =SUM(B44:F44)
B45: =Facilities!D52 | C45: =Facilities!E52 | G45: =SUM(B45:F45) | H45: Row used for PST reimbursement for use of EuroBank facilities
A46: TOTAL SERVICE DESK (seats supported) | B46: =SUM(B38:B45) | C46: =SUM(C38:C45) | D46: =SUM(D38:D45) | E46: =SUM(E38:E45) | F46: =SUM(F38:F45) | G46: =SUM(B46:F46)
A47: LAN Services
A48: Support Services | G48: =SUM(B48:F48)
A49: Monitoring LAN port IT, SP, ... | G49: =SUM(B49:F49)
A50: Site Type A: # of Active LAN Ports | B50: 534466.6 | C50: 404586.74 | D50: 387646.36 | E50: 387679.91 | F50: 387673.56 | G50: =SUM(B50:F50)
A51: Site Type B: # of Active LAN Ports | B51: 828804.71 | C51: 627398.22 | D51: 601128.53 | E51: 601180.57 | F51: 601170.72 | G51: =SUM(B51:F51)
A52: Site Type C: # of Active LAN Ports | B52: 3442812.2 | C52: 2606180 | D52: 2497057.1 | E52: 2497273.2 | F52: 2497232.3 | G52: =SUM(B52:F52)
A53: TOTAL LAN SERVICES | B53: =SUM(B47:B52) | C53: =SUM(C47:C52) | D53: =SUM(D47:D52) | E53: =SUM(E47:E52) | F53: =SUM(F47:F52) | G53: =SUM(B53:F53)
A54: Voice Services
A55: Locations (Systems & Services)
A56: Call Centres | B56: 2481253.6 | C56: 2374104.7 | D56: 2258930.1 | E56: 2132883 | F56: 2005976.8 | G56: =SUM(B56:F56)
A57: Employee ISDN | B57: 275904 | C57: 274464 | D57: 273024 | E57: 273024 | F57: 273024 | G57: =SUM(B57:F57)
A58: Dealing room voice | G58: =SUM(B58:F58)
A59: Video conferencing | B59: 104097.16 | C59: 73922.899 | D59: 73325.681 | E59: 72746.203 | F59: 72178.551 | G59: =SUM(B59:F59)
A60: Assets Call Center | B60: 357947.28 | C60: 403374.84 | D60: 448802.4 | E60: 493956.3 | F60: 493956.3 | G60: =SUM(B60:F60) | H60: Charges for PBX's: Small, Medium, and Large per Attachment 4-D are included in the Handsets
A61: Assets Digital Voice Fixed | B61: 821489.4 | C61: 947855.7 | D61: 1079202 | E61: 1214855.2 | F61: 1214855.2 | G61: =SUM(B61:F61) | H61: Charges for PBX's: Small, Medium, and Large per Attachment 4-D are included in the Handsets
A62: Assets Analogue Voice Fixed | B62: 204048 | C62: 212256 | D62: 216480 | E62: 216600 | F62: 216600 | G62: =SUM(B62:F62) | H62: Charges for PBX's: Small, Medium, and Large per Attachment 4-D are included in the Handsets
A63: Handsets - Digital (incl. DECT) | B63: 1873615.4 | C63: 1902185.6 | D63: 1867295.8 | E63: 1786478.3 | F63: 1662637.1 | G63: =SUM(B63:F63)
A64: Handsets - Analog | B64: 497489.17 | C64: 457572.24 | D64: 399567.3 | E64: 335745.38 | F64: 312945.38 | G64: =SUM(B64:F64)
A65: Cellular Phones management fee | B65: 711515.68 | C65: 549457.28 | D65: 563774.59 | E65: 527106.17 | F65: 492786.17 | G65: =SUM(B65:F65)
A66: Cellular Phones subscription | C66: 504000 | D66: 508200 | E66: 462000 | F66: 415800 | G66: =SUM(B66:F66)
A67: Cellular Phones refresh (budget) | B67: 287185 | C67: 302300 | D67: 332530 | E67: 332530 | F67: 332530 | G67: =SUM(B67:F67)
A68: GPRS/UMTS Cards or Devices management fee | B68: 6338.7943 | C68: 7098.534 | D68: 6608.4429 | E68: 6164.8328 | F68: 5749.8932 | G68: =SUM(B68:F68)
A69: GPRS/UMTS Cards or Devices subscription | B69: 72000 | C69: 86400 | D69: 82080 | E69: 77976 | F69: 74077.2 | G69: =SUM(B69:F69)
A70: GPRS/UMTS Cards or Devices refresh (budget) | B70: 8250 | C70: 9900 | D70: 9900 | E70: 9900 | F70: 9900 | G70: =SUM(B70:F70)
A71: Blackberries management fee | B71: 44712.163 | C71: 57758.805 | D71: 59740.817 | E71: 55717.134 | F71: 51955.257 | G71: =SUM(B71:F71)
A72: Blackberries subscription (data) | B72: 327600 | C72: 453600 | D72: 478800 | E72: 454860 | F72: 432117 | G72: =SUM(B72:F72)
A73: Blackberries refresh / new CAL licence (budget) | B73: 116639.26 | C73: 161500.52 | D73: 179445.02 | E73: 179445.02 | F73: 179445.02 | G73: =SUM(B73:F73)
A74: Internal Pagers management fee | G74: =SUM(B74:F74)
A75: Internal Pagers refresh (budget) | G75: =SUM(B75:F75)
A76: External Pagers management fee | B76: 5508 | C76: 4924.8 | D76: 4363.2 | E76: 3844.8 | F76: 3434.4 | G76: =SUM(B76:F76)
A77: External Pagers refresh (budget) | B77: 5670 | C77: 5670 | D77: 5670 | E77: 5670 | F77: 5670 | G77: =SUM(B77:F77)
A79: VOICE
A80: Domestic Outbound Calls - Local | B80: 590827.11 | C80: 531744.4 | D80: 531744.4 | E80: 531744.4 | F80: 531744.4 | G80: =SUM(B80:F80)
A81: Domestic Outbound Calls - Long Distance | B81: 1076330 | C81: 968696.99 | D81: 968696.99 | E81: 968696.99 | F81: 968696.99 | G81: =SUM(B81:F81)
A82: Domestic Outbound Calls - Cellular | B82: 1450621.4 | C82: 1122781 | D82: 1122781 | E82: 1122781 | F82: 1122781 | G82: =SUM(B82:F82)
A83: International Outbound Calls | B83: 328054.31 | C83: 282126.82 | D83: 282126.82 | E83: 282126.82 | F83: 282126.82 | G83: =SUM(B83:F83)
A84: Free phone Service Calls | B84: 114330 | C84: 112043.4 | D84: 109802.53 | E84: 107606.48 | F84: 105454.35 | G84: =SUM(B84:F84)
A85: Mobile - national | C85: 1280807.3 | D85: 1318274.1 | E85: 1251975.2 | F85: 1189376.4 | G85: =SUM(B85:F85)
A86: Mobile - international | C86: 206290.47 | D86: 212325.14 | E86: 201647.73 | F86: 191565.34 | G86: =SUM(B86:F86)
A87: Mobile - roaming outbound | C87: 513770.06 | D87: 528799.46 | E87: 502206.89 | F87: 477096.55 | G87: =SUM(B87:F87)
A88: Mobile - roaming inbound | C88: 177119.7 | D88: 168263.72 | E88: 159850.53 | F88: 151858 | G88: =SUM(B88:F88)
A89: Free phone Services Dedicated per min. | B89: 290800 | C89: 284984 | D89: 279284.32 | E89: 273698.63 | F89: 268224.66 | G89: =SUM(B89:F89)
A90: High Tariff Outbound Calls (0900) | B90: 191435.02 | C90: 95717.509 | D90: 95717.509 | E90: 95717.509 | F90: 95717.509 | G90: =SUM(B90:F90)
A91: High Tariff Outbound Calls (0676 internet) | B91: 502403.89 | C91: 401923.11 | D91: 200961.55 | E91: 200961.55 | F91: 200961.55 | G91: =SUM(B91:F91)
A92: High Tariff Outbound Calls Other | B92: 22854.762 | C92: 22511.941 | D92: 22511.941 | E92: 22511.941 | F92: 22511.941 | G92: =SUM(B92:F92)
A93: Voice - Directory Assistance Calls per call | B93: 0 | C93: 0 | D93: 0 | E93: 0 | F93: 0 | G93: =SUM(B93:F93)
A94: Voice - Hard IMACS | B94: 305060.66 | C94: 283777.35 | D94: 262494.05 | E94: 241210.75 | F94: 219927.45 | G94: =SUM(B94:F94)
A96: Subscriptions
A97: ISDN 1 | B97: 18754.56 | C97: 242743.68 | D97: 242743.68 | E97: 242743.68 | F97: 242743.68 | G97: =SUM(B97:F97)
A98: ISDN 2 | B98: 1335519.4 | C98: 719146.08 | D98: 719146.08 | E98: 719146.08 | F98: 719146.08 | G98: =SUM(B98:F98)
A99: ISDN 15 | B99: 9720 | C99: 6480 | D99: 6480 | E99: 6480 | F99: 6480 | G99: =SUM(B99:F99)
A100: ISDN 30 | B100: 490440.96 | C100: 393309.33 | D100: 393309.33 | E100: 393309.33 | F100: 393309.33 | G100: =SUM(B100:F100)
A101: ISDN 30 (CPA) | B101: 171180 | C101: 158220 | D101: 158220 | E101: 158220 | F101: 158220 | G101: =SUM(B101:F101)
A102: Dual homing telephony | B102: 116529 | C102: 116529.12 | D102: 116529.12 | E102: 116529.12 | F102: 116529.12 | G102: =SUM(B102:F102)
...

Sheet Detailed Base Charges BE
A1: Detailed Base Charges - Belgium | B1: Year 1 | C1: Year 2 | D1: Year 3 | E1: Year 4 | F1: Year 5 | G1: Total 5 Yr
A2: EUC
A3: Support Services
A4: Medium Service Level
A5: Standard Desktops (CEDS) | B5: 1055346.8 | C5: 1254087 | D5: 1121541 | E5: 1059318.6 | F5: 996578.1 | G5: =SUM(B5:F5)
A6: Non-Standard Desktops (non CEDS) | G6: =SUM(B6:F6)
A7: Standard Laptops (CEDS) | B7: 219999.86 | C7: 302976.32 | D7: 282586.31 | E7: 271739.73 | F7: 260929.55 | G7: =SUM(B7:F7)
A8: Non-Standard Laptops (non CEDS) | G8: =SUM(B8:F8)
A9: Standard Local Printers | B9: 153322.63 | C9: 462410.34 | D9: 454236.1 | E9: 448547.75 | F9: 438282.12 | G9: =SUM(B9:F9)
A10: Non-Standard Local Printers | G10: =SUM(B10:F10)
A11: Standard Network Printers | B11: 24490.295 | C11: 73845.554 | D11: 72829.524 | E11: 71966.601 | F11: 70604.96 | G11: =SUM(B11:F11)
A12: Non-Standard Network Printers | B12: 9852.5579 | C12: 29688.703 | D12: 29516.845 | E12: 29190.478 | F12: 28733.282 | G12: =SUM(B12:F12)
A13: Other Peripherals | G13: =SUM(B13:F13)
A14: Dealing room support | B14: =8*90000 | C14: =8*90000 | D14: =8*90000 | E14: =8*90000 | F14: =8*90000 | G14: =SUM(B14:F14)
A15: Installations | B15: 58096.401 | C15: 177612.12 | D15: 184560.57 | E15: 181456.99 | F15: 184199.69 | G15: =SUM(B15:F15)
A16: Moves | B16: 39457.95 | C16: 122794.25 | D16: 129784.99 | E16: 126439.93 | F16: 130534.06 | G16: =SUM(B16:F16)
A17: Adds | G17: =SUM(B17:F17)
A18: Changes | B18: 32693.73 | C18: 101743.8 | D18: 107536.14 | E18: 104764.51 | F18: 108156.79 | G18: =SUM(B18:F18)
A19: Low Service Level
A20: Standard Desktops | B20: 2382792.8 | C20: 2746253.2 | D20: 2461138 | E20: 2321270 | F20: 2185816.3 | G20: =SUM(B20:F20)
A21: Non-Standard Desktops | G21: =SUM(B21:F21)
A22: Standard Laptops | B22: 260168.32 | C22: 345669.56 | D22: 324284.38 | E22: 312304.91 | F22: 300903.59 | G22: =SUM(B22:F22)
A23: Non-Standard Laptops | G23: =SUM(B23:F23)
A24: Standard Local Printers | B24: 320061.2 | C24: 964786.87 | D24: 954226.31 | E24: 943029.49 | F24: 924969.74 | G24: =SUM(B24:F24)
A25: Non-Standard Local Printers | G25: =SUM(B25:F25)
A26: Standard Network Printers | B26: 86155.428 | C26: 181471.29 | D26: 167111.64 | E26: 165069.65 | F26: 162005.32 | G26: =SUM(B26:F26)
A27: Non-Standard Network Printers | B27: 23236.467 | C27: 64917.637 | D27: 64022.573 | E27: 63340.076 | F27: 62486.195 | G27: =SUM(B27:F27)
A28: Other Peripherals | G28: =SUM(B28:F28)
A29: Secondment of 5 FTE | B29: =560000/12*8 | G29: =SUM(B29:F29) | H29: Delivery of capacity of 5 named FTEs to EuroBank in order to monitor EuroBank Technics and AMSIT contracts on behalf of EuroBank during the period from commencement date until the date the in scope activities of AMSIT and INGTechnics will be taken over by Neptune (planned 11/01/07)
A30: Installations | B30: 87404.831 | C30: 266610.3 | D30: 271029.97 | E30: 268622.13 | F30: 273110.2 | G30: =SUM(B30:F30)
A31: Moves | B31: 59363.669 | C31: 184324.19 | D31: 190591.21 | E31: 187176.93 | F31: 193540.95 | G31: =SUM(B31:F31)
A32: Adds | G32: =SUM(B32:F32)
A33: Changes | B33: 49187.04 | C33: 152725.76 | D33: 157918.43 | E33: 155089.46 | F33: 160362.5 | G33: =SUM(B33:F33)
A34: Packaging & Distribution | B34: =SUM(Facilities!D45,Facilities!D47,Facilities!D49) | C34: =SUM(Facilities!E45,Facilities!E47,Facilities!E49) | G34: =SUM(B34:F34) | H34: Row used for PST reimbursement for use of EuroBank facilities
A35: Packaging | B35: 951790.23 | C35: 931495.02 | D35: 926579.68 | E35: 921664.35 | F35: 930070.01 | G35: =SUM(B35:F35)
A36: TOTAL EUC | B36: =SUM(B5:B35) | C36: =SUM(C5:C35) | D36: =SUM(D5:D35) | E36: =SUM(E5:E35) | F36: =SUM(F5:F35) | G36: =SUM(B36:F36)
A37: Service Desk
A38: Seats | B38: 1246672.5 | C38: 3503392.6 | D38: 2431876.9 | E38: 1905817 | F38: 1520623 | G38: =SUM(B38:F38)
G39: =SUM(B39:F39)
G40: =SUM(B40:F40)
G41: =SUM(B41:F41)
G42: =SUM(B42:F42)
G43: =SUM(B43:F43)
G44: =SUM(B44:F44)
B45: =Facilities!D53 | C45: =Facilities!E53 | G45: =SUM(B45:F45) | H45: Row used for PST reimbursement for use of EuroBank facilities
A46: TOTAL SERVICE DESK (seats supported) | B46: =SUM(B38:B45) | C46: =SUM(C38:C45) | D46: =SUM(D38:D45) | E46: =SUM(E38:E45) | F46: =SUM(F38:F45) | G46: =SUM(B46:F46)
A47: LAN Services
A48: Support Services
A49: Monitoring LAN port IT, SP, ... | B49: 75962.03 | C49: 75962.03 | D49: 69602.662 | E49: 69602.662 | F49: 69602.662 | G49: =SUM(B49:F49)
A50: Site Type A: # of Active LAN Ports | B50: 1452014.4 | C50: 993614.67 | D50: 947591.8 | E50: 947682.96 | F50: 947665.71 | G50: =SUM(B50:F50)
A51: Site Type B: # of Active LAN Ports | B51: 242838.98 | C51: 166174.91 | D51: 158477.92 | E51: 158493.16 | F51: 158490.28 | G51: =SUM(B51:F51)
A52: Site Type C: # of Active LAN Ports | B52: 1172734.6 | C52: 802503.22 | D52: 765332.37 | E52: 765406 | F52: 765392.06 | G52: =SUM(B52:F52)
A53: TOTAL LAN SERVICES | B53: =SUM(B47:B52) | C53: =SUM(C47:C52) | D53: =SUM(D47:D52) | E53: =SUM(E47:E52) | F53: =SUM(F47:F52) | G53: =SUM(B53:F53)
A54: Voice Services
A55: Locations (Systems & Services)
A56: Call Centres | B56: 130563.66 | C56: 124925.48 | D56: 118864.99 | E56: 112232.39 | F56: 105554.58 | G56: =SUM(B56:F56)
A57: Employee ISDN | B57: 75840 | C57: 75600 | D57: 75360 | E57: 75360 | F57: 75360 | G57: =SUM(B57:F57)
A58: Dealing room voice | G58: =SUM(B58:F58)
A59: Video conferencing | B59: 107158.84 | C59: 76097.101 | D59: 75482.319 | E59: 74885.797 | F59: 74301.449 | G59: =SUM(B59:F59)
A60: Assets Call Center | B60: 36907.2 | C60: 23097.6 | D60: 24638.4 | E60: 27014.4 | F60: 27014.4 | G60: =SUM(B60:F60) | H60: Charges for PBX's: Small, Medium, and Large per Attachment 4-D are included in the Handsets
A61: Assets Digital Voice Fixed | B61: 702236.37 | C61: 1203425.3 | D61: 1186437.9 | E61: 1186437.9 | F61: 1186437.9 | G61: =SUM(B61:F61) | H61: Charges for PBX's: Small, Medium, and Large per Attachment 4-D are included in the Handsets
A62: Assets Analogue Voice Fixed | B62: 122931.73 | C62: 76934.256 | D62: 82066.404 | E62: 89980.464 | F62: 89980.464 | G62: =SUM(B62:F62) | H62: Charges for PBX's: Small, Medium, and Large per Attachment 4-D are included in the Handsets
A63: Handsets - Digital (incl. DECT) | B63: 548883.85 | C63: 810481.06 | D63: 777479.51 | E63: 727252.35 | F63: 676838.19 | G63: =SUM(B63:F63)
A64: Handsets - Analog | B64: 152958.79 | C64: 152409.69 | D64: 145188.23 | E64: 134197.43 | F64: 125084.27 | G64: =SUM(B64:F64)
A65: Cellular Phones management fee | B65: 398284.31 | C65: 384070.64 | D65: 358253.13 | E65: 334952.01 | F65: 313143.21 | G65: =SUM(B65:F65)
A66: Cellular Phones subscription | B66: 234864 | C66: 322938 | D66: 293580 | E66: 264222 | F66: 234864 | G66: =SUM(B66:F66)
A67: Cellular Phones refresh (budget) + lease fees | B67: 211307.7 | C67: 211307.7 | D67: 211307.7 | E67: 211307.7 | F67: 211307.7 | G67: =SUM(B67:F67)
A68: GPRS/UMTS Cards or Devices management fee | G68: =SUM(B68:F68)
A69: GPRS/UMTS Cards or Devices subscription | G69: =SUM(B69:F69)
A70: GPRS/UMTS Cards or Devices refresh (budget) | G70: =SUM(B70:F70)
A71: Blackberries management fee | B71: 12381.83 | C71: 14760.584 | D71: 16727.429 | E71: 18386.654 | F71: 19742.998 | G71: =SUM(B71:F71)
A72: Blackberries subscription (data) | B72: 90720 | C72: 115920 | D72: 134064 | E72: 150103.8 | F72: 164204.46 | G72: =SUM(B72:F72)
A73: Blackberries refresh / new CAL licence (budget) | B73: 32300.104 | C73: 41272.355 | D73: 50244.606 | E73: 59216.857 | F73: 68189.108 | G73: =SUM(B73:F73)
A74: Internal Pagers management fee | B74: 14700 | C74: 13566 | D74: 12474 | E74: 11466 | F74: 10668 | G74: =SUM(B74:F74)
A75: Internal Pagers refresh (budget) | B75: 20825 | C75: 20825 | D75: 20825 | E75: 20825 | F75: 20825 | G75: =SUM(B75:F75)
A76: External Pagers management fee | G76: =SUM(B76:F76)
A77: External Pagers refresh (budget) | G77: =SUM(B77:F77)
A79: VOICE
A80: Domestic Outbound Calls - Local | B80: 692717.5 | C80: 662268.38 | D80: 650849.96 | E80: 635625.4 | F80: 620400.84 | G80: =SUM(B80:F80)
A81: Domestic Outbound Calls - Long Distance | G81: =SUM(B81:F81)
A82: Domestic Outbound Calls - Cellular | B82: 952787.05 | C82: 788772.46 | D82: 721413.79 | E82: 721413.79 | F82: 721413.79 | G82: =SUM(B82:F82)
A83: International Outbound Calls | B83: 170542.23 | C83: 149489.14 | D83: 149489.14 | E83: 149489.14 | F83: 149489.14 | G83: =SUM(B83:F83)
A84: Free phone Service Calls | G84: =SUM(B84:F84)
A85: Mobile - national | B85: 269751.14 | C85: 384395.38 | D85: 365175.61 | E85: 346916.83 | F85: 329570.98 | G85: =SUM(B85:F85)
A86: Mobile - international | B86: 17563.424 | C86: 25027.879 | D86: 23776.485 | E86: 22587.661 | F86: 21458.278 | G86: =SUM(B86:F86)
A87: Mobile - roaming outbound | B87: 67069.372 | C87: 95573.856 | D87: 90795.163 | E87: 86255.405 | F87: 81942.634 | G87: =SUM(B87:F87)
A88: Mobile - roaming inbound | B88: 23988.43 | C88: 34183.513 | D88: 32474.337 | E88: 30850.62 | F88: 29308.089 | G88: =SUM(B88:F88)
A89: Free phone Services Dedicated per min. | G89: =SUM(B89:F89)
A90: High Tariff Outbound Calls (0900) | B90: 5811.9887 | C90: 2905.9943 | D90: 2905.9943 | E90: 2905.9943 | F90: 2905.9943 | G90: =SUM(B90:F90)
A91: High Tariff Outbound Calls (0676 internet) | B91: 57072.069 | C91: 57072.069 | D91: 57072.069 | E91: 57072.069 | F91: 57072.069 | G91: =SUM(B91:F91)
A92: High Tariff Outbound Calls Other | G92: =SUM(B92:F92)
A93: Voice - Directory Assistance Calls per call | B93: 54900 | C93: 54900 | D93: 54900 | E93: 54900 | F93: 54900 | G93: =SUM(B93:F93)
A94: Voice - Hard IMACS | B94: 198644.77 | C94: 198644.77 | D94: 198644.77 | E94: 198644.77 | F94: 198644.77 | G94: =SUM(B94:F94)
A96: Subscriptions
A97: ISDN 1 | G97: =SUM(B97:F97)
A98: ISDN 2 | B98: 808404 | C98: 732540 | D98: 732540 | E98: 732540 | F98: 732540 | G98: =SUM(B98:F98)
A99: ISDN 15 | G99: =SUM(B99:F99)
A100: ISDN 30 | B100: 503304 | C100: 450720 | D100: 450720 | E100: 450720 | F100: 450720 | G100: =SUM(B100:F100)
A101: ISDN 30 (CPA) | G101: =SUM(B101:F101)
A102: Dual homing telephony | G102: =SUM(B102:F102)
...

Sheet Unit Rates (ARCs & RRCs) NL
A1: ARC'S & RRC'S - NETHERLANDS | B1: Year 1 ARC/RRC | C1: Year 2 ARC/RRC | D1: Year 3 ARC/RRC | E1: Year 4 ARC/RRC | F1: Year 5 ARC/RRC | G1: Resource Unit
A2: EUC
A3: Support Services
A4: Medium Service Level
A5: Standard Desktops (CEDS) | B5: 19.490122 | C5: 17.59544 | D5: 16.191966 | E5: 15.300583 | F5: 14.688882 | G5: per device per month
A6: Non-Standard Desktops (non CEDS) | B6: 22.025331 | C6: 20.083991 | D6: 18.685199 | E6: 17.759803 | F6: 17.155347 | G6: per device per month
A7: Standard Laptops (CEDS) | B7: 25.485917 | C7: 23.429118 | D7: 21.985615 | E7: 21.042926 | F7: 20.397432 | G7: per device per month
A8: Non-Standard Laptops (non CEDS)
A9: Standard Local Printers | B9: 12.218789 | C9: 11.96203 | D9: 11.953119 | E9: 11.807138 | F9: 11.81069 | G9: per device per month
A10: Non-Standard Local Printers
A11: Standard Network Printers
A12: Non-Standard Network Printers
A13: Other Peripherals
A15: Installations | B15: 184.46939 | C15: 143.8452 | D15: 145.67594 | E15: 144.66185 | F15: 146.52035 | G15: per installation
A16: Moves | B16: 59.12569 | C16: 47.114553 | D16: 48.716448 | E16: 47.829116 | F16: 49.455306 | G16: per move
A17: Adds | B17: 176.02286 | C17: 137.11455 | D17: 138.71645 | E17: 137.82912 | F17: 139.45531 | G17: per add
A18: Changes | B18: 59.12569 | C18: 47.114553 | D18: 48.716448 | E18: 47.829116 | F18: 49.455306 | G18: per change
A19: Low Service Level
A20: Standard Desktops (CEDS) | B20: 18.48514 | C20: 16.597617 | D20: 15.181099 | E20: 14.309577 | F20: 13.683852 | G20: per device per month
A21: Non-Standard Desktops (non CEDS) | B21: 20.804274 | C21: 18.870059 | D21: 17.453864 | E21: 16.553486 | F21: 15.930443 | G21: per device per month
A22: Standard Laptops (CEDS) | B22: 23.991999 | C22: 21.953578 | D22: 20.498319 | E22: 19.580801 | F22: 18.92207 | G22: per device per month
A23: Non-Standard Laptops (non CEDS) | B23: 29.538024 | C23: 27.359163 | D23: 25.876268 | E23: 24.90594 | F23: 24.225311 | G23: per device per month
A24: Standard Local Printers | B24: 10.374503 | C24: 10.148439 | D24: 10.132918 | E24: 10.013506 | F24: 10.008594 | G24: per device per month
A25: Non-Standard Local Printers | B25: 11.22217 | C25: 10.995503 | D25: 10.996351 | E25: 10.857128 | F25: 10.869391 | G25: per device per month
A26: Standard Network Printers | B26: 13.247286 | C26: 12.586341 | D26: 11.966514 | E26: 11.825331 | F26: 11.775327 | G26: per device per month
A27: Non-Standard Network Printers | B27: 19.800048 | C27: 19.132895 | D27: 18.748176 | E27: 18.548554 | F27: 18.477114 | G27: per device per month
A28: Other Peripherals | B28: 35.070566 | C28: 34.145279 | D28: 33.933803 | E28: 33.620786 | F28: 33.445712 | G28: per device per month
A30: Installations | B30: 142.02435 | C30: 143.8452 | D30: 145.67594 | E30: 144.66185 | F30: 146.52035 | G30: per installation
A31: Moves | B31: 45.521308 | C31: 47.114553 | D31: 48.716448 | E31: 47.829116 | F31: 49.455306 | G31: per move
A32: Adds | G32: per add
A33: Changes | B33: 45.521308 | C33: 47.114553 | D33: 48.716448 | E33: 47.829116 | F33: 49.455306 | G33: per change
A34: Packaging & Distribution
A35: Packaging | B35: 883.59941 | C35: 883.47981 | D35: 878.81784 | E35: 874.15588 | F35: 882.12825 | G35: per package
A36: TOTAL EUC
A37: Service Desk
A38: Seats Supported
A39: Price per seat | B39: 16.612705 | C39: 15.958459 | D39: 12.373182 | E39: 9.3140595 | F39: 8.4421914 | G39: per seat per month
A47: TOTAL SERVICE DESK (seats supported)
A48: LAN Services
A49: Support Services
A51: Site Type A: # of Active LAN Ports | B51: 8.3717045 | C51: 6.3327501 | D51: 6.0675926 | E51: 6.0681178 | F51: 6.0680184 | G51: per active LAN Port per month
A52: Site Type B: # of Active LAN Ports | B52: 8.3717045 | C52: 6.3327501 | D52: 6.0675926 | E52: 6.0681178 | F52: 6.0680184 | G52: per active LAN Port per month
A53: Site Type C: # of Active LAN Ports | B53: 8.3717045 | C53: 6.3327501 | D53: 6.0675926 | E53: 6.0681178 | F53: 6.0680184 | G53: per active LAN Port per month
A54: TOTAL LAN SERVICES
A55: Voice Services
A56: Locations (Systems & Services)
A57: Call Centres per seat | B57: 45.334606 | C57: 43.376903 | D57: 41.272567 | E57: 38.96958 | F57: 36.650896 | G57: per seat per month
A58: Employee ISDN | B58: 19.16 | C58: 19.06 | D58: 18.96 | E58: 18.96 | F58: 18.96 | G58: per subscription per month
A59: Dealing room voice | B59: 152.78343 | C59: 145.64676 | D59: 145.33406 | E59: 146.48094 | F59: 146.48094 | G59: per seat per month
A60: Video conferencing | B60: 255.1401 | C60: 181.18357 | D60: 179.71981 | E60: 178.29952 | F60: 176.90821 | G60: per room per month
A61: Assets Call Center | B61: 6.54 | C61: 7.37 | D61: 8.2 | E61: 9.025 | F61: 9.025 | G61: per call center seat per month | H61: Charges for PBX's: Small, Medium, and Large per Attachment 4-D are included in the Handsets
A62: Assets Digital Voice Fixed | B62: 1.635 | C62: 1.8425 | D62: 2.05 | E62: 2.25625 | F62: 2.25625 | G62: per handset per month | H62: Charges for PBX's: Small, Medium, and Large per Attachment 4-D are included in the Handsets
A63: Assets Analogue Voice Fixed | B63: 1.308 | C63: 1.474 | D63: 1.64 | E63: 1.805 | F63: 1.805 | G63: per handset per month | H63: Charges for PBX's: Small, Medium, and Large per Attachment 4-D are included in the Handsets
A64: Handsets - Digital (incl. DECT) | B64: 3.7290332 | C64: 3.697585 | D64: 3.547025 | E64: 3.3178781 | F64: 3.0878781 | G64: per handset per month
A65: Handsets - Analog | B65: 3.1890332 | C65: 3.177585 | D65: 3.027025 | E65: 2.7978781 | F65: 2.6078781 | G65: per handset per month
A66: Cellular Phones management fee | B66: 6.2413656 | C66: 4.5788107 | D66: 4.2710196 | E66: 3.9932286 | F66: 3.7332286 | G66: per handset per month
A67: Cellular Phones subscription | C67: 4.2 | D67: 3.85 | E67: 3.5 | F67: 3.15 | G67: per subscription per month
A68: Cellular Phones refresh (budget) | B68: 2.7615583 | C68: 2.7615583 | D68: 2.7615583 | E68: 2.7615583 | F68: 2.7615583 | G68: per subscription per month (excluding accessoires and car kits)
A69: GPRS/UMTS Cards or Devices management fee | B69: 5.2823286 | C69: 4.9295375 | D69: 4.5891964 | E69: 4.2811339 | F69: 3.9929814 | G69: per device per month
A70: GPRS/UMTS Cards or Devices subscription | B70: 60 | C70: 60 | D70: 57 | E70: 54.15 | F70: 51.4425 | G70: per subscription per month
A71: GPRS/UMTS Cards or Devices refresh (budget) | B71: 6.88 | C71: 6.88 | D71: 6.88 | E71: 6.88 | F71: 6.88 | G71: per subscription per month
A72: Blackberries management fee | B72: 5.7323286 | C72: 5.3480375 | D72: 4.9784014 | E72: 4.6430945 | F72: 4.3296048 | G72: per device per month
A73: Blackberries subscription (data) | B73: 42 | C73: 42 | D73: 39.9 | E73: 37.905 | F73: 36.00975 | G73: per subscription per month
A74: Blackberry refresh (budget) | B74: 9.6812037 | C74: 9.6812037 | D74: 9.6812037 | E74: 9.6812037 | F74: 9.6812037 | G74: per subscription per month (excluding new CAL license)
A75: Internal Pagers management fee | B75: 3.5 | C75: 3.23 | D75: 2.97 | E75: 2.73 | F75: 2.54 | G75: per device per month
A76: Internal Pagers refresh (budget)
A77: External Pagers management fee | B77: 2.55 | C77: 2.28 | D77: 2.02 | E77: 1.78 | F77: 1.59 | G77: per device per month
A78: External Pagers refresh (budget)
A80: VOICE
A81: Domestic Outbound Calls - Local | B81: 0.01697025 | C81: 0.015273225 | D81: 0.015273225 | E81: 0.015273225 | F81: 0.015273225 | G81: per minute
A82: Domestic Outbound Calls - Long Distance | B82: 0.024365249 | C82: 0.021928724 | D82: 0.021928724 | E82: 0.021928724 | F82: 0.021928724 | G82: per minute
A83: Domestic Outbound Calls - Cellular | B83: 0.13026419 | C83: 0.10082448 | D83: 0.10082448 | E83: 0.10082448 | F83: 0.10082448 | G83: per minute
A84: International Outbound Calls | B84: 0.045740118 | C84: 0.039336502 | D84: 0.039336502 | E84: 0.039336502 | F84: 0.039336502 | G84: per minute
A85: Free phone Service Calls | B85: 0.0309 | C85: 0.030282 | D85: 0.02967636 | E85: 0.029082833 | F85: 0.028501176 | G85: per call
A86: Mobile - national | C86: 0.052090918 | D86: 0.049490504 | E86: 0.047001518 | F86: 0.044651442 | G86: per minute
A87: Mobile - international | C87: 0.30141799 | D87: 0.28637247 | E87: 0.27197136 | F87: 0.2583728 | G87: per minute
A88: Mobile - roaming outbound | C88: 0.43734789 | D88: 0.41551705 | E88: 0.39462129 | F88: 0.37489022 | G88: per minute
A89: Mobile - roaming inbound | C89: 0.3903 | D89: 0.370785 | E89: 0.35224575 | F89: 0.33463346 | G89: per minute
A90: Free phone Services Dedicated per min. | B90: 0.02 | C90: 0.0196 | D90: 0.019208 | E90: 0.01882384 | F90: 0.018447363 | G90: per minute
A91: High Tariff Outbound Calls (0900) | B91: 0.081259565 | C91: 0.040629782 | D91: 0.040629782 | E91: 0.040629782 | F91: 0.040629782 | G91: per minute
A92: High Tariff Outbound Calls (0676 internet) | B92: 0.0130475 | C92: 0.010438 | D92: 0.005219 | E92: 0.005219 | F92: 0.005219 | G92: per minute
A93: High Tariff Outbound Calls Other | B93: 0.044269375 | C93: 0.043605334 | D93: 0.043605334 | E93: 0.043605334 | F93: 0.043605334 | G93: per minute
A94: Voice - Directory Assistance Calls per call
A95: Voice - Hard IMACS | B95: 35.472169 | C95: 35.472169 | D95: 35.472169 | E95: 35.472169 | F95: 35.472169 | G95: per IMAC
A97: Subscriptions
A98: ISDN 1 | B98: 17.76 | C98: 17.76 | D98: 17.76 | E98: 17.76 | F98: 17.76 | G98: per subscription per month
A99: ISDN 2 | B99: 21.96 | C99: 21.96 | D99: 21.96 | E99: 21.96 | F99: 21.96 | G99: per subscription per month
A100: ISDN 15 | B100: 135 | C100: 135 | D100: 135 | E100: 135 | F100: 135 | G100: per subscription per month
A101: ISDN 30 | B101: 197.44 | C101: 197.44 | D101: 197.44 | E101: 197.44 | F101: 197.44 | G101: per subscription per month
A102: ISDN 30 (CPA) | B102: 45 | C102: 45 | D102: 45 | E102: 45 | F102: 45 | G102: per subscription per month
A103: Dual homing telephony | B103: 1387.25 | C103: 1387.25 | D103: 1387.25 | E103: 1387.25 | F103: 1387.25 | G103: per subscription per month
A104: DDI reserved numbers (10) | B104: 10.95 | C104: 10.95 | D104: 10.95 | E104: 10.95 | F104: 10.95 | G104: per subscription per month
A105: DDI reserved numbers (100) | B105: 65.44 | C105: 65.44 | D105: 65.44 | E105: 65.44 | F105: 65.44 | G105: per subscription per month
A106: DDI reserved numbers (1000) | B106: 493.1 | C106: 493.1 | D106: 493.1 | E106: 493.1 | F106: 493.1 | G106: per subscription per month
A107: DDI reserved numbers (10000) | B107: 3500.77 | C107: 3500.77 | D107: 3500.77 | E107: 3500.77 | F107: 3500.77 | G107: per subscription per month
A108: DDI facilities | B108: 17.4 | C108: 17.4 | D108: 17.4 | E108: 17.4 | F108: 17.4 | G108: per subscription per month
A109: Calamity services | B109: 1061.55 | C109: 1061.55 | D109: 1061.55 | E109: 1061.55 | F109: 1061.55 | G109: per subscription per month
... A113: Telex | B113: 50.98 | C113: 50.98 | D113: 50.98 | E113: 50.98 | F113: 50.98 | G113: per subscription per month
A114: TOTAL VOICE SERVICES
A119: Server Management
...

Sheet Unit Rates (ARCs & RRCs) BE
A1: ARC'S & RRC'S - BELGIUM | B1: Year 1 ARC/RRC | C1: Year 2 ARC/RRC | D1: Year 3 ARC/RRC | E1: Year 4 ARC/RRC | F1: Year 5 ARC/RRC | G1: Resource Unit
A2: EUC
A3: Support Services
A4: Medium Service Level
A5: Standard Desktops (CEDS) | B5: 15.40611 | C5: 18.253015 | D5: 16.211472 | E5: 15.217466 | F5: 14.289316 | G5: per device per month
A6: Non-Standard Desktops (non CEDS)
A7: Standard Laptops (CEDS) | B7: 19.664698 | C7: 26.982629 | D7: 24.936186 | E7: 23.789231 | F7: 22.788477 | G7: per device per month
A8: Non-Standard Laptops (non CEDS)
A9: Standard Local Printers | B9: 4.669959 | C9: 14.049031 | D9: 13.568072 | E9: 13.211122 | F9: 12.861905 | G9: per device per month
A10: Non-Standard Local Printers
A11: Standard Network Printers | B11: 5.1851812 | C11: 15.595752 | D11: 15.121925 | E11: 14.734152 | F11: 14.402898 | G11: per device per month
A12: Non-Standard Network Printers | B12: 8.0524941 | C12: 24.203863 | D12: 23.658164 | E12: 23.069961 | F12: 22.626189 | G12: per device per month
A13: Other Peripherals
A15: Installations | B15: 233.09434 | C15: 236.94409 | D15: 242.0638 | E15: 234.67087 | F15: 237.35309 | G15: per installation
A16: Moves | B16: 99.511129 | C16: 102.96887 | D16: 106.99662 | E16: 102.78373 | F16: 105.72665 | G16: per move
A17: Adds
A18: Changes | B18: 99.511129 | C18: 102.96887 | D18: 106.99662 | E18: 102.78373 | F18: 105.72665 | G18: per change
A19: Low Service Level
A20: Standard Desktops (CEDS) | B20: 15.143977 | C20: 17.405809 | D20: 15.498816 | E20: 14.533839 | F20: 13.660993 | G20: per device per month
A21: Non-Standard Desktops (non CEDS)
A22: Standard Laptops (CEDS) | B22: 20.590327 | C22: 27.263378 | D22: 25.360272 | E22: 24.24555 | F22: 23.309048 | G22: per device per month
A23: Non-Standard Laptops (non CEDS)
A24: Standard Local Printers | B24: 4.3797813 | C24: 13.169304 | D24: 12.805616 | E24: 12.478687 | F24: 12.195277 | G24: per device per month
A25: Non-Standard Local Printers
A26: Standard Network Printers | B26: 6.4726358 | C26: 15.924445 | D26: 14.969315 | E26: 14.59554 | F26: 14.294395 | G26: per device per month
A27: Non-Standard Network Printers | B27: 8.5393805 | C27: 23.784507 | D27: 23.062964 | E27: 22.502588 | F27: 22.119177 | G27: per device per month
A28: Other Peripherals
A30: Installations | B30: 172.73682 | C30: 175.63261 | D30: 178.54412 | E30: 176.95793 | F30: 179.9145 | G30: per installation
A31: Moves | B31: 73.743688 | C31: 76.324717 | D31: 78.919757 | E31: 77.505977 | F31: 80.14118 | G31: per move
A32: Adds
A33: Changes | B33: 73.743688 | C33: 76.324717 | D33: 78.919757 | E33: 77.505977 | F33: 80.14118 | G33: per change
A34: Packaging & Distribution
A35: Packaging | B35: 883.59941 | C35: 883.47981 | D35: 878.81784 | E35: 874.15588 | F35: 882.12825 | G35: per package
A36: TOTAL EUC
A37: Service Desk
A38: Seats Supported
A39: Price per seat | B39: 6.6895925 | C39: 18.799059 | D39: 13.04935 | E39: 10.226535 | F39: 8.1595998 | G39: per seat per month
A47: TOTAL SERVICE DESK (seats supported)
A48: LAN Services
A49: Support Services
A50: Monitoring LAN port IT, SP, ... | B50: 3.1650846 | C50: 3.1650846 | D50: 2.9001109 | E50: 2.9001109 | F50: 2.9001109 | G50: per active LAN Port per month
A51: Site Type A: # of Active LAN Ports | B51: 8.3717045 | C51: 5.724642 | D51: 5.4594845 | E51: 5.4600097 | F51: 5.4599103 | G51: per active LAN Port per month
A52: Site Type B: # of Active LAN Ports | B52: 8.3717045 | C52: 5.724642 | D52: 5.4594845 | E52: 5.4600097 | F52: 5.4599103 | G52: per active LAN Port per month
A53: Site Type C: # of Active LAN Ports | B53: 8.3717045 | C53: 5.724642 | D53: 5.4594845 | E53: 5.4600097 | F53: 5.4599103 | G53: per active LAN Port per month
A54: TOTAL LAN SERVICES
A55: Voice Services
A56: Locations (Systems & Services)
A57: Call Centres per seat | B57: 45.334606 | C57: 43.376903 | D57: 41.272567 | E57: 38.96958 | F57: 36.650896 | G57: per seat per month
A58: Employee ISDN | B58: 31.6 | C58: 31.5 | D58: 31.4 | E58: 31.4 | F58: 31.4 | G58: per subscription per month
A59: Dealing room | B59: 152.78343 | C59: 145.64676 | D59: 145.33406 | E59: 146.48094 | F59: 146.48094 | G59: per seat per month
A60: Video conferencing | B60: 255.1401 | C60: 181.18357 | D60: 179.71981 | E60: 178.29952 | F60: 176.90821 | G60: per room per month
A61: Assets Call Center | B61: 12.815 | C61: 8.02 | D61: 8.555 | E61: 9.38 | F61: 9.38 | G61: per call center seat per month | H61: Charges for PBX's: Small, Medium, and Large per Attachment 4-D are included in the Handsets
A62: Assets Digital Voice Fixed | B62: 3.20375 | C62: 2.005 | D62: 2.13875 | E62: 2.345 | F62: 2.345 | G62: per handset per month | H62: Charges for PBX's: Small, Medium, and Large per Attachment 4-D are included in the Handsets
A63: Assets Analogue Voice Fixed | B63: 2.563 | C63: 1.604 | D63: 1.711 | E63: 1.876 | F63: 1.876 | G63: per handset per month | H63: Charges for PBX's: Small, Medium, and Large per Attachment 4-D are included in the Handsets
A64: Handsets - Digital (incl. DECT) | B64: 3.7290332 | C64: 3.697585 | D64: 3.547025 | E64: 3.3178781 | F64: 3.0878781 | G64: per handset per month
A65: Handsets - Analog | B65: 3.1890332 | C65: 3.177585 | D65: 3.027025 | E65: 2.7978781 | F65: 2.6078781 | G65: per handset per month
A66: Cellular Phones management fee | B66: 4.7482631 | C66: 4.5788107 | D66: 4.2710196 | E66: 3.9932286 | F66: 3.7332286 | G66: per handset per month
A67: Cellular Phones subscription | B67: 4.2 | C67: 3.85 | D67: 3.5 | E67: 3.15 | F67: 2.8 | G67: per subscription per month
A68: Cellular Phones refresh (budget) | B68: 2.7615583 | C68: 2.7615583 | D68: 2.7615583 | E68: 2.7615583 | F68: 2.7615583 | G68: per subscription per month (excluding accessoires and car kits)
A69: GPRS/UMTS Cards or Devices management fee | B69: 5.2823286 | C69: 4.9295375 | D69: 4.5891964 | E69: 4.2811339 | F69: 3.9929814 | G69: per device per month
A70: GPRS/UMTS Cards or Devices subscription | B70: 55 | C70: 55 | D70: 52.25 | E70: 49.6375 | F70: 47.155625 | G70: per subscription per month
A71: GPRS/UMTS Cards or Devices refresh (budget) | B71: 6.88 | C71: 6.88 | D71: 6.88 | E71: 6.88 | F71: 6.88 | G71: per subscription per month
A72: Blackberries management fee | B72: 5.7323286 | C72: 5.3480375 | D72: 4.9784014 | E72: 4.6430945 | F72: 4.3296048 | G72: per device per month
A73: Blackberries subscription (data) | B73: 42 | C73: 42 | D73: 39.9 | E73: 37.905 | F73: 36.00975 | G73: per subscription per month
A74: Blackberry refresh (budget) | B74: 9.6812037 | C74: 9.6812037 | D74: 9.6812037 | E74: 9.6812037 | F74: 9.6812037 | G74: per subscription per month (excluding new CAL license)
A75: Internal Pagers management fee | B75: 3.5 | C75: 3.23 | D75: 2.97 | E75: 2.73 | F75: 2.54 | G75: per device per month
A76: Internal Pagers refresh (budget)
A77: External Pagers management fee | B77: 2.55 | C77: 2.28 | D77: 2.02 | E77: 1.78 | F77: 1.59 | G77: per device per month
A78: External Pagers refresh (budget)
A80: VOICE
A81: Domestic Outbound Calls - Local | B81: 0.016994783 | C81: 0.016247759 | D81: 0.015967625 | E81: 0.015594114 | F81: 0.015220602 | G81: per minute
A82: Domestic Outbound Calls - Long Distance
A83: Domestic Outbound Calls - Cellular | B83: 0.14129298 | C83: 0.11697054 | D83: 0.10698162 | E83: 0.10698162 | F83: 0.10698162 | G83: per minute
A84: International Outbound Calls | B84: 0.060781447 | C84: 0.053278102 | D84: 0.053278102 | E84: 0.053278102 | F84: 0.053278102 | G84: per minute
A85: Free phone Service Calls
A86: Mobile - national | B86: 0.039096 | C86: 0.0371412 | D86: 0.03528414 | E86: 0.033519933 | F86: 0.031843936 | G86: per minute
A87: Mobile - international | B87: 0.19704075 | C87: 0.18718871 | D87: 0.17782927 | E87: 0.16893781 | F87: 0.16049092 | G87: per minute
A88: Mobile - roaming outbound | B88: 0.46418645 | C88: 0.44097713 | D88: 0.41892827 | E88: 0.39798186 | F88: 0.37808277 | G88: per minute
A89: Mobile - roaming inbound | B89: 0.19051742 | C89: 0.18099155 | D89: 0.17194198 | E89: 0.16334488 | F89: 0.15517763 | G89: per minute
A90: Free phone Services Dedicated per min.
A91: High Tariff Outbound Calls (0900) | B91: 0.078412173 | C91: 0.039206087 | D91: 0.039206087 | E91: 0.039206087 | F91: 0.039206087 | G91: per minute
A92: High Tariff Outbound Calls (0676 internet) | B92: 0.021010039 | C92: 0.021010039 | D92: 0.021010039 | E92: 0.021010039 | F92: 0.021010039 | G92: per minute
A93: High Tariff Outbound Calls Other
A94: Voice - Directory Assistance Calls per call | B94: 1.83 | C94: 1.83 | D94: 1.83 | E94: 1.83 | F94: 1.83
A95: Voice - IMACS | B95: 47.751147 | C95: 47.751147 | D95: 47.751147 | E95: 47.751147 | F95: 47.751147 | G95: per IMAC
A97: Subscriptions
A98: ISDN 1
A99: ISDN 2 | B99: 29 | C99: 29 | D99: 29 | E99: 29 | F99: 29 | G99: per subscription per month
A100: ISDN 15
A101: ISDN 30 | B101: 313 | C101: 313 | D101: 313 | E101: 313 | F101: 313 | G101: per subscription per month
A102: ISDN 30 (CPA)
A103: Dual homing telephony
A104: DDI reserved numbers (10) | B104: 7.44 | C104: 7.44 | D104: 7.44 | E104: 7.44 | F104: 7.44 | G104: per subscription per month
A105: DDI reserved numbers (100) | B105: 32 | C105: 32 | D105: 32 | E105: 32 | F105: 32 | G105: per subscription per month
A106: DDI reserved numbers (1000) | B106: 128 | C106: 128 | D106: 128 | E106: 128 | F106: 128 | G106: per subscription per month
A107: DDI reserved numbers (10000)
A108: DDI facilities
A109: Calamity services
A110: Infrastructure services
A111: ADSL
...

Sheet One Time Charges
B2: Total Transition phase
E3: HR prep | F3: Prep | H3: Transition
B4: 2IM | D4: Month -2 | E4: Month -1 | F4: Month 0 | G4: Month 1 | H4: Month 2 | I4: Month 3 | J4: Month 4 | K4: Month 5 | L4: Month 6 | M4: Month 7 | N4: Month 8 | O4: Month 9 | P4: Month 10 | Q4: Month 11 | R4: Month 12 | S4: Year 1 | T4: Month 13 | U4: Month 14 | V4: Month 15 | W4: Month 16 | X4: Month 17 | Y4: Month 18 | Z4: Month 19 | AA4: Month 20 | AB4: Month 21 | AC4: Month 22 | AD4: Month 23 | AE4: Month 24 | AF4: Year 2 | AG4: Month 25 | AH4: Month 26 | AI4: Month 27 | AJ4: Month 28 | AK4: Month 29 | AL4: Month 30 | AM4: Month 31 | AN4: Month 32 | AO4: Month 33 | AP4: Month 34 | AQ4: Month 35 | AR4: Month 36 | AS4: Year 3 | AT4: Month 37 | AU4: Month 38 | AV4: Month 39 | AW4: Month 40 | AX4: Month 41 | AY4: Month 42 | AZ4: Month 43 | BA4: Month 44 | BB4: Month 45 | BC4: Month 46 | BD4: Month 47 | BE4: Month 48 | BF4: Year 4 | BG4: Total
D5: (Euro) | E5: (Euro) | F5: (Euro) | G5: (Euro) | H5: (Euro) | I5: (Euro) | J5: (Euro) | K5: (Euro) | L5: (Euro) | M5: (Euro) | N5: (Euro) | O5: (Euro) | P5: (Euro) | Q5: (Euro) | R5: (Euro) | S5: (Euro) | T5: (Euro) | U5: (Euro) | V5: (Euro) | W5: (Euro) | X5: (Euro) | Y5: (Euro) | Z5: (Euro) | AA5: (Euro) | AB5: (Euro) | AC5: (Euro) | AD5: (Euro) | AE5: (Euro) | AF5: (Euro) | AG5: (Euro) | AH5: (Euro) | AI5: (Euro) | AJ5: (Euro) | AK5: (Euro) | AL5: (Euro) | AM5: (Euro) | AN5: (Euro) | AO5: (Euro) | AP5: (Euro) | AQ5: (Euro) | AR5: (Euro) | AS5: (Euro) | AT5: (Euro) | AU5: (Euro) | AV5: (Euro) | AW5: (Euro) | AX5: (Euro) | AY5: (Euro) | AZ5: (Euro) | BA5: (Euro) | BB5: (Euro) | BC5: (Euro) | BD5: (Euro) | BE5: (Euro) | BF5: (Euro) | BG5: (Euro)
B7: 1. Transition Program Management Stream | F7: 97878.137 | G7: 44490.062 | H7: 44490.062 | I7: 44490.062 | J7: 0 | K7: 0 | L7: 0 | M7: 0 | N7: 0 | O7: 0 | P7: 0 | Q7: 0 | R7: 0 | S7: =SUM(F7:R7) | AF7: =SUM(T7:AE7) | AS7: =SUM(AR7) | BF7: =SUM(BE7) | BG7: =SUM(S7,AF7,AS7,BF7)
B8: 2. Service Management Stream | F8: 0 | G8: 101771.02 | H8: 124016.05 | I8: 122903.8 | J8: 0 | K8: 0 | L8: 0 | M8: 0 | N8: 0 | O8: 0 | P8: 0 | Q8: 0 | R8: 0 | S8: =SUM(F8:R8) | AF8: =SUM(T8:AE8) | AS8: =SUM(AR8) | BF8: =SUM(BE8) | BG8: =SUM(S8,AF8,AS8,BF8)
B9: 3. Unit Operations Stream | F9: 0 | G9: 111225.16 | H9: 145148.83 | I9: 144036.58 | J9: 0 | K9: 0 | L9: 0 | M9: 0 | N9: 0 | O9: 0 | P9: 0 | Q9: 0 | R9: 0 | S9: =SUM(F9:R9) | AF9: =SUM(T9:AE9) | AS9: =SUM(AR9) | BF9: =SUM(BE9) | BG9: =SUM(S9,AF9,AS9,BF9)
B10: 4. Communications Stream | F10: 23357.283 | G10: 22245.031 | H10: 11122.516 | I10: 4449.0062 | J10: 0 | K10: 0 | L10: 0 | M10: 0 | N10: 0 | O10: 0 | P10: 0 | Q10: 0 | R10: 0 | S10: =SUM(F10:R10) | AF10: =SUM(T10:AE10) | AS10: =SUM(AR10) | BF10: =SUM(BE10) | BG10: =SUM(S10,AF10,AS10,BF10)
B11: 5. Finance and Contract Management Stream | F11: 16591.086 | G11: 58504.432 | H11: 69070.822 | I11: 69070.822 | J11: 0 | K11: 0 | L11: 0 | M11: 0 | N11: 0 | O11: 0 | P11: 0 | Q11: 0 | R11: 0 | S11: =SUM(F11:R11) | AF11: =SUM(T11:AE11) | AS11: =SUM(AR11) | BF11: =SUM(BE11) | BG11: =SUM(S11,AF11,AS11,BF11)
B12: 6. People Transfer Stream | F12: 0 | G12: 51386.022 | H12: 46714.565 | I12: 28028.739 | J12: 0 | K12: 0 | L12: 0 | M12: 0 | N12: 0 | O12: 0 | P12: 0 | Q12: 0 | R12: 0 | S12: =SUM(F12:R12) | AF12: =SUM(T12:AE12) | AS12: =SUM(AR12) | BF12: =SUM(BE12) | BG12: =SUM(S12,AF12,AS12,BF12)
B13: 7. Knowledge Transfer Stream | F13: 0 | G13: 23357.283 | H13: 23357.283 | I13: 23357.283 | J13: 0 | K13: 0 | L13: 0 | M13: 0 | N13: 0 | O13: 0 | P13: 0 | Q13: 0 | R13: 0 | S13: =SUM(F13:R13) | AF13: =SUM(T13:AE13) | AS13: =SUM(AR13) | BF13: =SUM(BE13) | BG13: =SUM(S13,AF13,AS13,BF13)
B14: TOTAL | E14: 0 | F14: =SUM(F7:F13) | G14: =SUM(G7:G13) | H14: =SUM(H7:H13) | I14: =SUM(I7:I13) | J14: =SUM(J7:J13) | K14: =SUM(K7:K13) | L14: =SUM(L7:L13) | M14: =SUM(M7:M13) | ... R14: =SUM(R7:R13) | S14: =SUM(F14:R14) | T14: =SUM(T7:T13) | U14: =SUM(U7:U13) | V14: =SUM(V7:V13) | W14: =SUM(W7:W13) | X14: =SUM(X7:X13) | Y14: =SUM(Y7:Y13) | Z14: =SUM(Z7:Z13) | AA14: =SUM(AA7:AA13) | ... AE14: =SUM(AE7:AE13) | AF14: =SUM(AE14) | AG14: =SUM(AG7:AG13) | AH14: =SUM(AH7:AH13) | AI14: =SUM(AI7:AI13) | AJ14: =SUM(AJ7:AJ13) | AK14: =SUM(AK7:AK13) | AL14: =SUM(AL7:AL13) | AM14: =SUM(AM7:AM13) | AN14: =SUM(AN7:AN13) | ... AR14: =SUM(AR7:AR13) | AS14: =SUM(AR14) | AT14: =SUM(AT7:AT13) | AU14: =SUM(AU7:AU13) | AV14: =SUM(AV7:AV13) | AW14: =SUM(AW7:AW13) | AX14: =SUM(AX7:AX13) | AY14: =SUM(AY7:AY13) | AZ14: =SUM(AZ7:AZ13) | BA14: =SUM(BA7:BA13) | ... BE14: =SUM(BE7:BE13) | BF14: =SUM(BE14) | BG14: =SUM(BG7:BG13)
E16: HR prep | F16: Prep | H16: Transition
B17: 2IM | E17: Month -1 | F17: Month 0 | G17: Month 1 | H17: Month 2 | I17: Month 3 | J17: Month 4 | K17: Month 5 | L17: Month 6 | M17: Month 7 | N17: Month 8 | O17: Month 9 | P17: Month 10 | Q17: Month 11 | R17: Month 12 | T17: Month 13 | U17: Month 14 | V17: Month 15 | W17: Month 16 | X17: Month 17 | Y17: Month 18 | Z17: Month 19 | AA17: Month 20 | AB17: Month 21 | AC17: Month 22 | AD17: Month 23 | AE17: Month 24 | AG17: Month 25 | AH17: Month 26 | AI17: Month 27 | AJ17: Month 28 | AK17: Month 29 | AL17: Month 30 | AM17: Month 31 | AN17: Month 32 | AO17: Month 33 | AP17: Month 34 | AQ17: Month 35 | AR17: Month 36 | AT17: Month 37 | AU17: Month 38 | AV17: Month 39 | AW17: Month 40 | AX17: Month 41 | AY17: Month 42 | AZ17: Month 43 | BA17: Month 44 | BB17: Month 45 | BC17: Month 46 | BD17: Month 47 | BE17: Month 48
E18: FTE's | F18: FTE's | G18: FTE's | H18: FTE's | I18: FTE's | J18: FTE's | K18: FTE's | L18: FTE's | M18: FTE's | N18: FTE's | O18: FTE's | P18: FTE's | Q18: FTE's | R18: FTE's | T18: FTE's | U18: FTE's | V18: FTE's | W18: FTE's | X18: FTE's | Y18: FTE's | Z18: FTE's | AA18: FTE's | AB18: FTE's | AC18: FTE's | AD18: FTE's | AE18: FTE's | AG18: FTE's | AH18: FTE's | AI18: FTE's | AJ18: FTE's | AK18: FTE's | AL18: FTE's | AM18: FTE's | AN18: FTE's | AO18: FTE's | AP18: FTE's | AQ18: FTE's | AR18: FTE's | AT18: FTE's | AU18: FTE's | AV18: FTE's | AW18: FTE's | AX18: FTE's | AY18: FTE's | AZ18: FTE's | BA18: FTE's | BB18: FTE's | BC18: FTE's | BD18: FTE's | BE18: FTE's
B20: 1. Transition Program Management Stream | E20: 0 | F20: 4.1904762 | G20: 1.9047619 | H20: 1.9047619 | I20: 1.9047619
B21: 2. Service Management Stream | E21: 0 | F21: 0 | G21: 4.3571429 | H21: 5.3095238 | I21: 5.2619048
B22: 3. Unit Operations Stream | E22: 0 | F22: 0 | G22: 4.7619048 | H22: 6.2142857 | I22: 6.1666667
B23: 4. Communications Stream | E23: 0 | F23: 1 | G23: 0.95238095 | H23: 0.47619048 | I23: 0.19047619
B24: 5. Finance and Contract Management Stream | E24: 0 | F24: 0.71031746 | G24: 2.5047619 | H24: 2.9571429 | I24: 2.9571429
B25: 6. People Transfer Stream | E25: 0 | F25: 0 | G25: 2.2 | H25: 2 | I25: 1.2
B26: 7. Knowledge Transfer Stream | E26: 0 | F26: 0 | G26: 1 | H26: 1 | I26: 1
B27: TOTAL | E27: 0 | F27: 5.9007937 | G27: 17.680952 | H27: 19.861905 | I27: 18.680952 | J27: 0 | K27: 0 | L27: 0 | M27: 0 | N27: 0 | O27: 0 | P27: 0 | Q27: 0 | R27: 0 | T27: 0 | U27: 0 | V27: 0 | W27: 0 | X27: 0 | Y27: 0 | Z27: 0 | AA27: 0 | AB27: 0 | AC27: 0 | AD27: 0 | AE27: 0 | AG27: 0 | AH27: 0 | AI27: 0 | AJ27: 0 | AK27: 0 | AL27: 0 | AM27: 0 | AN27: 0 | AO27: 0 | AP27: 0 | AQ27: 0 | AR27: 0 | AT27: 0 | AU27: 0 | AV27: 0 | AW27: 0 | AX27: 0 | AY27: 0 | AZ27: 0 | BA27: 0 | BB27: 0 | BC27: 0 | BD27: 0 | BE27: 0
E29: HR prep | F29: Prep | H29: Transition
B30: Vendor Alpha | D30: Month -2 | E30: Month -1 | F30: Month 0 | G30: Month 1 | H30: Month 2 | I30: Month 3 | J30: Month 4 | K30: Month 5 | L30: Month 6 | M30: Month 7 | N30: Month 8 | O30: Month 9 | P30: Month 10 | Q30: Month 11 | R30: Month 12 | S30: Year 1 | T30: Month 13 | U30: Month 14 | V30: Month 15 | W30: Month 16 | X30: Month 17 | Y30: Month 18 | Z30: Month 19 | AA30: Month 20 | AB30: Month 21 | AC30: Month 22 | AD30: Month 23 | AE30: Month 24 | AF30: Year 2 | AG30: Month 25 | AH30: Month 26 | AI30: Month 27 | AJ30: Month 28 | AK30: Month 29 | AL30: Month 30 | AM30: Month 31 | AN30: Month 32 | AO30: Month 33 | AP30: Month 34 | AQ30: Month 35 | AR30: Month 36 | AS30: Year 3 | AT30: Month 37 | AU30: Month 38 | AV30: Month 39 | AW30: Month 40 | AX30: Month 41 | AY30: Month 42 | AZ30: Month 43 | BA30: Month 44 | BB30: Month 45 | BC30: Month 46 | BD30: Month 47 | BE30: Month 48 | BF30: Year 4 | BG30: Total
D31: (Euro) | E31: (Euro) | F31: (Euro) | G31: (Euro) | H31: (Euro) | I31: (Euro) | J31: (Euro) | K31: (Euro) | L31: (Euro) | M31: (Euro) | N31: (Euro) | O31: (Euro) | P31: (Euro) | Q31: (Euro) | R31: (Euro) | S31: (Euro) | T31: (Euro) | U31: (Euro) | V31: (Euro) | W31: (Euro) | X31: (Euro) | Y31: (Euro) | Z31: (Euro) | AA31: (Euro) | AB31: (Euro) | AC31: (Euro) | AD31: (Euro) | AE31: (Euro) | AF31: (Euro) | AG31: (Euro) | AH31: (Euro) | AI31: (Euro) | AJ31: (Euro) | AK31: (Euro) | AL31: (Euro) | AM31: (Euro) | AN31: (Euro) | AO31: (Euro) | AP31: (Euro) | AQ31: (Euro) | AR31: (Euro) | AS31: (Euro) | AT31: (Euro) | AU31: (Euro) | AV31: (Euro) | AW31: (Euro) | AX31: (Euro) | AY31: (Euro) | AZ31: (Euro) | BA31: (Euro) | BB31: (Euro) | BC31: (Euro) | BD31: (Euro) | BE31: (Euro) | BF31: (Euro) | BG31: (Euro)
B33: 1. Transition Program Management Stream | E33: 0 | F33: 58880 | G33: 58880 | H33: 58880 | I33: 58880 | J33: 0 | K33: 0 | L33: 0 | M33: 0 | N33: 0 | O33: 0 | P33: 0 | Q33: 0 | R33: 0 | S33: =SUM(E33:R33) | AF33: =SUM(T33:AE33) | AS33: 0 | BF33: 0 | BG33: 235520
B34: 2. Service Management Stream | E34: 0 | F34: 47424 | G34: 51072 | H34: 40128 | I34: 25536 | J34: 0 | K34: 0 | L34: 0 | M34: 0 | N34: 0 | O34: 0 | P34: 0 | Q34: 0 | R34: 0 | S34: =SUM(E34:R34) | AF34: =SUM(T34:AE34) | AS34: 0 | BF34: 0 | BG34: 164160
B35: 3. Unit Operations Stream | E35: 0 | F35: 34320 | G35: 137280 | H35: 62400 | I35: 49920 | J35: 0 | K35: 0 | L35: 0 | M35: 0 | N35: 0 | O35: 0 | P35: 0 | Q35: 0 | R35: 0 | S35: =SUM(E35:R35) | AF35: =SUM(T35:AE35) | AS35: 0 | BF35: 0 | BG35: 283920
B36: 4. Communications Stream | E36: 26520 | F36: 18720 | G36: 15600 | H36: 15600 | I36: 15600 | J36: 0 | K36: 0 | L36: 0 | M36: 0 | N36: 0 | O36: 0 | P36: 0 | Q36: 0 | R36: 0 | S36: =SUM(E36:R36) | AF36: =SUM(T36:AE36) | AS36: 0 | BF36: 0 | BG36: 92040
B37: 5. Finance and Contract Management Stream | E37: 0 | F37: 24960 | G37: 51480 | H37: 48360 | I37: 15600 | J37: 0 | K37: 0 | L37: 0 | M37: 0 | N37: 0 | O37: 0 | P37: 0 | Q37: 0 | R37: 0 | S37: =SUM(E37:R37) | AF37: =SUM(T37:AE37) | AS37: 0 | BF37: 0 | BG37: 140400
B38: 6. People Transfer Stream | E38: 56908.8 | F38: 29366.4 | G38: 46694.4 | H38: 79161.6 | I38: 99590.4 | J38: 0 | K38: 0 | L38: 0 | M38: 0 | N38: 0 | O38: 0 | P38: 0 | Q38: 0 | R38: 0 | S38: =SUM(E38:R38) | AF38: =SUM(T38:AE38) | AS38: 0 | BF38: 0 | BG38: 311721.6
B39: 7. Knowledge Transfer Stream | E39: 0 | F39: 3120 | G39: 28080 | H39: 53040 | I39: 28080 | J39: 0 | K39: 0 | L39: 0 | M39: 0 | N39: 0 | O39: 0 | P39: 0 | Q39: 0 | R39: 0 | S39: =SUM(E39:R39) | AF39: =SUM(T39:AE39) | AS39: 0 | BF39: 0 | BG39: 112320
B40: Communication Expenses | E40: 0 | F40: 40000 | G40: 30000 | H40: 20000 | I40: 10000 | J40: 0 | K40: 0 | L40: 0 | M40: 0 | N40: 0 | O40: 0 | P40: 0 | Q40: 0 | R40: 0 | S40: =SUM(E40:R40) | AF40: =SUM(T40:AE40) | AS40: 0 | BF40: 0 | BG40: 100000
B41: Expenses | E41: 20000 | F41: 25000 | G41: 25000 | H41: 25000 | I41: 25000 | J41: 0 | K41: 0 | L41: 0 | M41: 0 | N41: 0 | O41: 0 | P41: 0 | Q41: 0 | R41: 0 | S41: =SUM(E41:R41) | AF41: =SUM(T41:AE41) | AS41: 0 | BF41: 0 | BG41: 120000
B42: TOTAL | E42: =SUM(E33:E41) | F42: =SUM(F33:F41) | G42: =SUM(G33:G41) | H42: =SUM(H33:H41) | I42: =SUM(I33:I41) | J42: =SUM(J33:J41) | K42: =SUM(K33:K41) | L42: =SUM(L33:L41) | ... BG42: =SUM(BG33:BG41)
E44: HR prep | F44: Prep | H44: Transition
B45: Vendor Alpha | E45: Month -1 | F45: Month 0 | G45: Month 1 | H45: Month 2 | I45: Month 3 | J45: Month 4 | K45: Month 5 | L45: Month 6 | M45: Month 7 | N45: Month 8 | O45: Month 9 | P45: Month 10 | Q45: Month 11 | R45: Month 12 | T45: Month 13 | U45: Month 14 | V45: Month 15 | W45: Month 16 | X45: Month 17 | Y45: Month 18 | Z45: Month 19 | AA45: Month 20 | AB45: Month 21 | AC45: Month 22 | AD45: Month 23 | AE45: Month 24 | AG45: Month 25 | AH45: Month 26 | AI45: Month 27 | AJ45: Month 28 | AK45: Month 29 | AL45: Month 30 | AM45: Month 31 | AN45: Month 32 | AO45: Month 33 | AP45: Month 34 | AQ45: Month 35 | AR45: Month 36 | AT45: Month 37 | AU45: Month 38 | AV45: Month 39 | AW45: Month 40 | AX45: Month 41 | AY45: Month 42 | AZ45: Month 43 | BA45: Month 44 | BB45: Month 45 | BC45: Month 46 | BD45: Month 47 | BE45: Month 48
E46: FTE's | F46: FTE's | G46: FTE's | H46: FTE's | I46: FTE's | J46: FTE's | K46: FTE's | L46: FTE's | M46: FTE's | N46: FTE's | O46: FTE's | P46: FTE's | Q46: FTE's | R46: FTE's | T46: FTE's | U46: FTE's | V46: FTE's | W46: FTE's | X46: FTE's | Y46: FTE's | Z46: FTE's | AA46: FTE's | AB46: FTE's | AC46: FTE's | AD46: FTE's | AE46: FTE's | AG46: FTE's | AH46: FTE's | AI46: FTE's | AJ46: FTE's | AK46: FTE's | AL46: FTE's | AM46: FTE's | AN46: FTE's | AO46: FTE's | AP46: FTE's | AQ46: FTE's | AR46: FTE's | AT46: FTE's | AU46: FTE's | AV46: FTE's | AW46: FTE's | AX46: FTE's | AY46: FTE's | AZ46: FTE's | BA46: FTE's | BB46: FTE's | BC46: FTE's | BD46: FTE's | BE46: FTE's
B48: 1. Transition Program Management Stream | E48: 0 | F48: 4.8 | G48: 4.8 | H48: 4.8 | I48: 4.8
B49: 2. Service Management Stream | E49: 0 | F49: 3.9 | G49: 4.2 | H49: 3.3 | I49: 2.1
B50: 3. Unit Operations Stream | E50: 0 | F50: 3.3 | G50: 13.2 | H50: 6 | I50: 4.8
B51: 4. Communications Stream | E51: 2.55 | F51: 1.8 | G51: 1.5 | H51: 1.5 | I51: 1.5
B52: 5. Finance and Contract Management Stream | E52: 0 | F52: 2.4 | G52: 4.95 | H52: 4.65 | I52: 1.5
B53: 6. People Transfer Stream | E53: 4.68 | F53: 2.415 | G53: 3.84 | H53: 6.51 | I53: 8.19
B54: 7. Knowledge Transfer Stream | E54: 0 | F54: 0.3 | G54: 2.7 | H54: 5.1 | I54: 2.7
B55: TOTAL | E55: 7.23 | F55: 18.915 | G55: 35.19 | H55: 31.86 | I55: 25.59 | J55: 0 | K55: 0 | L55: 0 | M55: 0 | N55: 0 | O55: 0 | P55: 0 | Q55: 0 | R55: 0 | T55: 0 | U55: 0 | V55: 0 | W55: 0 | X55: 0 | Y55: 0 | Z55: 0 | AA55: 0 | AB55: 0 | AC55: 0 | AD55: 0 | AE55: 0 | AG55: 0 | AH55: 0 | AI55: 0 | AJ55: 0 | AK55: 0 | AL55: 0 | AM55: 0 | AN55: 0 | AO55: 0 | AP55: 0 | AQ55: 0 | AR55: 0 | AT55: 0 | AU55: 0 | AV55: 0 | AW55: 0 | AX55: 0 | AY55: 0 | AZ55: 0 | BA55: 0 | BB55: 0 | BC55: 0 | BD55: 0 | BE55: 0
E58: HR prep | F58: Prep | H58: Transition
B59: Vendor Gamma | D59: Month -2 | E59: Month -1 | F59: Month 0 | G59: Month 1 | H59: Month 2 | I59: Month 3 | J59: Month 4 | K59: Month 5 | L59: Month 6 | M59: Month 7 | N59: Month 8 | O59: Month 9 | P59: Month 10 | Q59: Month 11 | R59: Month 12 | S59: Year 1 | T59: Month 13 | U59: Month 14 | V59: Month 15 | W59: Month 16 | X59: Month 17 | Y59: Month 18 | Z59: Month 19 | AA59: Month 20 | AB59: Month 21 | AC59: Month 22 | AD59: Month 23 | AE59: Month 24 | AF59: Year 2 | AG59: Month 25 | AH59: Month 26 | AI59: Month 27 | AJ59: Month 28 | AK59: Month 29 | AL59: Month 30 | AM59: Month 31 | AN59: Month 32 | AO59: Month 33 | AP59: Month 34 | AQ59: Month 35 | AR59: Month 36 | AS59: Year 3 | AT59: Month 37 | AU59: Month 38 | AV59: Month 39 | AW59: Month 40 | AX59: Month 41 | AY59: Month 42 | AZ59: Month 43 | BA59: Month 44 | BB59: Month 45 | BC59: Month 46 | BD59: Month 47 | BE59: Month 48 | BF59: Year 4 | BG59: Total
D60: (Euro) | E60: (Euro) | F60: (Euro) | G60: (Euro) | H60: (Euro) | I60: (Euro) | J60: (Euro) | K60: (Euro) | L60: (Euro) | M60: (Euro) | N60: (Euro) | O60: (Euro) | P60: (Euro) | Q60: (Euro) | R60: (Euro) | S60: (Euro) | T60: (Euro) | U60: (Euro) | V60: (Euro) | W60: (Euro) | X60: (Euro) | Y60: (Euro) | Z60: (Euro) | AA60: (Euro) | AB60: (Euro) | AC60: (Euro) | AD60: (Euro) | AE60: (Euro) | AF60: (Euro) | AG60: (Euro) | AH60: (Euro) | AI60: (Euro) | AJ60: (Euro) | AK60: (Euro) | AL60: (Euro) | AM60: (Euro) | AN60: (Euro) | AO60: (Euro) | AP60: (Euro) | AQ60: (Euro) | AR60: (Euro) | AS60: (Euro) | AT60: (Euro) | AU60: (Euro) | AV60: (Euro) | AW60: (Euro) | AX60: (Euro) | AY60: (Euro) | AZ60: (Euro) | BA60: (Euro) | BB60: (Euro) | BC60: (Euro) | BD60: (Euro) | BE60: (Euro) | BF60: (Euro) | BG60: (Euro)
B61: 0. asset management licences | E61: 0 | F61: 210000 | G61: 0 | H61: 0 | I61: 0 | J61: 0 | K61: 0 | L61: 0 | M61: 0 | N61: 0 | O61: 0 | P61: 0 | Q61: 0 | R61: 0 | S61: =F61 | BG61: =S61
B62: 1. Transition Program Management Stream | E62: 0 | F62: 58432 | G62: 58432 | H62: 58432 | I62: 53356.8 | J62: 0 | K62: 0 | L62: 0 | M62: 0 | N62: 0 | O62: 0 | P62: 0 | Q62: 0 | R62: 0 | S62: =SUM(D62:R62) | AF62: =SUM(T62:AE62) | AS62: =SUM(AG62:AR62) | BF62: =SUM(AT62:BE62) | BG62: =SUM(AS62,AF62,S62,BF62)
B63: 2. Service Management Stream | E63: 0 | F63: 40972.8 | G63: 65964.8 | H63: 42598.4 | I63: 11360 | J63: 0 | K63: 0 | L63: 0 | M63: 0 | N63: 0 | O63: 0 | P63: 0 | Q63: 0 | R63: 0 | S63: =SUM(D63:R63) | AF63: =SUM(T63:AE63) | AS63: =SUM(AG63:AR63) | BF63: =SUM(AT63:BE63) | BG63: =SUM(AS63,AF63,S63,BF63)
B64: 3. Unit Operations Stream | E64: 0 | F64: 19891.2 | G64: 126182.4 | H64: 68640 | I64: 53849.6 | J64: 0 | K64: 0 | L64: 0 | M64: 0 | N64: 0 | O64: 0 | P64: 0 | Q64: 0 | R64: 0 | S64: =SUM(D64:R64) | AF64: =SUM(T64:AE64) | AS64: =SUM(AG64:AR64) | BF64: =SUM(AT64:BE64) | BG64: =SUM(AS64,AF64,S64,BF64)
B65: 4. Communications Stream | E65: 13440 | F65: 5376 | G65: 11827.2 | H65: 11827.2 | I65: 11827.2 | J65: 0 | K65: 0 | L65: 0 | M65: 0 | N65: 0 | O65: 0 | P65: 0 | Q65: 0 | R65: 0 | S65: =SUM(D65:R65) | AF65: =SUM(T65:AE65) | AS65: =SUM(AG65:AR65) | BF65: =SUM(AT65:BE65) | BG65: =SUM(AS65,AF65,S65,BF65)
B66: 5. Finance and Contract Management Stream | E66: 0 | F66: 12352 | G66: 157428.48 | H66: 160244.48 | I66: 139406.08 | J66: 0 | K66: 0 | L66: 0 | M66: 0 | N66: 0 | O66: 0 | P66: 0 | Q66: 0 | R66: 0 | S66: =SUM(D66:R66) | AF66: =SUM(T66:AE66) | AS66: =SUM(AG66:AR66) | BF66: =SUM(AT66:BE66) | BG66: =SUM(AS66,AF66,S66,BF66)
B67: 6. People Transfer Stream | E67: 46592 | F67: 36691.2 | G67: 52416 | H67: 58240 | I67: 40768 | J67: 0 | K67: 0 | L67: 0 | M67: 0 | N67: 0 | O67: 0 | P67: 0 | Q67: 0 | R67: 0 | S67: =SUM(D67:R67) | AF67: =SUM(T67:AE67) | AS67: =SUM(AG67:AR67) | BF67: =SUM(AT67:BE67) | BG67: =SUM(AS67,AF67,S67,BF67)
B68: 7. Knowledge Transfer Stream | E68: 0 | F68: 0 | G68: 61737.6 | H68: 57369.6 | I68: 8448 | J68: 0 | K68: 0 | L68: 0 | M68: 0 | N68: 0 | O68: 0 | P68: 0 | Q68: 0 | R68: 0 | S68: =SUM(D68:R68) | AF68: =SUM(T68:AE68) | AS68: =SUM(AG68:AR68) | BF68: =SUM(AT68:BE68) | BG68: =SUM(AS68,AF68,S68,BF68)
B69: TOTAL | E69: =SUM(E61:E68) | F69: =SUM(F61:F68) | G69: =SUM(G61:G68) | H69: =SUM(H61:H68) | I69: =SUM(I61:I68) | J69: =SUM(J61:J68) | K69: =SUM(K61:K68) | L69: =SUM(L61:L68) | ... BG69: =SUM(BG61:BG68)
E71: HR prep | F71: Prep | H71: Transition
B72: Vendor Gamma | E72: Month -1 | F72: Month 0 | G72: Month 1 | H72: Month 2 | I72: Month 3 | J72: Month 4 | K72: Month 5 | L72: Month 6 | M72: Month 7 | N72: Month 8 | O72: Month 9 | P72: Month 10 | Q72: Month 11 | R72: Month 12 | T72: Month 13 | U72: Month 14 | V72: Month 15 | W72: Month 16 | X72: Month 17 | Y72: Month 18 | Z72: Month 19 | AA72: Month 20 | AB72: Month 21 | AC72: Month 22 | AD72: Month 23 | AE72: Month 24 | AG72: Month 25 | AH72: Month 26 | AI72: Month 27 | AJ72: Month 28 | AK72: Month 29 | AL72: Month 30 | AM72: Month 31 | AN72: Month 32 | AO72: Month 33 | AP72: Month 34 | AQ72: Month 35 | AR72: Month 36 | AT72: Month 37 | AU72: Month 38 | AV72: Month 39 | AW72: Month 40 | AX72: Month 41 | AY72: Month 42 | AZ72: Month 43 | BA72: Month 44 | BB72: Month 45 | BC72: Month 46 | BD72: Month 47 | BE72: Month 48
E73: FTE's | F73: FTE's | G73: FTE's | H73: FTE's | I73: FTE's | J73: FTE's | K73: FTE's | L73: FTE's | M73: FTE's | N73: FTE's | O73: FTE's | P73: FTE's | Q73: FTE's | R73: FTE's | T73: FTE's | U73: FTE's | V73: FTE's | W73: FTE's | X73: FTE's | Y73: FTE's | Z73: FTE's | AA73: FTE's | AB73: FTE's | AC73: FTE's | AD73: FTE's | AE73: FTE's | AG73: FTE's | AH73: FTE's | AI73: FTE's | AJ73: FTE's | AK73: FTE's | AL73: FTE's | AM73: FTE's | AN73: FTE's | AO73: FTE's | AP73: FTE's | AQ73: FTE's | AR73: FTE's | AT73: FTE's | AU73: FTE's | AV73: FTE's | AW73: FTE's | AX73: FTE's | AY73: FTE's | AZ73: FTE's | BA73: FTE's | BB73: FTE's | BC73: FTE's | BD73: FTE's | BE73: FTE's
B75: 1. Transition Program Management Stream | E75: 0 | F75: 6 | G75: 6 | H75: 6 | I75: 5.4090909
B76: 2. Service Management Stream | E76: 0 | F76: 3.2727273 | G76: 5.2727273 | H76: 2.9090909 | I76: 0.90909091
B77: 3. Unit Operations Stream | E77: 0 | F77: 1.6818182 | G77: 12.454545 | H77: 7.5 | I77: 5.6818182
B78: 4. Communications Stream | E78: 1.1363636 | F78: 0.45454545 | G78: 1 | H78: 1 | I78: 1
B79: 5. Finance and Contract Management Stream | E79: 0 | F79: 1.1363636 | G79: 25.754545 | H79: 25.981818 | I79: 24.209091
B80: 6. People Transfer Stream | E80: 3.6363636 | F80: 2.8636364 | G80: 4.0909091 | H80: 4.5454545 | I80: 3.1818182
B81: 7. Knowledge Transfer Stream | E81: 0 | F81: 0 | G81: 5.1590909 | H81: 4.8181818 | I81: 1
B82: TOTAL | E82: 4.7727273 | F82: 15.409091 | G82: 59.731818 | H82: 52.754545 | I82: 41.390909 | J82: 0 | K82: 0 | L82: 0 | M82: 0 | N82: 0 | O82: 0 | P82: 0 | Q82: 0 | R82: 0 | T82: 0 | U82: 0 | V82: 0 | W82: 0 | X82: 0 | Y82: 0 | Z82: 0 | AA82: 0 | AB82: 0 | AC82: 0 | AD82: 0 | AE82: 0 | AG82: 0 | AH82: 0 | AI82: 0 | AJ82: 0 | AK82: 0 | AL82: 0 | AM82: 0 | AN82: 0 | AO82: 0 | AP82: 0 | AQ82: 0 | AR82: 0 | AT82: 0 | AU82: 0 | AV82: 0 | AW82: 0 | AX82: 0 | AY82: 0 | AZ82: 0 | BA82: 0 | BB82: 0 | BC82: 0 | BD82: 0 | BE82: 0
E85: HR prep | F85: Prep | H85: Transition
B86: TelCo | D86: Month -2 | E86: Month -1 | F86: Month 0 | G86: Month 1 | H86: Month 2 | I86: Month 3 | J86: Month 4 | K86: Month 5 | L86: Month 6 | M86: Month 7 | N86: Month 8 | O86: Month 9 | P86: Month 10 | Q86: Month 11 | R86: Month 12 | S86: Year 1 | T86: Month 13 | U86: Month 14 | V86: Month 15 | W86: Month 16 | X86: Month 17 | Y86: Month 18 | Z86: Month 19 | AA86: Month 20 | AB86: Month 21 | AC86: Month 22 | AD86: Month 23 | AE86: Month 24 | AF86: Year 2 | AG86: Month 25 | AH86: Month 26 | AI86: Month 27 | AJ86: Month 28 | AK86: Month 29 | AL86: Month 30 | AM86: Month 31 | AN86: Month 32 | AO86: Month 33 | AP86: Month 34 | AQ86: Month 35 | AR86: Month 36 | AS86: Year 3 | AT86: Month 37 | AU86: Month 38 | AV86: Month 39 | AW86: Month 40 | AX86: Month 41 | AY86: Month 42 | AZ86: Month 43 | BA86: Month 44 | BB86: Month 45 | BC86: Month 46 | BD86: Month 47 | BE86: Month 48 | BF86: Year 4 | BG86: Total
D87: (Euro) | E87: (Euro) | F87: (Euro) | G87: (Euro) | H87: (Euro) | I87: (Euro) | J87: (Euro) | K87: (Euro) | L87: (Euro) | M87: (Euro) | N87: (Euro) | O87: (Euro) | P87: (Euro) | Q87: (Euro) | R87: (Euro) | S87: (Euro) | T87: (Euro) | U87: (Euro) | V87: (Euro) | W87: (Euro) | X87: (Euro) | Y87: (Euro) | Z87: (Euro) | AA87: (Euro) | AB87: (Euro) | AC87: (Euro) | AD87: (Euro) | AE87: (Euro) | AF87: (Euro) | AG87: (Euro) | AH87: (Euro) | AI87: (Euro) | AJ87: (Euro) | AK87: (Euro) | AL87: (Euro) | AM87: (Euro) | AN87: (Euro) | AO87: (Euro) | AP87: (Euro) | AQ87: (Euro) | AR87: (Euro) | AS87: (Euro) | AT87: (Euro) | AU87: (Euro) | AV87: (Euro) | AW87: (Euro) | AX87: (Euro) | AY87: (Euro) | AZ87: (Euro) | BA87: (Euro) | BB87: (Euro) | BC87: (Euro) | BD87: (Euro) | BE87: (Euro) | BF87: (Euro) | BG87: (Euro)
B89: 1. Transition Program Management Stream | E89: 0 | F89: 22500 | G89: 0 | H89: 0 | I89: 0 | J89: 0 | K89: 0 | L89: 0 | M89: 0 | N89: 0 | O89: 0 | P89: 0 | Q89: 0 | R89: 0 | S89: =SUM(E89:R89) | AF89: =SUM(T89:AE89) | AS89: =SUM(AG89:AR89) | BF89: =SUM(AT89:BE89) | BG89: =SUM(AS89,AF89,S89,BF89)
B90: 2. Service Management Stream | E90: 0 | F90: 9000 | G90: 71130 | H90: 33130 | I90: 10000 | J90: 0 | K90: 0 | L90: 0 | M90: 0 | N90: 0 | O90: 0 | P90: 0 | Q90: 0 | R90: 0 | S90: =SUM(E90:R90) | AF90: =SUM(T90:AE90) | AS90: =SUM(AG90:AR90) | BF90: =SUM(AT90:BE90) | BG90: =SUM(AS90,AF90,S90,BF90)
B91: 3. Unit Operations Stream | E91: 0 | F91: 13500 | G91: 109260 | H91: 71760 | I91: 0 | J91: 0 | K91: 0 | L91: 0 | M91: 0 | N91: 0 | O91: 0 | P91: 0 | Q91: 0 | R91: 0 | S91: =SUM(E91:R91) | AF91: =SUM(T91:AE91) | AS91: =SUM(AG91:AR91) | BF91: =SUM(AT91:BE91) | BG91: =SUM(AS91,AF91,S91,BF91)
B92: 4. Communications Stream | E92: 0 | F92: 8010 | G92: 6390 | H92: 12870 | I92: 0 | J92: 0 | K92: 0 | L92: 0 | M92: 0 | N92: 0 | O92: 0 | P92: 0 | Q92: 0 | R92: 0 | S92: =SUM(E92:R92) | AF92: =SUM(T92:AE92) | AS92: =SUM(AG92:AR92) | BF92: =SUM(AT92:BE92) | BG92: =SUM(AS92,AF92,S92,BF92)
B93: 5. Finance and Contract Management Stream | E93: 0 | F93: 12600 | G93: 30520 | H93: 31060 | I93: 8600 | J93: 0 | K93: 0 | L93: 0 | M93: 0 | N93: 0 | O93: 0 | P93: 0 | Q93: 0 | R93: 0 | S93: =SUM(E93:R93) | AF93: =SUM(T93:AE93) | AS93: =SUM(AG93:AR93) | BF93: =SUM(AT93:BE93) | BG93: =SUM(AS93,AF93,S93,BF93)
B94: 6. People Transfer Stream | E94: 0 | F94: 9540 | G94: 27000 | H94: 50220 | I94: 0 | J94: 0 | K94: 0 | L94: 0 | M94: 0 | N94: 0 | O94: 0 | P94: 0 | Q94: 0 | R94: 0 | S94: =SUM(E94:R94) | AF94: =SUM(T94:AE94) | AS94: =SUM(AG94:AR94) | BF94: =SUM(AT94:BE94) | BG94: =SUM(AS94,AF94,S94,BF94)
B95: 7. Knowledge Transfer Stream | E95: 0 | F95: 0 | G95: 25650 | H95: 8460 | I95: 4500 | J95: 0 | K95: 0 | L95: 0 | M95: 0 | N95: 0 | O95: 0 | P95: 0 | Q95: 0 | R95: 0 | S95: =SUM(E95:R95) | AF95: =SUM(T95:AE95) | AS95: =SUM(AG95:AR95) | BF95: =SUM(AT95:BE95) | BG95: =SUM(AS95,AF95,S95,BF95)
B96: TOTAL | E96: =SUM(E89:E95) | F96: =SUM(F89:F95) | G96: =SUM(G89:G95) | H96: =SUM(H89:H95) | I96: =SUM(I89:I95) | J96: =SUM(J89:J95) | K96: =SUM(K89:K95) | L96: =SUM(L89:L95) | ... BG96: =SUM(BG89:BG95)
E98: HR prep | F98: Prep | H98: Transition
B99: TelCo | E99: Month -1 | F99: Month 0 | G99: Month 1 | H99: Month 2 | I99: Month 3 | J99: Month 4 | K99: Month 5 | L99: Month 6 | M99: Month 7 | N99: Month 8 | O99: Month 9 | P99: Month 10 | Q99: Month 11 | R99: Month 12 | T99: Month 13 | U99: Month 14 | V99: Month 15 | W99: Month 16 | X99: Month 17 | Y99: Month 18 | Z99: Month 19 | AA99: Month 20 | AB99: Month 21 | AC99: Month 22 | AD99: Month 23 | AE99: Month 24 | AG99: Month 25 | AH99: Month 26 | AI99: Month 27 | AJ99: Month 28 | AK99: Month 29 | AL99: Month 30 | AM99: Month 31 | AN99: Month 32 | AO99: Month 33 | AP99: Month 34 | AQ99: Month 35 | AR99: Month 36 | AT99: Month 37 | AU99: Month 38 | AV99: Month 39 | AW99: Month 40 | AX99: Month 41 | AY99: Month 42 | AZ99: Month 43 | BA99: Month 44 | BB99: Month 45 | BC99: Month 46 | BD99: Month 47 | BE99: Month 48
E100: FTE's | F100: FTE's | G100: FTE's | H100: FTE's | I100: FTE's | J100: FTE's | K100: FTE's | L100: FTE's | M100: FTE's | N100: FTE's | O100: FTE's | P100: FTE's | Q100: FTE's | R100: FTE's | T100: FTE's | U100: FTE's | V100: FTE's | W100: FTE's | X100: FTE's | Y100: FTE's | Z100: FTE's | AA100: FTE's | AB100: FTE's | AC100: FTE's | AD100: FTE's | AE100: FTE's | AG100: FTE's | AH100: FTE's | AI100: FTE's | AJ100: FTE's | AK100: FTE's | AL100: FTE's | AM100: FTE's | AN100: FTE's | AO100: FTE's | AP100: FTE's | AQ100: FTE's | AR100: FTE's | AT100: FTE's | AU100: FTE's | AV100: FTE's | AW100: FTE's | AX100: FTE's | AY100: FTE's | AZ100: FTE's | BA100: FTE's | BB100: FTE's | BC100: FTE's | BD100: FTE's | BE100: FTE's
B102: 1. Transition Program Management Stream | E102: 0 | F102: 1.875 | G102: 0 | H102: 0 | I102: 0
B103: 2. Service Management Stream | E103: 0 | F103: 0.75 | G103: 5.9275 | H103: 2.7608333 | I103: 0.83333333
B104: 3. Unit Operations Stream | E104: 0 | F104: 1.125 | G104: 9.105 | H104: 5.98 | I104: 0
B105: 4. Communications Stream | E105: 0 | F105: 0.6675 | G105: 0.5325 | H105: 1.0725 | I105: 0
B106: 5. Finance and Contract Management Stream | E106: 0 | F106: 1.05 | G106: 2.5433333 | H106: 2.5883333 | I106: 0.71666667
B107: 6. People Transfer Stream | E107: 0 | F107: 0.795 | G107: 2.25 | H107: 4.185 | I107: 0
B108: 7. Knowledge Transfer Stream | E108: 0 | F108: 0 | G108: 2.1375 | H108: 0.705 | I108: 0.375
B109: TOTAL | E109: 0 | F109: =SUM(F102:F108) | G109: =SUM(G102:G108) | H109: =SUM(H102:H108) | I109: =SUM(I102:I108) | J109: 0 | K109: 0 | L109: 0 | M109: 0 | N109: 0 | O109: 0 | P109: 0 | Q109: 0 | R109: 0 | S109: 0 | T109: 0 | U109: 0 | V109: 0 | W109: 0 | X109: 0 | Y109: 0 | Z109: 0 | AA109: 0 | AB109: 0 | AC109: 0 | AD109: 0 | AE109: 0 | AF109: 0 | AG109: 0 | AH109: 0 | AI109: 0 | AJ109: 0 | AK109: 0 | AL109: 0 | AM109: 0 | AN109: 0 | AO109: 0 | AP109: 0 | AQ109: 0 | AR109: 0 | AS109: 0 | AT109: 0 | AU109: 0 | AV109: 0 | AW109: 0 | AX109: 0 | AY109: 0 | AZ109: 0 | BA109: 0 | BB109: 0 | BC109: 0 | BD109: 0 | BE109: 0 | BF109: 0 | BG109: 0
B111: Total Transformation phase
I112: Transformation
B113: 2IM | D113: Month -2 | E113: Month -1 | F113: Month 0 | G113: Month 1 | H113: Month 2 | I113: Month 3 | J113: Month 4 | K113: Month 5 | L113: Month 6 | M113: Month 7 | N113: Month 8 | O113: Month 9 | P113: Month 10 | Q113: Month 11 | R113: Month 12 | S113: Year 1 | T113: Month 13 | U113: Month 14 | V113: Month 15 | W113: Month 16 | X113: Month 17 | Y113: Month 18 | Z113: Month 19 | AA113: Month 20 | AB113: Month 21 | AC113: Month 22 | AD113: Month 23 | AE113: Month 24 | AF113: Year 2 | AG113: Month 25 | AH113: Month 26 | AI113: Month 27 | AJ113: Month 28 | AK113: Month 29 | AL113: Month 30 | AM113: Month 31 | AN113: Month 32 | AO113: Month 33 | AP113: Month 34 | AQ113: Month 35 | AR113: Month 36 | AS113: Year 3 | AT113: Month 37 | AU113: Month 38 | AV113: Month 39 | AW113: Month 40 | AX113: Month 41 | AY113: Month 42 | AZ113: Month 43 | BA113: Month 44 | BB113: Month 45 | BC113: Month 46 | BD113: Month 47 | BE113: Month 48 | BF113: Year 4 | BG113: Total
D114: (Euro) | E114: (Euro) | F114: (Euro) | G114: (Euro) | H114: (Euro) | I114: (Euro) | J114: (Euro) | K114: (Euro) | L114: (Euro) | M114: (Euro) | N114: (Euro) | O114: (Euro) | P114: (Euro) | Q114: (Euro) | R114: (Euro) | S114: (Euro) | T114: (Euro) | U114: (Euro) | V114: (Euro) | W114: (Euro) | X114: (Euro) | Y114: (Euro) | Z114: (Euro) | AA114: (Euro) | AB114: (Euro) | AC114: (Euro) | AD114: (Euro) | AE114: (Euro) | AF114: (Euro) | AG114: (Euro) | AH114: (Euro) | AI114: (Euro) | AJ114: (Euro) | AK114: (Euro) | AL114: (Euro) | AM114: (Euro) | AN114: (Euro) | AO114: (Euro) | AP114: (Euro) | AQ114: (Euro) | AR114: (Euro) | AS114: (Euro) | AT114: (Euro) | AU114: (Euro) | AV114: (Euro) | AW114: (Euro) | AX114: (Euro) | AY114: (Euro) | AZ114: (Euro) | BA114: (Euro) | BB114: (Euro) | BC114: (Euro) | BD114: (Euro) | BE114: (Euro) | BF114: (Euro) | BG114: (Euro)
E115: 0 | F115: 0 | G115: 0 | H115: 0 | I115: 0 | J115: 0 | K115: 0 | L115: 0 | M115: 0 | N115: 0 | O115: 0 | P115: 0 | Q115: 0 | R115: 0
B116: 1. From As to Be | E116: 0 | F116: 0 | G116: 0 | H116: 0 | I116: 0 | J116: 386618.64 | K116: 373457 | L116: 256262.76 | M116: 95097.508 | N116: 70071.848 | O116: 58949.332 | P116: 0 | Q116: 0 | R116: 0 | S116: =SUM(E116:R116) | T116: 0 | U116: 0 | V116: 0 | W116: 0 | X116: 0 | Y116: 0 | Z116: 0 | AA116: 0 | AB116: 0 | AC116: 0 | AD116: 0 | AE116: 0 | AF116: =SUM(T116:AE116) | AS116: =SUM(AG116:AR116) | BF116: =SUM(AT116:BE116) | BG116: =SUM(AS116,AF116,S116,BF116)
B117: 2. Business Continuity Planning (BCP) / Disaster Recovery (DR) (CAP €789.000) | E117: 0 | F117: 0 | G117: 0 | H117: 0 | I117: 0 | J117: 0 | K117: 0 | L117: 80000 | M117: 80000 | N117: 40000 | O117: 0 | P117: 0 | Q117: 0 | R117: 0 | S117: =SUM(E117:R117) | W117: 0 | X117: 0 | Y117: 0 | Z117: 0 | AA117: 0 | AB117: 0 | AC117: 0 | AD117: 0 | AE117: 0 | AF117: =SUM(T117:AE117) | AS117: =SUM(AG117:AR117) | BF117: =SUM(AT117:BE117) | BG117: =SUM(AS117,AF117,S117,BF117)
B118: 3. ITIL (CAP €996.000) | E118: 0 | F118: 0 | G118: 0 | H118: 0 | I118: 0 | J118: 0 | K118: 0 | L118: 80000 | M118: 80000 | N118: 40000 | O118: 0 | P118: 0 | Q118: 0 | R118: 0 | S118: =SUM(E118:R118) | AF118: =SUM(T118:AE118) | AS118: =SUM(AG118:AR118) | BF118: =SUM(AT118:BE118) | BG118: =SUM(AS118,AF118,S118,BF118)
...

Sheet Facilities
A6: Neptune - EuroBank located employees
A7: Date: | B7: 38683
A9: The Table below gives an overview of the averageNeptune employees per bundle, per country, working at EuroBank locations. Besides the number per year, also an explanation is given on whether housing costs at PST member premises is already included in our cost
A11: PST member | B11: Bundle | C11: Country | D11: Number of PST Supplier employees, working from EuroBank locations | I11: Did you also include 'm2 costs' for these employees in your pricing?
D12: Year 1 | E12: Year 2 | F12: Year 3 | G12: Year 4 | H12: Year 5
A13: Vendor Beta | B13: 2IM5 | C13: NL | D13: 20 | E13: 20 | F13: 20 | G13: 19 | H13: 18 | I13: No
C14: BE | D14: 4 | E14: 4 | F14: 4 | G14: 4 | H14: 3 | I14: No
A15: TelCo | B15: Voice | C15: NL | D15: 27 | E15: 5 | F15: 5 | G15: 5 | H15: 5 | I15: No
C16: BE | D16: 4 | E16: 2 | F16: 2 | G16: 2 | H16: 2 | I16: No
B17: LAN | C17: NL | D17: 3 | E17: 0 | F17: 0 | G17: 0 | H17: 0 | I17: No
C18: BE | D18: 0.5 | E18: 0 | F18: 0 | G18: 0 | H18: 0 | I18: No
A19: Vendor Alpha | B19: EUC-D&S | C19: NL | D19: 20 | E19: 2 | F19: 0 | G19: 0 | H19: 0 | I19: Yes
C20: BE | D20: 6 | E20: 1 | F20: 0 | G20: 0 | H20: 0 | I20: Yes
B21: EUC-UAS | C21: NL | D21: 28 | E21: 3 | F21: 0 | G21: 0 | H21: 0 | I21: Yes
C22: BE | D22: 9 | E22: 1 | F22: 0 | G22: 0 | H22: 0 | I22: Yes
B23: EUC-AS | C23: NL | D23: 34 | E23: 3 | F23: 0 | G23: 0 | H23: 0 | I23: Yes
C24: BE | D24: 11 | E24: 1 | F24: 0 | G24: 0 | H24: 0 | I24: Yes
B25: Server Management | C25: NL | D25: 26 | E25: 3 | F25: 0 | G25: 0 | H25: 0 | I25: Yes
C26: BE | D26: 8 | E26: 1 | F26: 0 | G26: 0 | H26: 0 | I26: Yes
A27: Vendor Gamma PinkRoccade | B27: Service Desk | C27: NL | D27: 98 | E27: =D27/4 | F27: 0 | G27: 0 | H27: 0 | I27: Yes
C28: BE | D28: 37 | E28: =D28/4 | F28: 0 | G28: 0 | H28: 0 | I28: Yes
B29: EUC-UIS | C29: NL | D29: 1.4 | E29: 1.4 | F29: 1.4 | G29: 1.4 | H29: 1.4 | I29: No
C30: BE | D30: 0 | E30: 0 | F30: 0 | G30: 0 | H30: 0 | I30: No
B31: DT-HW | C31: NL | D31: 0 | E31: 0 | F31: 0 | G31: 0 | H31: 0 | I31: No
C32: BE | D32: 0 | E32: 0 | F32: 0 | G32: 0 | H32: 0 | I32: No
A34: Note 1: Housing costs are only compensated for employees who spend all their working hours at EuroBank locations.
A35: Note 2: FTE's related to projects members, working at EuroBank premises, are not included in this calculation
A36: Note 3: On site transitioned EuroBank FTEs to be rationalized after Effective Date in line with Exhibit 5
A42: Reimbursement of facility costs
A44: Vendor Alpha | B44: EUC-D&S | C44: NL | D44: =D19*-$B$57 | E44: =E19*-$B$57
C45: BE | D45: =D20*-$B$57 | E45: =E20*-$B$57
B46: EUC-UAS | C46: NL | D46: =D21*-$B$57 | E46: =E21*-$B$57
C47: BE | D47: =D22*-$B$57 | E47: =E22*-$B$57
B48: EUC-AS | C48: NL | D48: =D23*-$B$57 | E48: =E23*-$B$57
C49: BE | D49: =D24*-$B$57 | E49: =E24*-$B$57
B50: Server Management | C50: NL | D50: =D25*-$B$57 | E50: =E25*-$B$57
C51: BE | D51: =D26*-$B$57 | E51: =E26*-$B$57
A52: Vendor Gamma | B52: Service Desk | C52: NL | D52: =D27*-$B$56 | E52: =E27*-$B$56
C53: BE | D53: =D28*-$B$56 | E53: =E28*-$B$56
A54: Total | D54: =SUM(D44:D53) | E54: =SUM(E44:E53)
A56: GTN facilities | B56: 2500 | C56: per full time fte per year
A57: VENDORA Facilities | B57: 4850 | C57: per full time fte per year

Sheet Acquisition of Assets
C1: Acquisition of Legacy Assets
E2: Amounts quoted herein are included in the Base Charges
D3: Initial Asset Purchase excl VAT - aligned with MATA | E3: Year 1 | F3: Year 2 | G3: Year 3 | H3: Year 4 | I3: Year 5 | J3: Total 5 Years including finance costs
C5: Total Assets Acquired - NBV
C6: EUC | J6: =SUM(E6:I6)
C8: Service Desk | J8: =SUM(E8:I8)
C10: LAN Services - NL | D10: 1134100 | E10: 1170044.5 | F10: 0 | G10: 0 | H10: 0 | I10: 0 | J10: =SUM(E10:I10)
C12: Voice Services - NL | D12: 2647120 | E12: 611165.15 | F12: 611165.15 | G12: 611165.15 | H12: 611165.15 | I12: 611165.15 | J12: =SUM(E12:I12)
C13: Voice Services - Be | D13: 956844 | E13: 220915.47 | F13: 220915.47 | G13: 220915.47 | H13: 220915.47 | I13: 220915.47 | J13: =SUM(E13:I13)
C14: Desktop Hardware | J14: =SUM(E14:I14)
C16: Server Management | J16: =SUM(E16:I16)
C18: 2IM | J18: =SUM(E18:I18)
C20: Cost of Money | J20: =SUM(E20:I20)
C22: Overhead | J22: =SUM(E22:I22)
C24: Other | J24: =SUM(E24:I24)
B28: TOTAL Charge | D28: =SUM(D5:D26) | E28: =SUM(E5:E26) | F28: =SUM(F5:F26) | G28: =SUM(G5:G26) | H28: =SUM(H5:H26) | I28: =SUM(I5:I26) | J28: =SUM(E28:I28)

Sheet PST Investments
B1: PST Supplier Investments (incl. refresh)
C3: Initial Asset Purchase | D3: Year 1 | E3: Year 2 | F3: Year 3 | G3: Year 4 | H3: Year 5 | I3: Total 5 Years
B5: EUC Assets | D5: 294000 | I5: =SUM(C5:H5)
B7: Service Desk Assets | I7: =SUM(C7:H7)
B9: LAN Assets | E9: 5440000 | I9: =SUM(C9:H9)
B11: Voice Assets | D11: 4400000 | E11: 1000000 | F11: 1000000 | G11: 1000000 | I11: =SUM(C11:H11)
B13: Desktop Hardware Assets | D13: 22089435 | E13: 8389138.3 | F13: 10641323 | G13: 22089435 | H13: 8389138.3 | I13: =SUM(C13:H13)
B15: Server Management Assets | D15: 2137933.5 | E15: 2128486.5 | F15: 3782288.5 | G15: 2137933.5 | H15: 2128486.5 | I15: =SUM(C15:H15)
B17: 2IM | I17: =SUM(C17:H17)
B19: Other Investments | I19: =SUM(C19:H19)
A21: TOTAL INVESTMENTS | C21: =SUM(C5:C19) | D21: =SUM(D5:D19) | E21: =SUM(E5:E19) | F21: =SUM(F5:F19) | G21: =SUM(G5:G19) | H21: =SUM(H5:H19) | I21: =SUM(C21:H21)

Sheet Pass Through overview
A1: Bundle | B1: Country | C1: Description | D1: I = Investment L = Lease C = Contract D = Direct Expence | E1: Investment amount | F1: Start Date (month) | G1: Duration (months) | H1: Y1 | I1: Y2 | J1: Y3 | K1: Y4 | L1: Y5
C2: Subtotals
C3: LAN | H3: =SUM(H10:H14) | I3: =SUM(I10:I14) | J3: =SUM(J10:J14) | K3: =SUM(K10:K14) | L3: =SUM(L10:L14)
C4: Voice | H4: =SUM(H17:H34) | I4: =SUM(I17:I34) | J4: =SUM(J17:J34) | K4: =SUM(K17:K34) | L4: =SUM(L17:L34)
C5: Desktop HW | H5: =SUM(H36:H149) | I5: =SUM(I36:I149) | J5: =SUM(J36:J149) | K5: =SUM(K36:K149) | L5: =SUM(L36:L149)
C6: Server | H6: =SUM(H151:H201) | I6: =SUM(I151:I201) | J6: =SUM(J151:J201) | K6: =SUM(K151:K201) | L6: =SUM(L151:L201)
C7: 2IM | H7: =SUM(H203:H204) | I7: =SUM(I203:I204) | J7: =SUM(J203:J204) | K7: =SUM(K203:K204) | L7: =SUM(L203:L204)
C8: Grand Total | H8: =SUM(H3:H7) | I8: =SUM(I3:I7) | J8: =SUM(J3:J7) | K8: =SUM(K3:K7) | L8: =SUM(L3:L7)
A10: LAN | B10: NL | D10: I | E10: 0 | H10: 0 | I10: 0 | J10: 0 | K10: 0
A11: LAN | B11: NL | C11: Management connections | D11: C | H11: 196512 | I11: 196512 | J11: 196512 | K11: 196512 | L11: 196512
A13: LAN | B13: BE | D13: I | E13: 0 | H13: 0 | I13: 0 | J13: 0 | K13: 0
A14: LAN | B14: BE
A17: Voice | B17: NL | C17: Refresh | D17: I
A18: Voice | B18: NL | D18: I
A19: Voice | B19: NL | D19: I
A20: Voice | B20: NL | D20: I
A21: Voice | B21: NL | D21: I
A22: Voice | B22: NL | D22: I
A23: Voice | B23: NL | D23: I
A24: Voice | B24: NL | C24: Acquisition assets (excl. Fin costs) | D24: I
A27: Voice | B27: BE | C27: Refresh | D27: I
A28: Voice | B28: BE | D28: I
A29: Voice | B29: BE | D29: I
A30: Voice | B30: BE | D30: I
A31: Voice | B31: BE | D31: I
A32: Voice | B32: BE | D32: I
A33: Voice | B33: BE | D33: I
A34: Voice | B34: BE | C34: Acquisition assets (excl. Fin costs) | D34: I
A36: Desktop HW | B36: NL | C36: Desktop | D36: L | E36: 11735935 | F36: 1 | G36: 36 | H36: 3298267.2 | I36: 3298267.2 | J36: 3298267.2
A37: Desktop HW | B37: NL | C37: Desktop | D37: L | E37: 1117723 | F37: 13 | G37: 36 | I37: 314124.87 | J37: 314124.87 | K37: 314124.87
A38: Desktop HW | B38: NL | C38: Desktop | D38: L | E38: 262607 | F38: 25 | G38: 36 | J38: 73803.071 | K38: 73803.071 | L38: 73803.071
A39: Desktop HW | B39: NL | C39: Desktop | D39: L | E39: 11735935 | F39: 37 | G39: 36 | K39: 3298267.2 | L39: 3298267.2
A40: Desktop HW | B40: NL | C40: Desktop | D40: L | E40: 1117723 | F40: 49 | G40: 36 | L40: 314124.87
A41: Desktop HW | B41: NL | C41: Laptop | D41: L | E41: 705795 | F41: 1 | G41: 36 | H41: 198356.63 | I41: 198356.63 | J41: 198356.63
A42: Desktop HW | B42: NL | C42: Laptop | D42: L | E42: 2010345 | F42: 13 | G42: 36 | I42: 564987.36 | J42: 564987.36 | K42: 564987.36
A43: Desktop HW | B43: NL | C43: Laptop | D43: L | E43: 331824 | F43: 25 | G43: 36 | J43: 93255.817 | K43: 93255.817 | L43: 93255.817
A44: Desktop HW | B44: NL | C44: Laptop | D44: L | E44: 705795 | F44: 37 | G44: 36 | K44: 198356.63 | L44: 198356.63
A45: Desktop HW | B45: NL | C45: Laptop | D45: L | E45: 2010345 | F45: 49 | G45: 36 | L45: 564987.36
A46: Desktop HW | B46: NL | C46: Monitor | D46: L | E46: 4063015 | F46: 1 | G46: 36 | H46: 1141869.7 | I46: 1141869.7 | J46: 1141869.7
A47: Desktop HW | B47: NL | C47: Monitor | D47: L | E47: 973710 | F47: 13 | G47: 36 | I47: 273651.46 | J47: 273651.46 | K47: 273651.46
A48: Desktop HW | B48: NL | C48: Monitor | D48: L | E48: 1458550 | F48: 25 | G48: 36 | J48: 409910.89 | K48: 409910.89 | L48: 409910.89
A49: Desktop HW | B49: NL | C49: Monitor | D49: L | E49: 4063015 | F49: 37 | G49: 36 | K49: 1141869.7 | L49: 1141869.7
A50: Desktop HW | B50: NL | C50: Monitor | D50: L | E50: 973710 | F50: 49 | G50: 36 | L50: 273651.46
A51: Desktop HW | B51: NL | C51: S&LB Printer Local Mono | D51: L | E51: 0 | F51: 1 | G51: 36 | H51: 11936.166
A52: Desktop HW | B52: NL | C52: S&LB Printer Local Mono | D52: L | E52: 0 | F52: 1 | G52: 36 | H52: 11936.166 | I52: 11936.166
A53: Desktop HW | B53: NL | C53: Printer Local Mono | D53: L | E53: 42471.415 | F53: 1 | G53: 36 | H53: 11936.166 | I53: 11936.166 | J53: 11936.166
A54: Desktop HW | B54: NL | C54: Printer Local Mono | D54: L | E54: 42471.415 | F54: 13 | G54: 36 | I54: 11936.166 | J54: 11936.166 | K54: 11936.166
A55: Desktop HW | B55: NL | C55: Printer Local Mono | D55: L | E55: 42471.415 | F55: 25 | G55: 36 | J55: 11936.166 | K55: 11936.166 | L55: 11936.166
A56: Desktop HW | B56: NL | C56: Printer Local Mono | D56: L | E56: 42471.415 | F56: 37 | G56: 36 | K56: 11936.166 | L56: 11936.166
A57: Desktop HW | B57: NL | C57: Printer Local Mono | D57: L | E57: 42471.415 | F57: 49 | G57: 36 | L57: 11936.166
A58: Desktop HW | B58: NL | C58: S&LB Printer Local Color | D58: L | E58: 0 | F58: 1 | G58: 36 | H58: 43682.455
A59: Desktop HW | B59: NL | C59: S&LB Printer Local Color | D59: L | E59: 0 | F59: 1 | G59: 36 | H59: 43682.455 | I59: 43682.455
A60: Desktop HW | B60: NL | C60: Printer Local Color | D60: L | E60: 155431.45 | F60: 1 | G60: 36 | H60: 43682.455 | I60: 43682.455 | J60: 43682.455
A61: Desktop HW | B61: NL | C61: Printer Local Color | D61: L | E61: 155431.45 | F61: 13 | G61: 36 | I61: 43682.455 | J61: 43682.455 | K61: 43682.455
A62: Desktop HW | B62: NL | C62: Printer Local Color | D62: L | E62: 155431.45 | F62: 25 | G62: 36 | J62: 43682.455 | K62: 43682.455 | L62: 43682.455
A63: Desktop HW | B63: NL | C63: Printer Local Color | D63: L | E63: 155431.45 | F63: 37 | G63: 36 | K63: 43682.455 | L63: 43682.455
A64: Desktop HW | B64: NL | C64: Printer Local Color | D64: L | E64: 155431.45 | F64: 49 | G64: 36 | L64: 43682.455
A65: Desktop HW | B65: NL | C65: S&LB Printer Network small Mono | D65: L | E65: 0 | F65: 1 | G65: 36 | H65: 35137.414
A66: Desktop HW | B66: NL | C66: S&LB Printer Network small Mono | D66: L | E66: 0 | F66: 1 | G66: 36 | H66: 35137.414 | I66: 35137.414
A67: Desktop HW | B67: NL | C67: Printer Network small Mono | D67: L | E67: 125026.38 | F67: 1 | G67: 36 | H67: 35137.414 | I67: 35137.414 | J67: 35137.414
A68: Desktop HW | B68: NL | C68: Printer Network small Mono | D68: L | E68: 125026.38 | F68: 13 | G68: 36 | I68: 35137.414 | J68: 35137.414 | K68: 35137.414
A69: Desktop HW | B69: NL | C69: Printer Network small Mono | D69: L | E69: 125026.38 | F69: 25 | G69: 36 | J69: 35137.414 | K69: 35137.414 | L69: 35137.414
A70: Desktop HW | B70: NL | C70: Printer Network small Mono | D70: L | E70: 125026.38 | F70: 37 | G70: 36 | K70: 35137.414 | L70: 35137.414
A71: Desktop HW | B71: NL | C71: Printer Network small Mono | D71: L | E71: 125026.38 | F71: 49 | G71: 36 | L71: 35137.414
A72: Desktop HW | B72: NL | C72: S&LB Printer Network small Color | D72: L | E72: 0 | F72: 1 | G72: 36 | H72: 78226.762
A73: Desktop HW | B73: NL | C73: S&LB Printer Network small Color | D73: L | E73: 0 | F73: 1 | G73: 36 | H73: 78226.762 | I73: 78226.762
A74: Desktop HW | B74: NL | C74: Printer Network small Color | D74: L | E74: 278347.43 | F74: 1 | G74: 36 | H74: 78226.762 | I74: 78226.762 | J74: 78226.762
A75: Desktop HW | B75: NL | C75: Printer Network small Color | D75: L | E75: 278347.43 | F75: 13 | G75: 36 | I75: 78226.762 | J75: 78226.762 | K75: 78226.762
A76: Desktop HW | B76: NL | C76: Printer Network small Color | D76: L | E76: 278347.43 | F76: 25 | G76: 36 | J76: 78226.762 | K76: 78226.762 | L76: 78226.762
A77: Desktop HW | B77: NL | C77: Printer Network small Color | D77: L | E77: 278347.43 | F77: 37 | G77: 36 | K77: 78226.762 | L77: 78226.762
A78: Desktop HW | B78: NL | C78: Printer Network small Color | D78: L | E78: 278347.43 | F78: 49 | G78: 36 | L78: 78226.762
A79: Desktop HW | B79: NL | C79: S&LB Printer Network big Mono | D79: L | E79: 0 | F79: 1 | G79: 36 | H79: 21465.936
A80: Desktop HW | B80: NL | C80: S&LB Printer Network big Mono | D80: L | E80: 0 | F80: 1 | G80: 36 | H80: 21465.936 | I80: 21465.936
A81: Desktop HW | B81: NL | C81: Printer Network big Mono | D81: L | E81: 76380.357 | F81: 1 | G81: 36 | H81: 21465.936 | I81: 21465.936 | J81: 21465.936
A82: Desktop HW | B82: NL | C82: Printer Network big Mono | D82: L | E82: 76380.357 | F82: 13 | G82: 36 | I82: 21465.936 | J82: 21465.936 | K82: 21465.936
A83: Desktop HW | B83: NL | C83: Printer Network big Mono | D83: L | E83: 76380.357 | F83: 25 | G83: 36 | J83: 21465.936 | K83: 21465.936 | L83: 21465.936
A84: Desktop HW | B84: NL | C84: Printer Network big Mono | D84: L | E84: 76380.357 | F84: 37 | G84: 36 | K84: 21465.936 | L84: 21465.936
A85: Desktop HW | B85: NL | C85: Printer Network big Mono | D85: L | E85: 76380.357 | F85: 49 | G85: 36 | L85: 21465.936
A86: Desktop HW | B86: NL | C86: S&LB Printer Network big color | D86: L | E86: 0 | F86: 1 | G86: 36 | H86: 64881.11
A87: Desktop HW | B87: NL | C87: S&LB Printer Network big color | D87: L | E87: 0 | F87: 1 | G87: 36 | H87: 64881.11 | I87: 64881.11
A88: Desktop HW | B88: NL | C88: Printer Network big color | D88: L | E88: 230860.77 | F88: 1 | G88: 36 | H88: 64881.11 | I88: 64881.11 | J88: 64881.11
A89: Desktop HW | B89: NL | C89: Printer Network big color | D89: L | E89: 230860.77 | F89: 13 | G89: 36 | I89: 64881.11 | J89: 64881.11 | K89: 64881.11
A90: Desktop HW | B90: NL | C90: Printer Network big color | D90: L | E90: 230860.77 | F90: 25 | G90: 36 | J90: 64881.11 | K90: 64881.11 | L90: 64881.11
A91: Desktop HW | B91: NL | C91: Printer Network big color | D91: L | E91: 230860.77 | F91: 37 | G91: 36 | K91: 64881.11 | L91: 64881.11
A92: Desktop HW | B92: NL | C92: Printer Network big color | D92: L | E92: 230860.77 | F92: 49 | G92: 36 | L92: 64881.11
A93: Desktop HW | B93: BE | C93: Desktop | D93: L | E93: 2099604 | F93: 1 | G93: 36 | H93: 590072.71 | I93: 590072.71 | J93: 590072.71
A94: Desktop HW | B94: BE | C94: Desktop | D94: L | E94: 778744 | F94: 13 | G94: 36 | I94: 218858.21 | J94: 218858.21 | K94: 218858.21
A95: Desktop HW | B95: BE | C95: Desktop | D95: L | E95: 2534674 | F95: 25 | G95: 36 | J95: 712344.78 | K95: 712344.78 | L95: 712344.78
A96: Desktop HW | B96: BE | C96: Desktop | D96: L | E96: 2099604 | F96: 37 | G96: 36 | K96: 590072.71 | L96: 590072.71
A97: Desktop HW | B97: BE | C97: Desktop | D97: L | E97: 778744 | F97: 49 | G97: 36 | L97: 218858.21
A98: Desktop HW | B98: BE | C98: Laptop | D98: L | E98: 0 | F98: 1 | G98: 36 | H98: 0 | I98: 0 | J98: 0
A99: Desktop HW | B99: BE | C99: Laptop | D99: L | E99: 137145 | F99: 13 | G99: 36 | I99: 38543.231 | J99: 38543.231 | K99: 38543.231
A100: Desktop HW | B100: BE | C100: Laptop | D100: L | E100: 1082442 | F100: 25 | G100: 36 | J100: 304209.5 | K100: 304209.5 | L100: 304209.5
A101: Desktop HW | B101: BE | C101: Laptop | D101: L | E101: 0 | F101: 37 | G101: 36 | K101: 0 | L101: 0
A102: Desktop HW | B102: BE | C102: Laptop | D102: L | E102: 137145 | F102: 49 | G102: 36 | L102: 38543.231
A103: Desktop HW | B103: BE | C103: Monitor | D103: L | E103: 436015 | F103: 1 | G103: 36 | H103: 122537.66 | I103: 122537.66 | J103: 122537.66
A104: Desktop HW | B104: BE | C104: Monitor | D104: L | E104: 322400 | F104: 13 | G104: 36 | I104: 90607.296 | J104: 90607.296 | K104: 90607.296
A105: Desktop HW | B105: BE | C105: Monitor | D105: L | E105: 1922155 | F105: 25 | G105: 36 | J105: 540202.44 | K105: 540202.44 | L105: 540202.44
A106: Desktop HW | B106: BE | C106: Monitor | D106: L | E106: 436015 | F106: 37 | G106: 36 | K106: 122537.66 | L106: 122537.66
A107: Desktop HW | B107: BE | C107: Monitor | D107: L | E107: 322400 | F107: 49 | G107: 36 | L107: 90607.296
...

Sheet Retained costs overview
A1: Retained contract values
A2: Amounts x Euro
A3: excluding VAT
A5: Location | B5: NL
A7: PST member | B7: Y1 ret EuroBank | C7: Y2 ret EuroBank | D7: Y3 ret EuroBank | E7: Y4 ret EuroBank | F7: Y5 ret EuroBank | G7: Total`Retained EuroBank
A8: VendorA | B8: 9710096.4 | C8: 9543575.6 | D8: 9543575.6 | E8: 9543575.6 | F8: 9543575.6 | G8: =SUM(B8:F8)
A9: Vendor Gamma | B9: 2081639.2 | C9: 867504.7 | D9: 867504.7 | E9: 867504.7 | F9: 867504.7 | G9: =SUM(B9:F9)
A10: TelCo | B10: 1446048.8 | C10: 180708 | D10: 180708 | E10: 180708 | F10: 180708 | G10: =SUM(B10:F10)
A11: Total | B11: =SUM(B8:B10) | C11: =SUM(C8:C10) | D11: =SUM(D8:D10) | E11: =SUM(E8:E10) | F11: =SUM(F8:F10) | G11: =SUM(G8:G10)
A14: Location | B14: BE
A16: PST member | B16: Y1 ret EuroBank | C16: Y2 ret EuroBank | D16: Y3 ret EuroBank | E16: Y4 ret EuroBank | F16: Y5 ret EuroBank | G16: Total`Retained EuroBank
A17: VendorA | B17: 3312235.7 | C17: 2908620.3 | D17: 2821424.3 | E17: 2821424.3 | F17: 2821424.3 | G17: =SUM(B17:F17)
A18: Vendor Gamma | B18: 7748051.8 | C18: 2821709.2 | D18: 2118037.8 | E18: 2118037.8 | F18: 2118037.8 | G18: =SUM(B18:F18)
A19: TelCo | B19: 2232956.2 | C19: 16912.303 | D19: 16912.303 | E19: 16912.303 | F19: 16912.303 | G19: =SUM(B19:F19)
A20: Total | B20: =SUM(B17:B19) | C20: =SUM(C17:C19) | D20: =SUM(D17:D19) | E20: =SUM(E17:E19) | F20: =SUM(F17:F19) | G20: =SUM(G17:G19)
A23: Location | B23: NL + BE
A25: PST member | B25: Y1 ret EuroBank | C25: Y2 ret EuroBank | D25: Y3 ret EuroBank | E25: Y4 ret EuroBank | F25: Y5 ret EuroBank | G25: Total`Retained EuroBank
A26: VendorA | B26: 13022332 | C26: 12452196 | D26: 12365000 | E26: 12365000 | F26: 12365000 | G26: =SUM(B26:F26)
A27: Vendor Gamma | B27: 9829691 | C27: 3689213.9 | D27: 2985542.5 | E27: 2985542.5 | F27: 2985542.5 | G27: =SUM(B27:F27)
A28: TelCo | B28: 3679005 | C28: 197620.3 | D28: 197620.3 | E28: 197620.3 | F28: 197620.3 | G28: =SUM(B28:F28)
A29: Total | B29: =SUM(B26:B28) | C29: =SUM(C26:C28) | D29: =SUM(D26:D28) | E29: =SUM(E26:E28) | F29: =SUM(F26:F28) | G29: =SUM(G26:G28)
A32: Retained Legacy assets
A34: Location | B34: NL
B36: Y1 ret EuroBank | C36: Y2 ret EuroBank | D36: Y3 ret EuroBank | E36: Y4 ret EuroBank | F36: Y5 ret EuroBank | G36: Total`Retained EuroBank
A37: Server Hardware | B37: 6724727.1 | C37: 1921350.6 | D37: 960675.3 | G37: =SUM(B37:F37)
A38: Desktop related Hardware | B38: 15401996 | C38: 4400570.4 | D38: 2200285.2 | G38: =SUM(B38:F38)
A39: Total | B39: =SUM(B37:B38) | C39: =SUM(C37:C38) | D39: =SUM(D37:D38) | G39: =SUM(G36:G38)
A41: Location | B41: BE
B43: Y1 ret EuroBank | C43: Y2 ret EuroBank | D43: Y3 ret EuroBank | E43: Y4 ret EuroBank | F43: Y5 ret EuroBank | G43: Total`Retained EuroBank
A44: Server Hardware | G44: =SUM(B44:F44)
A45: Desktop related Hardware | B45: 189753.2 | C45: 54215.2 | D45: 27107.6 | G45: =SUM(B45:F45)
A46: Total | B46: =SUM(B43:B45) | C46: =SUM(C43:C45) | D46: =SUM(D43:D45) | E46: =SUM(E43:E45) | F46: =SUM(F43:F45) | G46: =SUM(G43:G45)
A48: Location | B48: Total NL + BE
B50: Y1 ret EuroBank | C50: Y2 ret EuroBank | D50: Y3 ret EuroBank | E50: Y4 ret EuroBank | F50: Y5 ret EuroBank | G50: Total`Retained EuroBank
A51: Server Hardware | B51: =B37+B44 | C51: =C37+C44 | D51: =D37+D44 | E51: =E37+E44 | F51: =F37+F44 | G51: =SUM(B51:F51)
A52: Desktop related Hardware | B52: =B38+B45 | C52: =C38+C45 | D52: =D38+D45 | E52: =E38+E45 | F52: =F38+F45 | G52: =SUM(B52:F52)
A53: Total | B53: =SUM(B50:B52) | C53: =SUM(C50:C52) | D53: =SUM(D50:D52) | E53: =SUM(E50:E52) | F53: =SUM(F50:F52) | G53: =SUM(G50:G52)

Sheet Refresh cycles
B2: Overview of volumes used for refresh
D5: Year 1 Annual Avg. | E5: Year 2 Annual Avg. | F5: Year 3 Annual Avg. | G5: Year 4 Annual Avg. | H5: Year 5 Annual Avg.
B6: NL | C6: Desktop normal | D6: 29996 | E6: 2856.8 | F6: 671.2 | G6: 29996 | H6: 2856.8
C7: Desktop highend | D7: 7499 | E7: 714.2 | F7: 167.8 | G7: 7499 | H7: 714.2
C8: Laptop portable | D8: 844 | E8: 2404 | F8: 396.8 | G8: 844 | H8: 2404
C9: Laptop performance | D9: 211 | E9: 601 | F9: 99.2 | G9: 211 | H9: 601
C10: Monitor | D10: 26213 | E10: 6282 | F10: 9410 | G10: 26213 | H10: 6282
C11: Printer Local Mono | D11: 179.20428 | E11: 179.20428 | F11: 179.20428 | G11: 179.20428 | H11: 179.20428
C12: Printer Local Color | D12: 653.07332 | E12: 653.07332 | F12: 653.07332 | G12: 653.07332 | H12: 653.07332
C13: Printer Network small Mono | D13: 194.14034 | E13: 194.14034 | F13: 194.14034 | G13: 194.14034 | H13: 194.14034
C14: Printer Network small Color | D14: 383.39867 | E14: 383.39867 | F14: 383.39867 | G14: 383.39867 | H14: 383.39867
C15: Printer Network big Mono | D15: 83.203004 | E15: 83.203004 | F15: 83.203004 | G15: 83.203004 | H15: 83.203004
C16: Printer Network big color | D16: 164.31371 | E16: 164.31371 | F16: 164.31371 | G16: 164.31371 | H16: 164.31371
C17: Central 2 way Server | D17: 190.43223 | E17: 193.99225 | F17: 193.99225 | G17: 193.99225 | H17: 193.99225
C18: Central 4 way Server | D18: 215.16368 | E18: 219.18605 | F18: 219.18605 | G18: 219.18605 | H18: 219.18605
... C21: Decentral 2 way Server | D21: 48.638534 | E21: 49.547804 | F21: 49.547804 | G21: 49.547804 | H21: 49.547804
B22: BE | C22: Desktop normal | D22: 5366.4 | E22: 1990.4 | F22: 6478.4 | G22: 5366.4 | H22: 1990.4
C23: Desktop highend | D23: 1341.6 | E23: 497.6 | F23: 1619.6 | G23: 1341.6 | H23: 497.6
C24: Laptop portable | D24: 0 | E24: 164 | F24: 1294.4 | G24: 0 | H24: 164
C25: Laptop performance | D25: 0 | E25: 41 | F25: 323.6 | G25: 0 | H25: 41
C26: Monitor | D26: 2813 | E26: 2080 | F26: 12401 | G26: 2813 | H26: 2080
C27: Printer Local Mono | D27: 422.22216 | E27: 422.22216 | F27: 422.22216 | G27: 422.22216 | H27: 422.22216
C28: Printer Local Color | D28: 1538.7022 | E28: 1538.7022 | F28: 1538.7022 | G28: 1538.7022 | H28: 1538.7022
C29: Printer Network small Mono | D29: 457.41292 | E29: 457.41292 | F29: 457.41292 | G29: 457.41292 | H29: 457.41292
C30: Printer Network small Color | D30: 903.32335 | E30: 903.32335 | F30: 903.32335 | G30: 903.32335 | H30: 903.32335
C31: Printer Network big Mono | D31: 196.03411 | E31: 196.03411 | F31: 196.03411 | G31: 196.03411 | H31: 196.03411
C32: Printer Network big color | D32: 387.13858 | E32: 387.13858 | F32: 387.13858 | G32: 387.13858 | H32: 387.13858
C33: Central 2 way Server | D33: 40.567775 | E33: 37.007752 | F33: 37.007752 | G33: 37.007752 | H33: 37.007752
C34: Central 4 way Server | D34: 45.836317 | E34: 41.813953 | F34: 41.813953 | G34: 41.813953 | H34: 41.813953
... C37: Decentral 2 way Server | D37: 10.361466 | E37: 9.4521964 | F37: 9.4521964 | G37: 9.4521964 | H37: 9.4521964
C38: TPA Servers | F38: 911
B41: 3 year refresh cycle for all equipment.

Sheet Storage
A1: The prices below are available for acceptance by EuroBank during the period of 12 months after the effective date
A3: Detailed Base Charges - Total | B3: Year 1 | C3: Year 2 | D3: Year 3 | E3: Year 4 | F3: Year 5 | G3: Total 5 Yr
A4: Server Management
A5: Support Services
A6: Total SAN (TB) | B6: 2625168 | C6: 3242384 | D6: 2679575 | E6: 2468522 | F6: 2081591 | G6: 13097240
A7: Total NAS (TB) | B7: 737687 | C7: 925032 | D7: 760769 | E7: 706015 | F7: 590422 | G7: 3719925
A10: Detailed Base Charges - NL | B10: Year 1 | C10: Year 2 | D10: Year 3 | E10: Year 4 | F10: Year 5 | G10: Total 5 Yr
A11: Server Management
A12: Support Services
A13: Total SAN (TB) | B13: 1508075.2 | C13: 2018842.9 | D13: 1668414.6 | E13: 1537004.3 | F13: 1296085 | G13: =SUM(B13:F13)
A14: Total NAS (TB) | B14: 532773.94 | C14: 672750.55 | D14: 553286.55 | E14: 513465.45 | F14: 429397.82 | G14: =SUM(B14:F14)
A17: Detailed Base Charges - BE | B17: Year 1 | C17: Year 2 | D17: Year 3 | E17: Year 4 | F17: Year 5 | G17: Total 5 Yr
A18: Server Management
A19: Support Services
A20: Total SAN (TB) | B20: 1117092.8 | C20: 1223541.1 | D20: 1011160.4 | E20: 931517.74 | F20: 785506.04 | G20: =SUM(B20:F20)
A21: Total NAS (TB) | B21: 204913.06 | C21: 252281.45 | D21: 207482.45 | E21: 192549.55 | F21: 161024.18 | G21: =SUM(B21:F21)
A24: Resource Baseline - Total | B24: Year 1 | C24: Year 2 | D24: Year 3 | E24: Year 4 | F24: Year 5
A25: Server Management
A26: Support Services
A27: Total SAN (TB) | B27: 141 | C27: 212 | D27: 212 | E27: 212 | F27: 212
A28: Total NAS (TB) | B28: 36 | C28: 55 | D28: 55 | E28: 55 | F28: 55
A31: Resource Baseline - NL | B31: Year 1 | C31: Year 2 | D31: Year 3 | E31: Year 4 | F31: Year 5
A32: Server Management
A33: Support Services
A34: Total SAN (TB) | B34: 81 | C34: 132 | D34: 132 | E34: 132 | F34: 132
A35: Total NAS (TB) | B35: 26 | C35: 40 | D35: 40 | E35: 40 | F35: 40
A38: Resource Baseline - BE | B38: Year 1 | C38: Year 2 | D38: Year 3 | E38: Year 4 | F38: Year 5
A39: Server Management
A40: Support Services
A41: Total SAN (TB) | B41: 60 | C41: 80 | D41: 80 | E41: 80 | F41: 80
A42: Total NAS (TB) | B42: 10 | C42: 15 | D42: 15 | E42: 15 | F42: 15
