Workbook

Sheet Title Sheet
B2: GlobalPharma AG
B5: ATTACHMENT 4-C
B7: FINANCIAL BASE CASE
B8: Attachment to Exhibit 4 (Pricing and Financial Provisions)
B15: This document contains confidential and proprietary information of GlobalPharma AG. It is furnished for the performance of The Agreements only. Except with the express prior written permission of GlobalPharma AG, this document and the information contained herein may not be published, disclosed, or used for any other purpose.

Sheet Consolidated 
C1: Consolidated Summary
C2: TOTAL COSTS (US$ excl. VAT) | D2: BASE YEAR | E2: YEAR 1 | F2: YEAR 2 | G2: YEAR 3 | H2: YEAR 4 | I2: YEAR 5 | J2: 5 Year Total | L2: 5 YEAR + 1 | M2: 5 YEAR + 2 | N2: 7 Year Total
C3: Internal FTE | D3: =D46+D90+D133 | E3: =E46+E90+E133 | F3: =F46+F90+F133 | G3: =G46+G90+G133 | H3: =H46+H90+H133 | I3: =I46+I90+I133 | L3: =L46+L90+L133 | M3: =M46+M90+M133
C4: External FTE | D4: =D47+D91+D134 | E4: =E47+E91+E134 | F4: =F47+F91+F134 | G4: =G47+G91+G134 | H4: =H47+H91+H134 | I4: =I47+I91+I134 | L4: =L47+L91+L134 | M4: =M47+M91+M134
C5: Total FTE | D5: =SUM(D3:D4) | E5: =SUM(E3:E4) | F5: =SUM(F3:F4) | G5: =SUM(G3:G4) | H5: =SUM(H3:H4) | I5: =SUM(I3:I4) | L5: =SUM(L3:L4) | M5: =SUM(M3:M4)
C7: Salaries | D7: =D50+D94+D137 | E7: =E50+E94+E137 | F7: =F50+F94+F137 | G7: =G50+G94+G137 | H7: =H50+H94+H137 | I7: =I50+I94+I137 | J7: =SUM(E7:I7) | L7: =L50+L94+L137 | M7: =M50+M94+M137 | N7: =+J7+SUM(L7:M7)
C8: Bonuses | D8: =D51+D95+D138 | E8: =E51+E95+E138 | F8: =F51+F95+F138 | G8: =G51+G95+G138 | H8: =H51+H95+H138 | I8: =I51+I95+I138 | J8: =SUM(E8:I8) | L8: =L51+L95+L138 | M8: =M51+M95+M138 | N8: =+J8+SUM(L8:M8)
C9: Third party staff, ex IT | D9: =D52+D96+D139 | E9: =E52+E96+E139 | F9: =F52+F96+F139 | G9: =G52+G96+G139 | H9: =H52+H96+H139 | I9: =I52+I96+I139 | J9: =SUM(E9:I9) | L9: =L52+L96+L139 | M9: =M52+M96+M139 | N9: =+J9+SUM(L9:M9)
C10: Third party IT staff | D10: =D53+D97+D140 | E10: =E53+E97+E140 | F10: =F53+F97+F140 | G10: =G53+G97+G140 | H10: =H53+H97+H140 | I10: =I53+I97+I140 | J10: =SUM(E10:I10) | L10: =L53+L97+L140 | M10: =M53+M97+M140 | N10: =+J10+SUM(L10:M10)
C11: Employee education | D11: =D54+D98+D141 | E11: =E54+E98+E141 | F11: =F54+F98+F141 | G11: =G54+G98+G141 | H11: =H54+H98+H141 | I11: =I54+I98+I141 | J11: =SUM(E11:I11) | L11: =L54+L98+L141 | M11: =M54+M98+M141 | N11: =+J11+SUM(L11:M11)
C12: Other staff expenses | D12: =D55+D99+D142 | E12: =E55+E99+E142 | F12: =F55+F99+F142 | G12: =G55+G99+G142 | H12: =H55+H99+H142 | I12: =I55+I99+I142 | J12: =SUM(E12:I12) | L12: =L55+L99+L142 | M12: =M55+M99+M142 | N12: =+J12+SUM(L12:M12)
C13: Staff expenses | D13: =SUM(D7:D12) | E13: =SUM(E7:E12) | F13: =SUM(F7:F12) | G13: =SUM(G7:G12) | H13: =SUM(H7:H12) | I13: =SUM(I7:I12) | J13: =SUM(E13:I13) | L13: =SUM(L7:L12) | M13: =SUM(M7:M12) | N13: =SUM(N7:N12)
C14: Hardware expenses | D14: =D57+D101+D144 | E14: =E57+E101+E144 | F14: =F57+F101+F144 | G14: =G57+G101+G144 | H14: =H57+H101+H144 | I14: =I57+I101+I144 | J14: =SUM(E14:I14) | L14: =L57+L101+L144 | M14: =M57+M101+M144 | N14: =+J14+SUM(L14:M14)
C15: Leasing/renting hardware | D15: =D58+D102+D145 | E15: =E58+E102+E145 | F15: =F58+F102+F145 | G15: =G58+G102+G145 | H15: =H58+H102+H145 | I15: =I58+I102+I145 | J15: =SUM(E15:I15) | L15: =L58+L102+L145 | M15: =M58+M102+M145 | N15: =+J15+SUM(L15:M15)
C16: Software expenses | D16: =D59+D103+D146 | E16: =E59+E103+E146 | F16: =F59+F103+F146 | G16: =G59+G103+G146 | H16: =H59+H103+H146 | I16: =I59+I103+I146 | J16: =SUM(E16:I16) | L16: =L59+L103+L146 | M16: =M59+M103+M146 | N16: =+J16+SUM(L16:M16)
C17: Leasing/renting/licenses sw | D17: =D60+D104+D147 | E17: =E60+E104+E147 | F17: =F60+F104+F147 | G17: =G60+G104+G147 | H17: =H60+H104+H147 | I17: =I60+I104+I147 | J17: =SUM(E17:I17) | L17: =L60+L104+L147 | M17: =M60+M104+M147 | N17: =+J17+SUM(L17:M17)
C18: Depreciation hardware | D18: =D61+D105+D148 | E18: =E61+E105+E148 | F18: =F61+F105+F148 | G18: =G61+G105+G148 | H18: =H61+H105+H148 | I18: =I61+I105+I148 | J18: =SUM(E18:I18) | L18: =L61+L105+L148 | M18: =M61+M105+M148 | N18: =+J18+SUM(L18:M18)
C19: Depreciation software | D19: =D62+D106+D149 | E19: =E62+E106+E149 | F19: =F62+F106+F149 | G19: =G62+G106+G149 | H19: =H62+H106+H149 | I19: =I62+I106+I149 | J19: =SUM(E19:I19) | L19: =L62+L106+L149 | M19: =M62+M106+M149 | N19: =+J19+SUM(L19:M19)
C20: Outsourcing IT activities | D20: =D63+D107+D150 | E20: =E63+E107+E150 | F20: =F63+F107+F150 | G20: =G63+G107+G150 | H20: =H63+H107+H150 | I20: =I63+I107+I150 | J20: =SUM(E20:I20) | L20: =L63+L107+L150 | M20: =M63+M107+M150 | N20: =+J20+SUM(L20:M20)
C21: Other IT expenses | D21: =D64+D108+D151 | E21: =E64+E108+E151 | F21: =F64+F108+F151 | G21: =G64+G108+G151 | H21: =H64+H108+H151 | I21: =I64+I108+I151 | J21: =SUM(E21:I21) | L21: =L64+L108+L151 | M21: =M64+M108+M151 | N21: =+J21+SUM(L21:M21)
C22: EDP expenses | D22: =SUM(D14:D21) | E22: =SUM(E14:E21) | F22: =SUM(F14:F21) | G22: =SUM(G14:G21) | H22: =SUM(H14:H21) | I22: =SUM(I14:I21) | J22: =SUM(E22:I22) | L22: =SUM(L14:L21) | M22: =SUM(M14:M21) | N22: =SUM(N14:N21)
C23: Telecom expenses | D23: =D66+D110+D153 | E23: =E66+E110+E153 | F23: =F66+F110+F153 | G23: =G66+G110+G153 | H23: =H66+H110+H153 | I23: =I66+I110+I153 | J23: =SUM(E23:I23) | L23: =L66+L110+L153 | M23: =M66+M110+M153 | N23: =+J23+SUM(L23:M23)
C24: Office equipment and supplies | D24: =D67+D111+D154 | E24: =E67+E111+E154 | F24: =F67+F111+F154 | G24: =G67+G111+G154 | H24: =H67+H111+H154 | I24: =I67+I111+I154 | J24: =SUM(E24:I24) | L24: =L67+L111+L154 | M24: =M67+M111+M154 | N24: =+J24+SUM(L24:M24)
C25: Accomodation expenses | D25: =D68+D112+D155 | E25: =E68+E112+E155 | F25: =F68+F112+F155 | G25: =G68+G112+G155 | H25: =H68+H112+H155 | I25: =I68+I112+I155 | J25: =SUM(E25:I25) | L25: =L68+L112+L155 | M25: =M68+M112+M155 | N25: =+J25+SUM(L25:M25)
C26: Travel costs | D26: =D69+D113+D156 | E26: =E69+E113+E156 | F26: =F69+F113+F156 | G26: =G69+G113+G156 | H26: =H69+H113+H156 | I26: =I69+I113+I156 | J26: =SUM(E26:I26) | L26: =L69+L113+L156 | M26: =M69+M113+M156 | N26: =+J26+SUM(L26:M26)
C27: Postal and freight charges | D27: =D70+D114+D157 | E27: =E70+E114+E157 | F27: =F70+F114+F157 | G27: =G70+G114+G157 | H27: =H70+H114+H157 | I27: =I70+I114+I157 | J27: =SUM(E27:I27) | L27: =L70+L114+L157 | M27: =M70+M114+M157 | N27: =+J27+SUM(L27:M27)
C28: Prof serv and ext advisory fee | D28: =D71+D115+D158 | E28: =E71+E115+E158 | F28: =F71+F115+F158 | G28: =G71+G115+G158 | H28: =H71+H115+H158 | I28: =I71+I115+I158 | J28: =SUM(E28:I28) | L28: =L71+L115+L158 | M28: =M71+M115+M158 | N28: =+J28+SUM(L28:M28)
C29: Payment transfer expenses | D29: =D72+D116+D159 | E29: =E72+E116+E159 | F29: =F72+F116+F159 | G29: =G72+G116+G159 | H29: =H72+H116+H159 | I29: =I72+I116+I159 | J29: =SUM(E29:I29) | L29: =L72+L116+L159 | M29: =M72+M116+M159 | N29: =+J29+SUM(L29:M29)
C30: Other costs | D30: =D73+D117+D160 | E30: =E73+E117+E160 | F30: =F73+F117+F160 | G30: =G73+G117+G160 | H30: =H73+H117+H160 | I30: =I73+I117+I160 | J30: =SUM(E30:I30) | L30: =L73+L117+L160 | M30: =M73+M117+M160 | N30: =+J30+SUM(L30:M30)
C31: General expenses | D31: =SUM(D23:D30) | E31: =SUM(E23:E30) | F31: =SUM(F23:F30) | G31: =SUM(G23:G30) | H31: =SUM(H23:H30) | I31: =SUM(I23:I30) | J31: =SUM(E31:I31) | L31: =SUM(L23:L30) | M31: =SUM(M23:M30) | N31: =SUM(N23:N30)
C32: Own expenses | D32: =D31+D22+D13 | E32: =E31+E22+E13 | F32: =F31+F22+F13 | G32: =G31+G22+G13 | H32: =H31+H22+H13 | I32: =I31+I22+I13 | J32: =SUM(E32:I32) | L32: =L31+L22+L13 | M32: =M31+M22+M13 | N32: =+N13+N22+N31
C33: Other expenses | D33: =D76+D120+D163 | E33: =E76+E120+E163 | F33: =F76+F120+F163 | G33: =G76+G120+G163 | H33: =H76+H120+H163 | I33: =I76+I120+I163 | J33: =SUM(E33:I33) | L33: =L76+L120+L163 | M33: =M76+M120+M163 | N33: =+J33+SUM(L33:M33)
C34: Operating expenses | D34: =SUM(D32:D33) | E34: =SUM(E32:E33) | F34: =SUM(F32:F33) | G34: =SUM(G32:G33) | H34: =SUM(H32:H33) | I34: =SUM(I32:I33) | J34: =SUM(J32:J33) | L34: =SUM(L32:L33) | M34: =SUM(M32:M33) | N34: =SUM(N32:N33)
C36: HR & Comms | D36: =D79+D123+D166 | E36: =E79+E123+E166 | F36: =F79+F123+F166 | G36: =G79+G123+G166 | H36: =H79+H123+H166 | I36: =I79+I123+I166 | J36: =SUM(E36:I36) | L36: =L79+L123+L166 | M36: =M79+M123+M166 | N36: =+J36+SUM(L36:M36)
C37: Finance & Business Support | D37: =D80+D124+D167 | E37: =E80+E124+E167 | F37: =F80+F124+F167 | G37: =G80+G124+G167 | H37: =H80+H124+H167 | I37: =I80+I124+I167 | J37: =SUM(E37:I37) | L37: =L80+L124+L167 | M37: =M80+M124+M167 | N37: =+J37+SUM(L37:M37)
C38: HRN | D38: =D81+D125+D168 | E38: =E81+E125+E168 | F38: =F81+F125+F168 | G38: =G81+G125+G168 | H38: =H81+H125+H168 | I38: =I81+I125+I168 | J38: =SUM(E38:I38) | L38: =L81+L125+L168 | M38: =M81+M125+M168 | N38: =+J38+SUM(L38:M38)
C39: Facilities Management | D39: =D82+D126+D169 | E39: =E82+E126+E169 | F39: =F82+F126+F169 | G39: =G82+G126+G169 | H39: =H82+H126+H169 | I39: =I82+I126+I169 | J39: =SUM(E39:I39) | L39: =L82+L126+L169 | M39: =M82+M126+M169 | N39: =+J39+SUM(L39:M39)
C40: Overheads | D40: =SUM(D36:D39) | E40: =SUM(E36:E39) | F40: =SUM(F36:F39) | G40: =SUM(G36:G39) | H40: =SUM(H36:H39) | I40: =SUM(I36:I39) | J40: =SUM(J36:J39) | L40: =SUM(L36:L39) | M40: =SUM(M36:M39) | N40: =SUM(N36:N39)
C42: Total Operating Costs (incl. O/H) | D42: =D34+D40 | E42: =E34+E40 | F42: =F34+F40 | G42: =G34+G40 | H42: =H34+H40 | I42: =I34+I40 | J42: =J34+J40 | L42: =L34+L40 | M42: =M34+M40 | N42: =N34+N40
J43: =J42-J85-J129-J172
C45: SUPPLIER ASSUMED COSTS (EURO's excl. VAT) | D45: BASE YEAR | E45: YEAR 1 | F45: YEAR 2 | G45: YEAR 3 | H45: YEAR 4 | I45: YEAR 5 | J45: 5 Year Total | L45: 5 YEAR + 1 | M45: 5 YEAR +2 | N45: 7 Year Total
C46: Internal FTE | D46: =SUM(UK:Germany!D46) | E46: =SUM(UK:Germany!E46) | F46: =SUM(UK:Germany!F46) | G46: =SUM(UK:Germany!G46) | H46: =SUM(UK:Germany!H46) | I46: =SUM(UK:Germany!I46) | L46: =SUM(UK:Germany!L46) | M46: =SUM(UK:Germany!M46)
C47: External FTE | D47: =SUM(UK:Germany!D47) | E47: =SUM(UK:Germany!E47) | F47: =SUM(UK:Germany!F47) | G47: =SUM(UK:Germany!G47) | H47: =SUM(UK:Germany!H47) | I47: =SUM(UK:Germany!I47) | L47: =SUM(UK:Germany!L47) | M47: =SUM(UK:Germany!M47)
C48: Total FTE | D48: =SUM(D46:D47) | E48: =SUM(E46:E47) | F48: =SUM(F46:F47) | G48: =SUM(G46:G47) | H48: =SUM(H46:H47) | I48: =SUM(I46:I47) | L48: =SUM(L46:L47) | M48: =SUM(M46:M47)
C50: Salaries | D50: =SUM(UK:Germany!D50) | E50: =SUM(UK:Germany!E50) | F50: =SUM(UK:Germany!F50) | G50: =SUM(UK:Germany!G50) | H50: =SUM(UK:Germany!H50) | I50: =SUM(UK:Germany!I50) | J50: =SUM(E50:I50) | L50: =SUM(UK:Germany!L50) | M50: =SUM(UK:Germany!M50) | N50: =+J50+SUM(L50:M50)
C51: Bonuses | D51: =SUM(UK:Germany!D51) | E51: =SUM(UK:Germany!E51) | F51: =SUM(UK:Germany!F51) | G51: =SUM(UK:Germany!G51) | H51: =SUM(UK:Germany!H51) | I51: =SUM(UK:Germany!I51) | J51: =SUM(E51:I51) | L51: =SUM(UK:Germany!L51) | M51: =SUM(UK:Germany!M51) | N51: =+J51+SUM(L51:M51)
C52: Third party staff, ex IT | D52: =SUM(UK:Germany!D52) | E52: =SUM(UK:Germany!E52) | F52: =SUM(UK:Germany!F52) | G52: =SUM(UK:Germany!G52) | H52: =SUM(UK:Germany!H52) | I52: =SUM(UK:Germany!I52) | J52: =SUM(E52:I52) | L52: =SUM(UK:Germany!L52) | M52: =SUM(UK:Germany!M52) | N52: =+J52+SUM(L52:M52)
C53: Third party IT staff | D53: =SUM(UK:Germany!D53) | E53: =SUM(UK:Germany!E53) | F53: =SUM(UK:Germany!F53) | G53: =SUM(UK:Germany!G53) | H53: =SUM(UK:Germany!H53) | I53: =SUM(UK:Germany!I53) | J53: =SUM(E53:I53) | L53: =SUM(UK:Germany!L53) | M53: =SUM(UK:Germany!M53) | N53: =+J53+SUM(L53:M53)
C54: Employee education | D54: =SUM(UK:Germany!D54) | E54: =SUM(UK:Germany!E54) | F54: =SUM(UK:Germany!F54) | G54: =SUM(UK:Germany!G54) | H54: =SUM(UK:Germany!H54) | I54: =SUM(UK:Germany!I54) | J54: =SUM(E54:I54) | L54: =SUM(UK:Germany!L54) | M54: =SUM(UK:Germany!M54) | N54: =+J54+SUM(L54:M54)
C55: Other staff expenses | D55: =SUM(UK:Germany!D55) | E55: =SUM(UK:Germany!E55) | F55: =SUM(UK:Germany!F55) | G55: =SUM(UK:Germany!G55) | H55: =SUM(UK:Germany!H55) | I55: =SUM(UK:Germany!I55) | J55: =SUM(E55:I55) | L55: =SUM(UK:Germany!L55) | M55: =SUM(UK:Germany!M55) | N55: =+J55+SUM(L55:M55)
C56: Staff expenses | D56: =SUM(D50:D55) | E56: =SUM(E50:E55) | F56: =SUM(F50:F55) | G56: =SUM(G50:G55) | H56: =SUM(H50:H55) | I56: =SUM(I50:I55) | J56: =SUM(E56:I56) | L56: =SUM(L50:L55) | M56: =SUM(M50:M55) | N56: =SUM(N50:N55)
C57: Hardware expenses | D57: =SUM(UK:Germany!D57) | E57: =SUM(UK:Germany!E57) | F57: =SUM(UK:Germany!F57) | G57: =SUM(UK:Germany!G57) | H57: =SUM(UK:Germany!H57) | I57: =SUM(UK:Germany!I57) | J57: =SUM(E57:I57) | L57: =SUM(UK:Germany!L57) | M57: =SUM(UK:Germany!M57) | N57: =+J57+SUM(L57:M57)
C58: Leasing/renting hardware | D58: =SUM(UK:Germany!D58) | E58: =SUM(UK:Germany!E58) | F58: =SUM(UK:Germany!F58) | G58: =SUM(UK:Germany!G58) | H58: =SUM(UK:Germany!H58) | I58: =SUM(UK:Germany!I58) | J58: =SUM(E58:I58) | L58: =SUM(UK:Germany!L58) | M58: =SUM(UK:Germany!M58) | N58: =+J58+SUM(L58:M58)
C59: Software expenses | D59: =SUM(UK:Germany!D59) | E59: =SUM(UK:Germany!E59) | F59: =SUM(UK:Germany!F59) | G59: =SUM(UK:Germany!G59) | H59: =SUM(UK:Germany!H59) | I59: =SUM(UK:Germany!I59) | J59: =SUM(E59:I59) | L59: =SUM(UK:Germany!L59) | M59: =SUM(UK:Germany!M59) | N59: =+J59+SUM(L59:M59)
C60: Leasing/renting/licenses sw | D60: =SUM(UK:Germany!D60) | E60: =SUM(UK:Germany!E60) | F60: =SUM(UK:Germany!F60) | G60: =SUM(UK:Germany!G60) | H60: =SUM(UK:Germany!H60) | I60: =SUM(UK:Germany!I60) | J60: =SUM(E60:I60) | L60: =SUM(UK:Germany!L60) | M60: =SUM(UK:Germany!M60) | N60: =+J60+SUM(L60:M60)
C61: Depreciation hardware | D61: =SUM(UK:Germany!D61) | E61: =SUM(UK:Germany!E61) | F61: =SUM(UK:Germany!F61) | G61: =SUM(UK:Germany!G61) | H61: =SUM(UK:Germany!H61) | I61: =SUM(UK:Germany!I61) | J61: =SUM(E61:I61) | L61: =SUM(UK:Germany!L61) | M61: =SUM(UK:Germany!M61) | N61: =+J61+SUM(L61:M61)
C62: Depreciation software | D62: =SUM(UK:Germany!D62) | E62: =SUM(UK:Germany!E62) | F62: =SUM(UK:Germany!F62) | G62: =SUM(UK:Germany!G62) | H62: =SUM(UK:Germany!H62) | I62: =SUM(UK:Germany!I62) | J62: =SUM(E62:I62) | L62: =SUM(UK:Germany!L62) | M62: =SUM(UK:Germany!M62) | N62: =+J62+SUM(L62:M62)
C63: Outsourcing IT activities | D63: =SUM(UK:Germany!D63) | E63: =SUM(UK:Germany!E63) | F63: =SUM(UK:Germany!F63) | G63: =SUM(UK:Germany!G63) | H63: =SUM(UK:Germany!H63) | I63: =SUM(UK:Germany!I63) | J63: =SUM(E63:I63) | L63: =SUM(UK:Germany!L63) | M63: =SUM(UK:Germany!M63) | N63: =+J63+SUM(L63:M63)
C64: Other IT expenses | D64: =SUM(UK:Germany!D64) | E64: =SUM(UK:Germany!E64) | F64: =SUM(UK:Germany!F64) | G64: =SUM(UK:Germany!G64) | H64: =SUM(UK:Germany!H64) | I64: =SUM(UK:Germany!I64) | J64: =SUM(E64:I64) | L64: =SUM(UK:Germany!L64) | M64: =SUM(UK:Germany!M64) | N64: =+J64+SUM(L64:M64)
C65: EDP expenses | D65: =SUM(D57:D64) | E65: =SUM(E57:E64) | F65: =SUM(F57:F64) | G65: =SUM(G57:G64) | H65: =SUM(H57:H64) | I65: =SUM(I57:I64) | J65: =SUM(E65:I65) | L65: =SUM(L57:L64) | M65: =SUM(M57:M64) | N65: =SUM(N57:N64)
C66: Telecom expenses | D66: =SUM(UK:Germany!D66) | E66: =SUM(UK:Germany!E66) | F66: =SUM(UK:Germany!F66) | G66: =SUM(UK:Germany!G66) | H66: =SUM(UK:Germany!H66) | I66: =SUM(UK:Germany!I66) | J66: =SUM(E66:I66) | L66: =SUM(UK:Germany!L66) | M66: =SUM(UK:Germany!M66) | N66: =+J66+SUM(L66:M66)
C67: Office equipment and supplies | D67: =SUM(UK:Germany!D67) | E67: =SUM(UK:Germany!E67) | F67: =SUM(UK:Germany!F67) | G67: =SUM(UK:Germany!G67) | H67: =SUM(UK:Germany!H67) | I67: =SUM(UK:Germany!I67) | J67: =SUM(E67:I67) | L67: =SUM(UK:Germany!L67) | M67: =SUM(UK:Germany!M67) | N67: =+J67+SUM(L67:M67)
C68: Accomodation expenses | D68: =SUM(UK:Germany!D68) | E68: =SUM(UK:Germany!E68) | F68: =SUM(UK:Germany!F68) | G68: =SUM(UK:Germany!G68) | H68: =SUM(UK:Germany!H68) | I68: =SUM(UK:Germany!I68) | J68: =SUM(E68:I68) | L68: =SUM(UK:Germany!L68) | M68: =SUM(UK:Germany!M68) | N68: =+J68+SUM(L68:M68)
C69: Travel costs | D69: =SUM(UK:Germany!D69) | E69: =SUM(UK:Germany!E69) | F69: =SUM(UK:Germany!F69) | G69: =SUM(UK:Germany!G69) | H69: =SUM(UK:Germany!H69) | I69: =SUM(UK:Germany!I69) | J69: =SUM(E69:I69) | L69: =SUM(UK:Germany!L69) | M69: =SUM(UK:Germany!M69) | N69: =+J69+SUM(L69:M69)
C70: Postal and freight charges | D70: =SUM(UK:Germany!D70) | E70: =SUM(UK:Germany!E70) | F70: =SUM(UK:Germany!F70) | G70: =SUM(UK:Germany!G70) | H70: =SUM(UK:Germany!H70) | I70: =SUM(UK:Germany!I70) | J70: =SUM(E70:I70) | L70: =SUM(UK:Germany!L70) | M70: =SUM(UK:Germany!M70) | N70: =+J70+SUM(L70:M70)
C71: Prof serv and ext advisory fee | D71: =SUM(UK:Germany!D71) | E71: =SUM(UK:Germany!E71) | F71: =SUM(UK:Germany!F71) | G71: =SUM(UK:Germany!G71) | H71: =SUM(UK:Germany!H71) | I71: =SUM(UK:Germany!I71) | J71: =SUM(E71:I71) | L71: =SUM(UK:Germany!L71) | M71: =SUM(UK:Germany!M71) | N71: =+J71+SUM(L71:M71)
C72: Payment transfer expenses | D72: =SUM(UK:Germany!D72) | E72: =SUM(UK:Germany!E72) | F72: =SUM(UK:Germany!F72) | G72: =SUM(UK:Germany!G72) | H72: =SUM(UK:Germany!H72) | I72: =SUM(UK:Germany!I72) | J72: =SUM(E72:I72) | L72: =SUM(UK:Germany!L72) | M72: =SUM(UK:Germany!M72) | N72: =+J72+SUM(L72:M72)
C73: Other costs | D73: =SUM(UK:Germany!D73) | E73: =SUM(UK:Germany!E73) | F73: =SUM(UK:Germany!F73) | G73: =SUM(UK:Germany!G73) | H73: =SUM(UK:Germany!H73) | I73: =SUM(UK:Germany!I73) | J73: =SUM(E73:I73) | L73: =SUM(UK:Germany!L73) | M73: =SUM(UK:Germany!M73) | N73: =+J73+SUM(L73:M73)
C74: General expenses | D74: =SUM(D66:D73) | E74: =SUM(E66:E73) | F74: =SUM(F66:F73) | G74: =SUM(G66:G73) | H74: =SUM(H66:H73) | I74: =SUM(I66:I73) | J74: =SUM(E74:I74) | L74: =SUM(L66:L73) | M74: =SUM(M66:M73) | N74: =SUM(N66:N73)
C75: Own expenses | D75: =D74+D65+D56 | E75: =E74+E65+E56 | F75: =F74+F65+F56 | G75: =G74+G65+G56 | H75: =H74+H65+H56 | I75: =I74+I65+I56 | J75: =SUM(E75:I75) | L75: =L74+L65+L56 | M75: =M74+M65+M56 | N75: =+N56+N65+N74
C76: Other expenses | D76: =SUM(UK:Germany!D76) | E76: =SUM(UK:Germany!E76) | F76: =SUM(UK:Germany!F76) | G76: =SUM(UK:Germany!G76) | H76: =SUM(UK:Germany!H76) | I76: =SUM(UK:Germany!I76) | J76: =SUM(E76:I76) | L76: =SUM(UK:Germany!L76) | M76: =SUM(UK:Germany!M76) | N76: =+J76+SUM(L76:M76)
C77: Operating expenses | D77: =SUM(D75:D76) | E77: =SUM(E75:E76) | F77: =SUM(F75:F76) | G77: =SUM(G75:G76) | H77: =SUM(H75:H76) | I77: =SUM(I75:I76) | J77: =SUM(J75:J76) | L77: =SUM(L75:L76) | M77: =SUM(M75:M76) | N77: =SUM(N75:N76)
C79: HR & Comms | D79: =SUM(UK:Germany!D79) | E79: =SUM(UK:Germany!E79) | F79: =SUM(UK:Germany!F79) | G79: =SUM(UK:Germany!G79) | H79: =SUM(UK:Germany!H79) | I79: =SUM(UK:Germany!I79) | J79: =SUM(E79:I79) | L79: =SUM(UK:Germany!L79) | M79: =SUM(UK:Germany!M79) | N79: =+J79+SUM(L79:M79)
C80: Finance & Business Support | D80: =SUM(UK:Germany!D80) | E80: =SUM(UK:Germany!E80) | F80: =SUM(UK:Germany!F80) | G80: =SUM(UK:Germany!G80) | H80: =SUM(UK:Germany!H80) | I80: =SUM(UK:Germany!I80) | J80: =SUM(E80:I80) | L80: =SUM(UK:Germany!L80) | M80: =SUM(UK:Germany!M80) | N80: =+J80+SUM(L80:M80)
C81: HRN | D81: =SUM(UK:Germany!D81) | E81: =SUM(UK:Germany!E81) | F81: =SUM(UK:Germany!F81) | G81: =SUM(UK:Germany!G81) | H81: =SUM(UK:Germany!H81) | I81: =SUM(UK:Germany!I81) | J81: =SUM(E81:I81) | L81: =SUM(UK:Germany!L81) | M81: =SUM(UK:Germany!M81) | N81: =+J81+SUM(L81:M81)
C82: Facilities Management | D82: =SUM(UK:Germany!D82) | E82: =SUM(UK:Germany!E82) | F82: =SUM(UK:Germany!F82) | G82: =SUM(UK:Germany!G82) | H82: =SUM(UK:Germany!H82) | I82: =SUM(UK:Germany!I82) | J82: =SUM(E82:I82) | L82: =SUM(UK:Germany!L82) | M82: =SUM(UK:Germany!M82) | N82: =+J82+SUM(L82:M82)
C83: Overheads | D83: =SUM(D79:D82) | E83: =SUM(E79:E82) | F83: =SUM(F79:F82) | G83: =SUM(G79:G82) | H83: =SUM(H79:H82) | I83: =SUM(I79:I82) | J83: =SUM(J79:J82) | L83: =SUM(L79:L82) | M83: =SUM(M79:M82) | N83: =SUM(N79:N82)
C85: Total Operating Costs (incl. O/H) | D85: =+D83+D77 | E85: =+E83+E77 | F85: =+F83+F77 | G85: =+G83+G77 | H85: =+H83+H77 | I85: =+I83+I77 | J85: =J77+J83 | L85: =+L83+L77 | M85: =+M83+M77 | N85: =N77+N83
C89: PASS THROUGH COSTS (EURO's excl. VAT) | D89: BASE YEAR | E89: YEAR 1 | F89: YEAR 2 | G89: YEAR 3 | H89: YEAR 4 | I89: YEAR 5 | J89: 5 Year Total | L89: 5 YEAR + 1 | M89: 5 YEAR + 2 | N89: 7 Year Total
C90: Internal FTE | D90: =SUM(UK:Germany!D90) | E90: =SUM(UK:Germany!E90) | F90: =SUM(UK:Germany!F90) | G90: =SUM(UK:Germany!G90) | H90: =SUM(UK:Germany!H90) | I90: =SUM(UK:Germany!I90) | L90: =SUM(UK:Germany!L90) | M90: =SUM(UK:Germany!M90)
C91: External FTE | D91: =SUM(UK:Germany!D91) | E91: =SUM(UK:Germany!E91) | F91: =SUM(UK:Germany!F91) | G91: =SUM(UK:Germany!G91) | H91: =SUM(UK:Germany!H91) | I91: =SUM(UK:Germany!I91) | L91: =SUM(UK:Germany!L91) | M91: =SUM(UK:Germany!M91)
C92: Total FTE | D92: =SUM(D90:D91) | E92: =SUM(E90:E91) | F92: =SUM(F90:F91) | G92: =SUM(G90:G91) | H92: =SUM(H90:H91) | I92: =SUM(I90:I91) | L92: =SUM(L90:L91) | M92: =SUM(M90:M91)
C94: Salaries | D94: =SUM(UK:Germany!D94) | E94: =SUM(UK:Germany!E94) | F94: =SUM(UK:Germany!F94) | G94: =SUM(UK:Germany!G94) | H94: =SUM(UK:Germany!H94) | I94: =SUM(UK:Germany!I94) | J94: =SUM(E94:I94) | L94: =SUM(UK:Germany!L94) | M94: =SUM(UK:Germany!M94) | N94: =+J94+SUM(L94:M94)
C95: Bonuses | D95: =SUM(UK:Germany!D95) | E95: =SUM(UK:Germany!E95) | F95: =SUM(UK:Germany!F95) | G95: =SUM(UK:Germany!G95) | H95: =SUM(UK:Germany!H95) | I95: =SUM(UK:Germany!I95) | J95: =SUM(E95:I95) | L95: =SUM(UK:Germany!L95) | M95: =SUM(UK:Germany!M95) | N95: =+J95+SUM(L95:M95)
C96: Third party staff, ex IT | D96: =SUM(UK:Germany!D96) | E96: =SUM(UK:Germany!E96) | F96: =SUM(UK:Germany!F96) | G96: =SUM(UK:Germany!G96) | H96: =SUM(UK:Germany!H96) | I96: =SUM(UK:Germany!I96) | J96: =SUM(E96:I96) | L96: =SUM(UK:Germany!L96) | M96: =SUM(UK:Germany!M96) | N96: =+J96+SUM(L96:M96)
C97: Third party IT staff | D97: =SUM(UK:Germany!D97) | E97: =SUM(UK:Germany!E97) | F97: =SUM(UK:Germany!F97) | G97: =SUM(UK:Germany!G97) | H97: =SUM(UK:Germany!H97) | I97: =SUM(UK:Germany!I97) | J97: =SUM(E97:I97) | L97: =SUM(UK:Germany!L97) | M97: =SUM(UK:Germany!M97) | N97: =+J97+SUM(L97:M97)
C98: Employee education | D98: =SUM(UK:Germany!D98) | E98: =SUM(UK:Germany!E98) | F98: =SUM(UK:Germany!F98) | G98: =SUM(UK:Germany!G98) | H98: =SUM(UK:Germany!H98) | I98: =SUM(UK:Germany!I98) | J98: =SUM(E98:I98) | L98: =SUM(UK:Germany!L98) | M98: =SUM(UK:Germany!M98) | N98: =+J98+SUM(L98:M98)
C99: Other staff expenses | D99: =SUM(UK:Germany!D99) | E99: =SUM(UK:Germany!E99) | F99: =SUM(UK:Germany!F99) | G99: =SUM(UK:Germany!G99) | H99: =SUM(UK:Germany!H99) | I99: =SUM(UK:Germany!I99) | J99: =SUM(E99:I99) | L99: =SUM(UK:Germany!L99) | M99: =SUM(UK:Germany!M99) | N99: =+J99+SUM(L99:M99)
C100: Staff expenses | D100: =SUM(D94:D99) | E100: =SUM(E94:E99) | F100: =SUM(F94:F99) | G100: =SUM(G94:G99) | H100: =SUM(H94:H99) | I100: =SUM(I94:I99) | J100: =SUM(E100:I100) | L100: =SUM(L94:L99) | M100: =SUM(M94:M99) | N100: =SUM(N94:N99)
C101: Hardware expenses | D101: =SUM(UK:Germany!D101) | E101: =SUM(UK:Germany!E101) | F101: =SUM(UK:Germany!F101) | G101: =SUM(UK:Germany!G101) | H101: =SUM(UK:Germany!H101) | I101: =SUM(UK:Germany!I101) | J101: =SUM(E101:I101) | L101: =SUM(UK:Germany!L101) | M101: =SUM(UK:Germany!M101) | N101: =+J101+SUM(L101:M101)
C102: Leasing/renting hardware | D102: =SUM(UK:Germany!D102) | E102: =SUM(UK:Germany!E102) | F102: =SUM(UK:Germany!F102) | G102: =SUM(UK:Germany!G102) | H102: =SUM(UK:Germany!H102) | I102: =SUM(UK:Germany!I102) | J102: =SUM(E102:I102) | L102: =SUM(UK:Germany!L102) | M102: =SUM(UK:Germany!M102) | N102: =+J102+SUM(L102:M102)
C103: Software expenses | D103: =SUM(UK:Germany!D103) | E103: =SUM(UK:Germany!E103) | F103: =SUM(UK:Germany!F103) | G103: =SUM(UK:Germany!G103) | H103: =SUM(UK:Germany!H103) | I103: =SUM(UK:Germany!I103) | J103: =SUM(E103:I103) | L103: =SUM(UK:Germany!L103) | M103: =SUM(UK:Germany!M103) | N103: =+J103+SUM(L103:M103)
C104: Leasing/renting/licenses sw | D104: =SUM(UK:Germany!D104) | E104: =SUM(UK:Germany!E104) | F104: =SUM(UK:Germany!F104) | G104: =SUM(UK:Germany!G104) | H104: =SUM(UK:Germany!H104) | I104: =SUM(UK:Germany!I104) | J104: =SUM(E104:I104) | L104: =SUM(UK:Germany!L104) | M104: =SUM(UK:Germany!M104) | N104: =+J104+SUM(L104:M104)
C105: Depreciation hardware | D105: =SUM(UK:Germany!D105) | E105: =SUM(UK:Germany!E105) | F105: =SUM(UK:Germany!F105) | G105: =SUM(UK:Germany!G105) | H105: =SUM(UK:Germany!H105) | I105: =SUM(UK:Germany!I105) | J105: =SUM(E105:I105) | L105: =SUM(UK:Germany!L105) | M105: =SUM(UK:Germany!M105) | N105: =+J105+SUM(L105:M105)
C106: Depreciation software | D106: =SUM(UK:Germany!D106) | E106: =SUM(UK:Germany!E106) | F106: =SUM(UK:Germany!F106) | G106: =SUM(UK:Germany!G106) | H106: =SUM(UK:Germany!H106) | I106: =SUM(UK:Germany!I106) | J106: =SUM(E106:I106) | L106: =SUM(UK:Germany!L106) | M106: =SUM(UK:Germany!M106) | N106: =+J106+SUM(L106:M106)
C107: Outsourcing IT activities | D107: =SUM(UK:Germany!D107) | E107: =SUM(UK:Germany!E107) | F107: =SUM(UK:Germany!F107) | G107: =SUM(UK:Germany!G107) | H107: =SUM(UK:Germany!H107) | I107: =SUM(UK:Germany!I107) | J107: =SUM(E107:I107) | L107: =SUM(UK:Germany!L107) | M107: =SUM(UK:Germany!M107) | N107: =+J107+SUM(L107:M107)
C108: Other IT expenses | D108: =SUM(UK:Germany!D108) | E108: =SUM(UK:Germany!E108) | F108: =SUM(UK:Germany!F108) | G108: =SUM(UK:Germany!G108) | H108: =SUM(UK:Germany!H108) | I108: =SUM(UK:Germany!I108) | J108: =SUM(E108:I108) | L108: =SUM(UK:Germany!L108) | M108: =SUM(UK:Germany!M108) | N108: =+J108+SUM(L108:M108)
C109: EDP expenses | D109: =SUM(D101:D108) | E109: =SUM(E101:E108) | F109: =SUM(F101:F108) | G109: =SUM(G101:G108) | H109: =SUM(H101:H108) | I109: =SUM(I101:I108) | J109: =SUM(E109:I109) | L109: =SUM(L101:L108) | M109: =SUM(M101:M108) | N109: =SUM(N101:N108)
C110: Telecom expenses | D110: =SUM(UK:Germany!D110) | E110: =SUM(UK:Germany!E110) | F110: =SUM(UK:Germany!F110) | G110: =SUM(UK:Germany!G110) | H110: =SUM(UK:Germany!H110) | I110: =SUM(UK:Germany!I110) | J110: =SUM(E110:I110) | L110: =SUM(UK:Germany!L110) | M110: =SUM(UK:Germany!M110) | N110: =+J110+SUM(L110:M110)
C111: Office equipment and supplies | D111: =SUM(UK:Germany!D111) | E111: =SUM(UK:Germany!E111) | F111: =SUM(UK:Germany!F111) | G111: =SUM(UK:Germany!G111) | H111: =SUM(UK:Germany!H111) | I111: =SUM(UK:Germany!I111) | J111: =SUM(E111:I111) | L111: =SUM(UK:Germany!L111) | M111: =SUM(UK:Germany!M111) | N111: =+J111+SUM(L111:M111)
...

Sheet UK
C1: United Kingdom
C2: TOTAL COSTS (US$ excl. VAT) | D2: BASE YEAR | E2: YEAR 1 | F2: YEAR 2 | G2: YEAR 3 | H2: YEAR 4 | I2: YEAR 5 | J2: 5 Year Total | L2: 5 YEAR + 1 | M2: 5 YEAR + 2 | N2: 7 Year Total
C3: Internal FTE | D3: =[1]Consolidated!D3 | E3: =[1]Consolidated!E3 | F3: =[1]Consolidated!F3 | G3: =[1]Consolidated!G3 | H3: =[1]Consolidated!H3 | I3: =[1]Consolidated!I3 | L3: =[1]Consolidated!L3 | M3: =[1]Consolidated!M3 | N3: =[1]Consolidated!N3
C4: External FTE | D4: =[1]Consolidated!D4 | E4: =[1]Consolidated!E4 | F4: =[1]Consolidated!F4 | G4: =[1]Consolidated!G4 | H4: =[1]Consolidated!H4 | I4: =[1]Consolidated!I4 | L4: =[1]Consolidated!L4 | M4: =[1]Consolidated!M4 | N4: =[1]Consolidated!N4
C5: Total FTE | D5: =[1]Consolidated!D5 | E5: =[1]Consolidated!E5 | F5: =[1]Consolidated!F5 | G5: =[1]Consolidated!G5 | H5: =[1]Consolidated!H5 | I5: =[1]Consolidated!I5 | L5: =[1]Consolidated!L5 | M5: =[1]Consolidated!M5 | N5: =[1]Consolidated!N5
C7: Salaries | D7: =(([1]Consolidated!D7)*1000)*(1/0.79941) | E7: =(([1]Consolidated!E7)*1000)*(1/0.79941) | F7: =(([1]Consolidated!F7)*1000)*(1/0.79941) | G7: =(([1]Consolidated!G7)*1000)*(1/0.79941) | H7: =(([1]Consolidated!H7)*1000)*(1/0.79941) | I7: =(([1]Consolidated!I7)*1000)*(1/0.79941) | J7: =(([1]Consolidated!J7)*1000)*(1/0.79941) | L7: =(([1]Consolidated!L7)*1000)*(1/0.79941) | M7: =(([1]Consolidated!M7)*1000)*(1/0.79941) | N7: =(([1]Consolidated!N7)*1000)*(1/0.79941) | P7: 1000
C8: Bonuses | D8: =(([1]Consolidated!D8)*1000)*(1/0.79941) | E8: =(([1]Consolidated!E8)*1000)*(1/0.79941) | F8: =(([1]Consolidated!F8)*1000)*(1/0.79941) | G8: =(([1]Consolidated!G8)*1000)*(1/0.79941) | H8: =(([1]Consolidated!H8)*1000)*(1/0.79941) | I8: =(([1]Consolidated!I8)*1000)*(1/0.79941) | J8: =(([1]Consolidated!J8)*1000)*(1/0.79941) | L8: =(([1]Consolidated!L8)*1000)*(1/0.79941) | M8: =(([1]Consolidated!M8)*1000)*(1/0.79941) | N8: =(([1]Consolidated!N8)*1000)*(1/0.79941) | P8: =1/0.79941 | Q8: Euro to dollar
C9: Third party staff, ex IT | D9: =(([1]Consolidated!D9)*1000)*(1/0.79941) | E9: =(([1]Consolidated!E9)*1000)*(1/0.79941) | F9: =(([1]Consolidated!F9)*1000)*(1/0.79941) | G9: =(([1]Consolidated!G9)*1000)*(1/0.79941) | H9: =(([1]Consolidated!H9)*1000)*(1/0.79941) | I9: =(([1]Consolidated!I9)*1000)*(1/0.79941) | J9: =(([1]Consolidated!J9)*1000)*(1/0.79941) | L9: =(([1]Consolidated!L9)*1000)*(1/0.79941) | M9: =(([1]Consolidated!M9)*1000)*(1/0.79941) | N9: =(([1]Consolidated!N9)*1000)*(1/0.79941)
C10: Third party IT staff | D10: =(([1]Consolidated!D10)*1000)*(1/0.79941) | E10: =(([1]Consolidated!E10)*1000)*(1/0.79941) | F10: =(([1]Consolidated!F10)*1000)*(1/0.79941) | G10: =(([1]Consolidated!G10)*1000)*(1/0.79941) | H10: =(([1]Consolidated!H10)*1000)*(1/0.79941) | I10: =(([1]Consolidated!I10)*1000)*(1/0.79941) | J10: =(([1]Consolidated!J10)*1000)*(1/0.79941) | L10: =(([1]Consolidated!L10)*1000)*(1/0.79941) | M10: =(([1]Consolidated!M10)*1000)*(1/0.79941) | N10: =(([1]Consolidated!N10)*1000)*(1/0.79941)
C11: Employee education | D11: =(([1]Consolidated!D11)*1000)*(1/0.79941) | E11: =(([1]Consolidated!E11)*1000)*(1/0.79941) | F11: =(([1]Consolidated!F11)*1000)*(1/0.79941) | G11: =(([1]Consolidated!G11)*1000)*(1/0.79941) | H11: =(([1]Consolidated!H11)*1000)*(1/0.79941) | I11: =(([1]Consolidated!I11)*1000)*(1/0.79941) | J11: =(([1]Consolidated!J11)*1000)*(1/0.79941) | L11: =(([1]Consolidated!L11)*1000)*(1/0.79941) | M11: =(([1]Consolidated!M11)*1000)*(1/0.79941) | N11: =(([1]Consolidated!N11)*1000)*(1/0.79941)
C12: Other staff expenses | D12: =(([1]Consolidated!D12)*1000)*(1/0.79941) | E12: =(([1]Consolidated!E12)*1000)*(1/0.79941) | F12: =(([1]Consolidated!F12)*1000)*(1/0.79941) | G12: =(([1]Consolidated!G12)*1000)*(1/0.79941) | H12: =(([1]Consolidated!H12)*1000)*(1/0.79941) | I12: =(([1]Consolidated!I12)*1000)*(1/0.79941) | J12: =(([1]Consolidated!J12)*1000)*(1/0.79941) | L12: =(([1]Consolidated!L12)*1000)*(1/0.79941) | M12: =(([1]Consolidated!M12)*1000)*(1/0.79941) | N12: =(([1]Consolidated!N12)*1000)*(1/0.79941)
C13: Staff expenses | D13: =(([1]Consolidated!D13)*1000)*(1/0.79941) | E13: =(([1]Consolidated!E13)*1000)*(1/0.79941) | F13: =(([1]Consolidated!F13)*1000)*(1/0.79941) | G13: =(([1]Consolidated!G13)*1000)*(1/0.79941) | H13: =(([1]Consolidated!H13)*1000)*(1/0.79941) | I13: =(([1]Consolidated!I13)*1000)*(1/0.79941) | J13: =(([1]Consolidated!J13)*1000)*(1/0.79941) | L13: =(([1]Consolidated!L13)*1000)*(1/0.79941) | M13: =(([1]Consolidated!M13)*1000)*(1/0.79941) | N13: =(([1]Consolidated!N13)*1000)*(1/0.79941)
C14: Hardware expenses | D14: =(([1]Consolidated!D14)*1000)*(1/0.79941) | E14: =(([1]Consolidated!E14)*1000)*(1/0.79941) | F14: =(([1]Consolidated!F14)*1000)*(1/0.79941) | G14: =(([1]Consolidated!G14)*1000)*(1/0.79941) | H14: =(([1]Consolidated!H14)*1000)*(1/0.79941) | I14: =(([1]Consolidated!I14)*1000)*(1/0.79941) | J14: =(([1]Consolidated!J14)*1000)*(1/0.79941) | L14: =(([1]Consolidated!L14)*1000)*(1/0.79941) | M14: =(([1]Consolidated!M14)*1000)*(1/0.79941) | N14: =(([1]Consolidated!N14)*1000)*(1/0.79941)
C15: Leasing/renting hardware | D15: =(([1]Consolidated!D15)*1000)*(1/0.79941) | E15: =(([1]Consolidated!E15)*1000)*(1/0.79941) | F15: =(([1]Consolidated!F15)*1000)*(1/0.79941) | G15: =(([1]Consolidated!G15)*1000)*(1/0.79941) | H15: =(([1]Consolidated!H15)*1000)*(1/0.79941) | I15: =(([1]Consolidated!I15)*1000)*(1/0.79941) | J15: =(([1]Consolidated!J15)*1000)*(1/0.79941) | L15: =(([1]Consolidated!L15)*1000)*(1/0.79941) | M15: =(([1]Consolidated!M15)*1000)*(1/0.79941) | N15: =(([1]Consolidated!N15)*1000)*(1/0.79941)
C16: Software expenses | D16: =(([1]Consolidated!D16)*1000)*(1/0.79941) | E16: =(([1]Consolidated!E16)*1000)*(1/0.79941) | F16: =(([1]Consolidated!F16)*1000)*(1/0.79941) | G16: =(([1]Consolidated!G16)*1000)*(1/0.79941) | H16: =(([1]Consolidated!H16)*1000)*(1/0.79941) | I16: =(([1]Consolidated!I16)*1000)*(1/0.79941) | J16: =(([1]Consolidated!J16)*1000)*(1/0.79941) | L16: =(([1]Consolidated!L16)*1000)*(1/0.79941) | M16: =(([1]Consolidated!M16)*1000)*(1/0.79941) | N16: =(([1]Consolidated!N16)*1000)*(1/0.79941)
C17: Leasing/renting/licenses sw | D17: =(([1]Consolidated!D17)*1000)*(1/0.79941) | E17: =(([1]Consolidated!E17)*1000)*(1/0.79941) | F17: =(([1]Consolidated!F17)*1000)*(1/0.79941) | G17: =(([1]Consolidated!G17)*1000)*(1/0.79941) | H17: =(([1]Consolidated!H17)*1000)*(1/0.79941) | I17: =(([1]Consolidated!I17)*1000)*(1/0.79941) | J17: =(([1]Consolidated!J17)*1000)*(1/0.79941) | L17: =(([1]Consolidated!L17)*1000)*(1/0.79941) | M17: =(([1]Consolidated!M17)*1000)*(1/0.79941) | N17: =(([1]Consolidated!N17)*1000)*(1/0.79941)
C18: Depreciation hardware | D18: =(([1]Consolidated!D18)*1000)*(1/0.79941) | E18: =(([1]Consolidated!E18)*1000)*(1/0.79941) | F18: =(([1]Consolidated!F18)*1000)*(1/0.79941) | G18: =(([1]Consolidated!G18)*1000)*(1/0.79941) | H18: =(([1]Consolidated!H18)*1000)*(1/0.79941) | I18: =(([1]Consolidated!I18)*1000)*(1/0.79941) | J18: =(([1]Consolidated!J18)*1000)*(1/0.79941) | L18: =(([1]Consolidated!L18)*1000)*(1/0.79941) | M18: =(([1]Consolidated!M18)*1000)*(1/0.79941) | N18: =(([1]Consolidated!N18)*1000)*(1/0.79941)
C19: Depreciation software | D19: =(([1]Consolidated!D19)*1000)*(1/0.79941) | E19: =(([1]Consolidated!E19)*1000)*(1/0.79941) | F19: =(([1]Consolidated!F19)*1000)*(1/0.79941) | G19: =(([1]Consolidated!G19)*1000)*(1/0.79941) | H19: =(([1]Consolidated!H19)*1000)*(1/0.79941) | I19: =(([1]Consolidated!I19)*1000)*(1/0.79941) | J19: =(([1]Consolidated!J19)*1000)*(1/0.79941) | L19: =(([1]Consolidated!L19)*1000)*(1/0.79941) | M19: =(([1]Consolidated!M19)*1000)*(1/0.79941) | N19: =(([1]Consolidated!N19)*1000)*(1/0.79941)
C20: Outsourcing IT activities | D20: =(([1]Consolidated!D20)*1000)*(1/0.79941) | E20: =(([1]Consolidated!E20)*1000)*(1/0.79941) | F20: =(([1]Consolidated!F20)*1000)*(1/0.79941) | G20: =(([1]Consolidated!G20)*1000)*(1/0.79941) | H20: =(([1]Consolidated!H20)*1000)*(1/0.79941) | I20: =(([1]Consolidated!I20)*1000)*(1/0.79941) | J20: =(([1]Consolidated!J20)*1000)*(1/0.79941) | L20: =(([1]Consolidated!L20)*1000)*(1/0.79941) | M20: =(([1]Consolidated!M20)*1000)*(1/0.79941) | N20: =(([1]Consolidated!N20)*1000)*(1/0.79941)
... C34: Operating expenses | D34: =(([1]Consolidated!D34)*1000)*(1/0.79941) | E34: =(([1]Consolidated!E34)*1000)*(1/0.79941) | F34: =(([1]Consolidated!F34)*1000)*(1/0.79941) | G34: =(([1]Consolidated!G34)*1000)*(1/0.79941) | H34: =(([1]Consolidated!H34)*1000)*(1/0.79941) | I34: =(([1]Consolidated!I34)*1000)*(1/0.79941) | J34: =(([1]Consolidated!J34)*1000)*(1/0.79941) | L34: =(([1]Consolidated!L34)*1000)*(1/0.79941) | M34: =(([1]Consolidated!M34)*1000)*(1/0.79941) | N34: =(([1]Consolidated!N34)*1000)*(1/0.79941)
D35: =0*(1/0.79941) | E35: =0*(1/0.79941) | F35: =0*(1/0.79941) | G35: =0*(1/0.79941) | H35: =0*(1/0.79941) | I35: =0*(1/0.79941) | J35: =0*(1/0.79941) | L35: =0*(1/0.79941) | M35: =0*(1/0.79941) | N35: =0*(1/0.79941)
C36: HR & Comms | D36: =(([1]Consolidated!D36)*1000)*(1/0.79941) | E36: =(([1]Consolidated!E36)*1000)*(1/0.79941) | F36: =(([1]Consolidated!F36)*1000)*(1/0.79941) | G36: =(([1]Consolidated!G36)*1000)*(1/0.79941) | H36: =(([1]Consolidated!H36)*1000)*(1/0.79941) | I36: =(([1]Consolidated!I36)*1000)*(1/0.79941) | J36: =(([1]Consolidated!J36)*1000)*(1/0.79941) | L36: =(([1]Consolidated!L36)*1000)*(1/0.79941) | M36: =(([1]Consolidated!M36)*1000)*(1/0.79941) | N36: =(([1]Consolidated!N36)*1000)*(1/0.79941)
C37: Finance & Business Support | D37: =(([1]Consolidated!D37)*1000)*(1/0.79941) | E37: =(([1]Consolidated!E37)*1000)*(1/0.79941) | F37: =(([1]Consolidated!F37)*1000)*(1/0.79941) | G37: =(([1]Consolidated!G37)*1000)*(1/0.79941) | H37: =(([1]Consolidated!H37)*1000)*(1/0.79941) | I37: =(([1]Consolidated!I37)*1000)*(1/0.79941) | J37: =(([1]Consolidated!J37)*1000)*(1/0.79941) | L37: =(([1]Consolidated!L37)*1000)*(1/0.79941) | M37: =(([1]Consolidated!M37)*1000)*(1/0.79941) | N37: =(([1]Consolidated!N37)*1000)*(1/0.79941)
C38: IT alloc | D38: =(([1]Consolidated!D38)*1000)*(1/0.79941) | E38: =(([1]Consolidated!E38)*1000)*(1/0.79941) | F38: =(([1]Consolidated!F38)*1000)*(1/0.79941) | G38: =(([1]Consolidated!G38)*1000)*(1/0.79941) | H38: =(([1]Consolidated!H38)*1000)*(1/0.79941) | I38: =(([1]Consolidated!I38)*1000)*(1/0.79941) | J38: =(([1]Consolidated!J38)*1000)*(1/0.79941) | L38: =(([1]Consolidated!L38)*1000)*(1/0.79941) | M38: =(([1]Consolidated!M38)*1000)*(1/0.79941) | N38: =(([1]Consolidated!N38)*1000)*(1/0.79941)
C39: Facilities Management | D39: =(([1]Consolidated!D39)*1000)*(1/0.79941) | E39: =(([1]Consolidated!E39)*1000)*(1/0.79941) | F39: =(([1]Consolidated!F39)*1000)*(1/0.79941) | G39: =(([1]Consolidated!G39)*1000)*(1/0.79941) | H39: =(([1]Consolidated!H39)*1000)*(1/0.79941) | I39: =(([1]Consolidated!I39)*1000)*(1/0.79941) | J39: =(([1]Consolidated!J39)*1000)*(1/0.79941) | L39: =(([1]Consolidated!L39)*1000)*(1/0.79941) | M39: =(([1]Consolidated!M39)*1000)*(1/0.79941) | N39: =(([1]Consolidated!N39)*1000)*(1/0.79941)
C40: Overheads | D40: =(([1]Consolidated!D40)*1000)*(1/0.79941) | E40: =(([1]Consolidated!E40)*1000)*(1/0.79941) | F40: =(([1]Consolidated!F40)*1000)*(1/0.79941) | G40: =(([1]Consolidated!G40)*1000)*(1/0.79941) | H40: =(([1]Consolidated!H40)*1000)*(1/0.79941) | I40: =(([1]Consolidated!I40)*1000)*(1/0.79941) | J40: =(([1]Consolidated!J40)*1000)*(1/0.79941) | L40: =(([1]Consolidated!L40)*1000)*(1/0.79941) | M40: =(([1]Consolidated!M40)*1000)*(1/0.79941) | N40: =(([1]Consolidated!N40)*1000)*(1/0.79941)
C41: 0 | D41: =(([1]Consolidated!D41)*1000)*(1/0.79941) | E41: =(([1]Consolidated!E41)*1000)*(1/0.79941) | F41: =(([1]Consolidated!F41)*1000)*(1/0.79941) | G41: =(([1]Consolidated!G41)*1000)*(1/0.79941) | H41: =(([1]Consolidated!H41)*1000)*(1/0.79941) | I41: =(([1]Consolidated!I41)*1000)*(1/0.79941) | J41: =(([1]Consolidated!J41)*1000)*(1/0.79941) | L41: =(([1]Consolidated!L41)*1000)*(1/0.79941) | M41: =(([1]Consolidated!M41)*1000)*(1/0.79941) | N41: =(([1]Consolidated!N41)*1000)*(1/0.79941)
C42: Total Operating Costs (incl. O/H) | D42: =(([1]Consolidated!D42)*1000)*(1/0.79941) | E42: =(([1]Consolidated!E42)*1000)*(1/0.79941) | F42: =(([1]Consolidated!F42)*1000)*(1/0.79941) | G42: =(([1]Consolidated!G42)*1000)*(1/0.79941) | H42: =(([1]Consolidated!H42)*1000)*(1/0.79941) | I42: =(([1]Consolidated!I42)*1000)*(1/0.79941) | J42: =(([1]Consolidated!J42)*1000)*(1/0.79941) | L42: =(([1]Consolidated!L42)*1000)*(1/0.79941) | M42: =(([1]Consolidated!M42)*1000)*(1/0.79941) | N42: =(([1]Consolidated!N42)*1000)*(1/0.79941)
C45: SUPPLIER ASSUMED COSTS (US$ excl. VAT) | D45: =[1]Consolidated!D45 | E45: =[1]Consolidated!E45 | F45: =[1]Consolidated!F45 | G45: =[1]Consolidated!G45 | H45: =[1]Consolidated!H45 | I45: =[1]Consolidated!I45 | J45: =[1]Consolidated!J45 | L45: =[1]Consolidated!L45 | M45: =[1]Consolidated!M45 | N45: =[1]Consolidated!N45
C46: Internal FTE | D46: =[1]Consolidated!D46 | E46: =[1]Consolidated!E46 | F46: =[1]Consolidated!F46 | G46: =[1]Consolidated!G46 | H46: =[1]Consolidated!H46 | I46: =[1]Consolidated!I46 | L46: =[1]Consolidated!L46 | M46: =[1]Consolidated!M46 | N46: =[1]Consolidated!N46
C47: External FTE | D47: =[1]Consolidated!D47 | E47: =[1]Consolidated!E47 | F47: =[1]Consolidated!F47 | G47: =[1]Consolidated!G47 | H47: =[1]Consolidated!H47 | I47: =[1]Consolidated!I47 | L47: =[1]Consolidated!L47 | M47: =[1]Consolidated!M47 | N47: =[1]Consolidated!N47
C48: Total FTE | D48: =[1]Consolidated!D48 | E48: =[1]Consolidated!E48 | F48: =[1]Consolidated!F48 | G48: =[1]Consolidated!G48 | H48: =[1]Consolidated!H48 | I48: =[1]Consolidated!I48 | L48: =[1]Consolidated!L48 | M48: =[1]Consolidated!M48 | N48: =[1]Consolidated!N48
C50: Salaries | D50: =(([1]Consolidated!D50)*1000)*(1/0.79941) | E50: =(([1]Consolidated!E50)*1000)*(1/0.79941) | F50: =(([1]Consolidated!F50)*1000)*(1/0.79941) | G50: =(([1]Consolidated!G50)*1000)*(1/0.79941) | H50: =(([1]Consolidated!H50)*1000)*(1/0.79941) | I50: =(([1]Consolidated!I50)*1000)*(1/0.79941) | J50: =(([1]Consolidated!J50)*1000)*(1/0.79941) | L50: =(([1]Consolidated!L50)*1000)*(1/0.79941) | M50: =(([1]Consolidated!M50)*1000)*(1/0.79941) | N50: =(([1]Consolidated!N50)*1000)*(1/0.79941)
C51: Bonuses | D51: =(([1]Consolidated!D51)*1000)*(1/0.79941) | E51: =(([1]Consolidated!E51)*1000)*(1/0.79941) | F51: =(([1]Consolidated!F51)*1000)*(1/0.79941) | G51: =(([1]Consolidated!G51)*1000)*(1/0.79941) | H51: =(([1]Consolidated!H51)*1000)*(1/0.79941) | I51: =(([1]Consolidated!I51)*1000)*(1/0.79941) | J51: =(([1]Consolidated!J51)*1000)*(1/0.79941) | L51: =(([1]Consolidated!L51)*1000)*(1/0.79941) | M51: =(([1]Consolidated!M51)*1000)*(1/0.79941) | N51: =(([1]Consolidated!N51)*1000)*(1/0.79941)
C52: Third party staff, ex IT | D52: =(([1]Consolidated!D52)*1000)*(1/0.79941) | E52: =(([1]Consolidated!E52)*1000)*(1/0.79941) | F52: =(([1]Consolidated!F52)*1000)*(1/0.79941) | G52: =(([1]Consolidated!G52)*1000)*(1/0.79941) | H52: =(([1]Consolidated!H52)*1000)*(1/0.79941) | I52: =(([1]Consolidated!I52)*1000)*(1/0.79941) | J52: =(([1]Consolidated!J52)*1000)*(1/0.79941) | L52: =(([1]Consolidated!L52)*1000)*(1/0.79941) | M52: =(([1]Consolidated!M52)*1000)*(1/0.79941) | N52: =(([1]Consolidated!N52)*1000)*(1/0.79941)
C53: Third party IT staff | D53: =(([1]Consolidated!D53)*1000)*(1/0.79941) | E53: =(([1]Consolidated!E53)*1000)*(1/0.79941) | F53: =(([1]Consolidated!F53)*1000)*(1/0.79941) | G53: =(([1]Consolidated!G53)*1000)*(1/0.79941) | H53: =(([1]Consolidated!H53)*1000)*(1/0.79941) | I53: =(([1]Consolidated!I53)*1000)*(1/0.79941) | J53: =(([1]Consolidated!J53)*1000)*(1/0.79941) | L53: =(([1]Consolidated!L53)*1000)*(1/0.79941) | M53: =(([1]Consolidated!M53)*1000)*(1/0.79941) | N53: =(([1]Consolidated!N53)*1000)*(1/0.79941)
C54: Employee education | D54: =(([1]Consolidated!D54)*1000)*(1/0.79941) | E54: =(([1]Consolidated!E54)*1000)*(1/0.79941) | F54: =(([1]Consolidated!F54)*1000)*(1/0.79941) | G54: =(([1]Consolidated!G54)*1000)*(1/0.79941) | H54: =(([1]Consolidated!H54)*1000)*(1/0.79941) | I54: =(([1]Consolidated!I54)*1000)*(1/0.79941) | J54: =(([1]Consolidated!J54)*1000)*(1/0.79941) | L54: =(([1]Consolidated!L54)*1000)*(1/0.79941) | M54: =(([1]Consolidated!M54)*1000)*(1/0.79941) | N54: =(([1]Consolidated!N54)*1000)*(1/0.79941)
C55: Other staff expenses | D55: =(([1]Consolidated!D55)*1000)*(1/0.79941) | E55: =(([1]Consolidated!E55)*1000)*(1/0.79941) | F55: =(([1]Consolidated!F55)*1000)*(1/0.79941) | G55: =(([1]Consolidated!G55)*1000)*(1/0.79941) | H55: =(([1]Consolidated!H55)*1000)*(1/0.79941) | I55: =(([1]Consolidated!I55)*1000)*(1/0.79941) | J55: =(([1]Consolidated!J55)*1000)*(1/0.79941) | L55: =(([1]Consolidated!L55)*1000)*(1/0.79941) | M55: =(([1]Consolidated!M55)*1000)*(1/0.79941) | N55: =(([1]Consolidated!N55)*1000)*(1/0.79941)
C56: Staff expenses | D56: =(([1]Consolidated!D56)*1000)*(1/0.79941) | E56: =(([1]Consolidated!E56)*1000)*(1/0.79941) | F56: =(([1]Consolidated!F56)*1000)*(1/0.79941) | G56: =(([1]Consolidated!G56)*1000)*(1/0.79941) | H56: =(([1]Consolidated!H56)*1000)*(1/0.79941) | I56: =(([1]Consolidated!I56)*1000)*(1/0.79941) | J56: =(([1]Consolidated!J56)*1000)*(1/0.79941) | L56: =(([1]Consolidated!L56)*1000)*(1/0.79941) | M56: =(([1]Consolidated!M56)*1000)*(1/0.79941) | N56: =(([1]Consolidated!N56)*1000)*(1/0.79941)
C57: Hardware expenses | D57: =(([1]Consolidated!D57)*1000)*(1/0.79941) | E57: =(([1]Consolidated!E57)*1000)*(1/0.79941) | F57: =(([1]Consolidated!F57)*1000)*(1/0.79941) | G57: =(([1]Consolidated!G57)*1000)*(1/0.79941) | H57: =(([1]Consolidated!H57)*1000)*(1/0.79941) | I57: =(([1]Consolidated!I57)*1000)*(1/0.79941) | J57: =(([1]Consolidated!J57)*1000)*(1/0.79941) | L57: =(([1]Consolidated!L57)*1000)*(1/0.79941) | M57: =(([1]Consolidated!M57)*1000)*(1/0.79941) | N57: =(([1]Consolidated!N57)*1000)*(1/0.79941)
C58: Leasing/renting hardware | D58: =(([1]Consolidated!D58)*1000)*(1/0.79941) | E58: =(([1]Consolidated!E58)*1000)*(1/0.79941) | F58: =(([1]Consolidated!F58)*1000)*(1/0.79941) | G58: =(([1]Consolidated!G58)*1000)*(1/0.79941) | H58: =(([1]Consolidated!H58)*1000)*(1/0.79941) | I58: =(([1]Consolidated!I58)*1000)*(1/0.79941) | J58: =(([1]Consolidated!J58)*1000)*(1/0.79941) | L58: =(([1]Consolidated!L58)*1000)*(1/0.79941) | M58: =(([1]Consolidated!M58)*1000)*(1/0.79941) | N58: =(([1]Consolidated!N58)*1000)*(1/0.79941)
C59: Software expenses | D59: =(([1]Consolidated!D59)*1000)*(1/0.79941) | E59: =(([1]Consolidated!E59)*1000)*(1/0.79941) | F59: =(([1]Consolidated!F59)*1000)*(1/0.79941) | G59: =(([1]Consolidated!G59)*1000)*(1/0.79941) | H59: =(([1]Consolidated!H59)*1000)*(1/0.79941) | I59: =(([1]Consolidated!I59)*1000)*(1/0.79941) | J59: =(([1]Consolidated!J59)*1000)*(1/0.79941) | L59: =(([1]Consolidated!L59)*1000)*(1/0.79941) | M59: =(([1]Consolidated!M59)*1000)*(1/0.79941) | N59: =(([1]Consolidated!N59)*1000)*(1/0.79941)
C60: Leasing/renting/licenses sw | D60: =(([1]Consolidated!D60)*1000)*(1/0.79941) | E60: =(([1]Consolidated!E60)*1000)*(1/0.79941) | F60: =(([1]Consolidated!F60)*1000)*(1/0.79941) | G60: =(([1]Consolidated!G60)*1000)*(1/0.79941) | H60: =(([1]Consolidated!H60)*1000)*(1/0.79941) | I60: =(([1]Consolidated!I60)*1000)*(1/0.79941) | J60: =(([1]Consolidated!J60)*1000)*(1/0.79941) | L60: =(([1]Consolidated!L60)*1000)*(1/0.79941) | M60: =(([1]Consolidated!M60)*1000)*(1/0.79941) | N60: =(([1]Consolidated!N60)*1000)*(1/0.79941)
C61: Depreciation hardware | D61: =(([1]Consolidated!D61)*1000)*(1/0.79941) | E61: =(([1]Consolidated!E61)*1000)*(1/0.79941) | F61: =(([1]Consolidated!F61)*1000)*(1/0.79941) | G61: =(([1]Consolidated!G61)*1000)*(1/0.79941) | H61: =(([1]Consolidated!H61)*1000)*(1/0.79941) | I61: =(([1]Consolidated!I61)*1000)*(1/0.79941) | J61: =(([1]Consolidated!J61)*1000)*(1/0.79941) | L61: =(([1]Consolidated!L61)*1000)*(1/0.79941) | M61: =(([1]Consolidated!M61)*1000)*(1/0.79941) | N61: =(([1]Consolidated!N61)*1000)*(1/0.79941)
... C77: Operating expenses | D77: =(([1]Consolidated!D77)*1000)*(1/0.79941) | E77: =(([1]Consolidated!E77)*1000)*(1/0.79941) | F77: =(([1]Consolidated!F77)*1000)*(1/0.79941) | G77: =(([1]Consolidated!G77)*1000)*(1/0.79941) | H77: =(([1]Consolidated!H77)*1000)*(1/0.79941) | I77: =(([1]Consolidated!I77)*1000)*(1/0.79941) | J77: =(([1]Consolidated!J77)*1000)*(1/0.79941) | L77: =(([1]Consolidated!L77)*1000)*(1/0.79941) | M77: =(([1]Consolidated!M77)*1000)*(1/0.79941) | N77: =(([1]Consolidated!N77)*1000)*(1/0.79941)
D78: =0*(1/0.79941) | E78: =0*(1/0.79941) | F78: =0*(1/0.79941) | G78: =0*(1/0.79941) | H78: =0*(1/0.79941) | I78: =0*(1/0.79941) | J78: =0*(1/0.79941) | L78: =0*(1/0.79941) | M78: =0*(1/0.79941) | N78: =0*(1/0.79941)
C79: HR & Comms | D79: =(([1]Consolidated!D79)*1000)*(1/0.79941) | E79: =(([1]Consolidated!E79)*1000)*(1/0.79941) | F79: =(([1]Consolidated!F79)*1000)*(1/0.79941) | G79: =(([1]Consolidated!G79)*1000)*(1/0.79941) | H79: =(([1]Consolidated!H79)*1000)*(1/0.79941) | I79: =(([1]Consolidated!I79)*1000)*(1/0.79941) | J79: =(([1]Consolidated!J79)*1000)*(1/0.79941) | L79: =(([1]Consolidated!L79)*1000)*(1/0.79941) | M79: =(([1]Consolidated!M79)*1000)*(1/0.79941) | N79: =(([1]Consolidated!N79)*1000)*(1/0.79941)
C80: Finance & Business Support | D80: =(([1]Consolidated!D80)*1000)*(1/0.79941) | E80: =(([1]Consolidated!E80)*1000)*(1/0.79941) | F80: =(([1]Consolidated!F80)*1000)*(1/0.79941) | G80: =(([1]Consolidated!G80)*1000)*(1/0.79941) | H80: =(([1]Consolidated!H80)*1000)*(1/0.79941) | I80: =(([1]Consolidated!I80)*1000)*(1/0.79941) | J80: =(([1]Consolidated!J80)*1000)*(1/0.79941) | L80: =(([1]Consolidated!L80)*1000)*(1/0.79941) | M80: =(([1]Consolidated!M80)*1000)*(1/0.79941) | N80: =(([1]Consolidated!N80)*1000)*(1/0.79941)
C81: IT alloc | D81: =(([1]Consolidated!D81)*1000)*(1/0.79941) | E81: =(([1]Consolidated!E81)*1000)*(1/0.79941) | F81: =(([1]Consolidated!F81)*1000)*(1/0.79941) | G81: =(([1]Consolidated!G81)*1000)*(1/0.79941) | H81: =(([1]Consolidated!H81)*1000)*(1/0.79941) | I81: =(([1]Consolidated!I81)*1000)*(1/0.79941) | J81: =(([1]Consolidated!J81)*1000)*(1/0.79941) | L81: =(([1]Consolidated!L81)*1000)*(1/0.79941) | M81: =(([1]Consolidated!M81)*1000)*(1/0.79941) | N81: =(([1]Consolidated!N81)*1000)*(1/0.79941)
C82: Facilities Management | D82: =(([1]Consolidated!D82)*1000)*(1/0.79941) | E82: =(([1]Consolidated!E82)*1000)*(1/0.79941) | F82: =(([1]Consolidated!F82)*1000)*(1/0.79941) | G82: =(([1]Consolidated!G82)*1000)*(1/0.79941) | H82: =(([1]Consolidated!H82)*1000)*(1/0.79941) | I82: =(([1]Consolidated!I82)*1000)*(1/0.79941) | J82: =(([1]Consolidated!J82)*1000)*(1/0.79941) | L82: =(([1]Consolidated!L82)*1000)*(1/0.79941) | M82: =(([1]Consolidated!M82)*1000)*(1/0.79941) | N82: =(([1]Consolidated!N82)*1000)*(1/0.79941)
C83: Overheads | D83: =(([1]Consolidated!D83)*1000)*(1/0.79941) | E83: =(([1]Consolidated!E83)*1000)*(1/0.79941) | F83: =(([1]Consolidated!F83)*1000)*(1/0.79941) | G83: =(([1]Consolidated!G83)*1000)*(1/0.79941) | H83: =(([1]Consolidated!H83)*1000)*(1/0.79941) | I83: =(([1]Consolidated!I83)*1000)*(1/0.79941) | J83: =(([1]Consolidated!J83)*1000)*(1/0.79941) | L83: =(([1]Consolidated!L83)*1000)*(1/0.79941) | M83: =(([1]Consolidated!M83)*1000)*(1/0.79941) | N83: =(([1]Consolidated!N83)*1000)*(1/0.79941)
D84: =0*(1/0.79941) | E84: =0*(1/0.79941) | F84: =0*(1/0.79941) | G84: =0*(1/0.79941) | H84: =0*(1/0.79941) | I84: =0*(1/0.79941) | J84: =0*(1/0.79941) | L84: =0*(1/0.79941) | M84: =0*(1/0.79941) | N84: =0*(1/0.79941)
C85: Total Operating Costs (incl. O/H) | D85: =(([1]Consolidated!D85)*1000)*(1/0.79941) | E85: =(([1]Consolidated!E85)*1000)*(1/0.79941) | F85: =(([1]Consolidated!F85)*1000)*(1/0.79941) | G85: =(([1]Consolidated!G85)*1000)*(1/0.79941) | H85: =(([1]Consolidated!H85)*1000)*(1/0.79941) | I85: =(([1]Consolidated!I85)*1000)*(1/0.79941) | J85: =(([1]Consolidated!J85)*1000)*(1/0.79941) | L85: =(([1]Consolidated!L85)*1000)*(1/0.79941) | M85: =(([1]Consolidated!M85)*1000)*(1/0.79941) | N85: =(([1]Consolidated!N85)*1000)*(1/0.79941)
C89: PASS THROUGH COSTS (US$ excl. VAT) | D89: =[1]Consolidated!D89 | E89: =[1]Consolidated!E89 | F89: =[1]Consolidated!F89 | G89: =[1]Consolidated!G89 | H89: =[1]Consolidated!H89 | I89: =[1]Consolidated!I89 | J89: =[1]Consolidated!J89 | L89: =[1]Consolidated!L89 | M89: =[1]Consolidated!M89 | N89: =[1]Consolidated!N89
C90: Internal FTE | D90: =([1]Consolidated!D90)*(1/0.79941) | E90: =([1]Consolidated!E90)*(1/0.79941) | F90: =([1]Consolidated!F90)*(1/0.79941) | G90: =([1]Consolidated!G90)*(1/0.79941) | H90: =([1]Consolidated!H90)*(1/0.79941) | I90: =([1]Consolidated!I90)*(1/0.79941) | L90: =([1]Consolidated!L90)*(1/0.79941) | M90: =([1]Consolidated!M90)*(1/0.79941) | N90: =([1]Consolidated!N90)*(1/0.79941)
C91: External FTE | D91: =([1]Consolidated!D91)*(1/0.79941) | E91: =([1]Consolidated!E91)*(1/0.79941) | F91: =([1]Consolidated!F91)*(1/0.79941) | G91: =([1]Consolidated!G91)*(1/0.79941) | H91: =([1]Consolidated!H91)*(1/0.79941) | I91: =([1]Consolidated!I91)*(1/0.79941) | L91: =([1]Consolidated!L91)*(1/0.79941) | M91: =([1]Consolidated!M91)*(1/0.79941) | N91: =([1]Consolidated!N91)*(1/0.79941)
C92: Total FTE | D92: =([1]Consolidated!D92)*(1/0.79941) | E92: =([1]Consolidated!E92)*(1/0.79941) | F92: =([1]Consolidated!F92)*(1/0.79941) | G92: =([1]Consolidated!G92)*(1/0.79941) | H92: =([1]Consolidated!H92)*(1/0.79941) | I92: =([1]Consolidated!I92)*(1/0.79941) | L92: =([1]Consolidated!L92)*(1/0.79941) | M92: =([1]Consolidated!M92)*(1/0.79941) | N92: =([1]Consolidated!N92)*(1/0.79941)
D93: =0*(1/0.79941) | E93: =0*(1/0.79941) | F93: =0*(1/0.79941) | G93: =0*(1/0.79941) | H93: =0*(1/0.79941) | I93: =0*(1/0.79941) | L93: =0*(1/0.79941) | M93: =0*(1/0.79941) | N93: =0*(1/0.79941)
C94: Salaries | D94: =(([1]Consolidated!D94)*1000)*(1/0.79941) | E94: =(([1]Consolidated!E94)*1000)*(1/0.79941) | F94: =(([1]Consolidated!F94)*1000)*(1/0.79941) | G94: =(([1]Consolidated!G94)*1000)*(1/0.79941) | H94: =(([1]Consolidated!H94)*1000)*(1/0.79941) | I94: =(([1]Consolidated!I94)*1000)*(1/0.79941) | J94: =(([1]Consolidated!J94)*1000)*(1/0.79941) | L94: =(([1]Consolidated!L94)*1000)*(1/0.79941) | M94: =(([1]Consolidated!M94)*1000)*(1/0.79941) | N94: =(([1]Consolidated!N94)*1000)*(1/0.79941)
C95: Bonuses | D95: =(([1]Consolidated!D95)*1000)*(1/0.79941) | E95: =(([1]Consolidated!E95)*1000)*(1/0.79941) | F95: =(([1]Consolidated!F95)*1000)*(1/0.79941) | G95: =(([1]Consolidated!G95)*1000)*(1/0.79941) | H95: =(([1]Consolidated!H95)*1000)*(1/0.79941) | I95: =(([1]Consolidated!I95)*1000)*(1/0.79941) | J95: =(([1]Consolidated!J95)*1000)*(1/0.79941) | L95: =(([1]Consolidated!L95)*1000)*(1/0.79941) | M95: =(([1]Consolidated!M95)*1000)*(1/0.79941) | N95: =(([1]Consolidated!N95)*1000)*(1/0.79941)
C96: Third party staff, ex IT | D96: =(([1]Consolidated!D96)*1000)*(1/0.79941) | E96: =(([1]Consolidated!E96)*1000)*(1/0.79941) | F96: =(([1]Consolidated!F96)*1000)*(1/0.79941) | G96: =(([1]Consolidated!G96)*1000)*(1/0.79941) | H96: =(([1]Consolidated!H96)*1000)*(1/0.79941) | I96: =(([1]Consolidated!I96)*1000)*(1/0.79941) | J96: =(([1]Consolidated!J96)*1000)*(1/0.79941) | L96: =(([1]Consolidated!L96)*1000)*(1/0.79941) | M96: =(([1]Consolidated!M96)*1000)*(1/0.79941) | N96: =(([1]Consolidated!N96)*1000)*(1/0.79941)
C97: Third party IT staff | D97: =(([1]Consolidated!D97)*1000)*(1/0.79941) | E97: =(([1]Consolidated!E97)*1000)*(1/0.79941) | F97: =(([1]Consolidated!F97)*1000)*(1/0.79941) | G97: =(([1]Consolidated!G97)*1000)*(1/0.79941) | H97: =(([1]Consolidated!H97)*1000)*(1/0.79941) | I97: =(([1]Consolidated!I97)*1000)*(1/0.79941) | J97: =(([1]Consolidated!J97)*1000)*(1/0.79941) | L97: =(([1]Consolidated!L97)*1000)*(1/0.79941) | M97: =(([1]Consolidated!M97)*1000)*(1/0.79941) | N97: =(([1]Consolidated!N97)*1000)*(1/0.79941)
C98: Employee education | D98: =(([1]Consolidated!D98)*1000)*(1/0.79941) | E98: =(([1]Consolidated!E98)*1000)*(1/0.79941) | F98: =(([1]Consolidated!F98)*1000)*(1/0.79941) | G98: =(([1]Consolidated!G98)*1000)*(1/0.79941) | H98: =(([1]Consolidated!H98)*1000)*(1/0.79941) | I98: =(([1]Consolidated!I98)*1000)*(1/0.79941) | J98: =(([1]Consolidated!J98)*1000)*(1/0.79941) | L98: =(([1]Consolidated!L98)*1000)*(1/0.79941) | M98: =(([1]Consolidated!M98)*1000)*(1/0.79941) | N98: =(([1]Consolidated!N98)*1000)*(1/0.79941)
C99: Other staff expenses | D99: =(([1]Consolidated!D99)*1000)*(1/0.79941) | E99: =(([1]Consolidated!E99)*1000)*(1/0.79941) | F99: =(([1]Consolidated!F99)*1000)*(1/0.79941) | G99: =(([1]Consolidated!G99)*1000)*(1/0.79941) | H99: =(([1]Consolidated!H99)*1000)*(1/0.79941) | I99: =(([1]Consolidated!I99)*1000)*(1/0.79941) | J99: =(([1]Consolidated!J99)*1000)*(1/0.79941) | L99: =(([1]Consolidated!L99)*1000)*(1/0.79941) | M99: =(([1]Consolidated!M99)*1000)*(1/0.79941) | N99: =(([1]Consolidated!N99)*1000)*(1/0.79941)
C100: Staff expenses | D100: =(([1]Consolidated!D100)*1000)*(1/0.79941) | E100: =(([1]Consolidated!E100)*1000)*(1/0.79941) | F100: =(([1]Consolidated!F100)*1000)*(1/0.79941) | G100: =(([1]Consolidated!G100)*1000)*(1/0.79941) | H100: =(([1]Consolidated!H100)*1000)*(1/0.79941) | I100: =(([1]Consolidated!I100)*1000)*(1/0.79941) | J100: =(([1]Consolidated!J100)*1000)*(1/0.79941) | L100: =(([1]Consolidated!L100)*1000)*(1/0.79941) | M100: =(([1]Consolidated!M100)*1000)*(1/0.79941) | N100: =(([1]Consolidated!N100)*1000)*(1/0.79941)
C101: Hardware expenses | D101: =(([1]Consolidated!D101)*1000)*(1/0.79941) | E101: =(([1]Consolidated!E101)*1000)*(1/0.79941) | F101: =(([1]Consolidated!F101)*1000)*(1/0.79941) | G101: =(([1]Consolidated!G101)*1000)*(1/0.79941) | H101: =(([1]Consolidated!H101)*1000)*(1/0.79941) | I101: =(([1]Consolidated!I101)*1000)*(1/0.79941) | J101: =(([1]Consolidated!J101)*1000)*(1/0.79941) | L101: =(([1]Consolidated!L101)*1000)*(1/0.79941) | M101: =(([1]Consolidated!M101)*1000)*(1/0.79941) | N101: =(([1]Consolidated!N101)*1000)*(1/0.79941)
C102: Leasing/renting hardware | D102: =(([1]Consolidated!D102)*1000)*(1/0.79941) | E102: =(([1]Consolidated!E102)*1000)*(1/0.79941) | F102: =(([1]Consolidated!F102)*1000)*(1/0.79941) | G102: =(([1]Consolidated!G102)*1000)*(1/0.79941) | H102: =(([1]Consolidated!H102)*1000)*(1/0.79941) | I102: =(([1]Consolidated!I102)*1000)*(1/0.79941) | J102: =(([1]Consolidated!J102)*1000)*(1/0.79941) | L102: =(([1]Consolidated!L102)*1000)*(1/0.79941) | M102: =(([1]Consolidated!M102)*1000)*(1/0.79941) | N102: =(([1]Consolidated!N102)*1000)*(1/0.79941)
C103: Software expenses | D103: =(([1]Consolidated!D103)*1000)*(1/0.79941) | E103: =(([1]Consolidated!E103)*1000)*(1/0.79941) | F103: =(([1]Consolidated!F103)*1000)*(1/0.79941) | G103: =(([1]Consolidated!G103)*1000)*(1/0.79941) | H103: =(([1]Consolidated!H103)*1000)*(1/0.79941) | I103: =(([1]Consolidated!I103)*1000)*(1/0.79941) | J103: =(([1]Consolidated!J103)*1000)*(1/0.79941) | L103: =(([1]Consolidated!L103)*1000)*(1/0.79941) | M103: =(([1]Consolidated!M103)*1000)*(1/0.79941) | N103: =(([1]Consolidated!N103)*1000)*(1/0.79941)
C104: Leasing/renting/licenses sw | D104: =(([1]Consolidated!D104)*1000)*(1/0.79941) | E104: =(([1]Consolidated!E104)*1000)*(1/0.79941) | F104: =(([1]Consolidated!F104)*1000)*(1/0.79941) | G104: =(([1]Consolidated!G104)*1000)*(1/0.79941) | H104: =(([1]Consolidated!H104)*1000)*(1/0.79941) | I104: =(([1]Consolidated!I104)*1000)*(1/0.79941) | J104: =(([1]Consolidated!J104)*1000)*(1/0.79941) | L104: =(([1]Consolidated!L104)*1000)*(1/0.79941) | M104: =(([1]Consolidated!M104)*1000)*(1/0.79941) | N104: =(([1]Consolidated!N104)*1000)*(1/0.79941)
C105: Depreciation hardware | D105: =(([1]Consolidated!D105)*1000)*(1/0.79941) | E105: =(([1]Consolidated!E105)*1000)*(1/0.79941) | F105: =(([1]Consolidated!F105)*1000)*(1/0.79941) | G105: =(([1]Consolidated!G105)*1000)*(1/0.79941) | H105: =(([1]Consolidated!H105)*1000)*(1/0.79941) | I105: =(([1]Consolidated!I105)*1000)*(1/0.79941) | J105: =(([1]Consolidated!J105)*1000)*(1/0.79941) | L105: =(([1]Consolidated!L105)*1000)*(1/0.79941) | M105: =(([1]Consolidated!M105)*1000)*(1/0.79941) | N105: =(([1]Consolidated!N105)*1000)*(1/0.79941)
... C121: Operating expenses | D121: =(([1]Consolidated!D121)*1000)*(1/0.79941) | E121: =(([1]Consolidated!E121)*1000)*(1/0.79941) | F121: =(([1]Consolidated!F121)*1000)*(1/0.79941) | G121: =(([1]Consolidated!G121)*1000)*(1/0.79941) | H121: =(([1]Consolidated!H121)*1000)*(1/0.79941) | I121: =(([1]Consolidated!I121)*1000)*(1/0.79941) | J121: =(([1]Consolidated!J121)*1000)*(1/0.79941) | L121: =(([1]Consolidated!L121)*1000)*(1/0.79941) | M121: =(([1]Consolidated!M121)*1000)*(1/0.79941) | N121: =(([1]Consolidated!N121)*1000)*(1/0.79941)
D122: =0*(1/0.79941) | E122: =0*(1/0.79941) | F122: =0*(1/0.79941) | G122: =0*(1/0.79941) | H122: =0*(1/0.79941) | I122: =0*(1/0.79941) | J122: =0*(1/0.79941) | L122: =0*(1/0.79941) | M122: =0*(1/0.79941) | N122: =0*(1/0.79941)
C123: HR & Comms | D123: =(([1]Consolidated!D123)*1000)*(1/0.79941) | E123: =(([1]Consolidated!E123)*1000)*(1/0.79941) | F123: =(([1]Consolidated!F123)*1000)*(1/0.79941) | G123: =(([1]Consolidated!G123)*1000)*(1/0.79941) | H123: =(([1]Consolidated!H123)*1000)*(1/0.79941) | I123: =(([1]Consolidated!I123)*1000)*(1/0.79941) | J123: =(([1]Consolidated!J123)*1000)*(1/0.79941) | L123: =(([1]Consolidated!L123)*1000)*(1/0.79941) | M123: =(([1]Consolidated!M123)*1000)*(1/0.79941) | N123: =(([1]Consolidated!N123)*1000)*(1/0.79941)
C124: Finance & Business Support | D124: =(([1]Consolidated!D124)*1000)*(1/0.79941) | E124: =(([1]Consolidated!E124)*1000)*(1/0.79941) | F124: =(([1]Consolidated!F124)*1000)*(1/0.79941) | G124: =(([1]Consolidated!G124)*1000)*(1/0.79941) | H124: =(([1]Consolidated!H124)*1000)*(1/0.79941) | I124: =(([1]Consolidated!I124)*1000)*(1/0.79941) | J124: =(([1]Consolidated!J124)*1000)*(1/0.79941) | L124: =(([1]Consolidated!L124)*1000)*(1/0.79941) | M124: =(([1]Consolidated!M124)*1000)*(1/0.79941) | N124: =(([1]Consolidated!N124)*1000)*(1/0.79941)
C125: IT alloc | D125: =(([1]Consolidated!D125)*1000)*(1/0.79941) | E125: =(([1]Consolidated!E125)*1000)*(1/0.79941) | F125: =(([1]Consolidated!F125)*1000)*(1/0.79941) | G125: =(([1]Consolidated!G125)*1000)*(1/0.79941) | H125: =(([1]Consolidated!H125)*1000)*(1/0.79941) | I125: =(([1]Consolidated!I125)*1000)*(1/0.79941) | J125: =(([1]Consolidated!J125)*1000)*(1/0.79941) | L125: =(([1]Consolidated!L125)*1000)*(1/0.79941) | M125: =(([1]Consolidated!M125)*1000)*(1/0.79941) | N125: =(([1]Consolidated!N125)*1000)*(1/0.79941)
C126: Facilities Management | D126: =(([1]Consolidated!D126)*1000)*(1/0.79941) | E126: =(([1]Consolidated!E126)*1000)*(1/0.79941) | F126: =(([1]Consolidated!F126)*1000)*(1/0.79941) | G126: =(([1]Consolidated!G126)*1000)*(1/0.79941) | H126: =(([1]Consolidated!H126)*1000)*(1/0.79941) | I126: =(([1]Consolidated!I126)*1000)*(1/0.79941) | J126: =(([1]Consolidated!J126)*1000)*(1/0.79941) | L126: =(([1]Consolidated!L126)*1000)*(1/0.79941) | M126: =(([1]Consolidated!M126)*1000)*(1/0.79941) | N126: =(([1]Consolidated!N126)*1000)*(1/0.79941)
C127: Overheads | D127: =(([1]Consolidated!D127)*1000)*(1/0.79941) | E127: =(([1]Consolidated!E127)*1000)*(1/0.79941) | F127: =(([1]Consolidated!F127)*1000)*(1/0.79941) | G127: =(([1]Consolidated!G127)*1000)*(1/0.79941) | H127: =(([1]Consolidated!H127)*1000)*(1/0.79941) | I127: =(([1]Consolidated!I127)*1000)*(1/0.79941) | J127: =(([1]Consolidated!J127)*1000)*(1/0.79941) | L127: =(([1]Consolidated!L127)*1000)*(1/0.79941) | M127: =(([1]Consolidated!M127)*1000)*(1/0.79941) | N127: =(([1]Consolidated!N127)*1000)*(1/0.79941)
D128: =0*(1/0.79941) | E128: =0*(1/0.79941) | F128: =0*(1/0.79941) | G128: =0*(1/0.79941) | H128: =0*(1/0.79941) | I128: =0*(1/0.79941) | J128: =0*(1/0.79941) | L128: =0*(1/0.79941) | M128: =0*(1/0.79941) | N128: =0*(1/0.79941)
C129: Total Operating Costs (incl. O/H) | D129: =(([1]Consolidated!D129)*1000)*(1/0.79941) | E129: =(([1]Consolidated!E129)*1000)*(1/0.79941) | F129: =(([1]Consolidated!F129)*1000)*(1/0.79941) | G129: =(([1]Consolidated!G129)*1000)*(1/0.79941) | H129: =(([1]Consolidated!H129)*1000)*(1/0.79941) | I129: =(([1]Consolidated!I129)*1000)*(1/0.79941) | J129: =(([1]Consolidated!J129)*1000)*(1/0.79941) | L129: =(([1]Consolidated!L129)*1000)*(1/0.79941) | M129: =(([1]Consolidated!M129)*1000)*(1/0.79941) | N129: =(([1]Consolidated!N129)*1000)*(1/0.79941)
C132: RETAINED COSTS (US$ excl. VAT) | D132: =[1]Consolidated!D132 | E132: =[1]Consolidated!E132 | F132: =[1]Consolidated!F132 | G132: =[1]Consolidated!G132 | H132: =[1]Consolidated!H132 | I132: =[1]Consolidated!I132 | J132: =[1]Consolidated!J132 | L132: =[1]Consolidated!L132 | M132: =[1]Consolidated!M132 | N132: =[1]Consolidated!N132
C133: Internal FTE | D133: =[1]Consolidated!D133 | E133: =[1]Consolidated!E133 | F133: =[1]Consolidated!F133 | G133: =[1]Consolidated!G133 | H133: =[1]Consolidated!H133 | I133: =[1]Consolidated!I133 | L133: =[1]Consolidated!L133 | M133: =[1]Consolidated!M133 | N133: =[1]Consolidated!N133
C134: External FTE | D134: =[1]Consolidated!D134 | E134: =[1]Consolidated!E134 | F134: =[1]Consolidated!F134 | G134: =[1]Consolidated!G134 | H134: =[1]Consolidated!H134 | I134: =[1]Consolidated!I134 | L134: =[1]Consolidated!L134 | M134: =[1]Consolidated!M134 | N134: =[1]Consolidated!N134
C135: Total FTE | D135: =[1]Consolidated!D135 | E135: =[1]Consolidated!E135 | F135: =[1]Consolidated!F135 | G135: =[1]Consolidated!G135 | H135: =[1]Consolidated!H135 | I135: =[1]Consolidated!I135 | L135: =[1]Consolidated!L135 | M135: =[1]Consolidated!M135 | N135: =[1]Consolidated!N135
C137: Salaries | D137: =(([1]Consolidated!D137)*1000)*(1/0.79941) | E137: =(([1]Consolidated!E137)*1000)*(1/0.79941) | F137: =(([1]Consolidated!F137)*1000)*(1/0.79941) | G137: =(([1]Consolidated!G137)*1000)*(1/0.79941) | H137: =(([1]Consolidated!H137)*1000)*(1/0.79941) | I137: =(([1]Consolidated!I137)*1000)*(1/0.79941) | J137: =(([1]Consolidated!J137)*1000)*(1/0.79941) | L137: =(([1]Consolidated!L137)*1000)*(1/0.79941) | M137: =(([1]Consolidated!M137)*1000)*(1/0.79941) | N137: =(([1]Consolidated!N137)*1000)*(1/0.79941)
C138: Bonuses | D138: =(([1]Consolidated!D138)*1000)*(1/0.79941) | E138: =(([1]Consolidated!E138)*1000)*(1/0.79941) | F138: =(([1]Consolidated!F138)*1000)*(1/0.79941) | G138: =(([1]Consolidated!G138)*1000)*(1/0.79941) | H138: =(([1]Consolidated!H138)*1000)*(1/0.79941) | I138: =(([1]Consolidated!I138)*1000)*(1/0.79941) | J138: =(([1]Consolidated!J138)*1000)*(1/0.79941) | L138: =(([1]Consolidated!L138)*1000)*(1/0.79941) | M138: =(([1]Consolidated!M138)*1000)*(1/0.79941) | N138: =(([1]Consolidated!N138)*1000)*(1/0.79941)
C139: Third party staff, ex IT | D139: =(([1]Consolidated!D139)*1000)*(1/0.79941) | E139: =(([1]Consolidated!E139)*1000)*(1/0.79941) | F139: =(([1]Consolidated!F139)*1000)*(1/0.79941) | G139: =(([1]Consolidated!G139)*1000)*(1/0.79941) | H139: =(([1]Consolidated!H139)*1000)*(1/0.79941) | I139: =(([1]Consolidated!I139)*1000)*(1/0.79941) | J139: =(([1]Consolidated!J139)*1000)*(1/0.79941) | L139: =(([1]Consolidated!L139)*1000)*(1/0.79941) | M139: =(([1]Consolidated!M139)*1000)*(1/0.79941) | N139: =(([1]Consolidated!N139)*1000)*(1/0.79941)
C140: Third party IT staff | D140: =(([1]Consolidated!D140)*1000)*(1/0.79941) | E140: =(([1]Consolidated!E140)*1000)*(1/0.79941) | F140: =(([1]Consolidated!F140)*1000)*(1/0.79941) | G140: =(([1]Consolidated!G140)*1000)*(1/0.79941) | H140: =(([1]Consolidated!H140)*1000)*(1/0.79941) | I140: =(([1]Consolidated!I140)*1000)*(1/0.79941) | J140: =(([1]Consolidated!J140)*1000)*(1/0.79941) | L140: =(([1]Consolidated!L140)*1000)*(1/0.79941) | M140: =(([1]Consolidated!M140)*1000)*(1/0.79941) | N140: =(([1]Consolidated!N140)*1000)*(1/0.79941)
C141: Employee education | D141: =(([1]Consolidated!D141)*1000)*(1/0.79941) | E141: =(([1]Consolidated!E141)*1000)*(1/0.79941) | F141: =(([1]Consolidated!F141)*1000)*(1/0.79941) | G141: =(([1]Consolidated!G141)*1000)*(1/0.79941) | H141: =(([1]Consolidated!H141)*1000)*(1/0.79941) | I141: =(([1]Consolidated!I141)*1000)*(1/0.79941) | J141: =(([1]Consolidated!J141)*1000)*(1/0.79941) | L141: =(([1]Consolidated!L141)*1000)*(1/0.79941) | M141: =(([1]Consolidated!M141)*1000)*(1/0.79941) | N141: =(([1]Consolidated!N141)*1000)*(1/0.79941)
C142: Other staff expenses | D142: =(([1]Consolidated!D142)*1000)*(1/0.79941) | E142: =(([1]Consolidated!E142)*1000)*(1/0.79941) | F142: =(([1]Consolidated!F142)*1000)*(1/0.79941) | G142: =(([1]Consolidated!G142)*1000)*(1/0.79941) | H142: =(([1]Consolidated!H142)*1000)*(1/0.79941) | I142: =(([1]Consolidated!I142)*1000)*(1/0.79941) | J142: =(([1]Consolidated!J142)*1000)*(1/0.79941) | L142: =(([1]Consolidated!L142)*1000)*(1/0.79941) | M142: =(([1]Consolidated!M142)*1000)*(1/0.79941) | N142: =(([1]Consolidated!N142)*1000)*(1/0.79941)
C143: Staff expenses | D143: =(([1]Consolidated!D143)*1000)*(1/0.79941) | E143: =(([1]Consolidated!E143)*1000)*(1/0.79941) | F143: =(([1]Consolidated!F143)*1000)*(1/0.79941) | G143: =(([1]Consolidated!G143)*1000)*(1/0.79941) | H143: =(([1]Consolidated!H143)*1000)*(1/0.79941) | I143: =(([1]Consolidated!I143)*1000)*(1/0.79941) | J143: =(([1]Consolidated!J143)*1000)*(1/0.79941) | L143: =(([1]Consolidated!L143)*1000)*(1/0.79941) | M143: =(([1]Consolidated!M143)*1000)*(1/0.79941) | N143: =(([1]Consolidated!N143)*1000)*(1/0.79941)
C144: Hardware expenses | D144: =(([1]Consolidated!D144)*1000)*(1/0.79941) | E144: =(([1]Consolidated!E144)*1000)*(1/0.79941) | F144: =(([1]Consolidated!F144)*1000)*(1/0.79941) | G144: =(([1]Consolidated!G144)*1000)*(1/0.79941) | H144: =(([1]Consolidated!H144)*1000)*(1/0.79941) | I144: =(([1]Consolidated!I144)*1000)*(1/0.79941) | J144: =(([1]Consolidated!J144)*1000)*(1/0.79941) | L144: =(([1]Consolidated!L144)*1000)*(1/0.79941) | M144: =(([1]Consolidated!M144)*1000)*(1/0.79941) | N144: =(([1]Consolidated!N144)*1000)*(1/0.79941)
C145: Leasing/renting hardware | D145: =(([1]Consolidated!D145)*1000)*(1/0.79941) | E145: =(([1]Consolidated!E145)*1000)*(1/0.79941) | F145: =(([1]Consolidated!F145)*1000)*(1/0.79941) | G145: =(([1]Consolidated!G145)*1000)*(1/0.79941) | H145: =(([1]Consolidated!H145)*1000)*(1/0.79941) | I145: =(([1]Consolidated!I145)*1000)*(1/0.79941) | J145: =(([1]Consolidated!J145)*1000)*(1/0.79941) | L145: =(([1]Consolidated!L145)*1000)*(1/0.79941) | M145: =(([1]Consolidated!M145)*1000)*(1/0.79941) | N145: =(([1]Consolidated!N145)*1000)*(1/0.79941)
C146: Software expenses | D146: =(([1]Consolidated!D146)*1000)*(1/0.79941) | E146: =(([1]Consolidated!E146)*1000)*(1/0.79941) | F146: =(([1]Consolidated!F146)*1000)*(1/0.79941) | G146: =(([1]Consolidated!G146)*1000)*(1/0.79941) | H146: =(([1]Consolidated!H146)*1000)*(1/0.79941) | I146: =(([1]Consolidated!I146)*1000)*(1/0.79941) | J146: =(([1]Consolidated!J146)*1000)*(1/0.79941) | L146: =(([1]Consolidated!L146)*1000)*(1/0.79941) | M146: =(([1]Consolidated!M146)*1000)*(1/0.79941) | N146: =(([1]Consolidated!N146)*1000)*(1/0.79941)
C147: Leasing/renting/licenses sw | D147: =(([1]Consolidated!D147)*1000)*(1/0.79941) | E147: =(([1]Consolidated!E147)*1000)*(1/0.79941) | F147: =(([1]Consolidated!F147)*1000)*(1/0.79941) | G147: =(([1]Consolidated!G147)*1000)*(1/0.79941) | H147: =(([1]Consolidated!H147)*1000)*(1/0.79941) | I147: =(([1]Consolidated!I147)*1000)*(1/0.79941) | J147: =(([1]Consolidated!J147)*1000)*(1/0.79941) | L147: =(([1]Consolidated!L147)*1000)*(1/0.79941) | M147: =(([1]Consolidated!M147)*1000)*(1/0.79941) | N147: =(([1]Consolidated!N147)*1000)*(1/0.79941)
C148: Depreciation hardware | D148: =(([1]Consolidated!D148)*1000)*(1/0.79941) | E148: =(([1]Consolidated!E148)*1000)*(1/0.79941) | F148: =(([1]Consolidated!F148)*1000)*(1/0.79941) | G148: =(([1]Consolidated!G148)*1000)*(1/0.79941) | H148: =(([1]Consolidated!H148)*1000)*(1/0.79941) | I148: =(([1]Consolidated!I148)*1000)*(1/0.79941) | J148: =(([1]Consolidated!J148)*1000)*(1/0.79941) | L148: =(([1]Consolidated!L148)*1000)*(1/0.79941) | M148: =(([1]Consolidated!M148)*1000)*(1/0.79941) | N148: =(([1]Consolidated!N148)*1000)*(1/0.79941)
... C164: Operating expenses | D164: =(([1]Consolidated!D164)*1000)*(1/0.79941) | E164: =(([1]Consolidated!E164)*1000)*(1/0.79941) | F164: =(([1]Consolidated!F164)*1000)*(1/0.79941) | G164: =(([1]Consolidated!G164)*1000)*(1/0.79941) | H164: =(([1]Consolidated!H164)*1000)*(1/0.79941) | I164: =(([1]Consolidated!I164)*1000)*(1/0.79941) | J164: =(([1]Consolidated!J164)*1000)*(1/0.79941) | L164: =(([1]Consolidated!L164)*1000)*(1/0.79941) | M164: =(([1]Consolidated!M164)*1000)*(1/0.79941) | N164: =(([1]Consolidated!N164)*1000)*(1/0.79941)
D165: =0*(1/0.79941) | E165: =0*(1/0.79941) | F165: =0*(1/0.79941) | G165: =0*(1/0.79941) | H165: =0*(1/0.79941) | I165: =0*(1/0.79941) | J165: =0*(1/0.79941) | L165: =0*(1/0.79941) | M165: =0*(1/0.79941) | N165: =0*(1/0.79941)
C166: HR & Comms | D166: =(([1]Consolidated!D166)*1000)*(1/0.79941) | E166: =(([1]Consolidated!E166)*1000)*(1/0.79941) | F166: =(([1]Consolidated!F166)*1000)*(1/0.79941) | G166: =(([1]Consolidated!G166)*1000)*(1/0.79941) | H166: =(([1]Consolidated!H166)*1000)*(1/0.79941) | I166: =(([1]Consolidated!I166)*1000)*(1/0.79941) | J166: =(([1]Consolidated!J166)*1000)*(1/0.79941) | L166: =(([1]Consolidated!L166)*1000)*(1/0.79941) | M166: =(([1]Consolidated!M166)*1000)*(1/0.79941) | N166: =(([1]Consolidated!N166)*1000)*(1/0.79941)
C167: Finance & Business Support | D167: =(([1]Consolidated!D167)*1000)*(1/0.79941) | E167: =(([1]Consolidated!E167)*1000)*(1/0.79941) | F167: =(([1]Consolidated!F167)*1000)*(1/0.79941) | G167: =(([1]Consolidated!G167)*1000)*(1/0.79941) | H167: =(([1]Consolidated!H167)*1000)*(1/0.79941) | I167: =(([1]Consolidated!I167)*1000)*(1/0.79941) | J167: =(([1]Consolidated!J167)*1000)*(1/0.79941) | L167: =(([1]Consolidated!L167)*1000)*(1/0.79941) | M167: =(([1]Consolidated!M167)*1000)*(1/0.79941) | N167: =(([1]Consolidated!N167)*1000)*(1/0.79941)
C168: IT alloc | D168: =(([1]Consolidated!D168)*1000)*(1/0.79941) | E168: =(([1]Consolidated!E168)*1000)*(1/0.79941) | F168: =(([1]Consolidated!F168)*1000)*(1/0.79941) | G168: =(([1]Consolidated!G168)*1000)*(1/0.79941) | H168: =(([1]Consolidated!H168)*1000)*(1/0.79941) | I168: =(([1]Consolidated!I168)*1000)*(1/0.79941) | J168: =(([1]Consolidated!J168)*1000)*(1/0.79941) | L168: =(([1]Consolidated!L168)*1000)*(1/0.79941) | M168: =(([1]Consolidated!M168)*1000)*(1/0.79941) | N168: =(([1]Consolidated!N168)*1000)*(1/0.79941)
...

Sheet US
C1: United States
C2: TOTAL COSTS (US$ excl. VAT) | D2: =[2]Consolidated!D2 | E2: =[2]Consolidated!E2 | F2: =[2]Consolidated!F2 | G2: =[2]Consolidated!G2 | H2: =[2]Consolidated!H2 | I2: =[2]Consolidated!I2 | J2: =[2]Consolidated!J2 | L2: =[2]Consolidated!L2 | M2: =[2]Consolidated!M2 | N2: =[2]Consolidated!N2
C3: Internal FTE | D3: =[2]Consolidated!D3 | E3: =[2]Consolidated!E3 | F3: =[2]Consolidated!F3 | G3: =[2]Consolidated!G3 | H3: =[2]Consolidated!H3 | I3: =[2]Consolidated!I3 | L3: =[2]Consolidated!L3 | M3: =[2]Consolidated!M3 | N3: =[2]Consolidated!N3
C4: External FTE | D4: =[2]Consolidated!D4 | E4: =[2]Consolidated!E4 | F4: =[2]Consolidated!F4 | G4: =[2]Consolidated!G4 | H4: =[2]Consolidated!H4 | I4: =[2]Consolidated!I4 | L4: =[2]Consolidated!L4 | M4: =[2]Consolidated!M4 | N4: =[2]Consolidated!N4
C5: Total FTE | D5: =[2]Consolidated!D5 | E5: =[2]Consolidated!E5 | F5: =[2]Consolidated!F5 | G5: =[2]Consolidated!G5 | H5: =[2]Consolidated!H5 | I5: =[2]Consolidated!I5 | L5: =[2]Consolidated!L5 | M5: =[2]Consolidated!M5 | N5: =[2]Consolidated!N5
C7: Salaries | D7: =[2]Consolidated!D7 | E7: =[2]Consolidated!E7 | F7: =[2]Consolidated!F7 | G7: =[2]Consolidated!G7 | H7: =[2]Consolidated!H7 | I7: =[2]Consolidated!I7 | J7: =[2]Consolidated!J7 | L7: =[2]Consolidated!L7 | M7: =[2]Consolidated!M7 | N7: =[2]Consolidated!N7
C8: Bonuses | D8: =[2]Consolidated!D8 | E8: =[2]Consolidated!E8 | F8: =[2]Consolidated!F8 | G8: =[2]Consolidated!G8 | H8: =[2]Consolidated!H8 | I8: =[2]Consolidated!I8 | J8: =[2]Consolidated!J8 | L8: =[2]Consolidated!L8 | M8: =[2]Consolidated!M8 | N8: =[2]Consolidated!N8
C9: Third party staff, ex IT | D9: =[2]Consolidated!D9 | E9: =[2]Consolidated!E9 | F9: =[2]Consolidated!F9 | G9: =[2]Consolidated!G9 | H9: =[2]Consolidated!H9 | I9: =[2]Consolidated!I9 | J9: =[2]Consolidated!J9 | L9: =[2]Consolidated!L9 | M9: =[2]Consolidated!M9 | N9: =[2]Consolidated!N9
C10: Third party IT staff | D10: =[2]Consolidated!D10 | E10: =[2]Consolidated!E10 | F10: =[2]Consolidated!F10 | G10: =[2]Consolidated!G10 | H10: =[2]Consolidated!H10 | I10: =[2]Consolidated!I10 | J10: =[2]Consolidated!J10 | L10: =[2]Consolidated!L10 | M10: =[2]Consolidated!M10 | N10: =[2]Consolidated!N10
C11: Employee education | D11: =[2]Consolidated!D11 | E11: =[2]Consolidated!E11 | F11: =[2]Consolidated!F11 | G11: =[2]Consolidated!G11 | H11: =[2]Consolidated!H11 | I11: =[2]Consolidated!I11 | J11: =[2]Consolidated!J11 | L11: =[2]Consolidated!L11 | M11: =[2]Consolidated!M11 | N11: =[2]Consolidated!N11
C12: Other staff expenses | D12: =[2]Consolidated!D12 | E12: =[2]Consolidated!E12 | F12: =[2]Consolidated!F12 | G12: =[2]Consolidated!G12 | H12: =[2]Consolidated!H12 | I12: =[2]Consolidated!I12 | J12: =[2]Consolidated!J12 | L12: =[2]Consolidated!L12 | M12: =[2]Consolidated!M12 | N12: =[2]Consolidated!N12
C13: Staff expenses | D13: =[2]Consolidated!D13 | E13: =[2]Consolidated!E13 | F13: =[2]Consolidated!F13 | G13: =[2]Consolidated!G13 | H13: =[2]Consolidated!H13 | I13: =[2]Consolidated!I13 | J13: =[2]Consolidated!J13 | L13: =[2]Consolidated!L13 | M13: =[2]Consolidated!M13 | N13: =[2]Consolidated!N13
C14: Hardware expenses | D14: =[2]Consolidated!D14 | E14: =[2]Consolidated!E14 | F14: =[2]Consolidated!F14 | G14: =[2]Consolidated!G14 | H14: =[2]Consolidated!H14 | I14: =[2]Consolidated!I14 | J14: =[2]Consolidated!J14 | L14: =[2]Consolidated!L14 | M14: =[2]Consolidated!M14 | N14: =[2]Consolidated!N14
C15: Leasing/renting hardware | D15: =[2]Consolidated!D15 | E15: =[2]Consolidated!E15 | F15: =[2]Consolidated!F15 | G15: =[2]Consolidated!G15 | H15: =[2]Consolidated!H15 | I15: =[2]Consolidated!I15 | J15: =[2]Consolidated!J15 | L15: =[2]Consolidated!L15 | M15: =[2]Consolidated!M15 | N15: =[2]Consolidated!N15
C16: Software expenses | D16: =[2]Consolidated!D16 | E16: =[2]Consolidated!E16 | F16: =[2]Consolidated!F16 | G16: =[2]Consolidated!G16 | H16: =[2]Consolidated!H16 | I16: =[2]Consolidated!I16 | J16: =[2]Consolidated!J16 | L16: =[2]Consolidated!L16 | M16: =[2]Consolidated!M16 | N16: =[2]Consolidated!N16
C17: Leasing/renting/licenses sw | D17: =[2]Consolidated!D17 | E17: =[2]Consolidated!E17 | F17: =[2]Consolidated!F17 | G17: =[2]Consolidated!G17 | H17: =[2]Consolidated!H17 | I17: =[2]Consolidated!I17 | J17: =[2]Consolidated!J17 | L17: =[2]Consolidated!L17 | M17: =[2]Consolidated!M17 | N17: =[2]Consolidated!N17
C18: Depreciation hardware | D18: =[2]Consolidated!D18 | E18: =[2]Consolidated!E18 | F18: =[2]Consolidated!F18 | G18: =[2]Consolidated!G18 | H18: =[2]Consolidated!H18 | I18: =[2]Consolidated!I18 | J18: =[2]Consolidated!J18 | L18: =[2]Consolidated!L18 | M18: =[2]Consolidated!M18 | N18: =[2]Consolidated!N18
... C40: Overheads | D40: =[2]Consolidated!D40 | E40: =[2]Consolidated!E40 | F40: =[2]Consolidated!F40 | G40: =[2]Consolidated!G40 | H40: =[2]Consolidated!H40 | I40: =[2]Consolidated!I40 | J40: =[2]Consolidated!J40 | L40: =[2]Consolidated!L40 | M40: =[2]Consolidated!M40 | N40: =[2]Consolidated!N40
C41: 0
C42: Total Operating Costs (incl. O/H) | D42: =[2]Consolidated!D42 | E42: =[2]Consolidated!E42 | F42: =[2]Consolidated!F42 | G42: =[2]Consolidated!G42 | H42: =[2]Consolidated!H42 | I42: =[2]Consolidated!I42 | J42: =[2]Consolidated!J42 | L42: =[2]Consolidated!L42 | M42: =[2]Consolidated!M42 | N42: =[2]Consolidated!N42
C45: SUPPLIER ASSUMED COSTS (US$ excl. VAT) | D45: =[2]Consolidated!D45 | E45: =[2]Consolidated!E45 | F45: =[2]Consolidated!F45 | G45: =[2]Consolidated!G45 | H45: =[2]Consolidated!H45 | I45: =[2]Consolidated!I45 | J45: =[2]Consolidated!J45 | L45: =[2]Consolidated!L45 | M45: =[2]Consolidated!M45 | N45: =[2]Consolidated!N45
C46: Internal FTE | D46: =[2]Consolidated!D46 | E46: =[2]Consolidated!E46 | F46: =[2]Consolidated!F46 | G46: =[2]Consolidated!G46 | H46: =[2]Consolidated!H46 | I46: =[2]Consolidated!I46 | L46: =[2]Consolidated!L46 | M46: =[2]Consolidated!M46 | N46: =[2]Consolidated!N46
C47: External FTE | D47: =[2]Consolidated!D47 | E47: =[2]Consolidated!E47 | F47: =[2]Consolidated!F47 | G47: =[2]Consolidated!G47 | H47: =[2]Consolidated!H47 | I47: =[2]Consolidated!I47 | L47: =[2]Consolidated!L47 | M47: =[2]Consolidated!M47 | N47: =[2]Consolidated!N47
C48: Total FTE | D48: =[2]Consolidated!D48 | E48: =[2]Consolidated!E48 | F48: =[2]Consolidated!F48 | G48: =[2]Consolidated!G48 | H48: =[2]Consolidated!H48 | I48: =[2]Consolidated!I48 | L48: =[2]Consolidated!L48 | M48: =[2]Consolidated!M48 | N48: =[2]Consolidated!N48
C50: Salaries | D50: =[2]Consolidated!D50 | E50: =[2]Consolidated!E50 | F50: =[2]Consolidated!F50 | G50: =[2]Consolidated!G50 | H50: =[2]Consolidated!H50 | I50: =[2]Consolidated!I50 | J50: =[2]Consolidated!J50 | L50: =[2]Consolidated!L50 | M50: =[2]Consolidated!M50 | N50: =[2]Consolidated!N50
C51: Bonuses | D51: =[2]Consolidated!D51 | E51: =[2]Consolidated!E51 | F51: =[2]Consolidated!F51 | G51: =[2]Consolidated!G51 | H51: =[2]Consolidated!H51 | I51: =[2]Consolidated!I51 | J51: =[2]Consolidated!J51 | L51: =[2]Consolidated!L51 | M51: =[2]Consolidated!M51 | N51: =[2]Consolidated!N51
C52: Third party staff, ex IT | D52: =[2]Consolidated!D52 | E52: =[2]Consolidated!E52 | F52: =[2]Consolidated!F52 | G52: =[2]Consolidated!G52 | H52: =[2]Consolidated!H52 | I52: =[2]Consolidated!I52 | J52: =[2]Consolidated!J52 | L52: =[2]Consolidated!L52 | M52: =[2]Consolidated!M52 | N52: =[2]Consolidated!N52
C53: Third party IT staff | D53: =[2]Consolidated!D53 | E53: =[2]Consolidated!E53 | F53: =[2]Consolidated!F53 | G53: =[2]Consolidated!G53 | H53: =[2]Consolidated!H53 | I53: =[2]Consolidated!I53 | J53: =[2]Consolidated!J53 | L53: =[2]Consolidated!L53 | M53: =[2]Consolidated!M53 | N53: =[2]Consolidated!N53
C54: Employee education | D54: =[2]Consolidated!D54 | E54: =[2]Consolidated!E54 | F54: =[2]Consolidated!F54 | G54: =[2]Consolidated!G54 | H54: =[2]Consolidated!H54 | I54: =[2]Consolidated!I54 | J54: =[2]Consolidated!J54 | L54: =[2]Consolidated!L54 | M54: =[2]Consolidated!M54 | N54: =[2]Consolidated!N54
C55: Other staff expenses | D55: =[2]Consolidated!D55 | E55: =[2]Consolidated!E55 | F55: =[2]Consolidated!F55 | G55: =[2]Consolidated!G55 | H55: =[2]Consolidated!H55 | I55: =[2]Consolidated!I55 | J55: =[2]Consolidated!J55 | L55: =[2]Consolidated!L55 | M55: =[2]Consolidated!M55 | N55: =[2]Consolidated!N55
C56: Staff expenses | D56: =[2]Consolidated!D56 | E56: =[2]Consolidated!E56 | F56: =[2]Consolidated!F56 | G56: =[2]Consolidated!G56 | H56: =[2]Consolidated!H56 | I56: =[2]Consolidated!I56 | J56: =[2]Consolidated!J56 | L56: =[2]Consolidated!L56 | M56: =[2]Consolidated!M56 | N56: =[2]Consolidated!N56
C57: Hardware expenses | D57: =[2]Consolidated!D57 | E57: =[2]Consolidated!E57 | F57: =[2]Consolidated!F57 | G57: =[2]Consolidated!G57 | H57: =[2]Consolidated!H57 | I57: =[2]Consolidated!I57 | J57: =[2]Consolidated!J57 | L57: =[2]Consolidated!L57 | M57: =[2]Consolidated!M57 | N57: =[2]Consolidated!N57
C58: Leasing/renting hardware | D58: =[2]Consolidated!D58 | E58: =[2]Consolidated!E58 | F58: =[2]Consolidated!F58 | G58: =[2]Consolidated!G58 | H58: =[2]Consolidated!H58 | I58: =[2]Consolidated!I58 | J58: =[2]Consolidated!J58 | L58: =[2]Consolidated!L58 | M58: =[2]Consolidated!M58 | N58: =[2]Consolidated!N58
C59: Software expenses | D59: =[2]Consolidated!D59 | E59: =[2]Consolidated!E59 | F59: =[2]Consolidated!F59 | G59: =[2]Consolidated!G59 | H59: =[2]Consolidated!H59 | I59: =[2]Consolidated!I59 | J59: =[2]Consolidated!J59 | L59: =[2]Consolidated!L59 | M59: =[2]Consolidated!M59 | N59: =[2]Consolidated!N59
C60: Leasing/renting/licenses sw | D60: =[2]Consolidated!D60 | E60: =[2]Consolidated!E60 | F60: =[2]Consolidated!F60 | G60: =[2]Consolidated!G60 | H60: =[2]Consolidated!H60 | I60: =[2]Consolidated!I60 | J60: =[2]Consolidated!J60 | L60: =[2]Consolidated!L60 | M60: =[2]Consolidated!M60 | N60: =[2]Consolidated!N60
C61: Depreciation hardware | D61: =[2]Consolidated!D61 | E61: =[2]Consolidated!E61 | F61: =[2]Consolidated!F61 | G61: =[2]Consolidated!G61 | H61: =[2]Consolidated!H61 | I61: =[2]Consolidated!I61 | J61: =[2]Consolidated!J61 | L61: =[2]Consolidated!L61 | M61: =[2]Consolidated!M61 | N61: =[2]Consolidated!N61
... C63: Outsourcing IT activities | D63: =[2]Consolidated!D63 | E63: =[2]Consolidated!E63 | F63: =[2]Consolidated!F63 | G63: =[2]Consolidated!G63 | H63: =[2]Consolidated!H63 | I63: =[2]Consolidated!I63 | J63: =[2]Consolidated!J63 | L63: =[2]Consolidated!L63 | M63: =[2]Consolidated!M63 | N63: =[2]Consolidated!N63
C64: Other IT expenses | D64: =D65 | E64: =E65 | F64: =F65 | G64: =G65 | H64: =H65 | I64: =I65 | J64: =J65 | L64: =L65 | M64: =M65 | N64: =N65 | P64: Adjusted
C65: EDP expenses | D65: =[2]Consolidated!D65 | E65: =[2]Consolidated!E65 | F65: =[2]Consolidated!F65 | G65: =[2]Consolidated!G65 | H65: =[2]Consolidated!H65 | I65: =[2]Consolidated!I65 | J65: =[2]Consolidated!J65 | L65: =[2]Consolidated!L65 | M65: =[2]Consolidated!M65 | N65: =[2]Consolidated!N65
C66: Telecom expenses | D66: =[2]Consolidated!D66 | E66: =[2]Consolidated!E66 | F66: =[2]Consolidated!F66 | G66: =[2]Consolidated!G66 | H66: =[2]Consolidated!H66 | I66: =[2]Consolidated!I66 | J66: =[2]Consolidated!J66 | L66: =[2]Consolidated!L66 | M66: =[2]Consolidated!M66 | N66: =[2]Consolidated!N66
C67: Office equipment and supplies | D67: =[2]Consolidated!D67 | E67: =[2]Consolidated!E67 | F67: =[2]Consolidated!F67 | G67: =[2]Consolidated!G67 | H67: =[2]Consolidated!H67 | I67: =[2]Consolidated!I67 | J67: =[2]Consolidated!J67 | L67: =[2]Consolidated!L67 | M67: =[2]Consolidated!M67 | N67: =[2]Consolidated!N67
C68: Accomodation expenses | D68: =[2]Consolidated!D68 | E68: =[2]Consolidated!E68 | F68: =[2]Consolidated!F68 | G68: =[2]Consolidated!G68 | H68: =[2]Consolidated!H68 | I68: =[2]Consolidated!I68 | J68: =[2]Consolidated!J68 | L68: =[2]Consolidated!L68 | M68: =[2]Consolidated!M68 | N68: =[2]Consolidated!N68
C69: Travel costs | D69: =[2]Consolidated!D69 | E69: =[2]Consolidated!E69 | F69: =[2]Consolidated!F69 | G69: =[2]Consolidated!G69 | H69: =[2]Consolidated!H69 | I69: =[2]Consolidated!I69 | J69: =[2]Consolidated!J69 | L69: =[2]Consolidated!L69 | M69: =[2]Consolidated!M69 | N69: =[2]Consolidated!N69
C70: Postal and freight charges | D70: =[2]Consolidated!D70 | E70: =[2]Consolidated!E70 | F70: =[2]Consolidated!F70 | G70: =[2]Consolidated!G70 | H70: =[2]Consolidated!H70 | I70: =[2]Consolidated!I70 | J70: =[2]Consolidated!J70 | L70: =[2]Consolidated!L70 | M70: =[2]Consolidated!M70 | N70: =[2]Consolidated!N70
C71: Prof serv and ext advisory fee | D71: =[2]Consolidated!D71 | E71: =[2]Consolidated!E71 | F71: =[2]Consolidated!F71 | G71: =[2]Consolidated!G71 | H71: =[2]Consolidated!H71 | I71: =[2]Consolidated!I71 | J71: =[2]Consolidated!J71 | L71: =[2]Consolidated!L71 | M71: =[2]Consolidated!M71 | N71: =[2]Consolidated!N71
C72: Payment transfer expenses | D72: =[2]Consolidated!D72 | E72: =[2]Consolidated!E72 | F72: =[2]Consolidated!F72 | G72: =[2]Consolidated!G72 | H72: =[2]Consolidated!H72 | I72: =[2]Consolidated!I72 | J72: =[2]Consolidated!J72 | L72: =[2]Consolidated!L72 | M72: =[2]Consolidated!M72 | N72: =[2]Consolidated!N72
C73: Other costs | D73: =D74 | E73: =E74 | F73: =F74 | G73: =G74 | H73: =H74 | I73: =I74 | J73: =J74 | L73: =L74 | M73: =M74 | N73: =N74
C74: General expenses | D74: =[2]Consolidated!D74 | E74: =[2]Consolidated!E74 | F74: =[2]Consolidated!F74 | G74: =[2]Consolidated!G74 | H74: =[2]Consolidated!H74 | I74: =[2]Consolidated!I74 | J74: =[2]Consolidated!J74 | L74: =[2]Consolidated!L74 | M74: =[2]Consolidated!M74 | N74: =[2]Consolidated!N74 | P74: Adjusted
C75: Own expenses | D75: =[2]Consolidated!D75 | E75: =[2]Consolidated!E75 | F75: =[2]Consolidated!F75 | G75: =[2]Consolidated!G75 | H75: =[2]Consolidated!H75 | I75: =[2]Consolidated!I75 | J75: =[2]Consolidated!J75 | L75: =[2]Consolidated!L75 | M75: =[2]Consolidated!M75 | N75: =[2]Consolidated!N75
C76: Other expenses | D76: =[2]Consolidated!D76 | E76: =[2]Consolidated!E76 | F76: =[2]Consolidated!F76 | G76: =[2]Consolidated!G76 | H76: =[2]Consolidated!H76 | I76: =[2]Consolidated!I76 | J76: =[2]Consolidated!J76 | L76: =[2]Consolidated!L76 | M76: =[2]Consolidated!M76 | N76: =[2]Consolidated!N76
C77: Operating expenses | D77: =[2]Consolidated!D77 | E77: =[2]Consolidated!E77 | F77: =[2]Consolidated!F77 | G77: =[2]Consolidated!G77 | H77: =[2]Consolidated!H77 | I77: =[2]Consolidated!I77 | J77: =[2]Consolidated!J77 | L77: =[2]Consolidated!L77 | M77: =[2]Consolidated!M77 | N77: =[2]Consolidated!N77
C79: HR & Comms | D79: =[2]Consolidated!D79 | E79: =[2]Consolidated!E79 | F79: =[2]Consolidated!F79 | G79: =[2]Consolidated!G79 | H79: =[2]Consolidated!H79 | I79: =[2]Consolidated!I79 | J79: =[2]Consolidated!J79 | L79: =[2]Consolidated!L79 | M79: =[2]Consolidated!M79 | N79: =[2]Consolidated!N79
C80: Finance & Business Support | D80: =[2]Consolidated!D80 | E80: =[2]Consolidated!E80 | F80: =[2]Consolidated!F80 | G80: =[2]Consolidated!G80 | H80: =[2]Consolidated!H80 | I80: =[2]Consolidated!I80 | J80: =[2]Consolidated!J80 | L80: =[2]Consolidated!L80 | M80: =[2]Consolidated!M80 | N80: =[2]Consolidated!N80
C81: IT alloc | D81: =[2]Consolidated!D81 | E81: =[2]Consolidated!E81 | F81: =[2]Consolidated!F81 | G81: =[2]Consolidated!G81 | H81: =[2]Consolidated!H81 | I81: =[2]Consolidated!I81 | J81: =[2]Consolidated!J81 | L81: =[2]Consolidated!L81 | M81: =[2]Consolidated!M81 | N81: =[2]Consolidated!N81
C82: Facilities Management | D82: =[2]Consolidated!D82 | E82: =[2]Consolidated!E82 | F82: =[2]Consolidated!F82 | G82: =[2]Consolidated!G82 | H82: =[2]Consolidated!H82 | I82: =[2]Consolidated!I82 | J82: =[2]Consolidated!J82 | L82: =[2]Consolidated!L82 | M82: =[2]Consolidated!M82 | N82: =[2]Consolidated!N82
C83: Overheads | D83: =[2]Consolidated!D83 | E83: =[2]Consolidated!E83 | F83: =[2]Consolidated!F83 | G83: =[2]Consolidated!G83 | H83: =[2]Consolidated!H83 | I83: =[2]Consolidated!I83 | J83: =[2]Consolidated!J83 | L83: =[2]Consolidated!L83 | M83: =[2]Consolidated!M83 | N83: =[2]Consolidated!N83
C85: Total Operating Costs (incl. O/H) | D85: =[2]Consolidated!D85 | E85: =[2]Consolidated!E85 | F85: =[2]Consolidated!F85 | G85: =[2]Consolidated!G85 | H85: =[2]Consolidated!H85 | I85: =[2]Consolidated!I85 | J85: =[2]Consolidated!J85 | L85: =[2]Consolidated!L85 | M85: =[2]Consolidated!M85 | N85: =[2]Consolidated!N85
C89: PASS THROUGH COSTS (US$ excl. VAT) | D89: =[2]Consolidated!D89 | E89: =[2]Consolidated!E89 | F89: =[2]Consolidated!F89 | G89: =[2]Consolidated!G89 | H89: =[2]Consolidated!H89 | I89: =[2]Consolidated!I89 | J89: =[2]Consolidated!J89 | L89: =[2]Consolidated!L89 | M89: =[2]Consolidated!M89 | N89: =[2]Consolidated!N89
C90: Internal FTE | D90: =[2]Consolidated!D90 | E90: =[2]Consolidated!E90 | F90: =[2]Consolidated!F90 | G90: =[2]Consolidated!G90 | H90: =[2]Consolidated!H90 | I90: =[2]Consolidated!I90 | L90: =[2]Consolidated!L90 | M90: =[2]Consolidated!M90 | N90: =[2]Consolidated!N90
C91: External FTE | D91: =[2]Consolidated!D91 | E91: =[2]Consolidated!E91 | F91: =[2]Consolidated!F91 | G91: =[2]Consolidated!G91 | H91: =[2]Consolidated!H91 | I91: =[2]Consolidated!I91 | L91: =[2]Consolidated!L91 | M91: =[2]Consolidated!M91 | N91: =[2]Consolidated!N91
C92: Total FTE | D92: =[2]Consolidated!D92 | E92: =[2]Consolidated!E92 | F92: =[2]Consolidated!F92 | G92: =[2]Consolidated!G92 | H92: =[2]Consolidated!H92 | I92: =[2]Consolidated!I92 | L92: =[2]Consolidated!L92 | M92: =[2]Consolidated!M92 | N92: =[2]Consolidated!N92
C94: Salaries | D94: =[2]Consolidated!D94 | E94: =[2]Consolidated!E94 | F94: =[2]Consolidated!F94 | G94: =[2]Consolidated!G94 | H94: =[2]Consolidated!H94 | I94: =[2]Consolidated!I94 | J94: =[2]Consolidated!J94 | L94: =[2]Consolidated!L94 | M94: =[2]Consolidated!M94 | N94: =[2]Consolidated!N94
C95: Bonuses | D95: =[2]Consolidated!D95 | E95: =[2]Consolidated!E95 | F95: =[2]Consolidated!F95 | G95: =[2]Consolidated!G95 | H95: =[2]Consolidated!H95 | I95: =[2]Consolidated!I95 | J95: =[2]Consolidated!J95 | L95: =[2]Consolidated!L95 | M95: =[2]Consolidated!M95 | N95: =[2]Consolidated!N95
C96: Third party staff, ex IT | D96: =[2]Consolidated!D96 | E96: =[2]Consolidated!E96 | F96: =[2]Consolidated!F96 | G96: =[2]Consolidated!G96 | H96: =[2]Consolidated!H96 | I96: =[2]Consolidated!I96 | J96: =[2]Consolidated!J96 | L96: =[2]Consolidated!L96 | M96: =[2]Consolidated!M96 | N96: =[2]Consolidated!N96
C97: Third party IT staff | D97: =[2]Consolidated!D97 | E97: =[2]Consolidated!E97 | F97: =[2]Consolidated!F97 | G97: =[2]Consolidated!G97 | H97: =[2]Consolidated!H97 | I97: =[2]Consolidated!I97 | J97: =[2]Consolidated!J97 | L97: =[2]Consolidated!L97 | M97: =[2]Consolidated!M97 | N97: =[2]Consolidated!N97
C98: Employee education | D98: =[2]Consolidated!D98 | E98: =[2]Consolidated!E98 | F98: =[2]Consolidated!F98 | G98: =[2]Consolidated!G98 | H98: =[2]Consolidated!H98 | I98: =[2]Consolidated!I98 | J98: =[2]Consolidated!J98 | L98: =[2]Consolidated!L98 | M98: =[2]Consolidated!M98 | N98: =[2]Consolidated!N98
C99: Other staff expenses | D99: =[2]Consolidated!D99 | E99: =[2]Consolidated!E99 | F99: =[2]Consolidated!F99 | G99: =[2]Consolidated!G99 | H99: =[2]Consolidated!H99 | I99: =[2]Consolidated!I99 | J99: =[2]Consolidated!J99 | L99: =[2]Consolidated!L99 | M99: =[2]Consolidated!M99 | N99: =[2]Consolidated!N99
C100: Staff expenses | D100: =[2]Consolidated!D100 | E100: =[2]Consolidated!E100 | F100: =[2]Consolidated!F100 | G100: =[2]Consolidated!G100 | H100: =[2]Consolidated!H100 | I100: =[2]Consolidated!I100 | J100: =[2]Consolidated!J100 | L100: =[2]Consolidated!L100 | M100: =[2]Consolidated!M100 | N100: =[2]Consolidated!N100
C101: Hardware expenses | D101: =[2]Consolidated!D101 | E101: =[2]Consolidated!E101 | F101: =[2]Consolidated!F101 | G101: =[2]Consolidated!G101 | H101: =[2]Consolidated!H101 | I101: =[2]Consolidated!I101 | J101: =[2]Consolidated!J101 | L101: =[2]Consolidated!L101 | M101: =[2]Consolidated!M101 | N101: =[2]Consolidated!N101
C102: Leasing/renting hardware | D102: =[2]Consolidated!D102 | E102: =[2]Consolidated!E102 | F102: =[2]Consolidated!F102 | G102: =[2]Consolidated!G102 | H102: =[2]Consolidated!H102 | I102: =[2]Consolidated!I102 | J102: =[2]Consolidated!J102 | L102: =[2]Consolidated!L102 | M102: =[2]Consolidated!M102 | N102: =[2]Consolidated!N102
C103: Software expenses | D103: =[2]Consolidated!D103 | E103: =[2]Consolidated!E103 | F103: =[2]Consolidated!F103 | G103: =[2]Consolidated!G103 | H103: =[2]Consolidated!H103 | I103: =[2]Consolidated!I103 | J103: =[2]Consolidated!J103 | L103: =[2]Consolidated!L103 | M103: =[2]Consolidated!M103 | N103: =[2]Consolidated!N103
C104: Leasing/renting/licenses sw | D104: =[2]Consolidated!D104 | E104: =[2]Consolidated!E104 | F104: =[2]Consolidated!F104 | G104: =[2]Consolidated!G104 | H104: =[2]Consolidated!H104 | I104: =[2]Consolidated!I104 | J104: =[2]Consolidated!J104 | L104: =[2]Consolidated!L104 | M104: =[2]Consolidated!M104 | N104: =[2]Consolidated!N104
C105: Depreciation hardware | D105: =[2]Consolidated!D105 | E105: =[2]Consolidated!E105 | F105: =[2]Consolidated!F105 | G105: =[2]Consolidated!G105 | H105: =[2]Consolidated!H105 | I105: =[2]Consolidated!I105 | J105: =[2]Consolidated!J105 | L105: =[2]Consolidated!L105 | M105: =[2]Consolidated!M105 | N105: =[2]Consolidated!N105
... C121: Operating expenses | D121: =[2]Consolidated!D121 | E121: =[2]Consolidated!E121 | F121: =[2]Consolidated!F121 | G121: =[2]Consolidated!G121 | H121: =[2]Consolidated!H121 | I121: =[2]Consolidated!I121 | J121: =[2]Consolidated!J121 | L121: =[2]Consolidated!L121 | M121: =[2]Consolidated!M121 | N121: =[2]Consolidated!N121
D122: =[2]Consolidated!D122 | E122: =[2]Consolidated!E122 | F122: =[2]Consolidated!F122 | G122: =[2]Consolidated!G122 | H122: =[2]Consolidated!H122 | I122: =[2]Consolidated!I122 | J122: =[2]Consolidated!J122 | L122: =[2]Consolidated!L122 | M122: =[2]Consolidated!M122 | N122: =[2]Consolidated!N122
C123: HR & Comms | D123: =[2]Consolidated!D123 | E123: =[2]Consolidated!E123 | F123: =[2]Consolidated!F123 | G123: =[2]Consolidated!G123 | H123: =[2]Consolidated!H123 | I123: =[2]Consolidated!I123 | J123: =[2]Consolidated!J123 | L123: =[2]Consolidated!L123 | M123: =[2]Consolidated!M123 | N123: =[2]Consolidated!N123
C124: Finance & Business Support | D124: =[2]Consolidated!D124 | E124: =[2]Consolidated!E124 | F124: =[2]Consolidated!F124 | G124: =[2]Consolidated!G124 | H124: =[2]Consolidated!H124 | I124: =[2]Consolidated!I124 | J124: =[2]Consolidated!J124 | L124: =[2]Consolidated!L124 | M124: =[2]Consolidated!M124 | N124: =[2]Consolidated!N124
C125: IT alloc | D125: =[2]Consolidated!D125 | E125: =[2]Consolidated!E125 | F125: =[2]Consolidated!F125 | G125: =[2]Consolidated!G125 | H125: =[2]Consolidated!H125 | I125: =[2]Consolidated!I125 | J125: =[2]Consolidated!J125 | L125: =[2]Consolidated!L125 | M125: =[2]Consolidated!M125 | N125: =[2]Consolidated!N125
C126: Facilities Management | D126: =[2]Consolidated!D126 | E126: =[2]Consolidated!E126 | F126: =[2]Consolidated!F126 | G126: =[2]Consolidated!G126 | H126: =[2]Consolidated!H126 | I126: =[2]Consolidated!I126 | J126: =[2]Consolidated!J126 | L126: =[2]Consolidated!L126 | M126: =[2]Consolidated!M126 | N126: =[2]Consolidated!N126
C127: Overheads | D127: =[2]Consolidated!D127 | E127: =[2]Consolidated!E127 | F127: =[2]Consolidated!F127 | G127: =[2]Consolidated!G127 | H127: =[2]Consolidated!H127 | I127: =[2]Consolidated!I127 | J127: =[2]Consolidated!J127 | L127: =[2]Consolidated!L127 | M127: =[2]Consolidated!M127 | N127: =[2]Consolidated!N127
D128: =[2]Consolidated!D128 | E128: =[2]Consolidated!E128 | F128: =[2]Consolidated!F128 | G128: =[2]Consolidated!G128 | H128: =[2]Consolidated!H128 | I128: =[2]Consolidated!I128 | J128: =[2]Consolidated!J128 | L128: =[2]Consolidated!L128 | M128: =[2]Consolidated!M128 | N128: =[2]Consolidated!N128
C129: Total Operating Costs (incl. O/H) | D129: =[2]Consolidated!D129 | E129: =[2]Consolidated!E129 | F129: =[2]Consolidated!F129 | G129: =[2]Consolidated!G129 | H129: =[2]Consolidated!H129 | I129: =[2]Consolidated!I129 | J129: =[2]Consolidated!J129 | L129: =[2]Consolidated!L129 | M129: =[2]Consolidated!M129 | N129: =[2]Consolidated!N129
C132: RETAINED COSTS (US$ excl. VAT) | D132: =[2]Consolidated!D132 | E132: =[2]Consolidated!E132 | F132: =[2]Consolidated!F132 | G132: =[2]Consolidated!G132 | H132: =[2]Consolidated!H132 | I132: =[2]Consolidated!I132 | J132: =[2]Consolidated!J132 | L132: =[2]Consolidated!L132 | M132: =[2]Consolidated!M132 | N132: =[2]Consolidated!N132
C133: Internal FTE | D133: =[2]Consolidated!D133 | E133: =[2]Consolidated!E133 | F133: =[2]Consolidated!F133 | G133: =[2]Consolidated!G133 | H133: =[2]Consolidated!H133 | I133: =[2]Consolidated!I133 | J133: =[2]Consolidated!J133 | L133: =[2]Consolidated!L133 | M133: =[2]Consolidated!M133 | N133: =[2]Consolidated!N133
C134: External FTE | D134: =[2]Consolidated!D134 | E134: =[2]Consolidated!E134 | F134: =[2]Consolidated!F134 | G134: =[2]Consolidated!G134 | H134: =[2]Consolidated!H134 | I134: =[2]Consolidated!I134 | J134: =[2]Consolidated!J134 | L134: =[2]Consolidated!L134 | M134: =[2]Consolidated!M134 | N134: =[2]Consolidated!N134
C135: Total FTE | D135: =[2]Consolidated!D135 | E135: =[2]Consolidated!E135 | F135: =[2]Consolidated!F135 | G135: =[2]Consolidated!G135 | H135: =[2]Consolidated!H135 | I135: =[2]Consolidated!I135 | J135: =[2]Consolidated!J135 | L135: =[2]Consolidated!L135 | M135: =[2]Consolidated!M135 | N135: =[2]Consolidated!N135
D136: =[2]Consolidated!D136 | E136: =[2]Consolidated!E136 | F136: =[2]Consolidated!F136 | G136: =[2]Consolidated!G136 | H136: =[2]Consolidated!H136 | I136: =[2]Consolidated!I136 | J136: =[2]Consolidated!J136 | L136: =[2]Consolidated!L136 | M136: =[2]Consolidated!M136 | N136: =[2]Consolidated!N136
C137: Salaries | D137: =[2]Consolidated!D137 | E137: =[2]Consolidated!E137 | F137: =[2]Consolidated!F137 | G137: =[2]Consolidated!G137 | H137: =[2]Consolidated!H137 | I137: =[2]Consolidated!I137 | J137: =[2]Consolidated!J137 | L137: =[2]Consolidated!L137 | M137: =[2]Consolidated!M137 | N137: =[2]Consolidated!N137
C138: Bonuses | D138: =[2]Consolidated!D138 | E138: =[2]Consolidated!E138 | F138: =[2]Consolidated!F138 | G138: =[2]Consolidated!G138 | H138: =[2]Consolidated!H138 | I138: =[2]Consolidated!I138 | J138: =[2]Consolidated!J138 | L138: =[2]Consolidated!L138 | M138: =[2]Consolidated!M138 | N138: =[2]Consolidated!N138
C139: Third party staff, ex IT | D139: =[2]Consolidated!D139 | E139: =[2]Consolidated!E139 | F139: =[2]Consolidated!F139 | G139: =[2]Consolidated!G139 | H139: =[2]Consolidated!H139 | I139: =[2]Consolidated!I139 | J139: =[2]Consolidated!J139 | L139: =[2]Consolidated!L139 | M139: =[2]Consolidated!M139 | N139: =[2]Consolidated!N139
C140: Third party IT staff | D140: =[2]Consolidated!D140 | E140: =[2]Consolidated!E140 | F140: =[2]Consolidated!F140 | G140: =[2]Consolidated!G140 | H140: =[2]Consolidated!H140 | I140: =[2]Consolidated!I140 | J140: =[2]Consolidated!J140 | L140: =[2]Consolidated!L140 | M140: =[2]Consolidated!M140 | N140: =[2]Consolidated!N140
C141: Employee education | D141: =[2]Consolidated!D141 | E141: =[2]Consolidated!E141 | F141: =[2]Consolidated!F141 | G141: =[2]Consolidated!G141 | H141: =[2]Consolidated!H141 | I141: =[2]Consolidated!I141 | J141: =[2]Consolidated!J141 | L141: =[2]Consolidated!L141 | M141: =[2]Consolidated!M141 | N141: =[2]Consolidated!N141
C142: Other staff expenses | D142: =[2]Consolidated!D142 | E142: =[2]Consolidated!E142 | F142: =[2]Consolidated!F142 | G142: =[2]Consolidated!G142 | H142: =[2]Consolidated!H142 | I142: =[2]Consolidated!I142 | J142: =[2]Consolidated!J142 | L142: =[2]Consolidated!L142 | M142: =[2]Consolidated!M142 | N142: =[2]Consolidated!N142
C143: Staff expenses | D143: =[2]Consolidated!D143 | E143: =[2]Consolidated!E143 | F143: =[2]Consolidated!F143 | G143: =[2]Consolidated!G143 | H143: =[2]Consolidated!H143 | I143: =[2]Consolidated!I143 | J143: =[2]Consolidated!J143 | L143: =[2]Consolidated!L143 | M143: =[2]Consolidated!M143 | N143: =[2]Consolidated!N143
C144: Hardware expenses | D144: =[2]Consolidated!D144 | E144: =[2]Consolidated!E144 | F144: =[2]Consolidated!F144 | G144: =[2]Consolidated!G144 | H144: =[2]Consolidated!H144 | I144: =[2]Consolidated!I144 | J144: =[2]Consolidated!J144 | L144: =[2]Consolidated!L144 | M144: =[2]Consolidated!M144 | N144: =[2]Consolidated!N144
C145: Leasing/renting hardware | D145: =[2]Consolidated!D145 | E145: =[2]Consolidated!E145 | F145: =[2]Consolidated!F145 | G145: =[2]Consolidated!G145 | H145: =[2]Consolidated!H145 | I145: =[2]Consolidated!I145 | J145: =[2]Consolidated!J145 | L145: =[2]Consolidated!L145 | M145: =[2]Consolidated!M145 | N145: =[2]Consolidated!N145
C146: Software expenses | D146: =[2]Consolidated!D146 | E146: =[2]Consolidated!E146 | F146: =[2]Consolidated!F146 | G146: =[2]Consolidated!G146 | H146: =[2]Consolidated!H146 | I146: =[2]Consolidated!I146 | J146: =[2]Consolidated!J146 | L146: =[2]Consolidated!L146 | M146: =[2]Consolidated!M146 | N146: =[2]Consolidated!N146
C147: Leasing/renting/licenses sw | D147: =[2]Consolidated!D147 | E147: =[2]Consolidated!E147 | F147: =[2]Consolidated!F147 | G147: =[2]Consolidated!G147 | H147: =[2]Consolidated!H147 | I147: =[2]Consolidated!I147 | J147: =[2]Consolidated!J147 | L147: =[2]Consolidated!L147 | M147: =[2]Consolidated!M147 | N147: =[2]Consolidated!N147
C148: Depreciation hardware | D148: =[2]Consolidated!D148 | E148: =[2]Consolidated!E148 | F148: =[2]Consolidated!F148 | G148: =[2]Consolidated!G148 | H148: =[2]Consolidated!H148 | I148: =[2]Consolidated!I148 | J148: =[2]Consolidated!J148 | L148: =[2]Consolidated!L148 | M148: =[2]Consolidated!M148 | N148: =[2]Consolidated!N148
... C150: Outsourcing IT activities | D150: =[2]Consolidated!D150 | E150: =[2]Consolidated!E150 | F150: =[2]Consolidated!F150 | G150: =[2]Consolidated!G150 | H150: =[2]Consolidated!H150 | I150: =[2]Consolidated!I150 | J150: =[2]Consolidated!J150 | L150: =[2]Consolidated!L150 | M150: =[2]Consolidated!M150 | N150: =[2]Consolidated!N150
...

Sheet France
C1: France
C2: TOTAL COSTS (US$ excl. VAT) | D2: =[3]Consolidated!D2 | E2: =[3]Consolidated!E2 | F2: =[3]Consolidated!F2 | G2: =[3]Consolidated!G2 | H2: =[3]Consolidated!H2 | I2: =[3]Consolidated!I2 | J2: =[3]Consolidated!J2 | L2: =[3]Consolidated!L2 | M2: =[3]Consolidated!M2 | N2: =[3]Consolidated!N2
C3: Internal FTE | D3: =[3]Consolidated!D3 | E3: =[3]Consolidated!E3 | F3: =[3]Consolidated!F3 | G3: =[3]Consolidated!G3 | H3: =[3]Consolidated!H3 | I3: =[3]Consolidated!I3 | L3: =[3]Consolidated!L3 | M3: =[3]Consolidated!M3 | N3: =[3]Consolidated!N3
C4: External FTE | D4: =[3]Consolidated!D4 | E4: =[3]Consolidated!E4 | F4: =[3]Consolidated!F4 | G4: =[3]Consolidated!G4 | H4: =[3]Consolidated!H4 | I4: =[3]Consolidated!I4 | L4: =[3]Consolidated!L4 | M4: =[3]Consolidated!M4 | N4: =[3]Consolidated!N4
C5: Total FTE | D5: =[3]Consolidated!D5 | E5: =[3]Consolidated!E5 | F5: =[3]Consolidated!F5 | G5: =[3]Consolidated!G5 | H5: =[3]Consolidated!H5 | I5: =[3]Consolidated!I5 | L5: =[3]Consolidated!L5 | M5: =[3]Consolidated!M5 | N5: =[3]Consolidated!N5
C7: Salaries | D7: =(([3]Consolidated!D7)*1000)*(1/0.79941) | E7: =(([3]Consolidated!E7)*1000)*(1/0.79941) | F7: =(([3]Consolidated!F7)*1000)*(1/0.79941) | G7: =(([3]Consolidated!G7)*1000)*(1/0.79941) | H7: =(([3]Consolidated!H7)*1000)*(1/0.79941) | I7: =(([3]Consolidated!I7)*1000)*(1/0.79941) | J7: =(([3]Consolidated!J7)*1000)*(1/0.79941) | L7: =(([3]Consolidated!L7)*1000)*(1/0.79941) | M7: =(([3]Consolidated!M7)*1000)*(1/0.79941) | N7: =(([3]Consolidated!N7)*1000)*(1/0.79941) | P7: 1000
C8: Bonuses | D8: =(([3]Consolidated!D8)*1000)*(1/0.79941) | E8: =(([3]Consolidated!E8)*1000)*(1/0.79941) | F8: =(([3]Consolidated!F8)*1000)*(1/0.79941) | G8: =(([3]Consolidated!G8)*1000)*(1/0.79941) | H8: =(([3]Consolidated!H8)*1000)*(1/0.79941) | I8: =(([3]Consolidated!I8)*1000)*(1/0.79941) | J8: =(([3]Consolidated!J8)*1000)*(1/0.79941) | L8: =(([3]Consolidated!L8)*1000)*(1/0.79941) | M8: =(([3]Consolidated!M8)*1000)*(1/0.79941) | N8: =(([3]Consolidated!N8)*1000)*(1/0.79941) | P8: =1/0.79941 | Q8: Euro to Dollar Rate
C9: Third party staff, ex IT | D9: =(([3]Consolidated!D9)*1000)*(1/0.79941) | E9: =(([3]Consolidated!E9)*1000)*(1/0.79941) | F9: =(([3]Consolidated!F9)*1000)*(1/0.79941) | G9: =(([3]Consolidated!G9)*1000)*(1/0.79941) | H9: =(([3]Consolidated!H9)*1000)*(1/0.79941) | I9: =(([3]Consolidated!I9)*1000)*(1/0.79941) | J9: =(([3]Consolidated!J9)*1000)*(1/0.79941) | L9: =(([3]Consolidated!L9)*1000)*(1/0.79941) | M9: =(([3]Consolidated!M9)*1000)*(1/0.79941) | N9: =(([3]Consolidated!N9)*1000)*(1/0.79941)
C10: Third party IT staff | D10: =(([3]Consolidated!D10)*1000)*(1/0.79941) | E10: =(([3]Consolidated!E10)*1000)*(1/0.79941) | F10: =(([3]Consolidated!F10)*1000)*(1/0.79941) | G10: =(([3]Consolidated!G10)*1000)*(1/0.79941) | H10: =(([3]Consolidated!H10)*1000)*(1/0.79941) | I10: =(([3]Consolidated!I10)*1000)*(1/0.79941) | J10: =(([3]Consolidated!J10)*1000)*(1/0.79941) | L10: =(([3]Consolidated!L10)*1000)*(1/0.79941) | M10: =(([3]Consolidated!M10)*1000)*(1/0.79941) | N10: =(([3]Consolidated!N10)*1000)*(1/0.79941)
C11: Employee education | D11: =(([3]Consolidated!D11)*1000)*(1/0.79941) | E11: =(([3]Consolidated!E11)*1000)*(1/0.79941) | F11: =(([3]Consolidated!F11)*1000)*(1/0.79941) | G11: =(([3]Consolidated!G11)*1000)*(1/0.79941) | H11: =(([3]Consolidated!H11)*1000)*(1/0.79941) | I11: =(([3]Consolidated!I11)*1000)*(1/0.79941) | J11: =(([3]Consolidated!J11)*1000)*(1/0.79941) | L11: =(([3]Consolidated!L11)*1000)*(1/0.79941) | M11: =(([3]Consolidated!M11)*1000)*(1/0.79941) | N11: =(([3]Consolidated!N11)*1000)*(1/0.79941)
C12: Other staff expenses | D12: =(([3]Consolidated!D12)*1000)*(1/0.79941) | E12: =(([3]Consolidated!E12)*1000)*(1/0.79941) | F12: =(([3]Consolidated!F12)*1000)*(1/0.79941) | G12: =(([3]Consolidated!G12)*1000)*(1/0.79941) | H12: =(([3]Consolidated!H12)*1000)*(1/0.79941) | I12: =(([3]Consolidated!I12)*1000)*(1/0.79941) | J12: =(([3]Consolidated!J12)*1000)*(1/0.79941) | L12: =(([3]Consolidated!L12)*1000)*(1/0.79941) | M12: =(([3]Consolidated!M12)*1000)*(1/0.79941) | N12: =(([3]Consolidated!N12)*1000)*(1/0.79941)
C13: Staff expenses | D13: =(([3]Consolidated!D13)*1000)*(1/0.79941) | E13: =(([3]Consolidated!E13)*1000)*(1/0.79941) | F13: =(([3]Consolidated!F13)*1000)*(1/0.79941) | G13: =(([3]Consolidated!G13)*1000)*(1/0.79941) | H13: =(([3]Consolidated!H13)*1000)*(1/0.79941) | I13: =(([3]Consolidated!I13)*1000)*(1/0.79941) | J13: =(([3]Consolidated!J13)*1000)*(1/0.79941) | L13: =(([3]Consolidated!L13)*1000)*(1/0.79941) | M13: =(([3]Consolidated!M13)*1000)*(1/0.79941) | N13: =(([3]Consolidated!N13)*1000)*(1/0.79941)
C14: Hardware expenses | D14: =(([3]Consolidated!D14)*1000)*(1/0.79941) | E14: =(([3]Consolidated!E14)*1000)*(1/0.79941) | F14: =(([3]Consolidated!F14)*1000)*(1/0.79941) | G14: =(([3]Consolidated!G14)*1000)*(1/0.79941) | H14: =(([3]Consolidated!H14)*1000)*(1/0.79941) | I14: =(([3]Consolidated!I14)*1000)*(1/0.79941) | J14: =(([3]Consolidated!J14)*1000)*(1/0.79941) | L14: =(([3]Consolidated!L14)*1000)*(1/0.79941) | M14: =(([3]Consolidated!M14)*1000)*(1/0.79941) | N14: =(([3]Consolidated!N14)*1000)*(1/0.79941)
C15: Leasing/renting hardware | D15: =(([3]Consolidated!D15)*1000)*(1/0.79941) | E15: =(([3]Consolidated!E15)*1000)*(1/0.79941) | F15: =(([3]Consolidated!F15)*1000)*(1/0.79941) | G15: =(([3]Consolidated!G15)*1000)*(1/0.79941) | H15: =(([3]Consolidated!H15)*1000)*(1/0.79941) | I15: =(([3]Consolidated!I15)*1000)*(1/0.79941) | J15: =(([3]Consolidated!J15)*1000)*(1/0.79941) | L15: =(([3]Consolidated!L15)*1000)*(1/0.79941) | M15: =(([3]Consolidated!M15)*1000)*(1/0.79941) | N15: =(([3]Consolidated!N15)*1000)*(1/0.79941)
C16: Software expenses | D16: =(([3]Consolidated!D16)*1000)*(1/0.79941) | E16: =(([3]Consolidated!E16)*1000)*(1/0.79941) | F16: =(([3]Consolidated!F16)*1000)*(1/0.79941) | G16: =(([3]Consolidated!G16)*1000)*(1/0.79941) | H16: =(([3]Consolidated!H16)*1000)*(1/0.79941) | I16: =(([3]Consolidated!I16)*1000)*(1/0.79941) | J16: =(([3]Consolidated!J16)*1000)*(1/0.79941) | L16: =(([3]Consolidated!L16)*1000)*(1/0.79941) | M16: =(([3]Consolidated!M16)*1000)*(1/0.79941) | N16: =(([3]Consolidated!N16)*1000)*(1/0.79941)
C17: Leasing/renting/licenses sw | D17: =(([3]Consolidated!D17)*1000)*(1/0.79941) | E17: =(([3]Consolidated!E17)*1000)*(1/0.79941) | F17: =(([3]Consolidated!F17)*1000)*(1/0.79941) | G17: =(([3]Consolidated!G17)*1000)*(1/0.79941) | H17: =(([3]Consolidated!H17)*1000)*(1/0.79941) | I17: =(([3]Consolidated!I17)*1000)*(1/0.79941) | J17: =(([3]Consolidated!J17)*1000)*(1/0.79941) | L17: =(([3]Consolidated!L17)*1000)*(1/0.79941) | M17: =(([3]Consolidated!M17)*1000)*(1/0.79941) | N17: =(([3]Consolidated!N17)*1000)*(1/0.79941)
C18: Depreciation hardware | D18: =(([3]Consolidated!D18)*1000)*(1/0.79941) | E18: =(([3]Consolidated!E18)*1000)*(1/0.79941) | F18: =(([3]Consolidated!F18)*1000)*(1/0.79941) | G18: =(([3]Consolidated!G18)*1000)*(1/0.79941) | H18: =(([3]Consolidated!H18)*1000)*(1/0.79941) | I18: =(([3]Consolidated!I18)*1000)*(1/0.79941) | J18: =(([3]Consolidated!J18)*1000)*(1/0.79941) | L18: =(([3]Consolidated!L18)*1000)*(1/0.79941) | M18: =(([3]Consolidated!M18)*1000)*(1/0.79941) | N18: =(([3]Consolidated!N18)*1000)*(1/0.79941)
C19: Depreciation software | D19: =(([3]Consolidated!D19)*1000)*(1/0.79941) | E19: =(([3]Consolidated!E19)*1000)*(1/0.79941) | F19: =(([3]Consolidated!F19)*1000)*(1/0.79941) | G19: =(([3]Consolidated!G19)*1000)*(1/0.79941) | H19: =(([3]Consolidated!H19)*1000)*(1/0.79941) | I19: =(([3]Consolidated!I19)*1000)*(1/0.79941) | J19: =(([3]Consolidated!J19)*1000)*(1/0.79941) | L19: =(([3]Consolidated!L19)*1000)*(1/0.79941) | M19: =(([3]Consolidated!M19)*1000)*(1/0.79941) | N19: =(([3]Consolidated!N19)*1000)*(1/0.79941)
C20: Outsourcing IT activities | D20: =(([3]Consolidated!D20)*1000)*(1/0.79941) | E20: =(([3]Consolidated!E20)*1000)*(1/0.79941) | F20: =(([3]Consolidated!F20)*1000)*(1/0.79941) | G20: =(([3]Consolidated!G20)*1000)*(1/0.79941) | H20: =(([3]Consolidated!H20)*1000)*(1/0.79941) | I20: =(([3]Consolidated!I20)*1000)*(1/0.79941) | J20: =(([3]Consolidated!J20)*1000)*(1/0.79941) | L20: =(([3]Consolidated!L20)*1000)*(1/0.79941) | M20: =(([3]Consolidated!M20)*1000)*(1/0.79941) | N20: =(([3]Consolidated!N20)*1000)*(1/0.79941)
... C34: Operating expenses | D34: =(([3]Consolidated!D34)*1000)*(1/0.79941) | E34: =(([3]Consolidated!E34)*1000)*(1/0.79941) | F34: =(([3]Consolidated!F34)*1000)*(1/0.79941) | G34: =(([3]Consolidated!G34)*1000)*(1/0.79941) | H34: =(([3]Consolidated!H34)*1000)*(1/0.79941) | I34: =(([3]Consolidated!I34)*1000)*(1/0.79941) | J34: =(([3]Consolidated!J34)*1000)*(1/0.79941) | L34: =(([3]Consolidated!L34)*1000)*(1/0.79941) | M34: =(([3]Consolidated!M34)*1000)*(1/0.79941) | N34: =(([3]Consolidated!N34)*1000)*(1/0.79941)
D35: =0*(1/0.79941) | E35: =0*(1/0.79941) | F35: =0*(1/0.79941) | G35: =0*(1/0.79941) | H35: =0*(1/0.79941) | I35: =0*(1/0.79941) | J35: =0*(1/0.79941) | L35: =0*(1/0.79941) | M35: =0*(1/0.79941) | N35: =0*(1/0.79941)
C36: HR & Comms | D36: =(([3]Consolidated!D36)*1000)*(1/0.79941) | E36: =(([3]Consolidated!E36)*1000)*(1/0.79941) | F36: =(([3]Consolidated!F36)*1000)*(1/0.79941) | G36: =(([3]Consolidated!G36)*1000)*(1/0.79941) | H36: =(([3]Consolidated!H36)*1000)*(1/0.79941) | I36: =(([3]Consolidated!I36)*1000)*(1/0.79941) | J36: =(([3]Consolidated!J36)*1000)*(1/0.79941) | L36: =(([3]Consolidated!L36)*1000)*(1/0.79941) | M36: =(([3]Consolidated!M36)*1000)*(1/0.79941) | N36: =(([3]Consolidated!N36)*1000)*(1/0.79941)
C37: Finance & Business Support | D37: =(([3]Consolidated!D37)*1000)*(1/0.79941) | E37: =(([3]Consolidated!E37)*1000)*(1/0.79941) | F37: =(([3]Consolidated!F37)*1000)*(1/0.79941) | G37: =(([3]Consolidated!G37)*1000)*(1/0.79941) | H37: =(([3]Consolidated!H37)*1000)*(1/0.79941) | I37: =(([3]Consolidated!I37)*1000)*(1/0.79941) | J37: =(([3]Consolidated!J37)*1000)*(1/0.79941) | L37: =(([3]Consolidated!L37)*1000)*(1/0.79941) | M37: =(([3]Consolidated!M37)*1000)*(1/0.79941) | N37: =(([3]Consolidated!N37)*1000)*(1/0.79941)
C38: IT alloc | D38: =(([3]Consolidated!D38)*1000)*(1/0.79941) | E38: =(([3]Consolidated!E38)*1000)*(1/0.79941) | F38: =(([3]Consolidated!F38)*1000)*(1/0.79941) | G38: =(([3]Consolidated!G38)*1000)*(1/0.79941) | H38: =(([3]Consolidated!H38)*1000)*(1/0.79941) | I38: =(([3]Consolidated!I38)*1000)*(1/0.79941) | J38: =(([3]Consolidated!J38)*1000)*(1/0.79941) | L38: =(([3]Consolidated!L38)*1000)*(1/0.79941) | M38: =(([3]Consolidated!M38)*1000)*(1/0.79941) | N38: =(([3]Consolidated!N38)*1000)*(1/0.79941)
C39: Facilities Management | D39: =(([3]Consolidated!D39)*1000)*(1/0.79941) | E39: =(([3]Consolidated!E39)*1000)*(1/0.79941) | F39: =(([3]Consolidated!F39)*1000)*(1/0.79941) | G39: =(([3]Consolidated!G39)*1000)*(1/0.79941) | H39: =(([3]Consolidated!H39)*1000)*(1/0.79941) | I39: =(([3]Consolidated!I39)*1000)*(1/0.79941) | J39: =(([3]Consolidated!J39)*1000)*(1/0.79941) | L39: =(([3]Consolidated!L39)*1000)*(1/0.79941) | M39: =(([3]Consolidated!M39)*1000)*(1/0.79941) | N39: =(([3]Consolidated!N39)*1000)*(1/0.79941)
C40: Overheads | D40: =(([3]Consolidated!D40)*1000)*(1/0.79941) | E40: =(([3]Consolidated!E40)*1000)*(1/0.79941) | F40: =(([3]Consolidated!F40)*1000)*(1/0.79941) | G40: =(([3]Consolidated!G40)*1000)*(1/0.79941) | H40: =(([3]Consolidated!H40)*1000)*(1/0.79941) | I40: =(([3]Consolidated!I40)*1000)*(1/0.79941) | J40: =(([3]Consolidated!J40)*1000)*(1/0.79941) | L40: =(([3]Consolidated!L40)*1000)*(1/0.79941) | M40: =(([3]Consolidated!M40)*1000)*(1/0.79941) | N40: =(([3]Consolidated!N40)*1000)*(1/0.79941)
C41: 0 | D41: =0*(1/0.79941) | E41: =0*(1/0.79941) | F41: =0*(1/0.79941) | G41: =0*(1/0.79941) | H41: =0*(1/0.79941) | I41: =0*(1/0.79941) | J41: =0*(1/0.79941) | L41: =0*(1/0.79941) | M41: =0*(1/0.79941) | N41: =0*(1/0.79941)
C42: Total Operating Costs (incl. O/H) | D42: =(([3]Consolidated!D42)*1000)*(1/0.79941) | E42: =(([3]Consolidated!E42)*1000)*(1/0.79941) | F42: =(([3]Consolidated!F42)*1000)*(1/0.79941) | G42: =(([3]Consolidated!G42)*1000)*(1/0.79941) | H42: =(([3]Consolidated!H42)*1000)*(1/0.79941) | I42: =(([3]Consolidated!I42)*1000)*(1/0.79941) | J42: =(([3]Consolidated!J42)*1000)*(1/0.79941) | L42: =(([3]Consolidated!L42)*1000)*(1/0.79941) | M42: =(([3]Consolidated!M42)*1000)*(1/0.79941) | N42: =(([3]Consolidated!N42)*1000)*(1/0.79941)
C45: SUPPLIER ASSUMED COSTS (US$ excl. VAT) | D45: =[3]Consolidated!D45 | E45: =[3]Consolidated!E45 | F45: =[3]Consolidated!F45 | G45: =[3]Consolidated!G45 | H45: =[3]Consolidated!H45 | I45: =[3]Consolidated!I45 | J45: =[3]Consolidated!J45 | L45: =[3]Consolidated!L45 | M45: =[3]Consolidated!M45 | N45: =[3]Consolidated!N45
C46: Internal FTE | D46: =[3]Consolidated!D46 | E46: =[3]Consolidated!E46 | F46: =[3]Consolidated!F46 | G46: =[3]Consolidated!G46 | H46: =[3]Consolidated!H46 | I46: =[3]Consolidated!I46 | L46: =[3]Consolidated!L46 | M46: =[3]Consolidated!M46
C47: External FTE | D47: =[3]Consolidated!D47 | E47: =[3]Consolidated!E47 | F47: =[3]Consolidated!F47 | G47: =[3]Consolidated!G47 | H47: =[3]Consolidated!H47 | I47: =[3]Consolidated!I47 | L47: =[3]Consolidated!L47 | M47: =[3]Consolidated!M47
C48: Total FTE | D48: =[3]Consolidated!D48 | E48: =[3]Consolidated!E48 | F48: =[3]Consolidated!F48 | G48: =[3]Consolidated!G48 | H48: =[3]Consolidated!H48 | I48: =[3]Consolidated!I48 | L48: =[3]Consolidated!L48 | M48: =[3]Consolidated!M48
C50: Salaries | D50: =(([3]Consolidated!D50)*1000)*(1/0.79941) | E50: =(([3]Consolidated!E50)*1000)*(1/0.79941) | F50: =(([3]Consolidated!F50)*1000)*(1/0.79941) | G50: =(([3]Consolidated!G50)*1000)*(1/0.79941) | H50: =(([3]Consolidated!H50)*1000)*(1/0.79941) | I50: =(([3]Consolidated!I50)*1000)*(1/0.79941) | J50: =(([3]Consolidated!J50)*1000)*(1/0.79941) | L50: =(([3]Consolidated!L50)*1000)*(1/0.79941) | M50: =(([3]Consolidated!M50)*1000)*(1/0.79941) | N50: =(([3]Consolidated!N50)*1000)*(1/0.79941)
C51: Bonuses | D51: =(([3]Consolidated!D51)*1000)*(1/0.79941) | E51: =(([3]Consolidated!E51)*1000)*(1/0.79941) | F51: =(([3]Consolidated!F51)*1000)*(1/0.79941) | G51: =(([3]Consolidated!G51)*1000)*(1/0.79941) | H51: =(([3]Consolidated!H51)*1000)*(1/0.79941) | I51: =(([3]Consolidated!I51)*1000)*(1/0.79941) | J51: =(([3]Consolidated!J51)*1000)*(1/0.79941) | L51: =(([3]Consolidated!L51)*1000)*(1/0.79941) | M51: =(([3]Consolidated!M51)*1000)*(1/0.79941) | N51: =(([3]Consolidated!N51)*1000)*(1/0.79941)
C52: Third party staff, ex IT | D52: =(([3]Consolidated!D52)*1000)*(1/0.79941) | E52: =(([3]Consolidated!E52)*1000)*(1/0.79941) | F52: =(([3]Consolidated!F52)*1000)*(1/0.79941) | G52: =(([3]Consolidated!G52)*1000)*(1/0.79941) | H52: =(([3]Consolidated!H52)*1000)*(1/0.79941) | I52: =(([3]Consolidated!I52)*1000)*(1/0.79941) | J52: =(([3]Consolidated!J52)*1000)*(1/0.79941) | L52: =(([3]Consolidated!L52)*1000)*(1/0.79941) | M52: =(([3]Consolidated!M52)*1000)*(1/0.79941) | N52: =(([3]Consolidated!N52)*1000)*(1/0.79941)
C53: Third party IT staff | D53: =(([3]Consolidated!D53)*1000)*(1/0.79941) | E53: =(([3]Consolidated!E53)*1000)*(1/0.79941) | F53: =(([3]Consolidated!F53)*1000)*(1/0.79941) | G53: =(([3]Consolidated!G53)*1000)*(1/0.79941) | H53: =(([3]Consolidated!H53)*1000)*(1/0.79941) | I53: =(([3]Consolidated!I53)*1000)*(1/0.79941) | J53: =(([3]Consolidated!J53)*1000)*(1/0.79941) | L53: =(([3]Consolidated!L53)*1000)*(1/0.79941) | M53: =(([3]Consolidated!M53)*1000)*(1/0.79941) | N53: =(([3]Consolidated!N53)*1000)*(1/0.79941)
C54: Employee education | D54: =(([3]Consolidated!D54)*1000)*(1/0.79941) | E54: =(([3]Consolidated!E54)*1000)*(1/0.79941) | F54: =(([3]Consolidated!F54)*1000)*(1/0.79941) | G54: =(([3]Consolidated!G54)*1000)*(1/0.79941) | H54: =(([3]Consolidated!H54)*1000)*(1/0.79941) | I54: =(([3]Consolidated!I54)*1000)*(1/0.79941) | J54: =(([3]Consolidated!J54)*1000)*(1/0.79941) | L54: =(([3]Consolidated!L54)*1000)*(1/0.79941) | M54: =(([3]Consolidated!M54)*1000)*(1/0.79941) | N54: =(([3]Consolidated!N54)*1000)*(1/0.79941)
C55: Other staff expenses | D55: =(([3]Consolidated!D55)*1000)*(1/0.79941) | E55: =(([3]Consolidated!E55)*1000)*(1/0.79941) | F55: =(([3]Consolidated!F55)*1000)*(1/0.79941) | G55: =(([3]Consolidated!G55)*1000)*(1/0.79941) | H55: =(([3]Consolidated!H55)*1000)*(1/0.79941) | I55: =(([3]Consolidated!I55)*1000)*(1/0.79941) | J55: =(([3]Consolidated!J55)*1000)*(1/0.79941) | L55: =(([3]Consolidated!L55)*1000)*(1/0.79941) | M55: =(([3]Consolidated!M55)*1000)*(1/0.79941) | N55: =(([3]Consolidated!N55)*1000)*(1/0.79941)
C56: Staff expenses | D56: =(([3]Consolidated!D56)*1000)*(1/0.79941) | E56: =(([3]Consolidated!E56)*1000)*(1/0.79941) | F56: =(([3]Consolidated!F56)*1000)*(1/0.79941) | G56: =(([3]Consolidated!G56)*1000)*(1/0.79941) | H56: =(([3]Consolidated!H56)*1000)*(1/0.79941) | I56: =(([3]Consolidated!I56)*1000)*(1/0.79941) | J56: =(([3]Consolidated!J56)*1000)*(1/0.79941) | L56: =(([3]Consolidated!L56)*1000)*(1/0.79941) | M56: =(([3]Consolidated!M56)*1000)*(1/0.79941) | N56: =(([3]Consolidated!N56)*1000)*(1/0.79941)
C57: Hardware expenses | D57: =(([3]Consolidated!D57)*1000)*(1/0.79941) | E57: =(([3]Consolidated!E57)*1000)*(1/0.79941) | F57: =(([3]Consolidated!F57)*1000)*(1/0.79941) | G57: =(([3]Consolidated!G57)*1000)*(1/0.79941) | H57: =(([3]Consolidated!H57)*1000)*(1/0.79941) | I57: =(([3]Consolidated!I57)*1000)*(1/0.79941) | J57: =(([3]Consolidated!J57)*1000)*(1/0.79941) | L57: =(([3]Consolidated!L57)*1000)*(1/0.79941) | M57: =(([3]Consolidated!M57)*1000)*(1/0.79941) | N57: =(([3]Consolidated!N57)*1000)*(1/0.79941)
C58: Leasing/renting hardware | D58: =(([3]Consolidated!D58)*1000)*(1/0.79941) | E58: =(([3]Consolidated!E58)*1000)*(1/0.79941) | F58: =(([3]Consolidated!F58)*1000)*(1/0.79941) | G58: =(([3]Consolidated!G58)*1000)*(1/0.79941) | H58: =(([3]Consolidated!H58)*1000)*(1/0.79941) | I58: =(([3]Consolidated!I58)*1000)*(1/0.79941) | J58: =(([3]Consolidated!J58)*1000)*(1/0.79941) | L58: =(([3]Consolidated!L58)*1000)*(1/0.79941) | M58: =(([3]Consolidated!M58)*1000)*(1/0.79941) | N58: =(([3]Consolidated!N58)*1000)*(1/0.79941)
C59: Software expenses | D59: =(([3]Consolidated!D59)*1000)*(1/0.79941) | E59: =(([3]Consolidated!E59)*1000)*(1/0.79941) | F59: =(([3]Consolidated!F59)*1000)*(1/0.79941) | G59: =(([3]Consolidated!G59)*1000)*(1/0.79941) | H59: =(([3]Consolidated!H59)*1000)*(1/0.79941) | I59: =(([3]Consolidated!I59)*1000)*(1/0.79941) | J59: =(([3]Consolidated!J59)*1000)*(1/0.79941) | L59: =(([3]Consolidated!L59)*1000)*(1/0.79941) | M59: =(([3]Consolidated!M59)*1000)*(1/0.79941) | N59: =(([3]Consolidated!N59)*1000)*(1/0.79941)
C60: Leasing/renting/licenses sw | D60: =(([3]Consolidated!D60)*1000)*(1/0.79941) | E60: =(([3]Consolidated!E60)*1000)*(1/0.79941) | F60: =(([3]Consolidated!F60)*1000)*(1/0.79941) | G60: =(([3]Consolidated!G60)*1000)*(1/0.79941) | H60: =(([3]Consolidated!H60)*1000)*(1/0.79941) | I60: =(([3]Consolidated!I60)*1000)*(1/0.79941) | J60: =(([3]Consolidated!J60)*1000)*(1/0.79941) | L60: =(([3]Consolidated!L60)*1000)*(1/0.79941) | M60: =(([3]Consolidated!M60)*1000)*(1/0.79941) | N60: =(([3]Consolidated!N60)*1000)*(1/0.79941)
C61: Depreciation hardware | D61: =(([3]Consolidated!D61)*1000)*(1/0.79941) | E61: =(([3]Consolidated!E61)*1000)*(1/0.79941) | F61: =(([3]Consolidated!F61)*1000)*(1/0.79941) | G61: =(([3]Consolidated!G61)*1000)*(1/0.79941) | H61: =(([3]Consolidated!H61)*1000)*(1/0.79941) | I61: =(([3]Consolidated!I61)*1000)*(1/0.79941) | J61: =(([3]Consolidated!J61)*1000)*(1/0.79941) | L61: =(([3]Consolidated!L61)*1000)*(1/0.79941) | M61: =(([3]Consolidated!M61)*1000)*(1/0.79941) | N61: =(([3]Consolidated!N61)*1000)*(1/0.79941)
... C77: Operating expenses | D77: =(([3]Consolidated!D77)*1000)*(1/0.79941) | E77: =(([3]Consolidated!E77)*1000)*(1/0.79941) | F77: =(([3]Consolidated!F77)*1000)*(1/0.79941) | G77: =(([3]Consolidated!G77)*1000)*(1/0.79941) | H77: =(([3]Consolidated!H77)*1000)*(1/0.79941) | I77: =(([3]Consolidated!I77)*1000)*(1/0.79941) | J77: =(([3]Consolidated!J77)*1000)*(1/0.79941) | L77: =(([3]Consolidated!L77)*1000)*(1/0.79941) | M77: =(([3]Consolidated!M77)*1000)*(1/0.79941) | N77: =(([3]Consolidated!N77)*1000)*(1/0.79941)
D78: =0*(1/0.79941) | E78: =0*(1/0.79941) | F78: =0*(1/0.79941) | G78: =0*(1/0.79941) | H78: =0*(1/0.79941) | I78: =0*(1/0.79941) | J78: =0*(1/0.79941) | L78: =0*(1/0.79941) | M78: =0*(1/0.79941) | N78: =0*(1/0.79941)
C79: HR & Comms | D79: =(([3]Consolidated!D79)*1000)*(1/0.79941) | E79: =(([3]Consolidated!E79)*1000)*(1/0.79941) | F79: =(([3]Consolidated!F79)*1000)*(1/0.79941) | G79: =(([3]Consolidated!G79)*1000)*(1/0.79941) | H79: =(([3]Consolidated!H79)*1000)*(1/0.79941) | I79: =(([3]Consolidated!I79)*1000)*(1/0.79941) | J79: =(([3]Consolidated!J79)*1000)*(1/0.79941) | L79: =(([3]Consolidated!L79)*1000)*(1/0.79941) | M79: =(([3]Consolidated!M79)*1000)*(1/0.79941) | N79: =(([3]Consolidated!N79)*1000)*(1/0.79941)
C80: Finance & Business Support | D80: =(([3]Consolidated!D80)*1000)*(1/0.79941) | E80: =(([3]Consolidated!E80)*1000)*(1/0.79941) | F80: =(([3]Consolidated!F80)*1000)*(1/0.79941) | G80: =(([3]Consolidated!G80)*1000)*(1/0.79941) | H80: =(([3]Consolidated!H80)*1000)*(1/0.79941) | I80: =(([3]Consolidated!I80)*1000)*(1/0.79941) | J80: =(([3]Consolidated!J80)*1000)*(1/0.79941) | L80: =(([3]Consolidated!L80)*1000)*(1/0.79941) | M80: =(([3]Consolidated!M80)*1000)*(1/0.79941) | N80: =(([3]Consolidated!N80)*1000)*(1/0.79941)
C81: IT alloc | D81: =(([3]Consolidated!D81)*1000)*(1/0.79941) | E81: =(([3]Consolidated!E81)*1000)*(1/0.79941) | F81: =(([3]Consolidated!F81)*1000)*(1/0.79941) | G81: =(([3]Consolidated!G81)*1000)*(1/0.79941) | H81: =(([3]Consolidated!H81)*1000)*(1/0.79941) | I81: =(([3]Consolidated!I81)*1000)*(1/0.79941) | J81: =(([3]Consolidated!J81)*1000)*(1/0.79941) | L81: =(([3]Consolidated!L81)*1000)*(1/0.79941) | M81: =(([3]Consolidated!M81)*1000)*(1/0.79941) | N81: =(([3]Consolidated!N81)*1000)*(1/0.79941)
C82: Facilities Management | D82: =(([3]Consolidated!D82)*1000)*(1/0.79941) | E82: =(([3]Consolidated!E82)*1000)*(1/0.79941) | F82: =(([3]Consolidated!F82)*1000)*(1/0.79941) | G82: =(([3]Consolidated!G82)*1000)*(1/0.79941) | H82: =(([3]Consolidated!H82)*1000)*(1/0.79941) | I82: =(([3]Consolidated!I82)*1000)*(1/0.79941) | J82: =(([3]Consolidated!J82)*1000)*(1/0.79941) | L82: =(([3]Consolidated!L82)*1000)*(1/0.79941) | M82: =(([3]Consolidated!M82)*1000)*(1/0.79941) | N82: =(([3]Consolidated!N82)*1000)*(1/0.79941)
C83: Overheads | D83: =(([3]Consolidated!D83)*1000)*(1/0.79941) | E83: =(([3]Consolidated!E83)*1000)*(1/0.79941) | F83: =(([3]Consolidated!F83)*1000)*(1/0.79941) | G83: =(([3]Consolidated!G83)*1000)*(1/0.79941) | H83: =(([3]Consolidated!H83)*1000)*(1/0.79941) | I83: =(([3]Consolidated!I83)*1000)*(1/0.79941) | J83: =(([3]Consolidated!J83)*1000)*(1/0.79941) | L83: =(([3]Consolidated!L83)*1000)*(1/0.79941) | M83: =(([3]Consolidated!M83)*1000)*(1/0.79941) | N83: =(([3]Consolidated!N83)*1000)*(1/0.79941)
D84: =(([3]Consolidated!D84)*1000)*(1/0.79941) | E84: =(([3]Consolidated!E84)*1000)*(1/0.79941) | F84: =(([3]Consolidated!F84)*1000)*(1/0.79941) | G84: =(([3]Consolidated!G84)*1000)*(1/0.79941) | H84: =(([3]Consolidated!H84)*1000)*(1/0.79941) | I84: =(([3]Consolidated!I84)*1000)*(1/0.79941) | J84: =(([3]Consolidated!J84)*1000)*(1/0.79941) | L84: =(([3]Consolidated!L84)*1000)*(1/0.79941) | M84: =(([3]Consolidated!M84)*1000)*(1/0.79941) | N84: =(([3]Consolidated!N84)*1000)*(1/0.79941)
C85: Total Operating Costs (incl. O/H) | D85: =(([3]Consolidated!D85)*1000)*(1/0.79941) | E85: =(([3]Consolidated!E85)*1000)*(1/0.79941) | F85: =(([3]Consolidated!F85)*1000)*(1/0.79941) | G85: =(([3]Consolidated!G85)*1000)*(1/0.79941) | H85: =(([3]Consolidated!H85)*1000)*(1/0.79941) | I85: =(([3]Consolidated!I85)*1000)*(1/0.79941) | J85: =(([3]Consolidated!J85)*1000)*(1/0.79941) | L85: =(([3]Consolidated!L85)*1000)*(1/0.79941) | M85: =(([3]Consolidated!M85)*1000)*(1/0.79941) | N85: =(([3]Consolidated!N85)*1000)*(1/0.79941)
C89: PASS THROUGH COSTS (US$ excl. VAT) | D89: =[3]Consolidated!D89 | E89: =[3]Consolidated!E89 | F89: =[3]Consolidated!F89 | G89: =[3]Consolidated!G89 | H89: =[3]Consolidated!H89 | I89: =[3]Consolidated!I89 | J89: =[3]Consolidated!J89 | L89: =[3]Consolidated!L89 | M89: =[3]Consolidated!M89 | N89: =[3]Consolidated!N89
C90: Internal FTE | D90: =[3]Consolidated!D90 | E90: =[3]Consolidated!E90 | F90: =[3]Consolidated!F90 | G90: =[3]Consolidated!G90 | H90: =[3]Consolidated!H90 | I90: =[3]Consolidated!I90 | L90: =[3]Consolidated!L90 | M90: =[3]Consolidated!M90 | N90: =[3]Consolidated!N90
C91: External FTE | D91: =[3]Consolidated!D91 | E91: =[3]Consolidated!E91 | F91: =[3]Consolidated!F91 | G91: =[3]Consolidated!G91 | H91: =[3]Consolidated!H91 | I91: =[3]Consolidated!I91 | L91: =[3]Consolidated!L91 | M91: =[3]Consolidated!M91 | N91: =[3]Consolidated!N91
C92: Total FTE | D92: =[3]Consolidated!D92 | E92: =[3]Consolidated!E92 | F92: =[3]Consolidated!F92 | G92: =[3]Consolidated!G92 | H92: =[3]Consolidated!H92 | I92: =[3]Consolidated!I92 | L92: =[3]Consolidated!L92 | M92: =[3]Consolidated!M92 | N92: =[3]Consolidated!N92
C94: Salaries | D94: =(([3]Consolidated!D94)*1000)*(1/0.79941) | E94: =(([3]Consolidated!E94)*1000)*(1/0.79941) | F94: =(([3]Consolidated!F94)*1000)*(1/0.79941) | G94: =(([3]Consolidated!G94)*1000)*(1/0.79941) | H94: =(([3]Consolidated!H94)*1000)*(1/0.79941) | I94: =(([3]Consolidated!I94)*1000)*(1/0.79941) | J94: =(([3]Consolidated!J94)*1000)*(1/0.79941) | L94: =(([3]Consolidated!L94)*1000)*(1/0.79941) | M94: =(([3]Consolidated!M94)*1000)*(1/0.79941) | N94: =(([3]Consolidated!N94)*1000)*(1/0.79941)
C95: Bonuses | D95: =(([3]Consolidated!D95)*1000)*(1/0.79941) | E95: =(([3]Consolidated!E95)*1000)*(1/0.79941) | F95: =(([3]Consolidated!F95)*1000)*(1/0.79941) | G95: =(([3]Consolidated!G95)*1000)*(1/0.79941) | H95: =(([3]Consolidated!H95)*1000)*(1/0.79941) | I95: =(([3]Consolidated!I95)*1000)*(1/0.79941) | J95: =(([3]Consolidated!J95)*1000)*(1/0.79941) | L95: =(([3]Consolidated!L95)*1000)*(1/0.79941) | M95: =(([3]Consolidated!M95)*1000)*(1/0.79941) | N95: =(([3]Consolidated!N95)*1000)*(1/0.79941)
C96: Third party staff, ex IT | D96: =(([3]Consolidated!D96)*1000)*(1/0.79941) | E96: =(([3]Consolidated!E96)*1000)*(1/0.79941) | F96: =(([3]Consolidated!F96)*1000)*(1/0.79941) | G96: =(([3]Consolidated!G96)*1000)*(1/0.79941) | H96: =(([3]Consolidated!H96)*1000)*(1/0.79941) | I96: =(([3]Consolidated!I96)*1000)*(1/0.79941) | J96: =(([3]Consolidated!J96)*1000)*(1/0.79941) | L96: =(([3]Consolidated!L96)*1000)*(1/0.79941) | M96: =(([3]Consolidated!M96)*1000)*(1/0.79941) | N96: =(([3]Consolidated!N96)*1000)*(1/0.79941)
C97: Third party IT staff | D97: =(([3]Consolidated!D97)*1000)*(1/0.79941) | E97: =(([3]Consolidated!E97)*1000)*(1/0.79941) | F97: =(([3]Consolidated!F97)*1000)*(1/0.79941) | G97: =(([3]Consolidated!G97)*1000)*(1/0.79941) | H97: =(([3]Consolidated!H97)*1000)*(1/0.79941) | I97: =(([3]Consolidated!I97)*1000)*(1/0.79941) | J97: =(([3]Consolidated!J97)*1000)*(1/0.79941) | L97: =(([3]Consolidated!L97)*1000)*(1/0.79941) | M97: =(([3]Consolidated!M97)*1000)*(1/0.79941) | N97: =(([3]Consolidated!N97)*1000)*(1/0.79941)
C98: Employee education | D98: =(([3]Consolidated!D98)*1000)*(1/0.79941) | E98: =(([3]Consolidated!E98)*1000)*(1/0.79941) | F98: =(([3]Consolidated!F98)*1000)*(1/0.79941) | G98: =(([3]Consolidated!G98)*1000)*(1/0.79941) | H98: =(([3]Consolidated!H98)*1000)*(1/0.79941) | I98: =(([3]Consolidated!I98)*1000)*(1/0.79941) | J98: =(([3]Consolidated!J98)*1000)*(1/0.79941) | L98: =(([3]Consolidated!L98)*1000)*(1/0.79941) | M98: =(([3]Consolidated!M98)*1000)*(1/0.79941) | N98: =(([3]Consolidated!N98)*1000)*(1/0.79941)
C99: Other staff expenses | D99: =(([3]Consolidated!D99)*1000)*(1/0.79941) | E99: =(([3]Consolidated!E99)*1000)*(1/0.79941) | F99: =(([3]Consolidated!F99)*1000)*(1/0.79941) | G99: =(([3]Consolidated!G99)*1000)*(1/0.79941) | H99: =(([3]Consolidated!H99)*1000)*(1/0.79941) | I99: =(([3]Consolidated!I99)*1000)*(1/0.79941) | J99: =(([3]Consolidated!J99)*1000)*(1/0.79941) | L99: =(([3]Consolidated!L99)*1000)*(1/0.79941) | M99: =(([3]Consolidated!M99)*1000)*(1/0.79941) | N99: =(([3]Consolidated!N99)*1000)*(1/0.79941)
C100: Staff expenses | D100: =(([3]Consolidated!D100)*1000)*(1/0.79941) | E100: =(([3]Consolidated!E100)*1000)*(1/0.79941) | F100: =(([3]Consolidated!F100)*1000)*(1/0.79941) | G100: =(([3]Consolidated!G100)*1000)*(1/0.79941) | H100: =(([3]Consolidated!H100)*1000)*(1/0.79941) | I100: =(([3]Consolidated!I100)*1000)*(1/0.79941) | J100: =(([3]Consolidated!J100)*1000)*(1/0.79941) | L100: =(([3]Consolidated!L100)*1000)*(1/0.79941) | M100: =(([3]Consolidated!M100)*1000)*(1/0.79941) | N100: =(([3]Consolidated!N100)*1000)*(1/0.79941)
C101: Hardware expenses | D101: =(([3]Consolidated!D101)*1000)*(1/0.79941) | E101: =(([3]Consolidated!E101)*1000)*(1/0.79941) | F101: =(([3]Consolidated!F101)*1000)*(1/0.79941) | G101: =(([3]Consolidated!G101)*1000)*(1/0.79941) | H101: =(([3]Consolidated!H101)*1000)*(1/0.79941) | I101: =(([3]Consolidated!I101)*1000)*(1/0.79941) | J101: =(([3]Consolidated!J101)*1000)*(1/0.79941) | L101: =(([3]Consolidated!L101)*1000)*(1/0.79941) | M101: =(([3]Consolidated!M101)*1000)*(1/0.79941) | N101: =(([3]Consolidated!N101)*1000)*(1/0.79941)
C102: Leasing/renting hardware | D102: =(([3]Consolidated!D102)*1000)*(1/0.79941) | E102: =(([3]Consolidated!E102)*1000)*(1/0.79941) | F102: =(([3]Consolidated!F102)*1000)*(1/0.79941) | G102: =(([3]Consolidated!G102)*1000)*(1/0.79941) | H102: =(([3]Consolidated!H102)*1000)*(1/0.79941) | I102: =(([3]Consolidated!I102)*1000)*(1/0.79941) | J102: =(([3]Consolidated!J102)*1000)*(1/0.79941) | L102: =(([3]Consolidated!L102)*1000)*(1/0.79941) | M102: =(([3]Consolidated!M102)*1000)*(1/0.79941) | N102: =(([3]Consolidated!N102)*1000)*(1/0.79941)
C103: Software expenses | D103: =(([3]Consolidated!D103)*1000)*(1/0.79941) | E103: =(([3]Consolidated!E103)*1000)*(1/0.79941) | F103: =(([3]Consolidated!F103)*1000)*(1/0.79941) | G103: =(([3]Consolidated!G103)*1000)*(1/0.79941) | H103: =(([3]Consolidated!H103)*1000)*(1/0.79941) | I103: =(([3]Consolidated!I103)*1000)*(1/0.79941) | J103: =(([3]Consolidated!J103)*1000)*(1/0.79941) | L103: =(([3]Consolidated!L103)*1000)*(1/0.79941) | M103: =(([3]Consolidated!M103)*1000)*(1/0.79941) | N103: =(([3]Consolidated!N103)*1000)*(1/0.79941)
C104: Leasing/renting/licenses sw | D104: =(([3]Consolidated!D104)*1000)*(1/0.79941) | E104: =(([3]Consolidated!E104)*1000)*(1/0.79941) | F104: =(([3]Consolidated!F104)*1000)*(1/0.79941) | G104: =(([3]Consolidated!G104)*1000)*(1/0.79941) | H104: =(([3]Consolidated!H104)*1000)*(1/0.79941) | I104: =(([3]Consolidated!I104)*1000)*(1/0.79941) | J104: =(([3]Consolidated!J104)*1000)*(1/0.79941) | L104: =(([3]Consolidated!L104)*1000)*(1/0.79941) | M104: =(([3]Consolidated!M104)*1000)*(1/0.79941) | N104: =(([3]Consolidated!N104)*1000)*(1/0.79941)
C105: Depreciation hardware | D105: =(([3]Consolidated!D105)*1000)*(1/0.79941) | E105: =(([3]Consolidated!E105)*1000)*(1/0.79941) | F105: =(([3]Consolidated!F105)*1000)*(1/0.79941) | G105: =(([3]Consolidated!G105)*1000)*(1/0.79941) | H105: =(([3]Consolidated!H105)*1000)*(1/0.79941) | I105: =(([3]Consolidated!I105)*1000)*(1/0.79941) | J105: =(([3]Consolidated!J105)*1000)*(1/0.79941) | L105: =(([3]Consolidated!L105)*1000)*(1/0.79941) | M105: =(([3]Consolidated!M105)*1000)*(1/0.79941) | N105: =(([3]Consolidated!N105)*1000)*(1/0.79941)
... C121: Operating expenses | D121: =(([3]Consolidated!D121)*1000)*(1/0.79941) | E121: =(([3]Consolidated!E121)*1000)*(1/0.79941) | F121: =(([3]Consolidated!F121)*1000)*(1/0.79941) | G121: =(([3]Consolidated!G121)*1000)*(1/0.79941) | H121: =(([3]Consolidated!H121)*1000)*(1/0.79941) | I121: =(([3]Consolidated!I121)*1000)*(1/0.79941) | J121: =(([3]Consolidated!J121)*1000)*(1/0.79941) | L121: =(([3]Consolidated!L121)*1000)*(1/0.79941) | M121: =(([3]Consolidated!M121)*1000)*(1/0.79941) | N121: =(([3]Consolidated!N121)*1000)*(1/0.79941)
D122: =0*(1/0.79941) | E122: =0*(1/0.79941) | F122: =0*(1/0.79941) | G122: =0*(1/0.79941) | H122: =0*(1/0.79941) | I122: =0*(1/0.79941) | J122: =0*(1/0.79941) | L122: =0*(1/0.79941) | M122: =0*(1/0.79941) | N122: =0*(1/0.79941)
C123: HR & Comms | D123: =(([3]Consolidated!D123)*1000)*(1/0.79941) | E123: =(([3]Consolidated!E123)*1000)*(1/0.79941) | F123: =(([3]Consolidated!F123)*1000)*(1/0.79941) | G123: =(([3]Consolidated!G123)*1000)*(1/0.79941) | H123: =(([3]Consolidated!H123)*1000)*(1/0.79941) | I123: =(([3]Consolidated!I123)*1000)*(1/0.79941) | J123: =(([3]Consolidated!J123)*1000)*(1/0.79941) | L123: =(([3]Consolidated!L123)*1000)*(1/0.79941) | M123: =(([3]Consolidated!M123)*1000)*(1/0.79941) | N123: =(([3]Consolidated!N123)*1000)*(1/0.79941)
C124: Finance & Business Support | D124: =(([3]Consolidated!D124)*1000)*(1/0.79941) | E124: =(([3]Consolidated!E124)*1000)*(1/0.79941) | F124: =(([3]Consolidated!F124)*1000)*(1/0.79941) | G124: =(([3]Consolidated!G124)*1000)*(1/0.79941) | H124: =(([3]Consolidated!H124)*1000)*(1/0.79941) | I124: =(([3]Consolidated!I124)*1000)*(1/0.79941) | J124: =(([3]Consolidated!J124)*1000)*(1/0.79941) | L124: =(([3]Consolidated!L124)*1000)*(1/0.79941) | M124: =(([3]Consolidated!M124)*1000)*(1/0.79941) | N124: =(([3]Consolidated!N124)*1000)*(1/0.79941)
C125: IT alloc | D125: =(([3]Consolidated!D125)*1000)*(1/0.79941) | E125: =(([3]Consolidated!E125)*1000)*(1/0.79941) | F125: =(([3]Consolidated!F125)*1000)*(1/0.79941) | G125: =(([3]Consolidated!G125)*1000)*(1/0.79941) | H125: =(([3]Consolidated!H125)*1000)*(1/0.79941) | I125: =(([3]Consolidated!I125)*1000)*(1/0.79941) | J125: =(([3]Consolidated!J125)*1000)*(1/0.79941) | L125: =(([3]Consolidated!L125)*1000)*(1/0.79941) | M125: =(([3]Consolidated!M125)*1000)*(1/0.79941) | N125: =(([3]Consolidated!N125)*1000)*(1/0.79941)
C126: Facilities Management | D126: =(([3]Consolidated!D126)*1000)*(1/0.79941) | E126: =(([3]Consolidated!E126)*1000)*(1/0.79941) | F126: =(([3]Consolidated!F126)*1000)*(1/0.79941) | G126: =(([3]Consolidated!G126)*1000)*(1/0.79941) | H126: =(([3]Consolidated!H126)*1000)*(1/0.79941) | I126: =(([3]Consolidated!I126)*1000)*(1/0.79941) | J126: =(([3]Consolidated!J126)*1000)*(1/0.79941) | L126: =(([3]Consolidated!L126)*1000)*(1/0.79941) | M126: =(([3]Consolidated!M126)*1000)*(1/0.79941) | N126: =(([3]Consolidated!N126)*1000)*(1/0.79941)
C127: Overheads | D127: =(([3]Consolidated!D127)*1000)*(1/0.79941) | E127: =(([3]Consolidated!E127)*1000)*(1/0.79941) | F127: =(([3]Consolidated!F127)*1000)*(1/0.79941) | G127: =(([3]Consolidated!G127)*1000)*(1/0.79941) | H127: =(([3]Consolidated!H127)*1000)*(1/0.79941) | I127: =(([3]Consolidated!I127)*1000)*(1/0.79941) | J127: =(([3]Consolidated!J127)*1000)*(1/0.79941) | L127: =(([3]Consolidated!L127)*1000)*(1/0.79941) | M127: =(([3]Consolidated!M127)*1000)*(1/0.79941) | N127: =(([3]Consolidated!N127)*1000)*(1/0.79941)
D128: =0*(1/0.79941) | E128: =0*(1/0.79941) | F128: =0*(1/0.79941) | G128: =0*(1/0.79941) | H128: =0*(1/0.79941) | I128: =0*(1/0.79941) | J128: =0*(1/0.79941) | L128: =0*(1/0.79941) | M128: =0*(1/0.79941) | N128: =0*(1/0.79941)
C129: Total Operating Costs (incl. O/H) | D129: =(([3]Consolidated!D129)*1000)*(1/0.79941) | E129: =(([3]Consolidated!E129)*1000)*(1/0.79941) | F129: =(([3]Consolidated!F129)*1000)*(1/0.79941) | G129: =(([3]Consolidated!G129)*1000)*(1/0.79941) | H129: =(([3]Consolidated!H129)*1000)*(1/0.79941) | I129: =(([3]Consolidated!I129)*1000)*(1/0.79941) | J129: =(([3]Consolidated!J129)*1000)*(1/0.79941) | L129: =(([3]Consolidated!L129)*1000)*(1/0.79941) | M129: =(([3]Consolidated!M129)*1000)*(1/0.79941) | N129: =(([3]Consolidated!N129)*1000)*(1/0.79941)
C132: RETAINED COSTS (US$ excl. VAT) | D132: =[3]Consolidated!D132 | E132: =[3]Consolidated!E132 | F132: =[3]Consolidated!F132 | G132: =[3]Consolidated!G132 | H132: =[3]Consolidated!H132 | I132: =[3]Consolidated!I132 | J132: =[3]Consolidated!J132 | L132: =[3]Consolidated!L132 | M132: =[3]Consolidated!M132 | N132: =[3]Consolidated!N132
C133: Internal FTE | D133: =[3]Consolidated!D133 | E133: =[3]Consolidated!E133 | F133: =[3]Consolidated!F133 | G133: =[3]Consolidated!G133 | H133: =[3]Consolidated!H133 | I133: =[3]Consolidated!I133 | L133: =[3]Consolidated!L133 | M133: =[3]Consolidated!M133 | N133: =[3]Consolidated!N133
C134: External FTE | D134: =[3]Consolidated!D134 | E134: =[3]Consolidated!E134 | F134: =[3]Consolidated!F134 | G134: =[3]Consolidated!G134 | H134: =[3]Consolidated!H134 | I134: =[3]Consolidated!I134 | L134: =[3]Consolidated!L134 | M134: =[3]Consolidated!M134 | N134: =[3]Consolidated!N134
C135: Total FTE | D135: =[3]Consolidated!D135 | E135: =[3]Consolidated!E135 | F135: =[3]Consolidated!F135 | G135: =[3]Consolidated!G135 | H135: =[3]Consolidated!H135 | I135: =[3]Consolidated!I135 | L135: =[3]Consolidated!L135 | M135: =[3]Consolidated!M135 | N135: =[3]Consolidated!N135
C137: Salaries | D137: =(([3]Consolidated!D137)*1000)*(1/0.79941) | E137: =(([3]Consolidated!E137)*1000)*(1/0.79941) | F137: =(([3]Consolidated!F137)*1000)*(1/0.79941) | G137: =(([3]Consolidated!G137)*1000)*(1/0.79941) | H137: =(([3]Consolidated!H137)*1000)*(1/0.79941) | I137: =(([3]Consolidated!I137)*1000)*(1/0.79941) | J137: =(([3]Consolidated!J137)*1000)*(1/0.79941) | L137: =(([3]Consolidated!L137)*1000)*(1/0.79941) | M137: =(([3]Consolidated!M137)*1000)*(1/0.79941) | N137: =(([3]Consolidated!N137)*1000)*(1/0.79941)
C138: Bonuses | D138: =(([3]Consolidated!D138)*1000)*(1/0.79941) | E138: =(([3]Consolidated!E138)*1000)*(1/0.79941) | F138: =(([3]Consolidated!F138)*1000)*(1/0.79941) | G138: =(([3]Consolidated!G138)*1000)*(1/0.79941) | H138: =(([3]Consolidated!H138)*1000)*(1/0.79941) | I138: =(([3]Consolidated!I138)*1000)*(1/0.79941) | J138: =(([3]Consolidated!J138)*1000)*(1/0.79941) | L138: =(([3]Consolidated!L138)*1000)*(1/0.79941) | M138: =(([3]Consolidated!M138)*1000)*(1/0.79941) | N138: =(([3]Consolidated!N138)*1000)*(1/0.79941)
C139: Third party staff, ex IT | D139: =(([3]Consolidated!D139)*1000)*(1/0.79941) | E139: =(([3]Consolidated!E139)*1000)*(1/0.79941) | F139: =(([3]Consolidated!F139)*1000)*(1/0.79941) | G139: =(([3]Consolidated!G139)*1000)*(1/0.79941) | H139: =(([3]Consolidated!H139)*1000)*(1/0.79941) | I139: =(([3]Consolidated!I139)*1000)*(1/0.79941) | J139: =(([3]Consolidated!J139)*1000)*(1/0.79941) | L139: =(([3]Consolidated!L139)*1000)*(1/0.79941) | M139: =(([3]Consolidated!M139)*1000)*(1/0.79941) | N139: =(([3]Consolidated!N139)*1000)*(1/0.79941)
C140: Third party IT staff | D140: =(([3]Consolidated!D140)*1000)*(1/0.79941) | E140: =(([3]Consolidated!E140)*1000)*(1/0.79941) | F140: =(([3]Consolidated!F140)*1000)*(1/0.79941) | G140: =(([3]Consolidated!G140)*1000)*(1/0.79941) | H140: =(([3]Consolidated!H140)*1000)*(1/0.79941) | I140: =(([3]Consolidated!I140)*1000)*(1/0.79941) | J140: =(([3]Consolidated!J140)*1000)*(1/0.79941) | L140: =(([3]Consolidated!L140)*1000)*(1/0.79941) | M140: =(([3]Consolidated!M140)*1000)*(1/0.79941) | N140: =(([3]Consolidated!N140)*1000)*(1/0.79941)
C141: Employee education | D141: =(([3]Consolidated!D141)*1000)*(1/0.79941) | E141: =(([3]Consolidated!E141)*1000)*(1/0.79941) | F141: =(([3]Consolidated!F141)*1000)*(1/0.79941) | G141: =(([3]Consolidated!G141)*1000)*(1/0.79941) | H141: =(([3]Consolidated!H141)*1000)*(1/0.79941) | I141: =(([3]Consolidated!I141)*1000)*(1/0.79941) | J141: =(([3]Consolidated!J141)*1000)*(1/0.79941) | L141: =(([3]Consolidated!L141)*1000)*(1/0.79941) | M141: =(([3]Consolidated!M141)*1000)*(1/0.79941) | N141: =(([3]Consolidated!N141)*1000)*(1/0.79941)
C142: Other staff expenses | D142: =(([3]Consolidated!D142)*1000)*(1/0.79941) | E142: =(([3]Consolidated!E142)*1000)*(1/0.79941) | F142: =(([3]Consolidated!F142)*1000)*(1/0.79941) | G142: =(([3]Consolidated!G142)*1000)*(1/0.79941) | H142: =(([3]Consolidated!H142)*1000)*(1/0.79941) | I142: =(([3]Consolidated!I142)*1000)*(1/0.79941) | J142: =(([3]Consolidated!J142)*1000)*(1/0.79941) | L142: =(([3]Consolidated!L142)*1000)*(1/0.79941) | M142: =(([3]Consolidated!M142)*1000)*(1/0.79941) | N142: =(([3]Consolidated!N142)*1000)*(1/0.79941)
C143: Staff expenses | D143: =(([3]Consolidated!D143)*1000)*(1/0.79941) | E143: =(([3]Consolidated!E143)*1000)*(1/0.79941) | F143: =(([3]Consolidated!F143)*1000)*(1/0.79941) | G143: =(([3]Consolidated!G143)*1000)*(1/0.79941) | H143: =(([3]Consolidated!H143)*1000)*(1/0.79941) | I143: =(([3]Consolidated!I143)*1000)*(1/0.79941) | J143: =(([3]Consolidated!J143)*1000)*(1/0.79941) | L143: =(([3]Consolidated!L143)*1000)*(1/0.79941) | M143: =(([3]Consolidated!M143)*1000)*(1/0.79941) | N143: =(([3]Consolidated!N143)*1000)*(1/0.79941)
C144: Hardware expenses | D144: =(([3]Consolidated!D144)*1000)*(1/0.79941) | E144: =(([3]Consolidated!E144)*1000)*(1/0.79941) | F144: =(([3]Consolidated!F144)*1000)*(1/0.79941) | G144: =(([3]Consolidated!G144)*1000)*(1/0.79941) | H144: =(([3]Consolidated!H144)*1000)*(1/0.79941) | I144: =(([3]Consolidated!I144)*1000)*(1/0.79941) | J144: =(([3]Consolidated!J144)*1000)*(1/0.79941) | L144: =(([3]Consolidated!L144)*1000)*(1/0.79941) | M144: =(([3]Consolidated!M144)*1000)*(1/0.79941) | N144: =(([3]Consolidated!N144)*1000)*(1/0.79941)
C145: Leasing/renting hardware | D145: =(([3]Consolidated!D145)*1000)*(1/0.79941) | E145: =(([3]Consolidated!E145)*1000)*(1/0.79941) | F145: =(([3]Consolidated!F145)*1000)*(1/0.79941) | G145: =(([3]Consolidated!G145)*1000)*(1/0.79941) | H145: =(([3]Consolidated!H145)*1000)*(1/0.79941) | I145: =(([3]Consolidated!I145)*1000)*(1/0.79941) | J145: =(([3]Consolidated!J145)*1000)*(1/0.79941) | L145: =(([3]Consolidated!L145)*1000)*(1/0.79941) | M145: =(([3]Consolidated!M145)*1000)*(1/0.79941) | N145: =(([3]Consolidated!N145)*1000)*(1/0.79941)
C146: Software expenses | D146: =(([3]Consolidated!D146)*1000)*(1/0.79941) | E146: =(([3]Consolidated!E146)*1000)*(1/0.79941) | F146: =(([3]Consolidated!F146)*1000)*(1/0.79941) | G146: =(([3]Consolidated!G146)*1000)*(1/0.79941) | H146: =(([3]Consolidated!H146)*1000)*(1/0.79941) | I146: =(([3]Consolidated!I146)*1000)*(1/0.79941) | J146: =(([3]Consolidated!J146)*1000)*(1/0.79941) | L146: =(([3]Consolidated!L146)*1000)*(1/0.79941) | M146: =(([3]Consolidated!M146)*1000)*(1/0.79941) | N146: =(([3]Consolidated!N146)*1000)*(1/0.79941)
C147: Leasing/renting/licenses sw | D147: =(([3]Consolidated!D147)*1000)*(1/0.79941) | E147: =(([3]Consolidated!E147)*1000)*(1/0.79941) | F147: =(([3]Consolidated!F147)*1000)*(1/0.79941) | G147: =(([3]Consolidated!G147)*1000)*(1/0.79941) | H147: =(([3]Consolidated!H147)*1000)*(1/0.79941) | I147: =(([3]Consolidated!I147)*1000)*(1/0.79941) | J147: =(([3]Consolidated!J147)*1000)*(1/0.79941) | L147: =(([3]Consolidated!L147)*1000)*(1/0.79941) | M147: =(([3]Consolidated!M147)*1000)*(1/0.79941) | N147: =(([3]Consolidated!N147)*1000)*(1/0.79941)
C148: Depreciation hardware | D148: =(([3]Consolidated!D148)*1000)*(1/0.79941) | E148: =(([3]Consolidated!E148)*1000)*(1/0.79941) | F148: =(([3]Consolidated!F148)*1000)*(1/0.79941) | G148: =(([3]Consolidated!G148)*1000)*(1/0.79941) | H148: =(([3]Consolidated!H148)*1000)*(1/0.79941) | I148: =(([3]Consolidated!I148)*1000)*(1/0.79941) | J148: =(([3]Consolidated!J148)*1000)*(1/0.79941) | L148: =(([3]Consolidated!L148)*1000)*(1/0.79941) | M148: =(([3]Consolidated!M148)*1000)*(1/0.79941) | N148: =(([3]Consolidated!N148)*1000)*(1/0.79941)
... C164: Operating expenses | D164: =(([3]Consolidated!D164)*1000)*(1/0.79941) | E164: =(([3]Consolidated!E164)*1000)*(1/0.79941) | F164: =(([3]Consolidated!F164)*1000)*(1/0.79941) | G164: =(([3]Consolidated!G164)*1000)*(1/0.79941) | H164: =(([3]Consolidated!H164)*1000)*(1/0.79941) | I164: =(([3]Consolidated!I164)*1000)*(1/0.79941) | J164: =(([3]Consolidated!J164)*1000)*(1/0.79941) | L164: =(([3]Consolidated!L164)*1000)*(1/0.79941) | M164: =(([3]Consolidated!M164)*1000)*(1/0.79941) | N164: =(([3]Consolidated!N164)*1000)*(1/0.79941)
D165: =0*(1/0.79941) | E165: =0*(1/0.79941) | F165: =0*(1/0.79941) | G165: =0*(1/0.79941) | H165: =0*(1/0.79941) | I165: =0*(1/0.79941) | J165: =0*(1/0.79941) | L165: =0*(1/0.79941) | M165: =0*(1/0.79941) | N165: =0*(1/0.79941)
C166: HR & Comms | D166: =(([3]Consolidated!D166)*1000)*(1/0.79941) | E166: =(([3]Consolidated!E166)*1000)*(1/0.79941) | F166: =(([3]Consolidated!F166)*1000)*(1/0.79941) | G166: =(([3]Consolidated!G166)*1000)*(1/0.79941) | H166: =(([3]Consolidated!H166)*1000)*(1/0.79941) | I166: =(([3]Consolidated!I166)*1000)*(1/0.79941) | J166: =(([3]Consolidated!J166)*1000)*(1/0.79941) | L166: =(([3]Consolidated!L166)*1000)*(1/0.79941) | M166: =(([3]Consolidated!M166)*1000)*(1/0.79941) | N166: =(([3]Consolidated!N166)*1000)*(1/0.79941)
C167: Finance & Business Support | D167: =(([3]Consolidated!D167)*1000)*(1/0.79941) | E167: =(([3]Consolidated!E167)*1000)*(1/0.79941) | F167: =(([3]Consolidated!F167)*1000)*(1/0.79941) | G167: =(([3]Consolidated!G167)*1000)*(1/0.79941) | H167: =(([3]Consolidated!H167)*1000)*(1/0.79941) | I167: =(([3]Consolidated!I167)*1000)*(1/0.79941) | J167: =(([3]Consolidated!J167)*1000)*(1/0.79941) | L167: =(([3]Consolidated!L167)*1000)*(1/0.79941) | M167: =(([3]Consolidated!M167)*1000)*(1/0.79941) | N167: =(([3]Consolidated!N167)*1000)*(1/0.79941)
C168: IT alloc | D168: =(([3]Consolidated!D168)*1000)*(1/0.79941) | E168: =(([3]Consolidated!E168)*1000)*(1/0.79941) | F168: =(([3]Consolidated!F168)*1000)*(1/0.79941) | G168: =(([3]Consolidated!G168)*1000)*(1/0.79941) | H168: =(([3]Consolidated!H168)*1000)*(1/0.79941) | I168: =(([3]Consolidated!I168)*1000)*(1/0.79941) | J168: =(([3]Consolidated!J168)*1000)*(1/0.79941) | L168: =(([3]Consolidated!L168)*1000)*(1/0.79941) | M168: =(([3]Consolidated!M168)*1000)*(1/0.79941) | N168: =(([3]Consolidated!N168)*1000)*(1/0.79941)
C169: Facilities Management | D169: =(([3]Consolidated!D169)*1000)*(1/0.79941) | E169: =(([3]Consolidated!E169)*1000)*(1/0.79941) | F169: =(([3]Consolidated!F169)*1000)*(1/0.79941) | G169: =(([3]Consolidated!G169)*1000)*(1/0.79941) | H169: =(([3]Consolidated!H169)*1000)*(1/0.79941) | I169: =(([3]Consolidated!I169)*1000)*(1/0.79941) | J169: =(([3]Consolidated!J169)*1000)*(1/0.79941) | L169: =(([3]Consolidated!L169)*1000)*(1/0.79941) | M169: =(([3]Consolidated!M169)*1000)*(1/0.79941) | N169: =(([3]Consolidated!N169)*1000)*(1/0.79941)
...

Sheet Spain
C1: Spain (ES)
C2: TOTAL COSTS (US$ excl. VAT) | D2: =[4]Consolidated!D2 | E2: =[4]Consolidated!E2 | F2: =[4]Consolidated!F2 | G2: =[4]Consolidated!G2 | H2: =[4]Consolidated!H2 | I2: =[4]Consolidated!I2 | J2: =[4]Consolidated!J2 | L2: =[4]Consolidated!L2 | M2: =[4]Consolidated!M2 | N2: =[4]Consolidated!N2
C3: Internal FTE | D3: =[4]Consolidated!D3 | E3: =[4]Consolidated!E3 | F3: =[4]Consolidated!F3 | G3: =[4]Consolidated!G3 | H3: =[4]Consolidated!H3 | I3: =[4]Consolidated!I3 | L3: =[4]Consolidated!L3 | M3: =[4]Consolidated!M3 | N3: =[4]Consolidated!N3
C4: External FTE | D4: =[4]Consolidated!D4 | E4: =[4]Consolidated!E4 | F4: =[4]Consolidated!F4 | G4: =[4]Consolidated!G4 | H4: =[4]Consolidated!H4 | I4: =[4]Consolidated!I4 | L4: =[4]Consolidated!L4 | M4: =[4]Consolidated!M4 | N4: =[4]Consolidated!N4
C5: Total FTE | D5: =[4]Consolidated!D5 | E5: =[4]Consolidated!E5 | F5: =[4]Consolidated!F5 | G5: =[4]Consolidated!G5 | H5: =[4]Consolidated!H5 | I5: =[4]Consolidated!I5 | L5: =[4]Consolidated!L5 | M5: =[4]Consolidated!M5 | N5: =[4]Consolidated!N5
C7: Salaries | D7: =([4]Consolidated!D7)*(1/0.79941) | E7: =([4]Consolidated!E7)*(1/0.79941) | F7: =([4]Consolidated!F7)*(1/0.79941) | G7: =([4]Consolidated!G7)*(1/0.79941) | H7: =([4]Consolidated!H7)*(1/0.79941) | I7: =([4]Consolidated!I7)*(1/0.79941) | J7: =([4]Consolidated!J7)*(1/0.79941) | L7: =([4]Consolidated!L7)*(1/0.79941) | M7: =([4]Consolidated!M7)*(1/0.79941) | N7: =([4]Consolidated!N7)*(1/0.79941) | P7: 1000
C8: Bonuses | D8: =([4]Consolidated!D8)*(1/0.79941) | E8: =([4]Consolidated!E8)*(1/0.79941) | F8: =([4]Consolidated!F8)*(1/0.79941) | G8: =([4]Consolidated!G8)*(1/0.79941) | H8: =([4]Consolidated!H8)*(1/0.79941) | I8: =([4]Consolidated!I8)*(1/0.79941) | J8: =([4]Consolidated!J8)*(1/0.79941) | L8: =([4]Consolidated!L8)*(1/0.79941) | M8: =([4]Consolidated!M8)*(1/0.79941) | N8: =([4]Consolidated!N8)*(1/0.79941) | P8: =1/0.79941 | Q8: Euro to Dollar Rate
C9: Third party staff, ex IT | D9: =([4]Consolidated!D9)*(1/0.79941) | E9: =([4]Consolidated!E9)*(1/0.79941) | F9: =([4]Consolidated!F9)*(1/0.79941) | G9: =([4]Consolidated!G9)*(1/0.79941) | H9: =([4]Consolidated!H9)*(1/0.79941) | I9: =([4]Consolidated!I9)*(1/0.79941) | J9: =([4]Consolidated!J9)*(1/0.79941) | L9: =([4]Consolidated!L9)*(1/0.79941) | M9: =([4]Consolidated!M9)*(1/0.79941) | N9: =([4]Consolidated!N9)*(1/0.79941)
C10: Third party IT staff | D10: =([4]Consolidated!D10)*(1/0.79941) | E10: =([4]Consolidated!E10)*(1/0.79941) | F10: =([4]Consolidated!F10)*(1/0.79941) | G10: =([4]Consolidated!G10)*(1/0.79941) | H10: =([4]Consolidated!H10)*(1/0.79941) | I10: =([4]Consolidated!I10)*(1/0.79941) | J10: =([4]Consolidated!J10)*(1/0.79941) | L10: =([4]Consolidated!L10)*(1/0.79941) | M10: =([4]Consolidated!M10)*(1/0.79941) | N10: =([4]Consolidated!N10)*(1/0.79941)
C11: Employee education | D11: =([4]Consolidated!D11)*(1/0.79941) | E11: =([4]Consolidated!E11)*(1/0.79941) | F11: =([4]Consolidated!F11)*(1/0.79941) | G11: =([4]Consolidated!G11)*(1/0.79941) | H11: =([4]Consolidated!H11)*(1/0.79941) | I11: =([4]Consolidated!I11)*(1/0.79941) | J11: =([4]Consolidated!J11)*(1/0.79941) | L11: =([4]Consolidated!L11)*(1/0.79941) | M11: =([4]Consolidated!M11)*(1/0.79941) | N11: =([4]Consolidated!N11)*(1/0.79941)
C12: Other staff expenses | D12: =([4]Consolidated!D12)*(1/0.79941) | E12: =([4]Consolidated!E12)*(1/0.79941) | F12: =([4]Consolidated!F12)*(1/0.79941) | G12: =([4]Consolidated!G12)*(1/0.79941) | H12: =([4]Consolidated!H12)*(1/0.79941) | I12: =([4]Consolidated!I12)*(1/0.79941) | J12: =([4]Consolidated!J12)*(1/0.79941) | L12: =([4]Consolidated!L12)*(1/0.79941) | M12: =([4]Consolidated!M12)*(1/0.79941) | N12: =([4]Consolidated!N12)*(1/0.79941)
C13: Staff expenses | D13: =([4]Consolidated!D13)*(1/0.79941) | E13: =([4]Consolidated!E13)*(1/0.79941) | F13: =([4]Consolidated!F13)*(1/0.79941) | G13: =([4]Consolidated!G13)*(1/0.79941) | H13: =([4]Consolidated!H13)*(1/0.79941) | I13: =([4]Consolidated!I13)*(1/0.79941) | J13: =([4]Consolidated!J13)*(1/0.79941) | L13: =([4]Consolidated!L13)*(1/0.79941) | M13: =([4]Consolidated!M13)*(1/0.79941) | N13: =([4]Consolidated!N13)*(1/0.79941)
C14: Hardware expenses | D14: =([4]Consolidated!D14)*(1/0.79941) | E14: =([4]Consolidated!E14)*(1/0.79941) | F14: =([4]Consolidated!F14)*(1/0.79941) | G14: =([4]Consolidated!G14)*(1/0.79941) | H14: =([4]Consolidated!H14)*(1/0.79941) | I14: =([4]Consolidated!I14)*(1/0.79941) | J14: =([4]Consolidated!J14)*(1/0.79941) | L14: =([4]Consolidated!L14)*(1/0.79941) | M14: =([4]Consolidated!M14)*(1/0.79941) | N14: =([4]Consolidated!N14)*(1/0.79941)
C15: Leasing/renting hardware | D15: =([4]Consolidated!D15)*(1/0.79941) | E15: =([4]Consolidated!E15)*(1/0.79941) | F15: =([4]Consolidated!F15)*(1/0.79941) | G15: =([4]Consolidated!G15)*(1/0.79941) | H15: =([4]Consolidated!H15)*(1/0.79941) | I15: =([4]Consolidated!I15)*(1/0.79941) | J15: =([4]Consolidated!J15)*(1/0.79941) | L15: =([4]Consolidated!L15)*(1/0.79941) | M15: =([4]Consolidated!M15)*(1/0.79941) | N15: =([4]Consolidated!N15)*(1/0.79941)
C16: Software expenses | D16: =([4]Consolidated!D16)*(1/0.79941) | E16: =([4]Consolidated!E16)*(1/0.79941) | F16: =([4]Consolidated!F16)*(1/0.79941) | G16: =([4]Consolidated!G16)*(1/0.79941) | H16: =([4]Consolidated!H16)*(1/0.79941) | I16: =([4]Consolidated!I16)*(1/0.79941) | J16: =([4]Consolidated!J16)*(1/0.79941) | L16: =([4]Consolidated!L16)*(1/0.79941) | M16: =([4]Consolidated!M16)*(1/0.79941) | N16: =([4]Consolidated!N16)*(1/0.79941)
C17: Leasing/renting/licenses sw | D17: =([4]Consolidated!D17)*(1/0.79941) | E17: =([4]Consolidated!E17)*(1/0.79941) | F17: =([4]Consolidated!F17)*(1/0.79941) | G17: =([4]Consolidated!G17)*(1/0.79941) | H17: =([4]Consolidated!H17)*(1/0.79941) | I17: =([4]Consolidated!I17)*(1/0.79941) | J17: =([4]Consolidated!J17)*(1/0.79941) | L17: =([4]Consolidated!L17)*(1/0.79941) | M17: =([4]Consolidated!M17)*(1/0.79941) | N17: =([4]Consolidated!N17)*(1/0.79941)
C18: Depreciation hardware | D18: =([4]Consolidated!D18)*(1/0.79941) | E18: =([4]Consolidated!E18)*(1/0.79941) | F18: =([4]Consolidated!F18)*(1/0.79941) | G18: =([4]Consolidated!G18)*(1/0.79941) | H18: =([4]Consolidated!H18)*(1/0.79941) | I18: =([4]Consolidated!I18)*(1/0.79941) | J18: =([4]Consolidated!J18)*(1/0.79941) | L18: =([4]Consolidated!L18)*(1/0.79941) | M18: =([4]Consolidated!M18)*(1/0.79941) | N18: =([4]Consolidated!N18)*(1/0.79941)
C19: Depreciation software | D19: =([4]Consolidated!D19)*(1/0.79941) | E19: =([4]Consolidated!E19)*(1/0.79941) | F19: =([4]Consolidated!F19)*(1/0.79941) | G19: =([4]Consolidated!G19)*(1/0.79941) | H19: =([4]Consolidated!H19)*(1/0.79941) | I19: =([4]Consolidated!I19)*(1/0.79941) | J19: =([4]Consolidated!J19)*(1/0.79941) | L19: =([4]Consolidated!L19)*(1/0.79941) | M19: =([4]Consolidated!M19)*(1/0.79941) | N19: =([4]Consolidated!N19)*(1/0.79941)
C20: Outsourcing IT activities | D20: =([4]Consolidated!D20)*(1/0.79941) | E20: =([4]Consolidated!E20)*(1/0.79941) | F20: =([4]Consolidated!F20)*(1/0.79941) | G20: =([4]Consolidated!G20)*(1/0.79941) | H20: =([4]Consolidated!H20)*(1/0.79941) | I20: =([4]Consolidated!I20)*(1/0.79941) | J20: =([4]Consolidated!J20)*(1/0.79941) | L20: =([4]Consolidated!L20)*(1/0.79941) | M20: =([4]Consolidated!M20)*(1/0.79941) | N20: =([4]Consolidated!N20)*(1/0.79941)
... C34: Operating expenses | D34: =([4]Consolidated!D34)*(1/0.79941) | E34: =([4]Consolidated!E34)*(1/0.79941) | F34: =([4]Consolidated!F34)*(1/0.79941) | G34: =([4]Consolidated!G34)*(1/0.79941) | H34: =([4]Consolidated!H34)*(1/0.79941) | I34: =([4]Consolidated!I34)*(1/0.79941) | J34: =([4]Consolidated!J34)*(1/0.79941) | L34: =([4]Consolidated!L34)*(1/0.79941) | M34: =([4]Consolidated!M34)*(1/0.79941) | N34: =([4]Consolidated!N34)*(1/0.79941)
D35: =0*(1/0.79941) | E35: =0*(1/0.79941) | F35: =0*(1/0.79941) | G35: =0*(1/0.79941) | H35: =0*(1/0.79941) | I35: =0*(1/0.79941) | J35: =0*(1/0.79941) | L35: =0*(1/0.79941) | M35: =0*(1/0.79941) | N35: =0*(1/0.79941)
C36: HR & Comms | D36: =([4]Consolidated!D36)*(1/0.79941) | E36: =([4]Consolidated!E36)*(1/0.79941) | F36: =([4]Consolidated!F36)*(1/0.79941) | G36: =([4]Consolidated!G36)*(1/0.79941) | H36: =([4]Consolidated!H36)*(1/0.79941) | I36: =([4]Consolidated!I36)*(1/0.79941) | J36: =([4]Consolidated!J36)*(1/0.79941) | L36: =([4]Consolidated!L36)*(1/0.79941) | M36: =([4]Consolidated!M36)*(1/0.79941) | N36: =([4]Consolidated!N36)*(1/0.79941)
C37: Finance & Business Support | D37: =([4]Consolidated!D37)*(1/0.79941) | E37: =([4]Consolidated!E37)*(1/0.79941) | F37: =([4]Consolidated!F37)*(1/0.79941) | G37: =([4]Consolidated!G37)*(1/0.79941) | H37: =([4]Consolidated!H37)*(1/0.79941) | I37: =([4]Consolidated!I37)*(1/0.79941) | J37: =([4]Consolidated!J37)*(1/0.79941) | L37: =([4]Consolidated!L37)*(1/0.79941) | M37: =([4]Consolidated!M37)*(1/0.79941) | N37: =([4]Consolidated!N37)*(1/0.79941)
C38: IT alloc | D38: =([4]Consolidated!D38)*(1/0.79941) | E38: =([4]Consolidated!E38)*(1/0.79941) | F38: =([4]Consolidated!F38)*(1/0.79941) | G38: =([4]Consolidated!G38)*(1/0.79941) | H38: =([4]Consolidated!H38)*(1/0.79941) | I38: =([4]Consolidated!I38)*(1/0.79941) | J38: =([4]Consolidated!J38)*(1/0.79941) | L38: =([4]Consolidated!L38)*(1/0.79941) | M38: =([4]Consolidated!M38)*(1/0.79941) | N38: =([4]Consolidated!N38)*(1/0.79941)
C39: Facilities Management | D39: =([4]Consolidated!D39)*(1/0.79941) | E39: =([4]Consolidated!E39)*(1/0.79941) | F39: =([4]Consolidated!F39)*(1/0.79941) | G39: =([4]Consolidated!G39)*(1/0.79941) | H39: =([4]Consolidated!H39)*(1/0.79941) | I39: =([4]Consolidated!I39)*(1/0.79941) | J39: =([4]Consolidated!J39)*(1/0.79941) | L39: =([4]Consolidated!L39)*(1/0.79941) | M39: =([4]Consolidated!M39)*(1/0.79941) | N39: =([4]Consolidated!N39)*(1/0.79941)
C40: Overheads | D40: =([4]Consolidated!D40)*(1/0.79941) | E40: =([4]Consolidated!E40)*(1/0.79941) | F40: =([4]Consolidated!F40)*(1/0.79941) | G40: =([4]Consolidated!G40)*(1/0.79941) | H40: =([4]Consolidated!H40)*(1/0.79941) | I40: =([4]Consolidated!I40)*(1/0.79941) | J40: =([4]Consolidated!J40)*(1/0.79941) | L40: =([4]Consolidated!L40)*(1/0.79941) | M40: =([4]Consolidated!M40)*(1/0.79941) | N40: =([4]Consolidated!N40)*(1/0.79941)
C41: 0 | D41: =0*(1/0.79941) | E41: =0*(1/0.79941) | F41: =0*(1/0.79941) | G41: =0*(1/0.79941) | H41: =0*(1/0.79941) | I41: =0*(1/0.79941) | J41: =0*(1/0.79941) | L41: =0*(1/0.79941) | M41: =0*(1/0.79941) | N41: =0*(1/0.79941)
C42: Total Operating Costs (incl. O/H) | D42: =([4]Consolidated!D42)*(1/0.79941) | E42: =([4]Consolidated!E42)*(1/0.79941) | F42: =([4]Consolidated!F42)*(1/0.79941) | G42: =([4]Consolidated!G42)*(1/0.79941) | H42: =([4]Consolidated!H42)*(1/0.79941) | I42: =([4]Consolidated!I42)*(1/0.79941) | J42: =([4]Consolidated!J42)*(1/0.79941) | L42: =([4]Consolidated!L42)*(1/0.79941) | M42: =([4]Consolidated!M42)*(1/0.79941) | N42: =([4]Consolidated!N42)*(1/0.79941)
C45: SUPPLIER ASSUMED COSTS (US$ excl. VAT) | D45: =[4]Consolidated!D45 | E45: =[4]Consolidated!E45 | F45: =[4]Consolidated!F45 | G45: =[4]Consolidated!G45 | H45: =[4]Consolidated!H45 | I45: =[4]Consolidated!I45 | J45: =[4]Consolidated!J45 | L45: =[4]Consolidated!L45 | M45: =[4]Consolidated!M45 | N45: =[4]Consolidated!N45
C46: Internal FTE | D46: =[4]Consolidated!D46 | E46: =[4]Consolidated!E46 | F46: =[4]Consolidated!F46 | G46: =[4]Consolidated!G46 | H46: =[4]Consolidated!H46 | I46: =[4]Consolidated!I46 | L46: =[4]Consolidated!L46 | M46: =[4]Consolidated!M46 | N46: =[4]Consolidated!N46
C47: External FTE | D47: =[4]Consolidated!D47 | E47: =[4]Consolidated!E47 | F47: =[4]Consolidated!F47 | G47: =[4]Consolidated!G47 | H47: =[4]Consolidated!H47 | I47: =[4]Consolidated!I47 | L47: =[4]Consolidated!L47 | M47: =[4]Consolidated!M47 | N47: =[4]Consolidated!N47
C48: Total FTE | D48: =[4]Consolidated!D48 | E48: =[4]Consolidated!E48 | F48: =[4]Consolidated!F48 | G48: =[4]Consolidated!G48 | H48: =[4]Consolidated!H48 | I48: =[4]Consolidated!I48 | L48: =[4]Consolidated!L48 | M48: =[4]Consolidated!M48 | N48: =[4]Consolidated!N48
C50: Salaries | D50: =([4]Consolidated!D50)*(1/0.79941) | E50: =([4]Consolidated!E50)*(1/0.79941) | F50: =([4]Consolidated!F50)*(1/0.79941) | G50: =([4]Consolidated!G50)*(1/0.79941) | H50: =([4]Consolidated!H50)*(1/0.79941) | I50: =([4]Consolidated!I50)*(1/0.79941) | J50: =([4]Consolidated!J50)*(1/0.79941) | L50: =([4]Consolidated!L50)*(1/0.79941) | M50: =([4]Consolidated!M50)*(1/0.79941) | N50: =([4]Consolidated!N50)*(1/0.79941)
C51: Bonuses | D51: =([4]Consolidated!D51)*(1/0.79941) | E51: =([4]Consolidated!E51)*(1/0.79941) | F51: =([4]Consolidated!F51)*(1/0.79941) | G51: =([4]Consolidated!G51)*(1/0.79941) | H51: =([4]Consolidated!H51)*(1/0.79941) | I51: =([4]Consolidated!I51)*(1/0.79941) | J51: =([4]Consolidated!J51)*(1/0.79941) | L51: =([4]Consolidated!L51)*(1/0.79941) | M51: =([4]Consolidated!M51)*(1/0.79941) | N51: =([4]Consolidated!N51)*(1/0.79941)
C52: Third party staff, ex IT | D52: =([4]Consolidated!D52)*(1/0.79941) | E52: =([4]Consolidated!E52)*(1/0.79941) | F52: =([4]Consolidated!F52)*(1/0.79941) | G52: =([4]Consolidated!G52)*(1/0.79941) | H52: =([4]Consolidated!H52)*(1/0.79941) | I52: =([4]Consolidated!I52)*(1/0.79941) | J52: =([4]Consolidated!J52)*(1/0.79941) | L52: =([4]Consolidated!L52)*(1/0.79941) | M52: =([4]Consolidated!M52)*(1/0.79941) | N52: =([4]Consolidated!N52)*(1/0.79941)
C53: Third party IT staff | D53: =([4]Consolidated!D53)*(1/0.79941) | E53: =([4]Consolidated!E53)*(1/0.79941) | F53: =([4]Consolidated!F53)*(1/0.79941) | G53: =([4]Consolidated!G53)*(1/0.79941) | H53: =([4]Consolidated!H53)*(1/0.79941) | I53: =([4]Consolidated!I53)*(1/0.79941) | J53: =([4]Consolidated!J53)*(1/0.79941) | L53: =([4]Consolidated!L53)*(1/0.79941) | M53: =([4]Consolidated!M53)*(1/0.79941) | N53: =([4]Consolidated!N53)*(1/0.79941)
C54: Employee education | D54: =([4]Consolidated!D54)*(1/0.79941) | E54: =([4]Consolidated!E54)*(1/0.79941) | F54: =([4]Consolidated!F54)*(1/0.79941) | G54: =([4]Consolidated!G54)*(1/0.79941) | H54: =([4]Consolidated!H54)*(1/0.79941) | I54: =([4]Consolidated!I54)*(1/0.79941) | J54: =([4]Consolidated!J54)*(1/0.79941) | L54: =([4]Consolidated!L54)*(1/0.79941) | M54: =([4]Consolidated!M54)*(1/0.79941) | N54: =([4]Consolidated!N54)*(1/0.79941)
C55: Other staff expenses | D55: =([4]Consolidated!D55)*(1/0.79941) | E55: =([4]Consolidated!E55)*(1/0.79941) | F55: =([4]Consolidated!F55)*(1/0.79941) | G55: =([4]Consolidated!G55)*(1/0.79941) | H55: =([4]Consolidated!H55)*(1/0.79941) | I55: =([4]Consolidated!I55)*(1/0.79941) | J55: =([4]Consolidated!J55)*(1/0.79941) | L55: =([4]Consolidated!L55)*(1/0.79941) | M55: =([4]Consolidated!M55)*(1/0.79941) | N55: =([4]Consolidated!N55)*(1/0.79941)
C56: Staff expenses | D56: =([4]Consolidated!D56)*(1/0.79941) | E56: =([4]Consolidated!E56)*(1/0.79941) | F56: =([4]Consolidated!F56)*(1/0.79941) | G56: =([4]Consolidated!G56)*(1/0.79941) | H56: =([4]Consolidated!H56)*(1/0.79941) | I56: =([4]Consolidated!I56)*(1/0.79941) | J56: =([4]Consolidated!J56)*(1/0.79941) | L56: =([4]Consolidated!L56)*(1/0.79941) | M56: =([4]Consolidated!M56)*(1/0.79941) | N56: =([4]Consolidated!N56)*(1/0.79941)
C57: Hardware expenses | D57: =([4]Consolidated!D57)*(1/0.79941) | E57: =([4]Consolidated!E57)*(1/0.79941) | F57: =([4]Consolidated!F57)*(1/0.79941) | G57: =([4]Consolidated!G57)*(1/0.79941) | H57: =([4]Consolidated!H57)*(1/0.79941) | I57: =([4]Consolidated!I57)*(1/0.79941) | J57: =([4]Consolidated!J57)*(1/0.79941) | L57: =([4]Consolidated!L57)*(1/0.79941) | M57: =([4]Consolidated!M57)*(1/0.79941) | N57: =([4]Consolidated!N57)*(1/0.79941)
C58: Leasing/renting hardware | D58: =([4]Consolidated!D58)*(1/0.79941) | E58: =([4]Consolidated!E58)*(1/0.79941) | F58: =([4]Consolidated!F58)*(1/0.79941) | G58: =([4]Consolidated!G58)*(1/0.79941) | H58: =([4]Consolidated!H58)*(1/0.79941) | I58: =([4]Consolidated!I58)*(1/0.79941) | J58: =([4]Consolidated!J58)*(1/0.79941) | L58: =([4]Consolidated!L58)*(1/0.79941) | M58: =([4]Consolidated!M58)*(1/0.79941) | N58: =([4]Consolidated!N58)*(1/0.79941)
C59: Software expenses | D59: =([4]Consolidated!D59)*(1/0.79941) | E59: =([4]Consolidated!E59)*(1/0.79941) | F59: =([4]Consolidated!F59)*(1/0.79941) | G59: =([4]Consolidated!G59)*(1/0.79941) | H59: =([4]Consolidated!H59)*(1/0.79941) | I59: =([4]Consolidated!I59)*(1/0.79941) | J59: =([4]Consolidated!J59)*(1/0.79941) | L59: =([4]Consolidated!L59)*(1/0.79941) | M59: =([4]Consolidated!M59)*(1/0.79941) | N59: =([4]Consolidated!N59)*(1/0.79941)
C60: Leasing/renting/licenses sw | D60: =([4]Consolidated!D60)*(1/0.79941) | E60: =([4]Consolidated!E60)*(1/0.79941) | F60: =([4]Consolidated!F60)*(1/0.79941) | G60: =([4]Consolidated!G60)*(1/0.79941) | H60: =([4]Consolidated!H60)*(1/0.79941) | I60: =([4]Consolidated!I60)*(1/0.79941) | J60: =([4]Consolidated!J60)*(1/0.79941) | L60: =([4]Consolidated!L60)*(1/0.79941) | M60: =([4]Consolidated!M60)*(1/0.79941) | N60: =([4]Consolidated!N60)*(1/0.79941)
C61: Depreciation hardware | D61: =([4]Consolidated!D61)*(1/0.79941) | E61: =([4]Consolidated!E61)*(1/0.79941) | F61: =([4]Consolidated!F61)*(1/0.79941) | G61: =([4]Consolidated!G61)*(1/0.79941) | H61: =([4]Consolidated!H61)*(1/0.79941) | I61: =([4]Consolidated!I61)*(1/0.79941) | J61: =([4]Consolidated!J61)*(1/0.79941) | L61: =([4]Consolidated!L61)*(1/0.79941) | M61: =([4]Consolidated!M61)*(1/0.79941) | N61: =([4]Consolidated!N61)*(1/0.79941)
... C77: Operating expenses | D77: =([4]Consolidated!D77)*(1/0.79941) | E77: =([4]Consolidated!E77)*(1/0.79941) | F77: =([4]Consolidated!F77)*(1/0.79941) | G77: =([4]Consolidated!G77)*(1/0.79941) | H77: =([4]Consolidated!H77)*(1/0.79941) | I77: =([4]Consolidated!I77)*(1/0.79941) | J77: =([4]Consolidated!J77)*(1/0.79941) | L77: =([4]Consolidated!L77)*(1/0.79941) | M77: =([4]Consolidated!M77)*(1/0.79941) | N77: =([4]Consolidated!N77)*(1/0.79941)
D78: =0*(1/0.79941) | E78: =0*(1/0.79941) | F78: =0*(1/0.79941) | G78: =0*(1/0.79941) | H78: =0*(1/0.79941) | I78: =0*(1/0.79941) | J78: =0*(1/0.79941) | L78: =0*(1/0.79941) | M78: =0*(1/0.79941) | N78: =0*(1/0.79941)
C79: HR & Comms | D79: =([4]Consolidated!D79)*(1/0.79941) | E79: =([4]Consolidated!E79)*(1/0.79941) | F79: =([4]Consolidated!F79)*(1/0.79941) | G79: =([4]Consolidated!G79)*(1/0.79941) | H79: =([4]Consolidated!H79)*(1/0.79941) | I79: =([4]Consolidated!I79)*(1/0.79941) | J79: =([4]Consolidated!J79)*(1/0.79941) | L79: =([4]Consolidated!L79)*(1/0.79941) | M79: =([4]Consolidated!M79)*(1/0.79941) | N79: =([4]Consolidated!N79)*(1/0.79941)
C80: Finance & Business Support | D80: =([4]Consolidated!D80)*(1/0.79941) | E80: =([4]Consolidated!E80)*(1/0.79941) | F80: =([4]Consolidated!F80)*(1/0.79941) | G80: =([4]Consolidated!G80)*(1/0.79941) | H80: =([4]Consolidated!H80)*(1/0.79941) | I80: =([4]Consolidated!I80)*(1/0.79941) | J80: =([4]Consolidated!J80)*(1/0.79941) | L80: =([4]Consolidated!L80)*(1/0.79941) | M80: =([4]Consolidated!M80)*(1/0.79941) | N80: =([4]Consolidated!N80)*(1/0.79941)
C81: IT alloc | D81: =([4]Consolidated!D81)*(1/0.79941) | E81: =([4]Consolidated!E81)*(1/0.79941) | F81: =([4]Consolidated!F81)*(1/0.79941) | G81: =([4]Consolidated!G81)*(1/0.79941) | H81: =([4]Consolidated!H81)*(1/0.79941) | I81: =([4]Consolidated!I81)*(1/0.79941) | J81: =([4]Consolidated!J81)*(1/0.79941) | L81: =([4]Consolidated!L81)*(1/0.79941) | M81: =([4]Consolidated!M81)*(1/0.79941) | N81: =([4]Consolidated!N81)*(1/0.79941)
C82: Facilities Management | D82: =([4]Consolidated!D82)*(1/0.79941) | E82: =([4]Consolidated!E82)*(1/0.79941) | F82: =([4]Consolidated!F82)*(1/0.79941) | G82: =([4]Consolidated!G82)*(1/0.79941) | H82: =([4]Consolidated!H82)*(1/0.79941) | I82: =([4]Consolidated!I82)*(1/0.79941) | J82: =([4]Consolidated!J82)*(1/0.79941) | L82: =([4]Consolidated!L82)*(1/0.79941) | M82: =([4]Consolidated!M82)*(1/0.79941) | N82: =([4]Consolidated!N82)*(1/0.79941)
C83: Overheads | D83: =([4]Consolidated!D83)*(1/0.79941) | E83: =([4]Consolidated!E83)*(1/0.79941) | F83: =([4]Consolidated!F83)*(1/0.79941) | G83: =([4]Consolidated!G83)*(1/0.79941) | H83: =([4]Consolidated!H83)*(1/0.79941) | I83: =([4]Consolidated!I83)*(1/0.79941) | J83: =([4]Consolidated!J83)*(1/0.79941) | L83: =([4]Consolidated!L83)*(1/0.79941) | M83: =([4]Consolidated!M83)*(1/0.79941) | N83: =([4]Consolidated!N83)*(1/0.79941)
D84: =0*(1/0.79941) | E84: =0*(1/0.79941) | F84: =0*(1/0.79941) | G84: =0*(1/0.79941) | H84: =0*(1/0.79941) | I84: =0*(1/0.79941) | J84: =0*(1/0.79941) | L84: =0*(1/0.79941) | M84: =0*(1/0.79941) | N84: =0*(1/0.79941)
C85: Total Operating Costs (incl. O/H) | D85: =([4]Consolidated!D85)*(1/0.79941) | E85: =([4]Consolidated!E85)*(1/0.79941) | F85: =([4]Consolidated!F85)*(1/0.79941) | G85: =([4]Consolidated!G85)*(1/0.79941) | H85: =([4]Consolidated!H85)*(1/0.79941) | I85: =([4]Consolidated!I85)*(1/0.79941) | J85: =([4]Consolidated!J85)*(1/0.79941) | L85: =([4]Consolidated!L85)*(1/0.79941) | M85: =([4]Consolidated!M85)*(1/0.79941) | N85: =([4]Consolidated!N85)*(1/0.79941)
C89: PASS THROUGH COSTS (US$ excl. VAT) | D89: =[4]Consolidated!D89 | E89: =[4]Consolidated!E89 | F89: =[4]Consolidated!F89 | G89: =[4]Consolidated!G89 | H89: =[4]Consolidated!H89 | I89: =[4]Consolidated!I89 | J89: =[4]Consolidated!J89 | L89: =[4]Consolidated!L89 | M89: =[4]Consolidated!M89 | N89: =[4]Consolidated!N89
C90: Internal FTE | D90: =[4]Consolidated!D90 | E90: =[4]Consolidated!E90 | F90: =[4]Consolidated!F90 | G90: =[4]Consolidated!G90 | H90: =[4]Consolidated!H90 | I90: =[4]Consolidated!I90 | L90: =[4]Consolidated!L90 | M90: =[4]Consolidated!M90
C91: External FTE | D91: =[4]Consolidated!D91 | E91: =[4]Consolidated!E91 | F91: =[4]Consolidated!F91 | G91: =[4]Consolidated!G91 | H91: =[4]Consolidated!H91 | I91: =[4]Consolidated!I91 | L91: =[4]Consolidated!L91 | M91: =[4]Consolidated!M91
C92: Total FTE | D92: =[4]Consolidated!D92 | E92: =[4]Consolidated!E92 | F92: =[4]Consolidated!F92 | G92: =[4]Consolidated!G92 | H92: =[4]Consolidated!H92 | I92: =[4]Consolidated!I92 | L92: =[4]Consolidated!L92 | M92: =[4]Consolidated!M92
C94: Salaries | D94: =([4]Consolidated!D94)*(1/0.79941) | E94: =([4]Consolidated!E94)*(1/0.79941) | F94: =([4]Consolidated!F94)*(1/0.79941) | G94: =([4]Consolidated!G94)*(1/0.79941) | H94: =([4]Consolidated!H94)*(1/0.79941) | I94: =([4]Consolidated!I94)*(1/0.79941) | J94: =([4]Consolidated!J94)*(1/0.79941) | L94: =([4]Consolidated!L94)*(1/0.79941) | M94: =([4]Consolidated!M94)*(1/0.79941) | N94: =([4]Consolidated!N94)*(1/0.79941)
C95: Bonuses | D95: =([4]Consolidated!D95)*(1/0.79941) | E95: =([4]Consolidated!E95)*(1/0.79941) | F95: =([4]Consolidated!F95)*(1/0.79941) | G95: =([4]Consolidated!G95)*(1/0.79941) | H95: =([4]Consolidated!H95)*(1/0.79941) | I95: =([4]Consolidated!I95)*(1/0.79941) | J95: =([4]Consolidated!J95)*(1/0.79941) | L95: =([4]Consolidated!L95)*(1/0.79941) | M95: =([4]Consolidated!M95)*(1/0.79941) | N95: =([4]Consolidated!N95)*(1/0.79941)
C96: Third party staff, ex IT | D96: =([4]Consolidated!D96)*(1/0.79941) | E96: =([4]Consolidated!E96)*(1/0.79941) | F96: =([4]Consolidated!F96)*(1/0.79941) | G96: =([4]Consolidated!G96)*(1/0.79941) | H96: =([4]Consolidated!H96)*(1/0.79941) | I96: =([4]Consolidated!I96)*(1/0.79941) | J96: =([4]Consolidated!J96)*(1/0.79941) | L96: =([4]Consolidated!L96)*(1/0.79941) | M96: =([4]Consolidated!M96)*(1/0.79941) | N96: =([4]Consolidated!N96)*(1/0.79941)
C97: Third party IT staff | D97: =([4]Consolidated!D97)*(1/0.79941) | E97: =([4]Consolidated!E97)*(1/0.79941) | F97: =([4]Consolidated!F97)*(1/0.79941) | G97: =([4]Consolidated!G97)*(1/0.79941) | H97: =([4]Consolidated!H97)*(1/0.79941) | I97: =([4]Consolidated!I97)*(1/0.79941) | J97: =([4]Consolidated!J97)*(1/0.79941) | L97: =([4]Consolidated!L97)*(1/0.79941) | M97: =([4]Consolidated!M97)*(1/0.79941) | N97: =([4]Consolidated!N97)*(1/0.79941)
C98: Employee education | D98: =([4]Consolidated!D98)*(1/0.79941) | E98: =([4]Consolidated!E98)*(1/0.79941) | F98: =([4]Consolidated!F98)*(1/0.79941) | G98: =([4]Consolidated!G98)*(1/0.79941) | H98: =([4]Consolidated!H98)*(1/0.79941) | I98: =([4]Consolidated!I98)*(1/0.79941) | J98: =([4]Consolidated!J98)*(1/0.79941) | L98: =([4]Consolidated!L98)*(1/0.79941) | M98: =([4]Consolidated!M98)*(1/0.79941) | N98: =([4]Consolidated!N98)*(1/0.79941)
C99: Other staff expenses | D99: =([4]Consolidated!D99)*(1/0.79941) | E99: =([4]Consolidated!E99)*(1/0.79941) | F99: =([4]Consolidated!F99)*(1/0.79941) | G99: =([4]Consolidated!G99)*(1/0.79941) | H99: =([4]Consolidated!H99)*(1/0.79941) | I99: =([4]Consolidated!I99)*(1/0.79941) | J99: =([4]Consolidated!J99)*(1/0.79941) | L99: =([4]Consolidated!L99)*(1/0.79941) | M99: =([4]Consolidated!M99)*(1/0.79941) | N99: =([4]Consolidated!N99)*(1/0.79941)
C100: Staff expenses | D100: =([4]Consolidated!D100)*(1/0.79941) | E100: =([4]Consolidated!E100)*(1/0.79941) | F100: =([4]Consolidated!F100)*(1/0.79941) | G100: =([4]Consolidated!G100)*(1/0.79941) | H100: =([4]Consolidated!H100)*(1/0.79941) | I100: =([4]Consolidated!I100)*(1/0.79941) | J100: =([4]Consolidated!J100)*(1/0.79941) | L100: =([4]Consolidated!L100)*(1/0.79941) | M100: =([4]Consolidated!M100)*(1/0.79941) | N100: =([4]Consolidated!N100)*(1/0.79941)
C101: Hardware expenses | D101: =([4]Consolidated!D101)*(1/0.79941) | E101: =([4]Consolidated!E101)*(1/0.79941) | F101: =([4]Consolidated!F101)*(1/0.79941) | G101: =([4]Consolidated!G101)*(1/0.79941) | H101: =([4]Consolidated!H101)*(1/0.79941) | I101: =([4]Consolidated!I101)*(1/0.79941) | J101: =([4]Consolidated!J101)*(1/0.79941) | L101: =([4]Consolidated!L101)*(1/0.79941) | M101: =([4]Consolidated!M101)*(1/0.79941) | N101: =([4]Consolidated!N101)*(1/0.79941)
C102: Leasing/renting hardware | D102: =([4]Consolidated!D102)*(1/0.79941) | E102: =([4]Consolidated!E102)*(1/0.79941) | F102: =([4]Consolidated!F102)*(1/0.79941) | G102: =([4]Consolidated!G102)*(1/0.79941) | H102: =([4]Consolidated!H102)*(1/0.79941) | I102: =([4]Consolidated!I102)*(1/0.79941) | J102: =([4]Consolidated!J102)*(1/0.79941) | L102: =([4]Consolidated!L102)*(1/0.79941) | M102: =([4]Consolidated!M102)*(1/0.79941) | N102: =([4]Consolidated!N102)*(1/0.79941)
C103: Software expenses | D103: =([4]Consolidated!D103)*(1/0.79941) | E103: =([4]Consolidated!E103)*(1/0.79941) | F103: =([4]Consolidated!F103)*(1/0.79941) | G103: =([4]Consolidated!G103)*(1/0.79941) | H103: =([4]Consolidated!H103)*(1/0.79941) | I103: =([4]Consolidated!I103)*(1/0.79941) | J103: =([4]Consolidated!J103)*(1/0.79941) | L103: =([4]Consolidated!L103)*(1/0.79941) | M103: =([4]Consolidated!M103)*(1/0.79941) | N103: =([4]Consolidated!N103)*(1/0.79941)
C104: Leasing/renting/licenses sw | D104: =([4]Consolidated!D104)*(1/0.79941) | E104: =([4]Consolidated!E104)*(1/0.79941) | F104: =([4]Consolidated!F104)*(1/0.79941) | G104: =([4]Consolidated!G104)*(1/0.79941) | H104: =([4]Consolidated!H104)*(1/0.79941) | I104: =([4]Consolidated!I104)*(1/0.79941) | J104: =([4]Consolidated!J104)*(1/0.79941) | L104: =([4]Consolidated!L104)*(1/0.79941) | M104: =([4]Consolidated!M104)*(1/0.79941) | N104: =([4]Consolidated!N104)*(1/0.79941)
C105: Depreciation hardware | D105: =([4]Consolidated!D105)*(1/0.79941) | E105: =([4]Consolidated!E105)*(1/0.79941) | F105: =([4]Consolidated!F105)*(1/0.79941) | G105: =([4]Consolidated!G105)*(1/0.79941) | H105: =([4]Consolidated!H105)*(1/0.79941) | I105: =([4]Consolidated!I105)*(1/0.79941) | J105: =([4]Consolidated!J105)*(1/0.79941) | L105: =([4]Consolidated!L105)*(1/0.79941) | M105: =([4]Consolidated!M105)*(1/0.79941) | N105: =([4]Consolidated!N105)*(1/0.79941)
... C121: Operating expenses | D121: =([4]Consolidated!D121)*(1/0.79941) | E121: =([4]Consolidated!E121)*(1/0.79941) | F121: =([4]Consolidated!F121)*(1/0.79941) | G121: =([4]Consolidated!G121)*(1/0.79941) | H121: =([4]Consolidated!H121)*(1/0.79941) | I121: =([4]Consolidated!I121)*(1/0.79941) | J121: =([4]Consolidated!J121)*(1/0.79941) | L121: =([4]Consolidated!L121)*(1/0.79941) | M121: =([4]Consolidated!M121)*(1/0.79941) | N121: =([4]Consolidated!N121)*(1/0.79941)
D122: =0*(1/0.79941) | E122: =0*(1/0.79941) | F122: =0*(1/0.79941) | G122: =0*(1/0.79941) | H122: =0*(1/0.79941) | I122: =0*(1/0.79941) | J122: =0*(1/0.79941) | L122: =0*(1/0.79941) | M122: =0*(1/0.79941) | N122: =0*(1/0.79941)
C123: HR & Comms | D123: =([4]Consolidated!D123)*(1/0.79941) | E123: =([4]Consolidated!E123)*(1/0.79941) | F123: =([4]Consolidated!F123)*(1/0.79941) | G123: =([4]Consolidated!G123)*(1/0.79941) | H123: =([4]Consolidated!H123)*(1/0.79941) | I123: =([4]Consolidated!I123)*(1/0.79941) | J123: =([4]Consolidated!J123)*(1/0.79941) | L123: =([4]Consolidated!L123)*(1/0.79941) | M123: =([4]Consolidated!M123)*(1/0.79941) | N123: =([4]Consolidated!N123)*(1/0.79941)
C124: Finance & Business Support | D124: =([4]Consolidated!D124)*(1/0.79941) | E124: =([4]Consolidated!E124)*(1/0.79941) | F124: =([4]Consolidated!F124)*(1/0.79941) | G124: =([4]Consolidated!G124)*(1/0.79941) | H124: =([4]Consolidated!H124)*(1/0.79941) | I124: =([4]Consolidated!I124)*(1/0.79941) | J124: =([4]Consolidated!J124)*(1/0.79941) | L124: =([4]Consolidated!L124)*(1/0.79941) | M124: =([4]Consolidated!M124)*(1/0.79941) | N124: =([4]Consolidated!N124)*(1/0.79941)
C125: IT alloc | D125: =([4]Consolidated!D125)*(1/0.79941) | E125: =([4]Consolidated!E125)*(1/0.79941) | F125: =([4]Consolidated!F125)*(1/0.79941) | G125: =([4]Consolidated!G125)*(1/0.79941) | H125: =([4]Consolidated!H125)*(1/0.79941) | I125: =([4]Consolidated!I125)*(1/0.79941) | J125: =([4]Consolidated!J125)*(1/0.79941) | L125: =([4]Consolidated!L125)*(1/0.79941) | M125: =([4]Consolidated!M125)*(1/0.79941) | N125: =([4]Consolidated!N125)*(1/0.79941)
C126: Facilities Management | D126: =([4]Consolidated!D126)*(1/0.79941) | E126: =([4]Consolidated!E126)*(1/0.79941) | F126: =([4]Consolidated!F126)*(1/0.79941) | G126: =([4]Consolidated!G126)*(1/0.79941) | H126: =([4]Consolidated!H126)*(1/0.79941) | I126: =([4]Consolidated!I126)*(1/0.79941) | J126: =([4]Consolidated!J126)*(1/0.79941) | L126: =([4]Consolidated!L126)*(1/0.79941) | M126: =([4]Consolidated!M126)*(1/0.79941) | N126: =([4]Consolidated!N126)*(1/0.79941)
C127: Overheads | D127: =([4]Consolidated!D127)*(1/0.79941) | E127: =([4]Consolidated!E127)*(1/0.79941) | F127: =([4]Consolidated!F127)*(1/0.79941) | G127: =([4]Consolidated!G127)*(1/0.79941) | H127: =([4]Consolidated!H127)*(1/0.79941) | I127: =([4]Consolidated!I127)*(1/0.79941) | J127: =([4]Consolidated!J127)*(1/0.79941) | L127: =([4]Consolidated!L127)*(1/0.79941) | M127: =([4]Consolidated!M127)*(1/0.79941) | N127: =([4]Consolidated!N127)*(1/0.79941)
D128: =0*(1/0.79941) | E128: =0*(1/0.79941) | F128: =0*(1/0.79941) | G128: =0*(1/0.79941) | H128: =0*(1/0.79941) | I128: =0*(1/0.79941) | J128: =0*(1/0.79941) | L128: =0*(1/0.79941) | M128: =0*(1/0.79941) | N128: =0*(1/0.79941)
C129: Total Operating Costs (incl. O/H) | D129: =([4]Consolidated!D129)*(1/0.79941) | E129: =([4]Consolidated!E129)*(1/0.79941) | F129: =([4]Consolidated!F129)*(1/0.79941) | G129: =([4]Consolidated!G129)*(1/0.79941) | H129: =([4]Consolidated!H129)*(1/0.79941) | I129: =([4]Consolidated!I129)*(1/0.79941) | J129: =([4]Consolidated!J129)*(1/0.79941) | L129: =([4]Consolidated!L129)*(1/0.79941) | M129: =([4]Consolidated!M129)*(1/0.79941) | N129: =([4]Consolidated!N129)*(1/0.79941)
C132: RETAINED COSTS (US$ excl. VAT) | D132: =[4]Consolidated!D132 | E132: =[4]Consolidated!E132 | F132: =[4]Consolidated!F132 | G132: =[4]Consolidated!G132 | H132: =[4]Consolidated!H132 | I132: =[4]Consolidated!I132 | J132: =[4]Consolidated!J132 | L132: =[4]Consolidated!L132 | M132: =[4]Consolidated!M132 | N132: =[4]Consolidated!N132
C133: Internal FTE | D133: =[4]Consolidated!D133 | E133: =[4]Consolidated!E133 | F133: =[4]Consolidated!F133 | G133: =[4]Consolidated!G133 | H133: =[4]Consolidated!H133 | I133: =[4]Consolidated!I133 | L133: =[4]Consolidated!L133 | M133: =[4]Consolidated!M133 | N133: =[4]Consolidated!N133
C134: External FTE | D134: =[4]Consolidated!D134 | E134: =[4]Consolidated!E134 | F134: =[4]Consolidated!F134 | G134: =[4]Consolidated!G134 | H134: =[4]Consolidated!H134 | I134: =[4]Consolidated!I134 | L134: =[4]Consolidated!L134 | M134: =[4]Consolidated!M134 | N134: =[4]Consolidated!N134
C135: Total FTE | D135: =[4]Consolidated!D135 | E135: =[4]Consolidated!E135 | F135: =[4]Consolidated!F135 | G135: =[4]Consolidated!G135 | H135: =[4]Consolidated!H135 | I135: =[4]Consolidated!I135 | L135: =[4]Consolidated!L135 | M135: =[4]Consolidated!M135 | N135: =[4]Consolidated!N135
C137: Salaries | D137: =([4]Consolidated!D137)*(1/0.79941) | E137: =([4]Consolidated!E137)*(1/0.79941) | F137: =([4]Consolidated!F137)*(1/0.79941) | G137: =([4]Consolidated!G137)*(1/0.79941) | H137: =([4]Consolidated!H137)*(1/0.79941) | I137: =([4]Consolidated!I137)*(1/0.79941) | J137: =([4]Consolidated!J137)*(1/0.79941) | L137: =([4]Consolidated!L137)*(1/0.79941) | M137: =([4]Consolidated!M137)*(1/0.79941) | N137: =([4]Consolidated!N137)*(1/0.79941)
C138: Bonuses | D138: =([4]Consolidated!D138)*(1/0.79941) | E138: =([4]Consolidated!E138)*(1/0.79941) | F138: =([4]Consolidated!F138)*(1/0.79941) | G138: =([4]Consolidated!G138)*(1/0.79941) | H138: =([4]Consolidated!H138)*(1/0.79941) | I138: =([4]Consolidated!I138)*(1/0.79941) | J138: =([4]Consolidated!J138)*(1/0.79941) | L138: =([4]Consolidated!L138)*(1/0.79941) | M138: =([4]Consolidated!M138)*(1/0.79941) | N138: =([4]Consolidated!N138)*(1/0.79941)
C139: Third party staff, ex IT | D139: =([4]Consolidated!D139)*(1/0.79941) | E139: =([4]Consolidated!E139)*(1/0.79941) | F139: =([4]Consolidated!F139)*(1/0.79941) | G139: =([4]Consolidated!G139)*(1/0.79941) | H139: =([4]Consolidated!H139)*(1/0.79941) | I139: =([4]Consolidated!I139)*(1/0.79941) | J139: =([4]Consolidated!J139)*(1/0.79941) | L139: =([4]Consolidated!L139)*(1/0.79941) | M139: =([4]Consolidated!M139)*(1/0.79941) | N139: =([4]Consolidated!N139)*(1/0.79941)
C140: Third party IT staff | D140: =([4]Consolidated!D140)*(1/0.79941) | E140: =([4]Consolidated!E140)*(1/0.79941) | F140: =([4]Consolidated!F140)*(1/0.79941) | G140: =([4]Consolidated!G140)*(1/0.79941) | H140: =([4]Consolidated!H140)*(1/0.79941) | I140: =([4]Consolidated!I140)*(1/0.79941) | J140: =([4]Consolidated!J140)*(1/0.79941) | L140: =([4]Consolidated!L140)*(1/0.79941) | M140: =([4]Consolidated!M140)*(1/0.79941) | N140: =([4]Consolidated!N140)*(1/0.79941)
C141: Employee education | D141: =([4]Consolidated!D141)*(1/0.79941) | E141: =([4]Consolidated!E141)*(1/0.79941) | F141: =([4]Consolidated!F141)*(1/0.79941) | G141: =([4]Consolidated!G141)*(1/0.79941) | H141: =([4]Consolidated!H141)*(1/0.79941) | I141: =([4]Consolidated!I141)*(1/0.79941) | J141: =([4]Consolidated!J141)*(1/0.79941) | L141: =([4]Consolidated!L141)*(1/0.79941) | M141: =([4]Consolidated!M141)*(1/0.79941) | N141: =([4]Consolidated!N141)*(1/0.79941)
C142: Other staff expenses | D142: =([4]Consolidated!D142)*(1/0.79941) | E142: =([4]Consolidated!E142)*(1/0.79941) | F142: =([4]Consolidated!F142)*(1/0.79941) | G142: =([4]Consolidated!G142)*(1/0.79941) | H142: =([4]Consolidated!H142)*(1/0.79941) | I142: =([4]Consolidated!I142)*(1/0.79941) | J142: =([4]Consolidated!J142)*(1/0.79941) | L142: =([4]Consolidated!L142)*(1/0.79941) | M142: =([4]Consolidated!M142)*(1/0.79941) | N142: =([4]Consolidated!N142)*(1/0.79941)
C143: Staff expenses | D143: =([4]Consolidated!D143)*(1/0.79941) | E143: =([4]Consolidated!E143)*(1/0.79941) | F143: =([4]Consolidated!F143)*(1/0.79941) | G143: =([4]Consolidated!G143)*(1/0.79941) | H143: =([4]Consolidated!H143)*(1/0.79941) | I143: =([4]Consolidated!I143)*(1/0.79941) | J143: =([4]Consolidated!J143)*(1/0.79941) | L143: =([4]Consolidated!L143)*(1/0.79941) | M143: =([4]Consolidated!M143)*(1/0.79941) | N143: =([4]Consolidated!N143)*(1/0.79941)
C144: Hardware expenses | D144: =([4]Consolidated!D144)*(1/0.79941) | E144: =([4]Consolidated!E144)*(1/0.79941) | F144: =([4]Consolidated!F144)*(1/0.79941) | G144: =([4]Consolidated!G144)*(1/0.79941) | H144: =([4]Consolidated!H144)*(1/0.79941) | I144: =([4]Consolidated!I144)*(1/0.79941) | J144: =([4]Consolidated!J144)*(1/0.79941) | L144: =([4]Consolidated!L144)*(1/0.79941) | M144: =([4]Consolidated!M144)*(1/0.79941) | N144: =([4]Consolidated!N144)*(1/0.79941)
C145: Leasing/renting hardware | D145: =([4]Consolidated!D145)*(1/0.79941) | E145: =([4]Consolidated!E145)*(1/0.79941) | F145: =([4]Consolidated!F145)*(1/0.79941) | G145: =([4]Consolidated!G145)*(1/0.79941) | H145: =([4]Consolidated!H145)*(1/0.79941) | I145: =([4]Consolidated!I145)*(1/0.79941) | J145: =([4]Consolidated!J145)*(1/0.79941) | L145: =([4]Consolidated!L145)*(1/0.79941) | M145: =([4]Consolidated!M145)*(1/0.79941) | N145: =([4]Consolidated!N145)*(1/0.79941)
C146: Software expenses | D146: =([4]Consolidated!D146)*(1/0.79941) | E146: =([4]Consolidated!E146)*(1/0.79941) | F146: =([4]Consolidated!F146)*(1/0.79941) | G146: =([4]Consolidated!G146)*(1/0.79941) | H146: =([4]Consolidated!H146)*(1/0.79941) | I146: =([4]Consolidated!I146)*(1/0.79941) | J146: =([4]Consolidated!J146)*(1/0.79941) | L146: =([4]Consolidated!L146)*(1/0.79941) | M146: =([4]Consolidated!M146)*(1/0.79941) | N146: =([4]Consolidated!N146)*(1/0.79941)
C147: Leasing/renting/licenses sw | D147: =([4]Consolidated!D147)*(1/0.79941) | E147: =([4]Consolidated!E147)*(1/0.79941) | F147: =([4]Consolidated!F147)*(1/0.79941) | G147: =([4]Consolidated!G147)*(1/0.79941) | H147: =([4]Consolidated!H147)*(1/0.79941) | I147: =([4]Consolidated!I147)*(1/0.79941) | J147: =([4]Consolidated!J147)*(1/0.79941) | L147: =([4]Consolidated!L147)*(1/0.79941) | M147: =([4]Consolidated!M147)*(1/0.79941) | N147: =([4]Consolidated!N147)*(1/0.79941)
C148: Depreciation hardware | D148: =([4]Consolidated!D148)*(1/0.79941) | E148: =([4]Consolidated!E148)*(1/0.79941) | F148: =([4]Consolidated!F148)*(1/0.79941) | G148: =([4]Consolidated!G148)*(1/0.79941) | H148: =([4]Consolidated!H148)*(1/0.79941) | I148: =([4]Consolidated!I148)*(1/0.79941) | J148: =([4]Consolidated!J148)*(1/0.79941) | L148: =([4]Consolidated!L148)*(1/0.79941) | M148: =([4]Consolidated!M148)*(1/0.79941) | N148: =([4]Consolidated!N148)*(1/0.79941)
... C164: Operating expenses | D164: =([4]Consolidated!D164)*(1/0.79941) | E164: =([4]Consolidated!E164)*(1/0.79941) | F164: =([4]Consolidated!F164)*(1/0.79941) | G164: =([4]Consolidated!G164)*(1/0.79941) | H164: =([4]Consolidated!H164)*(1/0.79941) | I164: =([4]Consolidated!I164)*(1/0.79941) | J164: =([4]Consolidated!J164)*(1/0.79941) | L164: =([4]Consolidated!L164)*(1/0.79941) | M164: =([4]Consolidated!M164)*(1/0.79941) | N164: =([4]Consolidated!N164)*(1/0.79941)
D165: =0*(1/0.79941) | E165: =0*(1/0.79941) | F165: =0*(1/0.79941) | G165: =0*(1/0.79941) | H165: =0*(1/0.79941) | I165: =0*(1/0.79941) | J165: =0*(1/0.79941) | L165: =0*(1/0.79941) | M165: =0*(1/0.79941) | N165: =0*(1/0.79941)
C166: HR & Comms | D166: =([4]Consolidated!D166)*(1/0.79941) | E166: =([4]Consolidated!E166)*(1/0.79941) | F166: =([4]Consolidated!F166)*(1/0.79941) | G166: =([4]Consolidated!G166)*(1/0.79941) | H166: =([4]Consolidated!H166)*(1/0.79941) | I166: =([4]Consolidated!I166)*(1/0.79941) | J166: =([4]Consolidated!J166)*(1/0.79941) | L166: =([4]Consolidated!L166)*(1/0.79941) | M166: =([4]Consolidated!M166)*(1/0.79941) | N166: =([4]Consolidated!N166)*(1/0.79941)
C167: Finance & Business Support | D167: =([4]Consolidated!D167)*(1/0.79941) | E167: =([4]Consolidated!E167)*(1/0.79941) | F167: =([4]Consolidated!F167)*(1/0.79941) | G167: =([4]Consolidated!G167)*(1/0.79941) | H167: =([4]Consolidated!H167)*(1/0.79941) | I167: =([4]Consolidated!I167)*(1/0.79941) | J167: =([4]Consolidated!J167)*(1/0.79941) | L167: =([4]Consolidated!L167)*(1/0.79941) | M167: =([4]Consolidated!M167)*(1/0.79941) | N167: =([4]Consolidated!N167)*(1/0.79941)
C168: IT alloc | D168: =([4]Consolidated!D168)*(1/0.79941) | E168: =([4]Consolidated!E168)*(1/0.79941) | F168: =([4]Consolidated!F168)*(1/0.79941) | G168: =([4]Consolidated!G168)*(1/0.79941) | H168: =([4]Consolidated!H168)*(1/0.79941) | I168: =([4]Consolidated!I168)*(1/0.79941) | J168: =([4]Consolidated!J168)*(1/0.79941) | L168: =([4]Consolidated!L168)*(1/0.79941) | M168: =([4]Consolidated!M168)*(1/0.79941) | N168: =([4]Consolidated!N168)*(1/0.79941)
C169: Facilities Management | D169: =([4]Consolidated!D169)*(1/0.79941) | E169: =([4]Consolidated!E169)*(1/0.79941) | F169: =([4]Consolidated!F169)*(1/0.79941) | G169: =([4]Consolidated!G169)*(1/0.79941) | H169: =([4]Consolidated!H169)*(1/0.79941) | I169: =([4]Consolidated!I169)*(1/0.79941) | J169: =([4]Consolidated!J169)*(1/0.79941) | L169: =([4]Consolidated!L169)*(1/0.79941) | M169: =([4]Consolidated!M169)*(1/0.79941) | N169: =([4]Consolidated!N169)*(1/0.79941)
...

Sheet Italy
C1: Italy
C2: TOTAL COSTS (US$ excl. VAT) | D2: =[5]Consolidated!D2 | E2: =[5]Consolidated!E2 | F2: =[5]Consolidated!F2 | G2: =[5]Consolidated!G2 | H2: =[5]Consolidated!H2 | I2: =[5]Consolidated!I2 | J2: =[5]Consolidated!J2 | L2: =[5]Consolidated!L2 | M2: =[5]Consolidated!M2 | N2: =[5]Consolidated!N2
C3: Internal FTE | D3: =[5]Consolidated!D3 | E3: =[5]Consolidated!E3 | F3: =[5]Consolidated!F3 | G3: =[5]Consolidated!G3 | H3: =[5]Consolidated!H3 | I3: =[5]Consolidated!I3 | L3: =[5]Consolidated!L3 | M3: =[5]Consolidated!M3
C4: External FTE | D4: =[5]Consolidated!D4 | E4: =[5]Consolidated!E4 | F4: =[5]Consolidated!F4 | G4: =[5]Consolidated!G4 | H4: =[5]Consolidated!H4 | I4: =[5]Consolidated!I4 | L4: =[5]Consolidated!L4 | M4: =[5]Consolidated!M4
C5: Total FTE | D5: =[5]Consolidated!D5 | E5: =[5]Consolidated!E5 | F5: =[5]Consolidated!F5 | G5: =[5]Consolidated!G5 | H5: =[5]Consolidated!H5 | I5: =[5]Consolidated!I5 | L5: =[5]Consolidated!L5 | M5: =[5]Consolidated!M5
C7: Salaries | D7: =([5]Consolidated!D7)*(1/0.79941) | E7: =([5]Consolidated!E7)*(1/0.79941) | F7: =([5]Consolidated!F7)*(1/0.79941) | G7: =([5]Consolidated!G7)*(1/0.79941) | H7: =([5]Consolidated!H7)*(1/0.79941) | I7: =([5]Consolidated!I7)*(1/0.79941) | J7: =([5]Consolidated!J7)*(1/0.79941) | L7: =([5]Consolidated!L7)*(1/0.79941) | M7: =([5]Consolidated!M7)*(1/0.79941) | N7: =([5]Consolidated!N7)*(1/0.79941) | P7: 1000
C8: Bonuses | D8: =([5]Consolidated!D8)*(1/0.79941) | E8: =([5]Consolidated!E8)*(1/0.79941) | F8: =([5]Consolidated!F8)*(1/0.79941) | G8: =([5]Consolidated!G8)*(1/0.79941) | H8: =([5]Consolidated!H8)*(1/0.79941) | I8: =([5]Consolidated!I8)*(1/0.79941) | J8: =([5]Consolidated!J8)*(1/0.79941) | L8: =([5]Consolidated!L8)*(1/0.79941) | M8: =([5]Consolidated!M8)*(1/0.79941) | N8: =([5]Consolidated!N8)*(1/0.79941) | P8: =1/0.79941 | Q8: Euro to Dollar Rate
C9: Third party staff, ex IT | D9: =([5]Consolidated!D9)*(1/0.79941) | E9: =([5]Consolidated!E9)*(1/0.79941) | F9: =([5]Consolidated!F9)*(1/0.79941) | G9: =([5]Consolidated!G9)*(1/0.79941) | H9: =([5]Consolidated!H9)*(1/0.79941) | I9: =([5]Consolidated!I9)*(1/0.79941) | J9: =([5]Consolidated!J9)*(1/0.79941) | L9: =([5]Consolidated!L9)*(1/0.79941) | M9: =([5]Consolidated!M9)*(1/0.79941) | N9: =([5]Consolidated!N9)*(1/0.79941)
C10: Third party IT staff | D10: =([5]Consolidated!D10)*(1/0.79941) | E10: =([5]Consolidated!E10)*(1/0.79941) | F10: =([5]Consolidated!F10)*(1/0.79941) | G10: =([5]Consolidated!G10)*(1/0.79941) | H10: =([5]Consolidated!H10)*(1/0.79941) | I10: =([5]Consolidated!I10)*(1/0.79941) | J10: =([5]Consolidated!J10)*(1/0.79941) | L10: =([5]Consolidated!L10)*(1/0.79941) | M10: =([5]Consolidated!M10)*(1/0.79941) | N10: =([5]Consolidated!N10)*(1/0.79941)
C11: Employee education | D11: =([5]Consolidated!D11)*(1/0.79941) | E11: =([5]Consolidated!E11)*(1/0.79941) | F11: =([5]Consolidated!F11)*(1/0.79941) | G11: =([5]Consolidated!G11)*(1/0.79941) | H11: =([5]Consolidated!H11)*(1/0.79941) | I11: =([5]Consolidated!I11)*(1/0.79941) | J11: =([5]Consolidated!J11)*(1/0.79941) | L11: =([5]Consolidated!L11)*(1/0.79941) | M11: =([5]Consolidated!M11)*(1/0.79941) | N11: =([5]Consolidated!N11)*(1/0.79941)
C12: Other staff expenses | D12: =([5]Consolidated!D12)*(1/0.79941) | E12: =([5]Consolidated!E12)*(1/0.79941) | F12: =([5]Consolidated!F12)*(1/0.79941) | G12: =([5]Consolidated!G12)*(1/0.79941) | H12: =([5]Consolidated!H12)*(1/0.79941) | I12: =([5]Consolidated!I12)*(1/0.79941) | J12: =([5]Consolidated!J12)*(1/0.79941) | L12: =([5]Consolidated!L12)*(1/0.79941) | M12: =([5]Consolidated!M12)*(1/0.79941) | N12: =([5]Consolidated!N12)*(1/0.79941)
C13: Staff expenses | D13: =([5]Consolidated!D13)*(1/0.79941) | E13: =([5]Consolidated!E13)*(1/0.79941) | F13: =([5]Consolidated!F13)*(1/0.79941) | G13: =([5]Consolidated!G13)*(1/0.79941) | H13: =([5]Consolidated!H13)*(1/0.79941) | I13: =([5]Consolidated!I13)*(1/0.79941) | J13: =([5]Consolidated!J13)*(1/0.79941) | L13: =([5]Consolidated!L13)*(1/0.79941) | M13: =([5]Consolidated!M13)*(1/0.79941) | N13: =([5]Consolidated!N13)*(1/0.79941)
C14: Hardware expenses | D14: =([5]Consolidated!D14)*(1/0.79941) | E14: =([5]Consolidated!E14)*(1/0.79941) | F14: =([5]Consolidated!F14)*(1/0.79941) | G14: =([5]Consolidated!G14)*(1/0.79941) | H14: =([5]Consolidated!H14)*(1/0.79941) | I14: =([5]Consolidated!I14)*(1/0.79941) | J14: =([5]Consolidated!J14)*(1/0.79941) | L14: =([5]Consolidated!L14)*(1/0.79941) | M14: =([5]Consolidated!M14)*(1/0.79941) | N14: =([5]Consolidated!N14)*(1/0.79941)
C15: Leasing/renting hardware | D15: =([5]Consolidated!D15)*(1/0.79941) | E15: =([5]Consolidated!E15)*(1/0.79941) | F15: =([5]Consolidated!F15)*(1/0.79941) | G15: =([5]Consolidated!G15)*(1/0.79941) | H15: =([5]Consolidated!H15)*(1/0.79941) | I15: =([5]Consolidated!I15)*(1/0.79941) | J15: =([5]Consolidated!J15)*(1/0.79941) | L15: =([5]Consolidated!L15)*(1/0.79941) | M15: =([5]Consolidated!M15)*(1/0.79941) | N15: =([5]Consolidated!N15)*(1/0.79941)
C16: Software expenses | D16: =([5]Consolidated!D16)*(1/0.79941) | E16: =([5]Consolidated!E16)*(1/0.79941) | F16: =([5]Consolidated!F16)*(1/0.79941) | G16: =([5]Consolidated!G16)*(1/0.79941) | H16: =([5]Consolidated!H16)*(1/0.79941) | I16: =([5]Consolidated!I16)*(1/0.79941) | J16: =([5]Consolidated!J16)*(1/0.79941) | L16: =([5]Consolidated!L16)*(1/0.79941) | M16: =([5]Consolidated!M16)*(1/0.79941) | N16: =([5]Consolidated!N16)*(1/0.79941)
C17: Leasing/renting/licenses sw | D17: =([5]Consolidated!D17)*(1/0.79941) | E17: =([5]Consolidated!E17)*(1/0.79941) | F17: =([5]Consolidated!F17)*(1/0.79941) | G17: =([5]Consolidated!G17)*(1/0.79941) | H17: =([5]Consolidated!H17)*(1/0.79941) | I17: =([5]Consolidated!I17)*(1/0.79941) | J17: =([5]Consolidated!J17)*(1/0.79941) | L17: =([5]Consolidated!L17)*(1/0.79941) | M17: =([5]Consolidated!M17)*(1/0.79941) | N17: =([5]Consolidated!N17)*(1/0.79941)
C18: Depreciation hardware | D18: =([5]Consolidated!D18)*(1/0.79941) | E18: =([5]Consolidated!E18)*(1/0.79941) | F18: =([5]Consolidated!F18)*(1/0.79941) | G18: =([5]Consolidated!G18)*(1/0.79941) | H18: =([5]Consolidated!H18)*(1/0.79941) | I18: =([5]Consolidated!I18)*(1/0.79941) | J18: =([5]Consolidated!J18)*(1/0.79941) | L18: =([5]Consolidated!L18)*(1/0.79941) | M18: =([5]Consolidated!M18)*(1/0.79941) | N18: =([5]Consolidated!N18)*(1/0.79941)
C19: Depreciation software | D19: =([5]Consolidated!D19)*(1/0.79941) | E19: =([5]Consolidated!E19)*(1/0.79941) | F19: =([5]Consolidated!F19)*(1/0.79941) | G19: =([5]Consolidated!G19)*(1/0.79941) | H19: =([5]Consolidated!H19)*(1/0.79941) | I19: =([5]Consolidated!I19)*(1/0.79941) | J19: =([5]Consolidated!J19)*(1/0.79941) | L19: =([5]Consolidated!L19)*(1/0.79941) | M19: =([5]Consolidated!M19)*(1/0.79941) | N19: =([5]Consolidated!N19)*(1/0.79941)
C20: Outsourcing IT activities | D20: =([5]Consolidated!D20)*(1/0.79941) | E20: =([5]Consolidated!E20)*(1/0.79941) | F20: =([5]Consolidated!F20)*(1/0.79941) | G20: =([5]Consolidated!G20)*(1/0.79941) | H20: =([5]Consolidated!H20)*(1/0.79941) | I20: =([5]Consolidated!I20)*(1/0.79941) | J20: =([5]Consolidated!J20)*(1/0.79941) | L20: =([5]Consolidated!L20)*(1/0.79941) | M20: =([5]Consolidated!M20)*(1/0.79941) | N20: =([5]Consolidated!N20)*(1/0.79941)
... C34: Operating expenses | D34: =([5]Consolidated!D34)*(1/0.79941) | E34: =([5]Consolidated!E34)*(1/0.79941) | F34: =([5]Consolidated!F34)*(1/0.79941) | G34: =([5]Consolidated!G34)*(1/0.79941) | H34: =([5]Consolidated!H34)*(1/0.79941) | I34: =([5]Consolidated!I34)*(1/0.79941) | J34: =([5]Consolidated!J34)*(1/0.79941) | L34: =([5]Consolidated!L34)*(1/0.79941) | M34: =([5]Consolidated!M34)*(1/0.79941) | N34: =([5]Consolidated!N34)*(1/0.79941)
D35: =0*(1/0.79941) | E35: =0*(1/0.79941) | F35: =0*(1/0.79941) | G35: =0*(1/0.79941) | H35: =0*(1/0.79941) | I35: =0*(1/0.79941) | J35: =0*(1/0.79941) | L35: =0*(1/0.79941) | M35: =0*(1/0.79941) | N35: =0*(1/0.79941)
C36: HR & Comms | D36: =([5]Consolidated!D36)*(1/0.79941) | E36: =([5]Consolidated!E36)*(1/0.79941) | F36: =([5]Consolidated!F36)*(1/0.79941) | G36: =([5]Consolidated!G36)*(1/0.79941) | H36: =([5]Consolidated!H36)*(1/0.79941) | I36: =([5]Consolidated!I36)*(1/0.79941) | J36: =([5]Consolidated!J36)*(1/0.79941) | L36: =([5]Consolidated!L36)*(1/0.79941) | M36: =([5]Consolidated!M36)*(1/0.79941) | N36: =([5]Consolidated!N36)*(1/0.79941)
C37: Finance & Business Support | D37: =([5]Consolidated!D37)*(1/0.79941) | E37: =([5]Consolidated!E37)*(1/0.79941) | F37: =([5]Consolidated!F37)*(1/0.79941) | G37: =([5]Consolidated!G37)*(1/0.79941) | H37: =([5]Consolidated!H37)*(1/0.79941) | I37: =([5]Consolidated!I37)*(1/0.79941) | J37: =([5]Consolidated!J37)*(1/0.79941) | L37: =([5]Consolidated!L37)*(1/0.79941) | M37: =([5]Consolidated!M37)*(1/0.79941) | N37: =([5]Consolidated!N37)*(1/0.79941)
C38: IT alloc | D38: =([5]Consolidated!D38)*(1/0.79941) | E38: =([5]Consolidated!E38)*(1/0.79941) | F38: =([5]Consolidated!F38)*(1/0.79941) | G38: =([5]Consolidated!G38)*(1/0.79941) | H38: =([5]Consolidated!H38)*(1/0.79941) | I38: =([5]Consolidated!I38)*(1/0.79941) | J38: =([5]Consolidated!J38)*(1/0.79941) | L38: =([5]Consolidated!L38)*(1/0.79941) | M38: =([5]Consolidated!M38)*(1/0.79941) | N38: =([5]Consolidated!N38)*(1/0.79941)
C39: Facilities Management | D39: =([5]Consolidated!D39)*(1/0.79941) | E39: =([5]Consolidated!E39)*(1/0.79941) | F39: =([5]Consolidated!F39)*(1/0.79941) | G39: =([5]Consolidated!G39)*(1/0.79941) | H39: =([5]Consolidated!H39)*(1/0.79941) | I39: =([5]Consolidated!I39)*(1/0.79941) | J39: =([5]Consolidated!J39)*(1/0.79941) | L39: =([5]Consolidated!L39)*(1/0.79941) | M39: =([5]Consolidated!M39)*(1/0.79941) | N39: =([5]Consolidated!N39)*(1/0.79941)
C40: Overheads | D40: =([5]Consolidated!D40)*(1/0.79941) | E40: =([5]Consolidated!E40)*(1/0.79941) | F40: =([5]Consolidated!F40)*(1/0.79941) | G40: =([5]Consolidated!G40)*(1/0.79941) | H40: =([5]Consolidated!H40)*(1/0.79941) | I40: =([5]Consolidated!I40)*(1/0.79941) | J40: =([5]Consolidated!J40)*(1/0.79941) | L40: =([5]Consolidated!L40)*(1/0.79941) | M40: =([5]Consolidated!M40)*(1/0.79941) | N40: =([5]Consolidated!N40)*(1/0.79941)
C41: 0 | D41: =0*(1/0.79941) | E41: =0*(1/0.79941) | F41: =0*(1/0.79941) | G41: =0*(1/0.79941) | H41: =0*(1/0.79941) | I41: =0*(1/0.79941) | J41: =0*(1/0.79941) | L41: =0*(1/0.79941) | M41: =0*(1/0.79941) | N41: =0*(1/0.79941)
C42: Total Operating Costs (incl. O/H) | D42: =([5]Consolidated!D42)*(1/0.79941) | E42: =([5]Consolidated!E42)*(1/0.79941) | F42: =([5]Consolidated!F42)*(1/0.79941) | G42: =([5]Consolidated!G42)*(1/0.79941) | H42: =([5]Consolidated!H42)*(1/0.79941) | I42: =([5]Consolidated!I42)*(1/0.79941) | J42: =([5]Consolidated!J42)*(1/0.79941) | L42: =([5]Consolidated!L42)*(1/0.79941) | M42: =([5]Consolidated!M42)*(1/0.79941) | N42: =([5]Consolidated!N42)*(1/0.79941)
C45: SUPPLIER ASSUMED COSTS (US$ excl. VAT) | D45: =[5]Consolidated!D45 | E45: =[5]Consolidated!E45 | F45: =[5]Consolidated!F45 | G45: =[5]Consolidated!G45 | H45: =[5]Consolidated!H45 | I45: =[5]Consolidated!I45 | J45: =[5]Consolidated!J45 | L45: =[5]Consolidated!L45 | M45: =[5]Consolidated!M45 | N45: =[5]Consolidated!N45
C46: Internal FTE | D46: =[5]Consolidated!D46 | E46: =[5]Consolidated!E46 | F46: =[5]Consolidated!F46 | G46: =[5]Consolidated!G46 | H46: =[5]Consolidated!H46 | I46: =[5]Consolidated!I46 | L46: =[5]Consolidated!L46 | M46: =[5]Consolidated!M46
C47: External FTE | D47: =[5]Consolidated!D47 | E47: =[5]Consolidated!E47 | F47: =[5]Consolidated!F47 | G47: =[5]Consolidated!G47 | H47: =[5]Consolidated!H47 | I47: =[5]Consolidated!I47 | L47: =[5]Consolidated!L47 | M47: =[5]Consolidated!M47
