Workbook

Sheet Cover Page
B2: GlobalPharma AG
B5: ATTACHMENT 4-A
B7: SERVICE PROVIDER PRICING FORMS
B8: Attachment to Exhibit 4 (Pricing and Financial Provisions)
B15: This document contains confidential and proprietary information of GlobalPharma AG. It is furnished for the performance of The Agreements only. Except with the express prior written permission of GlobalPharma AG, this document and the information contained herein may not be published, disclosed, or used for any other purpose.

Sheet Summary Charges
A1: SUMMARY CHARGES (US$)
B3: Category of Services
A4: BASE CHARGES | C4: Year 1 | D4: Year 2 | E4: Year 3 | F4: Year 4 | G4: Year 5 | H4: Year 6 | I4: Year 7 | J4: Year 8 | K4: Total
B5: General Accounting & Sox | C5: ='Consolidated Base Charges'!C37 | D5: ='Consolidated Base Charges'!D37 | E5: ='Consolidated Base Charges'!E37 | F5: ='Consolidated Base Charges'!F37 | G5: ='Consolidated Base Charges'!G37 | H5: ='Consolidated Base Charges'!H37 | I5: ='Consolidated Base Charges'!I37 | J5: ='Consolidated Base Charges'!J37 | K5: =SUM(C5:J5)
B7: Fixed Assets | C7: ='Consolidated Base Charges'!C41 | D7: ='Consolidated Base Charges'!D41 | E7: ='Consolidated Base Charges'!E41 | F7: ='Consolidated Base Charges'!F41 | G7: ='Consolidated Base Charges'!G41 | H7: ='Consolidated Base Charges'!H41 | I7: ='Consolidated Base Charges'!I41 | J7: ='Consolidated Base Charges'!J41 | K7: =SUM(C7:J7)
B9: Accounts Payable | C9: ='Consolidated Base Charges'!C45 | D9: ='Consolidated Base Charges'!D45 | E9: ='Consolidated Base Charges'!E45 | F9: ='Consolidated Base Charges'!F45 | G9: ='Consolidated Base Charges'!G45 | H9: ='Consolidated Base Charges'!H45 | I9: ='Consolidated Base Charges'!I45 | J9: ='Consolidated Base Charges'!J45 | K9: =SUM(C9:J9)
B11: T&E | C11: ='Consolidated Base Charges'!C49 | D11: ='Consolidated Base Charges'!D49 | E11: ='Consolidated Base Charges'!E49 | F11: ='Consolidated Base Charges'!F49 | G11: ='Consolidated Base Charges'!G49 | H11: ='Consolidated Base Charges'!H49 | I11: ='Consolidated Base Charges'!I49 | J11: ='Consolidated Base Charges'!J49 | K11: =SUM(C11:J11)
B13: Order to Cash | C13: ='Consolidated Base Charges'!C53 | D13: ='Consolidated Base Charges'!D53 | E13: ='Consolidated Base Charges'!E53 | F13: ='Consolidated Base Charges'!F53 | G13: ='Consolidated Base Charges'!G53 | H13: ='Consolidated Base Charges'!H53 | I13: ='Consolidated Base Charges'!I53 | J13: ='Consolidated Base Charges'!J53 | K13: =SUM(C13:J13)
B15: Requistion to Pay | C15: ='Consolidated Base Charges'!C57 | D15: ='Consolidated Base Charges'!D57 | E15: ='Consolidated Base Charges'!E57 | F15: ='Consolidated Base Charges'!F57 | G15: ='Consolidated Base Charges'!G57 | H15: ='Consolidated Base Charges'!H57 | I15: ='Consolidated Base Charges'!I57 | J15: ='Consolidated Base Charges'!J57 | K15: =SUM(C15:J15)
A17: TOTAL BASE CHARGES | C17: =SUM(C5:C16) | D17: =SUM(D5:D16) | E17: =SUM(E5:E16) | F17: =SUM(F5:F16) | G17: =SUM(G5:G16) | H17: =SUM(H5:H16) | I17: =SUM(I5:I16) | J17: =SUM(J5:J16) | K17: =SUM(K5:K16)
A19: TRANSITION CHARGES | C19: Year 1 | D19: Year 2 | E19: Year 3 | F19: Year 4 | G19: Year 5 | H19: Year 6 | I19: Year 7 | J19: Year 8 | K19: Total
B20: General Accounting & Sox | C20: ='Transition Charges'!F13 | D20: ='Transition Charges'!K13 | E20: ='Transition Charges'!L13 | F20: ='Transition Charges'!M13 | G20: ='Transition Charges'!N13 | H20: ='Transition Charges'!O13 | I20: ='Transition Charges'!P13 | K20: =SUM(C20:J20)
B22: Fixed Assets | C22: ='Transition Charges'!F24 | D22: ='Transition Charges'!K24 | E22: ='Transition Charges'!L24 | F22: ='Transition Charges'!M24 | G22: ='Transition Charges'!N24 | H22: ='Transition Charges'!O24 | I22: ='Transition Charges'!P24 | K22: =SUM(C22:J22)
B24: Accounts Payable | C24: ='Transition Charges'!F35 | D24: ='Transition Charges'!K35 | E24: ='Transition Charges'!L35 | F24: ='Transition Charges'!M35 | G24: ='Transition Charges'!N35 | H24: ='Transition Charges'!O35 | I24: ='Transition Charges'!P35 | K24: =SUM(C24:J24)
B26: T&E | C26: ='Transition Charges'!F46 | D26: ='Transition Charges'!K46 | E26: ='Transition Charges'!L46 | F26: ='Transition Charges'!M46 | G26: ='Transition Charges'!N46 | H26: ='Transition Charges'!O46 | I26: ='Transition Charges'!P46 | K26: =SUM(C26:J26)
B28: Order to Cash | C28: ='Transition Charges'!F57 | D28: ='Transition Charges'!K57 | E28: ='Transition Charges'!L57 | F28: ='Transition Charges'!M57 | G28: ='Transition Charges'!N57 | H28: ='Transition Charges'!O57 | I28: ='Transition Charges'!P57 | K28: =SUM(C28:J28)
B30: Requistion to Pay | C30: ='Transition Charges'!F68 | D30: ='Transition Charges'!K68 | E30: ='Transition Charges'!L68 | F30: ='Transition Charges'!M68 | G30: ='Transition Charges'!N68 | H30: ='Transition Charges'!O68 | I30: ='Transition Charges'!P68 | K30: =SUM(C30:J30)
A32: TOTAL TRANSITION CHARGES | C32: =SUM(C20:C31) | D32: =SUM(D20:D31) | E32: =SUM(E20:E31) | F32: =SUM(F20:F31) | G32: =SUM(G20:G31) | H32: =SUM(H20:H31) | I32: =SUM(I20:I31) | J32: =SUM(J20:J31) | K32: =SUM(K20:K31)
A34: TRANSFORMATION CHARGES | C34: Year 1 | D34: Year 2 | E34: Year 3 | F34: Year 4 | G34: Year 5 | H34: Year 6 | I34: Year 7 | J34: Year 8 | K34: Total
B35: General Accounting & Sox | K35: =SUM(C35:J35)
B37: Fixed Assets | K37: =SUM(C37:J37)
B39: Accounts Payable | K39: =SUM(C39:J39)
B41: T&E | K41: =SUM(C41:J41)
B43: Order to Cash | K43: =SUM(C43:J43)
B45: Requistion to Pay | K45: =SUM(C45:J45)
A47: TOTAL TRANSFORMATION CHARGES | C47: =SUM(C35:C46) | D47: =SUM(D35:D46) | E47: =SUM(E35:E46) | F47: =SUM(F35:F46) | G47: =SUM(G35:G46) | H47: =SUM(H35:H46) | I47: =SUM(I35:I46) | J47: =SUM(J35:J46) | K47: =SUM(K35:K46)
A49: TOTAL SUPPLIER CHARGES | C49: =C47+C32+C17 | D49: =D47+D32+D17 | E49: =E47+E32+E17 | F49: =F47+F32+F17 | G49: =G47+G32+G17 | H49: =H47+H32+H17 | I49: =I47+I32+I17 | J49: =J47+J32+J17 | K49: =K47+K32+K17
A51: PASS THROUGH CHARGES | C51: Year 1 | D51: Year 2 | E51: Year 3 | F51: Year 4 | G51: Year 5 | H51: Year 6 | I51: Year 7 | J51: Year 8 | K51: Total
B52: General Accounting & Sox | C52: ='Pass-Thro-Charges'!C5 | D52: ='Pass-Thro-Charges'!D5 | E52: ='Pass-Thro-Charges'!E5 | F52: ='Pass-Thro-Charges'!F5 | G52: ='Pass-Thro-Charges'!G5 | H52: ='Pass-Thro-Charges'!H5 | I52: ='Pass-Thro-Charges'!I5 | J52: ='Pass-Thro-Charges'!J5 | K52: =SUM(C52:J52)
B54: Fixed Assets | C54: ='Pass-Thro-Charges'!C7 | D54: ='Pass-Thro-Charges'!D7 | E54: ='Pass-Thro-Charges'!E7 | F54: ='Pass-Thro-Charges'!F7 | G54: ='Pass-Thro-Charges'!G7 | H54: ='Pass-Thro-Charges'!H7 | I54: ='Pass-Thro-Charges'!I7 | J54: ='Pass-Thro-Charges'!J7 | K54: =SUM(C54:J54)
B56: Accounts Payable | C56: ='Pass-Thro-Charges'!C9 | D56: ='Pass-Thro-Charges'!D9 | E56: ='Pass-Thro-Charges'!E9 | F56: ='Pass-Thro-Charges'!F9 | G56: ='Pass-Thro-Charges'!G9 | H56: ='Pass-Thro-Charges'!H9 | I56: ='Pass-Thro-Charges'!I9 | J56: ='Pass-Thro-Charges'!J9 | K56: =SUM(C56:J56)
B58: T&E | C58: ='Pass-Thro-Charges'!C11 | D58: ='Pass-Thro-Charges'!D11 | E58: ='Pass-Thro-Charges'!E11 | F58: ='Pass-Thro-Charges'!F11 | G58: ='Pass-Thro-Charges'!G11 | H58: ='Pass-Thro-Charges'!H11 | I58: ='Pass-Thro-Charges'!I11 | J58: ='Pass-Thro-Charges'!J11 | K58: =SUM(C58:J58)
B60: Order to Cash | C60: ='Pass-Thro-Charges'!C13 | D60: ='Pass-Thro-Charges'!D13 | E60: ='Pass-Thro-Charges'!E13 | F60: ='Pass-Thro-Charges'!F13 | G60: ='Pass-Thro-Charges'!G13 | H60: ='Pass-Thro-Charges'!H13 | I60: ='Pass-Thro-Charges'!I13 | J60: ='Pass-Thro-Charges'!J13 | K60: =SUM(C60:J60)
B62: Requistion to Pay | C62: ='Pass-Thro-Charges'!C15 | D62: ='Pass-Thro-Charges'!D15 | E62: ='Pass-Thro-Charges'!E15 | F62: ='Pass-Thro-Charges'!F15 | G62: ='Pass-Thro-Charges'!G15 | H62: ='Pass-Thro-Charges'!H15 | I62: ='Pass-Thro-Charges'!I15 | J62: ='Pass-Thro-Charges'!J15 | K62: =SUM(C62:J62)
A64: TOTAL PASS THROUGH | C64: =SUM(C52:C63) | D64: =SUM(D52:D63) | E64: =SUM(E52:E63) | F64: =SUM(F52:F63) | G64: =SUM(G52:G63) | H64: =SUM(H52:H63) | I64: =SUM(I52:I63) | J64: =SUM(J52:J63) | K64: =SUM(K52:K63)
A66: GRAND TOTAL CHARGES | C66: =SUM(C64,C49) | D66: =SUM(D64,D49) | E66: =SUM(E64,E49) | F66: =SUM(F64,F49) | G66: =SUM(G64,G49) | H66: =SUM(H64,H49) | I66: =SUM(I64,I49) | J66: =SUM(J64,J49) | K66: =SUM(K64,K49)
A68: Walk from Nov 21 submission to Jan 17 Submission
A69: Submission as of Nov 21, 2006 | C69: 6423126 | D69: 6050465.6 | E69: 5673577.3 | F69: 5523567.4 | G69: 5467632 | H69: 5289616 | I69: 5192511.4 | J69: 432093.45 | K69: =SUM(C69:J69)
A70: Including Cognos reporting tool and customer portal | C70: 20604.101 | D70: 39473.472 | E70: 37285.654 | F70: 36230.246 | G70: 35568.224 | H70: 34642.202 | I70: 33969.258 | J70: 2826.2749 | K70: =SUM(C70:J70)
A71: Change in workflow solutions | C71: -63615.534 | D71: -157139.73 | E71: -149105.09 | F71: -143393.51 | G71: -143581.23 | H71: -137851.43 | I71: -131535.83 | J71: -10917.461 | K71: =SUM(C71:J71)
A72: Change in PSTN assumptions solutions | C72: -30555.251 | D72: -64130.625 | E72: -58432.987 | F72: -58354.814 | G72: -60769.278 | H72: -58959.149 | I72: -56629.823 | J72: -4702.902 | K72: =SUM(C72:J72)
A73: Price drop | C73: -169498.37 | D73: -459640.1 | E73: -345558.97 | F73: -413115.1 | G73: -523431.99 | H73: -532231.2 | I73: -501541.21 | J73: -41563.03 | K73: =SUM(C73:J73)
A74: Impact of awarding phase2 on phase 1 prices | C74: -49647.523 | D74: -99186.244 | E74: -94524.105 | F74: -90572.996 | G74: -87433.466 | H74: -84075.509 | I74: -82981.887 | J74: -6909.009 | K74: =SUM(C74:J74)
A75: Same scope w/ updated pricing | C75: =SUM(C69:C74) | D75: =SUM(D69:D74) | E75: =SUM(E69:E74) | F75: =SUM(F69:F74) | G75: =SUM(G69:G74) | H75: =SUM(H69:H74) | I75: =SUM(I69:I74) | J75: =SUM(J69:J74) | K75: =SUM(K69:K74)
A76: Change in transition assumptions | C76: -2683735.1 | D76: 1161836.7 | E76: 1108799.7 | F76: 568330.13 | G76: 0 | H76: 0 | I76: 0 | J76: 0 | K76: =SUM(C76:J76)
A77: Adding Scanning & Archiving | C77: 47593.46 | D77: 80988.807 | E77: 75461.434 | F77: 71039.535 | G77: 67944.531 | H77: 66369.772 | I77: 64922.251 | J77: 5400.1353 | K77: =SUM(C77:J77)
A78: Change in Transformation charges | C78: -114500 | D78: 331500 | E78: 194425 | F78: 76229.2 | G78: 76229.2 | H78: 76229.2 | I78: 76229.2 | J78: 84479.2 | K78: =SUM(C78:J78)
A79: Dec 20 Submission | C79: =SUM(C75:C78) | D79: =SUM(D75:D78) | E79: =SUM(E75:E78) | F79: =SUM(F75:F78) | G79: =SUM(G75:G78) | H79: =SUM(H75:H78) | I79: =SUM(I75:I78) | J79: =SUM(J75:J78) | K79: =SUM(K75:K78)
A80: Remove transformation projects | C80: 0 | D80: -340500 | E80: -203425 | F80: -85229.2 | G80: -85229.2 | H80: -85229.2 | I80: -85229.2 | J80: -85229.2 | K80: =SUM(C80:J80)
A81: Change in # Cognos licenses at GlobalPharma (from 10 to 20) | C81: 2045.1652 | D81: 3931.8498 | E81: 3743.3056 | F81: 3583.9425 | G81: 3453.4792 | H81: 3326.1217 | I81: 3286.6124 | J81: 273.66543 | K81: =SUM(C81:J81)
A82: BCP impact | C82: 50784.761 | D82: 97883.598 | E82: 93187.831 | F82: 89219.577 | G82: 85978.836 | H82: 82804.233 | I82: 81812.169 | J82: 6812.1693 | K82: =SUM(C82:J82)
A83: Changes in transition assumptions | C83: -473396.26 | D83: 6066.6667 | E83: 5789.3333 | F83: 2790.6667 | G83: 0 | H83: 0 | I83: 0 | J83: 0 | K83: =SUM(C83:J83)
A84: 3% inflation impact included | C84: 0 | D84: 148868.86 | E84: 287993.16 | F84: 420165.22 | G84: 548973.75 | H84: 669927.82 | I84: 805610.49 | J84: 79456.443 | K84: =SUM(C84:J84)
A85: Current Submission | C85: =SUM(C79:C84) | D85: =SUM(D79:D84) | E85: =SUM(E79:E84) | F85: =SUM(F79:F84) | G85: =SUM(G79:G84) | H85: =SUM(H79:H84) | I85: =SUM(I79:I84) | J85: =SUM(J79:J84) | K85: =SUM(K79:K84)
A89: Walk from Dec 18 submission to Jan 17 Submission
A90: Submission as of Dec 18, 2006 | C90: 3476790 | D90: 7097413.3 | E90: 6603790.9 | F90: 5802724.3 | G90: 5126028.1 | H90: 4988801.7 | I90: 4903772.1 | J90: 752994.33 | K90: =SUM(C90:J90)
A91: Impact of awarding phase2 on phase 1 prices | C91: -49652.087 | D91: -99193.467 | E91: -94531.032 | F91: -90579.66 | G91: -87439.866 | H91: -84081.671 | I91: -82988.03 | J91: -6909.5208 | K91: =SUM(C91:J91)
A92: Change in unit rates | C92: -26657.222 | D92: -55366.061 | E92: -52426.061 | F92: -66683.964 | G92: -65243.353 | H92: -63288.837 | I92: -62470.905 | J92: -5200.9749 | K92: =SUM(C92:J92)
A93: Change in productivity commitment | C93: 0 | D93: 0 | E93: 40754.795 | F93: -30150.715 | G93: -108608.77 | H93: -156173.14 | I93: -132295.81 | J93: -17159.368 | K93: =SUM(C93:J93)
A94: Transition cost saving | C94: -8834.8 | D94: -21018.4 | E94: -20061.6 | F94: -11440 | G94: 0 | H94: 0 | I94: 0 | J94: 0 | K94: =SUM(C94:J94)
A95: Modified PSTN assumptions | C95: -19874.099 | D95: -37667.5 | E95: -35599.078 | F95: -33909.891 | G95: -32578.203 | H95: -31518.094 | I95: -31074.062 | J95: -2586.7969 | K95: =SUM(C95:J95)
A96: Pass-through corrections | C96: 8000 | D96: 0 | E96: 0 | F96: 0 | G96: 0 | H96: 0 | I96: 0 | J96: -260431.01 | K96: =SUM(C96:J96)
A97: Dec 20 Submission | C97: =SUM(C90:C96) | D97: =SUM(D90:D96) | E97: =SUM(E90:E96) | F97: =SUM(F90:F96) | G97: =SUM(G90:G96) | H97: =SUM(H90:H96) | I97: =SUM(I90:I96) | J97: =SUM(J90:J96) | K97: =SUM(K90:K96)
A98: Remove transformation projects | C98: =C80 | D98: =D80 | E98: =E80 | F98: =F80 | G98: =G80 | H98: =H80 | I98: =I80 | J98: =J80 | K98: =SUM(C98:J98)
A99: Change in # Cognos licenses at GlobalPharma (from 10 to 20) | C99: =C81 | D99: =D81 | E99: =E81 | F99: =F81 | G99: =G81 | H99: =H81 | I99: =I81 | J99: =J81 | K99: =SUM(C99:J99)
A100: BCP impact | C100: =C82 | D100: =D82 | E100: =E82 | F100: =F82 | G100: =G82 | H100: =H82 | I100: =I82 | J100: =J82 | K100: =SUM(C100:J100)
A101: Changes in transition assumptions | C101: =C83 | D101: =D83 | E101: =E83 | F101: =F83 | G101: =G83 | H101: =H83 | I101: =I83 | J101: =J83 | K101: =SUM(C101:J101)
A102: 3% inflation impact included | C102: =C84 | D102: =D84 | E102: =E84 | F102: =F84 | G102: =G84 | H102: =H84 | I102: =I84 | J102: =J84 | K102: =SUM(C102:J102)
A103: Current Submission | C103: =SUM(C97:C102) | D103: =SUM(D97:D102) | E103: =SUM(E97:E102) | F103: =SUM(F97:F102) | G103: =SUM(G97:G102) | H103: =SUM(H97:H102) | I103: =SUM(I97:I102) | J103: =SUM(J97:J102) | K103: =SUM(K97:K102)

Sheet Consolidated Base Charges
A1: CONSOLIDATED BASE CHARGE SUMMARY (US$)
A2: Consolidated | C2: Year 1 | D2: Year 2 | E2: Year 3 | F2: Year 4 | G2: Year 5 | H2: Year 6 | I2: Year 7 | J2: Year 8
B3: Consolidated Summary
B4: Switzerland | C4: =C14+C24 | D4: =D14+D24 | E4: =E14+E24 | F4: =F14+F24 | G4: =G14+G24 | H4: =H14+H24 | I4: =I14+I24 | J4: =J14+J24
B5: United States | C5: =C15+C25 | D5: =D15+D25 | E5: =E15+E25 | F5: =F15+F25 | G5: =G15+G25 | H5: =H15+H25 | I5: =I15+I25 | J5: =J15+J25
B6: France | C6: =C16+C26 | D6: =D16+D26 | E6: =E16+E26 | F6: =F16+F26 | G6: =G16+G26 | H6: =H16+H26 | I6: =I16+I26 | J6: =J16+J26
B7: Germany | C7: =C17+C27 | D7: =D17+D27 | E7: =E17+E27 | F7: =F17+F27 | G7: =G17+G27 | H7: =H17+H27 | I7: =I17+I27 | J7: =J17+J27
B8: Germany Production | C8: =C18+C28 | D8: =D18+D28 | E8: =E18+E28 | F8: =F18+F28 | G8: =G18+G28 | H8: =H18+H28 | I8: =I18+I28 | J8: =J18+J28
B9: Spain | C9: =C19+C29 | D9: =D19+D29 | E9: =E19+E29 | F9: =F19+F29 | G9: =G19+G29 | H9: =H19+H29 | I9: =I19+I29 | J9: =J19+J29
B10: Italy | C10: =C20+C30 | D10: =D20+D30 | E10: =E20+E30 | F10: =F20+F30 | G10: =G20+G30 | H10: =H20+H30 | I10: =I20+I30 | J10: =J20+J30
B11: United Kingdom | C11: =C21+C31 | D11: =D21+D31 | E11: =E21+E31 | F11: =F21+F31 | G11: =G21+G31 | H11: =H21+H31 | I11: =I21+I31 | J11: =J21+J31
B12: Total Base Charges All Countries | C12: =SUM(C4:C11) | D12: =SUM(D4:D11) | E12: =SUM(E4:E11) | F12: =SUM(F4:F11) | G12: =SUM(G4:G11) | H12: =SUM(H4:H11) | I12: =SUM(I4:I11) | J12: =SUM(J4:J11)
B13: Centre One Summary
B14: Switzerland | C14: =+'Centre One-BC'!C73 | D14: =+'Centre One-BC'!D73 | E14: =+'Centre One-BC'!E73 | F14: =+'Centre One-BC'!F73 | G14: =+'Centre One-BC'!G73 | H14: =+'Centre One-BC'!H73 | I14: =+'Centre One-BC'!I73 | J14: =+'Centre One-BC'!J73
B15: United States | C15: =+'Centre One-BC'!C74 | D15: =+'Centre One-BC'!D74 | E15: =+'Centre One-BC'!E74 | F15: =+'Centre One-BC'!F74 | G15: =+'Centre One-BC'!G74 | H15: =+'Centre One-BC'!H74 | I15: =+'Centre One-BC'!I74 | J15: =+'Centre One-BC'!J74
B16: France | C16: =+'Centre One-BC'!C75 | D16: =+'Centre One-BC'!D75 | E16: =+'Centre One-BC'!E75 | F16: =+'Centre One-BC'!F75 | G16: =+'Centre One-BC'!G75 | H16: =+'Centre One-BC'!H75 | I16: =+'Centre One-BC'!I75 | J16: =+'Centre One-BC'!J75
B17: Germany | C17: =+'Centre One-BC'!C76 | D17: =+'Centre One-BC'!D76 | E17: =+'Centre One-BC'!E76 | F17: =+'Centre One-BC'!F76 | G17: =+'Centre One-BC'!G76 | H17: =+'Centre One-BC'!H76 | I17: =+'Centre One-BC'!I76 | J17: =+'Centre One-BC'!J76
B18: Germany Production | C18: =+'Centre One-BC'!C77 | D18: =+'Centre One-BC'!D77 | E18: =+'Centre One-BC'!E77 | F18: =+'Centre One-BC'!F77 | G18: =+'Centre One-BC'!G77 | H18: =+'Centre One-BC'!H77 | I18: =+'Centre One-BC'!I77 | J18: =+'Centre One-BC'!J77
B19: Spain | C19: =+'Centre One-BC'!C78 | D19: =+'Centre One-BC'!D78 | E19: =+'Centre One-BC'!E78 | F19: =+'Centre One-BC'!F78 | G19: =+'Centre One-BC'!G78 | H19: =+'Centre One-BC'!H78 | I19: =+'Centre One-BC'!I78 | J19: =+'Centre One-BC'!J78
B20: Italy | C20: =+'Centre One-BC'!C79 | D20: =+'Centre One-BC'!D79 | E20: =+'Centre One-BC'!E79 | F20: =+'Centre One-BC'!F79 | G20: =+'Centre One-BC'!G79 | H20: =+'Centre One-BC'!H79 | I20: =+'Centre One-BC'!I79 | J20: =+'Centre One-BC'!J79
B21: United Kingdom | C21: =+'Centre One-BC'!C80 | D21: =+'Centre One-BC'!D80 | E21: =+'Centre One-BC'!E80 | F21: =+'Centre One-BC'!F80 | G21: =+'Centre One-BC'!G80 | H21: =+'Centre One-BC'!H80 | I21: =+'Centre One-BC'!I80 | J21: =+'Centre One-BC'!J80
B22: Total Base Charges - Centre One | C22: =SUM(C14:C21) | D22: =SUM(D14:D21) | E22: =SUM(E14:E21) | F22: =SUM(F14:F21) | G22: =SUM(G14:G21) | H22: =SUM(H14:H21) | I22: =SUM(I14:I21) | J22: =SUM(J14:J21)
B23: Centre Two Summary
B24: Switzerland | C24: =+'Centre Two-BC'!C73 | D24: =+'Centre Two-BC'!D73 | E24: =+'Centre Two-BC'!E73 | F24: =+'Centre Two-BC'!F73 | G24: =+'Centre Two-BC'!G73 | H24: =+'Centre Two-BC'!H73 | I24: =+'Centre Two-BC'!I73 | J24: =+'Centre Two-BC'!J73
B25: United States | C25: =+'Centre Two-BC'!C74 | D25: =+'Centre Two-BC'!D74 | E25: =+'Centre Two-BC'!E74 | F25: =+'Centre Two-BC'!F74 | G25: =+'Centre Two-BC'!G74 | H25: =+'Centre Two-BC'!H74 | I25: =+'Centre Two-BC'!I74 | J25: =+'Centre Two-BC'!J74
B26: France | C26: =+'Centre Two-BC'!C75 | D26: =+'Centre Two-BC'!D75 | E26: =+'Centre Two-BC'!E75 | F26: =+'Centre Two-BC'!F75 | G26: =+'Centre Two-BC'!G75 | H26: =+'Centre Two-BC'!H75 | I26: =+'Centre Two-BC'!I75 | J26: =+'Centre Two-BC'!J75
B27: Germany | C27: =+'Centre Two-BC'!C76 | D27: =+'Centre Two-BC'!D76 | E27: =+'Centre Two-BC'!E76 | F27: =+'Centre Two-BC'!F76 | G27: =+'Centre Two-BC'!G76 | H27: =+'Centre Two-BC'!H76 | I27: =+'Centre Two-BC'!I76 | J27: =+'Centre Two-BC'!J76
B28: Germany Production | C28: =+'Centre Two-BC'!C77 | D28: =+'Centre Two-BC'!D77 | E28: =+'Centre Two-BC'!E77 | F28: =+'Centre Two-BC'!F77 | G28: =+'Centre Two-BC'!G77 | H28: =+'Centre Two-BC'!H77 | I28: =+'Centre Two-BC'!I77 | J28: =+'Centre Two-BC'!J77
B29: Spain | C29: =+'Centre Two-BC'!C78 | D29: =+'Centre Two-BC'!D78 | E29: =+'Centre Two-BC'!E78 | F29: =+'Centre Two-BC'!F78 | G29: =+'Centre Two-BC'!G78 | H29: =+'Centre Two-BC'!H78 | I29: =+'Centre Two-BC'!I78 | J29: =+'Centre Two-BC'!J78
B30: Italy | C30: =+'Centre Two-BC'!C79 | D30: =+'Centre Two-BC'!D79 | E30: =+'Centre Two-BC'!E79 | F30: =+'Centre Two-BC'!F79 | G30: =+'Centre Two-BC'!G79 | H30: =+'Centre Two-BC'!H79 | I30: =+'Centre Two-BC'!I79 | J30: =+'Centre Two-BC'!J79
B31: United Kingdom | C31: =+'Centre Two-BC'!C80 | D31: =+'Centre Two-BC'!D80 | E31: =+'Centre Two-BC'!E80 | F31: =+'Centre Two-BC'!F80 | G31: =+'Centre Two-BC'!G80 | H31: =+'Centre Two-BC'!H80 | I31: =+'Centre Two-BC'!I80 | J31: =+'Centre Two-BC'!J80
B32: Total Base Charges - Centre Two | C32: =SUM(C24:C31) | D32: =SUM(D24:D31) | E32: =SUM(E24:E31) | F32: =SUM(F24:F31) | G32: =SUM(G24:G31) | H32: =SUM(H24:H31) | I32: =SUM(I24:I31) | J32: =SUM(J24:J31)
B33: Process Summary
B34: General Accounting & Sox
B35: Centre One | C35: ='Centre One-BC'!$C$20 | D35: ='Centre One-BC'!$D$20 | E35: ='Centre One-BC'!$E$20 | F35: ='Centre One-BC'!$F$20 | G35: ='Centre One-BC'!$G$20 | H35: ='Centre One-BC'!$H$20 | I35: ='Centre One-BC'!$I$20 | J35: ='Centre One-BC'!$J$20
B36: Centre Two | C36: ='Centre Two-BC'!$C$20 | D36: ='Centre Two-BC'!$D$20 | E36: ='Centre Two-BC'!$E$20 | F36: ='Centre Two-BC'!$F$20 | G36: ='Centre Two-BC'!$G$20 | H36: ='Centre Two-BC'!$H$20 | I36: ='Centre Two-BC'!$I$20 | J36: ='Centre Two-BC'!$J$20
B37: Sub Total | C37: =SUM(C35:C36) | D37: =SUM(D35:D36) | E37: =SUM(E35:E36) | F37: =SUM(F35:F36) | G37: =SUM(G35:G36) | H37: =SUM(H35:H36) | I37: =SUM(I35:I36) | J37: =SUM(J35:J36)
B38: Fixed Assets
B39: Centre One | C39: ='Centre One-BC'!$C$30 | D39: ='Centre One-BC'!$D$30 | E39: ='Centre One-BC'!$E$30 | F39: ='Centre One-BC'!$F$30 | G39: ='Centre One-BC'!$G$30 | H39: ='Centre One-BC'!$H$30 | I39: ='Centre One-BC'!$I$30 | J39: ='Centre One-BC'!$J$30
B40: Centre Two | C40: ='Centre Two-BC'!$C$30 | D40: ='Centre Two-BC'!$D$30 | E40: ='Centre Two-BC'!$E$30 | F40: ='Centre Two-BC'!$F$30 | G40: ='Centre Two-BC'!$G$30 | H40: ='Centre Two-BC'!$H$30 | I40: ='Centre Two-BC'!$I$30 | J40: ='Centre Two-BC'!$J$30
B41: Sub Total | C41: =SUM(C39:C40) | D41: =SUM(D39:D40) | E41: =SUM(E39:E40) | F41: =SUM(F39:F40) | G41: =SUM(G39:G40) | H41: =SUM(H39:H40) | I41: =SUM(I39:I40) | J41: =SUM(J39:J40)
B42: Accounts Payable
B43: Centre One | C43: ='Centre One-BC'!$C$40 | D43: ='Centre One-BC'!$D$40 | E43: ='Centre One-BC'!$E$40 | F43: ='Centre One-BC'!$F$40 | G43: ='Centre One-BC'!$G$40 | H43: ='Centre One-BC'!$H$40 | I43: ='Centre One-BC'!$I$40 | J43: ='Centre One-BC'!$J$40
B44: Centre Two | C44: ='Centre Two-BC'!$C$40 | D44: ='Centre Two-BC'!$D$40 | E44: ='Centre Two-BC'!$E$40 | F44: ='Centre Two-BC'!$F$40 | G44: ='Centre Two-BC'!$G$40 | H44: ='Centre Two-BC'!$H$40 | I44: ='Centre Two-BC'!$I$40 | J44: ='Centre Two-BC'!$J$40
B45: Sub Total | C45: =SUM(C43:C44) | D45: =SUM(D43:D44) | E45: =SUM(E43:E44) | F45: =SUM(F43:F44) | G45: =SUM(G43:G44) | H45: =SUM(H43:H44) | I45: =SUM(I43:I44) | J45: =SUM(J43:J44)
B46: T&E
B47: Centre One | C47: ='Centre One-BC'!$C$50 | D47: ='Centre One-BC'!$D$50 | E47: ='Centre One-BC'!$E$50 | F47: ='Centre One-BC'!$F$50 | G47: ='Centre One-BC'!$G$50 | H47: ='Centre One-BC'!$H$50 | I47: ='Centre One-BC'!$I$50 | J47: ='Centre One-BC'!$J$50
B48: Centre Two | C48: ='Centre Two-BC'!$C$50 | D48: ='Centre Two-BC'!$D$50 | E48: ='Centre Two-BC'!$E$50 | F48: ='Centre Two-BC'!$F$50 | G48: ='Centre Two-BC'!$G$50 | H48: ='Centre Two-BC'!$H$50 | I48: ='Centre Two-BC'!$I$50 | J48: ='Centre Two-BC'!$J$50
B49: Sub Total | C49: =SUM(C47:C48) | D49: =SUM(D47:D48) | E49: =SUM(E47:E48) | F49: =SUM(F47:F48) | G49: =SUM(G47:G48) | H49: =SUM(H47:H48) | I49: =SUM(I47:I48) | J49: =SUM(J47:J48)
B50: Order to Cash
B51: Centre One | C51: ='Centre One-BC'!$C$60 | D51: ='Centre One-BC'!$D$60 | E51: ='Centre One-BC'!$E$60 | F51: ='Centre One-BC'!$F$60 | G51: ='Centre One-BC'!$G$60 | H51: ='Centre One-BC'!$H$60 | I51: ='Centre One-BC'!$I$60 | J51: ='Centre One-BC'!$J$60
B52: Centre Two | C52: ='Centre Two-BC'!$C$60 | D52: ='Centre Two-BC'!$D$60 | E52: ='Centre Two-BC'!$E$60 | F52: ='Centre Two-BC'!$F$60 | G52: ='Centre Two-BC'!$G$60 | H52: ='Centre Two-BC'!$H$60 | I52: ='Centre Two-BC'!$I$60 | J52: ='Centre Two-BC'!$J$60
B53: Sub Total | C53: =SUM(C51:C52) | D53: =SUM(D51:D52) | E53: =SUM(E51:E52) | F53: =SUM(F51:F52) | G53: =SUM(G51:G52) | H53: =SUM(H51:H52) | I53: =SUM(I51:I52) | J53: =SUM(J51:J52)
B54: Requistion to Pay
B55: Centre One | C55: ='Centre One-BC'!$C$70 | D55: ='Centre One-BC'!$D$70 | E55: ='Centre One-BC'!$E$70 | F55: ='Centre One-BC'!$F$70 | G55: ='Centre One-BC'!$G$70 | H55: ='Centre One-BC'!$H$70 | I55: ='Centre One-BC'!$I$70 | J55: ='Centre One-BC'!$J$70
B56: Centre Two | C56: ='Centre Two-BC'!$C$70 | D56: ='Centre Two-BC'!$D$70 | E56: ='Centre Two-BC'!$E$70 | F56: ='Centre Two-BC'!$F$70 | G56: ='Centre Two-BC'!$G$70 | H56: ='Centre Two-BC'!$H$70 | I56: ='Centre Two-BC'!$I$70 | J56: ='Centre Two-BC'!$J$70
B57: Sub Total | C57: =SUM(C55:C56) | D57: =SUM(D55:D56) | E57: =SUM(E55:E56) | F57: =SUM(F55:F56) | G57: =SUM(G55:G56) | H57: =SUM(H55:H56) | I57: =SUM(I55:I56) | J57: =SUM(J55:J56)
B58: Total Base Charges All Countries | C58: =C37+C41+C45+C49+C53+C57 | D58: =D37+D41+D45+D49+D53+D57 | E58: =E37+E41+E45+E49+E53+E57 | F58: =F37+F41+F45+F49+F53+F57 | G58: =G37+G41+G45+G49+G53+G57 | H58: =H37+H41+H45+H49+H53+H57 | I58: =I37+I41+I45+I49+I53+I57 | J58: =J37+J41+J45+J49+J53+J57

Sheet Pass-Thro-Charges
A1: PASS THROUGH CHARGES (US$)
B3: Category of Service | C3: Year 1 | D3: Year 2 | E3: Year 3 | F3: Year 4 | G3: Year 5 | H3: Year 6 | I3: Year 7 | J3: Year 8 | K3: Total
B5: General Accounting & Sox | C5: =SUM(C23,C41,C59,C77,C95) | D5: =SUM(D23,D41,D59,D77,D95) | E5: =SUM(E23,E41,E59,E77,E95) | F5: =SUM(F23,F41,F59,F77,F95) | G5: =SUM(G23,G41,G59,G77,G95) | H5: =SUM(H23,H41,H59,H77,H95) | I5: =SUM(I23,I41,I59,I77,I95) | J5: =SUM(J23,J41,J59,J77,J95) | K5: =SUM(C5:J5)
B7: Fixed Assets | C7: =SUM(C25,C43,C61,C79,C97) | D7: =SUM(D25,D43,D61,D79,D97) | E7: =SUM(E25,E43,E61,E79,E97) | F7: =SUM(F25,F43,F61,F79,F97) | G7: =SUM(G25,G43,G61,G79,G97) | H7: =SUM(H25,H43,H61,H79,H97) | I7: =SUM(I25,I43,I61,I79,I97) | J7: =SUM(J25,J43,J61,J79,J97) | K7: =SUM(C7:J7)
B9: Accounts Payable | C9: =SUM(C27,C45,C63,C81,C99) | D9: =SUM(D27,D45,D63,D81,D99) | E9: =SUM(E27,E45,E63,E81,E99) | F9: =SUM(F27,F45,F63,F81,F99) | G9: =SUM(G27,G45,G63,G81,G99) | H9: =SUM(H27,H45,H63,H81,H99) | I9: =SUM(I27,I45,I63,I81,I99) | J9: =SUM(J27,J45,J63,J81,J99) | K9: =SUM(C9:J9)
B11: T&E | C11: =SUM(C29,C47,C65,C83,C101) | D11: =SUM(D29,D47,D65,D83,D101) | E11: =SUM(E29,E47,E65,E83,E101) | F11: =SUM(F29,F47,F65,F83,F101) | G11: =SUM(G29,G47,G65,G83,G101) | H11: =SUM(H29,H47,H65,H83,H101) | I11: =SUM(I29,I47,I65,I83,I101) | J11: =SUM(J29,J47,J65,J83,J101) | K11: =SUM(C11:J11)
B13: Order to Cash | C13: =SUM(C31,C49,C67,C85,C103) | D13: =SUM(D31,D49,D67,D85,D103) | E13: =SUM(E31,E49,E67,E85,E103) | F13: =SUM(F31,F49,F67,F85,F103) | G13: =SUM(G31,G49,G67,G85,G103) | H13: =SUM(H31,H49,H67,H85,H103) | I13: =SUM(I31,I49,I67,I85,I103) | J13: =SUM(J31,J49,J67,J85,J103) | K13: =SUM(C13:J13)
B15: Requistion to Pay | C15: =SUM(C33,C51,C69,C87,C105) | D15: =SUM(D33,D51,D69,D87,D105) | E15: =SUM(E33,E51,E69,E87,E105) | F15: =SUM(F33,F51,F69,F87,F105) | G15: =SUM(G33,G51,G69,G87,G105) | H15: =SUM(H33,H51,H69,H87,H105) | I15: =SUM(I33,I51,I69,I87,I105) | J15: =SUM(J33,J51,J69,J87,J105) | K15: =SUM(C15:J15)
A17: TOTAL INVESTMENTS | C17: =SUM(C4:C16) | D17: =SUM(D4:D16) | E17: =SUM(E4:E16) | F17: =SUM(F4:F16) | G17: =SUM(G4:G16) | H17: =SUM(H4:H16) | I17: =SUM(I4:I16) | J17: =SUM(J4:J16) | K17: =SUM(K4:K16)
A20: Pass through -PSTN
B21: Category of Service | C21: Year 1 | D21: Year 2 | E21: Year 3 | F21: Year 4 | G21: Year 5 | H21: Year 6 | I21: Year 7 | J21: Year 8 | K21: Total
B23: General Accounting & Sox | C23: ='Pass-Thro-Charges'!$F174*'Consolidated FTE '!C37 | D23: ='Pass-Thro-Charges'!$F174*'Consolidated FTE '!D37 | E23: ='Pass-Thro-Charges'!$F174*'Consolidated FTE '!E37 | F23: ='Pass-Thro-Charges'!$F174*'Consolidated FTE '!F37 | G23: ='Pass-Thro-Charges'!$F174*'Consolidated FTE '!G37 | H23: ='Pass-Thro-Charges'!$F174*'Consolidated FTE '!H37 | I23: ='Pass-Thro-Charges'!$F174*'Consolidated FTE '!I37 | J23: ='Pass-Thro-Charges'!$F174*'Consolidated FTE '!J37/12 | K23: =SUM(C23:J23)
B25: Fixed Assets | C25: ='Pass-Thro-Charges'!$F176*'Consolidated FTE '!C41 | D25: ='Pass-Thro-Charges'!$F176*'Consolidated FTE '!D41 | E25: ='Pass-Thro-Charges'!$F176*'Consolidated FTE '!E41 | F25: ='Pass-Thro-Charges'!$F176*'Consolidated FTE '!F41 | G25: ='Pass-Thro-Charges'!$F176*'Consolidated FTE '!G41 | H25: ='Pass-Thro-Charges'!$F176*'Consolidated FTE '!H41 | I25: ='Pass-Thro-Charges'!$F176*'Consolidated FTE '!I41 | J25: ='Pass-Thro-Charges'!$F176*'Consolidated FTE '!J41/12 | K25: =SUM(C25:J25)
B27: Accounts Payable | C27: ='Pass-Thro-Charges'!$F178*'Consolidated FTE '!C45 | D27: ='Pass-Thro-Charges'!$F178*'Consolidated FTE '!D45 | E27: ='Pass-Thro-Charges'!$F178*'Consolidated FTE '!E45 | F27: ='Pass-Thro-Charges'!$F178*'Consolidated FTE '!F45 | G27: ='Pass-Thro-Charges'!$F178*'Consolidated FTE '!G45 | H27: ='Pass-Thro-Charges'!$F178*'Consolidated FTE '!H45 | I27: ='Pass-Thro-Charges'!$F178*'Consolidated FTE '!I45 | J27: ='Pass-Thro-Charges'!$F178*'Consolidated FTE '!J45/12 | K27: =SUM(C27:J27)
B29: T&E | C29: ='Pass-Thro-Charges'!$F180*'Consolidated FTE '!C49 | D29: ='Pass-Thro-Charges'!$F180*'Consolidated FTE '!D49 | E29: ='Pass-Thro-Charges'!$F180*'Consolidated FTE '!E49 | F29: ='Pass-Thro-Charges'!$F180*'Consolidated FTE '!F49 | G29: ='Pass-Thro-Charges'!$F180*'Consolidated FTE '!G49 | H29: ='Pass-Thro-Charges'!$F180*'Consolidated FTE '!H49 | I29: ='Pass-Thro-Charges'!$F180*'Consolidated FTE '!I49 | J29: ='Pass-Thro-Charges'!$F180*'Consolidated FTE '!J49/12 | K29: =SUM(C29:J29)
B31: Order to Cash | C31: ='Pass-Thro-Charges'!$F182*'Consolidated FTE '!C53 | D31: ='Pass-Thro-Charges'!$F182*'Consolidated FTE '!D53 | E31: ='Pass-Thro-Charges'!$F182*'Consolidated FTE '!E53 | F31: ='Pass-Thro-Charges'!$F182*'Consolidated FTE '!F53 | G31: ='Pass-Thro-Charges'!$F182*'Consolidated FTE '!G53 | H31: ='Pass-Thro-Charges'!$F182*'Consolidated FTE '!H53 | I31: ='Pass-Thro-Charges'!$F182*'Consolidated FTE '!I53 | J31: ='Pass-Thro-Charges'!$F182*'Consolidated FTE '!J53/12 | K31: =SUM(C31:J31)
B33: Requistion to Pay | C33: ='Pass-Thro-Charges'!$F184*'Consolidated FTE '!C57 | D33: ='Pass-Thro-Charges'!$F184*'Consolidated FTE '!D57 | E33: ='Pass-Thro-Charges'!$F184*'Consolidated FTE '!E57 | F33: ='Pass-Thro-Charges'!$F184*'Consolidated FTE '!F57 | G33: ='Pass-Thro-Charges'!$F184*'Consolidated FTE '!G57 | H33: ='Pass-Thro-Charges'!$F184*'Consolidated FTE '!H57 | I33: ='Pass-Thro-Charges'!$F184*'Consolidated FTE '!I57 | J33: ='Pass-Thro-Charges'!$F184*'Consolidated FTE '!J57/12 | K33: =SUM(C33:J33)
A35: TOTAL INVESTMENTS | C35: =SUM(C22:C34) | D35: =SUM(D22:D34) | E35: =SUM(E22:E34) | F35: =SUM(F22:F34) | G35: =SUM(G22:G34) | H35: =SUM(H22:H34) | I35: =SUM(I22:I34) | J35: =SUM(J22:J34) | K35: =SUM(K22:K34)
A38: Pass through -Workflow
B39: Category of Service | C39: Year 1 | D39: Year 2 | E39: Year 3 | F39: Year 4 | G39: Year 5 | H39: Year 6 | I39: Year 7 | J39: Year 8 | K39: Total
B41: General Accounting & Sox | C41: 0 | D41: 0 | E41: 0 | F41: 0 | G41: 0 | H41: 0 | I41: 0 | J41: 0 | K41: =SUM(C41:J41)
B43: Fixed Assets | C43: 0 | D43: 0 | E43: 0 | F43: 0 | G43: 0 | H43: 0 | I43: 0 | J43: 0 | K43: =SUM(C43:J43)
B45: Accounts Payable | C45: =C110 | D45: =D110 | E45: =E110 | F45: =F110 | G45: =G110 | H45: =H110 | I45: =I110 | J45: =J110 | K45: =SUM(C45:J45)
B47: T&E | C47: 0 | D47: 0 | E47: 0 | F47: 0 | G47: 0 | H47: 0 | I47: 0 | J47: 0 | K47: =SUM(C47:J47)
B49: Order to Cash | C49: 0 | D49: 0 | E49: 0 | F49: 0 | G49: 0 | H49: 0 | I49: 0 | J49: 0 | K49: =SUM(C49:J49)
B51: Requistion to Pay | C51: 0 | D51: 0 | E51: 0 | F51: 0 | G51: 0 | H51: 0 | I51: 0 | J51: 0 | K51: =SUM(C51:J51)
A53: TOTAL INVESTMENTS | C53: =SUM(C40:C52) | D53: =SUM(D40:D52) | E53: =SUM(E40:E52) | F53: =SUM(F40:F52) | G53: =SUM(G40:G52) | H53: =SUM(H40:H52) | I53: =SUM(I40:I52) | J53: =SUM(J40:J52) | K53: =SUM(K40:K52)
A56: Pass through -Scanning and Archiving
B57: Category of Service | C57: Year 1 | D57: Year 2 | E57: Year 3 | F57: Year 4 | G57: Year 5 | H57: Year 6 | I57: Year 7 | J57: Year 8 | K57: Total
B59: General Accounting & Sox | C59: 0 | D59: 0 | E59: 0 | F59: 0 | G59: 0 | H59: 0 | I59: 0 | J59: 0 | K59: =SUM(C59:J59)
B61: Fixed Assets | C61: 0 | D61: 0 | E61: 0 | F61: 0 | G61: 0 | H61: 0 | I61: 0 | J61: 0 | K61: =SUM(C61:J61)
B63: Accounts Payable | C63: =C143+C152+C126 | D63: =D143+D152 | E63: =E143+E152 | F63: =F143+F152 | G63: =G143+G152 | H63: =H143+H152 | I63: =I143+I152 | J63: =J143+J152 | K63: =SUM(C63:J63)
B65: T&E | C65: =C146 | D65: =D146 | E65: =E146 | F65: =F146 | G65: =G146 | H65: =H146 | I65: =I146 | J65: =J146 | K65: =SUM(C65:J65)
B67: Order to Cash | C67: 0 | D67: 0 | E67: 0 | F67: 0 | G67: 0 | H67: 0 | I67: 0 | J67: 0 | K67: =SUM(C67:J67)
B69: Requistion to Pay | C69: 0 | D69: 0 | E69: 0 | F69: 0 | G69: 0 | H69: 0 | I69: 0 | J69: 0 | K69: =SUM(C69:J69)
A71: TOTAL INVESTMENTS | C71: =SUM(C58:C70) | D71: =SUM(D58:D70) | E71: =SUM(E58:E70) | F71: =SUM(F58:F70) | G71: =SUM(G58:G70) | H71: =SUM(H58:H70) | I71: =SUM(I58:I70) | J71: =SUM(J58:J70) | K71: =SUM(K58:K70)
A74: Pass through -MPLS connection
B75: Category of Service | C75: Year 1 | D75: Year 2 | E75: Year 3 | F75: Year 4 | G75: Year 5 | H75: Year 6 | I75: Year 7 | J75: Year 8 | K75: Total
B77: General Accounting & Sox | C77: =$C$156*$C$158*'Centre One-FTE'!C4+'Pass-Thro-Charges'!$C$157*'Pass-Thro-Charges'!$C$158*'Centre Two-FTE'!C4 | D77: =$C$156*$C$158*'Centre One-FTE'!D4+'Pass-Thro-Charges'!$C$157*'Pass-Thro-Charges'!$C$158*'Centre Two-FTE'!D4 | E77: =$C$156*$C$158*'Centre One-FTE'!E4+'Pass-Thro-Charges'!$C$157*'Pass-Thro-Charges'!$C$158*'Centre Two-FTE'!E4 | F77: =$C$156*$C$158*'Centre One-FTE'!F4+'Pass-Thro-Charges'!$C$157*'Pass-Thro-Charges'!$C$158*'Centre Two-FTE'!F4 | G77: =$C$156*$C$158*'Centre One-FTE'!G4+'Pass-Thro-Charges'!$C$157*'Pass-Thro-Charges'!$C$158*'Centre Two-FTE'!G4 | H77: =$C$156*$C$158*'Centre One-FTE'!H4+'Pass-Thro-Charges'!$C$157*'Pass-Thro-Charges'!$C$158*'Centre Two-FTE'!H4 | I77: =$C$156*$C$158*'Centre One-FTE'!I4+'Pass-Thro-Charges'!$C$157*'Pass-Thro-Charges'!$C$158*'Centre Two-FTE'!I4 | J77: =($C$156*$C$158*'Centre One-FTE'!J4+'Pass-Thro-Charges'!$C$157*'Pass-Thro-Charges'!$C$158*'Centre Two-FTE'!J4)/12 | K77: =SUM(C77:J77)
J78: 0
B79: Fixed Assets | C79: =$C$156*$C$158*'Centre One-FTE'!C5+'Pass-Thro-Charges'!$C$157*'Pass-Thro-Charges'!$C$158*'Centre Two-FTE'!C5 | D79: =$C$156*$C$158*'Centre One-FTE'!D5+'Pass-Thro-Charges'!$C$157*'Pass-Thro-Charges'!$C$158*'Centre Two-FTE'!D5 | E79: =$C$156*$C$158*'Centre One-FTE'!E5+'Pass-Thro-Charges'!$C$157*'Pass-Thro-Charges'!$C$158*'Centre Two-FTE'!E5 | F79: =$C$156*$C$158*'Centre One-FTE'!F5+'Pass-Thro-Charges'!$C$157*'Pass-Thro-Charges'!$C$158*'Centre Two-FTE'!F5 | G79: =$C$156*$C$158*'Centre One-FTE'!G5+'Pass-Thro-Charges'!$C$157*'Pass-Thro-Charges'!$C$158*'Centre Two-FTE'!G5 | H79: =$C$156*$C$158*'Centre One-FTE'!H5+'Pass-Thro-Charges'!$C$157*'Pass-Thro-Charges'!$C$158*'Centre Two-FTE'!H5 | I79: =$C$156*$C$158*'Centre One-FTE'!I5+'Pass-Thro-Charges'!$C$157*'Pass-Thro-Charges'!$C$158*'Centre Two-FTE'!I5 | J79: =($C$156*$C$158*'Centre One-FTE'!J5+'Pass-Thro-Charges'!$C$157*'Pass-Thro-Charges'!$C$158*'Centre Two-FTE'!J5)/12 | K79: =SUM(C79:J79)
J80: 0
B81: Accounts Payable | C81: =$C$156*$C$158*'Centre One-FTE'!C6+'Pass-Thro-Charges'!$C$157*'Pass-Thro-Charges'!$C$158*'Centre Two-FTE'!C6 | D81: =$C$156*$C$158*'Centre One-FTE'!D6+'Pass-Thro-Charges'!$C$157*'Pass-Thro-Charges'!$C$158*'Centre Two-FTE'!D6 | E81: =$C$156*$C$158*'Centre One-FTE'!E6+'Pass-Thro-Charges'!$C$157*'Pass-Thro-Charges'!$C$158*'Centre Two-FTE'!E6 | F81: =$C$156*$C$158*'Centre One-FTE'!F6+'Pass-Thro-Charges'!$C$157*'Pass-Thro-Charges'!$C$158*'Centre Two-FTE'!F6 | G81: =$C$156*$C$158*'Centre One-FTE'!G6+'Pass-Thro-Charges'!$C$157*'Pass-Thro-Charges'!$C$158*'Centre Two-FTE'!G6 | H81: =$C$156*$C$158*'Centre One-FTE'!H6+'Pass-Thro-Charges'!$C$157*'Pass-Thro-Charges'!$C$158*'Centre Two-FTE'!H6 | I81: =$C$156*$C$158*'Centre One-FTE'!I6+'Pass-Thro-Charges'!$C$157*'Pass-Thro-Charges'!$C$158*'Centre Two-FTE'!I6 | J81: =($C$156*$C$158*'Centre One-FTE'!J6+'Pass-Thro-Charges'!$C$157*'Pass-Thro-Charges'!$C$158*'Centre Two-FTE'!J6)/12 | K81: =SUM(C81:J81)
J82: 0
B83: T&E | C83: =$C$156*$C$158*'Centre One-FTE'!C7+'Pass-Thro-Charges'!$C$157*'Pass-Thro-Charges'!$C$158*'Centre Two-FTE'!C7 | D83: =$C$156*$C$158*'Centre One-FTE'!D7+'Pass-Thro-Charges'!$C$157*'Pass-Thro-Charges'!$C$158*'Centre Two-FTE'!D7 | E83: =$C$156*$C$158*'Centre One-FTE'!E7+'Pass-Thro-Charges'!$C$157*'Pass-Thro-Charges'!$C$158*'Centre Two-FTE'!E7 | F83: =$C$156*$C$158*'Centre One-FTE'!F7+'Pass-Thro-Charges'!$C$157*'Pass-Thro-Charges'!$C$158*'Centre Two-FTE'!F7 | G83: =$C$156*$C$158*'Centre One-FTE'!G7+'Pass-Thro-Charges'!$C$157*'Pass-Thro-Charges'!$C$158*'Centre Two-FTE'!G7 | H83: =$C$156*$C$158*'Centre One-FTE'!H7+'Pass-Thro-Charges'!$C$157*'Pass-Thro-Charges'!$C$158*'Centre Two-FTE'!H7 | I83: =$C$156*$C$158*'Centre One-FTE'!I7+'Pass-Thro-Charges'!$C$157*'Pass-Thro-Charges'!$C$158*'Centre Two-FTE'!I7 | J83: =($C$156*$C$158*'Centre One-FTE'!J7+'Pass-Thro-Charges'!$C$157*'Pass-Thro-Charges'!$C$158*'Centre Two-FTE'!J7)/12 | K83: =SUM(C83:J83)
J84: 0
B85: Order to Cash | C85: =$C$156*$C$158*'Centre One-FTE'!C8+'Pass-Thro-Charges'!$C$157*'Pass-Thro-Charges'!$C$158*'Centre Two-FTE'!C8 | D85: =$C$156*$C$158*'Centre One-FTE'!D8+'Pass-Thro-Charges'!$C$157*'Pass-Thro-Charges'!$C$158*'Centre Two-FTE'!D8 | E85: =$C$156*$C$158*'Centre One-FTE'!E8+'Pass-Thro-Charges'!$C$157*'Pass-Thro-Charges'!$C$158*'Centre Two-FTE'!E8 | F85: =$C$156*$C$158*'Centre One-FTE'!F8+'Pass-Thro-Charges'!$C$157*'Pass-Thro-Charges'!$C$158*'Centre Two-FTE'!F8 | G85: =$C$156*$C$158*'Centre One-FTE'!G8+'Pass-Thro-Charges'!$C$157*'Pass-Thro-Charges'!$C$158*'Centre Two-FTE'!G8 | H85: =$C$156*$C$158*'Centre One-FTE'!H8+'Pass-Thro-Charges'!$C$157*'Pass-Thro-Charges'!$C$158*'Centre Two-FTE'!H8 | I85: =$C$156*$C$158*'Centre One-FTE'!I8+'Pass-Thro-Charges'!$C$157*'Pass-Thro-Charges'!$C$158*'Centre Two-FTE'!I8 | J85: =($C$156*$C$158*'Centre One-FTE'!J8+'Pass-Thro-Charges'!$C$157*'Pass-Thro-Charges'!$C$158*'Centre Two-FTE'!J8)/12 | K85: =SUM(C85:J85)
J86: 0
B87: Requistion to Pay | C87: =$C$156*$C$158*'Centre One-FTE'!C9+'Pass-Thro-Charges'!$C$157*'Pass-Thro-Charges'!$C$158*'Centre Two-FTE'!C9 | D87: =$C$156*$C$158*'Centre One-FTE'!D9+'Pass-Thro-Charges'!$C$157*'Pass-Thro-Charges'!$C$158*'Centre Two-FTE'!D9 | E87: =$C$156*$C$158*'Centre One-FTE'!E9+'Pass-Thro-Charges'!$C$157*'Pass-Thro-Charges'!$C$158*'Centre Two-FTE'!E9 | F87: =$C$156*$C$158*'Centre One-FTE'!F9+'Pass-Thro-Charges'!$C$157*'Pass-Thro-Charges'!$C$158*'Centre Two-FTE'!F9 | G87: =$C$156*$C$158*'Centre One-FTE'!G9+'Pass-Thro-Charges'!$C$157*'Pass-Thro-Charges'!$C$158*'Centre Two-FTE'!G9 | H87: =$C$156*$C$158*'Centre One-FTE'!H9+'Pass-Thro-Charges'!$C$157*'Pass-Thro-Charges'!$C$158*'Centre Two-FTE'!H9 | I87: =$C$156*$C$158*'Centre One-FTE'!I9+'Pass-Thro-Charges'!$C$157*'Pass-Thro-Charges'!$C$158*'Centre Two-FTE'!I9 | J87: =($C$156*$C$158*'Centre One-FTE'!J9+'Pass-Thro-Charges'!$C$157*'Pass-Thro-Charges'!$C$158*'Centre Two-FTE'!J9)/12 | K87: =SUM(C87:J87)
A89: TOTAL INVESTMENTS | C89: =SUM(C76:C88) | D89: =SUM(D76:D88) | E89: =SUM(E76:E88) | F89: =SUM(F76:F88) | G89: =SUM(G76:G88) | H89: =SUM(H76:H88) | I89: =SUM(I76:I88) | J89: =SUM(J76:J88) | K89: =SUM(K76:K88)
A92: Pass through - Leased line from BT to GlobalPharma
B93: Category of Service | C93: Year 1 | D93: Year 2 | E93: Year 3 | F93: Year 4 | G93: Year 5 | H93: Year 6 | I93: Year 7 | J93: Year 8 | K93: Total
B95: General Accounting & Sox | C95: ='Consolidated FTE '!C35*C$164+'Consolidated FTE '!C36*C$169 | D95: ='Consolidated FTE '!D35*D$164+'Consolidated FTE '!D36*D$169 | E95: ='Consolidated FTE '!E35*E$164+'Consolidated FTE '!E36*E$169 | F95: ='Consolidated FTE '!F35*F$164+'Consolidated FTE '!F36*F$169 | G95: ='Consolidated FTE '!G35*G$164+'Consolidated FTE '!G36*G$169 | H95: ='Consolidated FTE '!H35*H$164+'Consolidated FTE '!H36*H$169 | I95: ='Consolidated FTE '!I35*I$164+'Consolidated FTE '!I36*I$169 | J95: =('Consolidated FTE '!J35*J$164+'Consolidated FTE '!J36*J$169)/12 | K95: =SUM(C95:J95)
J96: 0
B97: Fixed Assets | C97: ='Consolidated FTE '!C39*C$164+'Consolidated FTE '!C40*C$169 | D97: ='Consolidated FTE '!D39*D$164+'Consolidated FTE '!D40*D$169 | E97: ='Consolidated FTE '!E39*E$164+'Consolidated FTE '!E40*E$169 | F97: ='Consolidated FTE '!F39*F$164+'Consolidated FTE '!F40*F$169 | G97: ='Consolidated FTE '!G39*G$164+'Consolidated FTE '!G40*G$169 | H97: ='Consolidated FTE '!H39*H$164+'Consolidated FTE '!H40*H$169 | I97: ='Consolidated FTE '!I39*I$164+'Consolidated FTE '!I40*I$169 | J97: =('Consolidated FTE '!J39*J$164+'Consolidated FTE '!J40*J$169)/12 | K97: =SUM(C97:J97)
J98: 0
B99: Accounts Payable | C99: ='Consolidated FTE '!C43*C$164+'Consolidated FTE '!C44*C$169 | D99: ='Consolidated FTE '!D43*D$164+'Consolidated FTE '!D44*D$169 | E99: ='Consolidated FTE '!E43*E$164+'Consolidated FTE '!E44*E$169 | F99: ='Consolidated FTE '!F43*F$164+'Consolidated FTE '!F44*F$169 | G99: ='Consolidated FTE '!G43*G$164+'Consolidated FTE '!G44*G$169 | H99: ='Consolidated FTE '!H43*H$164+'Consolidated FTE '!H44*H$169 | I99: ='Consolidated FTE '!I43*I$164+'Consolidated FTE '!I44*I$169 | J99: =('Consolidated FTE '!J43*J$164+'Consolidated FTE '!J44*J$169)/12 | K99: =SUM(C99:J99)
J100: 0
B101: T&E | C101: ='Consolidated FTE '!C47*C$164+'Consolidated FTE '!C48*C$169 | D101: ='Consolidated FTE '!D47*D$164+'Consolidated FTE '!D48*D$169 | E101: ='Consolidated FTE '!E47*E$164+'Consolidated FTE '!E48*E$169 | F101: ='Consolidated FTE '!F47*F$164+'Consolidated FTE '!F48*F$169 | G101: ='Consolidated FTE '!G47*G$164+'Consolidated FTE '!G48*G$169 | H101: ='Consolidated FTE '!H47*H$164+'Consolidated FTE '!H48*H$169 | I101: ='Consolidated FTE '!I47*I$164+'Consolidated FTE '!I48*I$169 | J101: =('Consolidated FTE '!J47*J$164+'Consolidated FTE '!J48*J$169)/12 | K101: =SUM(C101:J101)
J102: 0
B103: Order to Cash | C103: ='Consolidated FTE '!C51*C$164+'Consolidated FTE '!C52*C$169 | D103: ='Consolidated FTE '!D51*D$164+'Consolidated FTE '!D52*D$169 | E103: ='Consolidated FTE '!E51*E$164+'Consolidated FTE '!E52*E$169 | F103: ='Consolidated FTE '!F51*F$164+'Consolidated FTE '!F52*F$169 | G103: ='Consolidated FTE '!G51*G$164+'Consolidated FTE '!G52*G$169 | H103: ='Consolidated FTE '!H51*H$164+'Consolidated FTE '!H52*H$169 | I103: ='Consolidated FTE '!I51*I$164+'Consolidated FTE '!I52*I$169 | J103: =('Consolidated FTE '!J51*J$164+'Consolidated FTE '!J52*J$169)/12 | K103: =SUM(C103:J103)
J104: 0
B105: Requistion to Pay | C105: ='Consolidated FTE '!C55*C$164+'Consolidated FTE '!C56*C$169 | D105: ='Consolidated FTE '!D55*D$164+'Consolidated FTE '!D56*D$169 | E105: ='Consolidated FTE '!E55*E$164+'Consolidated FTE '!E56*E$169 | F105: ='Consolidated FTE '!F55*F$164+'Consolidated FTE '!F56*F$169 | G105: ='Consolidated FTE '!G55*G$164+'Consolidated FTE '!G56*G$169 | H105: ='Consolidated FTE '!H55*H$164+'Consolidated FTE '!H56*H$169 | I105: ='Consolidated FTE '!I55*I$164+'Consolidated FTE '!I56*I$169 | J105: =('Consolidated FTE '!J55*J$164+'Consolidated FTE '!J56*J$169)/12 | K105: =SUM(C105:J105)
A107: TOTAL INVESTMENTS | C107: =SUM(C94:C106) | D107: =SUM(D94:D106) | E107: =SUM(E94:E106) | F107: =SUM(F94:F106) | G107: =SUM(G94:G106) | H107: =SUM(H94:H106) | I107: =SUM(I94:I106) | J107: =SUM(J94:J106) | K107: =SUM(K94:K106)
A109: Workflow Details | C109: Year 1 | D109: Year 2 | E109: Year 3 | F109: Year 4 | G109: Year 5 | H109: Year 6 | I109: Year 7 | J109: Year 8 | K109: Total
B110: Total Cost for AP (UK) | C110: =SUM(C111,C116) | D110: =SUM(D111,D116) | E110: =SUM(E111,E116) | F110: =SUM(F111,F116) | G110: =SUM(G111,G116) | H110: =SUM(H111,H116) | I110: =SUM(I111,I116) | J110: =SUM(J111,J116) | K110: =SUM(C110:J110)
B111: One time cost | C111: =SUM(C112:C114) | D111: =SUM(D112:D114) | E111: =SUM(E112:E114) | F111: =SUM(F112:F114) | G111: =SUM(G112:G114) | H111: =SUM(H112:H114) | I111: =SUM(I112:I114) | J111: =SUM(J112:J114) | K111: =SUM(C111:J111)
B112: Development | C112: 55000 | D112: 0 | E112: 0 | F112: 0 | G112: 0 | H112: 0 | I112: 0 | J112: 0 | K112: =SUM(C112:J112)
B113: T&L | C113: 5000 | D113: 0 | E113: 0 | F113: 0 | G113: 0 | H113: 0 | I113: 0 | J113: 0 | K113: =SUM(C113:J113)
B114: Performance Testing | C114: 20000 | D114: 0 | E114: 0 | F114: 0 | G114: 0 | H114: 0 | I114: 0 | J114: 0 | K114: =SUM(C114:J114)
B116: Running costs | C116: =SUM(C117:C120) | D116: =SUM(D117:D120) | E116: =SUM(E117:E120) | F116: =SUM(F117:F120) | G116: =SUM(G117:G120) | H116: =SUM(H117:H120) | I116: =SUM(I117:I120) | J116: =SUM(J117:J120) | K116: =SUM(C116:J116)
B117: Licenses at ServicePro | C117: =750*('Centre Two-FTE'!C39+1)*(25%+18%) | D117: =750*('Centre Two-FTE'!D39+1)*(25%+18%) | E117: =750*('Centre Two-FTE'!E39+1)*(25%+18%) | F117: =750*('Centre Two-FTE'!F39+1)*(25%+18%) | G117: =750*('Centre Two-FTE'!G39+1)*(25%+18%) | H117: =750*('Centre Two-FTE'!H39+1)*(25%+18%) | I117: =750*('Centre Two-FTE'!I39+1)*(25%+18%) | J117: =(750*('Centre Two-FTE'!J39+1)*(25%+18%))/12 | K117: =SUM(C117:J117)
B118: Licenses at GlobalPharma | C118: =750*7*(25%+18%) | D118: =750*7*(25%+18%) | E118: =750*7*(25%+18%) | F118: =750*7*(25%+18%) | G118: =750*7*(25%+18%) | H118: =750*7*(25%+18%) | I118: =750*7*(25%+18%) | J118: =(750*7*(25%+18%))/12 | K118: =SUM(C118:J118)
B119: RTS/Maintenance | C119: 2636.4 | D119: 5077.5111 | E119: 4711.3444 | F119: 4418.4111 | G119: 4125.4778 | H119: 4101.0667 | I119: 4101.0667 | J119: 341.75556 | K119: =SUM(C119:J119)
B120: Asset Depreciation | C120: 2822.25 | D120: 5435.4444 | E120: 5043.4653 | F120: 4729.8819 | G120: 4416.2986 | H120: 4390.1667 | I120: 4390.1667 | J120: 365.84722 | K120: =SUM(C120:J120)
A123: Scanning Details
B124: Scope of countries: | C124: Italy, UK, Spain, Germany and France
B126: One-time setup costs | C126: 8000
B130: Running costs/annum | C130: =SUM(I135:J135)
B132: Running cost details | C132: Annual Volume (Document) | D132: Page/Document | E132: Indexing | F132: Scanning | G132: Barcoding | H132: Postage* | I132: Total Scanning/Postage | J132: Storage | K132: Total
B133: AP | C133: 217000 | D133: 1.5 | E133: =0.04*1.3 | F133: =0.04*1.3 | G133: =0.01*1.3 | H133: =170/200 | I133: =C133*E133+C133*D133*F133+C133*H133/5+C133*G133 | J133: =100*1.3*12 | K133: =SUM(I133:J133)
B134: T&E | C134: 0 | D134: 5 | E134: =0.04*1.3 | F134: =0.04*1.3 | G134: =0.01*1.3 | H134: =170/200 | I134: =C134*E134+C134*D134*F134+C134*H134/5+C134*G134 | J134: =100*1.3*12*0 | K134: =SUM(I134:J134)
B135: Total | C135: =SUM(C133:C134) | I135: =SUM(I133:I134) | J135: =SUM(J133) | K135: =SUM(I135:J135)
B138: *Not registered mail and an avg. 5 document per mail assumed
C140: Year 1 | D140: Year 2 | E140: Year 3 | F140: Year 4 | G140: Year 5 | H140: Year 6 | I140: Year 7 | J140: Year 8 | K140: Total
B141: # FTE (AP) | C141: =SUM('Centre One-FTE'!C34:C39)+SUM('Centre Two-FTE'!C34:C39) | D141: =SUM('Centre One-FTE'!D34:D39)+SUM('Centre Two-FTE'!D34:D39) | E141: =SUM('Centre One-FTE'!E34:E39)+SUM('Centre Two-FTE'!E34:E39) | F141: =SUM('Centre One-FTE'!F34:F39)+SUM('Centre Two-FTE'!F34:F39) | G141: =SUM('Centre One-FTE'!G34:G39)+SUM('Centre Two-FTE'!G34:G39) | H141: =SUM('Centre One-FTE'!H34:H39)+SUM('Centre Two-FTE'!H34:H39) | I141: =SUM('Centre One-FTE'!I34:I39)+SUM('Centre Two-FTE'!I34:I39) | J141: =SUM('Centre One-FTE'!J34:J39)+SUM('Centre Two-FTE'!J34:J39)
B142: Cost/FTE (AP) | C142: 2171.2812 | D142: 2171.2812 | E142: 2171.2812 | F142: 2171.2812 | G142: 2171.2812 | H142: 2171.2812 | I142: 2171.2812 | J142: 2171.2812
B143: Annual charge (AP) | C143: =C141*C142 | D143: =D141*D142 | E143: =E141*E142 | F143: =F141*F142 | G143: =G141*G142 | H143: =H141*H142 | I143: =I141*I142 | J143: =J141*J142/12
B144: # FTE (T&E) | C144: =SUM('Centre One-FTE'!C44:C49)+SUM('Centre Two-FTE'!C44:C49) | D144: =SUM('Centre One-FTE'!D44:D49)+SUM('Centre Two-FTE'!D44:D49) | E144: =SUM('Centre One-FTE'!E44:E49)+SUM('Centre Two-FTE'!E44:E49) | F144: =SUM('Centre One-FTE'!F44:F49)+SUM('Centre Two-FTE'!F44:F49) | G144: =SUM('Centre One-FTE'!G44:G49)+SUM('Centre Two-FTE'!G44:G49) | H144: =SUM('Centre One-FTE'!H44:H49)+SUM('Centre Two-FTE'!H44:H49) | I144: =SUM('Centre One-FTE'!I44:I49)+SUM('Centre Two-FTE'!I44:I49) | J144: =SUM('Centre One-FTE'!J44:J49)+SUM('Centre Two-FTE'!J44:J49)
B145: Cost/FTE (T&E) | C145: 0 | D145: 0 | E145: 0 | F145: 0 | G145: 0 | H145: 0 | I145: 0 | J145: 0
B146: Annual charge (T&E) | C146: =C144*C145 | D146: =D144*D145 | E146: =E144*E145 | F146: =F144*F145 | G146: =G144*G145 | H146: =H144*H145 | I146: =I144*I145 | J146: =J144*J145/12
A149: Archiving Details
C150: Year 1 | D150: Year 2 | E150: Year 3 | F150: Year 4 | G150: Year 5 | H150: Year 6 | I150: Year 7 | J150: Year 8 | K150: Total
B151: Charge/FTE | C151: 2409.29 | D151: 2409.29 | E151: 2409.29 | F151: 2409.29 | G151: 2409.29 | H151: 2409.29 | I151: 2409.29 | J151: 2409.29 | K151: =SUM(C151:J151)
B152: Total charge | C152: ='Centre Two-FTE'!C39*'Pass-Thro-Charges'!C151 | D152: ='Centre Two-FTE'!D39*'Pass-Thro-Charges'!D151 | E152: ='Centre Two-FTE'!E39*'Pass-Thro-Charges'!E151 | F152: ='Centre Two-FTE'!F39*'Pass-Thro-Charges'!F151 | G152: ='Centre Two-FTE'!G39*'Pass-Thro-Charges'!G151 | H152: ='Centre Two-FTE'!H39*'Pass-Thro-Charges'!H151 | I152: ='Centre Two-FTE'!I39*'Pass-Thro-Charges'!I151 | J152: ='Centre Two-FTE'!J39*'Pass-Thro-Charges'!J151/12 | K152: =SUM(C152:J152)
A155: MPLS Details
B156: Cost of 1 kbit bandwidth (Centre One) | C156: 120
B157: Cost of 1 kbit bandwidth (Centre Two) | C157: 75
B158: Bandwidth usage per FTE (kbit) | C158: 20
A160: Leased Line Details
...

Sheet Transition Charges
A1: TRANSITION CHARGES (US$)
A3: Description | B3: Q1 | C3: Q2 | D3: Q3 | E3: Q4 | F3: Year 1 | G3: Q1 | H3: Q2 | I3: Q3 | J3: Q4 | K3: Year 2 | L3: Year 3 | M3: Year 4 | N3: Year 5 | O3: Year 6 | P3: Year 7 | Q3: Year 8 | R3: Total
A4: General Accounting & Sox - TRANSITION ONLY
A5: General Accounting & Sox
A6: Labor | B6: 0 | C6: 0 | D6: 8505.8669 | E6: 12244.823 | F6: 20750.69 | G6: 12109.237 | H6: 11973.652 | I6: 11838.066 | J6: 11702.48 | K6: 47623.435 | L6: 45454.065 | M6: 25282.685 | R6: =SUM(K6:Q6)+F6
A7: Hardware/Ship | B7: 0 | C7: 0 | D7: 0 | E7: 0 | F7: 0 | G7: 0 | H7: 0 | I7: 0 | J7: 0 | K7: 0 | L7: 0 | M7: 0 | R7: =SUM(K7:Q7)+F7
A8: Software | B8: 0 | C8: 0 | D8: 0 | E8: 0 | F8: 0 | G8: 0 | H8: 0 | I8: 0 | J8: 0 | K8: 0 | L8: 0 | M8: 0 | R8: =SUM(K8:Q8)+F8
A9: Travel | B9: 1783.4947 | C9: 1763.8958 | D9: 16277.039 | E9: 21431.356 | F9: 41255.785 | G9: 21193.446 | H9: 20955.535 | I9: 20717.625 | J9: 20479.714 | K9: 83346.32 | L9: 79539.752 | M9: 39954.289 | R9: =SUM(K9:Q9)+F9
A10: Hires / M&Ls | B10: 0 | C10: 0 | D10: 0 | E10: 0 | F10: 0 | G10: 0 | H10: 0 | I10: 0 | J10: 0 | K10: 0 | L10: 0 | M10: 0 | R10: =SUM(K10:Q10)+F10
A11: Consulting | B11: 784.66435 | C11: 776.04167 | D11: 4886.5557 | E11: 6863.6671 | F11: 13310.929 | G11: 6787.4605 | H11: 6711.2539 | I11: 6635.0473 | J11: 6558.8407 | K11: 26692.602 | L11: 25473.297 | M11: 12711.141 | R11: =SUM(K11:Q11)+F11
A12: Communications | B12: 0 | C12: 0 | D12: 0 | E12: 0 | F12: 0 | G12: 0 | H12: 0 | I12: 0 | J12: 0 | K12: 0 | L12: 0 | M12: 0 | R12: =SUM(K12:Q12)+F12
A13: TOTAL General Accounting & Sox | B13: 2568.159 | C13: 2539.9375 | D13: 29669.461 | E13: 40539.846 | F13: 75317.404 | G13: 40090.143 | H13: 39640.441 | I13: 39190.738 | J13: 38741.035 | K13: 157662.36 | L13: 150467.11 | M13: 77948.115 | N13: =SUM(N6:N12) | O13: =SUM(O6:O12) | P13: =SUM(P6:P12) | Q13: =SUM(Q6:Q12) | R13: =SUM(R6:R12)
A15: Fixed Assets - TRANSITION ONLY
A16: Fixed Assets
A17: Labor | B17: 0 | C17: 0 | D17: 2175.5816 | E17: 2254.6585 | F17: 4430.2401 | G17: 2229.6193 | H17: 2204.5801 | I17: 2179.5409 | J17: 2154.5017 | K17: 8768.2421 | L17: 8367.6151 | M17: 4124.1081 | R17: =SUM(K17:Q17)+F17
A18: Hardware/Ship | B18: 0 | C18: 0 | D18: 0 | E18: 0 | F18: 0 | G18: 0 | H18: 0 | I18: 0 | J18: 0 | K18: 0 | L18: 0 | M18: 0 | R18: =SUM(K18:Q18)+F18
A19: Software | B19: 0 | C19: 0 | D19: 0 | E19: 0 | F19: 0 | G19: 0 | H19: 0 | I19: 0 | J19: 0 | K19: 0 | L19: 0 | M19: 0 | R19: =SUM(K19:Q19)+F19
A20: Travel | B20: 382.17743 | C20: 377.97768 | D20: 4292.4202 | E20: 4426.8888 | F20: 9479.4641 | G20: 4377.63 | H20: 4328.3712 | I20: 4279.1125 | J20: 4229.8537 | K20: 17214.967 | L20: 16426.827 | M20: 7418.2626 | R20: =SUM(K20:Q20)+F20
A21: Hires / M&Ls | B21: 0 | C21: 0 | D21: 0 | E21: 0 | F21: 0 | G21: 0 | H21: 0 | I21: 0 | J21: 0 | K21: 0 | L21: 0 | M21: 0 | R21: =SUM(K21:Q21)+F21
A22: Consulting | B22: 168.14236 | C22: 166.29464 | D22: 1047.1191 | E22: 1470.7858 | F22: 2852.3419 | G22: 1454.4558 | H22: 1438.1258 | I22: 1421.7958 | J22: 1405.4659 | K22: 5719.8433 | L22: 5458.5636 | M22: 2723.8159 | R22: =SUM(K22:Q22)+F22
A23: Communications | B23: 0 | C23: 0 | D23: 0 | E23: 0 | F23: 0 | G23: 0 | H23: 0 | I23: 0 | J23: 0 | K23: 0 | L23: 0 | M23: 0 | R23: =SUM(K23:Q23)+F23
A24: TOTAL Fixed Assets | B24: 550.31979 | C24: 544.27232 | D24: 7515.1208 | E24: 8152.3331 | F24: 16762.046 | G24: 8061.7051 | H24: 7971.0772 | I24: 7880.4492 | J24: 7789.8213 | K24: 31703.053 | L24: 30253.005 | M24: 14266.187 | N24: =SUM(N17:N23) | O24: =SUM(O17:O23) | P24: =SUM(P17:P23) | Q24: =SUM(Q17:Q23) | R24: =SUM(R17:R23)
A26: Accounts Payable - TRANSITION ONLY
A27: Accounts Payable
A28: Labor | B28: 0 | C28: 0 | D28: 26911.249 | E28: 37669.177 | F28: 64580.426 | G28: 37251.98 | H28: 36834.784 | I28: 36417.587 | J28: 36000.39 | K28: 146504.74 | L28: 139829.59 | M28: 77129.116 | R28: =SUM(K28:Q28)+F28
A29: Hardware/Ship | B29: 0 | C29: 0 | D29: 0 | E29: 0 | F29: 0 | G29: 0 | H29: 0 | I29: 0 | J29: 0 | K29: 0 | L29: 0 | M29: 0 | R29: =SUM(K29:Q29)+F29
A30: Software | B30: 0 | C30: 0 | D30: 0 | E30: 0 | F30: 0 | G30: 0 | H30: 0 | I30: 0 | J30: 0 | K30: 0 | L30: 0 | M30: 0 | R30: =SUM(K30:Q30)+F30
A31: Travel | B31: 7133.9787 | C31: 7055.5833 | D31: 50214.677 | E31: 64267.3 | F31: 128671.54 | G31: 63553.26 | H31: 62839.22 | I31: 62125.18 | J31: 61411.141 | K31: 249928.8 | L31: 238504.16 | M31: 115500.35 | R31: =SUM(K31:Q31)+F31
A32: Hires / M&Ls | B32: 0 | C32: 0 | D32: 0 | E32: 0 | F32: 0 | G32: 0 | H32: 0 | I32: 0 | J32: 0 | K32: 0 | L32: 0 | M32: 0 | R32: =SUM(K32:Q32)+F32
A33: Consulting | B33: 3138.6574 | C33: 3104.1667 | D33: 19546.223 | E33: 27454.668 | F33: 53243.715 | G33: 27149.842 | H33: 26845.015 | I33: 26540.189 | J33: 26235.363 | K33: 106770.41 | L33: 101893.19 | M33: 50844.564 | R33: =SUM(K33:Q33)+F33
A34: Communications | B34: 0 | C34: 0 | D34: 0 | E34: 0 | F34: 0 | G34: 0 | H34: 0 | I34: 0 | J34: 0 | K34: 0 | L34: 0 | M34: 0 | R34: =SUM(K34:Q34)+F34
A35: TOTAL Accounts Payable | B35: 10272.636 | C35: 10159.75 | D35: 96672.149 | E35: 129391.15 | F35: 246495.68 | G35: 127955.08 | H35: 126519.02 | I35: 125082.96 | J35: 123646.89 | K35: 503203.95 | L35: 480226.94 | M35: 243474.03 | N35: =SUM(N28:N34) | O35: =SUM(O28:O34) | P35: =SUM(P28:P34) | Q35: =SUM(Q28:Q34) | R35: =SUM(R28:R34)
A37: T&E - TRANSITION ONLY
A38: T&E
A39: Labor | B39: 0 | C39: 0 | D39: 4424.6192 | E39: 7528.9033 | F39: 11953.522 | G39: 7445.6338 | H39: 7362.3643 | I39: 7279.0947 | J39: 7195.8252 | K39: 29282.918 | L39: 27950.606 | M39: 16247.472 | R39: =SUM(K39:Q39)+F39
A40: Hardware/Ship | B40: 0 | C40: 0 | D40: 0 | E40: 0 | F40: 0 | G40: 0 | H40: 0 | I40: 0 | J40: 0 | K40: 0 | L40: 0 | M40: 0 | R40: =SUM(K40:Q40)+F40
A41: Software | B41: 0 | C41: 0 | D41: 0 | E41: 0 | F41: 0 | G41: 0 | H41: 0 | I41: 0 | J41: 0 | K41: 0 | L41: 0 | M41: 0 | R41: =SUM(K41:Q41)+F41
A42: Travel | B42: 1273.9248 | C42: 1259.9256 | D42: 9306.4165 | E42: 13260.025 | F42: 25100.292 | G42: 13112.876 | H42: 12965.726 | I42: 12818.577 | J42: 12671.427 | K42: 51568.607 | L42: 49214.215 | M42: 25092.218 | R42: =SUM(K42:Q42)+F42
A43: Hires / M&Ls | B43: 0 | C43: 0 | D43: 0 | E43: 0 | F43: 0 | G43: 0 | H43: 0 | I43: 0 | J43: 0 | K43: 0 | L43: 0 | M43: 0 | R43: =SUM(K43:Q43)+F43
A44: Consulting | B44: 560.47454 | C44: 554.31548 | D44: 3490.397 | E44: 4902.6193 | F44: 9507.8063 | G44: 4848.186 | H44: 4793.7528 | I44: 4739.3195 | J44: 4684.8862 | K44: 19066.144 | L44: 18195.212 | M44: 9079.3864 | R44: =SUM(K44:Q44)+F44
A45: Communications | B45: 0 | C45: 0 | D45: 0 | E45: 0 | F45: 0 | G45: 0 | H45: 0 | I45: 0 | J45: 0 | K45: 0 | L45: 0 | M45: 0 | R45: =SUM(K45:Q45)+F45
A46: TOTAL T&E | B46: 1834.3993 | C46: 1814.2411 | D46: 17221.433 | E46: 25691.548 | F46: 46561.621 | G46: 25406.696 | H46: 25121.843 | I46: 24836.991 | J46: 24552.139 | K46: 99917.669 | L46: 95360.033 | M46: 50419.076 | N46: =SUM(N39:N45) | O46: =SUM(O39:O45) | P46: =SUM(P39:P45) | Q46: =SUM(Q39:Q45) | R46: =SUM(R39:R45)
A48: Order To Cash - TRANSITION ONLY
A49: Order To Cash
A50: Labor | B50: 0 | C50: 0 | D50: 5165.4086 | E50: 10506.083 | F50: 15671.492 | G50: 10390.008 | H50: 10273.933 | I50: 10157.858 | J50: 10041.782 | K50: 40863.581 | L50: 39006.377 | M50: 23551.737 | R50: =SUM(K50:Q50)+F50
A51: Hardware/Ship | B51: 0 | C51: 0 | D51: 0 | E51: 0 | F51: 0 | G51: 0 | H51: 0 | I51: 0 | J51: 0 | K51: 0 | L51: 0 | M51: 0 | R51: =SUM(K51:Q51)+F51
A52: Software | B52: 0 | C52: 0 | D52: 0 | E52: 0 | F52: 0 | G52: 0 | H52: 0 | I52: 0 | J52: 0 | K52: 0 | L52: 0 | M52: 0 | R52: =SUM(K52:Q52)+F52
A53: Travel | B53: 1783.4947 | C53: 1763.8958 | D53: 11481.433 | E53: 18241.137 | F53: 33269.961 | G53: 18038.863 | H53: 17836.589 | I53: 17634.315 | J53: 17432.041 | K53: 70941.81 | L53: 67705.425 | M53: 35615.944 | R53: =SUM(K53:Q53)+F53
A54: Hires / M&Ls | B54: 0 | C54: 0 | D54: 0 | E54: 0 | F54: 0 | G54: 0 | H54: 0 | I54: 0 | J54: 0 | K54: 0 | L54: 0 | M54: 0 | R54: =SUM(K54:Q54)+F54
A55: Consulting | B55: 784.66435 | C55: 776.04167 | D55: 4886.5557 | E55: 6863.6671 | F55: 13310.929 | G55: 6787.4605 | H55: 6711.2539 | I55: 6635.0473 | J55: 6558.8407 | K55: 26692.602 | L55: 25473.297 | M55: 12711.141 | R55: =SUM(K55:Q55)+F55
A56: Communications | B56: 0 | C56: 0 | D56: 0 | E56: 0 | F56: 0 | G56: 0 | H56: 0 | I56: 0 | J56: 0 | K56: 0 | L56: 0 | M56: 0 | R56: =SUM(K56:Q56)+F56
A57: TOTAL Order To Cash | B57: 2568.159 | C57: 2539.9375 | D57: 21533.398 | E57: 35610.888 | F57: 62252.382 | G57: 35216.332 | H57: 34821.776 | I57: 34427.22 | J57: 34032.664 | K57: 138497.99 | L57: 132185.1 | M57: 71878.823 | N57: =SUM(N50:N56) | O57: =SUM(O50:O56) | P57: =SUM(P50:P56) | Q57: =SUM(Q50:Q56) | R57: =SUM(R50:R56)
A59: Requistion To Pay - TRANSITION ONLY
A60: Requistion To Pay
A61: Labor | B61: 0 | C61: 0 | D61: 12340.754 | E61: 17168.636 | F61: 29509.39 | G61: 16978.48 | H61: 16788.323 | I61: 16598.166 | J61: 16408.01 | K61: 66772.979 | L61: 63730.474 | M61: 35087.809 | R61: =SUM(K61:Q61)+F61
A62: Hardware/Ship | B62: 0 | C62: 0 | D62: 0 | E62: 0 | F62: 0 | G62: 0 | H62: 0 | I62: 0 | J62: 0 | K62: 0 | L62: 0 | M62: 0 | R62: =SUM(K62:Q62)+F62
A63: Software | B63: 0 | C63: 0 | D63: 0 | E63: 0 | F63: 0 | G63: 0 | H63: 0 | I63: 0 | J63: 0 | K63: 0 | L63: 0 | M63: 0 | R63: =SUM(K63:Q63)+F63
A64: Travel | B64: 3694.3818 | C64: 3653.7842 | D64: 23813.296 | E64: 29534.207 | F64: 60695.668 | G64: 29205.877 | H64: 28877.548 | I64: 28549.218 | J64: 28220.889 | K64: 114853.53 | L64: 109600.26 | M64: 51716.539 | R64: =SUM(K64:Q64)+F64
A65: Hires / M&Ls | B65: 0 | C65: 0 | D65: 0 | E65: 0 | F65: 0 | G65: 0 | H65: 0 | I65: 0 | J65: 0 | K65: 0 | L65: 0 | M65: 0 | R65: =SUM(K65:Q65)+F65
A66: Consulting | B66: 1625.3762 | C66: 1607.5149 | D66: 10122.151 | E66: 14217.596 | F66: 27572.638 | G66: 14059.74 | H66: 13901.883 | I66: 13744.026 | J66: 13586.17 | K66: 55291.819 | L66: 52766.115 | M66: 26330.221 | R66: =SUM(K66:Q66)+F66
A67: Communications | B67: 0 | C67: 0 | D67: 0 | E67: 0 | F67: 0 | G67: 0 | H67: 0 | I67: 0 | J67: 0 | K67: 0 | L67: 0 | M67: 0 | R67: =SUM(K67:Q67)+F67
A68: TOTAL Requistion To Pay | B68: =SUM(B61:B67) | C68: =SUM(C61:C67) | D68: =SUM(D61:D67) | E68: =SUM(E61:E67) | F68: =SUM(F61:F67) | G68: =SUM(G61:G67) | H68: =SUM(H61:H67) | I68: =SUM(I61:I67) | ... R68: =SUM(R61:R67)
A70: GRAND TOTAL SUPPLIER TRANSITION CHARGES | B70: =SUM(B13+B24+B35+B46+B57+B68) | C70: =SUM(C13+C24+C35+C46+C57+C68) | D70: =SUM(D13+D24+D35+D46+D57+D68) | E70: =SUM(E13+E24+E35+E46+E57+E68) | F70: =SUM(F13+F24+F35+F46+F57+F68) | G70: =SUM(G13+G24+G35+G46+G57+G68) | H70: =SUM(H13+H24+H35+H46+H57+H68) | I70: =SUM(I13+I24+I35+I46+I57+I68) | ... R70: =SUM(R13+R24+R35+R46+R57+R68)
A73: Category | B73: Definition
A74: Labor | B74: Labor costs of transition team not captured in categories below
A75: Hardware/Shipping | B75: Bubble hardware including shipping
A76: Software | B76: Includes Access Fees for system software and data movement software
A77: Travel | B77: Transition team travel included in the costs
A78: Hires/M&Ls | B78: Hiring expenses and Moving and Living for transitioned employees.
A79: Consulting | B79: Consolidation studies, Third party consultants (i.e. EMC Consultants), and transition planning
A80: Communications | B80: Transition bandwidth for data movement and cost to set-up communications

Sheet Service Provider Investments
A1: SERVICE PROVIDER INVESTMENTS (US$)
B3: Category of Service | C3: Initial Asset Purchase | D3: Year 1 | E3: Year 2 | F3: Year 3 | G3: Year 4 | H3: Year 5 | I3: Year 6 | J3: Year 7 | K3: Total
B5: General Accounting & Sox | K5: =SUM(C5:J5)
B7: Fixed Assets | K7: =SUM(C7:J7)
B9: Accounts Payable | K9: =SUM(C9:J9)
B11: T&E | K11: =SUM(C11:J11)
B13: Order to Cash | K13: =SUM(C13:J13)
B15: Requistion to Pay | K15: =SUM(C15:J15)
A17: TOTAL INVESTMENTS | C17: =SUM(C4:C16) | D17: =SUM(D4:D16) | E17: =SUM(E4:E16) | F17: =SUM(F4:F16) | G17: =SUM(G4:G16) | H17: =SUM(H4:H16) | I17: =SUM(I4:I16) | J17: =SUM(J4:J16) | K17: =SUM(K4:K16)

Sheet Termination Charges
A1: TERMINATION CHARGES (US$)
B2: Category of Services | C2: Year 1 | D2: Year 2 | E2: Year 3 | F2: Year 4 | G2: Year 5 | H2: Year 6 | I2: Year 7 | J2: Year 8
A3: TERMINATION FOR CAUSE
B4: General Accounting & Sox
B5: Fixed Assets
B6: Accounts Payable
B7: T&E
B8: Order to Cash
B9: Requistion to Pay
A10: TOTAL TERMINATION CHARGES
A13: TERMINATION FOR CHANGE OF CONTROL
B14: General Accounting & Sox | C14: 45709.246 | D14: 180755.73 | E14: 167560.56 | F14: 153411.01 | G14: 138261.67 | H14: 122065.3 | I14: 118473.77 | J14: 122027.98
B15: Fixed Assets | C15: 9641.9197 | D15: 22507.469 | E15: 20864.424 | F15: 19102.539 | G15: 17216.163 | H15: 15199.413 | I15: 14752.199 | J15: 15194.765
B16: Accounts Payable | C16: 171143.32 | D16: 610974.51 | E16: 566373.37 | F16: 518546.28 | G16: 467339.84 | H16: 412594.31 | I16: 353650.17 | J16: 363466.78
B17: T&E | C17: 26499.033 | D17: 100771.69 | E17: 93415.352 | F17: 85526.945 | G17: 77081.159 | H17: 68051.652 | I17: 66049.363 | J17: 68030.844
B18: Order to Cash | C18: 39002.952 | D18: 159172.68 | E18: 147553.08 | F18: 135093.04 | G18: 121752.6 | H18: 107490.16 | I18: 104327.46 | J18: 107457.29
B19: Requistion to Pay | C19: 117826.73 | D19: 339146.48 | E19: 314388.79 | F19: 287840.4 | G19: 259416.16 | H19: 229027.41 | I19: 210243.52 | J19: 216550.82
A20: TOTAL TERMINATION CHARGES | C20: =SUM(C14:C19) | D20: =SUM(D14:D19) | E20: =SUM(E14:E19) | F20: =SUM(F14:F19) | G20: =SUM(G14:G19) | H20: =SUM(H14:H19) | I20: =SUM(I14:I19) | J20: =SUM(J14:J19)
A23: TERMINATION FOR CONVENIENCE
B24: General Accounting & Sox | C24: 45709.246 | D24: 278085.74 | E24: 257785.48 | F24: 236016.93 | G24: 212710.26 | H24: 187792.77 | I24: 161188.8 | J24: 132819.57
B25: Fixed Assets | C25: 9641.9197 | D25: 34626.875 | E25: 32099.113 | F25: 29388.521 | G25: 26486.405 | H25: 23383.712 | I25: 20071.019 | J25: 16538.52
B26: Accounts Payable | C26: 171143.32 | D26: 939960.78 | E26: 871343.64 | F26: 797763.51 | G26: 718984.37 | H26: 634760.48 | I26: 544836.08 | J26: 448944.93
B27: T&E | C27: 26499.033 | D27: 155033.36 | E27: 143715.93 | F27: 131579.91 | G27: 118586.4 | H27: 104694.85 | I27: 89863.079 | J27: 74047.177
B28: Order to Cash | C28: 39002.952 | D28: 244881.05 | E28: 227004.74 | F28: 207835.45 | G28: 187311.7 | H28: 165369.47 | I28: 141942.13 | J28: 116960.31
B29: Requistion to Pay | C29: 117826.73 | D29: 521763.81 | E29: 483675.05 | F29: 442831.38 | G29: 399101.78 | H29: 352349.86 | I29: 302433.63 | J29: 249205.31
A30: TOTAL TERMINATION CHARGES | C30: =SUM(C24:C29) | D30: =SUM(D24:D29) | E30: =SUM(E24:E29) | F30: =SUM(F24:F29) | G30: =SUM(G24:G29) | H30: =SUM(H24:H29) | I30: =SUM(I24:I29) | J30: =SUM(J24:J29)
A34: ALGORITHM FOR CALCULATING FEES ON ANY DATE OTHER THAN THE CONTRACT ANNIVERSARY
A35: =A3
A36: =A13 | C36: Termination charges above have been calculated for the given year, i.e. at any point in that year a termination would result in the highligted charges
A37: =A23

Sheet Unit Rates (ARCs & RRCs)
A1: ARC/RRC RATES INPUT FORM
A2: $ RATE CHARGE PER FTE | B2: Year 1 | C2: Year 2 | D2: Year 3 | E2: Year 4 | F2: Year 5 | G2: Year 6 | H2: Year 7 | I2: Year 8
A3: Process Summary
A4: General Accounting & Sox
A5: Centre One | B5: ='Centre One-BC'!C$20/'Centre One-FTE'!C4 | C5: ='Centre One-BC'!D$20/'Centre One-FTE'!D4 | D5: ='Centre One-BC'!E$20/'Centre One-FTE'!E4 | E5: ='Centre One-BC'!F$20/'Centre One-FTE'!F4 | F5: ='Centre One-BC'!G$20/'Centre One-FTE'!G4 | G5: ='Centre One-BC'!H$20/'Centre One-FTE'!H4 | H5: ='Centre One-BC'!I$20/'Centre One-FTE'!I4 | I5: =('Centre One-BC'!J$20/'Centre One-FTE'!J4)*12
A6: Centre Two | B6: ='Centre Two-BC'!C$20/'Centre Two-FTE'!C4 | C6: ='Centre Two-BC'!D$20/'Centre Two-FTE'!D4 | D6: ='Centre Two-BC'!E$20/'Centre Two-FTE'!E4 | E6: ='Centre Two-BC'!F$20/'Centre Two-FTE'!F4 | F6: ='Centre Two-BC'!G$20/'Centre Two-FTE'!G4 | G6: ='Centre Two-BC'!H$20/'Centre Two-FTE'!H4 | H6: ='Centre Two-BC'!I$20/'Centre Two-FTE'!I4 | I6: =('Centre Two-BC'!J$20/'Centre Two-FTE'!J4)*12
A8: Fixed Assets
A9: Centre One | B9: ='Centre One-BC'!C$30/'Centre One-FTE'!C30 | C9: ='Centre One-BC'!D$30/'Centre One-FTE'!D30 | D9: ='Centre One-BC'!E$30/'Centre One-FTE'!E30 | E9: ='Centre One-BC'!F$30/'Centre One-FTE'!F30 | F9: ='Centre One-BC'!G$30/'Centre One-FTE'!G30 | G9: ='Centre One-BC'!H$30/'Centre One-FTE'!H30 | H9: ='Centre One-BC'!I$30/'Centre One-FTE'!I30 | I9: =('Centre One-BC'!J$30/'Centre One-FTE'!J30)*12
A10: Centre Two | B10: ='Centre Two-BC'!C$30/'Centre Two-FTE'!C30 | C10: ='Centre Two-BC'!D$30/'Centre Two-FTE'!D30 | D10: ='Centre Two-BC'!E$30/'Centre Two-FTE'!E30 | E10: ='Centre Two-BC'!F$30/'Centre Two-FTE'!F30 | F10: ='Centre Two-BC'!G$30/'Centre Two-FTE'!G30 | G10: ='Centre Two-BC'!H$30/'Centre Two-FTE'!H30 | H10: ='Centre Two-BC'!I$30/'Centre Two-FTE'!I30 | I10: =('Centre Two-BC'!J$30/'Centre Two-FTE'!J30)*12
A12: Accounts Payable
A13: Centre One | B13: ='Centre One-BC'!C$40/'Centre One-FTE'!C40 | C13: ='Centre One-BC'!D$40/'Centre One-FTE'!D40 | D13: ='Centre One-BC'!E$40/'Centre One-FTE'!E40 | E13: ='Centre One-BC'!F$40/'Centre One-FTE'!F40 | F13: ='Centre One-BC'!G$40/'Centre One-FTE'!G40 | G13: ='Centre One-BC'!H$40/'Centre One-FTE'!H40 | H13: ='Centre One-BC'!I$40/'Centre One-FTE'!I40 | I13: =('Centre One-BC'!J$40/'Centre One-FTE'!J40)*12
A14: Centre Two | B14: ='Centre Two-BC'!C$40/'Centre Two-FTE'!C40 | C14: ='Centre Two-BC'!D$40/'Centre Two-FTE'!D40 | D14: ='Centre Two-BC'!E$40/'Centre Two-FTE'!E40 | E14: ='Centre Two-BC'!F$40/'Centre Two-FTE'!F40 | F14: ='Centre Two-BC'!G$40/'Centre Two-FTE'!G40 | G14: ='Centre Two-BC'!H$40/'Centre Two-FTE'!H40 | H14: ='Centre Two-BC'!I$40/'Centre Two-FTE'!I40 | I14: =('Centre Two-BC'!J$40/'Centre Two-FTE'!J40)*12
A16: T&E
A17: Centre One | B17: ='Centre One-BC'!C$50/'Centre One-FTE'!C50 | C17: ='Centre One-BC'!D$50/'Centre One-FTE'!D50 | D17: ='Centre One-BC'!E$50/'Centre One-FTE'!E50 | E17: ='Centre One-BC'!F$50/'Centre One-FTE'!F50 | F17: ='Centre One-BC'!G$50/'Centre One-FTE'!G50 | G17: ='Centre One-BC'!H$50/'Centre One-FTE'!H50 | H17: ='Centre One-BC'!I$50/'Centre One-FTE'!I50 | I17: =('Centre One-BC'!J$50/'Centre One-FTE'!J50)*12
A18: Centre Two | B18: ='Centre Two-BC'!C$50/'Centre Two-FTE'!C50 | C18: ='Centre Two-BC'!D$50/'Centre Two-FTE'!D50 | D18: ='Centre Two-BC'!E$50/'Centre Two-FTE'!E50 | E18: ='Centre Two-BC'!F$50/'Centre Two-FTE'!F50 | F18: ='Centre Two-BC'!G$50/'Centre Two-FTE'!G50 | G18: ='Centre Two-BC'!H$50/'Centre Two-FTE'!H50 | H18: ='Centre Two-BC'!I$50/'Centre Two-FTE'!I50 | I18: =('Centre Two-BC'!J$50/'Centre Two-FTE'!J50)*12
A20: Order to Cash
A21: Centre One | B21: ='Centre One-BC'!C$60/'Centre One-FTE'!C60 | C21: ='Centre One-BC'!D$60/'Centre One-FTE'!D60 | D21: ='Centre One-BC'!E$60/'Centre One-FTE'!E60 | E21: ='Centre One-BC'!F$60/'Centre One-FTE'!F60 | F21: ='Centre One-BC'!G$60/'Centre One-FTE'!G60 | G21: ='Centre One-BC'!H$60/'Centre One-FTE'!H60 | H21: ='Centre One-BC'!I$60/'Centre One-FTE'!I60 | I21: =('Centre One-BC'!J$60/'Centre One-FTE'!J60)*12
A22: Centre Two | B22: ='Centre Two-BC'!C$60/'Centre Two-FTE'!C60 | C22: ='Centre Two-BC'!D$60/'Centre Two-FTE'!D60 | D22: ='Centre Two-BC'!E$60/'Centre Two-FTE'!E60 | E22: ='Centre Two-BC'!F$60/'Centre Two-FTE'!F60 | F22: ='Centre Two-BC'!G$60/'Centre Two-FTE'!G60 | G22: ='Centre Two-BC'!H$60/'Centre Two-FTE'!H60 | H22: ='Centre Two-BC'!I$60/'Centre Two-FTE'!I60 | I22: =('Centre Two-BC'!J$60/'Centre Two-FTE'!J60)*12
A24: Requistion to Pay
A25: Centre One | B25: ='Centre One-BC'!C$70/'Centre One-FTE'!C70 | C25: ='Centre One-BC'!D$70/'Centre One-FTE'!D70 | D25: ='Centre One-BC'!E$70/'Centre One-FTE'!E70 | E25: ='Centre One-BC'!F$70/'Centre One-FTE'!F70 | F25: ='Centre One-BC'!G$70/'Centre One-FTE'!G70 | G25: ='Centre One-BC'!H$70/'Centre One-FTE'!H70 | H25: ='Centre One-BC'!I$70/'Centre One-FTE'!I70 | I25: =('Centre One-BC'!J$70/'Centre One-FTE'!J70)*12
A26: Centre Two | B26: ='Centre Two-BC'!C$70/'Centre Two-FTE'!C70 | C26: ='Centre Two-BC'!D$70/'Centre Two-FTE'!D70 | D26: ='Centre Two-BC'!E$70/'Centre Two-FTE'!E70 | E26: ='Centre Two-BC'!F$70/'Centre Two-FTE'!F70 | F26: ='Centre Two-BC'!G$70/'Centre Two-FTE'!G70 | G26: ='Centre Two-BC'!H$70/'Centre Two-FTE'!H70 | H26: ='Centre Two-BC'!I$70/'Centre Two-FTE'!I70 | I26: =('Centre Two-BC'!J$70/'Centre Two-FTE'!J70)*12
A28: DEAD BAND % | B28: Year 1 | C28: Year 2 | D28: Year 3 | E28: Year 4 | F28: Year 5 | G28: Year 6 | H28: Year 7 | I28: Year 8
A29: Process Summary
A30: General Accounting & Sox
A31: Centre One | B31: 0.05 | C31: 0.05 | D31: 0.05 | E31: 0.05 | F31: 0.05 | G31: 0.05 | H31: 0.05 | I31: 0.05
A32: Centre Two | B32: 0.05 | C32: 0.05 | D32: 0.05 | E32: 0.05 | F32: 0.05 | G32: 0.05 | H32: 0.05 | I32: 0.05
A34: Fixed Assets
A35: Centre One | B35: 0.05 | C35: 0.05 | D35: 0.05 | E35: 0.05 | F35: 0.05 | G35: 0.05 | H35: 0.05 | I35: 0.05
A36: Centre Two | B36: 0.05 | C36: 0.05 | D36: 0.05 | E36: 0.05 | F36: 0.05 | G36: 0.05 | H36: 0.05 | I36: 0.05
A38: Accounts Payable
A39: Centre One | B39: 0.05 | C39: 0.05 | D39: 0.05 | E39: 0.05 | F39: 0.05 | G39: 0.05 | H39: 0.05 | I39: 0.05
A40: Centre Two | B40: 0.05 | C40: 0.05 | D40: 0.05 | E40: 0.05 | F40: 0.05 | G40: 0.05 | H40: 0.05 | I40: 0.05
A42: T&E
A43: Centre One | B43: 0.05 | C43: 0.05 | D43: 0.05 | E43: 0.05 | F43: 0.05 | G43: 0.05 | H43: 0.05 | I43: 0.05
A44: Centre Two | B44: 0.05 | C44: 0.05 | D44: 0.05 | E44: 0.05 | F44: 0.05 | G44: 0.05 | H44: 0.05 | I44: 0.05
A46: Order to Cash
A47: Centre One | B47: 0.05 | C47: 0.05 | D47: 0.05 | E47: 0.05 | F47: 0.05 | G47: 0.05 | H47: 0.05 | I47: 0.05
A48: Centre Two | B48: 0.05 | C48: 0.05 | D48: 0.05 | E48: 0.05 | F48: 0.05 | G48: 0.05 | H48: 0.05 | I48: 0.05
A50: Requistion to Pay
A51: Centre One | B51: 0.05 | C51: 0.05 | D51: 0.05 | E51: 0.05 | F51: 0.05 | G51: 0.05 | H51: 0.05 | I51: 0.05
A52: Centre Two | B52: 0.05 | C52: 0.05 | D52: 0.05 | E52: 0.05 | F52: 0.05 | G52: 0.05 | H52: 0.05 | I52: 0.05

Sheet Productivity
A1: PRODUCTIVITY % (Change in Base Charge)
B3: Year 1 | C3: Year 2 | D3: Year 3 | E3: Year 4 | F3: Year 5 | G3: Year 6 | H3: Year 7 | I3: Year 8
A4: Process Summary
A6: General Accounting & Sox | B6: 0 | C6: 0 | D6: 0.022916667 | E6: 0.047916667 | F6: 0.072916667 | G6: 0.12083333 | H6: 0.125 | I6: 0.125
A8: Fixed Assets | B8: 0 | C8: 0 | D8: 0.022916667 | E8: 0.047916667 | F8: 0.072916667 | G8: 0.12083333 | H8: 0.125 | I8: 0.125
A10: Accounts Payable | B10: 0 | C10: 0.038277512 | D10: 0.10087719 | E10: 0.15350877 | F10: 0.19005848 | G10: 0.20906433 | H10: 0.22660819 | I10: 0.22807018
A12: T&E | B12: 0 | C12: 0 | D12: 0.022916667 | E12: 0.047916667 | F12: 0.072916667 | G12: 0.12083333 | H12: 0.125 | I12: 0.125
A14: Order to Cash | B14: 0 | C14: 0 | D14: 0.022916667 | E14: 0.047916667 | F14: 0.072916667 | G14: 0.12083333 | H14: 0.125 | I14: 0.125
A16: Requistion to Pay | B16: 0 | C16: 0.02507837 | D16: 0.066091954 | E16: 0.10057471 | F16: 0.13505747 | G16: 0.16954023 | H16: 0.17241379 | I16: 0.17241379
A18: Productivity Measures
B19: Description of Measure | C19: Details of Calculation | D19: Annual Target Level
A20: Process Area | D20: Year 1 | E20: Year 2 | F20: Year 3 | G20: Year 4 | H20: Year 5 | I20: Year 6 | J20: Year 7 | K20: Year 8
A21: General Accounting & Sox | B21: FTE | C21: # FTE to be released (avg. Figures) | D21: 0 | E21: 0 | F21: 0.33229167 | G21: 0.69479167 | H21: 1.0572917 | I21: 1.7520833 | J21: 1.8125 | K21: 1.8125
A25: Fixed Assets | B25: FTE | C25: # FTE to be released (avg. Figures) | D25: 0 | E25: 0 | F25: 0.057291667 | G25: 0.11979167 | H25: 0.18229167 | I25: 0.30208333 | J25: 0.3125 | K25: 0.3125
A29: Accounts Payable | B29: FTE | C29: # FTE to be released (avg. Figures) | D29: 0 | E29: 2 | F29: 5.75 | G29: 8.75 | H29: 10.833333 | I29: 11.916667 | J29: 12.916667 | K29: 13
A33: T&E | B33: FTE | C33: # FTE to be released (avg. Figures) | D33: 0 | E33: 0 | F33: 0.20625 | G33: 0.43125 | H33: 0.65625 | I33: 1.0875 | J33: 1.125 | K33: 1.125
A37: Order To Cash | B37: FTE | C37: # FTE to be released (avg. Figures) | D37: 0 | E37: 0 | F37: 0.32083333 | G37: 0.67083333 | H37: 1.0208333 | I37: 1.6916667 | J37: 1.75 | K37: 1.75
A41: Requistion To Pay | B41: FTE | C41: # FTE to be released (avg. Figures) | D41: 0 | E41: 0.66666667 | F41: 1.9166667 | G41: 2.9166667 | H41: 3.9166667 | I41: 4.9166667 | J41: 5 | K41: 5

Sheet Centre One-BC
A1: BASE CHARGE SUMMARY (US$)
A2: Centre One | C2: Year 1 | D2: Year 2 | E2: Year 3 | F2: Year 4 | G2: Year 5 | H2: Year 6 | I2: Year 7 | J2: Year 8
B3: Process Summary
B4: General Accounting & Sox | C4: =+SUM('Switzerland-BC:UK-BC'!$C3) | D4: =+SUM('Switzerland-BC:UK-BC'!$D3) | E4: =+SUM('Switzerland-BC:UK-BC'!$E3) | F4: =+SUM('Switzerland-BC:UK-BC'!$F3) | G4: =+SUM('Switzerland-BC:UK-BC'!$G3) | H4: =+SUM('Switzerland-BC:UK-BC'!$H3) | I4: =+SUM('Switzerland-BC:UK-BC'!$I3) | J4: =+SUM('Switzerland-BC:UK-BC'!$J3)
B5: Fixed Assets | C5: =+SUM('Switzerland-BC:UK-BC'!$C4) | D5: =+SUM('Switzerland-BC:UK-BC'!$D4) | E5: =+SUM('Switzerland-BC:UK-BC'!$E4) | F5: =+SUM('Switzerland-BC:UK-BC'!$F4) | G5: =+SUM('Switzerland-BC:UK-BC'!$G4) | H5: =+SUM('Switzerland-BC:UK-BC'!$H4) | I5: =+SUM('Switzerland-BC:UK-BC'!$I4) | J5: =+SUM('Switzerland-BC:UK-BC'!$J4)
B6: Accounts Payable | C6: =+SUM('Switzerland-BC:UK-BC'!$C5) | D6: =+SUM('Switzerland-BC:UK-BC'!$D5) | E6: =+SUM('Switzerland-BC:UK-BC'!$E5) | F6: =+SUM('Switzerland-BC:UK-BC'!$F5) | G6: =+SUM('Switzerland-BC:UK-BC'!$G5) | H6: =+SUM('Switzerland-BC:UK-BC'!$H5) | I6: =+SUM('Switzerland-BC:UK-BC'!$I5) | J6: =+SUM('Switzerland-BC:UK-BC'!$J5)
B7: T&E | C7: =+SUM('Switzerland-BC:UK-BC'!$C6) | D7: =+SUM('Switzerland-BC:UK-BC'!$D6) | E7: =+SUM('Switzerland-BC:UK-BC'!$E6) | F7: =+SUM('Switzerland-BC:UK-BC'!$F6) | G7: =+SUM('Switzerland-BC:UK-BC'!$G6) | H7: =+SUM('Switzerland-BC:UK-BC'!$H6) | I7: =+SUM('Switzerland-BC:UK-BC'!$I6) | J7: =+SUM('Switzerland-BC:UK-BC'!$J6)
B8: Order to Cash | C8: =+SUM('Switzerland-BC:UK-BC'!$C7) | D8: =+SUM('Switzerland-BC:UK-BC'!$D7) | E8: =+SUM('Switzerland-BC:UK-BC'!$E7) | F8: =+SUM('Switzerland-BC:UK-BC'!$F7) | G8: =+SUM('Switzerland-BC:UK-BC'!$G7) | H8: =+SUM('Switzerland-BC:UK-BC'!$H7) | I8: =+SUM('Switzerland-BC:UK-BC'!$I7) | J8: =+SUM('Switzerland-BC:UK-BC'!$J7)
B9: Requistion to Pay | C9: =+SUM('Switzerland-BC:UK-BC'!$C8) | D9: =+SUM('Switzerland-BC:UK-BC'!$D8) | E9: =+SUM('Switzerland-BC:UK-BC'!$E8) | F9: =+SUM('Switzerland-BC:UK-BC'!$F8) | G9: =+SUM('Switzerland-BC:UK-BC'!$G8) | H9: =+SUM('Switzerland-BC:UK-BC'!$H8) | I9: =+SUM('Switzerland-BC:UK-BC'!$I8) | J9: =+SUM('Switzerland-BC:UK-BC'!$J8)
B10: Total Base Charge All Countries | C10: =SUM(C4:C9) | D10: =SUM(D4:D9) | E10: =SUM(E4:E9) | F10: =SUM(F4:F9) | G10: =SUM(G4:G9) | H10: =SUM(H4:H9) | I10: =SUM(I4:I9) | J10: =SUM(J4:J9)
B11: General Accounting & Sox
B12: Switzerland | C12: ='Switzerland-BC'!$C$3 | D12: ='Switzerland-BC'!$D$3 | E12: ='Switzerland-BC'!$E$3 | F12: ='Switzerland-BC'!$F$3 | G12: ='Switzerland-BC'!$G$3 | H12: ='Switzerland-BC'!$H$3 | I12: ='Switzerland-BC'!$I$3 | J12: ='Switzerland-BC'!$J$3
B13: United States | C13: ='US-BC'!$C$3 | D13: ='US-BC'!$D$3 | E13: ='US-BC'!$E$3 | F13: ='US-BC'!$F$3 | G13: ='US-BC'!$G$3 | H13: ='US-BC'!$H$3 | I13: ='US-BC'!$I$3 | J13: ='US-BC'!$J$3
B14: France | C14: ='France-BC'!$C$3 | D14: ='France-BC'!$D$3 | E14: ='France-BC'!$E$3 | F14: ='France-BC'!$F$3 | G14: ='France-BC'!$G$3 | H14: ='France-BC'!$H$3 | I14: ='France-BC'!$I$3 | J14: ='France-BC'!$J$3
B15: Germany | C15: ='Germany-BC'!$C$3 | D15: ='Germany-BC'!$D$3 | E15: ='Germany-BC'!$E$3 | F15: ='Germany-BC'!$F$3 | G15: ='Germany-BC'!$G$3 | H15: ='Germany-BC'!$H$3 | I15: ='Germany-BC'!$I$3 | J15: ='Germany-BC'!$J$3
B16: Germany Production | C16: ='Germany Production-BC'!$C$3 | D16: ='Germany Production-BC'!$D$3 | E16: ='Germany Production-BC'!$E$3 | F16: ='Germany Production-BC'!$F$3 | G16: ='Germany Production-BC'!$G$3 | H16: ='Germany Production-BC'!$H$3 | I16: ='Germany Production-BC'!$I$3 | J16: ='Germany Production-BC'!$J$3
B17: Spain | C17: ='Spain-BC'!$C$3 | D17: ='Spain-BC'!$D$3 | E17: ='Spain-BC'!$E$3 | F17: ='Spain-BC'!$F$3 | G17: ='Spain-BC'!$G$3 | H17: ='Spain-BC'!$H$3 | I17: ='Spain-BC'!$I$3 | J17: ='Spain-BC'!$J$3
B18: Italy | C18: ='Italy-BC'!$C$3 | D18: ='Italy-BC'!$D$3 | E18: ='Italy-BC'!$E$3 | F18: ='Italy-BC'!$F$3 | G18: ='Italy-BC'!$G$3 | H18: ='Italy-BC'!$H$3 | I18: ='Italy-BC'!$I$3 | J18: ='Italy-BC'!$J$3
B19: United Kingdom | C19: ='UK-BC'!$C$3 | D19: ='UK-BC'!$D$3 | E19: ='UK-BC'!$E$3 | F19: ='UK-BC'!$F$3 | G19: ='UK-BC'!$G$3 | H19: ='UK-BC'!$H$3 | I19: ='UK-BC'!$I$3 | J19: ='UK-BC'!$J$3
B20: Sub Total | C20: =SUM(C12:C19) | D20: =SUM(D12:D19) | E20: =SUM(E12:E19) | F20: =SUM(F12:F19) | G20: =SUM(G12:G19) | H20: =SUM(H12:H19) | I20: =SUM(I12:I19) | J20: =SUM(J12:J19)
B21: Fixed Assets
B22: Switzerland | C22: ='Switzerland-BC'!$C$4 | D22: ='Switzerland-BC'!$D$4 | E22: ='Switzerland-BC'!$E$4 | F22: ='Switzerland-BC'!$F$4 | G22: ='Switzerland-BC'!$G$4 | H22: ='Switzerland-BC'!$H$4 | I22: ='Switzerland-BC'!$I$4 | J22: ='Switzerland-BC'!$J$4
B23: United States | C23: ='US-BC'!$C$4 | D23: ='US-BC'!$D$4 | E23: ='US-BC'!$E$4 | F23: ='US-BC'!$F$4 | G23: ='US-BC'!$G$4 | H23: ='US-BC'!$H$4 | I23: ='US-BC'!$I$4 | J23: ='US-BC'!$J$4
B24: France | C24: ='France-BC'!$C$4 | D24: ='France-BC'!$D$4 | E24: ='France-BC'!$E$4 | F24: ='France-BC'!$F$4 | G24: ='France-BC'!$G$4 | H24: ='France-BC'!$H$4 | I24: ='France-BC'!$I$4 | J24: ='France-BC'!$J$4
B25: Germany | C25: ='Germany-BC'!$C$4 | D25: ='Germany-BC'!$D$4 | E25: ='Germany-BC'!$E$4 | F25: ='Germany-BC'!$F$4 | G25: ='Germany-BC'!$G$4 | H25: ='Germany-BC'!$H$4 | I25: ='Germany-BC'!$I$4 | J25: ='Germany-BC'!$J$4
B26: Germany Production | C26: ='Germany Production-BC'!$C$4 | D26: ='Germany Production-BC'!$D$4 | E26: ='Germany Production-BC'!$E$4 | F26: ='Germany Production-BC'!$F$4 | G26: ='Germany Production-BC'!$G$4 | H26: ='Germany Production-BC'!$H$4 | I26: ='Germany Production-BC'!$I$4 | J26: ='Germany Production-BC'!$J$4
B27: Spain | C27: ='Spain-BC'!$C$4 | D27: ='Spain-BC'!$D$4 | E27: ='Spain-BC'!$E$4 | F27: ='Spain-BC'!$F$4 | G27: ='Spain-BC'!$G$4 | H27: ='Spain-BC'!$H$4 | I27: ='Spain-BC'!$I$4 | J27: ='Spain-BC'!$J$4
B28: Italy | C28: ='Italy-BC'!$C$4 | D28: ='Italy-BC'!$D$4 | E28: ='Italy-BC'!$E$4 | F28: ='Italy-BC'!$F$4 | G28: ='Italy-BC'!$G$4 | H28: ='Italy-BC'!$H$4 | I28: ='Italy-BC'!$I$4 | J28: ='Italy-BC'!$J$4
B29: United Kingdom | C29: ='UK-BC'!$C$4 | D29: ='UK-BC'!$D$4 | E29: ='UK-BC'!$E$4 | F29: ='UK-BC'!$F$4 | G29: ='UK-BC'!$G$4 | H29: ='UK-BC'!$H$4 | I29: ='UK-BC'!$I$4 | J29: ='UK-BC'!$J$4
B30: Sub Total | C30: =SUM(C22:C29) | D30: =SUM(D22:D29) | E30: =SUM(E22:E29) | F30: =SUM(F22:F29) | G30: =SUM(G22:G29) | H30: =SUM(H22:H29) | I30: =SUM(I22:I29) | J30: =SUM(J22:J29)
B31: Accounts Payable
B32: Switzerland | C32: ='Switzerland-BC'!$C$5 | D32: ='Switzerland-BC'!$D$5 | E32: ='Switzerland-BC'!$E$5 | F32: ='Switzerland-BC'!$F$5 | G32: ='Switzerland-BC'!$G$5 | H32: ='Switzerland-BC'!$H$5 | I32: ='Switzerland-BC'!$I$5 | J32: ='Switzerland-BC'!$J$5
B33: United States | C33: ='US-BC'!$C$5 | D33: ='US-BC'!$D$5 | E33: ='US-BC'!$E$5 | F33: ='US-BC'!$F$5 | G33: ='US-BC'!$G$5 | H33: ='US-BC'!$H$5 | I33: ='US-BC'!$I$5 | J33: ='US-BC'!$J$5
B34: France | C34: ='France-BC'!$C$5 | D34: ='France-BC'!$D$5 | E34: ='France-BC'!$E$5 | F34: ='France-BC'!$F$5 | G34: ='France-BC'!$G$5 | H34: ='France-BC'!$H$5 | I34: ='France-BC'!$I$5 | J34: ='France-BC'!$J$5
B35: Germany | C35: ='Germany-BC'!$C$5 | D35: ='Germany-BC'!$D$5 | E35: ='Germany-BC'!$E$5 | F35: ='Germany-BC'!$F$5 | G35: ='Germany-BC'!$G$5 | H35: ='Germany-BC'!$H$5 | I35: ='Germany-BC'!$I$5 | J35: ='Germany-BC'!$J$5
B36: Germany Production | C36: ='Germany Production-BC'!$C$5 | D36: ='Germany Production-BC'!$D$5 | E36: ='Germany Production-BC'!$E$5 | F36: ='Germany Production-BC'!$F$5 | G36: ='Germany Production-BC'!$G$5 | H36: ='Germany Production-BC'!$H$5 | I36: ='Germany Production-BC'!$I$5 | J36: ='Germany Production-BC'!$J$5
B37: Spain | C37: ='Spain-BC'!$C$5 | D37: ='Spain-BC'!$D$5 | E37: ='Spain-BC'!$E$5 | F37: ='Spain-BC'!$F$5 | G37: ='Spain-BC'!$G$5 | H37: ='Spain-BC'!$H$5 | I37: ='Spain-BC'!$I$5 | J37: ='Spain-BC'!$J$5
B38: Italy | C38: ='Italy-BC'!$C$5 | D38: ='Italy-BC'!$D$5 | E38: ='Italy-BC'!$E$5 | F38: ='Italy-BC'!$F$5 | G38: ='Italy-BC'!$G$5 | H38: ='Italy-BC'!$H$5 | I38: ='Italy-BC'!$I$5 | J38: ='Italy-BC'!$J$5
B39: United Kingdom | C39: ='UK-BC'!$C$5 | D39: ='UK-BC'!$D$5 | E39: ='UK-BC'!$E$5 | F39: ='UK-BC'!$F$5 | G39: ='UK-BC'!$G$5 | H39: ='UK-BC'!$H$5 | I39: ='UK-BC'!$I$5 | J39: ='UK-BC'!$J$5
B40: Sub Total | C40: =SUM(C32:C39) | D40: =SUM(D32:D39) | E40: =SUM(E32:E39) | F40: =SUM(F32:F39) | G40: =SUM(G32:G39) | H40: =SUM(H32:H39) | I40: =SUM(I32:I39) | J40: =SUM(J32:J39)
B41: T&E
B42: Switzerland | C42: ='Switzerland-BC'!$C$6 | D42: ='Switzerland-BC'!$D$6 | E42: ='Switzerland-BC'!$E$6 | F42: ='Switzerland-BC'!$F$6 | G42: ='Switzerland-BC'!$G$6 | H42: ='Switzerland-BC'!$H$6 | I42: ='Switzerland-BC'!$I$6 | J42: ='Switzerland-BC'!$J$6
B43: United States | C43: ='US-BC'!$C$6 | D43: ='US-BC'!$D$6 | E43: ='US-BC'!$E$6 | F43: ='US-BC'!$F$6 | G43: ='US-BC'!$G$6 | H43: ='US-BC'!$H$6 | I43: ='US-BC'!$I$6 | J43: ='US-BC'!$J$6
B44: France | C44: ='France-BC'!$C$6 | D44: ='France-BC'!$D$6 | E44: ='France-BC'!$E$6 | F44: ='France-BC'!$F$6 | G44: ='France-BC'!$G$6 | H44: ='France-BC'!$H$6 | I44: ='France-BC'!$I$6 | J44: ='France-BC'!$J$6
B45: Germany | C45: ='Germany-BC'!$C$6 | D45: ='Germany-BC'!$D$6 | E45: ='Germany-BC'!$E$6 | F45: ='Germany-BC'!$F$6 | G45: ='Germany-BC'!$G$6 | H45: ='Germany-BC'!$H$6 | I45: ='Germany-BC'!$I$6 | J45: ='Germany-BC'!$J$6
B46: Germany Production | C46: ='Germany Production-BC'!$C$6 | D46: ='Germany Production-BC'!$D$6 | E46: ='Germany Production-BC'!$E$6 | F46: ='Germany Production-BC'!$F$6 | G46: ='Germany Production-BC'!$G$6 | H46: ='Germany Production-BC'!$H$6 | I46: ='Germany Production-BC'!$I$6 | J46: ='Germany Production-BC'!$J$6
B47: Spain | C47: ='Spain-BC'!$C$6 | D47: ='Spain-BC'!$D$6 | E47: ='Spain-BC'!$E$6 | F47: ='Spain-BC'!$F$6 | G47: ='Spain-BC'!$G$6 | H47: ='Spain-BC'!$H$6 | I47: ='Spain-BC'!$I$6 | J47: ='Spain-BC'!$J$6
B48: Italy | C48: ='Italy-BC'!$C$6 | D48: ='Italy-BC'!$D$6 | E48: ='Italy-BC'!$E$6 | F48: ='Italy-BC'!$F$6 | G48: ='Italy-BC'!$G$6 | H48: ='Italy-BC'!$H$6 | I48: ='Italy-BC'!$I$6 | J48: ='Italy-BC'!$J$6
B49: United Kingdom | C49: ='UK-BC'!$C$6 | D49: ='UK-BC'!$D$6 | E49: ='UK-BC'!$E$6 | F49: ='UK-BC'!$F$6 | G49: ='UK-BC'!$G$6 | H49: ='UK-BC'!$H$6 | I49: ='UK-BC'!$I$6 | J49: ='UK-BC'!$J$6
B50: Sub Total | C50: =SUM(C42:C49) | D50: =SUM(D42:D49) | E50: =SUM(E42:E49) | F50: =SUM(F42:F49) | G50: =SUM(G42:G49) | H50: =SUM(H42:H49) | I50: =SUM(I42:I49) | J50: =SUM(J42:J49)
B51: Order to Cash
B52: Switzerland | C52: ='Switzerland-BC'!$C$7 | D52: ='Switzerland-BC'!$D$7 | E52: ='Switzerland-BC'!$E$7 | F52: ='Switzerland-BC'!$F$7 | G52: ='Switzerland-BC'!$G$7 | H52: ='Switzerland-BC'!$H$7 | I52: ='Switzerland-BC'!$I$7 | J52: ='Switzerland-BC'!$J$7
B53: United States | C53: ='US-BC'!$C$7 | D53: ='US-BC'!$D$7 | E53: ='US-BC'!$E$7 | F53: ='US-BC'!$F$7 | G53: ='US-BC'!$G$7 | H53: ='US-BC'!$H$7 | I53: ='US-BC'!$I$7 | J53: ='US-BC'!$J$7
B54: France | C54: ='France-BC'!$C$7 | D54: ='France-BC'!$D$7 | E54: ='France-BC'!$E$7 | F54: ='France-BC'!$F$7 | G54: ='France-BC'!$G$7 | H54: ='France-BC'!$H$7 | I54: ='France-BC'!$I$7 | J54: ='France-BC'!$J$7
B55: Germany | C55: ='Germany-BC'!$C$7 | D55: ='Germany-BC'!$D$7 | E55: ='Germany-BC'!$E$7 | F55: ='Germany-BC'!$F$7 | G55: ='Germany-BC'!$G$7 | H55: ='Germany-BC'!$H$7 | I55: ='Germany-BC'!$I$7 | J55: ='Germany-BC'!$J$7
B56: Germany Production | C56: ='Germany Production-BC'!$C$7 | D56: ='Germany Production-BC'!$D$7 | E56: ='Germany Production-BC'!$E$7 | F56: ='Germany Production-BC'!$F$7 | G56: ='Germany Production-BC'!$G$7 | H56: ='Germany Production-BC'!$H$7 | I56: ='Germany Production-BC'!$I$7 | J56: ='Germany Production-BC'!$J$7
B57: Spain | C57: ='Spain-BC'!$C$7 | D57: ='Spain-BC'!$D$7 | E57: ='Spain-BC'!$E$7 | F57: ='Spain-BC'!$F$7 | G57: ='Spain-BC'!$G$7 | H57: ='Spain-BC'!$H$7 | I57: ='Spain-BC'!$I$7 | J57: ='Spain-BC'!$J$7
B58: Italy | C58: ='Italy-BC'!$C$7 | D58: ='Italy-BC'!$D$7 | E58: ='Italy-BC'!$E$7 | F58: ='Italy-BC'!$F$7 | G58: ='Italy-BC'!$G$7 | H58: ='Italy-BC'!$H$7 | I58: ='Italy-BC'!$I$7 | J58: ='Italy-BC'!$J$7
B59: United Kingdom | C59: ='UK-BC'!$C$7 | D59: ='UK-BC'!$D$7 | E59: ='UK-BC'!$E$7 | F59: ='UK-BC'!$F$7 | G59: ='UK-BC'!$G$7 | H59: ='UK-BC'!$H$7 | I59: ='UK-BC'!$I$7 | J59: ='UK-BC'!$J$7
B60: Sub Total | C60: =SUM(C52:C59) | D60: =SUM(D52:D59) | E60: =SUM(E52:E59) | F60: =SUM(F52:F59) | G60: =SUM(G52:G59) | H60: =SUM(H52:H59) | I60: =SUM(I52:I59) | J60: =SUM(J52:J59)
B61: Requistion to Pay
B62: Switzerland | C62: ='Switzerland-BC'!$C$8 | D62: ='Switzerland-BC'!$D$8 | E62: ='Switzerland-BC'!$E$8 | F62: ='Switzerland-BC'!$F$8 | G62: ='Switzerland-BC'!$G$8 | H62: ='Switzerland-BC'!$H$8 | I62: ='Switzerland-BC'!$I$8 | J62: ='Switzerland-BC'!$J$8
B63: United States | C63: ='US-BC'!$C$8 | D63: ='US-BC'!$D$8 | E63: ='US-BC'!$E$8 | F63: ='US-BC'!$F$8 | G63: ='US-BC'!$G$8 | H63: ='US-BC'!$H$8 | I63: ='US-BC'!$I$8 | J63: ='US-BC'!$J$8
B64: France | C64: ='France-BC'!$C$8 | D64: ='France-BC'!$D$8 | E64: ='France-BC'!$E$8 | F64: ='France-BC'!$F$8 | G64: ='France-BC'!$G$8 | H64: ='France-BC'!$H$8 | I64: ='France-BC'!$I$8 | J64: ='France-BC'!$J$8
B65: Germany | C65: ='Germany-BC'!$C$8 | D65: ='Germany-BC'!$D$8 | E65: ='Germany-BC'!$E$8 | F65: ='Germany-BC'!$F$8 | G65: ='Germany-BC'!$G$8 | H65: ='Germany-BC'!$H$8 | I65: ='Germany-BC'!$I$8 | J65: ='Germany-BC'!$J$8
B66: Germany Production | C66: ='Germany Production-BC'!$C$8 | D66: ='Germany Production-BC'!$D$8 | E66: ='Germany Production-BC'!$E$8 | F66: ='Germany Production-BC'!$F$8 | G66: ='Germany Production-BC'!$G$8 | H66: ='Germany Production-BC'!$H$8 | I66: ='Germany Production-BC'!$I$8 | J66: ='Germany Production-BC'!$J$8
B67: Spain | C67: ='Spain-BC'!$C$8 | D67: ='Spain-BC'!$D$8 | E67: ='Spain-BC'!$E$8 | F67: ='Spain-BC'!$F$8 | G67: ='Spain-BC'!$G$8 | H67: ='Spain-BC'!$H$8 | I67: ='Spain-BC'!$I$8 | J67: ='Spain-BC'!$J$8
B68: Italy | C68: ='Italy-BC'!$C$8 | D68: ='Italy-BC'!$D$8 | E68: ='Italy-BC'!$E$8 | F68: ='Italy-BC'!$F$8 | G68: ='Italy-BC'!$G$8 | H68: ='Italy-BC'!$H$8 | I68: ='Italy-BC'!$I$8 | J68: ='Italy-BC'!$J$8
B69: United Kingdom | C69: ='UK-BC'!$C$8 | D69: ='UK-BC'!$D$8 | E69: ='UK-BC'!$E$8 | F69: ='UK-BC'!$F$8 | G69: ='UK-BC'!$G$8 | H69: ='UK-BC'!$H$8 | I69: ='UK-BC'!$I$8 | J69: ='UK-BC'!$J$8
B70: Sub Total | C70: =SUM(C62:C69) | D70: =SUM(D62:D69) | E70: =SUM(E62:E69) | F70: =SUM(F62:F69) | G70: =SUM(G62:G69) | H70: =SUM(H62:H69) | I70: =SUM(I62:I69) | J70: =SUM(J62:J69)
B71: Total Base Charges All Countries | C71: =C20+C30+C40+C50+C60+C70 | D71: =D20+D30+D40+D50+D60+D70 | E71: =E20+E30+E40+E50+E60+E70 | F71: =F20+F30+F40+F50+F60+F70 | G71: =G20+G30+G40+G50+G60+G70 | H71: =H20+H30+H40+H50+H60+H70 | I71: =I20+I30+I40+I50+I60+I70 | J71: =J20+J30+J40+J50+J60+J70
B72: Country Summary
B73: Switzerland | C73: ='Switzerland-BC'!C9 | D73: ='Switzerland-BC'!D9 | E73: ='Switzerland-BC'!E9 | F73: ='Switzerland-BC'!F9 | G73: ='Switzerland-BC'!G9 | H73: ='Switzerland-BC'!H9 | I73: ='Switzerland-BC'!I9 | J73: ='Switzerland-BC'!J9
B74: United States | C74: ='US-BC'!C9 | D74: ='US-BC'!D9 | E74: ='US-BC'!E9 | F74: ='US-BC'!F9 | G74: ='US-BC'!G9 | H74: ='US-BC'!H9 | I74: ='US-BC'!I9 | J74: ='US-BC'!J9
B75: France | C75: ='France-BC'!C9 | D75: ='France-BC'!D9 | E75: ='France-BC'!E9 | F75: ='France-BC'!F9 | G75: ='France-BC'!G9 | H75: ='France-BC'!H9 | I75: ='France-BC'!I9 | J75: ='France-BC'!J9
B76: Germany | C76: ='Germany-BC'!C9 | D76: ='Germany-BC'!D9 | E76: ='Germany-BC'!E9 | F76: ='Germany-BC'!F9 | G76: ='Germany-BC'!G9 | H76: ='Germany-BC'!H9 | I76: ='Germany-BC'!I9 | J76: ='Germany-BC'!J9
B77: Germany Production | C77: ='Germany Production-BC'!C9 | D77: ='Germany Production-BC'!D9 | E77: ='Germany Production-BC'!E9 | F77: ='Germany Production-BC'!F9 | G77: ='Germany Production-BC'!G9 | H77: ='Germany Production-BC'!H9 | I77: ='Germany Production-BC'!I9 | J77: ='Germany Production-BC'!J9
B78: Spain | C78: ='Spain-BC'!C9 | D78: ='Spain-BC'!D9 | E78: ='Spain-BC'!E9 | F78: ='Spain-BC'!F9 | G78: ='Spain-BC'!G9 | H78: ='Spain-BC'!H9 | I78: ='Spain-BC'!I9 | J78: ='Spain-BC'!J9
B79: Italy | C79: ='Italy-BC'!C9 | D79: ='Italy-BC'!D9 | E79: ='Italy-BC'!E9 | F79: ='Italy-BC'!F9 | G79: ='Italy-BC'!G9 | H79: ='Italy-BC'!H9 | I79: ='Italy-BC'!I9 | J79: ='Italy-BC'!J9
B80: United Kingdom | C80: ='UK-BC'!C9 | D80: ='UK-BC'!D9 | E80: ='UK-BC'!E9 | F80: ='UK-BC'!F9 | G80: ='UK-BC'!G9 | H80: ='UK-BC'!H9 | I80: ='UK-BC'!I9 | J80: ='UK-BC'!J9
B81: Total Base Charges All Countries | C81: =SUM(C73:C80) | D81: =SUM(D73:D80) | E81: =SUM(E73:E80) | F81: =SUM(F73:F80) | G81: =SUM(G73:G80) | H81: =SUM(H73:H80) | I81: =SUM(I73:I80) | J81: =SUM(J73:J80)

Sheet Switzerland-BC
A1: BASE CHARGES INPUT FORM - CENTRE ONE (US$)
A2: Country | B2: Process Area | C2: Year 1 | D2: Year 2 | E2: Year 3 | F2: Year 4 | G2: Year 5 | H2: Year 6 | I2: Year 7 | J2: Year 8
A3: Switzerland | B3: General Accounting & Sox | C3: =SUM('Appendix B - prod by country'!D2:O3,'Appendix B - prod by country'!D6:O6)*1.3*1000+SUM('Appendix A - pilot by country'!D2:O3,'Appendix A - pilot by country'!D6:O6)*1.3*1000 | D3: =SUM('Appendix B - prod by country'!P2:AA3,'Appendix B - prod by country'!P6:AA6)*1.3*1000 | E3: =SUM('Appendix B - prod by country'!AB2:AM3,'Appendix B - prod by country'!AB6:AM6)*1.3*1000 | F3: =SUM('Appendix B - prod by country'!AN2:AY3,'Appendix B - prod by country'!AN6:AY6)*1.3*1000 | G3: =SUM('Appendix B - prod by country'!AZ2:BK3,'Appendix B - prod by country'!AZ6:BK6)*1.3*1000 | H3: =SUM('Appendix B - prod by country'!BL2:BW3,'Appendix B - prod by country'!BL6:BW6)*1.3*1000 | I3: =SUM('Appendix B - prod by country'!BX2:CI3,'Appendix B - prod by country'!BX6:CI6)*1.3*1000 | J3: =SUM('Appendix B - prod by country'!CJ2:CJ3,'Appendix B - prod by country'!CJ6)*1.3*1000
B4: Fixed Assets | C4: =SUM('Appendix B - prod by country'!D4:O4)*1.3*1000+SUM('Appendix A - pilot by country'!D4:O4)*1.3*1000 | D4: =SUM('Appendix B - prod by country'!P4:AA4)*1.3*1000 | E4: =SUM('Appendix B - prod by country'!AB4:AM4)*1.3*1000 | F4: =SUM('Appendix B - prod by country'!AN4:AY4)*1.3*1000 | G4: =SUM('Appendix B - prod by country'!AZ4:BK4)*1.3*1000 | H4: =SUM('Appendix B - prod by country'!BL4:BW4)*1.3*1000 | I4: =SUM('Appendix B - prod by country'!BX4:CI4)*1.3*1000 | J4: =SUM('Appendix B - prod by country'!CJ4)*1.3*1000
B5: Accounts Payable | C5: =SUM('Appendix B - prod by country'!D5:O5)*1.3*1000+SUM('Appendix A - pilot by country'!D5:O5)*1.3*1000 | D5: =SUM('Appendix B - prod by country'!P5:AA5)*1.3*1000 | E5: =SUM('Appendix B - prod by country'!AB5:AM5)*1.3*1000 | F5: =SUM('Appendix B - prod by country'!AN5:AY5)*1.3*1000 | G5: =SUM('Appendix B - prod by country'!AZ5:BK5)*1.3*1000 | H5: =SUM('Appendix B - prod by country'!BL5:BW5)*1.3*1000 | I5: =SUM('Appendix B - prod by country'!BX5:CI5)*1.3*1000 | J5: =SUM('Appendix B - prod by country'!CJ5)*1.3*1000
B6: T&E | C6: =SUM('Appendix B - prod by country'!D7:O7)*1.3*1000+SUM('Appendix A - pilot by country'!D7:O7)*1.3*1000 | D6: =SUM('Appendix B - prod by country'!P7:AA7)*1.3*1000 | E6: =SUM('Appendix B - prod by country'!AB7:AM7)*1.3*1000 | F6: =SUM('Appendix B - prod by country'!AN7:AY7)*1.3*1000 | G6: =SUM('Appendix B - prod by country'!AZ7:BK7)*1.3*1000 | H6: =SUM('Appendix B - prod by country'!BL7:BW7)*1.3*1000 | I6: =SUM('Appendix B - prod by country'!BX7:CI7)*1.3*1000 | J6: =SUM('Appendix B - prod by country'!CJ7)*1.3*1000
B7: Order to Cash | C7: =SUM('Appendix B - prod by country'!D8:O8)*1.3*1000+SUM('Appendix A - pilot by country'!D8:O8)*1.3*1000 | D7: =SUM('Appendix B - prod by country'!P8:AA8)*1.3*1000 | E7: =SUM('Appendix B - prod by country'!AB8:AM8)*1.3*1000 | F7: =SUM('Appendix B - prod by country'!AN8:AY8)*1.3*1000 | G7: =SUM('Appendix B - prod by country'!AZ8:BK8)*1.3*1000 | H7: =SUM('Appendix B - prod by country'!BL8:BW8)*1.3*1000 | I7: =SUM('Appendix B - prod by country'!BX8:CI8)*1.3*1000 | J7: =SUM('Appendix B - prod by country'!CJ8)*1.3*1000
B8: Requistion to Pay | C8: =SUM('Appendix B - prod by country'!D9:O9)*1.3*1000+SUM('Appendix A - pilot by country'!D9:O9)*1.3*1000 | D8: =SUM('Appendix B - prod by country'!P9:AA9)*1.3*1000 | E8: =SUM('Appendix B - prod by country'!AB9:AM9)*1.3*1000 | F8: =SUM('Appendix B - prod by country'!AN9:AY9)*1.3*1000 | G8: =SUM('Appendix B - prod by country'!AZ9:BK9)*1.3*1000 | H8: =SUM('Appendix B - prod by country'!BL9:BW9)*1.3*1000 | I8: =SUM('Appendix B - prod by country'!BX9:CI9)*1.3*1000 | J8: =SUM('Appendix B - prod by country'!CJ9)*1.3*1000
B9: TOTAL BASE CHARGES | C9: =SUM(C3:C8) | D9: =SUM(D3:D8) | E9: =SUM(E3:E8) | F9: =SUM(F3:F8) | G9: =SUM(G3:G8) | H9: =SUM(H3:H8) | I9: =SUM(I3:I8) | J9: =SUM(J3:J8)

Sheet US-BC
A1: BASE CHARGES INPUT FORM - CENTRE ONE (US$)
A2: Country | B2: Process Area | C2: Year 1 | D2: Year 2 | E2: Year 3 | F2: Year 4 | G2: Year 5 | H2: Year 6 | I2: Year 7
A3: United States | B3: General Accounting & Sox
B4: Fixed Assets
B5: Accounts Payable
B6: T&E
B7: Order to Cash
B8: Requistion to Pay
B9: TOTAL BASE CHARGES | C9: =SUM(C3:C8) | D9: =SUM(D3:D8) | E9: =SUM(E3:E8) | F9: =SUM(F3:F8) | G9: =SUM(G3:G8) | H9: =SUM(H3:H8) | I9: =SUM(I3:I8)

Sheet France-BC
A1: BASE CHARGES INPUT FORM - CENTRE ONE (US$)
A2: Country | B2: Process Area | C2: Year 1 | D2: Year 2 | E2: Year 3 | F2: Year 4 | G2: Year 5 | H2: Year 6 | I2: Year 7 | J2: Year 8
A3: France | B3: General Accounting & Sox | C3: =SUM('Appendix B - prod by country'!D24:O25,'Appendix B - prod by country'!D28:O28)*1.3*1000+SUM('Appendix A - pilot by country'!D24:O25,'Appendix A - pilot by country'!D28:O28)*1.3*1000 | D3: =SUM('Appendix B - prod by country'!P24:AA25,'Appendix B - prod by country'!P28:AA28)*1.3*1000 | E3: =SUM('Appendix B - prod by country'!AB24:AM25,'Appendix B - prod by country'!AB28:AM28)*1.3*1000 | F3: =SUM('Appendix B - prod by country'!AN24:AY25,'Appendix B - prod by country'!AN28:AY28)*1.3*1000 | G3: =SUM('Appendix B - prod by country'!AZ24:BK25,'Appendix B - prod by country'!AZ28:BK28)*1.3*1000 | H3: =SUM('Appendix B - prod by country'!BL24:BW25,'Appendix B - prod by country'!BL28:BW28)*1.3*1000 | I3: =SUM('Appendix B - prod by country'!BX24:CI25,'Appendix B - prod by country'!BX28:CI28)*1.3*1000 | J3: =SUM('Appendix B - prod by country'!CJ24:CJ25,'Appendix B - prod by country'!CJ28)*1.3*1000
B4: Fixed Assets | C4: =SUM('Appendix B - prod by country'!D26:O26)*1.3*1000+SUM('Appendix A - pilot by country'!D26:O26)*1.3*1000 | D4: =SUM('Appendix B - prod by country'!P26:AA26)*1.3*1000 | E4: =SUM('Appendix B - prod by country'!AB26:AM26)*1.3*1000 | F4: =SUM('Appendix B - prod by country'!AN26:AY26)*1.3*1000 | G4: =SUM('Appendix B - prod by country'!AZ26:BK26)*1.3*1000 | H4: =SUM('Appendix B - prod by country'!BL26:BW26)*1.3*1000 | I4: =SUM('Appendix B - prod by country'!BX26:CI26)*1.3*1000 | J4: =SUM('Appendix B - prod by country'!CJ26)*1.3*1000
B5: Accounts Payable | C5: =SUM('Appendix B - prod by country'!D27:O27)*1.3*1000+SUM('Appendix A - pilot by country'!D27:O27)*1.3*1000 | D5: =SUM('Appendix B - prod by country'!P27:AA27)*1.3*1000 | E5: =SUM('Appendix B - prod by country'!AB27:AM27)*1.3*1000 | F5: =SUM('Appendix B - prod by country'!AN27:AY27)*1.3*1000 | G5: =SUM('Appendix B - prod by country'!AZ27:BK27)*1.3*1000 | H5: =SUM('Appendix B - prod by country'!BL27:BW27)*1.3*1000 | I5: =SUM('Appendix B - prod by country'!BX27:CI27)*1.3*1000 | J5: =SUM('Appendix B - prod by country'!CJ27)*1.3*1000
B6: T&E | C6: =SUM('Appendix B - prod by country'!D29:O29)*1.3*1000+SUM('Appendix A - pilot by country'!D29:O29)*1.3*1000 | D6: =SUM('Appendix B - prod by country'!P29:AA29)*1.3*1000 | E6: =SUM('Appendix B - prod by country'!AB29:AM29)*1.3*1000 | F6: =SUM('Appendix B - prod by country'!AN29:AY29)*1.3*1000 | G6: =SUM('Appendix B - prod by country'!AZ29:BK29)*1.3*1000 | H6: =SUM('Appendix B - prod by country'!BL29:BW29)*1.3*1000 | I6: =SUM('Appendix B - prod by country'!BX29:CI29)*1.3*1000 | J6: =SUM('Appendix B - prod by country'!CJ29)*1.3*1000
B7: Order to Cash | C7: =SUM('Appendix B - prod by country'!D30:O30)*1.3*1000+SUM('Appendix A - pilot by country'!D30:O30)*1.3*1000 | D7: =SUM('Appendix B - prod by country'!P30:AA30)*1.3*1000 | E7: =SUM('Appendix B - prod by country'!AB30:AM30)*1.3*1000 | F7: =SUM('Appendix B - prod by country'!AN30:AY30)*1.3*1000 | G7: =SUM('Appendix B - prod by country'!AZ30:BK30)*1.3*1000 | H7: =SUM('Appendix B - prod by country'!BL30:BW30)*1.3*1000 | I7: =SUM('Appendix B - prod by country'!BX30:CI30)*1.3*1000 | J7: =SUM('Appendix B - prod by country'!CJ30)*1.3*1000
B8: Requistion to Pay | C8: =SUM('Appendix B - prod by country'!D31:O31)*1.3*1000+SUM('Appendix A - pilot by country'!D31:O31)*1.3*1000 | D8: =SUM('Appendix B - prod by country'!P31:AA31)*1.3*1000 | E8: =SUM('Appendix B - prod by country'!AB31:AM31)*1.3*1000 | F8: =SUM('Appendix B - prod by country'!AN31:AY31)*1.3*1000 | G8: =SUM('Appendix B - prod by country'!AZ31:BK31)*1.3*1000 | H8: =SUM('Appendix B - prod by country'!BL31:BW31)*1.3*1000 | I8: =SUM('Appendix B - prod by country'!BX31:CI31)*1.3*1000 | J8: =SUM('Appendix B - prod by country'!CJ31)*1.3*1000
B9: TOTAL BASE CHARGES | C9: =SUM(C3:C8) | D9: =SUM(D3:D8) | E9: =SUM(E3:E8) | F9: =SUM(F3:F8) | G9: =SUM(G3:G8) | H9: =SUM(H3:H8) | I9: =SUM(I3:I8) | J9: =SUM(J3:J8)

Sheet Germany-BC
A1: BASE CHARGES INPUT FORM - CENTRE ONE (US$)
A2: Country | B2: Process Area | C2: Year 1 | D2: Year 2 | E2: Year 3 | F2: Year 4 | G2: Year 5 | H2: Year 6 | I2: Year 7 | J2: Year 8
A3: Germany | B3: General Accounting & Sox | C3: =SUM('Appendix B - prod by country'!D35:O36,'Appendix B - prod by country'!D39:O39)*1.3*1000+SUM('Appendix A - pilot by country'!D35:O36,'Appendix A - pilot by country'!D39:O39)*1.3*1000 | D3: =SUM('Appendix B - prod by country'!P35:AA36,'Appendix B - prod by country'!P39:AA39)*1.3*1000 | E3: =SUM('Appendix B - prod by country'!AB35:AM36,'Appendix B - prod by country'!AB39:AM39)*1.3*1000 | F3: =SUM('Appendix B - prod by country'!AN35:AY36,'Appendix B - prod by country'!AN39:AY39)*1.3*1000 | G3: =SUM('Appendix B - prod by country'!AZ35:BK36,'Appendix B - prod by country'!AZ39:BK39)*1.3*1000 | H3: =SUM('Appendix B - prod by country'!BL35:BW36,'Appendix B - prod by country'!BL39:BW39)*1.3*1000 | I3: =SUM('Appendix B - prod by country'!BX35:CI36,'Appendix B - prod by country'!BX39:CI39)*1.3*1000 | J3: =SUM('Appendix B - prod by country'!CJ35:CJ36,'Appendix B - prod by country'!CJ39)*1.3*1000
B4: Fixed Assets | C4: =SUM('Appendix B - prod by country'!D37:O37)*1.3*1000+SUM('Appendix A - pilot by country'!D37:O37)*1.3*1000 | D4: =SUM('Appendix B - prod by country'!P37:AA37)*1.3*1000 | E4: =SUM('Appendix B - prod by country'!AB37:AM37)*1.3*1000 | F4: =SUM('Appendix B - prod by country'!AN37:AY37)*1.3*1000 | G4: =SUM('Appendix B - prod by country'!AZ37:BK37)*1.3*1000 | H4: =SUM('Appendix B - prod by country'!BL37:BW37)*1.3*1000 | I4: =SUM('Appendix B - prod by country'!BX37:CI37)*1.3*1000 | J4: =SUM('Appendix B - prod by country'!CJ37)*1.3*1000
B5: Accounts Payable | C5: =SUM('Appendix B - prod by country'!D38:O38)*1.3*1000+SUM('Appendix A - pilot by country'!D38:O38)*1.3*1000 | D5: =SUM('Appendix B - prod by country'!P38:AA38)*1.3*1000 | E5: =SUM('Appendix B - prod by country'!AB38:AM38)*1.3*1000 | F5: =SUM('Appendix B - prod by country'!AN38:AY38)*1.3*1000 | G5: =SUM('Appendix B - prod by country'!AZ38:BK38)*1.3*1000 | H5: =SUM('Appendix B - prod by country'!BL38:BW38)*1.3*1000 | I5: =SUM('Appendix B - prod by country'!BX38:CI38)*1.3*1000 | J5: =SUM('Appendix B - prod by country'!CJ38)*1.3*1000
B6: T&E | C6: =SUM('Appendix B - prod by country'!D40:O40)*1.3*1000+SUM('Appendix A - pilot by country'!D40:O40)*1.3*1000 | D6: =SUM('Appendix B - prod by country'!P40:AA40)*1.3*1000 | E6: =SUM('Appendix B - prod by country'!AB40:AM40)*1.3*1000 | F6: =SUM('Appendix B - prod by country'!AN40:AY40)*1.3*1000 | G6: =SUM('Appendix B - prod by country'!AZ40:BK40)*1.3*1000 | H6: =SUM('Appendix B - prod by country'!BL40:BW40)*1.3*1000 | I6: =SUM('Appendix B - prod by country'!BX40:CI40)*1.3*1000 | J6: =SUM('Appendix B - prod by country'!CJ40)*1.3*1000
B7: Order to Cash | C7: =SUM('Appendix B - prod by country'!D41:O41)*1.3*1000+SUM('Appendix A - pilot by country'!D41:O41)*1.3*1000 | D7: =SUM('Appendix B - prod by country'!P41:AA41)*1.3*1000 | E7: =SUM('Appendix B - prod by country'!AB41:AM41)*1.3*1000 | F7: =SUM('Appendix B - prod by country'!AN41:AY41)*1.3*1000 | G7: =SUM('Appendix B - prod by country'!AZ41:BK41)*1.3*1000 | H7: =SUM('Appendix B - prod by country'!BL41:BW41)*1.3*1000 | I7: =SUM('Appendix B - prod by country'!BX41:CI41)*1.3*1000 | J7: =SUM('Appendix B - prod by country'!CJ41)*1.3*1000
B8: Requistion to Pay | C8: =SUM('Appendix B - prod by country'!D42:O42)*1.3*1000+SUM('Appendix A - pilot by country'!D42:O42)*1.3*1000 | D8: =SUM('Appendix B - prod by country'!P42:AA42)*1.3*1000 | E8: =SUM('Appendix B - prod by country'!AB42:AM42)*1.3*1000 | F8: =SUM('Appendix B - prod by country'!AN42:AY42)*1.3*1000 | G8: =SUM('Appendix B - prod by country'!AZ42:BK42)*1.3*1000 | H8: =SUM('Appendix B - prod by country'!BL42:BW42)*1.3*1000 | I8: =SUM('Appendix B - prod by country'!BX42:CI42)*1.3*1000 | J8: =SUM('Appendix B - prod by country'!CJ42)*1.3*1000
B9: TOTAL BASE CHARGES | C9: =SUM(C3:C8) | D9: =SUM(D3:D8) | E9: =SUM(E3:E8) | F9: =SUM(F3:F8) | G9: =SUM(G3:G8) | H9: =SUM(H3:H8) | I9: =SUM(I3:I8) | J9: =SUM(J3:J8)

Sheet Germany Production-BC
A1: BASE CHARGES INPUT FORM - CENTRE ONE (US$)
A2: Country | B2: Process Area | C2: Year 1 | D2: Year 2 | E2: Year 3 | F2: Year 4 | G2: Year 5 | H2: Year 6 | I2: Year 7 | J2: Year 8
A3: Germany Production | B3: General Accounting & Sox | C3: =SUM('Appendix B - prod by country'!D79:O80,'Appendix B - prod by country'!D83:O83)*1.3*1000+SUM('Appendix A - pilot by country'!D79:O80,'Appendix A - pilot by country'!D83:O83)*1.3*1000 | D3: =SUM('Appendix B - prod by country'!P79:AA80,'Appendix B - prod by country'!P83:AA83)*1.3*1000 | E3: =SUM('Appendix B - prod by country'!AB79:AM80,'Appendix B - prod by country'!AB83:AM83)*1.3*1000 | F3: =SUM('Appendix B - prod by country'!AN79:AY80,'Appendix B - prod by country'!AN83:AY83)*1.3*1000 | G3: =SUM('Appendix B - prod by country'!AZ79:BK80,'Appendix B - prod by country'!AZ83:BK83)*1.3*1000 | H3: =SUM('Appendix B - prod by country'!BL79:BW80,'Appendix B - prod by country'!BL83:BW83)*1.3*1000 | I3: =SUM('Appendix B - prod by country'!BX79:CI80,'Appendix B - prod by country'!BX83:CI83)*1.3*1000 | J3: =SUM('Appendix B - prod by country'!CJ79:CJ80,'Appendix B - prod by country'!CJ83)*1.3*1000
B4: Fixed Assets | C4: =SUM('Appendix B - prod by country'!D81:O81)*1.3*1000+SUM('Appendix A - pilot by country'!D81:O81)*1.3*1000 | D4: =SUM('Appendix B - prod by country'!P81:AA81)*1.3*1000 | E4: =SUM('Appendix B - prod by country'!AB81:AM81)*1.3*1000 | F4: =SUM('Appendix B - prod by country'!AN81:AY81)*1.3*1000 | G4: =SUM('Appendix B - prod by country'!AZ81:BK81)*1.3*1000 | H4: =SUM('Appendix B - prod by country'!BL81:BW81)*1.3*1000 | I4: =SUM('Appendix B - prod by country'!BX81:CI81)*1.3*1000 | J4: =SUM('Appendix B - prod by country'!CJ81)*1.3*1000
B5: Accounts Payable | C5: =SUM('Appendix B - prod by country'!D82:O82)*1.3*1000+SUM('Appendix A - pilot by country'!D82:O82)*1.3*1000 | D5: =SUM('Appendix B - prod by country'!P82:AA82)*1.3*1000 | E5: =SUM('Appendix B - prod by country'!AB82:AM82)*1.3*1000 | F5: =SUM('Appendix B - prod by country'!AN82:AY82)*1.3*1000 | G5: =SUM('Appendix B - prod by country'!AZ82:BK82)*1.3*1000 | H5: =SUM('Appendix B - prod by country'!BL82:BW82)*1.3*1000 | I5: =SUM('Appendix B - prod by country'!BX82:CI82)*1.3*1000 | J5: =SUM('Appendix B - prod by country'!CJ82)*1.3*1000
B6: T&E | C6: =SUM('Appendix B - prod by country'!D84:O84)*1.3*1000+SUM('Appendix A - pilot by country'!D84:O84)*1.3*1000 | D6: =SUM('Appendix B - prod by country'!P84:AA84)*1.3*1000 | E6: =SUM('Appendix B - prod by country'!AB84:AM84)*1.3*1000 | F6: =SUM('Appendix B - prod by country'!AN84:AY84)*1.3*1000 | G6: =SUM('Appendix B - prod by country'!AZ84:BK84)*1.3*1000 | H6: =SUM('Appendix B - prod by country'!BL84:BW84)*1.3*1000 | I6: =SUM('Appendix B - prod by country'!BX84:CI84)*1.3*1000 | J6: =SUM('Appendix B - prod by country'!CJ84)*1.3*1000
B7: Order to Cash | C7: =SUM('Appendix B - prod by country'!D85:O85)*1.3*1000+SUM('Appendix A - pilot by country'!D85:O85)*1.3*1000 | D7: =SUM('Appendix B - prod by country'!P85:AA85)*1.3*1000 | E7: =SUM('Appendix B - prod by country'!AB85:AM85)*1.3*1000 | F7: =SUM('Appendix B - prod by country'!AN85:AY85)*1.3*1000 | G7: =SUM('Appendix B - prod by country'!AZ85:BK85)*1.3*1000 | H7: =SUM('Appendix B - prod by country'!BL85:BW85)*1.3*1000 | I7: =SUM('Appendix B - prod by country'!BX85:CI85)*1.3*1000 | J7: =SUM('Appendix B - prod by country'!CJ85)*1.3*1000
B8: Requistion to Pay | C8: =SUM('Appendix B - prod by country'!D86:O86)*1.3*1000+SUM('Appendix A - pilot by country'!D86:O86)*1.3*1000 | D8: =SUM('Appendix B - prod by country'!P86:AA86)*1.3*1000 | E8: =SUM('Appendix B - prod by country'!AB86:AM86)*1.3*1000 | F8: =SUM('Appendix B - prod by country'!AN86:AY86)*1.3*1000 | G8: =SUM('Appendix B - prod by country'!AZ86:BK86)*1.3*1000 | H8: =SUM('Appendix B - prod by country'!BL86:BW86)*1.3*1000 | I8: =SUM('Appendix B - prod by country'!BX86:CI86)*1.3*1000 | J8: =SUM('Appendix B - prod by country'!CJ86)*1.3*1000
B9: TOTAL BASE CHARGES | C9: =SUM(C3:C8) | D9: =SUM(D3:D8) | E9: =SUM(E3:E8) | F9: =SUM(F3:F8) | G9: =SUM(G3:G8) | H9: =SUM(H3:H8) | I9: =SUM(I3:I8) | J9: =SUM(J3:J8)

Sheet Spain-BC
A1: BASE CHARGES INPUT FORM - CENTRE ONE (US$)
A2: Country | B2: Process Area | C2: Year 1 | D2: Year 2 | E2: Year 3 | F2: Year 4 | G2: Year 5 | H2: Year 6 | I2: Year 7 | J2: Year 8
A3: Spain | B3: General Accounting & Sox | C3: =SUM('Appendix B - prod by country'!D46:O47,'Appendix B - prod by country'!D50:O50)*1.3*1000+SUM('Appendix A - pilot by country'!D46:O47,'Appendix A - pilot by country'!D50:O50)*1.3*1000 | D3: =SUM('Appendix B - prod by country'!P46:AA47,'Appendix B - prod by country'!P50:AA50)*1.3*1000 | E3: =SUM('Appendix B - prod by country'!AB46:AM47,'Appendix B - prod by country'!AB50:AM50)*1.3*1000 | F3: =SUM('Appendix B - prod by country'!AN46:AY47,'Appendix B - prod by country'!AN50:AY50)*1.3*1000 | G3: =SUM('Appendix B - prod by country'!AZ46:BK47,'Appendix B - prod by country'!AZ50:BK50)*1.3*1000 | H3: =SUM('Appendix B - prod by country'!BL46:BW47,'Appendix B - prod by country'!BL50:BW50)*1.3*1000 | I3: =SUM('Appendix B - prod by country'!BX46:CI47,'Appendix B - prod by country'!BX50:CI50)*1.3*1000 | J3: =SUM('Appendix B - prod by country'!CJ46:CJ47,'Appendix B - prod by country'!CJ50)*1.3*1000
B4: Fixed Assets | C4: =SUM('Appendix B - prod by country'!D48:O48)*1.3*1000+SUM('Appendix A - pilot by country'!D48:O48)*1.3*1000 | D4: =SUM('Appendix B - prod by country'!P48:AA48)*1.3*1000 | E4: =SUM('Appendix B - prod by country'!AB48:AM48)*1.3*1000 | F4: =SUM('Appendix B - prod by country'!AN48:AY48)*1.3*1000 | G4: =SUM('Appendix B - prod by country'!AZ48:BK48)*1.3*1000 | H4: =SUM('Appendix B - prod by country'!BL48:BW48)*1.3*1000 | I4: =SUM('Appendix B - prod by country'!BX48:CI48)*1.3*1000 | J4: =SUM('Appendix B - prod by country'!CJ48)*1.3*1000
B5: Accounts Payable | C5: =SUM('Appendix B - prod by country'!D49:O49)*1.3*1000+SUM('Appendix A - pilot by country'!D49:O49)*1.3*1000 | D5: =SUM('Appendix B - prod by country'!P49:AA49)*1.3*1000 | E5: =SUM('Appendix B - prod by country'!AB49:AM49)*1.3*1000 | F5: =SUM('Appendix B - prod by country'!AN49:AY49)*1.3*1000 | G5: =SUM('Appendix B - prod by country'!AZ49:BK49)*1.3*1000 | H5: =SUM('Appendix B - prod by country'!BL49:BW49)*1.3*1000 | I5: =SUM('Appendix B - prod by country'!BX49:CI49)*1.3*1000 | J5: =SUM('Appendix B - prod by country'!CJ49)*1.3*1000
B6: T&E | C6: =SUM('Appendix B - prod by country'!D51:O51)*1.3*1000+SUM('Appendix A - pilot by country'!D51:O51)*1.3*1000 | D6: =SUM('Appendix B - prod by country'!P51:AA51)*1.3*1000 | E6: =SUM('Appendix B - prod by country'!AB51:AM51)*1.3*1000 | F6: =SUM('Appendix B - prod by country'!AN51:AY51)*1.3*1000 | G6: =SUM('Appendix B - prod by country'!AZ51:BK51)*1.3*1000 | H6: =SUM('Appendix B - prod by country'!BL51:BW51)*1.3*1000 | I6: =SUM('Appendix B - prod by country'!BX51:CI51)*1.3*1000 | J6: =SUM('Appendix B - prod by country'!CJ51)*1.3*1000
B7: Order to Cash | C7: =SUM('Appendix B - prod by country'!D52:O52)*1.3*1000+SUM('Appendix A - pilot by country'!D52:O52)*1.3*1000 | D7: =SUM('Appendix B - prod by country'!P52:AA52)*1.3*1000 | E7: =SUM('Appendix B - prod by country'!AB52:AM52)*1.3*1000 | F7: =SUM('Appendix B - prod by country'!AN52:AY52)*1.3*1000 | G7: =SUM('Appendix B - prod by country'!AZ52:BK52)*1.3*1000 | H7: =SUM('Appendix B - prod by country'!BL52:BW52)*1.3*1000 | I7: =SUM('Appendix B - prod by country'!BX52:CI52)*1.3*1000 | J7: =SUM('Appendix B - prod by country'!CJ52)*1.3*1000
B8: Requistion to Pay | C8: =SUM('Appendix B - prod by country'!D53:O53)*1.3*1000+SUM('Appendix A - pilot by country'!D53:O53)*1.3*1000 | D8: =SUM('Appendix B - prod by country'!P53:AA53)*1.3*1000 | E8: =SUM('Appendix B - prod by country'!AB53:AM53)*1.3*1000 | F8: =SUM('Appendix B - prod by country'!AN53:AY53)*1.3*1000 | G8: =SUM('Appendix B - prod by country'!AZ53:BK53)*1.3*1000 | H8: =SUM('Appendix B - prod by country'!BL53:BW53)*1.3*1000 | I8: =SUM('Appendix B - prod by country'!BX53:CI53)*1.3*1000 | J8: =SUM('Appendix B - prod by country'!CJ53)*1.3*1000
B9: TOTAL BASE CHARGES | C9: =SUM(C3:C8) | D9: =SUM(D3:D8) | E9: =SUM(E3:E8) | F9: =SUM(F3:F8) | G9: =SUM(G3:G8) | H9: =SUM(H3:H8) | I9: =SUM(I3:I8) | J9: =SUM(J3:J8)

Sheet Italy-BC
A1: BASE CHARGES INPUT FORM - CENTRE ONE (US$)
A2: Country | B2: Process Area | C2: Year 1 | D2: Year 2 | E2: Year 3 | F2: Year 4 | G2: Year 5 | H2: Year 6 | I2: Year 7 | J2: Year 8
A3: Italy | B3: General Accounting & Sox | C3: =SUM('Appendix B - prod by country'!D57:O58,'Appendix B - prod by country'!D61:O61)*1.3*1000+SUM('Appendix A - pilot by country'!D57:O58,'Appendix A - pilot by country'!D61:O61)*1.3*1000 | D3: =SUM('Appendix B - prod by country'!P57:AA58,'Appendix B - prod by country'!P61:AA61)*1.3*1000 | E3: =SUM('Appendix B - prod by country'!AB57:AM58,'Appendix B - prod by country'!AB61:AM61)*1.3*1000 | F3: =SUM('Appendix B - prod by country'!AN57:AY58,'Appendix B - prod by country'!AN61:AY61)*1.3*1000 | G3: =SUM('Appendix B - prod by country'!AZ57:BK58,'Appendix B - prod by country'!AZ61:BK61)*1.3*1000 | H3: =SUM('Appendix B - prod by country'!BL57:BW58,'Appendix B - prod by country'!BL61:BW61)*1.3*1000 | I3: =SUM('Appendix B - prod by country'!BX57:CI58,'Appendix B - prod by country'!BX61:CI61)*1.3*1000 | J3: =SUM('Appendix B - prod by country'!CJ57:CJ58,'Appendix B - prod by country'!CJ61)*1.3*1000
B4: Fixed Assets | C4: =SUM('Appendix B - prod by country'!D59:O59)*1.3*1000+SUM('Appendix A - pilot by country'!D59:O59)*1.3*1000 | D4: =SUM('Appendix B - prod by country'!P59:AA59)*1.3*1000 | E4: =SUM('Appendix B - prod by country'!AB59:AM59)*1.3*1000 | F4: =SUM('Appendix B - prod by country'!AN59:AY59)*1.3*1000 | G4: =SUM('Appendix B - prod by country'!AZ59:BK59)*1.3*1000 | H4: =SUM('Appendix B - prod by country'!BL59:BW59)*1.3*1000 | I4: =SUM('Appendix B - prod by country'!BX59:CI59)*1.3*1000 | J4: =SUM('Appendix B - prod by country'!CJ59)*1.3*1000
B5: Accounts Payable | C5: =SUM('Appendix B - prod by country'!D60:O60)*1.3*1000+SUM('Appendix A - pilot by country'!D60:O60)*1.3*1000 | D5: =SUM('Appendix B - prod by country'!P60:AA60)*1.3*1000 | E5: =SUM('Appendix B - prod by country'!AB60:AM60)*1.3*1000 | F5: =SUM('Appendix B - prod by country'!AN60:AY60)*1.3*1000 | G5: =SUM('Appendix B - prod by country'!AZ60:BK60)*1.3*1000 | H5: =SUM('Appendix B - prod by country'!BL60:BW60)*1.3*1000 | I5: =SUM('Appendix B - prod by country'!BX60:CI60)*1.3*1000 | J5: =SUM('Appendix B - prod by country'!CJ60)*1.3*1000
B6: T&E | C6: =SUM('Appendix B - prod by country'!D62:O62)*1.3*1000+SUM('Appendix A - pilot by country'!D62:O62)*1.3*1000 | D6: =SUM('Appendix B - prod by country'!P62:AA62)*1.3*1000 | E6: =SUM('Appendix B - prod by country'!AB62:AM62)*1.3*1000 | F6: =SUM('Appendix B - prod by country'!AN62:AY62)*1.3*1000 | G6: =SUM('Appendix B - prod by country'!AZ62:BK62)*1.3*1000 | H6: =SUM('Appendix B - prod by country'!BL62:BW62)*1.3*1000 | I6: =SUM('Appendix B - prod by country'!BX62:CI62)*1.3*1000 | J6: =SUM('Appendix B - prod by country'!CJ62)*1.3*1000
B7: Order to Cash | C7: =SUM('Appendix B - prod by country'!D63:O63)*1.3*1000+SUM('Appendix A - pilot by country'!D63:O63)*1.3*1000 | D7: =SUM('Appendix B - prod by country'!P63:AA63)*1.3*1000 | E7: =SUM('Appendix B - prod by country'!AB63:AM63)*1.3*1000 | F7: =SUM('Appendix B - prod by country'!AN63:AY63)*1.3*1000 | G7: =SUM('Appendix B - prod by country'!AZ63:BK63)*1.3*1000 | H7: =SUM('Appendix B - prod by country'!BL63:BW63)*1.3*1000 | I7: =SUM('Appendix B - prod by country'!BX63:CI63)*1.3*1000 | J7: =SUM('Appendix B - prod by country'!CJ63)*1.3*1000
B8: Requistion to Pay | C8: =SUM('Appendix B - prod by country'!D64:O64)*1.3*1000+SUM('Appendix A - pilot by country'!D64:O64)*1.3*1000 | D8: =SUM('Appendix B - prod by country'!P64:AA64)*1.3*1000 | E8: =SUM('Appendix B - prod by country'!AB64:AM64)*1.3*1000 | F8: =SUM('Appendix B - prod by country'!AN64:AY64)*1.3*1000 | G8: =SUM('Appendix B - prod by country'!AZ64:BK64)*1.3*1000 | H8: =SUM('Appendix B - prod by country'!BL64:BW64)*1.3*1000 | I8: =SUM('Appendix B - prod by country'!BX64:CI64)*1.3*1000 | J8: =SUM('Appendix B - prod by country'!CJ64)*1.3*1000
B9: TOTAL BASE CHARGES | C9: =SUM(C3:C8) | D9: =SUM(D3:D8) | E9: =SUM(E3:E8) | F9: =SUM(F3:F8) | G9: =SUM(G3:G8) | H9: =SUM(H3:H8) | I9: =SUM(I3:I8) | J9: =SUM(J3:J8)

Sheet UK-BC
A1: BASE CHARGES INPUT FORM - CENTRE ONE (US$)
A2: Country | B2: Process Area | C2: Year 1 | D2: Year 2 | E2: Year 3 | F2: Year 4 | G2: Year 5 | H2: Year 6 | I2: Year 7
A3: United Kingdom | B3: General Accounting & Sox
B4: Fixed Assets
B5: Accounts Payable
B6: T&E
B7: Order to Cash
B8: Requistion to Pay
B9: TOTAL BASE CHARGES | C9: =SUM(C3:C8) | D9: =SUM(D3:D8) | E9: =SUM(E3:E8) | F9: =SUM(F3:F8) | G9: =SUM(G3:G8) | H9: =SUM(H3:H8) | I9: =SUM(I3:I8)

Sheet Centre Two-BC
A1: BASE CHARGE SUMMARY (US$)
A2: Centre Two | C2: Year 1 | D2: Year 2 | E2: Year 3 | F2: Year 4 | G2: Year 5 | H2: Year 6 | I2: Year 7 | J2: Year 8
B3: Process Summary
B4: General Accounting & Sox | C4: =+SUM('Switzerland-BC-2:UK-BC-2'!$C3) | D4: =+SUM('Switzerland-BC-2:UK-BC-2'!$D3) | E4: =+SUM('Switzerland-BC-2:UK-BC-2'!$E3) | F4: =+SUM('Switzerland-BC-2:UK-BC-2'!$F3) | G4: =+SUM('Switzerland-BC-2:UK-BC-2'!$G3) | H4: =+SUM('Switzerland-BC-2:UK-BC-2'!$H3) | I4: =+SUM('Switzerland-BC-2:UK-BC-2'!$I3) | J4: =+SUM('Switzerland-BC-2:UK-BC-2'!$J3)
B5: Fixed Assets | C5: =+SUM('Switzerland-BC-2:UK-BC-2'!$C4) | D5: =+SUM('Switzerland-BC-2:UK-BC-2'!$D4) | E5: =+SUM('Switzerland-BC-2:UK-BC-2'!$E4) | F5: =+SUM('Switzerland-BC-2:UK-BC-2'!$F4) | G5: =+SUM('Switzerland-BC-2:UK-BC-2'!$G4) | H5: =+SUM('Switzerland-BC-2:UK-BC-2'!$H4) | I5: =+SUM('Switzerland-BC-2:UK-BC-2'!$I4) | J5: =+SUM('Switzerland-BC-2:UK-BC-2'!$J4)
B6: Accounts Payable | C6: =+SUM('Switzerland-BC-2:UK-BC-2'!$C5) | D6: =+SUM('Switzerland-BC-2:UK-BC-2'!$D5) | E6: =+SUM('Switzerland-BC-2:UK-BC-2'!$E5) | F6: =+SUM('Switzerland-BC-2:UK-BC-2'!$F5) | G6: =+SUM('Switzerland-BC-2:UK-BC-2'!$G5) | H6: =+SUM('Switzerland-BC-2:UK-BC-2'!$H5) | I6: =+SUM('Switzerland-BC-2:UK-BC-2'!$I5) | J6: =+SUM('Switzerland-BC-2:UK-BC-2'!$J5)
B7: T&E | C7: =+SUM('Switzerland-BC-2:UK-BC-2'!$C6) | D7: =+SUM('Switzerland-BC-2:UK-BC-2'!$D6) | E7: =+SUM('Switzerland-BC-2:UK-BC-2'!$E6) | F7: =+SUM('Switzerland-BC-2:UK-BC-2'!$F6) | G7: =+SUM('Switzerland-BC-2:UK-BC-2'!$G6) | H7: =+SUM('Switzerland-BC-2:UK-BC-2'!$H6) | I7: =+SUM('Switzerland-BC-2:UK-BC-2'!$I6) | J7: =+SUM('Switzerland-BC-2:UK-BC-2'!$J6)
B8: Order to Cash | C8: =+SUM('Switzerland-BC-2:UK-BC-2'!$C7) | D8: =+SUM('Switzerland-BC-2:UK-BC-2'!$D7) | E8: =+SUM('Switzerland-BC-2:UK-BC-2'!$E7) | F8: =+SUM('Switzerland-BC-2:UK-BC-2'!$F7) | G8: =+SUM('Switzerland-BC-2:UK-BC-2'!$G7) | H8: =+SUM('Switzerland-BC-2:UK-BC-2'!$H7) | I8: =+SUM('Switzerland-BC-2:UK-BC-2'!$I7) | J8: =+SUM('Switzerland-BC-2:UK-BC-2'!$J7)
B9: Requistion to Pay | C9: =+SUM('Switzerland-BC-2:UK-BC-2'!$C8) | D9: =+SUM('Switzerland-BC-2:UK-BC-2'!$D8) | E9: =+SUM('Switzerland-BC-2:UK-BC-2'!$E8) | F9: =+SUM('Switzerland-BC-2:UK-BC-2'!$F8) | G9: =+SUM('Switzerland-BC-2:UK-BC-2'!$G8) | H9: =+SUM('Switzerland-BC-2:UK-BC-2'!$H8) | I9: =+SUM('Switzerland-BC-2:UK-BC-2'!$I8) | J9: =+SUM('Switzerland-BC-2:UK-BC-2'!$J8)
B10: Total Base Charge All Countries | C10: =SUM(C4:C9) | D10: =SUM(D4:D9) | E10: =SUM(E4:E9) | F10: =SUM(F4:F9) | G10: =SUM(G4:G9) | H10: =SUM(H4:H9) | I10: =SUM(I4:I9) | J10: =SUM(J4:J9)
B11: General Accounting & Sox
B12: Switzerland | C12: ='Switzerland-BC-2'!$C$3 | D12: ='Switzerland-BC-2'!$D$3 | E12: ='Switzerland-BC-2'!$E$3 | F12: ='Switzerland-BC-2'!$F$3 | G12: ='Switzerland-BC-2'!$G$3 | H12: ='Switzerland-BC-2'!$H$3 | I12: ='Switzerland-BC-2'!$I$3 | J12: ='Switzerland-BC-2'!$J$3
B13: United States | C13: ='US-BC-2'!$C$3 | D13: ='US-BC-2'!$D$3 | E13: ='US-BC-2'!$E$3 | F13: ='US-BC-2'!$F$3 | G13: ='US-BC-2'!$G$3 | H13: ='US-BC-2'!$H$3 | I13: ='US-BC-2'!$I$3 | J13: ='US-BC-2'!$J$3
B14: France | C14: ='France-BC-2'!$C$3 | D14: ='France-BC-2'!$D$3 | E14: ='France-BC-2'!$E$3 | F14: ='France-BC-2'!$F$3 | G14: ='France-BC-2'!$G$3 | H14: ='France-BC-2'!$H$3 | I14: ='France-BC-2'!$I$3 | J14: ='France-BC-2'!$J$3
B15: Germany | C15: ='Germany-BC-2'!$C$3 | D15: ='Germany-BC-2'!$D$3 | E15: ='Germany-BC-2'!$E$3 | F15: ='Germany-BC-2'!$F$3 | G15: ='Germany-BC-2'!$G$3 | H15: ='Germany-BC-2'!$H$3 | I15: ='Germany-BC-2'!$I$3 | J15: ='Germany-BC-2'!$J$3
B16: Germany Production | C16: ='Germany Production-BC-2'!$C$3 | D16: ='Germany Production-BC-2'!$D$3 | E16: ='Germany Production-BC-2'!$E$3 | F16: ='Germany Production-BC-2'!$F$3 | G16: ='Germany Production-BC-2'!$G$3 | H16: ='Germany Production-BC-2'!$H$3 | I16: ='Germany Production-BC-2'!$I$3 | J16: ='Germany Production-BC-2'!$J$3
B17: Spain | C17: ='Spain-BC-2'!$C$3 | D17: ='Spain-BC-2'!$D$3 | E17: ='Spain-BC-2'!$E$3 | F17: ='Spain-BC-2'!$F$3 | G17: ='Spain-BC-2'!$G$3 | H17: ='Spain-BC-2'!$H$3 | I17: ='Spain-BC-2'!$I$3 | J17: ='Spain-BC-2'!$J$3
B18: Italy | C18: ='Italy-BC-2'!$C$3 | D18: ='Italy-BC-2'!$D$3 | E18: ='Italy-BC-2'!$E$3 | F18: ='Italy-BC-2'!$F$3 | G18: ='Italy-BC-2'!$G$3 | H18: ='Italy-BC-2'!$H$3 | I18: ='Italy-BC-2'!$I$3 | J18: ='Italy-BC-2'!$J$3
B19: United Kingdom | C19: ='UK-BC-2'!$C$3 | D19: ='UK-BC-2'!$D$3 | E19: ='UK-BC-2'!$E$3 | F19: ='UK-BC-2'!$F$3 | G19: ='UK-BC-2'!$G$3 | H19: ='UK-BC-2'!$H$3 | I19: ='UK-BC-2'!$I$3 | J19: ='UK-BC-2'!$J$3
B20: Sub Total | C20: =SUM(C12:C19) | D20: =SUM(D12:D19) | E20: =SUM(E12:E19) | F20: =SUM(F12:F19) | G20: =SUM(G12:G19) | H20: =SUM(H12:H19) | I20: =SUM(I12:I19) | J20: =SUM(J12:J19)
B21: Fixed Assets
B22: Switzerland | C22: ='Switzerland-BC-2'!$C$4 | D22: ='Switzerland-BC-2'!$D$4 | E22: ='Switzerland-BC-2'!$E$4 | F22: ='Switzerland-BC-2'!$F$4 | G22: ='Switzerland-BC-2'!$G$4 | H22: ='Switzerland-BC-2'!$H$4 | I22: ='Switzerland-BC-2'!$I$4 | J22: ='Switzerland-BC-2'!$J$4
B23: United States | C23: ='US-BC-2'!$C$4 | D23: ='US-BC-2'!$D$4 | E23: ='US-BC-2'!$E$4 | F23: ='US-BC-2'!$F$4 | G23: ='US-BC-2'!$G$4 | H23: ='US-BC-2'!$H$4 | I23: ='US-BC-2'!$I$4 | J23: ='US-BC-2'!$J$4
B24: France | C24: ='France-BC-2'!$C$4 | D24: ='France-BC-2'!$D$4 | E24: ='France-BC-2'!$E$4 | F24: ='France-BC-2'!$F$4 | G24: ='France-BC-2'!$G$4 | H24: ='France-BC-2'!$H$4 | I24: ='France-BC-2'!$I$4 | J24: ='France-BC-2'!$J$4
B25: Germany | C25: ='Germany-BC-2'!$C$4 | D25: ='Germany-BC-2'!$D$4 | E25: ='Germany-BC-2'!$E$4 | F25: ='Germany-BC-2'!$F$4 | G25: ='Germany-BC-2'!$G$4 | H25: ='Germany-BC-2'!$H$4 | I25: ='Germany-BC-2'!$I$4 | J25: ='Germany-BC-2'!$J$4
B26: Germany Production | C26: ='Germany Production-BC-2'!$C$4 | D26: ='Germany Production-BC-2'!$D$4 | E26: ='Germany Production-BC-2'!$E$4 | F26: ='Germany Production-BC-2'!$F$4 | G26: ='Germany Production-BC-2'!$G$4 | H26: ='Germany Production-BC-2'!$H$4 | I26: ='Germany Production-BC-2'!$I$4 | J26: ='Germany Production-BC-2'!$J$4
B27: Spain | C27: ='Spain-BC-2'!$C$4 | D27: ='Spain-BC-2'!$D$4 | E27: ='Spain-BC-2'!$E$4 | F27: ='Spain-BC-2'!$F$4 | G27: ='Spain-BC-2'!$G$4 | H27: ='Spain-BC-2'!$H$4 | I27: ='Spain-BC-2'!$I$4 | J27: ='Spain-BC-2'!$J$4
B28: Italy | C28: ='Italy-BC-2'!$C$4 | D28: ='Italy-BC-2'!$D$4 | E28: ='Italy-BC-2'!$E$4 | F28: ='Italy-BC-2'!$F$4 | G28: ='Italy-BC-2'!$G$4 | H28: ='Italy-BC-2'!$H$4 | I28: ='Italy-BC-2'!$I$4 | J28: ='Italy-BC-2'!$J$4
B29: United Kingdom | C29: ='UK-BC-2'!$C$4 | D29: ='UK-BC-2'!$D$4 | E29: ='UK-BC-2'!$E$4 | F29: ='UK-BC-2'!$F$4 | G29: ='UK-BC-2'!$G$4 | H29: ='UK-BC-2'!$H$4 | I29: ='UK-BC-2'!$I$4 | J29: ='UK-BC-2'!$J$4
B30: Sub Total | C30: =SUM(C22:C29) | D30: =SUM(D22:D29) | E30: =SUM(E22:E29) | F30: =SUM(F22:F29) | G30: =SUM(G22:G29) | H30: =SUM(H22:H29) | I30: =SUM(I22:I29) | J30: =SUM(J22:J29)
B31: Accounts Payable
B32: Switzerland | C32: ='Switzerland-BC-2'!$C$5 | D32: ='Switzerland-BC-2'!$D$5 | E32: ='Switzerland-BC-2'!$E$5 | F32: ='Switzerland-BC-2'!$F$5 | G32: ='Switzerland-BC-2'!$G$5 | H32: ='Switzerland-BC-2'!$H$5 | I32: ='Switzerland-BC-2'!$I$5 | J32: ='Switzerland-BC-2'!$J$5
B33: United States | C33: ='US-BC-2'!$C$5 | D33: ='US-BC-2'!$D$5 | E33: ='US-BC-2'!$E$5 | F33: ='US-BC-2'!$F$5 | G33: ='US-BC-2'!$G$5 | H33: ='US-BC-2'!$H$5 | I33: ='US-BC-2'!$I$5 | J33: ='US-BC-2'!$J$5
B34: France | C34: ='France-BC-2'!$C$5 | D34: ='France-BC-2'!$D$5 | E34: ='France-BC-2'!$E$5 | F34: ='France-BC-2'!$F$5 | G34: ='France-BC-2'!$G$5 | H34: ='France-BC-2'!$H$5 | I34: ='France-BC-2'!$I$5 | J34: ='France-BC-2'!$J$5
B35: Germany | C35: ='Germany-BC-2'!$C$5 | D35: ='Germany-BC-2'!$D$5 | E35: ='Germany-BC-2'!$E$5 | F35: ='Germany-BC-2'!$F$5 | G35: ='Germany-BC-2'!$G$5 | H35: ='Germany-BC-2'!$H$5 | I35: ='Germany-BC-2'!$I$5 | J35: ='Germany-BC-2'!$J$5
B36: Germany Production | C36: ='Germany Production-BC-2'!$C$5 | D36: ='Germany Production-BC-2'!$D$5 | E36: ='Germany Production-BC-2'!$E$5 | F36: ='Germany Production-BC-2'!$F$5 | G36: ='Germany Production-BC-2'!$G$5 | H36: ='Germany Production-BC-2'!$H$5 | I36: ='Germany Production-BC-2'!$I$5 | J36: ='Germany Production-BC-2'!$J$5
B37: Spain | C37: ='Spain-BC-2'!$C$5 | D37: ='Spain-BC-2'!$D$5 | E37: ='Spain-BC-2'!$E$5 | F37: ='Spain-BC-2'!$F$5 | G37: ='Spain-BC-2'!$G$5 | H37: ='Spain-BC-2'!$H$5 | I37: ='Spain-BC-2'!$I$5 | J37: ='Spain-BC-2'!$J$5
B38: Italy | C38: ='Italy-BC-2'!$C$5 | D38: ='Italy-BC-2'!$D$5 | E38: ='Italy-BC-2'!$E$5 | F38: ='Italy-BC-2'!$F$5 | G38: ='Italy-BC-2'!$G$5 | H38: ='Italy-BC-2'!$H$5 | I38: ='Italy-BC-2'!$I$5 | J38: ='Italy-BC-2'!$J$5
B39: United Kingdom | C39: ='UK-BC-2'!$C$5 | D39: ='UK-BC-2'!$D$5 | E39: ='UK-BC-2'!$E$5 | F39: ='UK-BC-2'!$F$5 | G39: ='UK-BC-2'!$G$5 | H39: ='UK-BC-2'!$H$5 | I39: ='UK-BC-2'!$I$5 | J39: ='UK-BC-2'!$J$5
B40: Sub Total | C40: =SUM(C32:C39) | D40: =SUM(D32:D39) | E40: =SUM(E32:E39) | F40: =SUM(F32:F39) | G40: =SUM(G32:G39) | H40: =SUM(H32:H39) | I40: =SUM(I32:I39) | J40: =SUM(J32:J39)
B41: T&E
B42: Switzerland | C42: ='Switzerland-BC-2'!$C$6 | D42: ='Switzerland-BC-2'!$D$6 | E42: ='Switzerland-BC-2'!$E$6 | F42: ='Switzerland-BC-2'!$F$6 | G42: ='Switzerland-BC-2'!$G$6 | H42: ='Switzerland-BC-2'!$H$6 | I42: ='Switzerland-BC-2'!$I$6 | J42: ='Switzerland-BC-2'!$J$6
B43: United States | C43: ='US-BC-2'!$C$6 | D43: ='US-BC-2'!$D$6 | E43: ='US-BC-2'!$E$6 | F43: ='US-BC-2'!$F$6 | G43: ='US-BC-2'!$G$6 | H43: ='US-BC-2'!$H$6 | I43: ='US-BC-2'!$I$6 | J43: ='US-BC-2'!$J$6
B44: France | C44: ='France-BC-2'!$C$6 | D44: ='France-BC-2'!$D$6 | E44: ='France-BC-2'!$E$6 | F44: ='France-BC-2'!$F$6 | G44: ='France-BC-2'!$G$6 | H44: ='France-BC-2'!$H$6 | I44: ='France-BC-2'!$I$6 | J44: ='France-BC-2'!$J$6
B45: Germany | C45: ='Germany-BC-2'!$C$6 | D45: ='Germany-BC-2'!$D$6 | E45: ='Germany-BC-2'!$E$6 | F45: ='Germany-BC-2'!$F$6 | G45: ='Germany-BC-2'!$G$6 | H45: ='Germany-BC-2'!$H$6 | I45: ='Germany-BC-2'!$I$6 | J45: ='Germany-BC-2'!$J$6
B46: Germany Production | C46: ='Germany Production-BC-2'!$C$6 | D46: ='Germany Production-BC-2'!$D$6 | E46: ='Germany Production-BC-2'!$E$6 | F46: ='Germany Production-BC-2'!$F$6 | G46: ='Germany Production-BC-2'!$G$6 | H46: ='Germany Production-BC-2'!$H$6 | I46: ='Germany Production-BC-2'!$I$6 | J46: ='Germany Production-BC-2'!$J$6
B47: Spain | C47: ='Spain-BC-2'!$C$6 | D47: ='Spain-BC-2'!$D$6 | E47: ='Spain-BC-2'!$E$6 | F47: ='Spain-BC-2'!$F$6 | G47: ='Spain-BC-2'!$G$6 | H47: ='Spain-BC-2'!$H$6 | I47: ='Spain-BC-2'!$I$6 | J47: ='Spain-BC-2'!$J$6
B48: Italy | C48: ='Italy-BC-2'!$C$6 | D48: ='Italy-BC-2'!$D$6 | E48: ='Italy-BC-2'!$E$6 | F48: ='Italy-BC-2'!$F$6 | G48: ='Italy-BC-2'!$G$6 | H48: ='Italy-BC-2'!$H$6 | I48: ='Italy-BC-2'!$I$6 | J48: ='Italy-BC-2'!$J$6
B49: United Kingdom | C49: ='UK-BC-2'!$C$6 | D49: ='UK-BC-2'!$D$6 | E49: ='UK-BC-2'!$E$6 | F49: ='UK-BC-2'!$F$6 | G49: ='UK-BC-2'!$G$6 | H49: ='UK-BC-2'!$H$6 | I49: ='UK-BC-2'!$I$6 | J49: ='UK-BC-2'!$J$6
B50: Sub Total | C50: =SUM(C42:C49) | D50: =SUM(D42:D49) | E50: =SUM(E42:E49) | F50: =SUM(F42:F49) | G50: =SUM(G42:G49) | H50: =SUM(H42:H49) | I50: =SUM(I42:I49) | J50: =SUM(J42:J49)
B51: Order to Cash
B52: Switzerland | C52: ='Switzerland-BC-2'!$C$7 | D52: ='Switzerland-BC-2'!$D$7 | E52: ='Switzerland-BC-2'!$E$7 | F52: ='Switzerland-BC-2'!$F$7 | G52: ='Switzerland-BC-2'!$G$7 | H52: ='Switzerland-BC-2'!$H$7 | I52: ='Switzerland-BC-2'!$I$7 | J52: ='Switzerland-BC-2'!$J$7
B53: United States | C53: ='US-BC-2'!$C$7 | D53: ='US-BC-2'!$D$7 | E53: ='US-BC-2'!$E$7 | F53: ='US-BC-2'!$F$7 | G53: ='US-BC-2'!$G$7 | H53: ='US-BC-2'!$H$7 | I53: ='US-BC-2'!$I$7 | J53: ='US-BC-2'!$J$7
B54: France | C54: ='France-BC-2'!$C$7 | D54: ='France-BC-2'!$D$7 | E54: ='France-BC-2'!$E$7 | F54: ='France-BC-2'!$F$7 | G54: ='France-BC-2'!$G$7 | H54: ='France-BC-2'!$H$7 | I54: ='France-BC-2'!$I$7 | J54: ='France-BC-2'!$J$7
B55: Germany | C55: ='Germany-BC-2'!$C$7 | D55: ='Germany-BC-2'!$D$7 | E55: ='Germany-BC-2'!$E$7 | F55: ='Germany-BC-2'!$F$7 | G55: ='Germany-BC-2'!$G$7 | H55: ='Germany-BC-2'!$H$7 | I55: ='Germany-BC-2'!$I$7 | J55: ='Germany-BC-2'!$J$7
B56: Germany Production | C56: ='Germany Production-BC-2'!$C$7 | D56: ='Germany Production-BC-2'!$D$7 | E56: ='Germany Production-BC-2'!$E$7 | F56: ='Germany Production-BC-2'!$F$7 | G56: ='Germany Production-BC-2'!$G$7 | H56: ='Germany Production-BC-2'!$H$7 | I56: ='Germany Production-BC-2'!$I$7 | J56: ='Germany Production-BC-2'!$J$7
B57: Spain | C57: ='Spain-BC-2'!$C$7 | D57: ='Spain-BC-2'!$D$7 | E57: ='Spain-BC-2'!$E$7 | F57: ='Spain-BC-2'!$F$7 | G57: ='Spain-BC-2'!$G$7 | H57: ='Spain-BC-2'!$H$7 | I57: ='Spain-BC-2'!$I$7 | J57: ='Spain-BC-2'!$J$7
B58: Italy | C58: ='Italy-BC-2'!$C$7 | D58: ='Italy-BC-2'!$D$7 | E58: ='Italy-BC-2'!$E$7 | F58: ='Italy-BC-2'!$F$7 | G58: ='Italy-BC-2'!$G$7 | H58: ='Italy-BC-2'!$H$7 | I58: ='Italy-BC-2'!$I$7 | J58: ='Italy-BC-2'!$J$7
B59: United Kingdom | C59: ='UK-BC-2'!$C$7 | D59: ='UK-BC-2'!$D$7 | E59: ='UK-BC-2'!$E$7 | F59: ='UK-BC-2'!$F$7 | G59: ='UK-BC-2'!$G$7 | H59: ='UK-BC-2'!$H$7 | I59: ='UK-BC-2'!$I$7 | J59: ='UK-BC-2'!$J$7
B60: Sub Total | C60: =SUM(C52:C59) | D60: =SUM(D52:D59) | E60: =SUM(E52:E59) | F60: =SUM(F52:F59) | G60: =SUM(G52:G59) | H60: =SUM(H52:H59) | I60: =SUM(I52:I59) | J60: =SUM(J52:J59)
B61: Requistion to Pay
B62: Switzerland | C62: ='Switzerland-BC-2'!$C$8 | D62: ='Switzerland-BC-2'!$D$8 | E62: ='Switzerland-BC-2'!$E$8 | F62: ='Switzerland-BC-2'!$F$8 | G62: ='Switzerland-BC-2'!$G$8 | H62: ='Switzerland-BC-2'!$H$8 | I62: ='Switzerland-BC-2'!$I$8 | J62: ='Switzerland-BC-2'!$J$8
B63: United States | C63: ='US-BC-2'!$C$8 | D63: ='US-BC-2'!$D$8 | E63: ='US-BC-2'!$E$8 | F63: ='US-BC-2'!$F$8 | G63: ='US-BC-2'!$G$8 | H63: ='US-BC-2'!$H$8 | I63: ='US-BC-2'!$I$8 | J63: ='US-BC-2'!$J$8
B64: France | C64: ='France-BC-2'!$C$8 | D64: ='France-BC-2'!$D$8 | E64: ='France-BC-2'!$E$8 | F64: ='France-BC-2'!$F$8 | G64: ='France-BC-2'!$G$8 | H64: ='France-BC-2'!$H$8 | I64: ='France-BC-2'!$I$8 | J64: ='France-BC-2'!$J$8
B65: Germany | C65: ='Germany-BC-2'!$C$8 | D65: ='Germany-BC-2'!$D$8 | E65: ='Germany-BC-2'!$E$8 | F65: ='Germany-BC-2'!$F$8 | G65: ='Germany-BC-2'!$G$8 | H65: ='Germany-BC-2'!$H$8 | I65: ='Germany-BC-2'!$I$8 | J65: ='Germany-BC-2'!$J$8
B66: Germany Production | C66: ='Germany Production-BC-2'!$C$8 | D66: ='Germany Production-BC-2'!$D$8 | E66: ='Germany Production-BC-2'!$E$8 | F66: ='Germany Production-BC-2'!$F$8 | G66: ='Germany Production-BC-2'!$G$8 | H66: ='Germany Production-BC-2'!$H$8 | I66: ='Germany Production-BC-2'!$I$8 | J66: ='Germany Production-BC-2'!$J$8
B67: Spain | C67: ='Spain-BC-2'!$C$8 | D67: ='Spain-BC-2'!$D$8 | E67: ='Spain-BC-2'!$E$8 | F67: ='Spain-BC-2'!$F$8 | G67: ='Spain-BC-2'!$G$8 | H67: ='Spain-BC-2'!$H$8 | I67: ='Spain-BC-2'!$I$8 | J67: ='Spain-BC-2'!$J$8
B68: Italy | C68: ='Italy-BC-2'!$C$8 | D68: ='Italy-BC-2'!$D$8 | E68: ='Italy-BC-2'!$E$8 | F68: ='Italy-BC-2'!$F$8 | G68: ='Italy-BC-2'!$G$8 | H68: ='Italy-BC-2'!$H$8 | I68: ='Italy-BC-2'!$I$8 | J68: ='Italy-BC-2'!$J$8
B69: United Kingdom | C69: ='UK-BC-2'!$C$8 | D69: ='UK-BC-2'!$D$8 | E69: ='UK-BC-2'!$E$8 | F69: ='UK-BC-2'!$F$8 | G69: ='UK-BC-2'!$G$8 | H69: ='UK-BC-2'!$H$8 | I69: ='UK-BC-2'!$I$8 | J69: ='UK-BC-2'!$J$8
B70: Sub Total | C70: =SUM(C62:C69) | D70: =SUM(D62:D69) | E70: =SUM(E62:E69) | F70: =SUM(F62:F69) | G70: =SUM(G62:G69) | H70: =SUM(H62:H69) | I70: =SUM(I62:I69) | J70: =SUM(J62:J69)
B71: Total Base Charges All Countries | C71: =C20+C30+C40+C50+C60+C70 | D71: =D20+D30+D40+D50+D60+D70 | E71: =E20+E30+E40+E50+E60+E70 | F71: =F20+F30+F40+F50+F60+F70 | G71: =G20+G30+G40+G50+G60+G70 | H71: =H20+H30+H40+H50+H60+H70 | I71: =I20+I30+I40+I50+I60+I70 | J71: =J20+J30+J40+J50+J60+J70
B72: Country Summary
B73: Switzerland | C73: ='Switzerland-BC-2'!C9 | D73: ='Switzerland-BC-2'!D9 | E73: ='Switzerland-BC-2'!E9 | F73: ='Switzerland-BC-2'!F9 | G73: ='Switzerland-BC-2'!G9 | H73: ='Switzerland-BC-2'!H9 | I73: ='Switzerland-BC-2'!I9 | J73: ='Switzerland-BC-2'!J9
B74: United States | C74: ='US-BC-2'!C9 | D74: ='US-BC-2'!D9 | E74: ='US-BC-2'!E9 | F74: ='US-BC-2'!F9 | G74: ='US-BC-2'!G9 | H74: ='US-BC-2'!H9 | I74: ='US-BC-2'!I9 | J74: ='US-BC-2'!J9
B75: France | C75: ='France-BC-2'!C9 | D75: ='France-BC-2'!D9 | E75: ='France-BC-2'!E9 | F75: ='France-BC-2'!F9 | G75: ='France-BC-2'!G9 | H75: ='France-BC-2'!H9 | I75: ='France-BC-2'!I9 | J75: ='France-BC-2'!J9
B76: Germany | C76: ='Germany-BC-2'!C9 | D76: ='Germany-BC-2'!D9 | E76: ='Germany-BC-2'!E9 | F76: ='Germany-BC-2'!F9 | G76: ='Germany-BC-2'!G9 | H76: ='Germany-BC-2'!H9 | I76: ='Germany-BC-2'!I9 | J76: ='Germany-BC-2'!J9
B77: Germany Production | C77: ='Germany Production-BC-2'!C9 | D77: ='Germany Production-BC-2'!D9 | E77: ='Germany Production-BC-2'!E9 | F77: ='Germany Production-BC-2'!F9 | G77: ='Germany Production-BC-2'!G9 | H77: ='Germany Production-BC-2'!H9 | I77: ='Germany Production-BC-2'!I9 | J77: ='Germany Production-BC-2'!J9
B78: Spain | C78: ='Spain-BC-2'!C9 | D78: ='Spain-BC-2'!D9 | E78: ='Spain-BC-2'!E9 | F78: ='Spain-BC-2'!F9 | G78: ='Spain-BC-2'!G9 | H78: ='Spain-BC-2'!H9 | I78: ='Spain-BC-2'!I9 | J78: ='Spain-BC-2'!J9
B79: Italy | C79: ='Italy-BC-2'!C9 | D79: ='Italy-BC-2'!D9 | E79: ='Italy-BC-2'!E9 | F79: ='Italy-BC-2'!F9 | G79: ='Italy-BC-2'!G9 | H79: ='Italy-BC-2'!H9 | I79: ='Italy-BC-2'!I9 | J79: ='Italy-BC-2'!J9
B80: United Kingdom | C80: ='UK-BC-2'!C9 | D80: ='UK-BC-2'!D9 | E80: ='UK-BC-2'!E9 | F80: ='UK-BC-2'!F9 | G80: ='UK-BC-2'!G9 | H80: ='UK-BC-2'!H9 | I80: ='UK-BC-2'!I9 | J80: ='UK-BC-2'!J9
B81: Total Base Charges All Countries | C81: =SUM(C73:C80) | D81: =SUM(D73:D80) | E81: =SUM(E73:E80) | F81: =SUM(F73:F80) | G81: =SUM(G73:G80) | H81: =SUM(H73:H80) | I81: =SUM(I73:I80) | J81: =SUM(J73:J80)

Sheet Switzerland-BC-2
A1: BASE CHARGES INPUT FORM - CENTRE TWO (US$)
A2: Country | B2: Process Area | C2: Year 1 | D2: Year 2 | E2: Year 3 | F2: Year 4 | G2: Year 5 | H2: Year 6 | I2: Year 7
A3: Switzerland | B3: General Accounting & Sox
B4: Fixed Assets
B5: Accounts Payable
B6: T&E
B7: Order to Cash
B8: Requistion to Pay
B9: TOTAL BASE CHARGES | C9: =SUM(C3:C8) | D9: =SUM(D3:D8) | E9: =SUM(E3:E8) | F9: =SUM(F3:F8) | G9: =SUM(G3:G8) | H9: =SUM(H3:H8) | I9: =SUM(I3:I8)

Sheet US-BC-2
A1: BASE CHARGES INPUT FORM - CENTRE TWO (US$)
A2: Country | B2: Process Area | C2: Year 1 | D2: Year 2 | E2: Year 3 | F2: Year 4 | G2: Year 5 | H2: Year 6 | I2: Year 7 | J2: Year 8
A3: United States | B3: General Accounting & Sox | C3: =SUM('Appendix B - prod by country'!D13:O14,'Appendix B - prod by country'!D17:O17)*1.3*1000+SUM('Appendix A - pilot by country'!D13:O14,'Appendix A - pilot by country'!D17:O17)*1.3*1000 | D3: =SUM('Appendix B - prod by country'!P13:AA14,'Appendix B - prod by country'!P17:AA17)*1.3*1000 | E3: =SUM('Appendix B - prod by country'!AB13:AM14,'Appendix B - prod by country'!AB17:AM17)*1.3*1000 | F3: =SUM('Appendix B - prod by country'!AN13:AY14,'Appendix B - prod by country'!AN17:AY17)*1.3*1000 | G3: =SUM('Appendix B - prod by country'!AZ13:BK14,'Appendix B - prod by country'!AZ17:BK17)*1.3*1000 | H3: =SUM('Appendix B - prod by country'!BL13:BW14,'Appendix B - prod by country'!BL17:BW17)*1.3*1000 | I3: =SUM('Appendix B - prod by country'!BX13:CI14,'Appendix B - prod by country'!BX17:CI17)*1.3*1000 | J3: =SUM('Appendix B - prod by country'!CJ13:CJ14,'Appendix B - prod by country'!CJ17)*1.3*1000
B4: Fixed Assets | C4: =SUM('Appendix B - prod by country'!D15:O15)*1.3*1000+SUM('Appendix A - pilot by country'!D15:O15)*1.3*1000 | D4: =SUM('Appendix B - prod by country'!P15:AA15)*1.3*1000 | E4: =SUM('Appendix B - prod by country'!AB15:AM15)*1.3*1000 | F4: =SUM('Appendix B - prod by country'!AN15:AY15)*1.3*1000 | G4: =SUM('Appendix B - prod by country'!AZ15:BK15)*1.3*1000 | H4: =SUM('Appendix B - prod by country'!BL15:BW15)*1.3*1000 | I4: =SUM('Appendix B - prod by country'!BX15:CI15)*1.3*1000 | J4: =SUM('Appendix B - prod by country'!CJ15)*1.3*1000
B5: Accounts Payable | C5: =SUM('Appendix B - prod by country'!D16:O16)*1.3*1000+SUM('Appendix A - pilot by country'!D16:O16)*1.3*1000 | D5: =SUM('Appendix B - prod by country'!P16:AA16)*1.3*1000 | E5: =SUM('Appendix B - prod by country'!AB16:AM16)*1.3*1000 | F5: =SUM('Appendix B - prod by country'!AN16:AY16)*1.3*1000 | G5: =SUM('Appendix B - prod by country'!AZ16:BK16)*1.3*1000 | H5: =SUM('Appendix B - prod by country'!BL16:BW16)*1.3*1000 | I5: =SUM('Appendix B - prod by country'!BX16:CI16)*1.3*1000 | J5: =SUM('Appendix B - prod by country'!CJ16)*1.3*1000
B6: T&E | C6: =SUM('Appendix B - prod by country'!D18:O18)*1.3*1000+SUM('Appendix A - pilot by country'!D18:O18)*1.3*1000 | D6: =SUM('Appendix B - prod by country'!P18:AA18)*1.3*1000 | E6: =SUM('Appendix B - prod by country'!AB18:AM18)*1.3*1000 | F6: =SUM('Appendix B - prod by country'!AN18:AY18)*1.3*1000 | G6: =SUM('Appendix B - prod by country'!AZ18:BK18)*1.3*1000 | H6: =SUM('Appendix B - prod by country'!BL18:BW18)*1.3*1000 | I6: =SUM('Appendix B - prod by country'!BX18:CI18)*1.3*1000 | J6: =SUM('Appendix B - prod by country'!CJ18)*1.3*1000
B7: Order to Cash | C7: =SUM('Appendix B - prod by country'!D19:O19)*1.3*1000+SUM('Appendix A - pilot by country'!D19:O19)*1.3*1000 | D7: =SUM('Appendix B - prod by country'!P19:AA19)*1.3*1000 | E7: =SUM('Appendix B - prod by country'!AB19:AM19)*1.3*1000 | F7: =SUM('Appendix B - prod by country'!AN19:AY19)*1.3*1000 | G7: =SUM('Appendix B - prod by country'!AZ19:BK19)*1.3*1000 | H7: =SUM('Appendix B - prod by country'!BL19:BW19)*1.3*1000 | I7: =SUM('Appendix B - prod by country'!BX19:CI19)*1.3*1000 | J7: =SUM('Appendix B - prod by country'!CJ19)*1.3*1000
B8: Requistion to Pay | C8: =SUM('Appendix B - prod by country'!D20:O20)*1.3*1000+SUM('Appendix A - pilot by country'!D20:O20)*1.3*1000 | D8: =SUM('Appendix B - prod by country'!P20:AA20)*1.3*1000 | E8: =SUM('Appendix B - prod by country'!AB20:AM20)*1.3*1000 | F8: =SUM('Appendix B - prod by country'!AN20:AY20)*1.3*1000 | G8: =SUM('Appendix B - prod by country'!AZ20:BK20)*1.3*1000 | H8: =SUM('Appendix B - prod by country'!BL20:BW20)*1.3*1000 | I8: =SUM('Appendix B - prod by country'!BX20:CI20)*1.3*1000 | J8: =SUM('Appendix B - prod by country'!CJ20)*1.3*1000
B9: TOTAL BASE CHARGES | C9: =SUM(C3:C8) | D9: =SUM(D3:D8) | E9: =SUM(E3:E8) | F9: =SUM(F3:F8) | G9: =SUM(G3:G8) | H9: =SUM(H3:H8) | I9: =SUM(I3:I8) | J9: =SUM(J3:J8)

Sheet France-BC-2
A1: BASE CHARGES INPUT FORM - CENTRE TWO (US$)
A2: Country | B2: Process Area | C2: Year 1 | D2: Year 2 | E2: Year 3 | F2: Year 4 | G2: Year 5 | H2: Year 6 | I2: Year 7
A3: France | B3: General Accounting & Sox
B4: Fixed Assets
B5: Accounts Payable
B6: T&E
B7: Order to Cash
B8: Requistion to Pay
B9: TOTAL BASE CHARGES | C9: =SUM(C3:C8) | D9: =SUM(D3:D8) | E9: =SUM(E3:E8) | F9: =SUM(F3:F8) | G9: =SUM(G3:G8) | H9: =SUM(H3:H8) | I9: =SUM(I3:I8)

Sheet Germany-BC-2
A1: BASE CHARGES INPUT FORM - CENTRE TWO (US$)
A2: Country | B2: Process Area | C2: Year 1 | D2: Year 2 | E2: Year 3 | F2: Year 4 | G2: Year 5 | H2: Year 6 | I2: Year 7
A3: Germany | B3: General Accounting & Sox
B4: Fixed Assets
B5: Accounts Payable
B6: T&E
B7: Order to Cash
B8: Requistion to Pay
B9: TOTAL BASE CHARGES | C9: =SUM(C3:C8) | D9: =SUM(D3:D8) | E9: =SUM(E3:E8) | F9: =SUM(F3:F8) | G9: =SUM(G3:G8) | H9: =SUM(H3:H8) | I9: =SUM(I3:I8)

Sheet Germany Production-BC-2
A1: BASE CHARGES INPUT FORM - CENTRE TWO (US$)
A2: Country | B2: Process Area | C2: Year 1 | D2: Year 2 | E2: Year 3 | F2: Year 4 | G2: Year 5 | H2: Year 6 | I2: Year 7
A3: Germany Production | B3: General Accounting & Sox
B4: Fixed Assets
B5: Accounts Payable
B6: T&E
B7: Order to Cash
B8: Requistion to Pay
B9: TOTAL BASE CHARGES | C9: =SUM(C3:C8) | D9: =SUM(D3:D8) | E9: =SUM(E3:E8) | F9: =SUM(F3:F8) | G9: =SUM(G3:G8) | H9: =SUM(H3:H8) | I9: =SUM(I3:I8)

Sheet Spain-BC-2
A1: BASE CHARGES INPUT FORM - CENTRE TWO (US$)
A2: Country | B2: Process Area | C2: Year 1 | D2: Year 2 | E2: Year 3 | F2: Year 4 | G2: Year 5 | H2: Year 6 | I2: Year 7
A3: Spain | B3: General Accounting & Sox
B4: Fixed Assets
B5: Accounts Payable
B6: T&E
B7: Order to Cash
B8: Requistion to Pay
B9: TOTAL BASE CHARGES | C9: =SUM(C3:C8) | D9: =SUM(D3:D8) | E9: =SUM(E3:E8) | F9: =SUM(F3:F8) | G9: =SUM(G3:G8) | H9: =SUM(H3:H8) | I9: =SUM(I3:I8)

Sheet Italy-BC-2
A1: BASE CHARGES INPUT FORM - CENTRE TWO (US$)
A2: Country | B2: Process Area | C2: Year 1 | D2: Year 2 | E2: Year 3 | F2: Year 4 | G2: Year 5 | H2: Year 6 | I2: Year 7
A3: Italy | B3: General Accounting & Sox
B4: Fixed Assets
B5: Accounts Payable
B6: T&E
B7: Order to Cash
B8: Requistion to Pay
B9: TOTAL BASE CHARGES | C9: =SUM(C3:C8) | D9: =SUM(D3:D8) | E9: =SUM(E3:E8) | F9: =SUM(F3:F8) | G9: =SUM(G3:G8) | H9: =SUM(H3:H8) | I9: =SUM(I3:I8)

Sheet UK-BC-2
A1: BASE CHARGES INPUT FORM - CENTRE TWO (US$)
A2: Country | B2: Process Area | C2: Year 1 | D2: Year 2 | E2: Year 3 | F2: Year 4 | G2: Year 5 | H2: Year 6 | I2: Year 7 | J2: Year 8
A3: United Kingdom | B3: General Accounting & Sox | C3: =SUM('Appendix B - prod by country'!D68:O69,'Appendix B - prod by country'!D72:O72)*1.3*1000+SUM('Appendix A - pilot by country'!D68:O69,'Appendix A - pilot by country'!D72:O72)*1.3*1000 | D3: =SUM('Appendix B - prod by country'!P68:AA69,'Appendix B - prod by country'!P72:AA72)*1.3*1000 | E3: =SUM('Appendix B - prod by country'!AB68:AM69,'Appendix B - prod by country'!AB72:AM72)*1.3*1000 | F3: =SUM('Appendix B - prod by country'!AN68:AY69,'Appendix B - prod by country'!AN72:AY72)*1.3*1000 | G3: =SUM('Appendix B - prod by country'!AZ68:BK69,'Appendix B - prod by country'!AZ72:BK72)*1.3*1000 | H3: =SUM('Appendix B - prod by country'!BL68:BW69,'Appendix B - prod by country'!BL72:BW72)*1.3*1000 | I3: =SUM('Appendix B - prod by country'!BX68:CI69,'Appendix B - prod by country'!BX72:CI72)*1.3*1000 | J3: =SUM('Appendix B - prod by country'!CJ68:CJ69,'Appendix B - prod by country'!CJ72)*1.3*1000
B4: Fixed Assets | C4: =SUM('Appendix B - prod by country'!D70:O70)*1.3*1000+SUM('Appendix A - pilot by country'!D70:O70)*1.3*1000 | D4: =SUM('Appendix B - prod by country'!P70:AA70)*1.3*1000 | E4: =SUM('Appendix B - prod by country'!AB70:AM70)*1.3*1000 | F4: =SUM('Appendix B - prod by country'!AN70:AY70)*1.3*1000 | G4: =SUM('Appendix B - prod by country'!AZ70:BK70)*1.3*1000 | H4: =SUM('Appendix B - prod by country'!BL70:BW70)*1.3*1000 | I4: =SUM('Appendix B - prod by country'!BX70:CI70)*1.3*1000 | J4: =SUM('Appendix B - prod by country'!CJ70)*1.3*1000
B5: Accounts Payable | C5: =SUM('Appendix B - prod by country'!D71:O71)*1.3*1000+SUM('Appendix A - pilot by country'!D71:O71)*1.3*1000 | D5: =SUM('Appendix B - prod by country'!P71:AA71)*1.3*1000 | E5: =SUM('Appendix B - prod by country'!AB71:AM71)*1.3*1000 | F5: =SUM('Appendix B - prod by country'!AN71:AY71)*1.3*1000 | G5: =SUM('Appendix B - prod by country'!AZ71:BK71)*1.3*1000 | H5: =SUM('Appendix B - prod by country'!BL71:BW71)*1.3*1000 | I5: =SUM('Appendix B - prod by country'!BX71:CI71)*1.3*1000 | J5: =SUM('Appendix B - prod by country'!CJ71)*1.3*1000
B6: T&E | C6: =SUM('Appendix B - prod by country'!D73:O73)*1.3*1000+SUM('Appendix A - pilot by country'!D73:O73)*1.3*1000 | D6: =SUM('Appendix B - prod by country'!P73:AA73)*1.3*1000 | E6: =SUM('Appendix B - prod by country'!AB73:AM73)*1.3*1000 | F6: =SUM('Appendix B - prod by country'!AN73:AY73)*1.3*1000 | G6: =SUM('Appendix B - prod by country'!AZ73:BK73)*1.3*1000 | H6: =SUM('Appendix B - prod by country'!BL73:BW73)*1.3*1000 | I6: =SUM('Appendix B - prod by country'!BX73:CI73)*1.3*1000 | J6: =SUM('Appendix B - prod by country'!CJ73)*1.3*1000
B7: Order to Cash | C7: =SUM('Appendix B - prod by country'!D74:O74)*1.3*1000+SUM('Appendix A - pilot by country'!D74:O74)*1.3*1000 | D7: =SUM('Appendix B - prod by country'!P74:AA74)*1.3*1000 | E7: =SUM('Appendix B - prod by country'!AB74:AM74)*1.3*1000 | F7: =SUM('Appendix B - prod by country'!AN74:AY74)*1.3*1000 | G7: =SUM('Appendix B - prod by country'!AZ74:BK74)*1.3*1000 | H7: =SUM('Appendix B - prod by country'!BL74:BW74)*1.3*1000 | I7: =SUM('Appendix B - prod by country'!BX74:CI74)*1.3*1000 | J7: =SUM('Appendix B - prod by country'!CJ74)*1.3*1000
B8: Requistion to Pay | C8: =SUM('Appendix B - prod by country'!D75:O75)*1.3*1000+SUM('Appendix A - pilot by country'!D75:O75)*1.3*1000 | D8: =SUM('Appendix B - prod by country'!P75:AA75)*1.3*1000 | E8: =SUM('Appendix B - prod by country'!AB75:AM75)*1.3*1000 | F8: =SUM('Appendix B - prod by country'!AN75:AY75)*1.3*1000 | G8: =SUM('Appendix B - prod by country'!AZ75:BK75)*1.3*1000 | H8: =SUM('Appendix B - prod by country'!BL75:BW75)*1.3*1000 | I8: =SUM('Appendix B - prod by country'!BX75:CI75)*1.3*1000 | J8: =SUM('Appendix B - prod by country'!CJ75)*1.3*1000
B9: TOTAL BASE CHARGES | C9: =SUM(C3:C8) | D9: =SUM(D3:D8) | E9: =SUM(E3:E8) | F9: =SUM(F3:F8) | G9: =SUM(G3:G8) | H9: =SUM(H3:H8) | I9: =SUM(I3:I8) | J9: =SUM(J3:J8)

Sheet Consolidated FTE 
A1: FTE PROJECTION INPUT SUMMARY
A2: Consolidated | C2: Year 1 | D2: Year 2 | E2: Year 3 | F2: Year 4 | G2: Year 5 | H2: Year 6 | I2: Year 7 | J2: Year 8
B3: Consolidated Summary
B4: Switzerland | C4: =C14+C24 | D4: =D14+D24 | E4: =E14+E24 | F4: =F14+F24 | G4: =G14+G24 | H4: =H14+H24 | I4: =I14+I24 | J4: =J14+J24
B5: United States | C5: =C15+C25 | D5: =D15+D25 | E5: =E15+E25 | F5: =F15+F25 | G5: =G15+G25 | H5: =H15+H25 | I5: =I15+I25 | J5: =J15+J25
B6: France | C6: =C16+C26 | D6: =D16+D26 | E6: =E16+E26 | F6: =F16+F26 | G6: =G16+G26 | H6: =H16+H26 | I6: =I16+I26 | J6: =J16+J26
B7: Germany | C7: =C17+C27 | D7: =D17+D27 | E7: =E17+E27 | F7: =F17+F27 | G7: =G17+G27 | H7: =H17+H27 | I7: =I17+I27 | J7: =J17+J27
B8: Germany Production | C8: =C18+C28 | D8: =D18+D28 | E8: =E18+E28 | F8: =F18+F28 | G8: =G18+G28 | H8: =H18+H28 | I8: =I18+I28 | J8: =J18+J28
B9: Spain | C9: =C19+C29 | D9: =D19+D29 | E9: =E19+E29 | F9: =F19+F29 | G9: =G19+G29 | H9: =H19+H29 | I9: =I19+I29 | J9: =J19+J29
B10: Italy | C10: =C20+C30 | D10: =D20+D30 | E10: =E20+E30 | F10: =F20+F30 | G10: =G20+G30 | H10: =H20+H30 | I10: =I20+I30 | J10: =J20+J30
B11: United Kingdom | C11: =C21+C31 | D11: =D21+D31 | E11: =E21+E31 | F11: =F21+F31 | G11: =G21+G31 | H11: =H21+H31 | I11: =I21+I31 | J11: =J21+J31
B12: Total FTEs All Countries | C12: =SUM(C4:C11) | D12: =SUM(D4:D11) | E12: =SUM(E4:E11) | F12: =SUM(F4:F11) | G12: =SUM(G4:G11) | H12: =SUM(H4:H11) | I12: =SUM(I4:I11) | J12: =SUM(J4:J11)
B13: Centre One Summary
B14: Switzerland | C14: =+'Centre One-FTE'!C73 | D14: =+'Centre One-FTE'!D73 | E14: =+'Centre One-FTE'!E73 | F14: =+'Centre One-FTE'!F73 | G14: =+'Centre One-FTE'!G73 | H14: =+'Centre One-FTE'!H73 | I14: =+'Centre One-FTE'!I73 | J14: =+'Centre One-FTE'!J73
B15: United States | C15: =+'Centre One-FTE'!C74 | D15: =+'Centre One-FTE'!D74 | E15: =+'Centre One-FTE'!E74 | F15: =+'Centre One-FTE'!F74 | G15: =+'Centre One-FTE'!G74 | H15: =+'Centre One-FTE'!H74 | I15: =+'Centre One-FTE'!I74 | J15: =+'Centre One-FTE'!J74
B16: France | C16: =+'Centre One-FTE'!C75 | D16: =+'Centre One-FTE'!D75 | E16: =+'Centre One-FTE'!E75 | F16: =+'Centre One-FTE'!F75 | G16: =+'Centre One-FTE'!G75 | H16: =+'Centre One-FTE'!H75 | I16: =+'Centre One-FTE'!I75 | J16: =+'Centre One-FTE'!J75
B17: Germany | C17: =+'Centre One-FTE'!C76 | D17: =+'Centre One-FTE'!D76 | E17: =+'Centre One-FTE'!E76 | F17: =+'Centre One-FTE'!F76 | G17: =+'Centre One-FTE'!G76 | H17: =+'Centre One-FTE'!H76 | I17: =+'Centre One-FTE'!I76 | J17: =+'Centre One-FTE'!J76
B18: Germany Production | C18: =+'Centre One-FTE'!C77 | D18: =+'Centre One-FTE'!D77 | E18: =+'Centre One-FTE'!E77 | F18: =+'Centre One-FTE'!F77 | G18: =+'Centre One-FTE'!G77 | H18: =+'Centre One-FTE'!H77 | I18: =+'Centre One-FTE'!I77 | J18: =+'Centre One-FTE'!J77
B19: Spain | C19: =+'Centre One-FTE'!C78 | D19: =+'Centre One-FTE'!D78 | E19: =+'Centre One-FTE'!E78 | F19: =+'Centre One-FTE'!F78 | G19: =+'Centre One-FTE'!G78 | H19: =+'Centre One-FTE'!H78 | I19: =+'Centre One-FTE'!I78 | J19: =+'Centre One-FTE'!J78
B20: Italy | C20: =+'Centre One-FTE'!C79 | D20: =+'Centre One-FTE'!D79 | E20: =+'Centre One-FTE'!E79 | F20: =+'Centre One-FTE'!F79 | G20: =+'Centre One-FTE'!G79 | H20: =+'Centre One-FTE'!H79 | I20: =+'Centre One-FTE'!I79 | J20: =+'Centre One-FTE'!J79
B21: United Kingdom | C21: =+'Centre One-FTE'!C80 | D21: =+'Centre One-FTE'!D80 | E21: =+'Centre One-FTE'!E80 | F21: =+'Centre One-FTE'!F80 | G21: =+'Centre One-FTE'!G80 | H21: =+'Centre One-FTE'!H80 | I21: =+'Centre One-FTE'!I80 | J21: =+'Centre One-FTE'!J80
B22: Total FTEs - Centre One | C22: =SUM(C14:C21) | D22: =SUM(D14:D21) | E22: =SUM(E14:E21) | F22: =SUM(F14:F21) | G22: =SUM(G14:G21) | H22: =SUM(H14:H21) | I22: =SUM(I14:I21) | J22: =SUM(J14:J21)
B23: Centre Two Summary
B24: Switzerland | C24: =+'Centre Two-FTE'!C73 | D24: =+'Centre Two-FTE'!D73 | E24: =+'Centre Two-FTE'!E73 | F24: =+'Centre Two-FTE'!F73 | G24: =+'Centre Two-FTE'!G73 | H24: =+'Centre Two-FTE'!H73 | I24: =+'Centre Two-FTE'!I73 | J24: =+'Centre Two-FTE'!J73
B25: United States | C25: =+'Centre Two-FTE'!C74 | D25: =+'Centre Two-FTE'!D74 | E25: =+'Centre Two-FTE'!E74 | F25: =+'Centre Two-FTE'!F74 | G25: =+'Centre Two-FTE'!G74 | H25: =+'Centre Two-FTE'!H74 | I25: =+'Centre Two-FTE'!I74 | J25: =+'Centre Two-FTE'!J74
B26: France | C26: =+'Centre Two-FTE'!C75 | D26: =+'Centre Two-FTE'!D75 | E26: =+'Centre Two-FTE'!E75 | F26: =+'Centre Two-FTE'!F75 | G26: =+'Centre Two-FTE'!G75 | H26: =+'Centre Two-FTE'!H75 | I26: =+'Centre Two-FTE'!I75 | J26: =+'Centre Two-FTE'!J75
B27: Germany | C27: =+'Centre Two-FTE'!C76 | D27: =+'Centre Two-FTE'!D76 | E27: =+'Centre Two-FTE'!E76 | F27: =+'Centre Two-FTE'!F76 | G27: =+'Centre Two-FTE'!G76 | H27: =+'Centre Two-FTE'!H76 | I27: =+'Centre Two-FTE'!I76 | J27: =+'Centre Two-FTE'!J76
B28: Germany Production | C28: =+'Centre Two-FTE'!C77 | D28: =+'Centre Two-FTE'!D77 | E28: =+'Centre Two-FTE'!E77 | F28: =+'Centre Two-FTE'!F77 | G28: =+'Centre Two-FTE'!G77 | H28: =+'Centre Two-FTE'!H77 | I28: =+'Centre Two-FTE'!I77 | J28: =+'Centre Two-FTE'!J77
B29: Spain | C29: =+'Centre Two-FTE'!C78 | D29: =+'Centre Two-FTE'!D78 | E29: =+'Centre Two-FTE'!E78 | F29: =+'Centre Two-FTE'!F78 | G29: =+'Centre Two-FTE'!G78 | H29: =+'Centre Two-FTE'!H78 | I29: =+'Centre Two-FTE'!I78 | J29: =+'Centre Two-FTE'!J78
B30: Italy | C30: =+'Centre Two-FTE'!C79 | D30: =+'Centre Two-FTE'!D79 | E30: =+'Centre Two-FTE'!E79 | F30: =+'Centre Two-FTE'!F79 | G30: =+'Centre Two-FTE'!G79 | H30: =+'Centre Two-FTE'!H79 | I30: =+'Centre Two-FTE'!I79 | J30: =+'Centre Two-FTE'!J79
B31: United Kingdom | C31: =+'Centre Two-FTE'!C80 | D31: =+'Centre Two-FTE'!D80 | E31: =+'Centre Two-FTE'!E80 | F31: =+'Centre Two-FTE'!F80 | G31: =+'Centre Two-FTE'!G80 | H31: =+'Centre Two-FTE'!H80 | I31: =+'Centre Two-FTE'!I80 | J31: =+'Centre Two-FTE'!J80
B32: Total FTEs - Centre Two | C32: =SUM(C24:C31) | D32: =SUM(D24:D31) | E32: =SUM(E24:E31) | F32: =SUM(F24:F31) | G32: =SUM(G24:G31) | H32: =SUM(H24:H31) | I32: =SUM(I24:I31) | J32: =SUM(J24:J31)
B33: Process Summary
B34: General Accounting & Sox
B35: Centre One | C35: ='Centre One-FTE'!$C$20 | D35: ='Centre One-FTE'!$D$20 | E35: ='Centre One-FTE'!$E$20 | F35: ='Centre One-FTE'!$F$20 | G35: ='Centre One-FTE'!$G$20 | H35: ='Centre One-FTE'!$H$20 | I35: ='Centre One-FTE'!$I$20 | J35: ='Centre One-FTE'!$J$20
B36: Centre Two | C36: ='Centre Two-FTE'!$C$20 | D36: ='Centre Two-FTE'!$D$20 | E36: ='Centre Two-FTE'!$E$20 | F36: ='Centre Two-FTE'!$F$20 | G36: ='Centre Two-FTE'!$G$20 | H36: ='Centre Two-FTE'!$H$20 | I36: ='Centre Two-FTE'!$I$20 | J36: ='Centre Two-FTE'!$J$20
B37: Sub Total | C37: =SUM(C35:C36) | D37: =SUM(D35:D36) | E37: =SUM(E35:E36) | F37: =SUM(F35:F36) | G37: =SUM(G35:G36) | H37: =SUM(H35:H36) | I37: =SUM(I35:I36) | J37: =SUM(J35:J36)
B38: Fixed Assets
B39: Centre One | C39: ='Centre One-FTE'!$C$30 | D39: ='Centre One-FTE'!$D$30 | E39: ='Centre One-FTE'!$E$30 | F39: ='Centre One-FTE'!$F$30 | G39: ='Centre One-FTE'!$G$30 | H39: ='Centre One-FTE'!$H$30 | I39: ='Centre One-FTE'!$I$30 | J39: ='Centre One-FTE'!$J$30
B40: Centre Two | C40: ='Centre Two-FTE'!$C$30 | D40: ='Centre Two-FTE'!$D$30 | E40: ='Centre Two-FTE'!$E$30 | F40: ='Centre Two-FTE'!$F$30 | G40: ='Centre Two-FTE'!$G$30 | H40: ='Centre Two-FTE'!$H$30 | I40: ='Centre Two-FTE'!$I$30 | J40: ='Centre Two-FTE'!$J$30
B41: Sub Total | C41: =SUM(C39:C40) | D41: =SUM(D39:D40) | E41: =SUM(E39:E40) | F41: =SUM(F39:F40) | G41: =SUM(G39:G40) | H41: =SUM(H39:H40) | I41: =SUM(I39:I40) | J41: =SUM(J39:J40)
B42: Accounts Payable
B43: Centre One | C43: ='Centre One-FTE'!$C$40 | D43: ='Centre One-FTE'!$D$40 | E43: ='Centre One-FTE'!$E$40 | F43: ='Centre One-FTE'!$F$40 | G43: ='Centre One-FTE'!$G$40 | H43: ='Centre One-FTE'!$H$40 | I43: ='Centre One-FTE'!$I$40 | J43: ='Centre One-FTE'!$J$40
B44: Centre Two | C44: ='Centre Two-FTE'!$C$40 | D44: ='Centre Two-FTE'!$D$40 | E44: ='Centre Two-FTE'!$E$40 | F44: ='Centre Two-FTE'!$F$40 | G44: ='Centre Two-FTE'!$G$40 | H44: ='Centre Two-FTE'!$H$40 | I44: ='Centre Two-FTE'!$I$40 | J44: ='Centre Two-FTE'!$J$40
B45: Sub Total | C45: =SUM(C43:C44) | D45: =SUM(D43:D44) | E45: =SUM(E43:E44) | F45: =SUM(F43:F44) | G45: =SUM(G43:G44) | H45: =SUM(H43:H44) | I45: =SUM(I43:I44) | J45: =SUM(J43:J44)
B46: T&E
B47: Centre One | C47: ='Centre One-FTE'!$C$50 | D47: ='Centre One-FTE'!$D$50 | E47: ='Centre One-FTE'!$E$50 | F47: ='Centre One-FTE'!$F$50 | G47: ='Centre One-FTE'!$G$50 | H47: ='Centre One-FTE'!$H$50 | I47: ='Centre One-FTE'!$I$50 | J47: ='Centre One-FTE'!$J$50
B48: Centre Two | C48: ='Centre Two-FTE'!$C$50 | D48: ='Centre Two-FTE'!$D$50 | E48: ='Centre Two-FTE'!$E$50 | F48: ='Centre Two-FTE'!$F$50 | G48: ='Centre Two-FTE'!$G$50 | H48: ='Centre Two-FTE'!$H$50 | I48: ='Centre Two-FTE'!$I$50 | J48: ='Centre Two-FTE'!$J$50
B49: Sub Total | C49: =SUM(C47:C48) | D49: =SUM(D47:D48) | E49: =SUM(E47:E48) | F49: =SUM(F47:F48) | G49: =SUM(G47:G48) | H49: =SUM(H47:H48) | I49: =SUM(I47:I48) | J49: =SUM(J47:J48)
B50: Order to Cash
B51: Centre One | C51: ='Centre One-FTE'!$C$60 | D51: ='Centre One-FTE'!$D$60 | E51: ='Centre One-FTE'!$E$60 | F51: ='Centre One-FTE'!$F$60 | G51: ='Centre One-FTE'!$G$60 | H51: ='Centre One-FTE'!$H$60 | I51: ='Centre One-FTE'!$I$60 | J51: ='Centre One-FTE'!$J$60
B52: Centre Two | C52: ='Centre Two-FTE'!$C$60 | D52: ='Centre Two-FTE'!$D$60 | E52: ='Centre Two-FTE'!$E$60 | F52: ='Centre Two-FTE'!$F$60 | G52: ='Centre Two-FTE'!$G$60 | H52: ='Centre Two-FTE'!$H$60 | I52: ='Centre Two-FTE'!$I$60 | J52: ='Centre Two-FTE'!$J$60
B53: Sub Total | C53: =SUM(C51:C52) | D53: =SUM(D51:D52) | E53: =SUM(E51:E52) | F53: =SUM(F51:F52) | G53: =SUM(G51:G52) | H53: =SUM(H51:H52) | I53: =SUM(I51:I52) | J53: =SUM(J51:J52)
B54: Requistion to Pay
B55: Centre One | C55: ='Centre One-FTE'!$C$70 | D55: ='Centre One-FTE'!$D$70 | E55: ='Centre One-FTE'!$E$70 | F55: ='Centre One-FTE'!$F$70 | G55: ='Centre One-FTE'!$G$70 | H55: ='Centre One-FTE'!$H$70 | I55: ='Centre One-FTE'!$I$70 | J55: ='Centre One-FTE'!$J$70
B56: Centre Two | C56: ='Centre Two-FTE'!$C$70 | D56: ='Centre Two-FTE'!$D$70 | E56: ='Centre Two-FTE'!$E$70 | F56: ='Centre Two-FTE'!$F$70 | G56: ='Centre Two-FTE'!$G$70 | H56: ='Centre Two-FTE'!$H$70 | I56: ='Centre Two-FTE'!$I$70 | J56: ='Centre Two-FTE'!$J$70
B57: Sub Total | C57: =SUM(C55:C56) | D57: =SUM(D55:D56) | E57: =SUM(E55:E56) | F57: =SUM(F55:F56) | G57: =SUM(G55:G56) | H57: =SUM(H55:H56) | I57: =SUM(I55:I56) | J57: =SUM(J55:J56)
B58: Total FTEs All Countries | C58: =C37+C41+C45+C49+C53+C57 | D58: =D37+D41+D45+D49+D53+D57 | E58: =E37+E41+E45+E49+E53+E57 | F58: =F37+F41+F45+F49+F53+F57 | G58: =G37+G41+G45+G49+G53+G57 | H58: =H37+H41+H45+H49+H53+H57 | I58: =I37+I41+I45+I49+I53+I57 | J58: =J37+J41+J45+J49+J53+J57

Sheet Centre One-FTE
A1: FTE PROJECTION INPUT SUMMARY
A2: Centre One | C2: Year 1 | D2: Year 2 | E2: Year 3 | F2: Year 4 | G2: Year 5 | H2: Year 6 | I2: Year 7 | J2: Year 8
B3: Process Summary
B4: General Accounting & Sox | C4: =+SUM('Switzerland-FTE:UK-FTE'!$C3) | D4: =+SUM('Switzerland-FTE:UK-FTE'!$D3) | E4: =+SUM('Switzerland-FTE:UK-FTE'!$E3) | F4: =+SUM('Switzerland-FTE:UK-FTE'!$F3) | G4: =+SUM('Switzerland-FTE:UK-FTE'!$G3) | H4: =+SUM('Switzerland-FTE:UK-FTE'!$H3) | I4: =+SUM('Switzerland-FTE:UK-FTE'!$I3) | J4: =+SUM('Switzerland-FTE:UK-FTE'!$J3)
B5: Fixed Assets | C5: =+SUM('Switzerland-FTE:UK-FTE'!$C4) | D5: =+SUM('Switzerland-FTE:UK-FTE'!$D4) | E5: =+SUM('Switzerland-FTE:UK-FTE'!$E4) | F5: =+SUM('Switzerland-FTE:UK-FTE'!$F4) | G5: =+SUM('Switzerland-FTE:UK-FTE'!$G4) | H5: =+SUM('Switzerland-FTE:UK-FTE'!$H4) | I5: =+SUM('Switzerland-FTE:UK-FTE'!$I4) | J5: =+SUM('Switzerland-FTE:UK-FTE'!$J4)
B6: Accounts Payable | C6: =+SUM('Switzerland-FTE:UK-FTE'!$C5) | D6: =+SUM('Switzerland-FTE:UK-FTE'!$D5) | E6: =+SUM('Switzerland-FTE:UK-FTE'!$E5) | F6: =+SUM('Switzerland-FTE:UK-FTE'!$F5) | G6: =+SUM('Switzerland-FTE:UK-FTE'!$G5) | H6: =+SUM('Switzerland-FTE:UK-FTE'!$H5) | I6: =+SUM('Switzerland-FTE:UK-FTE'!$I5) | J6: =+SUM('Switzerland-FTE:UK-FTE'!$J5)
B7: T&E | C7: =+SUM('Switzerland-FTE:UK-FTE'!$C6) | D7: =+SUM('Switzerland-FTE:UK-FTE'!$D6) | E7: =+SUM('Switzerland-FTE:UK-FTE'!$E6) | F7: =+SUM('Switzerland-FTE:UK-FTE'!$F6) | G7: =+SUM('Switzerland-FTE:UK-FTE'!$G6) | H7: =+SUM('Switzerland-FTE:UK-FTE'!$H6) | I7: =+SUM('Switzerland-FTE:UK-FTE'!$I6) | J7: =+SUM('Switzerland-FTE:UK-FTE'!$J6)
B8: Order to Cash | C8: =+SUM('Switzerland-FTE:UK-FTE'!$C7) | D8: =+SUM('Switzerland-FTE:UK-FTE'!$D7) | E8: =+SUM('Switzerland-FTE:UK-FTE'!$E7) | F8: =+SUM('Switzerland-FTE:UK-FTE'!$F7) | G8: =+SUM('Switzerland-FTE:UK-FTE'!$G7) | H8: =+SUM('Switzerland-FTE:UK-FTE'!$H7) | I8: =+SUM('Switzerland-FTE:UK-FTE'!$I7) | J8: =+SUM('Switzerland-FTE:UK-FTE'!$J7)
B9: Requistion to Pay | C9: =+SUM('Switzerland-FTE:UK-FTE'!$C8) | D9: =+SUM('Switzerland-FTE:UK-FTE'!$D8) | E9: =+SUM('Switzerland-FTE:UK-FTE'!$E8) | F9: =+SUM('Switzerland-FTE:UK-FTE'!$F8) | G9: =+SUM('Switzerland-FTE:UK-FTE'!$G8) | H9: =+SUM('Switzerland-FTE:UK-FTE'!$H8) | I9: =+SUM('Switzerland-FTE:UK-FTE'!$I8) | J9: =+SUM('Switzerland-FTE:UK-FTE'!$J8)
B10: Total FTEs All Countries | C10: =SUM(C4:C9) | D10: =SUM(D4:D9) | E10: =SUM(E4:E9) | F10: =SUM(F4:F9) | G10: =SUM(G4:G9) | H10: =SUM(H4:H9) | I10: =SUM(I4:I9) | J10: =SUM(J4:J9)
B11: General Accounting & Sox
B12: Switzerland | C12: ='Switzerland-FTE'!$C$3 | D12: ='Switzerland-FTE'!$D$3 | E12: ='Switzerland-FTE'!$E$3 | F12: ='Switzerland-FTE'!$F$3 | G12: ='Switzerland-FTE'!$G$3 | H12: ='Switzerland-FTE'!$H$3 | I12: ='Switzerland-FTE'!$I$3 | J12: ='Switzerland-FTE'!$J$3
B13: United States | C13: ='US-FTE'!$C$3 | D13: ='US-FTE'!$D$3 | E13: ='US-FTE'!$E$3 | F13: ='US-FTE'!$F$3 | G13: ='US-FTE'!$G$3 | H13: ='US-FTE'!$H$3 | I13: ='US-FTE'!$I$3 | J13: ='US-FTE'!$J$3
B14: France | C14: ='France-FTE'!$C$3 | D14: ='France-FTE'!$D$3 | E14: ='France-FTE'!$E$3 | F14: ='France-FTE'!$F$3 | G14: ='France-FTE'!$G$3 | H14: ='France-FTE'!$H$3 | I14: ='France-FTE'!$I$3 | J14: ='France-FTE'!$J$3
B15: Germany | C15: ='Germany-FTE'!$C$3 | D15: ='Germany-FTE'!$D$3 | E15: ='Germany-FTE'!$E$3 | F15: ='Germany-FTE'!$F$3 | G15: ='Germany-FTE'!$G$3 | H15: ='Germany-FTE'!$H$3 | I15: ='Germany-FTE'!$I$3 | J15: ='Germany-FTE'!$J$3
B16: Germany Production | C16: ='Germany Production-FTE'!$C$3 | D16: ='Germany Production-FTE'!$D$3 | E16: ='Germany Production-FTE'!$E$3 | F16: ='Germany Production-FTE'!$F$3 | G16: ='Germany Production-FTE'!$G$3 | H16: ='Germany Production-FTE'!$H$3 | I16: ='Germany Production-FTE'!$I$3 | J16: ='Germany Production-FTE'!$J$3
B17: Spain | C17: ='Spain-FTE'!$C$3 | D17: ='Spain-FTE'!$D$3 | E17: ='Spain-FTE'!$E$3 | F17: ='Spain-FTE'!$F$3 | G17: ='Spain-FTE'!$G$3 | H17: ='Spain-FTE'!$H$3 | I17: ='Spain-FTE'!$I$3 | J17: ='Spain-FTE'!$J$3
B18: Italy | C18: ='Italy-FTE'!$C$3 | D18: ='Italy-FTE'!$D$3 | E18: ='Italy-FTE'!$E$3 | F18: ='Italy-FTE'!$F$3 | G18: ='Italy-FTE'!$G$3 | H18: ='Italy-FTE'!$H$3 | I18: ='Italy-FTE'!$I$3 | J18: ='Italy-FTE'!$J$3
B19: United Kingdom | C19: ='UK-FTE'!$C$3 | D19: ='UK-FTE'!$D$3 | E19: ='UK-FTE'!$E$3 | F19: ='UK-FTE'!$F$3 | G19: ='UK-FTE'!$G$3 | H19: ='UK-FTE'!$H$3 | I19: ='UK-FTE'!$I$3 | J19: ='UK-FTE'!$J$3
B20: Sub Total | C20: =SUM(C12:C19) | D20: =SUM(D12:D19) | E20: =SUM(E12:E19) | F20: =SUM(F12:F19) | G20: =SUM(G12:G19) | H20: =SUM(H12:H19) | I20: =SUM(I12:I19) | J20: =SUM(J12:J19)
B21: Fixed Assets
B22: Switzerland | C22: ='Switzerland-FTE'!$C$4 | D22: ='Switzerland-FTE'!$D$4 | E22: ='Switzerland-FTE'!$E$4 | F22: ='Switzerland-FTE'!$F$4 | G22: ='Switzerland-FTE'!$G$4 | H22: ='Switzerland-FTE'!$H$4 | I22: ='Switzerland-FTE'!$I$4 | J22: ='Switzerland-FTE'!$J$4
B23: United States | C23: ='US-FTE'!$C$4 | D23: ='US-FTE'!$D$4 | E23: ='US-FTE'!$E$4 | F23: ='US-FTE'!$F$4 | G23: ='US-FTE'!$G$4 | H23: ='US-FTE'!$H$4 | I23: ='US-FTE'!$I$4 | J23: ='US-FTE'!$J$4
B24: France | C24: ='France-FTE'!$C$4 | D24: ='France-FTE'!$D$4 | E24: ='France-FTE'!$E$4 | F24: ='France-FTE'!$F$4 | G24: ='France-FTE'!$G$4 | H24: ='France-FTE'!$H$4 | I24: ='France-FTE'!$I$4 | J24: ='France-FTE'!$J$4
B25: Germany | C25: ='Germany-FTE'!$C$4 | D25: ='Germany-FTE'!$D$4 | E25: ='Germany-FTE'!$E$4 | F25: ='Germany-FTE'!$F$4 | G25: ='Germany-FTE'!$G$4 | H25: ='Germany-FTE'!$H$4 | I25: ='Germany-FTE'!$I$4 | J25: ='Germany-FTE'!$J$4
B26: Germany Production | C26: ='Germany Production-FTE'!$C$4 | D26: ='Germany Production-FTE'!$D$4 | E26: ='Germany Production-FTE'!$E$4 | F26: ='Germany Production-FTE'!$F$4 | G26: ='Germany Production-FTE'!$G$4 | H26: ='Germany Production-FTE'!$H$4 | I26: ='Germany Production-FTE'!$I$4 | J26: ='Germany Production-FTE'!$J$4
B27: Spain | C27: ='Spain-FTE'!$C$4 | D27: ='Spain-FTE'!$D$4 | E27: ='Spain-FTE'!$E$4 | F27: ='Spain-FTE'!$F$4 | G27: ='Spain-FTE'!$G$4 | H27: ='Spain-FTE'!$H$4 | I27: ='Spain-FTE'!$I$4 | J27: ='Spain-FTE'!$J$4
B28: Italy | C28: ='Italy-FTE'!$C$4 | D28: ='Italy-FTE'!$D$4 | E28: ='Italy-FTE'!$E$4 | F28: ='Italy-FTE'!$F$4 | G28: ='Italy-FTE'!$G$4 | H28: ='Italy-FTE'!$H$4 | I28: ='Italy-FTE'!$I$4 | J28: ='Italy-FTE'!$J$4
B29: United Kingdom | C29: ='UK-FTE'!$C$4 | D29: ='UK-FTE'!$D$4 | E29: ='UK-FTE'!$E$4 | F29: ='UK-FTE'!$F$4 | G29: ='UK-FTE'!$G$4 | H29: ='UK-FTE'!$H$4 | I29: ='UK-FTE'!$I$4 | J29: ='UK-FTE'!$J$4
B30: Sub Total | C30: =SUM(C22:C29) | D30: =SUM(D22:D29) | E30: =SUM(E22:E29) | F30: =SUM(F22:F29) | G30: =SUM(G22:G29) | H30: =SUM(H22:H29) | I30: =SUM(I22:I29) | J30: =SUM(J22:J29)
B31: Accounts Payable
B32: Switzerland | C32: ='Switzerland-FTE'!$C$5 | D32: ='Switzerland-FTE'!$D$5 | E32: ='Switzerland-FTE'!$E$5 | F32: ='Switzerland-FTE'!$F$5 | G32: ='Switzerland-FTE'!$G$5 | H32: ='Switzerland-FTE'!$H$5 | I32: ='Switzerland-FTE'!$I$5 | J32: ='Switzerland-FTE'!$J$5
B33: United States | C33: ='US-FTE'!$C$5 | D33: ='US-FTE'!$D$5 | E33: ='US-FTE'!$E$5 | F33: ='US-FTE'!$F$5 | G33: ='US-FTE'!$G$5 | H33: ='US-FTE'!$H$5 | I33: ='US-FTE'!$I$5 | J33: ='US-FTE'!$J$5
B34: France | C34: ='France-FTE'!$C$5 | D34: ='France-FTE'!$D$5 | E34: ='France-FTE'!$E$5 | F34: ='France-FTE'!$F$5 | G34: ='France-FTE'!$G$5 | H34: ='France-FTE'!$H$5 | I34: ='France-FTE'!$I$5 | J34: ='France-FTE'!$J$5
B35: Germany | C35: ='Germany-FTE'!$C$5 | D35: ='Germany-FTE'!$D$5 | E35: ='Germany-FTE'!$E$5 | F35: ='Germany-FTE'!$F$5 | G35: ='Germany-FTE'!$G$5 | H35: ='Germany-FTE'!$H$5 | I35: ='Germany-FTE'!$I$5 | J35: ='Germany-FTE'!$J$5
B36: Germany Production | C36: ='Germany Production-FTE'!$C$5 | D36: ='Germany Production-FTE'!$D$5 | E36: ='Germany Production-FTE'!$E$5 | F36: ='Germany Production-FTE'!$F$5 | G36: ='Germany Production-FTE'!$G$5 | H36: ='Germany Production-FTE'!$H$5 | I36: ='Germany Production-FTE'!$I$5 | J36: ='Germany Production-FTE'!$J$5
B37: Spain | C37: ='Spain-FTE'!$C$5 | D37: ='Spain-FTE'!$D$5 | E37: ='Spain-FTE'!$E$5 | F37: ='Spain-FTE'!$F$5 | G37: ='Spain-FTE'!$G$5 | H37: ='Spain-FTE'!$H$5 | I37: ='Spain-FTE'!$I$5 | J37: ='Spain-FTE'!$J$5
B38: Italy | C38: ='Italy-FTE'!$C$5 | D38: ='Italy-FTE'!$D$5 | E38: ='Italy-FTE'!$E$5 | F38: ='Italy-FTE'!$F$5 | G38: ='Italy-FTE'!$G$5 | H38: ='Italy-FTE'!$H$5 | I38: ='Italy-FTE'!$I$5 | J38: ='Italy-FTE'!$J$5
B39: United Kingdom | C39: ='UK-FTE'!$C$5 | D39: ='UK-FTE'!$D$5 | E39: ='UK-FTE'!$E$5 | F39: ='UK-FTE'!$F$5 | G39: ='UK-FTE'!$G$5 | H39: ='UK-FTE'!$H$5 | I39: ='UK-FTE'!$I$5 | J39: ='UK-FTE'!$J$5
B40: Sub Total | C40: =SUM(C32:C39) | D40: =SUM(D32:D39) | E40: =SUM(E32:E39) | F40: =SUM(F32:F39) | G40: =SUM(G32:G39) | H40: =SUM(H32:H39) | I40: =SUM(I32:I39) | J40: =SUM(J32:J39)
B41: T&E
B42: Switzerland | C42: ='Switzerland-FTE'!$C$6 | D42: ='Switzerland-FTE'!$D$6 | E42: ='Switzerland-FTE'!$E$6 | F42: ='Switzerland-FTE'!$F$6 | G42: ='Switzerland-FTE'!$G$6 | H42: ='Switzerland-FTE'!$H$6 | I42: ='Switzerland-FTE'!$I$6 | J42: ='Switzerland-FTE'!$J$6
B43: United States | C43: ='US-FTE'!$C$6 | D43: ='US-FTE'!$D$6 | E43: ='US-FTE'!$E$6 | F43: ='US-FTE'!$F$6 | G43: ='US-FTE'!$G$6 | H43: ='US-FTE'!$H$6 | I43: ='US-FTE'!$I$6 | J43: ='US-FTE'!$J$6
B44: France | C44: ='France-FTE'!$C$6 | D44: ='France-FTE'!$D$6 | E44: ='France-FTE'!$E$6 | F44: ='France-FTE'!$F$6 | G44: ='France-FTE'!$G$6 | H44: ='France-FTE'!$H$6 | I44: ='France-FTE'!$I$6 | J44: ='France-FTE'!$J$6
B45: Germany | C45: ='Germany-FTE'!$C$6 | D45: ='Germany-FTE'!$D$6 | E45: ='Germany-FTE'!$E$6 | F45: ='Germany-FTE'!$F$6 | G45: ='Germany-FTE'!$G$6 | H45: ='Germany-FTE'!$H$6 | I45: ='Germany-FTE'!$I$6 | J45: ='Germany-FTE'!$J$6
B46: Germany Production | C46: ='Germany Production-FTE'!$C$6 | D46: ='Germany Production-FTE'!$D$6 | E46: ='Germany Production-FTE'!$E$6 | F46: ='Germany Production-FTE'!$F$6 | G46: ='Germany Production-FTE'!$G$6 | H46: ='Germany Production-FTE'!$H$6 | I46: ='Germany Production-FTE'!$I$6 | J46: ='Germany Production-FTE'!$J$6
B47: Spain | C47: ='Spain-FTE'!$C$6 | D47: ='Spain-FTE'!$D$6 | E47: ='Spain-FTE'!$E$6 | F47: ='Spain-FTE'!$F$6 | G47: ='Spain-FTE'!$G$6 | H47: ='Spain-FTE'!$H$6 | I47: ='Spain-FTE'!$I$6 | J47: ='Spain-FTE'!$J$6
B48: Italy | C48: ='Italy-FTE'!$C$6 | D48: ='Italy-FTE'!$D$6 | E48: ='Italy-FTE'!$E$6 | F48: ='Italy-FTE'!$F$6 | G48: ='Italy-FTE'!$G$6 | H48: ='Italy-FTE'!$H$6 | I48: ='Italy-FTE'!$I$6 | J48: ='Italy-FTE'!$J$6
B49: United Kingdom | C49: ='UK-FTE'!$C$6 | D49: ='UK-FTE'!$D$6 | E49: ='UK-FTE'!$E$6 | F49: ='UK-FTE'!$F$6 | G49: ='UK-FTE'!$G$6 | H49: ='UK-FTE'!$H$6 | I49: ='UK-FTE'!$I$6 | J49: ='UK-FTE'!$J$6
B50: Sub Total | C50: =SUM(C42:C49) | D50: =SUM(D42:D49) | E50: =SUM(E42:E49) | F50: =SUM(F42:F49) | G50: =SUM(G42:G49) | H50: =SUM(H42:H49) | I50: =SUM(I42:I49) | J50: =SUM(J42:J49)
B51: Order to Cash
B52: Switzerland | C52: ='Switzerland-FTE'!$C$7 | D52: ='Switzerland-FTE'!$D$7 | E52: ='Switzerland-FTE'!$E$7 | F52: ='Switzerland-FTE'!$F$7 | G52: ='Switzerland-FTE'!$G$7 | H52: ='Switzerland-FTE'!$H$7 | I52: ='Switzerland-FTE'!$I$7 | J52: ='Switzerland-FTE'!$J$7
B53: United States | C53: ='US-FTE'!$C$7 | D53: ='US-FTE'!$D$7 | E53: ='US-FTE'!$E$7 | F53: ='US-FTE'!$F$7 | G53: ='US-FTE'!$G$7 | H53: ='US-FTE'!$H$7 | I53: ='US-FTE'!$I$7 | J53: ='US-FTE'!$J$7
B54: France | C54: ='France-FTE'!$C$7 | D54: ='France-FTE'!$D$7 | E54: ='France-FTE'!$E$7 | F54: ='France-FTE'!$F$7 | G54: ='France-FTE'!$G$7 | H54: ='France-FTE'!$H$7 | I54: ='France-FTE'!$I$7 | J54: ='France-FTE'!$J$7
B55: Germany | C55: ='Germany-FTE'!$C$7 | D55: ='Germany-FTE'!$D$7 | E55: ='Germany-FTE'!$E$7 | F55: ='Germany-FTE'!$F$7 | G55: ='Germany-FTE'!$G$7 | H55: ='Germany-FTE'!$H$7 | I55: ='Germany-FTE'!$I$7 | J55: ='Germany-FTE'!$J$7
B56: Germany Production | C56: ='Germany Production-FTE'!$C$7 | D56: ='Germany Production-FTE'!$D$7 | E56: ='Germany Production-FTE'!$E$7 | F56: ='Germany Production-FTE'!$F$7 | G56: ='Germany Production-FTE'!$G$7 | H56: ='Germany Production-FTE'!$H$7 | I56: ='Germany Production-FTE'!$I$7 | J56: ='Germany Production-FTE'!$J$7
B57: Spain | C57: ='Spain-FTE'!$C$7 | D57: ='Spain-FTE'!$D$7 | E57: ='Spain-FTE'!$E$7 | F57: ='Spain-FTE'!$F$7 | G57: ='Spain-FTE'!$G$7 | H57: ='Spain-FTE'!$H$7 | I57: ='Spain-FTE'!$I$7 | J57: ='Spain-FTE'!$J$7
B58: Italy | C58: ='Italy-FTE'!$C$7 | D58: ='Italy-FTE'!$D$7 | E58: ='Italy-FTE'!$E$7 | F58: ='Italy-FTE'!$F$7 | G58: ='Italy-FTE'!$G$7 | H58: ='Italy-FTE'!$H$7 | I58: ='Italy-FTE'!$I$7 | J58: ='Italy-FTE'!$J$7
B59: United Kingdom | C59: ='UK-FTE'!$C$7 | D59: ='UK-FTE'!$D$7 | E59: ='UK-FTE'!$E$7 | F59: ='UK-FTE'!$F$7 | G59: ='UK-FTE'!$G$7 | H59: ='UK-FTE'!$H$7 | I59: ='UK-FTE'!$I$7 | J59: ='UK-FTE'!$J$7
B60: Sub Total | C60: =SUM(C52:C59) | D60: =SUM(D52:D59) | E60: =SUM(E52:E59) | F60: =SUM(F52:F59) | G60: =SUM(G52:G59) | H60: =SUM(H52:H59) | I60: =SUM(I52:I59) | J60: =SUM(J52:J59)
B61: Requistion to Pay
B62: Switzerland | C62: ='Switzerland-FTE'!$C$8 | D62: ='Switzerland-FTE'!$D$8 | E62: ='Switzerland-FTE'!$E$8 | F62: ='Switzerland-FTE'!$F$8 | G62: ='Switzerland-FTE'!$G$8 | H62: ='Switzerland-FTE'!$H$8 | I62: ='Switzerland-FTE'!$I$8 | J62: ='Switzerland-FTE'!$J$8
B63: United States | C63: ='US-FTE'!$C$8 | D63: ='US-FTE'!$D$8 | E63: ='US-FTE'!$E$8 | F63: ='US-FTE'!$F$8 | G63: ='US-FTE'!$G$8 | H63: ='US-FTE'!$H$8 | I63: ='US-FTE'!$I$8 | J63: ='US-FTE'!$J$8
B64: France | C64: ='France-FTE'!$C$8 | D64: ='France-FTE'!$D$8 | E64: ='France-FTE'!$E$8 | F64: ='France-FTE'!$F$8 | G64: ='France-FTE'!$G$8 | H64: ='France-FTE'!$H$8 | I64: ='France-FTE'!$I$8 | J64: ='France-FTE'!$J$8
B65: Germany | C65: ='Germany-FTE'!$C$8 | D65: ='Germany-FTE'!$D$8 | E65: ='Germany-FTE'!$E$8 | F65: ='Germany-FTE'!$F$8 | G65: ='Germany-FTE'!$G$8 | H65: ='Germany-FTE'!$H$8 | I65: ='Germany-FTE'!$I$8 | J65: ='Germany-FTE'!$J$8
B66: Germany Production | C66: ='Germany Production-FTE'!$C$8 | D66: ='Germany Production-FTE'!$D$8 | E66: ='Germany Production-FTE'!$E$8 | F66: ='Germany Production-FTE'!$F$8 | G66: ='Germany Production-FTE'!$G$8 | H66: ='Germany Production-FTE'!$H$8 | I66: ='Germany Production-FTE'!$I$8 | J66: ='Germany Production-FTE'!$J$8
B67: Spain | C67: ='Spain-FTE'!$C$8 | D67: ='Spain-FTE'!$D$8 | E67: ='Spain-FTE'!$E$8 | F67: ='Spain-FTE'!$F$8 | G67: ='Spain-FTE'!$G$8 | H67: ='Spain-FTE'!$H$8 | I67: ='Spain-FTE'!$I$8 | J67: ='Spain-FTE'!$J$8
B68: Italy | C68: ='Italy-FTE'!$C$8 | D68: ='Italy-FTE'!$D$8 | E68: ='Italy-FTE'!$E$8 | F68: ='Italy-FTE'!$F$8 | G68: ='Italy-FTE'!$G$8 | H68: ='Italy-FTE'!$H$8 | I68: ='Italy-FTE'!$I$8 | J68: ='Italy-FTE'!$J$8
B69: United Kingdom | C69: ='UK-FTE'!$C$8 | D69: ='UK-FTE'!$D$8 | E69: ='UK-FTE'!$E$8 | F69: ='UK-FTE'!$F$8 | G69: ='UK-FTE'!$G$8 | H69: ='UK-FTE'!$H$8 | I69: ='UK-FTE'!$I$8 | J69: ='UK-FTE'!$J$8
B70: Sub Total | C70: =SUM(C62:C69) | D70: =SUM(D62:D69) | E70: =SUM(E62:E69) | F70: =SUM(F62:F69) | G70: =SUM(G62:G69) | H70: =SUM(H62:H69) | I70: =SUM(I62:I69) | J70: =SUM(J62:J69)
B71: Total FTEs All Countries | C71: =C20+C30+C40+C50+C60+C70 | D71: =D20+D30+D40+D50+D60+D70 | E71: =E20+E30+E40+E50+E60+E70 | F71: =F20+F30+F40+F50+F60+F70 | G71: =G20+G30+G40+G50+G60+G70 | H71: =H20+H30+H40+H50+H60+H70 | I71: =I20+I30+I40+I50+I60+I70 | J71: =J20+J30+J40+J50+J60+J70
B72: Country Summary
B73: Switzerland | C73: ='Switzerland-FTE'!C9 | D73: ='Switzerland-FTE'!D9 | E73: ='Switzerland-FTE'!E9 | F73: ='Switzerland-FTE'!F9 | G73: ='Switzerland-FTE'!G9 | H73: ='Switzerland-FTE'!H9 | I73: ='Switzerland-FTE'!I9 | J73: ='Switzerland-FTE'!J9
B74: United States | C74: ='US-FTE'!C9 | D74: ='US-FTE'!D9 | E74: ='US-FTE'!E9 | F74: ='US-FTE'!F9 | G74: ='US-FTE'!G9 | H74: ='US-FTE'!H9 | I74: ='US-FTE'!I9 | J74: ='US-FTE'!J9
B75: France | C75: ='France-FTE'!C9 | D75: ='France-FTE'!D9 | E75: ='France-FTE'!E9 | F75: ='France-FTE'!F9 | G75: ='France-FTE'!G9 | H75: ='France-FTE'!H9 | I75: ='France-FTE'!I9 | J75: ='France-FTE'!J9
B76: Germany | C76: ='Germany-FTE'!C9 | D76: ='Germany-FTE'!D9 | E76: ='Germany-FTE'!E9 | F76: ='Germany-FTE'!F9 | G76: ='Germany-FTE'!G9 | H76: ='Germany-FTE'!H9 | I76: ='Germany-FTE'!I9 | J76: ='Germany-FTE'!J9
B77: Germany Production | C77: ='Germany Production-FTE'!C9 | D77: ='Germany Production-FTE'!D9 | E77: ='Germany Production-FTE'!E9 | F77: ='Germany Production-FTE'!F9 | G77: ='Germany Production-FTE'!G9 | H77: ='Germany Production-FTE'!H9 | I77: ='Germany Production-FTE'!I9 | J77: ='Germany Production-FTE'!J9
B78: Spain | C78: ='Spain-FTE'!C9 | D78: ='Spain-FTE'!D9 | E78: ='Spain-FTE'!E9 | F78: ='Spain-FTE'!F9 | G78: ='Spain-FTE'!G9 | H78: ='Spain-FTE'!H9 | I78: ='Spain-FTE'!I9 | J78: ='Spain-FTE'!J9
B79: Italy | C79: ='Italy-FTE'!C9 | D79: ='Italy-FTE'!D9 | E79: ='Italy-FTE'!E9 | F79: ='Italy-FTE'!F9 | G79: ='Italy-FTE'!G9 | H79: ='Italy-FTE'!H9 | I79: ='Italy-FTE'!I9 | J79: ='Italy-FTE'!J9
B80: United Kingdom | C80: ='UK-FTE'!C9 | D80: ='UK-FTE'!D9 | E80: ='UK-FTE'!E9 | F80: ='UK-FTE'!F9 | G80: ='UK-FTE'!G9 | H80: ='UK-FTE'!H9 | I80: ='UK-FTE'!I9 | J80: ='UK-FTE'!J9
B81: Total FTEs All Countries | C81: =SUM(C73:C80) | D81: =SUM(D73:D80) | E81: =SUM(E73:E80) | F81: =SUM(F73:F80) | G81: =SUM(G73:G80) | H81: =SUM(H73:H80) | I81: =SUM(I73:I80) | J81: =SUM(J73:J80)

Sheet Switzerland-FTE
A1: FTE Projection Input Form - Centre One
A2: Country | B2: Process Area | C2: Year 1 | D2: Year 2 | E2: Year 3 | F2: Year 4 | G2: Year 5 | H2: Year 6 | I2: Year 7 | J2: Year 8
A3: Switzerland | B3: General Accounting & Sox | C3: 0.875 | D3: 2 | E3: 1.9541667 | F3: 1.9041667 | G3: 1.8541667 | H3: 1.7583333 | I3: 1.75 | J3: 1.75
B4: Fixed Assets | C4: 0 | D4: 0 | E4: 0 | F4: 0 | G4: 0 | H4: 0 | I4: 0 | J4: 0
B5: Accounts Payable | C5: 5.9408602 | D5: 12.555556 | E5: 11.722222 | F5: 11.055556 | G5: 10.694444 | H5: 10.361111 | I5: 10.027778 | J5: 10
B6: T&E | C6: 0 | D6: 0 | E6: 0 | F6: 0 | G6: 0 | H6: 0 | I6: 0 | J6: 0
B7: Order to Cash | C7: 0.43817204 | D7: 1 | E7: 0.97708333 | F7: 0.95208333 | G7: 0.92708333 | H7: 0.87916667 | I7: 0.875 | J7: 0.875
B8: Requistion to Pay | C8: 3 | D8: 5.862069 | E8: 5.6034483 | F8: 5.3965517 | G8: 5.1896552 | H8: 4.9827586 | I8: 4.9655172 | J8: 4.9655172
B9: Total FTEs | C9: =SUM(C3:C8) | D9: =SUM(D3:D8) | E9: =SUM(E3:E8) | F9: =SUM(F3:F8) | G9: =SUM(G3:G8) | H9: =SUM(H3:H8) | I9: =SUM(I3:I8) | J9: =SUM(J3:J8)

Sheet US-FTE
A1: FTE Projection Input Form - Centre One
A2: Country | B2: Process Area | C2: Year 1 | D2: Year 2 | E2: Year 3 | F2: Year 4 | G2: Year 5 | H2: Year 6 | I2: Year 7
A3: United States | B3: General Accounting & Sox
B4: Fixed Assets
B5: Accounts Payable
B6: T&E
B7: Order to Cash
B8: Requistion to Pay
B9: Total FTEs | C9: =SUM(C3:C8) | D9: =SUM(D3:D8) | E9: =SUM(E3:E8) | F9: =SUM(F3:F8) | G9: =SUM(G3:G8) | H9: =SUM(H3:H8) | I9: =SUM(I3:I8)

Sheet France-FTE
A1: FTE Projection Input Form - Centre One
A2: Country | B2: Process Area | C2: Year 1 | D2: Year 2 | E2: Year 3 | F2: Year 4 | G2: Year 5 | H2: Year 6 | I2: Year 7 | J2: Year 8
A3: France | B3: General Accounting & Sox | C3: 0.62903226 | D3: 3 | E3: 2.93125 | F3: 2.85625 | G3: 2.78125 | H3: 2.6375 | I3: 2.625 | J3: 2.625
B4: Fixed Assets | C4: 0 | D4: 0 | E4: 0 | F4: 0 | G4: 0 | H4: 0 | I4: 0 | J4: 0
B5: Accounts Payable | C5: 1.9784946 | D5: 7.7264957 | E5: 7.2136752 | F5: 6.8034188 | G5: 6.5811966 | H5: 6.3760684 | I5: 6.1709402 | J5: 6.1538462
B6: T&E | C6: 0.24731183 | D6: 1 | E6: 0.97708333 | F6: 0.95208333 | G6: 0.92708333 | H6: 0.87916667 | I6: 0.875 | J6: 0.875
B7: Order to Cash | C7: 1.2365591 | D7: 5 | E7: 4.8854167 | F7: 4.7604167 | G7: 4.6354167 | H7: 4.3958333 | I7: 4.375 | J7: 4.375
B8: Requistion to Pay | C8: 1.7166667 | D8: 5.862069 | E8: 5.6034483 | F8: 5.3965517 | G8: 5.1896552 | H8: 4.9827586 | I8: 4.9655172 | J8: 4.9655172
B9: Total FTEs | C9: =SUM(C3:C8) | D9: =SUM(D3:D8) | E9: =SUM(E3:E8) | F9: =SUM(F3:F8) | G9: =SUM(G3:G8) | H9: =SUM(H3:H8) | I9: =SUM(I3:I8) | J9: =SUM(J3:J8)

Sheet Germany-FTE
A1: FTE Projection Input Form - Centre One
A2: Country | B2: Process Area | C2: Year 1 | D2: Year 2 | E2: Year 3 | F2: Year 4 | G2: Year 5 | H2: Year 6 | I2: Year 7 | J2: Year 8
A3: Germany | B3: General Accounting & Sox | C3: 0.41801075 | D3: 1.5 | E3: 1.465625 | F3: 1.428125 | G3: 1.390625 | H3: 1.31875 | I3: 1.3125 | J3: 1.3125
B4: Fixed Assets | C4: 0.41666667 | D4: 0.5 | E4: 0.48854167 | F4: 0.47604167 | G4: 0.46354167 | H4: 0.43958333 | I4: 0.4375 | J4: 0.4375
B5: Accounts Payable | C5: 2.75 | D5: 8.6923077 | E5: 8.1153846 | F5: 7.6538462 | G5: 7.4038462 | H5: 7.1730769 | I5: 6.9423077 | J5: 6.9230769
B6: T&E | C6: 0.74193548 | D6: 3 | E6: 2.93125 | F6: 2.85625 | G6: 2.78125 | H6: 2.6375 | I6: 2.625 | J6: 2.625
B7: Order to Cash | C7: 0.49462366 | D7: 2 | E7: 1.9541667 | F7: 1.9041667 | G7: 1.8541667 | H7: 1.7583333 | I7: 1.75 | J7: 1.75
B8: Requistion to Pay | C8: 0.5 | D8: 0.97701149 | E8: 0.93390805 | F8: 0.89942529 | G8: 0.86494253 | H8: 0.83045977 | I8: 0.82758621 | J8: 0.82758621
B9: Total FTEs | C9: =SUM(C3:C8) | D9: =SUM(D3:D8) | E9: =SUM(E3:E8) | F9: =SUM(F3:F8) | G9: =SUM(G3:G8) | H9: =SUM(H3:H8) | I9: =SUM(I3:I8) | J9: =SUM(J3:J8)

Sheet Germany Production-FTE
A1: FTE Projection Input Form - Centre One
A2: Country | B2: Process Area | C2: Year 1 | D2: Year 2 | E2: Year 3 | F2: Year 4 | G2: Year 5 | H2: Year 6 | I2: Year 7 | J2: Year 8
A3: Germany Production | B3: General Accounting & Sox | C3: 0.20967742 | D3: 1 | E3: 0.97708333 | F3: 0.95208333 | G3: 0.92708333 | H3: 0.87916667 | I3: 0.875 | J3: 0.875
B4: Fixed Assets | C4: 0 | D4: 0 | E4: 0 | F4: 0 | G4: 0 | H4: 0 | I4: 0 | J4: 0
B5: Accounts Payable | C5: 0 | D5: 0 | E5: 0 | F5: 0 | G5: 0 | H5: 0 | I5: 0 | J5: 0
B6: T&E | C6: 0 | D6: 0 | E6: 0 | F6: 0 | G6: 0 | H6: 0 | I6: 0 | J6: 0
B7: Order to Cash | C7: 0 | D7: 0 | E7: 0 | F7: 0 | G7: 0 | H7: 0 | I7: 0 | J7: 0
B8: Requistion to Pay | C8: 0.5 | D8: 0 | E8: 0 | F8: 0 | G8: 0 | H8: 0 | I8: 0 | J8: 0
B9: Total FTEs | C9: =SUM(C3:C8) | D9: =SUM(D3:D8) | E9: =SUM(E3:E8) | F9: =SUM(F3:F8) | G9: =SUM(G3:G8) | H9: =SUM(H3:H8) | I9: =SUM(I3:I8) | J9: =SUM(J3:J8)

Sheet Spain-FTE
A1: FTE Projection Input Form - Centre One
A2: Country | B2: Process Area | C2: Year 1 | D2: Year 2 | E2: Year 3 | F2: Year 4 | G2: Year 5 | H2: Year 6 | I2: Year 7 | J2: Year 8
A3: Spain | B3: General Accounting & Sox | C3: 1.25 | D3: 3 | E3: 2.93125 | F3: 2.85625 | G3: 2.78125 | H3: 2.6375 | I3: 2.625 | J3: 2.625
B4: Fixed Assets | C4: 0 | D4: 0 | E4: 0 | F4: 0 | G4: 0 | H4: 0 | I4: 0 | J4: 0
B5: Accounts Payable | C5: 1.6760753 | D5: 3.3803419 | E5: 3.1559829 | F5: 2.9764957 | G5: 2.8792735 | H5: 2.7895299 | I5: 2.6997863 | J5: 2.6923077
B6: T&E | C6: 0.41801075 | D6: 0.5 | E6: 0.48854167 | F6: 0.47604167 | G6: 0.46354167 | H6: 0.43958333 | I6: 0.4375 | J6: 0.4375
B7: Order to Cash | C7: 0.41935484 | D7: 1 | E7: 0.97708333 | F7: 0.95208333 | G7: 0.92708333 | H7: 0.87916667 | I7: 0.875 | J7: 0.875
B8: Requistion to Pay | C8: 1.827957 | D8: 3.908046 | E8: 3.7356322 | F8: 3.5977011 | G8: 3.4597701 | H8: 3.3218391 | I8: 3.3103448 | J8: 3.3103448
B9: Total FTEs | C9: =SUM(C3:C8) | D9: =SUM(D3:D8) | E9: =SUM(E3:E8) | F9: =SUM(F3:F8) | G9: =SUM(G3:G8) | H9: =SUM(H3:H8) | I9: =SUM(I3:I8) | J9: =SUM(J3:J8)

Sheet Italy-FTE
A1: FTE Projection Input Form - Centre One
A2: Country | B2: Process Area | C2: Year 1 | D2: Year 2 | E2: Year 3 | F2: Year 4 | G2: Year 5 | H2: Year 6 | I2: Year 7 | J2: Year 8
A3: Italy | B3: General Accounting & Sox | C3: 0.41666667 | D3: 1 | E3: 0.97708333 | F3: 0.95208333 | G3: 0.92708333 | H3: 0.87916667 | I3: 0.875 | J3: 0.875
B4: Fixed Assets | C4: 0 | D4: 0 | E4: 0 | F4: 0 | G4: 0 | H4: 0 | I4: 0 | J4: 0
B5: Accounts Payable | C5: 2.3064516 | D5: 5.3119658 | E5: 4.9594017 | F5: 4.6773504 | G5: 4.5245726 | H5: 4.383547 | I5: 4.2425214 | J5: 4.2307692
B6: T&E | C6: 0.96505376 | D6: 2.5 | E6: 2.4427083 | F6: 2.3802083 | G6: 2.3177083 | H6: 2.1979167 | I6: 2.1875 | J6: 2.1875
B7: Order to Cash | C7: 0.83870968 | D7: 2 | E7: 1.9541667 | F7: 1.9041667 | G7: 1.8541667 | H7: 1.7583333 | I7: 1.75 | J7: 1.75
B8: Requistion to Pay | C8: 1.2043011 | D8: 2.9310345 | E8: 2.8017241 | F8: 2.6982759 | G8: 2.5948276 | H8: 2.4913793 | I8: 2.4827586 | J8: 2.4827586
B9: Total FTEs | C9: =SUM(C3:C8) | D9: =SUM(D3:D8) | E9: =SUM(E3:E8) | F9: =SUM(F3:F8) | G9: =SUM(G3:G8) | H9: =SUM(H3:H8) | I9: =SUM(I3:I8) | J9: =SUM(J3:J8)

Sheet UK-FTE
A1: FTE Projection Input Form - Centre Two
A2: Country | B2: Process Area | C2: Year 1 | D2: Year 2 | E2: Year 3 | F2: Year 4 | G2: Year 5 | H2: Year 6 | I2: Year 7
A3: United Kingdom | B3: General Accounting & Sox
B4: Fixed Assets
B5: Accounts Payable
B6: T&E
B7: Order to Cash
B8: Requistion to Pay
B9: Total FTEs | C9: =SUM(C3:C8) | D9: =SUM(D3:D8) | E9: =SUM(E3:E8) | F9: =SUM(F3:F8) | G9: =SUM(G3:G8) | H9: =SUM(H3:H8) | I9: =SUM(I3:I8)

Sheet Centre Two-FTE
A1: FTE PROJECTION INPUT SUMMARY
A2: Centre Two | C2: Year 1 | D2: Year 2 | E2: Year 3 | F2: Year 4 | G2: Year 5 | H2: Year 6 | I2: Year 7 | J2: Year 8
B3: Process Summary
B4: General Accounting & Sox | C4: =+SUM('Switzerland-FTE-2:UK-FTE-2'!$C3) | D4: =+SUM('Switzerland-FTE-2:UK-FTE-2'!$D3) | E4: =+SUM('Switzerland-FTE-2:UK-FTE-2'!$E3) | F4: =+SUM('Switzerland-FTE-2:UK-FTE-2'!$F3) | G4: =+SUM('Switzerland-FTE-2:UK-FTE-2'!$G3) | H4: =+SUM('Switzerland-FTE-2:UK-FTE-2'!$H3) | I4: =+SUM('Switzerland-FTE-2:UK-FTE-2'!$I3) | J4: =+SUM('Switzerland-FTE-2:UK-FTE-2'!$J3)
B5: Fixed Assets | C5: =+SUM('Switzerland-FTE-2:UK-FTE-2'!$C4) | D5: =+SUM('Switzerland-FTE-2:UK-FTE-2'!$D4) | E5: =+SUM('Switzerland-FTE-2:UK-FTE-2'!$E4) | F5: =+SUM('Switzerland-FTE-2:UK-FTE-2'!$F4) | G5: =+SUM('Switzerland-FTE-2:UK-FTE-2'!$G4) | H5: =+SUM('Switzerland-FTE-2:UK-FTE-2'!$H4) | I5: =+SUM('Switzerland-FTE-2:UK-FTE-2'!$I4) | J5: =+SUM('Switzerland-FTE-2:UK-FTE-2'!$J4)
B6: Accounts Payable | C6: =+SUM('Switzerland-FTE-2:UK-FTE-2'!$C5) | D6: =+SUM('Switzerland-FTE-2:UK-FTE-2'!$D5) | E6: =+SUM('Switzerland-FTE-2:UK-FTE-2'!$E5) | F6: =+SUM('Switzerland-FTE-2:UK-FTE-2'!$F5) | G6: =+SUM('Switzerland-FTE-2:UK-FTE-2'!$G5) | H6: =+SUM('Switzerland-FTE-2:UK-FTE-2'!$H5) | I6: =+SUM('Switzerland-FTE-2:UK-FTE-2'!$I5) | J6: =+SUM('Switzerland-FTE-2:UK-FTE-2'!$J5)
B7: T&E | C7: =+SUM('Switzerland-FTE-2:UK-FTE-2'!$C6) | D7: =+SUM('Switzerland-FTE-2:UK-FTE-2'!$D6) | E7: =+SUM('Switzerland-FTE-2:UK-FTE-2'!$E6) | F7: =+SUM('Switzerland-FTE-2:UK-FTE-2'!$F6) | G7: =+SUM('Switzerland-FTE-2:UK-FTE-2'!$G6) | H7: =+SUM('Switzerland-FTE-2:UK-FTE-2'!$H6) | I7: =+SUM('Switzerland-FTE-2:UK-FTE-2'!$I6) | J7: =+SUM('Switzerland-FTE-2:UK-FTE-2'!$J6)
B8: Order to Cash | C8: =+SUM('Switzerland-FTE-2:UK-FTE-2'!$C7) | D8: =+SUM('Switzerland-FTE-2:UK-FTE-2'!$D7) | E8: =+SUM('Switzerland-FTE-2:UK-FTE-2'!$E7) | F8: =+SUM('Switzerland-FTE-2:UK-FTE-2'!$F7) | G8: =+SUM('Switzerland-FTE-2:UK-FTE-2'!$G7) | H8: =+SUM('Switzerland-FTE-2:UK-FTE-2'!$H7) | I8: =+SUM('Switzerland-FTE-2:UK-FTE-2'!$I7) | J8: =+SUM('Switzerland-FTE-2:UK-FTE-2'!$J7)
B9: Requistion to Pay | C9: =+SUM('Switzerland-FTE-2:UK-FTE-2'!$C8) | D9: =+SUM('Switzerland-FTE-2:UK-FTE-2'!$D8) | E9: =+SUM('Switzerland-FTE-2:UK-FTE-2'!$E8) | F9: =+SUM('Switzerland-FTE-2:UK-FTE-2'!$F8) | G9: =+SUM('Switzerland-FTE-2:UK-FTE-2'!$G8) | H9: =+SUM('Switzerland-FTE-2:UK-FTE-2'!$H8) | I9: =+SUM('Switzerland-FTE-2:UK-FTE-2'!$I8) | J9: =+SUM('Switzerland-FTE-2:UK-FTE-2'!$J8)
B10: Total FTEs All Countries | C10: =SUM(C4:C9) | D10: =SUM(D4:D9) | E10: =SUM(E4:E9) | F10: =SUM(F4:F9) | G10: =SUM(G4:G9) | H10: =SUM(H4:H9) | I10: =SUM(I4:I9) | J10: =SUM(J4:J9)
B11: General Accounting & Sox
B12: Switzerland | C12: ='Switzerland-FTE-2'!$C$3 | D12: ='Switzerland-FTE-2'!$D$3 | E12: ='Switzerland-FTE-2'!$E$3 | F12: ='Switzerland-FTE-2'!$F$3 | G12: ='Switzerland-FTE-2'!$G$3 | H12: ='Switzerland-FTE-2'!$H$3 | I12: ='Switzerland-FTE-2'!$I$3 | J12: ='Switzerland-FTE-2'!$J$3
B13: United States | C13: ='US-FTE-2'!$C$3 | D13: ='US-FTE-2'!$D$3 | E13: ='US-FTE-2'!$E$3 | F13: ='US-FTE-2'!$F$3 | G13: ='US-FTE-2'!$G$3 | H13: ='US-FTE-2'!$H$3 | I13: ='US-FTE-2'!$I$3 | J13: ='US-FTE-2'!$J$3
B14: France | C14: ='France-FTE-2'!$C$3 | D14: ='France-FTE-2'!$D$3 | E14: ='France-FTE-2'!$E$3 | F14: ='France-FTE-2'!$F$3 | G14: ='France-FTE-2'!$G$3 | H14: ='France-FTE-2'!$H$3 | I14: ='France-FTE-2'!$I$3 | J14: ='France-FTE-2'!$J$3
B15: Germany | C15: ='Germany-FTE-2'!$C$3 | D15: ='Germany-FTE-2'!$D$3 | E15: ='Germany-FTE-2'!$E$3 | F15: ='Germany-FTE-2'!$F$3 | G15: ='Germany-FTE-2'!$G$3 | H15: ='Germany-FTE-2'!$H$3 | I15: ='Germany-FTE-2'!$I$3 | J15: ='Germany-FTE-2'!$J$3
B16: Germany Production | C16: ='Germany Production-FTE-2'!$C$3 | D16: ='Germany Production-FTE-2'!$D$3 | E16: ='Germany Production-FTE-2'!$E$3 | F16: ='Germany Production-FTE-2'!$F$3 | G16: ='Germany Production-FTE-2'!$G$3 | H16: ='Germany Production-FTE-2'!$H$3 | I16: ='Germany Production-FTE-2'!$I$3 | J16: ='Germany Production-FTE-2'!$J$3
B17: Spain | C17: ='Spain-FTE-2'!$C$3 | D17: ='Spain-FTE-2'!$D$3 | E17: ='Spain-FTE-2'!$E$3 | F17: ='Spain-FTE-2'!$F$3 | G17: ='Spain-FTE-2'!$G$3 | H17: ='Spain-FTE-2'!$H$3 | I17: ='Spain-FTE-2'!$I$3 | J17: ='Spain-FTE-2'!$J$3
B18: Italy | C18: ='Italy-FTE-2'!$C$3 | D18: ='Italy-FTE-2'!$D$3 | E18: ='Italy-FTE-2'!$E$3 | F18: ='Italy-FTE-2'!$F$3 | G18: ='Italy-FTE-2'!$G$3 | H18: ='Italy-FTE-2'!$H$3 | I18: ='Italy-FTE-2'!$I$3 | J18: ='Italy-FTE-2'!$J$3
B19: United Kingdom | C19: ='UK-FTE-2'!$C$3 | D19: ='UK-FTE-2'!$D$3 | E19: ='UK-FTE-2'!$E$3 | F19: ='UK-FTE-2'!$F$3 | G19: ='UK-FTE-2'!$G$3 | H19: ='UK-FTE-2'!$H$3 | I19: ='UK-FTE-2'!$I$3 | J19: ='UK-FTE-2'!$J$3
B20: Sub Total | C20: =SUM(C12:C19) | D20: =SUM(D12:D19) | E20: =SUM(E12:E19) | F20: =SUM(F12:F19) | G20: =SUM(G12:G19) | H20: =SUM(H12:H19) | I20: =SUM(I12:I19) | J20: =SUM(J12:J19)
B21: Fixed Assets
B22: Switzerland | C22: ='Switzerland-FTE-2'!$C$4 | D22: ='Switzerland-FTE-2'!$D$4 | E22: ='Switzerland-FTE-2'!$E$4 | F22: ='Switzerland-FTE-2'!$F$4 | G22: ='Switzerland-FTE-2'!$G$4 | H22: ='Switzerland-FTE-2'!$H$4 | I22: ='Switzerland-FTE-2'!$I$4 | J22: ='Switzerland-FTE-2'!$J$4
B23: United States | C23: ='US-FTE-2'!$C$4 | D23: ='US-FTE-2'!$D$4 | E23: ='US-FTE-2'!$E$4 | F23: ='US-FTE-2'!$F$4 | G23: ='US-FTE-2'!$G$4 | H23: ='US-FTE-2'!$H$4 | I23: ='US-FTE-2'!$I$4 | J23: ='US-FTE-2'!$J$4
B24: France | C24: ='France-FTE-2'!$C$4 | D24: ='France-FTE-2'!$D$4 | E24: ='France-FTE-2'!$E$4 | F24: ='France-FTE-2'!$F$4 | G24: ='France-FTE-2'!$G$4 | H24: ='France-FTE-2'!$H$4 | I24: ='France-FTE-2'!$I$4 | J24: ='France-FTE-2'!$J$4
B25: Germany | C25: ='Germany-FTE-2'!$C$4 | D25: ='Germany-FTE-2'!$D$4 | E25: ='Germany-FTE-2'!$E$4 | F25: ='Germany-FTE-2'!$F$4 | G25: ='Germany-FTE-2'!$G$4 | H25: ='Germany-FTE-2'!$H$4 | I25: ='Germany-FTE-2'!$I$4 | J25: ='Germany-FTE-2'!$J$4
B26: Germany Production | C26: ='Germany Production-FTE-2'!$C$4 | D26: ='Germany Production-FTE-2'!$D$4 | E26: ='Germany Production-FTE-2'!$E$4 | F26: ='Germany Production-FTE-2'!$F$4 | G26: ='Germany Production-FTE-2'!$G$4 | H26: ='Germany Production-FTE-2'!$H$4 | I26: ='Germany Production-FTE-2'!$I$4 | J26: ='Germany Production-FTE-2'!$J$4
B27: Spain | C27: ='Spain-FTE-2'!$C$4 | D27: ='Spain-FTE-2'!$D$4 | E27: ='Spain-FTE-2'!$E$4 | F27: ='Spain-FTE-2'!$F$4 | G27: ='Spain-FTE-2'!$G$4 | H27: ='Spain-FTE-2'!$H$4 | I27: ='Spain-FTE-2'!$I$4 | J27: ='Spain-FTE-2'!$J$4
B28: Italy | C28: ='Italy-FTE-2'!$C$4 | D28: ='Italy-FTE-2'!$D$4 | E28: ='Italy-FTE-2'!$E$4 | F28: ='Italy-FTE-2'!$F$4 | G28: ='Italy-FTE-2'!$G$4 | H28: ='Italy-FTE-2'!$H$4 | I28: ='Italy-FTE-2'!$I$4 | J28: ='Italy-FTE-2'!$J$4
B29: United Kingdom | C29: ='UK-FTE-2'!$C$4 | D29: ='UK-FTE-2'!$D$4 | E29: ='UK-FTE-2'!$E$4 | F29: ='UK-FTE-2'!$F$4 | G29: ='UK-FTE-2'!$G$4 | H29: ='UK-FTE-2'!$H$4 | I29: ='UK-FTE-2'!$I$4 | J29: ='UK-FTE-2'!$J$4
B30: Sub Total | C30: =SUM(C22:C29) | D30: =SUM(D22:D29) | E30: =SUM(E22:E29) | F30: =SUM(F22:F29) | G30: =SUM(G22:G29) | H30: =SUM(H22:H29) | I30: =SUM(I22:I29) | J30: =SUM(J22:J29)
B31: Accounts Payable
B32: Switzerland | C32: ='Switzerland-FTE-2'!$C$5 | D32: ='Switzerland-FTE-2'!$D$5 | E32: ='Switzerland-FTE-2'!$E$5 | F32: ='Switzerland-FTE-2'!$F$5 | G32: ='Switzerland-FTE-2'!$G$5 | H32: ='Switzerland-FTE-2'!$H$5 | I32: ='Switzerland-FTE-2'!$I$5 | J32: ='Switzerland-FTE-2'!$J$5
B33: United States | C33: ='US-FTE-2'!$C$5 | D33: ='US-FTE-2'!$D$5 | E33: ='US-FTE-2'!$E$5 | F33: ='US-FTE-2'!$F$5 | G33: ='US-FTE-2'!$G$5 | H33: ='US-FTE-2'!$H$5 | I33: ='US-FTE-2'!$I$5 | J33: ='US-FTE-2'!$J$5
B34: France | C34: ='France-FTE-2'!$C$5 | D34: ='France-FTE-2'!$D$5 | E34: ='France-FTE-2'!$E$5 | F34: ='France-FTE-2'!$F$5 | G34: ='France-FTE-2'!$G$5 | H34: ='France-FTE-2'!$H$5 | I34: ='France-FTE-2'!$I$5 | J34: ='France-FTE-2'!$J$5
B35: Germany | C35: ='Germany-FTE-2'!$C$5 | D35: ='Germany-FTE-2'!$D$5 | E35: ='Germany-FTE-2'!$E$5 | F35: ='Germany-FTE-2'!$F$5 | G35: ='Germany-FTE-2'!$G$5 | H35: ='Germany-FTE-2'!$H$5 | I35: ='Germany-FTE-2'!$I$5 | J35: ='Germany-FTE-2'!$J$5
B36: Germany Production | C36: ='Germany Production-FTE-2'!$C$5 | D36: ='Germany Production-FTE-2'!$D$5 | E36: ='Germany Production-FTE-2'!$E$5 | F36: ='Germany Production-FTE-2'!$F$5 | G36: ='Germany Production-FTE-2'!$G$5 | H36: ='Germany Production-FTE-2'!$H$5 | I36: ='Germany Production-FTE-2'!$I$5 | J36: ='Germany Production-FTE-2'!$J$5
B37: Spain | C37: ='Spain-FTE-2'!$C$5 | D37: ='Spain-FTE-2'!$D$5 | E37: ='Spain-FTE-2'!$E$5 | F37: ='Spain-FTE-2'!$F$5 | G37: ='Spain-FTE-2'!$G$5 | H37: ='Spain-FTE-2'!$H$5 | I37: ='Spain-FTE-2'!$I$5 | J37: ='Spain-FTE-2'!$J$5
B38: Italy | C38: ='Italy-FTE-2'!$C$5 | D38: ='Italy-FTE-2'!$D$5 | E38: ='Italy-FTE-2'!$E$5 | F38: ='Italy-FTE-2'!$F$5 | G38: ='Italy-FTE-2'!$G$5 | H38: ='Italy-FTE-2'!$H$5 | I38: ='Italy-FTE-2'!$I$5 | J38: ='Italy-FTE-2'!$J$5
B39: United Kingdom | C39: ='UK-FTE-2'!$C$5 | D39: ='UK-FTE-2'!$D$5 | E39: ='UK-FTE-2'!$E$5 | F39: ='UK-FTE-2'!$F$5 | G39: ='UK-FTE-2'!$G$5 | H39: ='UK-FTE-2'!$H$5 | I39: ='UK-FTE-2'!$I$5 | J39: ='UK-FTE-2'!$J$5
B40: Sub Total | C40: =SUM(C32:C39) | D40: =SUM(D32:D39) | E40: =SUM(E32:E39) | F40: =SUM(F32:F39) | G40: =SUM(G32:G39) | H40: =SUM(H32:H39) | I40: =SUM(I32:I39) | J40: =SUM(J32:J39)
B41: T&E
B42: Switzerland | C42: ='Switzerland-FTE-2'!$C$6 | D42: ='Switzerland-FTE-2'!$D$6 | E42: ='Switzerland-FTE-2'!$E$6 | F42: ='Switzerland-FTE-2'!$F$6 | G42: ='Switzerland-FTE-2'!$G$6 | H42: ='Switzerland-FTE-2'!$H$6 | I42: ='Switzerland-FTE-2'!$I$6 | J42: ='Switzerland-FTE-2'!$J$6
B43: United States | C43: ='US-FTE-2'!$C$6 | D43: ='US-FTE-2'!$D$6 | E43: ='US-FTE-2'!$E$6 | F43: ='US-FTE-2'!$F$6 | G43: ='US-FTE-2'!$G$6 | H43: ='US-FTE-2'!$H$6 | I43: ='US-FTE-2'!$I$6 | J43: ='US-FTE-2'!$J$6
B44: France | C44: ='France-FTE-2'!$C$6 | D44: ='France-FTE-2'!$D$6 | E44: ='France-FTE-2'!$E$6 | F44: ='France-FTE-2'!$F$6 | G44: ='France-FTE-2'!$G$6 | H44: ='France-FTE-2'!$H$6 | I44: ='France-FTE-2'!$I$6 | J44: ='France-FTE-2'!$J$6
B45: Germany | C45: ='Germany-FTE-2'!$C$6 | D45: ='Germany-FTE-2'!$D$6 | E45: ='Germany-FTE-2'!$E$6 | F45: ='Germany-FTE-2'!$F$6 | G45: ='Germany-FTE-2'!$G$6 | H45: ='Germany-FTE-2'!$H$6 | I45: ='Germany-FTE-2'!$I$6 | J45: ='Germany-FTE-2'!$J$6
B46: Germany Production | C46: ='Germany Production-FTE-2'!$C$6 | D46: ='Germany Production-FTE-2'!$D$6 | E46: ='Germany Production-FTE-2'!$E$6 | F46: ='Germany Production-FTE-2'!$F$6 | G46: ='Germany Production-FTE-2'!$G$6 | H46: ='Germany Production-FTE-2'!$H$6 | I46: ='Germany Production-FTE-2'!$I$6 | J46: ='Germany Production-FTE-2'!$J$6
B47: Spain | C47: ='Spain-FTE-2'!$C$6 | D47: ='Spain-FTE-2'!$D$6 | E47: ='Spain-FTE-2'!$E$6 | F47: ='Spain-FTE-2'!$F$6 | G47: ='Spain-FTE-2'!$G$6 | H47: ='Spain-FTE-2'!$H$6 | I47: ='Spain-FTE-2'!$I$6 | J47: ='Spain-FTE-2'!$J$6
B48: Italy | C48: ='Italy-FTE-2'!$C$6 | D48: ='Italy-FTE-2'!$D$6 | E48: ='Italy-FTE-2'!$E$6 | F48: ='Italy-FTE-2'!$F$6 | G48: ='Italy-FTE-2'!$G$6 | H48: ='Italy-FTE-2'!$H$6 | I48: ='Italy-FTE-2'!$I$6 | J48: ='Italy-FTE-2'!$J$6
B49: United Kingdom | C49: ='UK-FTE-2'!$C$6 | D49: ='UK-FTE-2'!$D$6 | E49: ='UK-FTE-2'!$E$6 | F49: ='UK-FTE-2'!$F$6 | G49: ='UK-FTE-2'!$G$6 | H49: ='UK-FTE-2'!$H$6 | I49: ='UK-FTE-2'!$I$6 | J49: ='UK-FTE-2'!$J$6
B50: Sub Total | C50: =SUM(C42:C49) | D50: =SUM(D42:D49) | E50: =SUM(E42:E49) | F50: =SUM(F42:F49) | G50: =SUM(G42:G49) | H50: =SUM(H42:H49) | I50: =SUM(I42:I49) | J50: =SUM(J42:J49)
B51: Order to Cash
B52: Switzerland | C52: ='Switzerland-FTE-2'!$C$7 | D52: ='Switzerland-FTE-2'!$D$7 | E52: ='Switzerland-FTE-2'!$E$7 | F52: ='Switzerland-FTE-2'!$F$7 | G52: ='Switzerland-FTE-2'!$G$7 | H52: ='Switzerland-FTE-2'!$H$7 | I52: ='Switzerland-FTE-2'!$I$7 | J52: ='Switzerland-FTE-2'!$J$7
B53: United States | C53: ='US-FTE-2'!$C$7 | D53: ='US-FTE-2'!$D$7 | E53: ='US-FTE-2'!$E$7 | F53: ='US-FTE-2'!$F$7 | G53: ='US-FTE-2'!$G$7 | H53: ='US-FTE-2'!$H$7 | I53: ='US-FTE-2'!$I$7 | J53: ='US-FTE-2'!$J$7
B54: France | C54: ='France-FTE-2'!$C$7 | D54: ='France-FTE-2'!$D$7 | E54: ='France-FTE-2'!$E$7 | F54: ='France-FTE-2'!$F$7 | G54: ='France-FTE-2'!$G$7 | H54: ='France-FTE-2'!$H$7 | I54: ='France-FTE-2'!$I$7 | J54: ='France-FTE-2'!$J$7
B55: Germany | C55: ='Germany-FTE-2'!$C$7 | D55: ='Germany-FTE-2'!$D$7 | E55: ='Germany-FTE-2'!$E$7 | F55: ='Germany-FTE-2'!$F$7 | G55: ='Germany-FTE-2'!$G$7 | H55: ='Germany-FTE-2'!$H$7 | I55: ='Germany-FTE-2'!$I$7 | J55: ='Germany-FTE-2'!$J$7
B56: Germany Production | C56: ='Germany Production-FTE-2'!$C$7 | D56: ='Germany Production-FTE-2'!$D$7 | E56: ='Germany Production-FTE-2'!$E$7 | F56: ='Germany Production-FTE-2'!$F$7 | G56: ='Germany Production-FTE-2'!$G$7 | H56: ='Germany Production-FTE-2'!$H$7 | I56: ='Germany Production-FTE-2'!$I$7 | J56: ='Germany Production-FTE-2'!$J$7
B57: Spain | C57: ='Spain-FTE-2'!$C$7 | D57: ='Spain-FTE-2'!$D$7 | E57: ='Spain-FTE-2'!$E$7 | F57: ='Spain-FTE-2'!$F$7 | G57: ='Spain-FTE-2'!$G$7 | H57: ='Spain-FTE-2'!$H$7 | I57: ='Spain-FTE-2'!$I$7 | J57: ='Spain-FTE-2'!$J$7
B58: Italy | C58: ='Italy-FTE-2'!$C$7 | D58: ='Italy-FTE-2'!$D$7 | E58: ='Italy-FTE-2'!$E$7 | F58: ='Italy-FTE-2'!$F$7 | G58: ='Italy-FTE-2'!$G$7 | H58: ='Italy-FTE-2'!$H$7 | I58: ='Italy-FTE-2'!$I$7 | J58: ='Italy-FTE-2'!$J$7
B59: United Kingdom | C59: ='UK-FTE-2'!$C$7 | D59: ='UK-FTE-2'!$D$7 | E59: ='UK-FTE-2'!$E$7 | F59: ='UK-FTE-2'!$F$7 | G59: ='UK-FTE-2'!$G$7 | H59: ='UK-FTE-2'!$H$7 | I59: ='UK-FTE-2'!$I$7 | J59: ='UK-FTE-2'!$J$7
B60: Sub Total | C60: =SUM(C52:C59) | D60: =SUM(D52:D59) | E60: =SUM(E52:E59) | F60: =SUM(F52:F59) | G60: =SUM(G52:G59) | H60: =SUM(H52:H59) | I60: =SUM(I52:I59) | J60: =SUM(J52:J59)
B61: Requistion to Pay
B62: Switzerland | C62: ='Switzerland-FTE-2'!$C$8 | D62: ='Switzerland-FTE-2'!$D$8 | E62: ='Switzerland-FTE-2'!$E$8 | F62: ='Switzerland-FTE-2'!$F$8 | G62: ='Switzerland-FTE-2'!$G$8 | H62: ='Switzerland-FTE-2'!$H$8 | I62: ='Switzerland-FTE-2'!$I$8 | J62: ='Switzerland-FTE-2'!$J$8
B63: United States | C63: ='US-FTE-2'!$C$8 | D63: ='US-FTE-2'!$D$8 | E63: ='US-FTE-2'!$E$8 | F63: ='US-FTE-2'!$F$8 | G63: ='US-FTE-2'!$G$8 | H63: ='US-FTE-2'!$H$8 | I63: ='US-FTE-2'!$I$8 | J63: ='US-FTE-2'!$J$8
B64: France | C64: ='France-FTE-2'!$C$8 | D64: ='France-FTE-2'!$D$8 | E64: ='France-FTE-2'!$E$8 | F64: ='France-FTE-2'!$F$8 | G64: ='France-FTE-2'!$G$8 | H64: ='France-FTE-2'!$H$8 | I64: ='France-FTE-2'!$I$8 | J64: ='France-FTE-2'!$J$8
B65: Germany | C65: ='Germany-FTE-2'!$C$8 | D65: ='Germany-FTE-2'!$D$8 | E65: ='Germany-FTE-2'!$E$8 | F65: ='Germany-FTE-2'!$F$8 | G65: ='Germany-FTE-2'!$G$8 | H65: ='Germany-FTE-2'!$H$8 | I65: ='Germany-FTE-2'!$I$8 | J65: ='Germany-FTE-2'!$J$8
B66: Germany Production | C66: ='Germany Production-FTE-2'!$C$8 | D66: ='Germany Production-FTE-2'!$D$8 | E66: ='Germany Production-FTE-2'!$E$8 | F66: ='Germany Production-FTE-2'!$F$8 | G66: ='Germany Production-FTE-2'!$G$8 | H66: ='Germany Production-FTE-2'!$H$8 | I66: ='Germany Production-FTE-2'!$I$8 | J66: ='Germany Production-FTE-2'!$J$8
B67: Spain | C67: ='Spain-FTE-2'!$C$8 | D67: ='Spain-FTE-2'!$D$8 | E67: ='Spain-FTE-2'!$E$8 | F67: ='Spain-FTE-2'!$F$8 | G67: ='Spain-FTE-2'!$G$8 | H67: ='Spain-FTE-2'!$H$8 | I67: ='Spain-FTE-2'!$I$8 | J67: ='Spain-FTE-2'!$J$8
B68: Italy | C68: ='Italy-FTE-2'!$C$8 | D68: ='Italy-FTE-2'!$D$8 | E68: ='Italy-FTE-2'!$E$8 | F68: ='Italy-FTE-2'!$F$8 | G68: ='Italy-FTE-2'!$G$8 | H68: ='Italy-FTE-2'!$H$8 | I68: ='Italy-FTE-2'!$I$8 | J68: ='Italy-FTE-2'!$J$8
B69: United Kingdom | C69: ='UK-FTE-2'!$C$8 | D69: ='UK-FTE-2'!$D$8 | E69: ='UK-FTE-2'!$E$8 | F69: ='UK-FTE-2'!$F$8 | G69: ='UK-FTE-2'!$G$8 | H69: ='UK-FTE-2'!$H$8 | I69: ='UK-FTE-2'!$I$8 | J69: ='UK-FTE-2'!$J$8
B70: Sub Total | C70: =SUM(C62:C69) | D70: =SUM(D62:D69) | E70: =SUM(E62:E69) | F70: =SUM(F62:F69) | G70: =SUM(G62:G69) | H70: =SUM(H62:H69) | I70: =SUM(I62:I69) | J70: =SUM(J62:J69)
B71: Total FTEs All Countries | C71: =C20+C30+C40+C50+C60+C70 | D71: =D20+D30+D40+D50+D60+D70 | E71: =E20+E30+E40+E50+E60+E70 | F71: =F20+F30+F40+F50+F60+F70 | G71: =G20+G30+G40+G50+G60+G70 | H71: =H20+H30+H40+H50+H60+H70 | I71: =I20+I30+I40+I50+I60+I70 | J71: =J20+J30+J40+J50+J60+J70
B72: Country Summary
B73: Switzerland | C73: ='Switzerland-FTE-2'!C9 | D73: ='Switzerland-FTE-2'!D9 | E73: ='Switzerland-FTE-2'!E9 | F73: ='Switzerland-FTE-2'!F9 | G73: ='Switzerland-FTE-2'!G9 | H73: ='Switzerland-FTE-2'!H9 | I73: ='Switzerland-FTE-2'!I9 | J73: ='Switzerland-FTE-2'!J9
B74: United States | C74: ='US-FTE-2'!C9 | D74: ='US-FTE-2'!D9 | E74: ='US-FTE-2'!E9 | F74: ='US-FTE-2'!F9 | G74: ='US-FTE-2'!G9 | H74: ='US-FTE-2'!H9 | I74: ='US-FTE-2'!I9 | J74: ='US-FTE-2'!J9
B75: France | C75: ='France-FTE-2'!C9 | D75: ='France-FTE-2'!D9 | E75: ='France-FTE-2'!E9 | F75: ='France-FTE-2'!F9 | G75: ='France-FTE-2'!G9 | H75: ='France-FTE-2'!H9 | I75: ='France-FTE-2'!I9 | J75: ='France-FTE-2'!J9
B76: Germany | C76: ='Germany-FTE-2'!C9 | D76: ='Germany-FTE-2'!D9 | E76: ='Germany-FTE-2'!E9 | F76: ='Germany-FTE-2'!F9 | G76: ='Germany-FTE-2'!G9 | H76: ='Germany-FTE-2'!H9 | I76: ='Germany-FTE-2'!I9 | J76: ='Germany-FTE-2'!J9
B77: Germany Production | C77: ='Germany Production-FTE-2'!C9 | D77: ='Germany Production-FTE-2'!D9 | E77: ='Germany Production-FTE-2'!E9 | F77: ='Germany Production-FTE-2'!F9 | G77: ='Germany Production-FTE-2'!G9 | H77: ='Germany Production-FTE-2'!H9 | I77: ='Germany Production-FTE-2'!I9 | J77: ='Germany Production-FTE-2'!J9
B78: Spain | C78: ='Spain-FTE-2'!C9 | D78: ='Spain-FTE-2'!D9 | E78: ='Spain-FTE-2'!E9 | F78: ='Spain-FTE-2'!F9 | G78: ='Spain-FTE-2'!G9 | H78: ='Spain-FTE-2'!H9 | I78: ='Spain-FTE-2'!I9 | J78: ='Spain-FTE-2'!J9
B79: Italy | C79: ='Italy-FTE-2'!C9 | D79: ='Italy-FTE-2'!D9 | E79: ='Italy-FTE-2'!E9 | F79: ='Italy-FTE-2'!F9 | G79: ='Italy-FTE-2'!G9 | H79: ='Italy-FTE-2'!H9 | I79: ='Italy-FTE-2'!I9 | J79: ='Italy-FTE-2'!J9
B80: United Kingdom | C80: ='UK-FTE-2'!C9 | D80: ='UK-FTE-2'!D9 | E80: ='UK-FTE-2'!E9 | F80: ='UK-FTE-2'!F9 | G80: ='UK-FTE-2'!G9 | H80: ='UK-FTE-2'!H9 | I80: ='UK-FTE-2'!I9 | J80: ='UK-FTE-2'!J9
B81: Total FTEs All Countries | C81: =SUM(C73:C80) | D81: =SUM(D73:D80) | E81: =SUM(E73:E80) | F81: =SUM(F73:F80) | G81: =SUM(G73:G80) | H81: =SUM(H73:H80) | I81: =SUM(I73:I80) | J81: =SUM(J73:J80)

Sheet Switzerland-FTE-2
A1: FTE Projection Input Form - Centre Two
A2: Country | B2: Process Area | C2: Year 1 | D2: Year 2 | E2: Year 3 | F2: Year 4 | G2: Year 5 | H2: Year 6 | I2: Year 7
A3: Switzerland | B3: General Accounting & Sox
B4: Fixed Assets
B5: Accounts Payable
B6: T&E
B7: Order to Cash
B8: Requistion to Pay
B9: Total FTEs | C9: =SUM(C3:C8) | D9: =SUM(D3:D8) | E9: =SUM(E3:E8) | F9: =SUM(F3:F8) | G9: =SUM(G3:G8) | H9: =SUM(H3:H8) | I9: =SUM(I3:I8)

Sheet US-FTE-2
A1: FTE Projection Input Form - Centre Two
A2: Country | B2: Process Area | C2: Year 1 | D2: Year 2 | E2: Year 3 | F2: Year 4 | G2: Year 5 | H2: Year 6 | I2: Year 7 | J2: Year 8
A3: United States | B3: General Accounting & Sox | C3: 1.0134409 | D3: 2 | E3: 1.9541667 | F3: 1.9041667 | G3: 1.8541667 | H3: 1.7583333 | I3: 1.75 | J3: 1.75
B4: Fixed Assets | C4: 0.98924731 | D4: 2 | E4: 1.9541667 | F4: 1.9041667 | G4: 1.8541667 | H4: 1.7583333 | I4: 1.75 | J4: 1.75
B5: Accounts Payable | C5: 5.0322581 | D5: 11.555556 | E5: 10.722222 | F5: 10.055556 | G5: 9.3888889 | H5: 9.3333333 | I5: 9.3333333 | J5: 9.3333333
B6: T&E | C6: 0 | D6: 0 | E6: 0 | F6: 0 | G6: 0 | H6: 0 | I6: 0 | J6: 0
B7: Order to Cash | C7: 0.53333333 | D7: 1 | E7: 0.97708333 | F7: 0.95208333 | G7: 0.92708333 | H7: 0.87916667 | I7: 0.875 | J7: 0.875
B8: Requistion to Pay | C8: 5.15 | D8: 8.7931034 | E8: 8.4051724 | F8: 8.0948276 | G8: 7.7844828 | H8: 7.4741379 | I8: 7.4482759 | J8: 7.4482759
B9: Total FTEs | C9: =SUM(C3:C8) | D9: =SUM(D3:D8) | E9: =SUM(E3:E8) | F9: =SUM(F3:F8) | G9: =SUM(G3:G8) | H9: =SUM(H3:H8) | I9: =SUM(I3:I8) | J9: =SUM(J3:J8)

Sheet France-FTE-2
A1: FTE Projection Input Form - Centre Two
A2: Country | B2: Process Area | C2: Year 1 | D2: Year 2 | E2: Year 3 | F2: Year 4 | G2: Year 5 | H2: Year 6 | I2: Year 7
A3: France | B3: General Accounting & Sox
B4: Fixed Assets
B5: Accounts Payable
B6: T&E
B7: Order to Cash
B8: Requistion to Pay
B9: Total FTEs | C9: =SUM(C3:C8) | D9: =SUM(D3:D8) | E9: =SUM(E3:E8) | F9: =SUM(F3:F8) | G9: =SUM(G3:G8) | H9: =SUM(H3:H8) | I9: =SUM(I3:I8)

Sheet Germany-FTE-2
A1: FTE Projection Input Form - Centre Two
A2: Country | B2: Process Area | C2: Year 1 | D2: Year 2 | E2: Year 3 | F2: Year 4 | G2: Year 5 | H2: Year 6 | I2: Year 7
